Workbook
Name \a: #REF!
Name \b: #N/A
Name \g: #N/A
Name \n: #N/A
Name ________TGL1: #REF!
Name ________TGL2: #REF!
Name _______TGL1: #REF!
Name _______TGL2: #REF!
Name ______TGL1: #REF!
Name ______TGL2: #REF!
Name _____TGL1: #REF!
Name _____TGL2: #REF!
Name ____DAT1: #REF!
Name ____DAT10: #REF!
Name ____DAT11: #REF!
Name ____DAT12: #REF!
Name ____DAT13: #REF!
Name ____DAT14: #REF!
Name ____DAT15: #REF!
Name ____DAT16: #REF!
Name ____DAT17: #REF!
Name ____DAT18: #REF!
Name ____DAT19: #REF!
Name ____DAT2: #REF!
Name ____DAT20: #REF!
Name ____DAT3: #REF!
Name ____DAT4: #REF!
Name ____DAT5: #REF!
Name ____DAT6: #REF!
Name ____DAT7: #REF!
Name ____DAT8: #REF!
Name ____DAT9: #REF!
Name ____TGL1: #REF!
Name ____TGL2: #REF!
Name ___RSE2: '[1]CMA Addition'!$H$139
Name ___TGL1: #REF!
Name ___TGL2: #REF!
Name __COA08: [5]coa!$E$6:$E$944
Name __DAT1: #REF!
Name __DAT10: #REF!
Name __DAT11: #REF!
Name __DAT12: #REF!
Name __DAT13: #REF!
Name __DAT14: #REF!
Name __DAT15: #REF!
Name __DAT16: #REF!
Name __DAT17: #REF!
Name __DAT18: #REF!
Name __DAT19: #REF!
Name __DAT2: #REF!
Name __DAT20: #REF!
Name __DAT3: #REF!
Name __DAT4: #REF!
Name __DAT5: #REF!
Name __DAT6: #REF!
Name __DAT7: #REF!
Name __DAT8: #REF!
Name __DAT9: #REF!
Name __m70000: #REF!
Name __RSE1: '[1]CMA Addition'!$E$139

Sheet TB
C1: 2022 | E1: 2022 | G1: 2021 | I1: 2021 | K1: 2020 | M1: 2020
B2: Tanah | C2: 11934000000 | E2: =C2+D2 -> 11934000000 | G2: 11934000000 | I2: =G2+H2 -> 11934000000 | K2: 11934000000 | M2: =K2+L2 -> 11934000000
B3: Bangunan | C3: 24671108216 | E3: =C3+D3 -> 24671108216 | G3: 24671108216 | I3: =G3+H3 -> 24671108216 | K3: 14898332500 | M3: =K3+L3 -> 14898332500
B4: Mesin | C4: 12464903552 | E4: =C4+D4 -> 12464903552 | G4: 12427073552 | I4: =G4+H4 -> 12427073552 | K4: 12196073552 | M4: =K4+L4 -> 12196073552
B5: Kendaraan | C5: 1630238788 | E5: =C5+D5 -> 1630238788 | G5: 1431471000 | I5: =G5+H5 -> 1431471000 | K5: 1431471000 | M5: =K5+L5 -> 1431471000
B6: Kendaraan Alat Berat | C6: 545000000 | E6: =C6+D6 -> 545000000 | G6: 545000000 | I6: =G6+H6 -> 545000000 | K6: 545000000 | M6: =K6+L6 -> 545000000
B7: Peralatan Kantor | C7: 234184005 | E7: =C7+D7 -> 234184005 | G7: 229134005 | I7: =G7+H7 -> 229134005 | K7: 227534005 | M7: =K7+L7 -> 227534005
B8: Peralatan Produksi | C8: 1389452351 | E8: =C8+D8 -> 1389452351 | G8: 1371567751 | I8: =G8+H8 -> 1371567751 | K8: 1356328751 | M8: =K8+L8 -> 1356328751
B9: Sumur Bor | C9: 337941600 | E9: =C9+D9 -> 337941600 | G9: 337941600 | I9: =G9+H9 -> 337941600 | K9: 337941600 | M9: =K9+L9 -> 337941600
B10: Peralatan Labolatorium | C10: 112970000 | E10: =C10+D10 -> 112970000 | G10: 112970000 | I10: =G10+H10 -> 112970000 | K10: 112970000 | M10: =K10+L10 -> 112970000
C11: =SUM(C2:C10) -> 53319798512 | E11: =SUM(E2:E10) -> 53319798512 | G11: =SUM(G2:G10) -> 53060266124 | I11: =SUM(I2:I10) -> 53060266124 | K11: =SUM(K2:K10) -> 43039651408 | L11: =SUM(L2:L10) -> 0 | M11: =SUM(M2:M10) -> 43039651408
M12: =M11-'ADJ 2020'!F18 -> -4.1695423e+10
B14: Akum Peny. Bangunan | C14: 5887753759 | E14: =C14-D14 -> 5887753759 | G14: 4654194214 | H14: ='ADJ 2021'!G21 -> -2.6862994e+09 | I14: =G14-H14 -> 7.3404936e+09 | K14: 3909277573 | L14: ='ADJ 2020'!G21 -> -2.0223688e+09 | M14: =K14-L14 -> 5.9316464e+09
B15: Aum. Peny. Mesin | C15: 5321002979 | E15: =C15-D15 -> 5321002979 | G15: 4543719794 | H15: ='ADJ 2021'!G22 -> -1.0220462e+10 | I15: =G15-H15 -> 1.4764182e+10 | K15: 3779058952 | L15: ='ADJ 2020'!G22 -> -8.1596562e+09 | M15: =K15-L15 -> 1.1938715e+10
B16: Akum. Peny. Kendaraan | C16: 758337911 | E16: =C16-D16 -> 758337911 | G16: 575795564 | H16: ='ADJ 2021'!G23 -> -5728781936 | I16: =G16-H16 -> 6304577500 | K16: 396861684 | L16: ='ADJ 2020'!G23 -> -4865695816 | M16: =K16-L16 -> 5262557500
B17: Akum. Peny. Kendaraan Alat Berat | C17: 523581250 | E17: =C17-D17 -> 523581250 | G17: 467031250 | H17: ='ADJ 2021'!G24 -> 142467250 | I17: =G17-H17 -> 324564000 | K17: 398906250 | L17: ='ADJ 2020'!G24 -> 146956250 | M17: =K17-L17 -> 251950000
B18: Akum. Peny. Peralatan Kantor | C18: 202378387 | E18: =C18-D18 -> 202378387 | G18: 176328564 | H18: ='ADJ 2021'!G25 -> -9.1383662e+08 | I18: =G18-H18 -> 1.0901652e+09 | K18: 145371960 | L18: ='ADJ 2020'!G25 -> -8.6361391e+08 | M18: =K18-L18 -> 1.0089859e+09
B19: Akum. Peny. Peralatan Produksi | C19: 1323116936 | E19: =C19-D19 -> 1323116936 | G19: 1281284963 | H19: ='ADJ 2021'!G26 -> -6.440213e+09 | I19: =G19-H19 -> 7.7214979e+09 | K19: 1238393423 | L19: ='ADJ 2020'!G26 -> -5.1164124e+09 | M19: =K19-L19 -> 6.3548058e+09
B20: Akum. Peny. Sumur Bor | C20: 284202368 | E20: =C20-D20 -> 284202368 | G20: 247367639 | H20: ='ADJ 2021'!G27 -> -55558486 | I20: =G20-H20 -> 302926125 | K20: 205124939 | L20: ='ADJ 2020'!G27 -> -42168748 | M20: =K20-L20 -> 2.4729369e+08
B21: Akum. Peny. Peralatan Labolatorium | C21: 112970014 | E21: =C21-D21 -> 112970014 | G21: 96085012 | H21: ='ADJ 2021'!G28 -> -2.780119e+09 | I21: =G21-H21 -> 2.876204e+09 | K21: 67842508 | L21: ='ADJ 2020'!G28 -> -2.3111475e+09 | M21: =K21-L21 -> 2.37899e+09
C22: =SUM(C14:C21) -> 14413343604 | E22: =SUM(E14:E21) -> 14413343604 | G22: =SUM(G14:G21) -> 12041807000 | I22: =SUM(I14:I21) -> 4.072461e+10 | K22: =SUM(K14:K21) -> 10140837289 | L22: =SUM(L14:L21) -> -2.3234107e+10 | M22: =SUM(M14:M21) -> 3.3374944e+10
M23: =M22-'ADJ 2020'!F29 -> 0
B24: R/E | C24: 8151563821 | E24: =C24-D24 -> 8151563821 | G24: 2701171287 | I24: =G24-H24 -> 2701171287 | K24: 695537211 | L24: =-'ADJ 2020'!K38-'ADJ 2020'!K55 -> 1.7853017e+10 | M24: =K24-L24 -> -1.7157479e+10
B25: tahun berjalan | E25: =C25-D25 -> 0 | I25: =G25-H25 -> 0 | K25: 2005634076 | M25: =K25-L25 -> 2005634076
A27: COGS | B27: Depreciation | C27: 2328601782 | E27: =C27+D27 -> 2328601782 | G27: 1841766477 | I27: =G27+H27 -> 1841766477 | K27: 1216185335 | L27: =-'ADJ 2020'!G43 -> 4.319879e+09 | M27: =K27+L27 -> 5.5360643e+09
M28: =M27-'ADJ 2020'!F43 -> 0
A30: Opex | B30: Beban Depresiasi Dan Amortisasi | E30: =C30+D30 -> 0 | I30: =G30+H30 -> 0 | K30: 662689697 | L30: =-'ADJ 2020'!G44 -> -662689697 | M30: =K30+L30 -> 0
B31: Penyusutan Peralatan Kantor | C31: 26049820 | E31: =C31+D31 -> 26049820 | G31: 30960732 | I31: =G31+H31 -> 30960732 | L31: =-'ADJ 2020'!G45 -> 1.8287965e+08 | M31: =K31+L31 -> 1.8287965e+08
B32: Penyusutan Peralatan LAB | C32: 16885002 | E32: =C32+D32 -> 16885002 | G32: 28242504 | I32: =G32+H32 -> 28242504 | L32: =-'ADJ 2020'!G46 -> 4.9721397e+08 | M32: =K32+L32 -> 4.9721397e+08
B33: Penyusutan Kendaraan | E33: =C33+D33 -> 0 | I33: =G33+H33 -> 0 | L33: =-'ADJ 2020'!G47 -> 1043807500 | M33: =K33+L33 -> 1043807500
C34: =SUM(C30:C33) -> 42934822 | E34: =SUM(E30:E33) -> 42934822 | G34: =SUM(G30:G33) -> 59203236 | I34: =SUM(I30:I33) -> 59203236 | K34: =SUM(K30:K33) -> 662689697 | L34: =SUM(L30:L33) -> 1.0612114e+09 | M34: =SUM(M30:M33) -> 1.7239011e+09
C36: =C27+C34 -> 2371536604 | E36: =E27+E34 -> 2371536604 | G36: =G27+G34 -> 1900969713 | I36: =I27+I34 -> 1900969713 | K36: =K27+K34 -> 1878875032 | L36: =L27+L34 -> 5.3810904e+09 | M36: =K36+L36 -> 7.2599655e+09
M37: =M36-'ADJ 2020'!F48 -> 0

Sheet ADJ 2022
A1: Klien | C1: : | D1: PT. INDO AMERICAN SEAFOODS
A2: Tahun Buku | C2: : | D2: 31 Desember 2022
A3: Adjustment Audited
A5: No. | B5: No. Akun | C5: Jurnal | H5: Debit | I5: Kredit | J5: Efek Ke Neraca | M5: Efek ke LR | O5: Keterangan
J6: Debit | K6: Kredit | M6: Debit | N6: Kredit
A8: 1 | D8: Harga perolehan | E8: Inhouse | F8: Daftar Aset Tetap | G8: Selisih
D9: =TB!B2 -> Tanah | E9: =TB!C2 -> 11934000000 | F9: ='1. Tanah'!D4 -> 655809273 | G9: =E9-F9 -> 11278190727
D10: =TB!B3 -> Bangunan | E10: =TB!C3 -> 24671108216 | F10: ='2. Bangunan'!E128 -> 3.7188156e+10 | G10: =E10-F10 -> -1.2517048e+10
D11: =TB!B4 -> Mesin | E11: =TB!C4 -> 12464903552 | F11: ='5. Mesin'!E328 -> 3.7618136e+10 | G11: =E11-F11 -> -2.5153233e+10
D12: =TB!B5 -> Kendaraan | E12: =TB!C5 -> 1630238788 | F12: ='7. Kendaraan'!E81 -> 8342660000 | G12: =E12-F12 -> -6712421212
D13: =TB!B6 -> Kendaraan Alat Berat | E13: =TB!C6 -> 545000000 | F13: ='6. Instalasi Elektrik'!E55 -> 1452280000 | G13: =E13-F13 -> -907280000
D14: =TB!B7 -> Peralatan Kantor | E14: =TB!C7 -> 234184005 | F14: ='8 Peralatan & Perlengkapan'!E161 -> 1274154796 | G14: =E14-F14 -> -1039970791
D15: =TB!B8 -> Peralatan Produksi | E15: =TB!C8 -> 1389452351 | F15: ='9. Infrastruktur'!E62 -> 1.1170379e+10 | G15: =E15-F15 -> -9.7809271e+09
D16: =TB!B9 -> Sumur Bor | E16: =TB!C9 -> 337941600 | F16: ='3. Sumur Bor'!E53 -> 445059500 | G16: =E16-F16 -> -107117900
D17: =TB!B10 -> Peralatan Labolatorium | E17: =TB!C10 -> 112970000 | F17: ='4. Sarana & Prasarana'!E42 -> 6200217370 | G17: =E17-F17 -> -6087247370
E18: =SUM(E9:E17) -> 53319798512 | F18: =SUM(F9:F17) -> 1.0434685e+11
A20: 2 | D20: Akumulasi Penyusutan | E20: Inhouse | F20: Daftar Aset Tetap | G20: Selisih
D21: =TB!B14 -> Akum Peny. Bangunan | E21: =TB!C14 -> 5887753759 | F21: ='2. Bangunan'!AI115 -> 9.2122918e+09 | G21: =E21-F21 -> -3.324538e+09
D22: =TB!B15 -> Aum. Peny. Mesin | E22: =TB!C15 -> 5321002979 | F22: ='5. Mesin'!AH315 -> 1.8146072e+10 | G22: =E22-F22 -> -1.2825069e+10
D23: =TB!B16 -> Akum. Peny. Kendaraan | E23: =TB!C16 -> 758337911 | F23: ='7. Kendaraan'!AH69 -> 7346435000 | G23: =E23-F23 -> -6588097089
D24: =TB!B17 -> Akum. Peny. Kendaraan Alat Berat | E24: =TB!C17 -> 523581250 | F24: ='6. Instalasi Elektrik'!AH43 -> 397178000 | G24: =E24-F24 -> 126403250
D25: =TB!B18 -> Akum. Peny. Peralatan Kantor | E25: =TB!C18 -> 202378387 | F25: ='8 Peralatan & Perlengkapan'!AH149 -> 1.1746927e+09 | G25: =E25-F25 -> -9.7231429e+08
D26: =TB!B19 -> Akum. Peny. Peralatan Produksi | E26: =TB!C19 -> 1323116936 | F26: ='9. Infrastruktur'!AH50 -> 9.0558485e+09 | G26: =E26-F26 -> -7.7327316e+09
D27: =TB!B20 -> Akum. Peny. Sumur Bor | E27: =TB!C20 -> 284202368 | F27: ='3. Sumur Bor'!AI40 -> 3.5855856e+08 | G27: =E27-F27 -> -74356194
D28: =TB!B21 -> Akum. Peny. Peralatan Labolatorium | E28: =TB!C21 -> 112970014 | F28: ='4. Sarana & Prasarana'!AI29 -> 3366962620 | G28: =E28-F28 -> -3253992606
E29: =SUM(E21:E28) -> 14413343604 | F29: =SUM(F21:F28) -> 4.9058039e+10
F30: =E29-F29 -> -3.4644696e+10
D32: =D21 -> Akum Peny. Bangunan | H32: =G21 -> -3.324538e+09 | J32: =H32 -> -3.324538e+09
D33: =D22 -> Aum. Peny. Mesin | H33: =G22 -> -1.2825069e+10 | J33: =H33 -> -1.2825069e+10
D34: =D24 -> Akum. Peny. Kendaraan Alat Berat | H34: =G24 -> 126403250 | J34: =H34 -> 126403250
D35: =D26 -> Akum. Peny. Peralatan Produksi | H35: =G26 -> -7.7327316e+09 | J35: =H35 -> -7.7327316e+09
D36: =D28 -> Akum. Peny. Peralatan Labolatorium | H36: =G28 -> -3253992606 | J36: =H36 -> -3253992606
D37: R/E | I37: =SUM(H32:H36)-SUM(I38:I40) -> -3.4644696e+10 | K37: =I37 -> -3.4644696e+10
D38: =D23 -> Akum. Peny. Kendaraan | I38: =-G23 -> 6588097089 | K38: =I38 -> 6588097089
D39: =D25 -> Akum. Peny. Peralatan Kantor | I39: =-G25 -> 9.7231429e+08 | K39: =I39 -> 9.7231429e+08
D40: =D27 -> Akum. Peny. Sumur Bor | I40: =-G27 -> 74356194 | K40: =I40 -> 74356194
D41: (Penyesuaian akumulasi penyusutan aset tetap sesuai dengan daftar aset tetap)
A43: 3 | D43: Beban Penyusutan | E43: Inhouse | F43: Daftar Aset Tetap | G43: Selisih
D44: Depreciation | E44: =TB!C27 -> 2328601782 | F44: ='2. Bangunan'!AH115+'5. Mesin'!AG315+'6. Instalasi Elektrik'!AG43+'9. Infrastruktur'!AG50+'3. Sumur Bor'!AH40 -> 6.704861e+09 | G44: =E44-F44 -> -4.3762593e+09
D45: Beban Depresiasi Dan Amortisasi | E45: =TB!C30 -> 0 | G45: =E45-F45 -> 0
D46: Penyusutan Peralatan Kantor | E46: =TB!C31 -> 26049820 | F46: ='8 Peralatan & Perlengkapan'!AG149 -> 84527500 | G46: =E46-F46 -> -58477680
D47: Penyusutan Peralatan LAB | E47: =TB!C32 -> 16885002 | F47: ='4. Sarana & Prasarana'!AH29 -> 4.9075862e+08 | G47: =E47-F47 -> -4.7387362e+08
D48: Penyusutan Kendaraan | E48: =TB!C33 -> 0 | F48: ='7. Kendaraan'!AG69 -> 1041857500 | G48: =E48-F48 -> -1041857500
E49: =SUM(E44:E48) -> 2371536604 | F49: =SUM(F44:F48) -> 8.3220047e+09
F50: =E49-F49 -> -5.9504681e+09
A51: 4 | D51: =D46 -> Penyusutan Peralatan Kantor | H51: =-G46 -> 58477680 | M51: =H51 -> 58477680
D52: =D48 -> Penyusutan Kendaraan | H52: =-G48 -> 1041857500 | M52: =H52 -> 1041857500
D53: R/E | I53: =SUM(H51:H52)-SUM(I54:I55) -> 5.9504681e+09 | K53: =I53 -> 5.9504681e+09
D54: =D44 -> Depreciation | I54: =G44 -> -4.3762593e+09 | N54: =I54 -> -4.3762593e+09
D55: =D47 -> Penyusutan Peralatan LAB | I55: =G47 -> -4.7387362e+08 | N55: =I55 -> -4.7387362e+08
D56: (Penyesuaian beban penyusutan aset tetap sesuai dengan daftar aset tetap)
A58: =A51+1 -> 5
H63: =SUM(H7:H62) -> -2.5909593e+10 | I63: =SUM(I7:I62) -> -2.5909593e+10 | J63: =SUM(J7:J62) -> -2.7009928e+10 | K63: =SUM(K7:K62) -> -2.105946e+10 | M63: =SUM(M7:M62) -> 1.1003352e+09 | N63: =SUM(N7:N62) -> -4.8501329e+09
I64: =H63-I63 -> 0 | J64: =J63-K63 -> -5.9504681e+09 | N64: =N63-M63 -> -5.9504681e+09
F65: =F30-F50 -> -2.8694228e+10
E66: Laba (Rugi) sebelum Audit
E67: Laba (Rugi) setelah Audit
E68: Selisih | N68: =N66-N67 -> 0
B70: Disetujui Oleh,
B74: Direksi

Sheet ADJ 2021
A1: Klien | C1: : | D1: PT. INDO AMERICAN SEAFOODS
A2: Tahun Buku | C2: : | D2: 31 Desember 2021
A3: Adjustment Audited
A5: No. | B5: No. Akun | C5: Jurnal | H5: Debit | I5: Kredit | J5: Efek Ke Neraca | M5: Efek ke LR | O5: Keterangan
J6: Debit | K6: Kredit | M6: Debit | N6: Kredit
A8: 1 | D8: Harga perolehan | E8: Inhouse | F8: Daftar Aset Tetap | G8: Selisih
D9: =TB!B2 -> Tanah | E9: =TB!G2 -> 11934000000 | F9: ='1. Tanah'!D4 -> 655809273 | G9: =E9-F9 -> 11278190727
D10: =TB!B3 -> Bangunan | E10: =TB!G3 -> 24671108216 | F10: ='2. Bangunan'!E127 -> 3.7188156e+10 | G10: =E10-F10 -> -1.2517048e+10
D11: =TB!B4 -> Mesin | E11: =TB!G4 -> 12427073552 | F11: ='5. Mesin'!E327 -> 3.7601207e+10 | G11: =E11-F11 -> -2.5174133e+10
D12: =TB!B5 -> Kendaraan | E12: =TB!G5 -> 1431471000 | F12: ='7. Kendaraan'!E80 -> 8342660000 | G12: =E12-F12 -> -6911189000
D13: =TB!B6 -> Kendaraan Alat Berat | E13: =TB!G6 -> 545000000 | F13: ='6. Instalasi Elektrik'!E54 -> 1452280000 | G13: =E13-F13 -> -907280000
D14: =TB!B7 -> Peralatan Kantor | E14: =TB!G7 -> 229134005 | F14: ='8 Peralatan & Perlengkapan'!E160 -> 1212799796 | G14: =E14-F14 -> -983665791
D15: =TB!B8 -> Peralatan Produksi | E15: =TB!G8 -> 1371567751 | F15: ='9. Infrastruktur'!E61 -> 1.1170379e+10 | G15: =E15-F15 -> -9.7988117e+09
D16: =TB!B9 -> Sumur Bor | E16: =TB!G9 -> 337941600 | F16: ='3. Sumur Bor'!E52 -> 445059500 | G16: =E16-F16 -> -107117900
D17: =TB!B10 -> Peralatan Labolatorium | E17: =TB!G10 -> 112970000 | F17: ='4. Sarana & Prasarana'!E41 -> 6200217370 | G17: =E17-F17 -> -6087247370
E18: =SUM(E9:E17) -> 53060266124 | F18: =SUM(F9:F17) -> 1.0426857e+11
A20: 2 | D20: Akumulasi Penyusutan | E20: Inhouse | F20: Daftar Aset Tetap | G20: Selisih
D21: =TB!B14 -> Akum Peny. Bangunan | E21: =TB!G14 -> 4654194214 | F21: ='2. Bangunan'!AF115 -> 7.3404936e+09 | G21: =E21-F21 -> -2.6862994e+09
D22: =TB!B15 -> Aum. Peny. Mesin | E22: =TB!G15 -> 4543719794 | F22: ='5. Mesin'!AE315 -> 1.4764182e+10 | G22: =E22-F22 -> -1.0220462e+10
D23: =TB!B16 -> Akum. Peny. Kendaraan | E23: =TB!G16 -> 575795564 | F23: ='7. Kendaraan'!AE69 -> 6304577500 | G23: =E23-F23 -> -5728781936
D24: =TB!B17 -> Akum. Peny. Kendaraan Alat Berat | E24: =TB!G17 -> 467031250 | F24: ='6. Instalasi Elektrik'!AE43 -> 324564000 | G24: =E24-F24 -> 142467250
D25: =TB!B18 -> Akum. Peny. Peralatan Kantor | E25: =TB!G18 -> 176328564 | F25: ='8 Peralatan & Perlengkapan'!AE149 -> 1.0901652e+09 | G25: =E25-F25 -> -9.1383662e+08
D26: =TB!B19 -> Akum. Peny. Peralatan Produksi | E26: =TB!G19 -> 1281284963 | F26: ='9. Infrastruktur'!AE50 -> 7.7214979e+09 | G26: =E26-F26 -> -6.440213e+09
D27: =TB!B20 -> Akum. Peny. Sumur Bor | E27: =TB!G20 -> 247367639 | F27: ='3. Sumur Bor'!AF40 -> 302926125 | G27: =E27-F27 -> -55558486
D28: =TB!B21 -> Akum. Peny. Peralatan Labolatorium | E28: =TB!G21 -> 96085012 | F28: ='4. Sarana & Prasarana'!AF29 -> 2.876204e+09 | G28: =E28-F28 -> -2.780119e+09
E29: =SUM(E21:E28) -> 12041807000 | F29: =SUM(F21:F28) -> 4.072461e+10
F30: =E29-F29 -> -2.8682803e+10
D31: =D21 -> Akum Peny. Bangunan | H31: =G21 -> -2.6862994e+09 | J31: =H31 -> -2.6862994e+09
D32: =D22 -> Aum. Peny. Mesin | H32: =G22 -> -1.0220462e+10 | J32: =H32 -> -1.0220462e+10
D33: Akum. Peny. Kendaraan | H33: =G23 -> -5728781936 | J33: =H33 -> -5728781936
D34: =D24 -> Akum. Peny. Kendaraan Alat Berat | H34: =G24 -> 142467250 | J34: =H34 -> 142467250
D35: =D25 -> Akum. Peny. Peralatan Kantor | H35: =G25 -> -9.1383662e+08 | J35: =H35 -> -9.1383662e+08
D36: =D26 -> Akum. Peny. Peralatan Produksi | H36: =G26 -> -6.440213e+09 | J36: =H36 -> -6.440213e+09
D37: =D27 -> Akum. Peny. Sumur Bor | H37: =G27 -> -55558486 | J37: =H37 -> -55558486
D38: =D28 -> Akum. Peny. Peralatan Labolatorium | H38: =G28 -> -2.780119e+09 | J38: =H38 -> -2.780119e+09
D39: R/E | I39: =SUM(H31:H38) -> -2.8682803e+10 | K39: =I39 -> -2.8682803e+10
D40: (Penyesuaian akumulasi penyusutan aset tetap sesuai dengan daftar aset tetap)
A42: 3 | D42: Beban Penyusutan | E42: Inhouse | F42: Daftar Aset Tetap | G42: Selisih
D43: Depreciation | E43: =TB!G27 -> 1841766477 | F43: ='2. Bangunan'!AE115+'5. Mesin'!AD315+'6. Instalasi Elektrik'!AD43+'9. Infrastruktur'!AD50+'3. Sumur Bor'!AE40 -> 5.740677e+09 | G43: =E43-F43 -> -3.8989105e+09
D44: Beban Depresiasi Dan Amortisasi | E44: =TB!G30 -> 0 | G44: =E44-F44 -> 0
D45: Penyusutan Peralatan Kantor | E45: =TB!G31 -> 30960732 | F45: ='8 Peralatan & Perlengkapan'!AD149 -> 81179313 | G45: =E45-F45 -> -50218581
D46: Penyusutan Peralatan LAB | E46: =TB!G32 -> 28242504 | F46: ='4. Sarana & Prasarana'!AE29 -> 4.9721397e+08 | G46: =E46-F46 -> -4.6897146e+08
D47: Penyusutan Kendaraan | E47: =TB!G33 -> 0 | F47: ='7. Kendaraan'!AD69 -> 1042020000 | G47: =E47-F47 -> -1042020000
E48: =SUM(E43:E47) -> 1900969713 | F48: =SUM(F43:F47) -> 7.3610903e+09
F49: =E48-F48 -> -5.4601206e+09
A50: 4 | D50: =D45 -> Penyusutan Peralatan Kantor | H50: =-G45 -> 50218581 | M50: =H50 -> 50218581
D51: =D47 -> Penyusutan Kendaraan | H51: =-G47 -> 1042020000 | M51: =H51 -> 1042020000
D52: R/E | H52: =SUM(I53:I54)-SUM(H50:H51) -> -5.4601206e+09 | J52: =H52 -> -5.4601206e+09
D53: =D43 -> Depreciation | I53: =G43 -> -3.8989105e+09 | N53: =I53 -> -3.8989105e+09
D54: =D46 -> Penyusutan Peralatan LAB | I54: =G46 -> -4.6897146e+08 | N54: =I54 -> -4.6897146e+08
D55: (Penyesuaian beban penyusutan aset tetap sesuai dengan daftar aset tetap)
A57: =A50+1 -> 5
H62: =SUM(H7:H61) -> -3.3050685e+10 | I62: =SUM(I7:I61) -> -3.3050685e+10 | J62: =SUM(J7:J61) -> -3.4142924e+10 | K62: =SUM(K7:K61) -> -2.8682803e+10 | M62: =SUM(M7:M61) -> 1.0922386e+09 | N62: =SUM(N7:N61) -> -4.367882e+09
I63: =H62-I62 -> 0 | J63: =J62-K62 -> -5.4601206e+09 | N63: =N62-M62 -> -5.4601206e+09
E65: Laba (Rugi) sebelum Audit
E66: Laba (Rugi) setelah Audit
E67: Selisih | N67: =N65-N66 -> 0
B69: Disetujui Oleh,
B73: Direksi

Sheet ADJ 2020
A1: Klien | C1: : | D1: PT. INDO AMERICAN SEAFOODS
A2: Tahun Buku | C2: : | D2: 31 Desember 2020
A3: Adjustment Audited
A5: No. | B5: No. Akun | C5: Jurnal | H5: Debit | I5: Kredit | J5: Efek Ke Neraca | M5: Efek ke LR | O5: Keterangan
J6: Debit | K6: Kredit | M6: Debit | N6: Kredit
A8: 1 | D8: Harga perolehan | E8: Inhouse | F8: Daftar Aset Tetap | G8: Selisih
D9: =TB!B2 -> Tanah | E9: =TB!K2 -> 11934000000 | F9: ='1. Tanah'!D4 -> 655809273 | G9: =E9-F9 -> 11278190727
D10: =TB!B3 -> Bangunan | E10: =TB!K3 -> 14898332500 | F10: ='2. Bangunan'!E126 -> 2.7419763e+10 | G10: =E10-F10 -> -1.252143e+10
D11: =TB!B4 -> Mesin | E11: =TB!K4 -> 12196073552 | F11: ='5. Mesin'!E326 -> 2.8284388e+10 | G11: =E11-F11 -> -1.6088314e+10
D12: =TB!B5 -> Kendaraan | E12: =TB!K5 -> 1431471000 | F12: ='7. Kendaraan'!E79 -> 8342660000 | G12: =E12-F12 -> -6911189000
D13: =TB!B6 -> Kendaraan Alat Berat | E13: =TB!K6 -> 545000000 | F13: ='6. Instalasi Elektrik'!E53 -> 1007800000 | G13: =E13-F13 -> -462800000
D14: =TB!B7 -> Peralatan Kantor | E14: =TB!K7 -> 227534005 | F14: ='8 Peralatan & Perlengkapan'!E159 -> 1208997796 | G14: =E14-F14 -> -981463791
D15: =TB!B8 -> Peralatan Produksi | E15: =TB!K8 -> 1356328751 | F15: ='9. Infrastruktur'!E60 -> 1.1170379e+10 | G15: =E15-F15 -> -9.8140507e+09
D16: =TB!B9 -> Sumur Bor | E16: =TB!K9 -> 337941600 | F16: ='3. Sumur Bor'!E51 -> 445059500 | G16: =E16-F16 -> -107117900
D17: =TB!B10 -> Peralatan Labolatorium | E17: =TB!K10 -> 112970000 | F17: ='4. Sarana & Prasarana'!E40 -> 6200217370 | G17: =E17-F17 -> -6087247370
E18: =SUM(E9:E17) -> 43039651408 | F18: =SUM(F9:F17) -> 8.4735074e+10
A20: 2 | D20: Akumulasi Penyusutan | E20: Inhouse | F20: Daftar Aset Tetap | G20: Selisih
D21: =TB!B14 -> Akum Peny. Bangunan | E21: =TB!K14 -> 3909277573 | F21: ='2. Bangunan'!AC115 -> 5.9316464e+09 | G21: =E21-F21 -> -2.0223688e+09
D22: =TB!B15 -> Aum. Peny. Mesin | E22: =TB!K15 -> 3779058952 | F22: ='5. Mesin'!AB315 -> 1.1938715e+10 | G22: =E22-F22 -> -8.1596562e+09
D23: =TB!B16 -> Akum. Peny. Kendaraan | E23: =TB!K16 -> 396861684 | F23: ='7. Kendaraan'!AB69 -> 5262557500 | G23: =E23-F23 -> -4865695816
D24: =TB!B17 -> Akum. Peny. Kendaraan Alat Berat | E24: =TB!K17 -> 398906250 | F24: ='6. Instalasi Elektrik'!AB43 -> 251950000 | G24: =E24-F24 -> 146956250
D25: =TB!B18 -> Akum. Peny. Peralatan Kantor | E25: =TB!K18 -> 145371960 | F25: ='8 Peralatan & Perlengkapan'!AB149 -> 1.0089859e+09 | G25: =E25-F25 -> -8.6361391e+08
D26: =TB!B19 -> Akum. Peny. Peralatan Produksi | E26: =TB!K19 -> 1238393423 | F26: ='9. Infrastruktur'!AB50 -> 6.3548058e+09 | G26: =E26-F26 -> -5.1164124e+09
D27: =TB!B20 -> Akum. Peny. Sumur Bor | E27: =TB!K20 -> 205124939 | F27: ='3. Sumur Bor'!AC40 -> 2.4729369e+08 | G27: =E27-F27 -> -42168748
D28: =TB!B21 -> Akum. Peny. Peralatan Labolatorium | E28: =TB!K21 -> 67842508 | F28: ='4. Sarana & Prasarana'!AC29 -> 2.37899e+09 | G28: =E28-F28 -> -2.3111475e+09
E29: =SUM(E21:E28) -> 10140837289 | F29: =SUM(F21:F28) -> 3.3374944e+10
F30: =E29-F29 -> -2.3234107e+10
D31: =D21 -> Akum Peny. Bangunan | H31: =G21 -> -2.0223688e+09 | J31: =H31 -> -2.0223688e+09
D32: =D22 -> Aum. Peny. Mesin | H32: =G22 -> -8.1596562e+09 | J32: =H32 -> -8.1596562e+09
D33: =D24 -> Akum. Peny. Kendaraan Alat Berat | H33: =G24 -> 146956250 | J33: =H33 -> 146956250
D34: =D25 -> Akum. Peny. Peralatan Kantor | H34: =G25 -> -8.6361391e+08 | J34: =H34 -> -8.6361391e+08
D35: =D26 -> Akum. Peny. Peralatan Produksi | H35: =G26 -> -5.1164124e+09 | J35: =H35 -> -5.1164124e+09
D36: =D27 -> Akum. Peny. Sumur Bor | H36: =G27 -> -42168748 | J36: =H36 -> -42168748
D37: =D28 -> Akum. Peny. Peralatan Labolatorium | H37: =G28 -> -2.3111475e+09 | J37: =H37 -> -2.3111475e+09
D38: R/E | I38: =SUM(H31:H37)-I39 -> -2.3234107e+10 | K38: =I38 -> -2.3234107e+10
D39: =D23 -> Akum. Peny. Kendaraan | I39: =-G23 -> 4865695816 | K39: =I39 -> 4865695816
D40: (Penyesuaian akumulasi penyusutan aset tetap sesuai dengan daftar aset tetap)
A42: 3 | D42: Beban Penyusutan | E42: Inhouse | F42: Daftar Aset Tetap | G42: Selisih
D43: Depreciation | E43: =TB!K27 -> 1216185335 | F43: ='2. Bangunan'!AB115+'5. Mesin'!AA315+'6. Instalasi Elektrik'!AA43+'9. Infrastruktur'!AA50+'3. Sumur Bor'!AB40 -> 5.5360643e+09 | G43: =E43-F43 -> -4.319879e+09
D44: Beban Depresiasi Dan Amortisasi | E44: =TB!K30 -> 662689697 | G44: =E44-F44 -> 662689697
D45: Penyusutan Peralatan Kantor | F45: ='8 Peralatan & Perlengkapan'!AA149 -> 1.8287965e+08 | G45: =E45-F45 -> -1.8287965e+08
D46: Penyusutan Peralatan LAB | F46: ='4. Sarana & Prasarana'!AB29 -> 4.9721397e+08 | G46: =E46-F46 -> -4.9721397e+08
D47: Penyusutan Kendaraan | F47: ='7. Kendaraan'!AA69 -> 1043807500 | G47: =E47-F47 -> -1043807500
E48: =SUM(E43:E47) -> 1878875032 | F48: =SUM(F43:F47) -> 7.2599655e+09
F49: =E48-F48 -> -5.3810904e+09
A50: 4 | D50: =D43 -> Depreciation | H50: =-G43 -> 4.319879e+09 | M50: =H50 -> 4.319879e+09
D51: =D45 -> Penyusutan Peralatan Kantor | H51: =-G45 -> 1.8287965e+08 | M51: =H51 -> 1.8287965e+08
D52: =D46 -> Penyusutan Peralatan LAB | H52: =-G46 -> 4.9721397e+08 | M52: =H52 -> 4.9721397e+08
D53: =D47 -> Penyusutan Kendaraan | H53: =-G47 -> 1043807500 | M53: =H53 -> 1043807500
D54: =D44 -> Beban Depresiasi Dan Amortisasi | I54: =G44 -> 662689697 | N54: =I54 -> 662689697
D55: R/E | I55: =SUM(H50:H53)-I54 -> 5.3810904e+09 | K55: =I55 -> 5.3810904e+09
D56: (Penyesuaian beban penyusutan aset tetap sesuai dengan daftar aset tetap)
A58: =A50+1 -> 5
H63: =SUM(H7:H62) -> -1.2324631e+10 | I63: =SUM(I7:I62) -> -1.2324631e+10 | J63: =SUM(J7:J62) -> -1.8368411e+10 | K63: =SUM(K7:K62) -> -1.2987321e+10 | M63: =SUM(M7:M62) -> 6.0437801e+09 | N63: =SUM(N7:N62) -> 662689697
I64: =H63-I63 -> 0 | J64: =J63-K63 -> -5.3810904e+09 | N64: =N63-M63 -> -5.3810904e+09
E66: Laba (Rugi) sebelum Audit | N66: 2224905504
E67: Laba (Rugi) setelah Audit | N67: 2.2248634e+09
E68: Selisih | N68: =N66-N67 -> 42096.198
B70: Disetujui Oleh,
B74: Direksi

Sheet Aset Tetap
D1: PT. INDOKOM SAMUDERA PERSADA
D2: DIVISI COLD STORAGE 1
D3: DAFTAR ASET TETAP DAN PENYUSUTAN | Q3: Bak mobil Budidaya
D4: DESEMBER 2022
B5: 1 | C5: 1 | K5: 1.4112772e+11 | L5: 7.4137718e+09 | M5: 15636001272 | N5: 1.3291008e+11 | O5: 4.2713813e+10 | P5: 1.0115152e+10 | Q5: 2.5693171e+09 | R5: 5.0259648e+10 | S5: Dalam Rupiah (Rp)
D6: No | F6: Nama Asset | I6: Tahun | J6: % | K6: Harga Perolehan | L6: Mutasi | N6: Harga Perolehan | O6: Akm. Penyusutan | P6: Penyusutan Desember 2021 | R6: Akm. Penyusutan | S6: Nilai Buku
I8: Perolehan | K8: Per | N8: Per | O8: s/d | R8: s/d | S8: Per
K9: 31 Desember 2021 | L9: Penambahan | M9: Pengurangan | N9: 31 Desember 2022 | O9: 31 Desember 2021 | P9: Penambahan | Q9: Pengurangan | R9: 31 Desember 2022 | S9: 31 Desember 2022
A11: COLD STORAGE | B11: TANAH | C11: TANAH | D11: 1 | E11: TANAH
A12: COLD STORAGE | E12: 1.1 | F12: Tanah Cold Storage
A13: COLD STORAGE | H13: Tanah Divisi Cold Storage 1 | I13: 2002 | K13: 893958647 | L13: 0 | N13: =K13+L13-M13 -> 893958647 | O13: 0 | P13: 0 | Q13: 0 | R13: =O13+P13-Q13 -> 0 | S13: =N13-R13 -> 893958647
A14: COLD STORAGE | H14: Tanah Divisi Cold Storage 2 | I14: 2002 | K14: 200000000 | L14: 0 | N14: =K14+L14-M14 -> 200000000 | O14: 0 | P14: 0 | Q14: 0 | R14: =O14+P14-Q14 -> 0 | S14: =N14-R14 -> 200000000
H15: Tanah SHM NO.776,777,778 | I15: 2002 | K15: 226850626 | L15: 0 | N15: =K15+L15-M15 -> 226850626 | O15: 0 | P15: 0 | Q15: 0 | R15: =O15+P15-Q15 -> 0 | S15: =N15-R15 -> 226850626
A16: COLD STORAGE | E16: Subtotal Tanah Cold Storage | K16: =SUM(K13:K15) -> 1320809273 | L16: =SUM(L13:L15) -> 0 | M16: =SUM(M13:M15) -> 0 | N16: =SUM(N13:N15) -> 1320809273 | O16: =SUM(O13:O15) -> 0 | P16: =SUM(P13:P15) -> 0 | Q16: =SUM(Q13:Q15) -> 0 | R16: =SUM(R13:R15) -> 0 | S16: =SUM(S13:S15) -> 1320809273
A18: GEBANG | E18: 1.2 | F18: Tanah Gebang
A19: GEBANG | H19: Tanah Divisi Gebang | I19: 2005 | K19: 2538567500 | L19: 0 | M19: 0 | N19: =K19+L19-M19 -> 2538567500 | O19: 0 | P19: 0 | Q19: 0 | R19: =O19+P19-Q19 -> 0 | S19: =N19-R19 -> 2538567500
A20: GEBANG | E20: Subtotal Tanah Gebang | K20: =SUM(K19) -> 2538567500 | L20: =SUM(L19) -> 0 | M20: =SUM(M19) -> 0 | N20: =SUM(N19) -> 2538567500 | O20: =SUM(O19) -> 0 | P20: =SUM(P19) -> 0 | Q20: =SUM(Q19) -> 0 | R20: =SUM(R19) -> 0 | S20: =SUM(S19) -> 2538567500
A22: HOLDING | E22: 1.3 | F22: Tanah Holding
A23: HOLDING | H23: Tanah Divisi Holding | I23: 2008 | K23: 1533972000 | L23: 0 | M23: 0 | N23: =K23+L23-M23 -> 1533972000 | O23: 0 | P23: 0 | Q23: 0 | R23: =O23+P23-Q23 -> 0 | S23: =N23-R23 -> 1533972000
A24: HOLDING | H24: Tanah Divisi Maringgai | I24: 2002 | K24: 202373350 | L24: 0 | M24: 0 | N24: =K24+L24-M24 -> 202373350 | O24: 0 | P24: 0 | Q24: 0 | R24: =O24+P24-Q24 -> 0 | S24: =N24-R24 -> 202373350
A25: HOLDING | E25: Subtotal Tanah Holding | K25: =SUM(K23:K24) -> 1736345350 | L25: =SUM(L23:L24) -> 0 | M25: =SUM(M23:M24) -> 0 | N25: =SUM(N23:N24) -> 1736345350 | O25: =SUM(O23:O24) -> 0 | P25: =SUM(P23:P24) -> 0 | Q25: =SUM(Q23:Q24) -> 0 | R25: =SUM(R23:R24) -> 0 | S25: =SUM(S23:S24) -> 1736345350
A27: KETAPANG | E27: 1.4 | F27: Tanah Ketapang
A28: KETAPANG | H28: Tanah Divisi Ketapang | K28: 3436245000 | L28: 0 | M28: 0 | N28: =K28+L28-M28 -> 3436245000 | O28: 0 | P28: 0 | Q28: 0 | R28: =O28+P28-Q28 -> 0 | S28: =N28-R28 -> 3436245000
A29: KETAPANG | E29: Subtotal Tanah Ketapang | K29: =SUM(K28) -> 3436245000 | L29: =SUM(L28) -> 0 | M29: =SUM(M28) -> 0 | N29: =SUM(N28) -> 3436245000 | O29: =SUM(O28) -> 0 | P29: =SUM(P28) -> 0 | Q29: =SUM(Q28) -> 0 | R29: =SUM(R28) -> 0 | S29: =SUM(S28) -> 3436245000
A31: PAKAN | E31: 1.4 | F31: Tanah Pakan
A32: PAKAN | H32: Tanah Divisi Pakan | I32: 2006 | K32: 0 | L32: 0 | N32: =K32+L32-M32 -> 0 | O32: 0 | P32: 0 | Q32: 0 | R32: =O32+P32-Q32 -> 0 | S32: =N32-R32 -> 0
A33: PAKAN | E33: Subtotal Tanah Pakan | K33: =SUM(K32) -> 0 | L33: =SUM(L32) -> 0 | M33: =SUM(M32) -> 0 | N33: =SUM(N32) -> 0 | O33: =SUM(O32) -> 0 | P33: =SUM(P32) -> 0 | Q33: =SUM(Q32) -> 0 | R33: =SUM(R32) -> 0 | S33: =SUM(S32) -> 0
D35: TOTAL TANAH | K35: =K16+K20+K25+K29 -> 9031967123 | L35: =L16+L20+L25+L29 -> 0 | M35: =M16+M20+M25+M29 -> 0 | N35: =N16+N20+N25+N29 -> 9031967123 | O35: =O16+O20+O25+O29 -> 0 | P35: =P16+P20+P25+P29 -> 0 | Q35: =Q16+Q20+Q25+Q29 -> 0 | R35: =R16+R20+R25+R29 -> 0 | S35: =S16+S20+S25+S29 -> 9031967123
A37: COLD STORAGE | B37: BANGUNAN | C37: BANGUNAN | D37: 2 | E37: BANGUNAN
A38: COLD STORAGE | E38: 2.1 | F38: Bangunan Cold Storage
A39: COLD STORAGE | F39: 2.1.1 | G39: DIVISI ISP 1
A40: COLD STORAGE | H40: Bangunan ISP 1 | I40: 2005 | J40: 0.05 | K40: 5564855579 | L40: 0 | N40: =K40+L40-M40 -> 5564855579 | O40: 1.133304e+09 | P40: =23186898.2458333*12 -> 2.7824278e+08 | R40: =O40+P40-Q40 -> 1.4115468e+09 | S40: =N40-R40 -> 4.1533088e+09
A41: COLD STORAGE | H41: Bangunan Pos Satpam | I41: 2005 | J41: 0.05 | K41: 39450000 | L41: 0 | M41: 0 | N41: =K41+L41-M41 -> 39450000 | O41: 11835000 | P41: =164375*12 -> 1972500 | R41: =O41+P41-Q41 -> 13807500 | S41: =N41-R41 -> 25642500
A42: COLD STORAGE | H42: Bangunan Genset | I42: 2005 | J42: 0.05 | K42: 742420000 | L42: 0 | M42: 0 | N42: =K42+L42-M42 -> 742420000 | O42: 2.22726e+08 | P42: =3093416.66666667*12 -> 37121000 | R42: =O42+P42-Q42 -> 2.59847e+08 | S42: =N42-R42 -> 4.82573e+08
A43: COLD STORAGE | H43: KM/WC | I43: 2005 | J43: 0.05 | K43: 8100000 | L43: 0 | M43: 0 | N43: =K43+L43-M43 -> 8100000 | O43: 2430000 | P43: =33750*12 -> 405000 | R43: =O43+P43-Q43 -> 2835000 | S43: =N43-R43 -> 5265000
A44: COLD STORAGE | H44: Kantor 1 | I44: 2006 | J44: 0.05 | K44: 203210000 | L44: 0 | M44: 0 | N44: =K44+L44-M44 -> 203210000 | O44: 42335416 | P44: =846708.333333333*12 -> 10160500 | R44: =O44+P44-Q44 -> 52495916 | S44: =N44-R44 -> 150714084
A45: COLD STORAGE | H45: Kantin & KM/WC | I45: 2010 | J45: 0.05 | K45: 262080000 | L45: 0 | M45: 0 | N45: =K45+L45-M45 -> 262080000 | O45: 78624000 | P45: =1092000*12 -> 13104000 | R45: =O45+P45-Q45 -> 91728000 | S45: =N45-R45 -> 170352000
A46: COLD STORAGE | H46: Mushola | I46: 2010 | J46: 0.05 | K46: 194080000 | L46: 0 | M46: 0 | N46: =K46+L46-M46 -> 194080000 | O46: 58224000 | P46: =808666.666666667*12 -> 9704000 | R46: =O46+P46-Q46 -> 67928000 | S46: =N46-R46 -> 1.26152e+08
A47: COLD STORAGE | H47: Cafetaria | I47: 2010 | J47: 0.05 | K47: 313090000 | L47: 0 | M47: 0 | N47: =K47+L47-M47 -> 313090000 | O47: 93927000 | P47: =1304541.66666667*12 -> 15654500 | R47: =O47+P47-Q47 -> 1.095815e+08 | S47: =N47-R47 -> 2.035085e+08
A48: COLD STORAGE | H48: Panggung Ekspor | I48: 2010 | J48: 0.05 | K48: 23340000 | L48: 0 | M48: 0 | N48: =K48+L48-M48 -> 23340000 | O48: 4862500 | P48: =97250*12 -> 1167000 | R48: =O48+P48-Q48 -> 6029500 | S48: =N48-R48 -> 17310500
A49: COLD STORAGE | H49: Bangunan Receiver | I49: 2010 | J49: 0.05 | K49: 66130000 | L49: 0 | M49: 0 | N49: =K49+L49-M49 -> 66130000 | O49: 13777083 | P49: =275541.666666667*12 -> 3306500 | R49: =O49+P49-Q49 -> 17083583 | S49: =N49-R49 -> 49046417
A50: COLD STORAGE | H50: Kantor 3 (3lt) | I50: 2010 | J50: 0.05 | K50: 753420000 | L50: 0 | M50: 0 | N50: =K50+L50-M50 -> 753420000 | O50: 226026000 | P50: =3139250*12 -> 37671000 | R50: =O50+P50-Q50 -> 263697000 | S50: =N50-R50 -> 489723000
A51: COLD STORAGE | H51: Parkir Terbuka | I51: 2010 | J51: 0.05 | K51: 73630000 | L51: 0 | M51: 0 | N51: =K51+L51-M51 -> 73630000 | O51: 22089000 | P51: =306791.666666667*12 -> 3681500 | R51: =O51+P51-Q51 -> 25770500 | S51: =N51-R51 -> 47859500
A52: COLD STORAGE | H52: Gudang Trafo (2 unit) | I52: 2014 | J52: 0.05 | K52: 50330000 | N52: =K52+L52-M52 -> 50330000 | O52: 15099000 | P52: =209708.333333333*12 -> 2516500 | R52: =O52+P52-Q52 -> 17615500 | S52: =N52-R52 -> 32714500
A53: COLD STORAGE | H53: Bangunan ATM | I53: 2015 | J53: 0.05 | K53: 9720000 | N53: =K53+L53-M53 -> 9720000 | O53: 2916000 | P53: =40500*12 -> 486000 | R53: =O53+P53-Q53 -> 3402000 | S53: =N53-R53 -> 6318000
H54: Bangunan Baru | I54: 43708 | J54: 0.05 | K54: 3.9492779e+09 | N54: =K54+L54-M54 -> 3.9492779e+09 | O54: 4.6074908e+08 | P54: =16455324.420125*12 -> 1.9746389e+08 | R54: =O54+P54-Q54 -> 6.5821298e+08 | S54: =N54-R54 -> 3.2910649e+09
H55: Bangunan Renovasi | I55: 44561 | J55: 0.05 | K55: 2.6670787e+10 | N55: =K55+L55-M55 -> 2.6670787e+10 | O55: 1.2438996e+08 | P55: =37194980.1594167*12 -> 4.4633976e+08 | R55: =O55+P55-Q55 -> 5.7072972e+08 | S55: =N55-R55 -> 2.6100058e+10
A56: COLD STORAGE | F56: Jumlah Bangunan Div.ISP 1 | K56: =SUM(K40:K55) -> 3.8923921e+10 | L56: =SUM(L40:L55) -> 0 | M56: =SUM(M40:M55) -> 0 | N56: =SUM(N40:N55) -> 3.8923921e+10 | O56: =SUM(O40:O55) -> 2.5133141e+09 | P56: =SUM(P40:P55) -> 1.0589964e+09 | Q56: =SUM(Q40:Q55) -> 0 | R56: =SUM(R40:R55) -> 3.5723105e+09 | S56: =SUM(S40:S55) -> 3.535161e+10
A57: COLD STORAGE | F57: 2.1.2 | G57: DIVISI ISP 2
A58: COLD STORAGE | H58: Mess 2 | I58: 2005 | J58: 0.05 | K58: 0 | L58: 0 | N58: 0 | O58: 0 | R58: 0 | S58: 0
A59: COLD STORAGE | H59: Kantor 2 | I59: 2010 | J59: 0.05 | K59: 128910000 | L59: 0 | M59: 0 | N59: =K59+L59-M59 -> 128910000 | O59: 38673000 | P59: =537125*12 -> 6445500 | R59: =O59+P59-Q59 -> 45118500 | S59: =N59-R59 -> 83791500
A60: COLD STORAGE | H60: Bangunan ISP 2 | I60: 2011 | J60: 0.05 | K60: 9.4432849e+09 | L60: 0 | M60: 0 | N60: =K60+L60-M60 -> 9.4432849e+09 | O60: 2.638797e+09 | P60: =39347020.3333333*12 -> 4.7216424e+08 | R60: =O60+P60-Q60 -> 3.1109612e+09 | S60: =N60-R60 -> 6.3323237e+09
A61: COLD STORAGE | F61: Jumlah Bangunan Div.ISP 2 | K61: =SUM(K59:K60) -> 9.5721949e+09 | L61: =SUM(L59:L60) -> 0 | M61: =SUM(M59:M60) -> 0 | N61: =SUM(N59:N60) -> 9.5721949e+09 | O61: =SUM(O59:O60) -> 2.67747e+09 | P61: =SUM(P59:P60) -> 4.7860974e+08 | Q61: =SUM(Q59:Q60) -> 0 | R61: =SUM(R59:R60) -> 3.1560797e+09 | S61: =SUM(S59:S60) -> 6.4161152e+09
A62: COLD STORAGE | F62: 2.1.3 | G62: PABRIK ROTI
A63: COLD STORAGE | H63: Kantor | I63: 2012 | J63: 0.05 | K63: 0 | L63: 0 | N63: =K63+L63-M63 -> 0 | O63: 0 | R63: =O63+P63-Q63 -> 0 | S63: =N63-R63 -> 0
A64: COLD STORAGE | H64: Gudang Roti | I64: 2012 | J64: 0.05 | K64: 0 | L64: 0 | N64: =K64+L64-M64 -> 0 | O64: 0 | R64: =O64+P64-Q64 -> 0 | S64: =N64-R64 -> 0
A65: COLD STORAGE | F65: Jumlah Bangunan Div. Pabrik Roti | K65: =SUM(K63:K64) -> 0 | L65: =SUM(L63:L64) -> 0 | M65: =SUM(M63:M64) -> 0 | N65: =SUM(N63:N64) -> 0 | O65: =SUM(O63:O64) -> 0 | P65: =SUM(P63:P64) -> 0 | Q65: =SUM(Q63:Q64) -> 0 | R65: =SUM(R63:R64) -> 0 | S65: =SUM(S63:S64) -> 0
A66: COLD STORAGE | E66: Subtotal Bangunan Cold Storage | K66: =K56+K61+K65 -> 4.8496116e+10 | L66: =L56+L61+L65 -> 0 | M66: =M56+M61+M65 -> 0 | N66: =N56+N61+N65 -> 4.8496116e+10 | O66: =O56+O61+O65 -> 5.190784e+09 | P66: =P56+P61+P65 -> 1.5376062e+09 | Q66: =Q56+Q61+Q65 -> 0 | R66: =R56+R61+R65 -> 6.7283902e+09 | S66: =S56+S61+S65 -> 4.1767726e+10
A68: GEBANG | E68: 2.2 | F68: Bangunan Gebang
A69: GEBANG | F69: 2.2.1 | G69: Bangunan Umum Tambak 1000
A70: GEBANG | H70: Pos Satpam | I70: 2005 | J70: 0.05 | K70: 10960000 | L70: 0 | M70: 0 | N70: =K70+L70-M70 -> 10960000 | O70: 1644000 | P70: 0 | Q70: 0 | R70: =O70+P70-Q70 -> 1644000 | S70: =N70-R70 -> 9316000
A71: GEBANG | H71: Kantor, Mess, Logistik & Lab | I71: 2005 | J71: 0.05 | K71: 596230000 | L71: 0 | M71: 0 | N71: =K71+L71-M71 -> 596230000 | O71: 89434500 | P71: 0 | Q71: 0 | R71: =O71+P71-Q71 -> 89434500 | S71: =N71-R71 -> 506795500
A72: GEBANG | H72: Mess Umum | I72: 2011 | J72: 0.05 | K72: 97760000 | L72: 0 | M72: 0 | N72: =K72+L72-M72 -> 97760000 | O72: 14664000 | P72: 0 | Q72: 0 | R72: =O72+P72-Q72 -> 14664000 | S72: =N72-R72 -> 83096000
A73: GEBANG | H73: Bengkel +Mess | I73: 2011 | J73: 0.05 | K73: 131970000 | L73: 0 | M73: 0 | N73: =K73+L73-M73 -> 131970000 | O73: 19795500 | P73: 0 | Q73: 0 | R73: =O73+P73-Q73 -> 19795500 | S73: =N73-R73 -> 112174500
A74: GEBANG | H74: Dapur + Kantin | I74: 2011 | J74: 0.05 | K74: 98820000 | L74: 0 | M74: 0 | N74: =K74+L74-M74 -> 98820000 | O74: 14823000 | P74: 0 | Q74: 0 | R74: =O74+P74-Q74 -> 14823000 | S74: =N74-R74 -> 83997000
A75: GEBANG | H75: Gudang Barang | I75: 2011 | J75: 0.05 | K75: 89000000 | L75: 0 | M75: 0 | N75: =K75+L75-M75 -> 89000000 | O75: 13350000 | P75: 0 | Q75: 0 | R75: =O75+P75-Q75 -> 13350000 | S75: =N75-R75 -> 75650000
A76: GEBANG | H76: Gudang Trafo | I76: 2014 | J76: 0.05 | K76: 51410000 | L76: 0 | M76: 0 | N76: =K76+L76-M76 -> 51410000 | O76: 7711500 | P76: 0 | Q76: 0 | R76: =O76+P76-Q76 -> 7711500 | S76: =N76-R76 -> 43698500
A77: GEBANG | H77: KM/WC | I77: 2014 | J77: 0.05 | K77: 24700000 | L77: 0 | M77: 0 | N77: =K77+L77-M77 -> 24700000 | O77: 3705000 | P77: 0 | Q77: 0 | R77: =O77+P77-Q77 -> 3705000 | S77: =N77-R77 -> 20995000
A78: GEBANG | H78: Mushola | I78: 2014 | J78: 0.05 | K78: 65020000 | L78: 0 | M78: 0 | N78: =K78+L78-M78 -> 65020000 | O78: 9753000 | P78: 0 | Q78: 0 | R78: =O78+P78-Q78 -> 9753000 | S78: =N78-R78 -> 55267000
A79: GEBANG | F79: Jumlah Bangunan Umum Tambak 1000 | K79: =SUM(K70:K78) -> 1165870000 | L79: =SUM(L70:L78) -> 0 | M79: =SUM(M70:M78) -> 0 | N79: =SUM(N70:N78) -> 1165870000 | O79: =SUM(O70:O78) -> 174880500 | P79: =SUM(P70:P78) -> 0 | Q79: =SUM(Q70:Q78) -> 0 | R79: =SUM(R70:R78) -> 174880500 | S79: =SUM(S70:S78) -> 990989500
A80: GEBANG
A81: GEBANG | F81: 2.2.2 | G81: Bangunan Tambak Blok A-C
A82: GEBANG | H82: Rumah Genset Blok A-C | I82: 2005 | J82: 0.05 | K82: 185540000 | L82: 0 | M82: 0 | N82: =K82+L82-M82 -> 185540000 | O82: 27831000 | P82: 0 | Q82: 0 | R82: =O82+P82-Q82 -> 27831000 | S82: =N82-R82 -> 157709000
A83: GEBANG | H83: Bak Colling Tower | I83: 2005 | J83: 0.05 | K83: 24330000 | L83: 0 | M83: 0 | N83: =K83+L83-M83 -> 24330000 | O83: 3649500 | P83: 0 | Q83: 0 | R83: =O83+P83-Q83 -> 3649500 | S83: =N83-R83 -> 20680500
A84: GEBANG | H84: Mess Proses Blok C + KM/WC | I84: 2005 | J84: 0.05 | K84: 64480000 | L84: 0 | M84: 0 | N84: =K84+L84-M84 -> 64480000 | O84: 9672000 | P84: 0 | Q84: 0 | R84: =O84+P84-Q84 -> 9672000 | S84: =N84-R84 -> 54808000
A85: GEBANG | H85: Mess Assisten + kantin Blok C | I85: 2011 | J85: 0.05 | K85: 149230000 | L85: 0 | M85: 0 | N85: =K85+L85-M85 -> 149230000 | O85: 22384500 | P85: 0 | Q85: 0 | R85: =O85+P85-Q85 -> 22384500 | S85: =N85-R85 -> 126845500
A86: GEBANG | H86: Mess Assisten Blok A | I86: 2011 | J86: 0.05 | K86: 26170000 | L86: 0 | M86: 0 | N86: =K86+L86-M86 -> 26170000 | O86: 3925500 | P86: 0 | Q86: 0 | R86: =O86+P86-Q86 -> 3925500 | S86: =N86-R86 -> 22244500
A87: GEBANG | H87: Mess Feeder (14 Unit) | I87: 2011 | J87: 0.05 | K87: 109140000 | L87: 0 | M87: 0 | N87: =K87+L87-M87 -> 109140000 | O87: 16371000 | P87: 0 | Q87: 0 | R87: =O87+P87-Q87 -> 16371000 | S87: =N87-R87 -> 92769000
A88: GEBANG | H88: Gudang Pakan ( 4 Unit) | I88: 2011 | J88: 0.05 | K88: 48450000 | L88: 0 | M88: 0 | N88: =K88+L88-M88 -> 48450000 | O88: 7267500 | P88: 0 | Q88: 0 | R88: =O88+P88-Q88 -> 7267500 | S88: =N88-R88 -> 41182500
A89: GEBANG | H89: Kantin Blok A | I89: 2011 | J89: 0.05 | K89: 83160000 | L89: 0 | M89: 0 | N89: =K89+L89-M89 -> 83160000 | O89: 12474000 | P89: 0 | Q89: 0 | R89: =O89+P89-Q89 -> 12474000 | S89: =N89-R89 -> 70686000
A90: GEBANG | H90: Rumah Proses | I90: 2011 | J90: 0.05 | K90: 90770000 | L90: 0 | M90: 0 | N90: =K90+L90-M90 -> 90770000 | O90: 13615500 | P90: 0 | Q90: 0 | R90: =O90+P90-Q90 -> 13615500 | S90: =N90-R90 -> 77154500
A91: GEBANG | H91: Mess Karyawan Blok A + WC | I91: 2014 | J91: 0.05 | K91: 88740000 | L91: 0 | M91: 0 | N91: =K91+L91-M91 -> 88740000 | O91: 13311000 | P91: 0 | Q91: 0 | R91: =O91+P91-Q91 -> 13311000 | S91: =N91-R91 -> 75429000
A92: GEBANG | H92: Mess Baru Blok C | I92: 2014 | J92: 0.05 | K92: 553010000 | L92: 0 | M92: 0 | N92: =K92+L92-M92 -> 553010000 | O92: 82951500 | P92: 0 | Q92: 0 | R92: =O92+P92-Q92 -> 82951500 | S92: =N92-R92 -> 470058500
A93: GEBANG | F93: Jumlah Bangunan Tambak Blok A-C | K93: =SUM(K82:K92) -> 1423020000 | L93: =SUM(L82:L92) -> 0 | M93: =SUM(M82:M92) -> 0 | N93: =SUM(N82:N92) -> 1423020000 | O93: =SUM(O82:O92) -> 213453000 | P93: =SUM(P82:P92) -> 0 | Q93: =SUM(Q82:Q92) -> 0 | R93: =SUM(R82:R92) -> 213453000 | S93: =SUM(S82:S92) -> 1209567000
A94: GEBANG
A95: GEBANG | F95: 2.2.3 | G95: Bangunan Tambak Blok D & E
A96: GEBANG | H96: Bak Colling Tower | I96: 2005 | J96: 0.05 | K96: 19950000 | L96: 0 | M96: 0 | N96: =K96+L96-M96 -> 19950000 | O96: 2992500 | P96: 0 | Q96: 0 | R96: =O96+P96-Q96 -> 2992500 | S96: =N96-R96 -> 16957500
A97: GEBANG | H97: Mess Asisten + Tempat Kultur + Wc | I97: 2005 | J97: 0.05 | K97: 84240000 | L97: 0 | M97: 0 | N97: =K97+L97-M97 -> 84240000 | O97: 12636000 | P97: 0 | Q97: 0 | R97: =O97+P97-Q97 -> 12636000 | S97: =N97-R97 -> 71604000
A98: GEBANG | H98: Rumah Genset Blok D & E | I98: 2011 | J98: 0.05 | K98: 150150000 | L98: 0 | M98: 0 | N98: =K98+L98-M98 -> 150150000 | O98: 22522500 | P98: 0 | Q98: 0 | R98: =O98+P98-Q98 -> 22522500 | S98: =N98-R98 -> 127627500
A99: GEBANG | H99: Mess Asisten + Kantin | I99: 2011 | J99: 0.05 | K99: 104895000 | L99: 0 | M99: 0 | N99: =K99+L99-M99 -> 104895000 | O99: 15734250 | P99: 0 | Q99: 0 | R99: =O99+P99-Q99 -> 15734250 | S99: =N99-R99 -> 89160750
A100: GEBANG | H100: Mess Feeder (11 Unit) | I100: 2011 | J100: 0.05 | K100: 40800000 | L100: 0 | M100: 0 | N100: =K100+L100-M100 -> 40800000 | O100: 6120000 | P100: 0 | Q100: 0 | R100: =O100+P100-Q100 -> 6120000 | S100: =N100-R100 -> 34680000
A101: GEBANG | H101: Gudang Pakan ( 2 Unit) | I101: 2011 | J101: 0.05 | K101: 19950000 | L101: 0 | M101: 0 | N101: =K101+L101-M101 -> 19950000 | O101: 2992500 | P101: 0 | Q101: 0 | R101: =O101+P101-Q101 -> 2992500 | S101: =N101-R101 -> 16957500
A102: GEBANG | H102: Mess + Gudang Pakan | I102: 2014 | J102: 0.05 | K102: 46762500 | L102: 0 | M102: 0 | N102: =K102+L102-M102 -> 46762500 | O102: 7014375 | P102: 0 | Q102: 0 | R102: =O102+P102-Q102 -> 7014375 | S102: =N102-R102 -> 39748125
A103: GEBANG | F103: Jumlah Bangunan Tambak Blok D & E | K103: =SUM(K96:K102) -> 466747500 | L103: =SUM(L96:L102) -> 0 | M103: =SUM(M96:M102) -> 0 | N103: =SUM(N96:N102) -> 466747500 | O103: =SUM(O96:O102) -> 70012125 | P103: =SUM(P96:P102) -> 0 | Q103: =SUM(Q96:Q102) -> 0 | R103: =SUM(R96:R102) -> 70012125 | S103: =SUM(S96:S102) -> 396735375
A104: GEBANG
A105: GEBANG | F105: 2.2.4 | G105: Bangunan Tambak Blok F-H
A106: GEBANG | H106: Bak Colling Tower | I106: 2005 | J106: 0.05 | K106: 14250000 | L106: 0 | M106: 0 | N106: =K106+L106-M106 -> 14250000 | O106: 2137500 | P106: 0 | Q106: 0 | R106: =O106+P106-Q106 -> 2137500 | S106: =N106-R106 -> 12112500
A107: GEBANG | H107: Rumah Genset Blok F-H | I107: 2011 | J107: 0.05 | K107: 115500000 | L107: 0 | M107: 0 | N107: =K107+L107-M107 -> 115500000 | O107: 17325000 | P107: 0 | Q107: 0 | R107: =O107+P107-Q107 -> 17325000 | S107: =N107-R107 -> 98175000
A108: GEBANG | H108: Mess Asisten + Kantin | I108: 2011 | J108: 0.05 | K108: 211680000 | L108: 0 | M108: 0 | N108: =K108+L108-M108 -> 211680000 | O108: 31752000 | P108: 0 | Q108: 0 | R108: =O108+P108-Q108 -> 31752000 | S108: =N108-R108 -> 179928000
A109: GEBANG | H109: Mess Feeder ( 14 Unit) | I109: 2011 | J109: 0.05 | K109: 42840000 | L109: 0 | M109: 0 | N109: =K109+L109-M109 -> 42840000 | O109: 6426000 | P109: 0 | Q109: 0 | R109: =O109+P109-Q109 -> 6426000 | S109: =N109-R109 -> 36414000
...

Sheet Summary
B1: Aet Tambak Ketapang | F1: Aset Lainnya | J1: Total Aset yang akan di takeout
A2: 1 | B2: Tanah | C2: ='1. Tanah'!D16 -> 0 | E2: 1 | F2: Tanah | G2: 0
A3: 2 | B3: Bangunan | C3: =SUM('2. Bangunan'!E82:E106) -> 0 | E3: 2 | F3: Bangunan | G3: ='2. Bangunan'!E10+'2. Bangunan'!E44+'2. Bangunan'!E55+'2. Bangunan'!E63+'2. Bangunan'!E73+'2. Bangunan'!E75 -> 0 | J3: Aet Tambak Ketapang | K3: =C11 -> 0
A4: 3 | B4: Sumur Bor | C4: =SUM('3. Sumur Bor'!E25:E36) -> 0 | E4: 3 | F4: Sumur Bor | G4: =SUM('3. Sumur Bor'!E8:E11) -> 0 | J4: Aset Lainnya | K4: =G11 -> 0
A5: 4 | B5: Sarana & Prasarana | C5: =SUM('4. Sarana & Prasarana'!E18:E27) -> 0 | E5: 4 | F5: Sarana & Prasarana | G5: =SUM('4. Sarana & Prasarana'!E13:E14)+'4. Sarana & Prasarana'!E16 -> 0 | K5: =SUM(K3:K4) -> 0
A6: 5 | B6: Mesin | C6: =SUM('5. Mesin'!E240:E308) -> 0 | E6: 5 | F6: Mesin | G6: ='5. Mesin'!E80+'5. Mesin'!E87+'5. Mesin'!E88 -> 0
A7: 6 | B7: Instalasi Elektrik | C7: =SUM('6. Instalasi Elektrik'!E13:E40) -> 0 | E7: 6 | F7: Instalasi Elektrik | G7: 0
A8: 7 | B8: Kendaraan | C8: =SUM('7. Kendaraan'!E51:E62) -> 0 | E8: 7 | F8: Kendaraan | G8: ='7. Kendaraan'!E46 -> 0 | J8: Hutang Pak Usman | K8: 2.0363316e+10
A9: 8 | B9: Perlengkapan | C9: 0 | E9: 8 | F9: Perlengkapan | G9: ='8 Peralatan & Perlengkapan'!E87+'8 Peralatan & Perlengkapan'!E89+'8 Peralatan & Perlengkapan'!E95+'8 Peralatan & Perlengkapan'!E102+'8 Peralatan & Perlengkapan'!E104+'8 Peralatan & Perlengkapan'!E108+'8 Peralatan & Perlengkapan'!E109+'8 Peralatan & Perlengkapan'!E111 -> 0 | J9: Surplus RAT | K9: 56060619982
A10: 9 | B10: Infrastruktur | C10: =SUM('9. Infrastruktur'!E37:E44)-'9. Infrastruktur'!E38 -> 0 | E10: 9 | F10: Infrastruktur | G10: ='9. Infrastruktur'!E11+'9. Infrastruktur'!E32+'9. Infrastruktur'!E34+'9. Infrastruktur'!E35 -> 0 | K10: =K5-K8-K9 -> -7.6423936e+10
C11: =SUM(C2:C10) -> 0 | G11: =SUM(G2:G10) -> 0
J12: Penyusutan Peralatan Tambak ,Biaya
J13: Penyusutan Peralatan Produksi, Biaya
B14: Akmulasi Penyusutan Tambak Ketapang 2020 | F14: Akumulasi Penyusutan Aset Lainnya 2020 | J14: Penyusutan Sarana & Prasarana, Biaya
A15: 1 | B15: Bangunan | C15: =SUM('2. Bangunan'!AC82:AC106) -> 0 | E15: 1 | F15: Bangunan | G15: ='2. Bangunan'!AC10+'2. Bangunan'!AC44+'2. Bangunan'!AC55+'2. Bangunan'!AC63+'2. Bangunan'!AC73+'2. Bangunan'!AC75 -> 0 | J15: Penyusutan Bangunan, Biaya
A16: =A15+1 -> 2 | B16: Sumur Bor | C16: =SUM('3. Sumur Bor'!AC25:AC36) -> 0 | E16: =E15+1 -> 2 | F16: Sumur Bor | G16: ='3. Sumur Bor'!AC8+'3. Sumur Bor'!AC9+'3. Sumur Bor'!AC10+'3. Sumur Bor'!AC11 -> 0 | J16: Penyusutan Electricity Instalasi, Biaya
A17: =A16+1 -> 3 | B17: Sarana & Prasarana | C17: =SUM('4. Sarana & Prasarana'!AC18:AC27) -> 0 | E17: =E16+1 -> 3 | F17: Sarana & Prasarana | G17: =SUM('4. Sarana & Prasarana'!AC13+'4. Sarana & Prasarana'!AC14+'4. Sarana & Prasarana'!AC16) -> 0 | J17: Penyusutan Infrastruktur, Biaya
A18: =A17+1 -> 4 | B18: Mesin | C18: =SUM('5. Mesin'!AB240:AB308) -> 0 | E18: =E17+1 -> 4 | F18: Mesin | G18: =SUM('5. Mesin'!AB80+'5. Mesin'!AB87+'5. Mesin'!AB88) -> 0 | J18: Penyusutan Kendaraan, Biaya
A19: =A18+1 -> 5 | B19: Instalasi Elektrik | C19: =SUM('6. Instalasi Elektrik'!AB13:AB40) -> 0 | E19: =E18+1 -> 5 | F19: Kendaraan | G19: =SUM('7. Kendaraan'!AB46) -> 0 | J19: Penyusutan Mesin-Mesin, Biaya
A20: =A19+1 -> 6 | B20: Kendaraan | C20: =SUM('7. Kendaraan'!AB51:AB62) -> 0 | E20: =E19+1 -> 6 | F20: Perlengkapan | G20: =SUM('8 Peralatan & Perlengkapan'!AB87+'8 Peralatan & Perlengkapan'!AB89+'8 Peralatan & Perlengkapan'!AB95+'8 Peralatan & Perlengkapan'!AB102+'8 Peralatan & Perlengkapan'!AB104+'8 Peralatan & Perlengkapan'!AB108+'8 Peralatan & Perlengkapan'!AB109+'8 Peralatan & Perlengkapan'!AB111) -> 0 | J20: Penyusutan Peralatan Kantor, Biaya
A21: =A20+1 -> 7 | B21: Infrastruktur | C21: =SUM('9. Infrastruktur'!AB37:AB44)-'9. Infrastruktur'!AB38 -> 0 | E21: =E20+1 -> 7 | F21: Infrastruktur | G21: =SUM('9. Infrastruktur'!AB11+'9. Infrastruktur'!AB32+'9. Infrastruktur'!AB34+'9. Infrastruktur'!AB35) -> 0 | J21: Penyusutan Sumur Bor, Biaya
B24: Beban Penyusutan Tambak Ketapang 2020 | F24: Beban Penyusutam Aset Lainnya 2020
A25: 1 | B25: Bangunan | C25: =SUM('2. Bangunan'!AB82:AB106) -> 0 | E25: 1 | F25: Bangunan | G25: ='2. Bangunan'!AB10+'2. Bangunan'!AB44+'2. Bangunan'!AB55+'2. Bangunan'!AB63+'2. Bangunan'!AB73+'2. Bangunan'!AB75 -> 0
A26: =A25+1 -> 2 | B26: Sumur Bor | C26: =SUM('3. Sumur Bor'!AB25:AB36) -> 0 | E26: =E25+1 -> 2 | F26: Sumur Bor | G26: ='3. Sumur Bor'!AB8+'3. Sumur Bor'!AB9+'3. Sumur Bor'!AB10+'3. Sumur Bor'!AB11 -> 0
A27: =A26+1 -> 3 | B27: Sarana & Prasarana | C27: =SUM('4. Sarana & Prasarana'!AB18:AB27) -> 0 | E27: =E26+1 -> 3 | F27: Sarana & Prasarana | G27: ='4. Sarana & Prasarana'!AB13+'4. Sarana & Prasarana'!AB14+'4. Sarana & Prasarana'!AB16 -> 0
A28: =A27+1 -> 4 | B28: Mesin | C28: =SUM('5. Mesin'!AA240:AA308) -> 0 | E28: =E27+1 -> 4 | F28: Mesin | G28: ='5. Mesin'!AA80+'5. Mesin'!AA87+'5. Mesin'!AA88 -> 0
A29: =A28+1 -> 5 | B29: Instalasi Elektrik | C29: =SUM('6. Instalasi Elektrik'!AA13:AA40) -> 0 | E29: =E28+1 -> 5 | F29: Kendaraan | G29: ='7. Kendaraan'!AA46 -> 0
A30: =A29+1 -> 6 | B30: Kendaraan | C30: =SUM('7. Kendaraan'!AA51:AA62) -> 0 | E30: =E29+1 -> 6 | F30: Perlengkapan | G30: ='8 Peralatan & Perlengkapan'!AA87+'8 Peralatan & Perlengkapan'!AA89+'8 Peralatan & Perlengkapan'!AA95+'8 Peralatan & Perlengkapan'!AA102+'8 Peralatan & Perlengkapan'!AA104+'8 Peralatan & Perlengkapan'!AA108+'8 Peralatan & Perlengkapan'!AA109+'8 Peralatan & Perlengkapan'!AA111 -> 0
A31: =A30+1 -> 7 | B31: Infrastruktur | C31: =SUM('9. Infrastruktur'!AA37:AA44)-'9. Infrastruktur'!AA38 -> 0 | E31: =E30+1 -> 7 | F31: Infrastruktur | G31: ='9. Infrastruktur'!AA11+'9. Infrastruktur'!AA32+'9. Infrastruktur'!AA34+'9. Infrastruktur'!AA35 -> 0

Sheet AT
D1: PT. INDOKOM SAMUDERA PERSADA
D2: DIVISI COLD STORAGE 1
D3: DAFTAR ASET TETAP DAN PENYUSUTAN | Q3: Bak mobil Budidaya
D4: DESEMBER 2022
B5: 1 | C5: 1 | K5: 1.4112772e+11 | L5: 7.4137718e+09 | M5: 15636001272 | N5: 1.3291008e+11 | O5: 4.2713813e+10 | P5: 1.0115152e+10 | Q5: 2.5693171e+09 | R5: 5.0259648e+10 | S5: Dalam Rupiah (Rp)
D6: No | F6: Nama Asset | I6: Tahun | J6: % | K6: Harga Perolehan | L6: Mutasi | N6: Harga Perolehan | O6: Akm. Penyusutan | P6: Penyusutan Desember 2022 | R6: Akm. Penyusutan | S6: Nilai Buku
I8: Perolehan | K8: Per | N8: Per | O8: s/d | R8: s/d | S8: Per
K9: 44561 | L9: Penambahan | M9: Pengurangan | N9: 31 Desember 2022 | O9: 44561 | P9: Penambahan | Q9: Pengurangan | R9: 31 Desember 2022 | S9: 31 Desember 2022
A11: COLD STORAGE | B11: TANAH | C11: TANAH | D11: 1 | E11: TANAH
A12: COLD STORAGE | E12: 1.1 | F12: Tanah Cold Storage
A13: COLD STORAGE | H13: Tanah Divisi Cold Storage 1 | I13: 2002 | K13: 655809273 | L13: 0 | N13: =K13+L13-M13 -> 655809273 | O13: 0 | P13: 0 | Q13: 0 | R13: =O13+P13-Q13 -> 0 | S13: =N13-R13 -> 655809273
A14: COLD STORAGE | H14: Tanah Divisi Cold Storage 2 | I14: 2002 | K14: 200000000 | L14: 0 | N14: =K14+L14-M14 -> 200000000 | O14: 0 | P14: 0 | Q14: 0 | R14: =O14+P14-Q14 -> 0 | S14: =N14-R14 -> 200000000
H15: Tanah SHM NO.776,777,778 | I15: 2002 | K15: 226850626 | L15: 0 | N15: =K15+L15-M15 -> 226850626 | O15: 0 | P15: 0 | Q15: 0 | R15: =O15+P15-Q15 -> 0 | S15: =N15-R15 -> 226850626
A16: COLD STORAGE | E16: Subtotal Tanah Cold Storage | K16: =SUM(K13:K15) -> 1082659899 | L16: =SUM(L13:L15) -> 0 | M16: =SUM(M13:M15) -> 0 | N16: =SUM(N13:N15) -> 1082659899 | O16: =SUM(O13:O15) -> 0 | P16: =SUM(P13:P15) -> 0 | Q16: =SUM(Q13:Q15) -> 0 | R16: =SUM(R13:R15) -> 0 | S16: =SUM(S13:S15) -> 1082659899
A18: GEBANG | E18: 1.2 | F18: Tanah Gebang
A19: GEBANG | H19: Tanah Divisi Gebang | I19: 2005 | K19: 2538567500 | L19: 0 | M19: 0 | N19: =K19+L19-M19 -> 2538567500 | O19: 0 | P19: 0 | Q19: 0 | R19: =O19+P19-Q19 -> 0 | S19: =N19-R19 -> 2538567500
A20: GEBANG | E20: Subtotal Tanah Gebang | K20: =SUM(K19) -> 2538567500 | L20: =SUM(L19) -> 0 | M20: =SUM(M19) -> 0 | N20: =SUM(N19) -> 2538567500 | O20: =SUM(O19) -> 0 | P20: =SUM(P19) -> 0 | Q20: =SUM(Q19) -> 0 | R20: =SUM(R19) -> 0 | S20: =SUM(S19) -> 2538567500
A22: HOLDING | E22: 1.3 | F22: Tanah Holding
A23: HOLDING | H23: Tanah Divisi Holding | I23: 2008 | K23: 1533972000 | L23: 0 | M23: 0 | N23: =K23+L23-M23 -> 1533972000 | O23: 0 | P23: 0 | Q23: 0 | R23: =O23+P23-Q23 -> 0 | S23: =N23-R23 -> 1533972000
A24: HOLDING | H24: Tanah Divisi Maringgai | I24: 2002 | K24: 202373350 | L24: 0 | M24: 0 | N24: =K24+L24-M24 -> 202373350 | O24: 0 | P24: 0 | Q24: 0 | R24: =O24+P24-Q24 -> 0 | S24: =N24-R24 -> 202373350
A25: HOLDING | E25: Subtotal Tanah Holding | K25: =SUM(K23:K24) -> 1736345350 | L25: =SUM(L23:L24) -> 0 | M25: =SUM(M23:M24) -> 0 | N25: =SUM(N23:N24) -> 1736345350 | O25: =SUM(O23:O24) -> 0 | P25: =SUM(P23:P24) -> 0 | Q25: =SUM(Q23:Q24) -> 0 | R25: =SUM(R23:R24) -> 0 | S25: =SUM(S23:S24) -> 1736345350
A27: KETAPANG | E27: 1.4 | F27: Tanah Ketapang
A28: KETAPANG | H28: Tanah Divisi Ketapang | K28: 3436245000 | L28: 0 | M28: 0 | N28: =K28+L28-M28 -> 3436245000 | O28: 0 | P28: 0 | Q28: 0 | R28: =O28+P28-Q28 -> 0 | S28: =N28-R28 -> 3436245000
A29: KETAPANG | E29: Subtotal Tanah Ketapang | K29: =SUM(K28) -> 3436245000 | L29: =SUM(L28) -> 0 | M29: =SUM(M28) -> 0 | N29: =SUM(N28) -> 3436245000 | O29: =SUM(O28) -> 0 | P29: =SUM(P28) -> 0 | Q29: =SUM(Q28) -> 0 | R29: =SUM(R28) -> 0 | S29: =SUM(S28) -> 3436245000
A31: PAKAN | E31: 1.4 | F31: Tanah Pakan
A32: PAKAN | H32: Tanah Divisi Pakan | I32: 2006 | K32: 0 | L32: 0 | N32: =K32+L32-M32 -> 0 | O32: 0 | P32: 0 | Q32: 0 | R32: =O32+P32-Q32 -> 0 | S32: =N32-R32 -> 0
A33: PAKAN | E33: Subtotal Tanah Pakan | K33: =SUM(K32) -> 0 | L33: =SUM(L32) -> 0 | M33: =SUM(M32) -> 0 | N33: =SUM(N32) -> 0 | O33: =SUM(O32) -> 0 | P33: =SUM(P32) -> 0 | Q33: =SUM(Q32) -> 0 | R33: =SUM(R32) -> 0 | S33: =SUM(S32) -> 0
D35: TOTAL TANAH | K35: =K16+K20+K25+K29 -> 8793817749 | L35: =L16+L20+L25+L29 -> 0 | M35: =M16+M20+M25+M29 -> 0 | N35: =N16+N20+N25+N29 -> 8793817749 | O35: =O16+O20+O25+O29 -> 0 | P35: =P16+P20+P25+P29 -> 0 | Q35: =Q16+Q20+Q25+Q29 -> 0 | R35: =R16+R20+R25+R29 -> 0 | S35: =S16+S20+S25+S29 -> 8793817749
A37: COLD STORAGE | B37: BANGUNAN | C37: BANGUNAN | D37: 2 | E37: BANGUNAN
A38: COLD STORAGE | E38: 2.1 | F38: Bangunan Cold Storage
A39: COLD STORAGE | F39: 2.1.1 | G39: DIVISI ISP 1
A40: COLD STORAGE | H40: Bangunan ISP 1 | I40: 2005 | J40: 0.05 | K40: 5564855579 | L40: 0 | N40: =K40+L40-M40 -> 5564855579 | O40: 1.4115468e+09 | P40: =N40*J40 -> 2.7824278e+08 | R40: =O40+P40-Q40 -> 1.6897896e+09 | S40: =N40-R40 -> 3.875066e+09
A41: COLD STORAGE | H41: Bangunan Pos Satpam | I41: 2005 | J41: 0.05 | K41: 39450000 | L41: 0 | M41: 0 | N41: =K41+L41-M41 -> 39450000 | O41: 11835000 | P41: =N41*J41 -> 1972500 | R41: =O41+P41-Q41 -> 13807500 | S41: =N41-R41 -> 25642500
A42: COLD STORAGE | H42: Bangunan Genset | I42: 2005 | J42: 0.05 | K42: 742420000 | L42: 0 | M42: 0 | N42: =K42+L42-M42 -> 742420000 | O42: 2.22726e+08 | P42: =N42*J42 -> 37121000 | R42: =O42+P42-Q42 -> 2.59847e+08 | S42: =N42-R42 -> 4.82573e+08
A43: COLD STORAGE | H43: KM/WC | I43: 2005 | J43: 0.05 | K43: 8100000 | L43: 0 | M43: 0 | N43: =K43+L43-M43 -> 8100000 | O43: 2430000 | P43: =N43*J43 -> 405000 | R43: =O43+P43-Q43 -> 2835000 | S43: =N43-R43 -> 5265000
A44: COLD STORAGE | H44: Kantor 1 | I44: 2006 | J44: 0.05 | K44: 203210000 | L44: 0 | M44: 0 | N44: =K44+L44-M44 -> 203210000 | O44: 52495916 | P44: =N44*J44 -> 10160500 | R44: =O44+P44-Q44 -> 62656416 | S44: =N44-R44 -> 1.4055358e+08
A45: COLD STORAGE | H45: Kantin & KM/WC | I45: 2010 | J45: 0.05 | K45: 262080000 | L45: 0 | M45: 0 | N45: =K45+L45-M45 -> 262080000 | O45: 78624000 | P45: =N45*J45 -> 13104000 | R45: =O45+P45-Q45 -> 91728000 | S45: =N45-R45 -> 170352000
A46: COLD STORAGE | H46: Mushola | I46: 2010 | J46: 0.05 | K46: 194080000 | L46: 0 | M46: 0 | N46: =K46+L46-M46 -> 194080000 | O46: 58224000 | P46: =N46*J46 -> 9704000 | R46: =O46+P46-Q46 -> 67928000 | S46: =N46-R46 -> 1.26152e+08
A47: COLD STORAGE | H47: Cafetaria | I47: 2010 | J47: 0.05 | K47: 313090000 | L47: 0 | M47: 0 | N47: =K47+L47-M47 -> 313090000 | O47: 93927000 | P47: =N47*J47 -> 15654500 | R47: =O47+P47-Q47 -> 1.095815e+08 | S47: =N47-R47 -> 2.035085e+08
A48: COLD STORAGE | H48: Panggung Ekspor | I48: 2010 | J48: 0.05 | K48: 23340000 | L48: 0 | M48: 0 | N48: =K48+L48-M48 -> 23340000 | O48: 6029500 | P48: =N48*J48 -> 1167000 | R48: =O48+P48-Q48 -> 7196500 | S48: =N48-R48 -> 16143500
A49: COLD STORAGE | H49: Bangunan Receiver | I49: 2010 | J49: 0.05 | K49: 66130000 | L49: 0 | M49: 0 | N49: =K49+L49-M49 -> 66130000 | O49: 17083583 | P49: =N49*J49 -> 3306500 | R49: =O49+P49-Q49 -> 20390083 | S49: =N49-R49 -> 45739917
A50: COLD STORAGE | H50: Kantor 3 (3lt) | I50: 2010 | J50: 0.05 | K50: 753420000 | L50: 0 | M50: 0 | N50: =K50+L50-M50 -> 753420000 | O50: 226026000 | P50: =N50*J50 -> 37671000 | R50: =O50+P50-Q50 -> 263697000 | S50: =N50-R50 -> 489723000
A51: COLD STORAGE | H51: Parkir Terbuka | I51: 2010 | J51: 0.05 | K51: 73630000 | L51: 0 | M51: 0 | N51: =K51+L51-M51 -> 73630000 | O51: 22089000 | P51: =N51*J51 -> 3681500 | R51: =O51+P51-Q51 -> 25770500 | S51: =N51-R51 -> 47859500
A52: COLD STORAGE | H52: Gudang Trafo (2 unit) | I52: 2014 | J52: 0.05 | K52: 50330000 | L52: 0 | M52: 0 | N52: =K52+L52-M52 -> 50330000 | O52: 15099000 | P52: =N52*J52 -> 2516500 | R52: =O52+P52-Q52 -> 17615500 | S52: =N52-R52 -> 32714500
A53: COLD STORAGE | H53: Bangunan ATM | I53: 2015 | J53: 0.05 | K53: 9720000 | L53: 0 | M53: 0 | N53: =K53+L53-M53 -> 9720000 | O53: 2916000 | P53: =N53*J53 -> 486000 | R53: =O53+P53-Q53 -> 3402000 | S53: =N53-R53 -> 6318000
H54: Bangunan Baru | I54: 43708 | J54: 0.05 | K54: 3.9492779e+09 | L54: 0 | M54: 0 | N54: =K54+L54-M54 -> 3.9492779e+09 | O54: 4.6074908e+08 | P54: =N54*J54 -> 1.9746389e+08 | R54: =O54+P54-Q54 -> 6.5821298e+08 | S54: =N54-R54 -> 3.2910649e+09
H55: Bangunan Renovasi | I55: 44561 | J55: 0.05 | K55: 8.9267952e+09 | L55: 0 | M55: 0 | N55: =K55+L55-M55 -> 8.9267952e+09 | O55: 74389960 | P55: =N55*J55 -> 4.4633976e+08 | R55: =O55+P55-Q55 -> 5.2072972e+08 | S55: =N55-R55 -> 8.4060655e+09
A56: COLD STORAGE | F56: Jumlah Bangunan Div.ISP 1 | K56: =SUM(K40:K55) -> 2.1179929e+10 | L56: =SUM(L40:L55) -> 0 | M56: =SUM(M40:M55) -> 0 | N56: =SUM(N40:N55) -> 2.1179929e+10 | O56: =SUM(O40:O55) -> 2.7561908e+09 | P56: =SUM(P40:P55) -> 1.0589964e+09 | Q56: =SUM(Q40:Q55) -> 0 | R56: =SUM(R40:R55) -> 3.8151873e+09 | S56: =SUM(S40:S55) -> 1.7364741e+10
A57: COLD STORAGE | F57: 2.1.2 | G57: DIVISI ISP 2
A58: COLD STORAGE | H58: Mess 2 | I58: 2005 | J58: 0.05 | K58: 0 | L58: 0 | N58: 0 | O58: 0 | P58: 0 | R58: 0 | S58: 0
A59: COLD STORAGE | H59: Kantor 2 | I59: 2010 | J59: 0.05 | K59: 128910000 | L59: 0 | M59: 0 | N59: =K59+L59-M59 -> 128910000 | O59: 38673000 | P59: =N59*J59 -> 6445500 | R59: =O59+P59-Q59 -> 45118500 | S59: =N59-R59 -> 83791500
A60: COLD STORAGE | H60: Bangunan ISP 2 | I60: 2011 | J60: 0.05 | K60: 9.4432849e+09 | L60: 0 | M60: 0 | N60: =K60+L60-M60 -> 9.4432849e+09 | O60: 2.638797e+09 | P60: =N60*J60 -> 4.7216424e+08 | R60: =O60+P60-Q60 -> 3.1109612e+09 | S60: =N60-R60 -> 6.3323237e+09
A61: COLD STORAGE | F61: Jumlah Bangunan Div.ISP 2 | K61: =SUM(K59:K60) -> 9.5721949e+09 | L61: =SUM(L59:L60) -> 0 | M61: =SUM(M59:M60) -> 0 | N61: =SUM(N59:N60) -> 9.5721949e+09 | O61: =SUM(O59:O60) -> 2.67747e+09 | P61: =SUM(P59:P60) -> 4.7860974e+08 | Q61: =SUM(Q59:Q60) -> 0 | R61: =SUM(R59:R60) -> 3.1560797e+09 | S61: =SUM(S59:S60) -> 6.4161152e+09
A62: COLD STORAGE | F62: 2.1.3 | G62: PABRIK ROTI
A63: COLD STORAGE | H63: Kantor | I63: 2012 | J63: 0.05 | K63: 0 | L63: 0 | N63: =K63+L63-M63 -> 0 | O63: 0 | R63: =O63+P63-Q63 -> 0 | S63: =N63-R63 -> 0
A64: COLD STORAGE | H64: Gudang Roti | I64: 2012 | J64: 0.05 | K64: 0 | L64: 0 | N64: =K64+L64-M64 -> 0 | O64: 0 | R64: =O64+P64-Q64 -> 0 | S64: =N64-R64 -> 0
A65: COLD STORAGE | F65: Jumlah Bangunan Div. Pabrik Roti | K65: =SUM(K63:K64) -> 0 | L65: =SUM(L63:L64) -> 0 | M65: =SUM(M63:M64) -> 0 | N65: =SUM(N63:N64) -> 0 | O65: =SUM(O63:O64) -> 0 | P65: =SUM(P63:P64) -> 0 | Q65: =SUM(Q63:Q64) -> 0 | R65: =SUM(R63:R64) -> 0 | S65: =SUM(S63:S64) -> 0
A66: COLD STORAGE | E66: Subtotal Bangunan Cold Storage | K66: =K56+K61+K65 -> 3.0752124e+10 | L66: =L56+L61+L65 -> 0 | M66: =M56+M61+M65 -> 0 | N66: =N56+N61+N65 -> 3.0752124e+10 | O66: =O56+O61+O65 -> 5.4336608e+09 | P66: =P56+P61+P65 -> 1.5376062e+09 | Q66: =Q56+Q61+Q65 -> 0 | R66: =R56+R61+R65 -> 6.971267e+09 | S66: =S56+S61+S65 -> 2.3780857e+10
A68: GEBANG | E68: 2.2 | F68: Bangunan Gebang
A69: GEBANG | F69: 2.2.1 | G69: Bangunan Umum Tambak 1000
A70: GEBANG | H70: Pos Satpam | I70: 2005 | J70: 0.05 | K70: 10960000 | L70: 0 | M70: 0 | N70: =K70+L70-M70 -> 10960000 | O70: 1644000 | P70: 0 | Q70: 0 | R70: =O70+P70-Q70 -> 1644000 | S70: =N70-R70 -> 9316000
A71: GEBANG | H71: Kantor, Mess, Logistik & Lab | I71: 2005 | J71: 0.05 | K71: 596230000 | L71: 0 | M71: 0 | N71: =K71+L71-M71 -> 596230000 | O71: 89434500 | P71: 0 | Q71: 0 | R71: =O71+P71-Q71 -> 89434500 | S71: =N71-R71 -> 506795500
A72: GEBANG | H72: Mess Umum | I72: 2011 | J72: 0.05 | K72: 97760000 | L72: 0 | M72: 0 | N72: =K72+L72-M72 -> 97760000 | O72: 14664000 | P72: 0 | Q72: 0 | R72: =O72+P72-Q72 -> 14664000 | S72: =N72-R72 -> 83096000
A73: GEBANG | H73: Bengkel +Mess | I73: 2011 | J73: 0.05 | K73: 131970000 | L73: 0 | M73: 0 | N73: =K73+L73-M73 -> 131970000 | O73: 19795500 | P73: 0 | Q73: 0 | R73: =O73+P73-Q73 -> 19795500 | S73: =N73-R73 -> 112174500
A74: GEBANG | H74: Dapur + Kantin | I74: 2011 | J74: 0.05 | K74: 98820000 | L74: 0 | M74: 0 | N74: =K74+L74-M74 -> 98820000 | O74: 14823000 | P74: 0 | Q74: 0 | R74: =O74+P74-Q74 -> 14823000 | S74: =N74-R74 -> 83997000
A75: GEBANG | H75: Gudang Barang | I75: 2011 | J75: 0.05 | K75: 89000000 | L75: 0 | M75: 0 | N75: =K75+L75-M75 -> 89000000 | O75: 13350000 | P75: 0 | Q75: 0 | R75: =O75+P75-Q75 -> 13350000 | S75: =N75-R75 -> 75650000
A76: GEBANG | H76: Gudang Trafo | I76: 2014 | J76: 0.05 | K76: 51410000 | L76: 0 | M76: 0 | N76: =K76+L76-M76 -> 51410000 | O76: 7711500 | P76: 0 | Q76: 0 | R76: =O76+P76-Q76 -> 7711500 | S76: =N76-R76 -> 43698500
A77: GEBANG | H77: KM/WC | I77: 2014 | J77: 0.05 | K77: 24700000 | L77: 0 | M77: 0 | N77: =K77+L77-M77 -> 24700000 | O77: 3705000 | P77: 0 | Q77: 0 | R77: =O77+P77-Q77 -> 3705000 | S77: =N77-R77 -> 20995000
A78: GEBANG | H78: Mushola | I78: 2014 | J78: 0.05 | K78: 65020000 | L78: 0 | M78: 0 | N78: =K78+L78-M78 -> 65020000 | O78: 9753000 | P78: 0 | Q78: 0 | R78: =O78+P78-Q78 -> 9753000 | S78: =N78-R78 -> 55267000
A79: GEBANG | F79: Jumlah Bangunan Umum Tambak 1000 | K79: =SUM(K70:K78) -> 1165870000 | L79: =SUM(L70:L78) -> 0 | M79: =SUM(M70:M78) -> 0 | N79: =SUM(N70:N78) -> 1165870000 | O79: =SUM(O70:O78) -> 174880500 | P79: =SUM(P70:P78) -> 0 | Q79: =SUM(Q70:Q78) -> 0 | R79: =SUM(R70:R78) -> 174880500 | S79: =SUM(S70:S78) -> 990989500
A80: GEBANG
A81: GEBANG | F81: 2.2.2 | G81: Bangunan Tambak Blok A-C
A82: GEBANG | H82: Rumah Genset Blok A-C | I82: 2005 | J82: 0.05 | K82: 185540000 | L82: 0 | M82: 0 | N82: =K82+L82-M82 -> 185540000 | O82: 27831000 | P82: 0 | Q82: 0 | R82: =O82+P82-Q82 -> 27831000 | S82: =N82-R82 -> 157709000
A83: GEBANG | H83: Bak Colling Tower | I83: 2005 | J83: 0.05 | K83: 24330000 | L83: 0 | M83: 0 | N83: =K83+L83-M83 -> 24330000 | O83: 3649500 | P83: 0 | Q83: 0 | R83: =O83+P83-Q83 -> 3649500 | S83: =N83-R83 -> 20680500
A84: GEBANG | H84: Mess Proses Blok C + KM/WC | I84: 2005 | J84: 0.05 | K84: 64480000 | L84: 0 | M84: 0 | N84: =K84+L84-M84 -> 64480000 | O84: 9672000 | P84: 0 | Q84: 0 | R84: =O84+P84-Q84 -> 9672000 | S84: =N84-R84 -> 54808000
A85: GEBANG | H85: Mess Assisten + kantin Blok C | I85: 2011 | J85: 0.05 | K85: 149230000 | L85: 0 | M85: 0 | N85: =K85+L85-M85 -> 149230000 | O85: 22384500 | P85: 0 | Q85: 0 | R85: =O85+P85-Q85 -> 22384500 | S85: =N85-R85 -> 126845500
A86: GEBANG | H86: Mess Assisten Blok A | I86: 2011 | J86: 0.05 | K86: 26170000 | L86: 0 | M86: 0 | N86: =K86+L86-M86 -> 26170000 | O86: 3925500 | P86: 0 | Q86: 0 | R86: =O86+P86-Q86 -> 3925500 | S86: =N86-R86 -> 22244500
A87: GEBANG | H87: Mess Feeder (14 Unit) | I87: 2011 | J87: 0.05 | K87: 109140000 | L87: 0 | M87: 0 | N87: =K87+L87-M87 -> 109140000 | O87: 16371000 | P87: 0 | Q87: 0 | R87: =O87+P87-Q87 -> 16371000 | S87: =N87-R87 -> 92769000
A88: GEBANG | H88: Gudang Pakan ( 4 Unit) | I88: 2011 | J88: 0.05 | K88: 48450000 | L88: 0 | M88: 0 | N88: =K88+L88-M88 -> 48450000 | O88: 7267500 | P88: 0 | Q88: 0 | R88: =O88+P88-Q88 -> 7267500 | S88: =N88-R88 -> 41182500
A89: GEBANG | H89: Kantin Blok A | I89: 2011 | J89: 0.05 | K89: 83160000 | L89: 0 | M89: 0 | N89: =K89+L89-M89 -> 83160000 | O89: 12474000 | P89: 0 | Q89: 0 | R89: =O89+P89-Q89 -> 12474000 | S89: =N89-R89 -> 70686000
A90: GEBANG | H90: Rumah Proses | I90: 2011 | J90: 0.05 | K90: 90770000 | L90: 0 | M90: 0 | N90: =K90+L90-M90 -> 90770000 | O90: 13615500 | P90: 0 | Q90: 0 | R90: =O90+P90-Q90 -> 13615500 | S90: =N90-R90 -> 77154500
A91: GEBANG | H91: Mess Karyawan Blok A + WC | I91: 2014 | J91: 0.05 | K91: 88740000 | L91: 0 | M91: 0 | N91: =K91+L91-M91 -> 88740000 | O91: 13311000 | P91: 0 | Q91: 0 | R91: =O91+P91-Q91 -> 13311000 | S91: =N91-R91 -> 75429000
A92: GEBANG | H92: Mess Baru Blok C | I92: 2014 | J92: 0.05 | K92: 553010000 | L92: 0 | M92: 0 | N92: =K92+L92-M92 -> 553010000 | O92: 82951500 | P92: 0 | Q92: 0 | R92: =O92+P92-Q92 -> 82951500 | S92: =N92-R92 -> 470058500
A93: GEBANG | F93: Jumlah Bangunan Tambak Blok A-C | K93: =SUM(K82:K92) -> 1423020000 | L93: =SUM(L82:L92) -> 0 | M93: =SUM(M82:M92) -> 0 | N93: =SUM(N82:N92) -> 1423020000 | O93: =SUM(O82:O92) -> 213453000 | P93: =SUM(P82:P92) -> 0 | Q93: =SUM(Q82:Q92) -> 0 | R93: =SUM(R82:R92) -> 213453000 | S93: =SUM(S82:S92) -> 1209567000
A94: GEBANG
A95: GEBANG | F95: 2.2.3 | G95: Bangunan Tambak Blok D & E
A96: GEBANG | H96: Bak Colling Tower | I96: 2005 | J96: 0.05 | K96: 19950000 | L96: 0 | M96: 0 | N96: =K96+L96-M96 -> 19950000 | O96: 2992500 | P96: 0 | Q96: 0 | R96: =O96+P96-Q96 -> 2992500 | S96: =N96-R96 -> 16957500
A97: GEBANG | H97: Mess Asisten + Tempat Kultur + Wc | I97: 2005 | J97: 0.05 | K97: 84240000 | L97: 0 | M97: 0 | N97: =K97+L97-M97 -> 84240000 | O97: 12636000 | P97: 0 | Q97: 0 | R97: =O97+P97-Q97 -> 12636000 | S97: =N97-R97 -> 71604000
A98: GEBANG | H98: Rumah Genset Blok D & E | I98: 2011 | J98: 0.05 | K98: 150150000 | L98: 0 | M98: 0 | N98: =K98+L98-M98 -> 150150000 | O98: 22522500 | P98: 0 | Q98: 0 | R98: =O98+P98-Q98 -> 22522500 | S98: =N98-R98 -> 127627500
A99: GEBANG | H99: Mess Asisten + Kantin | I99: 2011 | J99: 0.05 | K99: 104895000 | L99: 0 | M99: 0 | N99: =K99+L99-M99 -> 104895000 | O99: 15734250 | P99: 0 | Q99: 0 | R99: =O99+P99-Q99 -> 15734250 | S99: =N99-R99 -> 89160750
A100: GEBANG | H100: Mess Feeder (11 Unit) | I100: 2011 | J100: 0.05 | K100: 40800000 | L100: 0 | M100: 0 | N100: =K100+L100-M100 -> 40800000 | O100: 6120000 | P100: 0 | Q100: 0 | R100: =O100+P100-Q100 -> 6120000 | S100: =N100-R100 -> 34680000
A101: GEBANG | H101: Gudang Pakan ( 2 Unit) | I101: 2011 | J101: 0.05 | K101: 19950000 | L101: 0 | M101: 0 | N101: =K101+L101-M101 -> 19950000 | O101: 2992500 | P101: 0 | Q101: 0 | R101: =O101+P101-Q101 -> 2992500 | S101: =N101-R101 -> 16957500
A102: GEBANG | H102: Mess + Gudang Pakan | I102: 2014 | J102: 0.05 | K102: 46762500 | L102: 0 | M102: 0 | N102: =K102+L102-M102 -> 46762500 | O102: 7014375 | P102: 0 | Q102: 0 | R102: =O102+P102-Q102 -> 7014375 | S102: =N102-R102 -> 39748125
A103: GEBANG | F103: Jumlah Bangunan Tambak Blok D & E | K103: =SUM(K96:K102) -> 466747500 | L103: =SUM(L96:L102) -> 0 | M103: =SUM(M96:M102) -> 0 | N103: =SUM(N96:N102) -> 466747500 | O103: =SUM(O96:O102) -> 70012125 | P103: =SUM(P96:P102) -> 0 | Q103: =SUM(Q96:Q102) -> 0 | R103: =SUM(R96:R102) -> 70012125 | S103: =SUM(S96:S102) -> 396735375
A104: GEBANG
A105: GEBANG | F105: 2.2.4 | G105: Bangunan Tambak Blok F-H
A106: GEBANG | H106: Bak Colling Tower | I106: 2005 | J106: 0.05 | K106: 14250000 | L106: 0 | M106: 0 | N106: =K106+L106-M106 -> 14250000 | O106: 2137500 | P106: 0 | Q106: 0 | R106: =O106+P106-Q106 -> 2137500 | S106: =N106-R106 -> 12112500
A107: GEBANG | H107: Rumah Genset Blok F-H | I107: 2011 | J107: 0.05 | K107: 115500000 | L107: 0 | M107: 0 | N107: =K107+L107-M107 -> 115500000 | O107: 17325000 | P107: 0 | Q107: 0 | R107: =O107+P107-Q107 -> 17325000 | S107: =N107-R107 -> 98175000
A108: GEBANG | H108: Mess Asisten + Kantin | I108: 2011 | J108: 0.05 | K108: 211680000 | L108: 0 | M108: 0 | N108: =K108+L108-M108 -> 211680000 | O108: 31752000 | P108: 0 | Q108: 0 | R108: =O108+P108-Q108 -> 31752000 | S108: =N108-R108 -> 179928000
A109: GEBANG | H109: Mess Feeder ( 14 Unit) | I109: 2011 | J109: 0.05 | K109: 42840000 | L109: 0 | M109: 0 | N109: =K109+L109-M109 -> 42840000 | O109: 6426000 | P109: 0 | Q109: 0 | R109: =O109+P109-Q109 -> 6426000 | S109: =N109-R109 -> 36414000
...

Sheet COA AT
A2: No. Akun | B2: COA
A3: 1-61.101 | B3: Hak atas Tanah
A4: 1-61.102 | B4: Tanah (Tax Amnesty)
A5: 1-61.103 | B5: Bangunan
A6: 1-61.104 | B6: Sarana & Prasarana
A7: 1-61.105 | B7: Mesin & Perlengkapan
A8: 1-61.106 | B8: Kendaraan
A9: 1-61.107 | B9: Peralatan & Perlengkapan
A10: 1-61.108 | B10: Instalasi Listrik
A11: 1-61.109 | B11: Infrastruktur
A12: 1-61.110 | B12: Sumur Bor
A14: 1-61.201 | B14: Akumulasi Bangunan
... A23: 5-11.700 | B23: Depresiasi
A25: 6-11.501 | B25: Penyusutan Peralatan & Perlengkapan, Biaya | C25: OPEX | E25: 51186083
A26: 6-11.502 | B26: Penyusutan Sarana & Prasarana, Biaya | C26: OPEX | E26: 4.9721397e+08
A27: 6-11.503 | B27: Penyusutan Bangunan, Biaya | C27: OPEX | E27: 41407000
A28: 6-11.504 | B28: Penyusutan Electricity Instalasi, Biaya | C28: COGS | E28: 0
A29: 6-11.505 | B29: Penyusutan Infrastruktur, Biaya | C29: COGS | E29: 0
A30: 6-11.506 | B30: Penyusutan Kendaraan, Biaya | C30: OPEX | E30: 789225000
A31: 6-11.507 | B31: Penyusutan Mesin-Mesin, Biaya | C31: COGS | E31: 0
A32: 6-11.508 | B32: Penyusutan Sumur Bor, Biaya | C32: COGS | E32: 0

Sheet Adjustment 2023
D1: =E1-F1 -> 0 | E1: =SUM(E4:E295) -> 1.2622752e+10 | F1: =SUM(F4:F295) -> 1.2622752e+10
A2: Tanggal | B2: Account No. | C2: Account Name | D2: WP Reff | E2: Balance Sheet | G2: Description
E3: Debit | F3: Credit
B5: 6-11.501 | C5: Penyusutan Peralatan & Perlengkapan, Biaya | E5: ='Disclosure Aset'!E32 -> 64098844 | G5: Adjustment Penyusutan Aset Tetap Jan s.d Des 2023
B6: 6-11.502 | C6: Penyusutan Sarana & Prasarana, Biaya | E6: ='Disclosure Aset'!E28 -> 378489750 | G6: =G5 -> Adjustment Penyusutan Aset Tetap Jan s.d Des 2023
B7: 6-11.503 | C7: Penyusutan Bangunan, Biaya | E7: ='Disclosure Aset'!E26 -> 1.8603735e+09 | G7: =G6 -> Adjustment Penyusutan Aset Tetap Jan s.d Des 2023
B8: 6-11.504 | C8: Penyusutan Electricity Instalasi, Biaya | E8: ='Disclosure Aset'!E30 -> 72614000 | G8: =G7 -> Adjustment Penyusutan Aset Tetap Jan s.d Des 2023
B9: 6-11.505 | C9: Penyusutan Infrastruktur, Biaya | E9: ='Disclosure Aset'!E33 -> 1.3247535e+09 | G9: =G8 -> Adjustment Penyusutan Aset Tetap Jan s.d Des 2023
B10: 6-11.506 | C10: Penyusutan Kendaraan, Biaya | E10: ='Disclosure Aset'!E31 -> 982475000 | G10: =G9 -> Adjustment Penyusutan Aset Tetap Jan s.d Des 2023
B11: 6-11.507 | C11: Penyusutan Mesin-Mesin, Biaya | E11: ='Disclosure Aset'!E29 -> 3.2177823e+09 | G11: =G10 -> Adjustment Penyusutan Aset Tetap Jan s.d Des 2023
B12: 6-11.508 | C12: Penyusutan Sumur Bor, Biaya | E12: ='Disclosure Aset'!E27 -> 53507438 | G12: =G11 -> Adjustment Penyusutan Aset Tetap Jan s.d Des 2023
B13: 1-61.201 | C13: Akumulasi Bangunan | F13: =E7 -> 1.8603735e+09 | G13: =G12 -> Adjustment Penyusutan Aset Tetap Jan s.d Des 2023
B14: 1-61.202 | C14: Akumulasi Sarana & Prasarana | F14: =E6 -> 378489750 | G14: =G13 -> Adjustment Penyusutan Aset Tetap Jan s.d Des 2023
B15: 1-61.203 | C15: Akumulasi Mesin & Perlengkapan | F15: =E11 -> 3.2177823e+09 | G15: =G14 -> Adjustment Penyusutan Aset Tetap Jan s.d Des 2023
B16: 1-61.204 | C16: Akumulasi Kendaraan | F16: =E10 -> 982475000 | G16: =G15 -> Adjustment Penyusutan Aset Tetap Jan s.d Des 2023
B17: 1-61.205 | C17: Akumulasi Peralatan & Perlengkapan | F17: =E5 -> 64098844 | G17: =G16 -> Adjustment Penyusutan Aset Tetap Jan s.d Des 2023
B18: 1-61.206 | C18: Akumulasi Instalasi Listrik | F18: =E8 -> 72614000 | G18: =G17 -> Adjustment Penyusutan Aset Tetap Jan s.d Des 2023
B19: 1-61.207 | C19: Akumulasi Infrastruktur | F19: =E9 -> 1.3247535e+09 | G19: =G18 -> Adjustment Penyusutan Aset Tetap Jan s.d Des 2023
B20: 1-61.208 | C20: Akumulasi Sumur Bor | F20: =E12 -> 53507438 | G20: =G19 -> Adjustment Penyusutan Aset Tetap Jan s.d Des 2023
B22: 5-11.700 | C22: Depresiasi | E22: =SUM(F23:F26) -> 4.6686572e+09 | G22: Reklas Penyusutan GA ke penyusutan COGS per 2023
B23: ='COA AT'!A28 -> 6-11.504 | C23: ='COA AT'!B28 -> Penyusutan Electricity Instalasi, Biaya | F23: =E8 -> 72614000 | G23: =G22 -> Reklas Penyusutan GA ke penyusutan COGS per 2023
B24: ='COA AT'!A29 -> 6-11.505 | C24: ='COA AT'!B29 -> Penyusutan Infrastruktur, Biaya | F24: =E9 -> 1.3247535e+09 | G24: =G23 -> Reklas Penyusutan GA ke penyusutan COGS per 2023
B25: ='COA AT'!A31 -> 6-11.507 | C25: ='COA AT'!B31 -> Penyusutan Mesin-Mesin, Biaya | F25: =E11 -> 3.2177823e+09 | G25: =G24 -> Reklas Penyusutan GA ke penyusutan COGS per 2023
B26: ='COA AT'!A32 -> 6-11.508 | C26: ='COA AT'!B32 -> Penyusutan Sumur Bor, Biaya | F26: =E12 -> 53507438 | G26: =G25 -> Reklas Penyusutan GA ke penyusutan COGS per 2023

Sheet Disclosure Aset
M1: 0.05
B2: ASET TETAP | G2: PMK >> | L2: 8 thn | M2: 0.125
B3: Akm Penyusutan 2016 | M3: 0.25
C4: WS | L4: 16 thn | M4: 0.0625
C5: 2023
C6: Saldo Awal | E6: Penambahan | G6: Pengurangan | I6: Reklasifikasi | K6: Saldo Akhir | Q6: WBS | S6: Selisih
B8: Nilai Perolehan
B9: Tanah | C9: =K46 -> 0 | E9: =0 -> 0 | G9: 0 | K9: =C9+E9+G9+I9 -> 0
B10: Bangunan | C10: =K47 -> 3.7188156e+10 | E10: ='2. Bangunan'!F129 -> 0 | G10: 0 | I10: 0 | K10: =C10+E10+G10+I10 -> 3.7188156e+10
B11: Sumur Bor | C11: =K48 -> 445059500 | E11: ='3. Sumur Bor'!F54 -> 0 | G11: 0 | K11: =C11+E11+G11+I11 -> 445059500
B12: Sarana dan Prasarana | C12: =K49 -> 6200217370 | E12: ='4. Sarana & Prasarana'!F43 -> 0 | G12: 0 | K12: =C12+E12+G12+I12 -> 6200217370
B13: Mesin | C13: =K50 -> 3.7618136e+10 | E13: ='5. Mesin'!F329 -> 0 | G13: 0 | K13: =C13+E13+G13+I13 -> 3.7618136e+10
B14: Instalasi Elektrik | C14: =K51 -> 1452280000 | E14: ='6. Instalasi Elektrik'!F56 -> 0 | G14: 0 | K14: =C14+E14+G14+I14 -> 1452280000
B15: Kendaraan | C15: =K52 -> 8342660000 | E15: ='7. Kendaraan'!F82 -> 120000000 | G15: 0 | I15: 0 | K15: =C15+E15+G15+I15 -> 8462660000
B16: Peralatan dan Perlengkapan | C16: =K53 -> 1274154796 | E16: ='8 Peralatan & Perlengkapan'!F162 -> 29115000 | G16: 0 | I16: 0 | K16: =C16+E16+G16+I16 -> 1303269796
B17: Infrastruktur | C17: =K54 -> 1.1170379e+10 | E17: ='9. Infrastruktur'!F63 -> 0 | G17: 0 | I17: 0 | K17: =C17+E17+G17+I17 -> 1.1170379e+10 | AQ17: WBS | AR17: Selisih
B19: Sub-Jumlah | C19: =SUM(C9:C17) -> 1.0369104e+11 | E19: =SUM(E9:E17) -> 149115000 | G19: =SUM(G9:G17) -> 0 | H19: =SUM(H10:H17) -> 0 | I19: =SUM(I10:I17) -> 0 | J19: =SUM(J10:J17) -> 0 | K19: =SUM(K9:K17) -> 1.0384016e+11 | AQ19: 1.0384016e+11 | AR19: =AQ19-K19 -> 0.8999939
B21: Aset Tetap Dalam Pembangunan | C21: =K58 -> 0 | G21: 0 | I21: 0 | K21: =C21+E21-G21+I21 -> 0
B23: Jumlah | C23: =C19+C21 -> 1.0369104e+11 | E23: =E19+E21 -> 149115000 | G23: =G19+G21 -> 0 | H23: =SUM(H14:H21) -> 0 | I23: =SUM(I14:I21) -> 0 | J23: =SUM(J14:J21) -> 0 | K23: =K19+K21 -> 1.0384016e+11
C24: 2023 | AQ24: Akumulasi akhir WBS | AR24: Diff | AT24: Beban Penyusutan WBS | AU24: Diff
B25: Akumulasi Penyusutan
B26: Bangunan | C26: =K63 -> 9.2122918e+09 | E26: ='2. Bangunan'!AQ115 -> 1.8603735e+09 | G26: 0 | I26: 0 | K26: =C26+E26+G26+I26 -> 1.1072665e+10 | AG26: =E26/C26 -> 0.2019447 | AQ26: -10981268315 | AR26: =AQ26+K26 -> 91396967
B27: Sumur Bor | C27: =K64 -> 3.5855856e+08 | E27: ='3. Sumur Bor'!AQ40 -> 53507438 | G27: 0 | K27: =C27+E27+G27+I27 -> 412066000 | AQ27: -412066001 | AR27: =AQ27+K27 -> -1
B28: Sarana dan Prasarana | C28: =K65 -> 3.3669626e+09 | E28: ='4. Sarana & Prasarana'!AQ29 -> 378489750 | G28: 0 | K28: =C28+E28+G28+I28 -> 3.7454524e+09 | AQ28: -3745452370 | AR28: =AQ28+K28 -> 0
B29: Mesin | C29: =K66 -> 1.8146072e+10 | E29: ='5. Mesin'!AP315 -> 3.2177823e+09 | G29: 0 | K29: =C29+E29+G29+I29 -> 2.1363854e+10 | AG29: =E29/C29 -> 0.17732665 | AQ29: -21314681680 | AR29: =AQ29+K29 -> 49172771
B30: Instalasi Elektrik | C30: =K67 -> 397178000 | E30: ='6. Instalasi Elektrik'!AP43 -> 72614000 | G30: 0 | K30: =C30+E30+G30+I30 -> 469792000 | AQ30: -469792000 | AR30: =AQ30+K30 -> 0
B31: Kendaraan | C31: =K68 -> 7346435000 | E31: ='7. Kendaraan'!AP69 -> 982475000 | G31: 0 | I31: 0 | K31: =C31+E31+G31+I31+0.5 -> 8.32891e+09 | AQ31: -8328910000 | AR31: =AQ31+K31 -> 0.5
B32: Peralatan dan Perlengkapan | C32: =K69 -> 1.1746927e+09 | E32: ='8 Peralatan & Perlengkapan'!AP149 -> 64098844 | G32: 0 | I32: 0 | K32: =C32+E32+G32+I32 -> 1.2387915e+09 | AQ32: -1238791525 | AR32: =AQ32+K32 -> 0.16666675
B33: Infrastruktur | C33: =K70 -> 9.0731326e+09 | E33: ='9. Infrastruktur'!AP50 -> 1.3247535e+09 | G33: 0 | I33: 0 | K33: =C33+E33+G33+I33 -> 1.0397886e+10 | AQ33: -10397886078 | AR33: =AQ33+K33 -> 0.35000038
B35: Jumlah | C35: =SUM(C26:C34) -> 4.9075323e+10 | E35: =SUM(E26:E34) -> 7.9540943e+09 | G35: =SUM(G26:G34) -> 0 | H35: =SUM(H26:H33) -> 0 | I35: =SUM(I26:I34) -> 0 | K35: =SUM(K26:K34) -> 5.7029418e+10 | AQ35: WBS | AR35: Selisih By Penyusutan | AS35: WBS | AT35: Selisih Akm Penyusutan
AQ36: 7.9540943e+09 | AR36: =AQ36-E35 -> 0 | AS36: 5.7029418e+10 | AT36: =K35+AS36 -> 1.1405884e+11
B37: Nilai Buku | C37: =C23-C35 -> 5.461572e+10 | K37: =K23-K35 -> 4.6810741e+10
C41: WS
C42: 2022
C43: Saldo Awal | E43: Penambahan | G43: Pengurangan | I43: Reklasifikasi | K43: Saldo Akhir
B45: Nilai Perolehan
B46: Tanah | C46: =K85 -> 0 | E46: 0 | G46: 0 | K46: =C46+E46+G46+I46 -> 0 | Q46: 5357572749 | S46: =K46-Q46 -> -5357572749 | T46: 5357572749 | U46: =K46-T46 -> -5357572749
B47: Bangunan | C47: =K86 -> 3.7188156e+10 | E47: ='2. Bangunan'!F128 -> 0 | G47: 0 | I47: 0 | K47: =C47+E47+G47+I47 -> 3.7188156e+10 | Q47: 36346508225 | S47: =K47-Q47 -> 8.4164793e+08 | T47: 36346558225 | U47: =K47-T47 -> 8.4159793e+08 | AF47: 36346558225 | AG47: =K47-AF47 -> 8.4159793e+08
B48: Sumur Bor | C48: =K87 -> 445059500 | E48: ='3. Sumur Bor'!F53 -> 0 | G48: 0 | K48: =C48+E48+G48+I48 -> 445059500 | Q48: 445059500 | S48: =K48-Q48 -> 0 | T48: 445059500 | U48: =K48-T48 -> 0 | AF48: 445059500 | AG48: =K48-AF48 -> 0
B49: Sarana dan Prasarana | C49: =K88 -> 6200217370 | E49: ='4. Sarana & Prasarana'!F42 -> 0 | G49: 0 | K49: =C49+E49+G49+I49 -> 6200217370 | Q49: 6241971770 | S49: =K49-Q49 -> -41754400 | T49: 6241971770 | U49: =K49-T49 -> -41754400 | AF49: 6200217370 | AG49: =K49-AF49 -> 0
B50: Mesin | C50: =K89 -> 3.7601207e+10 | E50: ='5. Mesin'!F328 -> 16929730 | G50: 0 | K50: =C50+E50+G50+I50 -> 3.7618136e+10 | Q50: 37258829288 | S50: =K50-Q50 -> 3.5930716e+08 | T50: 37248739288 | U50: =K50-T50 -> 3.6939716e+08 | AF50: 37224754289 | AG50: =K50-AF50 -> 3.9338216e+08
B51: Instalasi Elektrik | C51: =K90 -> 1452280000 | E51: ='6. Instalasi Elektrik'!F55 -> 0 | G51: 0 | K51: =C51+E51+G51+I51 -> 1452280000 | Q51: 1452280000 | S51: =K51-Q51 -> 0 | T51: 1452280000 | U51: =K51-T51 -> 0 | AF51: 1452280000 | AG51: =K51-AF51 -> 0
B52: Kendaraan | C52: =K91 -> 8342660000 | E52: ='7. Kendaraan'!F81 -> 0 | G52: 0 | I52: 0 | K52: =C52+E52+G52+I52 -> 8342660000 | Q52: 6719860000 | S52: =K52-Q52 -> 1622800000 | T52: 6719860000 | U52: =K52-T52 -> 1622800000 | AF52: 8342660000 | AG52: =K52-AF52 -> 0
B53: Peralatan dan Perlengkapan | C53: =K92 -> 1212799796 | E53: ='8 Peralatan & Perlengkapan'!F161 -> 61355000 | G53: 0 | I53: 0 | K53: =C53+E53+G53+I53 -> 1274154796 | Q53: 1253169796 | S53: =K53-Q53 -> 20985000 | T53: 1253169796 | U53: =K53-T53 -> 20985000 | AF53: 1274154796 | AG53: =K53-AF53 -> 0
B54: Infrastruktur | C54: =K93 -> 1.1170379e+10 | E54: ='9. Infrastruktur'!F62 -> 0 | G54: 0 | I54: 0 | K54: =C54+E54+G54+I54 -> 1.1170379e+10 | Q54: 15904584670 | S54: =K54-Q54 -> -4.7342052e+09 | T54: 12793179447 | U54: =K54-T54 -> -1.6228e+09 | AF54: 1.1170379e+10 | AG54: =K54-AF54 -> 0 | AQ54: WBS | AR54: Selisih
B56: Sub-Jumlah | C56: =SUM(C46:C54) -> 1.0361276e+11 | E56: =SUM(E46:E54) -> 78284730 | G56: =SUM(G46:G54) -> 0 | H56: =SUM(H47:H54) -> 0 | I56: =SUM(I47:I54) -> 0 | J56: =SUM(J47:J54) -> 0 | K56: =SUM(K46:K54) -> 1.0369104e+11 | O56: Perubahan Harga Perolehan | AQ56: 103691043717 | AR56: =AQ56-K56 -> 0.69999695
B58: Aset Tetap Dalam Pembangunan | C58: =K97 -> 0 | E58: 0 | G58: 0 | I58: 0 | K58: =C58+E58+G58+I58 -> 0
B60: Jumlah | C60: =C56+C58 -> 1.0361276e+11 | E60: =E56+E58 -> 78284730 | G60: =G56+G58 -> 0 | H60: =SUM(H51:H58) -> 0 | I60: =SUM(I51:I58) -> 0 | J60: =SUM(J51:J58) -> 0 | K60: =K56+K58 -> 1.0369104e+11
C61: 2022 | AQ61: Akumulasi akhir WBS | AR61: Diff | AT61: Beban Penyusutan WBS | AU61: Diff
B62: Akumulasi Penyusutan
B63: Bangunan | C63: =K102 -> 7.3519183e+09 | E63: ='2. Bangunan'!AH115 -> 1.8603735e+09 | G63: 0 | I63: 0 | K63: =C63+E63+G63+I63 -> 9.2122918e+09 | L63: 1809532236 | M63: =E63-L63 -> 50841272 | Q63: 17195403665 | S63: =K63-Q63 -> -7.9831119e+09 | T63: 1809532236 | U63: =E63-T63 -> 50841272 | X63: 9159088806 | Y63: =K63-X63 -> 53202968 | AD63: 9159088806 | AE63: =K63-AD63 -> 53202968 | AG63: 1.814675e+09 | AH63: =E63-AG63 -> 45698483 | AJ63: 9.1551687e+09 | AK63: =K63-AJ63 -> 57123104 | AQ63: -9212291774 | AR63: =K63+AQ63 -> 0.16246033
B64: Sumur Bor | C64: =K103 -> 302926125 | E64: ='3. Sumur Bor'!AH40 -> 55632438 | G64: 0 | K64: =C64+E64+G64+I64 -> 3.5855856e+08 | L64: 121115280 | M64: =E64-L64 -> -65482842 | Q64: 405154938 | S64: =K64-Q64 -> -46596376 | T64: 121115280 | U64: =E64-T64 -> -65482842 | X64: 358558562 | Y64: =K64-X64 -> 0.5 | AD64: 358558562 | AE64: =K64-AD64 -> 0.5 | AG64: 55632438 | AH64: =E64-AG64 -> 0 | AJ64: 3.5855856e+08 | AK64: =K64-AJ64 -> 0 | AQ64: -358558563 | AR64: =AQ64+K64 -> -0.5
B65: Sarana dan Prasarana | C65: =K104 -> 2.876204e+09 | E65: ='4. Sarana & Prasarana'!AH29 -> 4.9075862e+08 | G65: 0 | K65: =C65+E65+G65+I65 -> 3.3669626e+09 | L65: 197131302 | M65: =E65-L65 -> 2.9362732e+08 | Q65: 6245549791 | S65: =K65-Q65 -> -2.8785872e+09 | T65: 197131302 | U65: =E65-T65 -> 2.9362732e+08 | X65: 5560214416 | Y65: =K65-X65 -> -2.1932518e+09 | AA65: 197131302 | AB65: =E65-AA65 -> 2.9362732e+08 | AD65: 3412295041 | AE65: =K65-AD65 -> -45332421 | AG65: 4.9075862e+08 | AH65: =E65-AG65 -> 0 | AJ65: 3366962620 | AK65: =K65-AJ65 -> 0 | AQ65: -3366962620 | AR65: =K65+AQ65 -> 0
B66: Mesin | C66: =K105 -> 1.4764182e+10 | E66: ='5. Mesin'!AG315 -> 3.3818905e+09 | G66: 0 | K66: =C66+E66+G66+I66 -> 1.8146072e+10 | L66: 4644184476 | M66: =E66-L66 -> -1.262294e+09 | Q66: 20344699220 | S66: =K66-Q66 -> -2.198627e+09 | T66: 4644184476 | U66: =E66-T66 -> -1.262294e+09 | X66: 18084606220 | Y66: =K66-X66 -> 61465962 | AD66: 18084606220 | AE66: =K66-AD66 -> 61465962 | AG66: 3.3327177e+09 | AH66: =E66-AG66 -> 49172770 | AJ66: 1.8084606e+10 | AK66: =K66-AJ66 -> 61465963 | AQ66: -18146072182 | AR66: =AQ66+K66 -> 0.13332748
B67: Instalasi Elektrik | C67: =K106 -> 324564000 | E67: ='6. Instalasi Elektrik'!AG43 -> 72614000 | G67: 0 | K67: =C67+E67+G67+I67 -> 397178000 | L67: 203696556 | M67: =E67-L67 -> -131082556 | Q67: 983618000 | S67: =K67-Q67 -> -586440000 | T67: 203696556 | U67: =E67-T67 -> -131082556 | X67: 397178000 | Y67: =K67-X67 -> 0 | AD67: 397178000 | AE67: =K67-AD67 -> 0 | AG67: 72614000 | AH67: =E67-AG67 -> 0 | AJ67: 397178000 | AK67: =K67-AJ67 -> 0 | AQ67: -397178000 | AR67: =AQ67+K67 -> 0
B68: Kendaraan | C68: =K107 -> 6304577500 | E68: ='7. Kendaraan'!AG69 -> 1041857500 | G68: 0 | I68: 0 | K68: =C68+E68+G68+I68 -> 7346435000 | L68: 951212496 | M68: =E68-L68 -> 90645004 | Q68: 6541097500 | S68: =K68-Q68 -> 805337500 | T68: 951212496 | U68: =E68-T68 -> 90645004 | X68: 5926485000 | Y68: =K68-X68 -> 1419950000 | AD68: 5926485000 | AE68: =K68-AD68 -> 1419950000 | AG68: 1041857500 | AH68: =E68-AG68 -> 0 | AJ68: 7346435000 | AK68: =K68-AJ68 -> 0 | AQ68: -7346435000 | AR68: =AQ68+K68 -> 0
B69: Peralatan dan Perlengkapan | C69: =K108 -> 1.0901652e+09 | E69: ='8 Peralatan & Perlengkapan'!AG149 -> 84527500 | G69: 0 | I69: 0 | K69: =C69+E69+G69+I69 -> 1.1746927e+09 | L69: 92011831 | M69: =E69-L69 -> -7484330.8 | Q69: 676466038 | S69: =K69-Q69 -> 4.9822664e+08 | T69: 92011831 | U69: =E69-T69 -> -7484330.8 | X69: 1129360260 | Y69: =K69-X69 -> 45332421 | AD69: 1129360260 | AE69: =K69-AD69 -> 45332421 | AG69: 84527500 | AH69: =E69-AG69 -> 0 | AJ69: 1.1746927e+09 | AK69: =K69-AJ69 -> 0.5916667 | AQ69: -1174692681 | AR69: =AQ69+K69 -> 0.29166675 | AT69: 8322004658 | AU69: =AT69-E72 -> -1.0049973
B70: Infrastruktur | C70: =K109 -> 7.738782e+09 | E70: ='9. Infrastruktur'!AG50 -> 1.3343506e+09 | G70: 0 | I70: 0 | K70: =C70+E70+G70+I70 -> 9.0731326e+09 | L70: 257190050 | M70: =E70-L70 -> 1.0771605e+09 | Q70: 15904584670 | S70: =K70-Q70 -> -6.8314521e+09 | T70: 257190050 | U70: =E70-T70 -> 1.0771605e+09 | X70: 11234408628 | Y70: =K70-X70 -> -2.161276e+09 | AA70: 257190050 | AB70: =E70-AA70 -> 1.0771605e+09 | AD70: 10475798490 | AE70: =K70-AD70 -> -1.4026659e+09 | AG70: 1.3343506e+09 | AH70: =E70-AG70 -> 0 | AJ70: 9.0558485e+09 | AK70: =K70-AJ70 -> 17284095 | AQ70: -9073132585 | AR70: =AQ70+K70 -> 0.14999962
B72: Jumlah | C72: =SUM(C63:C71) -> 4.0753319e+10 | E72: =SUM(E63:E71) -> 8.3220047e+09 | G72: =SUM(G63:G71) -> 0 | H72: =SUM(H63:H70) -> 0 | I72: =SUM(I63:I71) -> 0 | K72: =SUM(K63:K71) -> 4.9075323e+10
B74: Nilai Buku | C74: =C60-C72 -> 6.285944e+10 | K74: =K60-K72 -> 5.461572e+10 | AQ74: WBS | AR74: Selisih By Penyusutan | AS74: WBS | AT74: Selisih Akm Penyusutan
AQ76: 8322004658 | AR76: =E72-AQ76 -> 1.0049973 | AS76: -49075323405 | AT76: =AS76+K72 -> 0.23745728
B77: C o n t r o l | C77: =[65]AT!K29 -> #REF! | K77: =[65]AT!I29 -> #REF!
B78: S e l i s i h | C78: =C74-C77 -> #REF! | K78: =K74-K77 -> #REF!
C81: 2021 | L81: SPT 2021
C82: Saldo Awal | E82: Penambahan | G82: Pengurangan | I82: Reklasifikasi | K82: Saldo Akhir
B84: Nilai Perolehan
B85: Tanah | C85: =K119 -> 0 | E85: =0 -> 0 | G85: 0 | K85: =C85+E85+G85+I85 -> 0 | Q85: 5357572749 | S85: =K85-Q85 -> -5357572749 | T85: 5357572749 | U85: =K85-T85 -> -5357572749
B86: Bangunan | C86: =K120 -> 2.7419763e+10 | E86: ='2. Bangunan'!F127 -> 9.7683932e+09 | G86: 0 | I86: 0 | K86: =C86+E86+G86+I86 -> 3.7188156e+10 | Q86: 3.6346508e+10 | S86: =K86-Q86 -> 8.4164793e+08 | T86: 36346558226 | U86: =K86-T86 -> 8.4159793e+08 | AF86: 3.6346558e+10 | AG86: =K86-AF86 -> 8.4159793e+08
B87: Sumur Bor | C87: =K121 -> 445059500 | E87: ='3. Sumur Bor'!F52 -> 0 | G87: 0 | K87: =C87+E87+G87+I87 -> 445059500 | Q87: 832237957 | S87: =K87-Q87 -> -387178457 | T87: 833372957 | U87: =K87-T87 -> -388313457 | AA87: Selisih karen ada yg di takeout | AF87: 445059500 | AG87: =K87-AF87 -> 0
B88: Sarana dan Prasarana | C88: =K122 -> 6200217370 | E88: ='4. Sarana & Prasarana'!F41 -> 0 | G88: 0 | K88: =C88+E88+G88+I88 -> 6200217370 | Q88: 6200217370 | S88: =K88-Q88 -> 0 | T88: 6200217370 | U88: =K88-T88 -> 0 | AF88: 6200217370 | AG88: =K88-AF88 -> 0
B89: Mesin | C89: =K123 -> 2.8284388e+10 | E89: ='5. Mesin'!F327 -> 9.3168187e+09 | G89: 0 | K89: =C89+E89+G89+I89 -> 3.7601207e+10 | Q89: 3.7217915e+10 | S89: =K89-Q89 -> 3.8329216e+08 | T89: 37207824558 | U89: =K89-T89 -> 3.9338216e+08 | AF89: 3.7207825e+10 | AG89: =K89-AF89 -> 3.9338216e+08
B90: Instalasi Elektrik | C90: =K124 -> 1007800000 | E90: ='6. Instalasi Elektrik'!F54 -> 444480000 | G90: 0 | K90: =C90+E90+G90+I90 -> 1452280000 | Q90: 1452280000 | S90: =K90-Q90 -> 0 | T90: 1452280000 | U90: =K90-T90 -> 0 | AF90: 1452280000 | AG90: =K90-AF90 -> 0
B91: Kendaraan | C91: =K125 -> 8342660000 | E91: ='7. Kendaraan'!F80 -> 0 | G91: 0 | I91: 0 | K91: =C91+E91+G91+I91 -> 8342660000 | Q91: 6719860000 | S91: =K91-Q91 -> 1622800000 | T91: 6719860000 | U91: =K91-T91 -> 1622800000 | AF91: 8342660000 | AG91: =K91-AF91 -> 0
B92: Peralatan dan Perlengkapan | C92: =K126 -> 1208997796 | E92: ='8 Peralatan & Perlengkapan'!F160 -> 3802000 | G92: 0 | I92: 0 | K92: =C92+E92+G92+I92 -> 1212799796 | Q92: 1213849796 | S92: =K92-Q92 -> -1050000 | T92: 1213849796 | U92: =K92-T92 -> -1050000 | AF92: 1212799796 | AG92: =K92-AF92 -> 0
B93: Infrastruktur | C93: =K127 -> 1.1170379e+10 | E93: ='9. Infrastruktur'!F61 -> 0 | G93: 0 | I93: 0 | K93: =C93+E93+G93+I93 -> 1.1170379e+10 | Q93: 1.5904585e+10 | S93: =K93-Q93 -> -4734205223 | T93: 12793259447 | U93: =K93-T93 -> -1.62288e+09 | AF93: 1.1170379e+10 | AG93: =K93-AF93 -> 0 | AH93: 1.1170379e+10 | AI93: =K93-AH93 -> 0 | AQ93: WBS | AR93: Selisih
B95: Sub-Jumlah | C95: =SUM(C85:C93) -> 8.4079265e+10 | E95: =SUM(E85:E93) -> 1.9533494e+10 | G95: =SUM(G85:G93) -> 0 | H95: =SUM(H86:H93) -> 0 | I95: =SUM(I86:I93) -> 0 | J95: =SUM(J86:J93) -> 0 | K95: =SUM(K85:K93) -> 1.0361276e+11 | L95: 1.5225272e+11 | M95: =K95-L95 -> -4.8639958e+10 | O95: Ada perubahan Harga Perolehan | AQ95: 1.0361276e+11 | AR95: =AQ95-K95 -> 0.3999939
B97: Aset Tetap Dalam Pembangunan | C97: =K131 -> 5294378786 | E97: 0 | G97: =C97 -> 5294378786 | I97: 0 | K97: =C97+E97-G97 -> 0
B99: Jumlah | C99: =C95+C97 -> 8.9373644e+10 | E99: =E95+E97 -> 1.9533494e+10 | G99: =G95+G97 -> 5294378786 | H99: =SUM(H90:H97) -> 0 | I99: =SUM(I90:I97) -> 0 | J99: =SUM(J90:J97) -> 0 | K99: =K95+K97 -> 1.0361276e+11
C100: 2021
B101: Akumulasi Penyusutan | AQ101: Akumulasi akhir WBS | AR101: Diff | AT101: Beban Penyusutan WBS | AU101: Diff
B102: Bangunan | C102: =K136 -> 5.9316464e+09 | E102: ='2. Bangunan'!AE115 -> 1.4202719e+09 | G102: 0 | I102: 0 | K102: =C102+E102+G102+I102 -> 7.3519183e+09 | L102: 1193518456 | M102: =E102-L102 -> 2.2675345e+08 | Q102: 1.5377113e+10 | S102: =K102-Q102 -> -8.0251943e+09 | T102: 1193518456 | U102: =E102-T102 -> 2.2675345e+08 | X102: 7.3407952e+09 | Y102: =K102-X102 -> 11123072 | AG102: =1409148829.50842-301549 -> 1.4088473e+09 | AH102: =E102-AG102 -> 11424621 | AJ102: 7340493646 | AK102: =K102-AJ102 -> 11424621 | AM102: 1.4088473e+09 | AN102: =E102-AM102 -> 11424621 | AO102: 7.3404936e+09 | AP102: =K102-AO102 -> 11424621 | AQ102: -7351918267 | AR102: =K102+AQ102 -> -0.44254112
B103: Sumur Bor | C103: =K137 -> 2.4729369e+08 | E103: ='3. Sumur Bor'!AE40 -> 55632438 | G103: 0 | K103: =C103+E103+G103+I103 -> 302926125 | L103: 77167812 | M103: =E103-L103 -> -21535374 | Q103: 394460000 | S103: =K103-Q103 -> -91533875 | T103: 77167812 | U103: =E103-T103 -> -21535374 | X103: 3.0292612e+08 | Y103: =K103-X103 -> 0.5 | AG103: 55632438 | AH103: =E103-AG103 -> 0 | AJ103: 3.0292612e+08 | AK103: =K103-AJ103 -> 0.5 | AM103: 55632438 | AN103: =E103-AM103 -> 0 | AO103: 302926125 | AP103: =K103-AO103 -> 0 | AQ103: -302926125 | AR103: =K103+AQ103 -> 0
B104: Sarana dan Prasarana | C104: =K138 -> 2.37899e+09 | E104: ='4. Sarana & Prasarana'!AE29 -> 4.9721397e+08 | G104: 0 | K104: =C104+E104+G104+I104 -> 2.876204e+09 | L104: 191912004 | M104: =E104-L104 -> 3.0530196e+08 | Q104: 6.0879485e+09 | S104: =K104-Q104 -> -3.2117445e+09 | T104: 191912004 | U104: =E104-T104 -> 3.0530196e+08 | X104: 4.7172777e+09 | Y104: =K104-X104 -> -1.8410737e+09 | AA104: 191912004 | AB104: =E104-AA104 -> 3.0530196e+08 | AD104: 2876203996 | AE104: =K104-AD104 -> -0.16666698 | AG104: 4.9721397e+08 | AH104: =E104-AG104 -> 0 | AJ104: 2876203996 | AK104: =K104-AJ104 -> -0.16666698 | AM104: 4.9721397e+08 | AN104: =E104-AM104 -> 0 | AO104: 2.876204e+09 | AP104: =K104-AO104 -> 0.00033283234 | AQ104: -2876203996 | AR104: =K104+AQ104 -> -0.16666698
B105: Mesin | C105: =K139 -> 1.1938715e+10 | E105: ='5. Mesin'!AD315 -> 2.8254665e+09 | G105: 0 | K105: =C105+E105+G105+I105 -> 1.4764182e+10 | L105: 2067321482 | M105: =E105-L105 -> 7.5814507e+08 | Q105: 1.8710336e+10 | S105: =K105-Q105 -> -3.9461543e+09 | T105: 2067321482 | U105: =E105-T105 -> 7.5814507e+08 | X105: 1.4751888e+10 | Y105: =K105-X105 -> 12293192 | AG105: 2.8131734e+09 | AH105: =E105-AG105 -> 12293193 | AJ105: 14751888474 | AK105: =K105-AJ105 -> 12293193 | AM105: 2.8131734e+09 | AN105: =E105-AM105 -> 12293193 | AO105: 1.4751888e+10 | AP105: =K105-AO105 -> 12293193 | AQ105: -14764181667 | AR105: =K105+AQ105 -> -0.066669464
B106: Instalasi Elektrik | C106: =K140 -> 251950000 | E106: ='6. Instalasi Elektrik'!AD43 -> 72614000 | G106: 0 | K106: =C106+E106+G106+I106 -> 324564000 | L106: 183324556 | M106: =E106-L106 -> -110710556 | Q106: 927079000 | S106: =K106-Q106 -> -602515000 | T106: 183324556 | U106: =E106-T106 -> -110710556 | X106: 324564000 | Y106: =K106-X106 -> 0 | AG106: 72614000 | AH106: =E106-AG106 -> 0 | AJ106: 324564000 | AK106: =K106-AJ106 -> 0 | AM106: 72614000 | AN106: =E106-AM106 -> 0 | AO106: 324564000 | AP106: =K106-AO106 -> 0 | AQ106: -324564000 | AR106: =K106+AQ106 -> 0
B107: Kendaraan | C107: =K141 -> 5262557500 | E107: ='7. Kendaraan'!AD69 -> 1042020000 | G107: 0 | I107: 0 | K107: =C107+E107+G107+I107 -> 6304577500 | L107: 951212496 | M107: =E107-L107 -> 90807504 | Q107: 6311015000 | S107: =K107-Q107 -> -6437500 | T107: 951212496 | U107: =E107-T107 -> 90807504 | X107: 5087477500 | Y107: =K107-X107 -> 1217100000 | AG107: 1042020000 | AH107: =E107-AG107 -> 0 | AJ107: 6304577500 | AK107: =K107-AJ107 -> 0 | AM107: 1042020000 | AN107: =E107-AM107 -> 0 | AO107: 6304577500 | AP107: =K107-AO107 -> 0 | AQ107: -6304577500 | AR107: =K107+AQ107 -> 0
B108: Peralatan dan Perlengkapan | C108: =K142 -> 1.0089859e+09 | E108: ='8 Peralatan & Perlengkapan'!AD149 -> 81179313 | G108: 0 | I108: 0 | K108: =C108+E108+G108+I108 -> 1.0901652e+09 | L108: 113536277 | M108: =E108-L108 -> -32356964 | Q108: 6.3727096e+08 | S108: =K108-Q108 -> 4.5289422e+08 | T108: 113536277 | U108: =E108-T108 -> -32356964 | X108: 1.0901652e+09 | Y108: =K108-X108 -> 0.29166675 | AG108: 81179313 | AH108: =E108-AG108 -> 0 | AJ108: 1090165181 | AK108: =K108-AJ108 -> 0.041666746 | AM108: 81179313 | AN108: =E108-AM108 -> 0 | AO108: 1.0901652e+09 | AP108: =K108-AO108 -> -0.00033330917 | AQ108: -1090165181 | AR108: =K108+AQ108 -> 0.041666746
B109: Infrastruktur | C109: =K143+17284095 -> 6.3720899e+09 | E109: ='9. Infrastruktur'!AD50 -> 1.3666921e+09 | G109: 0 | I109: 0 | K109: =C109+E109+G109+I109 -> 7.738782e+09 | L109: 547236300 | M109: =E109-L109 -> 8.1945582e+08 | Q109: 1.5709901e+10 | S109: =K109-Q109 -> -7.9711195e+09 | T109: 547236300 | U109: =E109-T109 -> 8.1945582e+08 | X109: 1.0014118e+10 | Y109: =K109-X109 -> -2.2753363e+09 | AA109: 547236300 | AB109: =E109-AA109 -> 8.1945582e+08 | AD109: 8.9385979e+09 | AE109: =K109-AD109 -> -1.1998159e+09 | AG109: 1.3666921e+09 | AH109: =E109-AG109 -> 0 | AJ109: 7.7214979e+09 | AK109: =K109-AJ109 -> 17284095 | AM109: 1.3666921e+09 | AN109: =E109-AM109 -> 0 | AO109: 7.7214979e+09 | AP109: =K109-AO109 -> 17284095 | AQ109: -7738782011 | AR109: =K109+AQ109 -> -0.13333321 | AT109: 7361090287 | AU109: =E111-AT109 -> -0.27770901
B111: Jumlah | C111: =SUM(C102:C110) -> 3.3392228e+10 | E111: =SUM(E102:E110) -> 7.3610903e+09 | G111: =SUM(G102:G110) -> 0 | H111: =SUM(H102:H109) -> 0 | I111: =SUM(I102:I110) -> 0 | K111: =SUM(K102:K110) -> 4.0753319e+10 | AQ111: WBS | AR111: Selisih By Penyusutan | AS111: WBS | AT111: Selisih Akm Penyusutan
B113: Nilai Buku | C113: =C99-C111 -> 5.5981415e+10 | K113: =K99-K111 -> 6.285944e+10 | AQ113: 7361090287 | AR113: =E111-AQ113 -> -0.27770901 | AS113: -40753318747 | AT113: =K111+AS113 -> -0.76753998
C115: 2020 | L115: Tally | M115: Selisih
C116: Saldo Awal | E116: Penambahan | G116: Pengurangan | I116: Reklasifikasi | K116: Saldo Akhir
B118: Nilai Perolehan
B119: Tanah | C119: ='1. Tanah'!B21 -> 0 | E119: 0 | G119: 0 | K119: =C119+E119+G119+I119 -> 0 | Q119: 8793817749 | S119: =Q119-K119 -> 8793817749 | T119: 8793817749 | U119: =K119-T119 -> -8793817749
B120: Bangunan | C120: ='2. Bangunan'!E126 -> 2.7419763e+10 | E120: ='2. Bangunan'!F126 -> 0 | G120: 0 | I120: 0 | K120: =C120+E120+G120+I120 -> 2.7419763e+10 | Q120: 3.1938422e+10 | S120: =Q120-K120 -> 4.5186592e+09 | T120: 31526945374 | U120: =K120-T120 -> -4.1071824e+09 | AF120: 27419762987 | AG120: =K120-AF120 -> -0.020004272 | AI120: 27419762987 | AJ120: =K120-AI120 -> -0.020004272
B121: Sumur Bor | C121: ='3. Sumur Bor'!E50 -> 401196000 | E121: ='3. Sumur Bor'!F51 -> 43863500 | G121: 0 | K121: =C121+E121+G121+I121 -> 445059500 | Q121: 624472308 | S121: =Q121-K121 -> 179412808 | T121: 565140570 | U121: =K121-T121 -> -120081070 | AF121: 445059500 | AG121: =K121-AF121 -> 0 | AI121: 445059500 | AJ121: =K121-AI121 -> 0
B122: Sarana dan Prasarana | C122: ='4. Sarana & Prasarana'!E39 -> 6200217370 | E122: ='4. Sarana & Prasarana'!F40 -> 0 | G122: 0 | K122: =C122+E122+G122+I122 -> 6200217370 | Q122: 1.716794e+10 | S122: =Q122-K122 -> 1.0967722e+10 | T122: 5727182097 | U122: =K122-T122 -> 473035273 | AA122: 4499799597 | AB122: =K122-AA122 -> 1700417773 | AF122: 6200217370 | AG122: =K122-AF122 -> 0 | AI122: 6200217370 | AJ122: =K122-AI122 -> 0
B123: Mesin | C123: ='5. Mesin'!E325 -> 2.8268513e+10 | E123: ='5. Mesin'!F326 -> 15875000 | G123: 0 | K123: =C123+E123+G123+I123 -> 2.8284388e+10 | O123: 2020-Sesuai dgn list TA di SPT 2020 | Q123: 4.2347341e+10 | S123: =Q123-K123 -> 1.4062953e+10 | T123: 36407364059 | U123: =K123-T123 -> -8.122976e+09 | AF123: 28284388018 | AG123: =K123-AF123 -> 0.29999924 | AI123: 28284388018 | AJ123: =K123-AI123 -> 0.29999924
B124: Instalasi Elektrik | C124: ='6. Instalasi Elektrik'!E52 -> 1007800000 | E124: ='6. Instalasi Elektrik'!F53 -> 0 | G124: 0 | K124: =C124+E124+G124+I124 -> 1007800000 | Q124: 3629451000 | S124: =Q124-K124 -> 2621651000 | T124: 3102721721 | U124: =K124-T124 -> -2094921721 | AF124: 1007800000 | AG124: =K124-AF124 -> 0 | AI124: 1007800000 | AJ124: =K124-AI124 -> 0
B125: Kendaraan | C125: ='7. Kendaraan'!E78 -> 8342660000 | E125: ='7. Kendaraan'!F79 -> 0 | G125: 0 | I125: 0 | K125: =C125+E125+G125+I125 -> 8342660000 | Q125: 7907060000 | S125: =Q125-K125 -> -435600000 | T125: 7455853989 | U125: =K125-T125 -> 886806011 | AF125: 8342660000 | AG125: =K125-AF125 -> 0 | AI125: 8342660000 | AJ125: =K125-AI125 -> 0
...

Sheet NBV sdh habis
A1: KATEGORI ASET YANG SUDAH HABIS NBV
C3: 2024 | F3: =SUM(F5:F279) -> 3.076226e+10 | K3: 2023 | N3: =SUM(N5:N253) -> 2.5397181e+10
B4: No | C4: Kategori Aset | D4: Nama Aset | E4: Tahun Perolehan | F4: Nilai Aset | J4: No | K4: Kategori Aset | L4: Nama Aset | M4: Tahun Perolehan | N4: Nilai Aset
B5: 1 | C5: Sumur Bor | D5: ='3. Sumur Bor'!B5 -> Sumur Bor | E5: ='3. Sumur Bor'!C5 -> 37257 | F5: ='3. Sumur Bor'!E5 -> 222800000 | J5: 1 | K5: Sumur Bor | L5: ='3. Sumur Bor'!B5 -> Sumur Bor | M5: ='3. Sumur Bor'!C5 -> 37257 | N5: ='3. Sumur Bor'!E5 -> 222800000
B6: =B5+1 -> 2 | C6: Sumur Bor | D6: ='3. Sumur Bor'!B6 -> Sumur Bor | E6: ='3. Sumur Bor'!C6 -> 38353 | F6: ='3. Sumur Bor'!E6 -> 68200000 | J6: =J5+1 -> 2 | K6: Sumur Bor | L6: ='3. Sumur Bor'!B6 -> Sumur Bor | M6: ='3. Sumur Bor'!C6 -> 38353 | N6: ='3. Sumur Bor'!E6 -> 68200000
B7: =B6+1 -> 3 | C7: Sumur Bor | D7: ='3. Sumur Bor'!B7 -> Sumur Bor | E7: ='3. Sumur Bor'!C7 -> 38718 | F7: ='3. Sumur Bor'!E7 -> 68500000 | J7: =J6+1 -> 3 | K7: Sumur Bor | L7: ='3. Sumur Bor'!B7 -> Sumur Bor | M7: ='3. Sumur Bor'!C7 -> 38718 | N7: ='3. Sumur Bor'!E7 -> 68500000
B8: =B7+1 -> 4 | C8: Sumur Bor | D8: ='3. Sumur Bor'!B8 -> Pompa Submersible SP17 | E8: 42005 | F8: ='3. Sumur Bor'!E12 -> 17000000 | J8: =J7+1 -> 4 | K8: Sumur Bor | L8: ='3. Sumur Bor'!B12 -> Pompa Submersible Type MS 4000 | M8: ='3. Sumur Bor'!C12 -> 42005 | N8: ='3. Sumur Bor'!E12 -> 17000000
B9: =B8+1 -> 5 | C9: Sarana dan Prasarana | D9: Perkerasan Paving Blok | E9: 40544 | F9: ='4. Sarana & Prasarana'!E6 -> 573153000 | J9: =J8+1 -> 5 | K9: Sarana & Prasarana | L9: ='4. Sarana & Prasarana'!B6 -> Perkerasan Paving Blok | M9: ='4. Sarana & Prasarana'!C6 -> 40544 | N9: ='4. Sarana & Prasarana'!E6 -> 573153000
B10: =B9+1 -> 6 | C10: Sarana dan Prasarana | D10: Paving Blok Uni Abu-Abu | E10: 43466 | F10: ='4. Sarana & Prasarana'!E8 -> 397432750 | J10: =J9+1 -> 6 | K10: Sarana & Prasarana | L10: ='4. Sarana & Prasarana'!B8 -> Paving Blok Uni Abu-Abu | M10: ='4. Sarana & Prasarana'!C8 -> 43466 | N10: ='4. Sarana & Prasarana'!E8 -> 397432750
B11: =B10+1 -> 7 | C11: Sarana dan Prasarana | D11: Talud | E11: 38353 | F11: ='4. Sarana & Prasarana'!E10 -> 117276000 | J11: =J10+1 -> 7 | K11: Sarana & Prasarana | L11: ='4. Sarana & Prasarana'!B10 -> Talud | M11: ='4. Sarana & Prasarana'!C10 -> 38353 | N11: ='4. Sarana & Prasarana'!E10 -> 117276000
B12: =B11+1 -> 8 | C12: Sarana dan Prasarana | D12: Pagar | E12: 41640 | F12: ='4. Sarana & Prasarana'!E12 -> 125361500 | J12: =J11+1 -> 8 | K12: Sarana & Prasarana | L12: ='4. Sarana & Prasarana'!B12 -> Pagar | M12: ='4. Sarana & Prasarana'!C12 -> 41640 | N12: ='4. Sarana & Prasarana'!E12 -> 125361500
B13: =B12+1 -> 9 | C13: Sarana dan Prasarana | D13: Jembatan Automatis Feeder | E13: 43344 | F13: ='4. Sarana & Prasarana'!E15 -> 77464120 | J13: =J12+1 -> 9 | K13: Sarana & Prasarana | L13: ='4. Sarana & Prasarana'!B15 -> Jembatan Automatis Feeder | M13: ='4. Sarana & Prasarana'!C15 -> 43344 | N13: ='4. Sarana & Prasarana'!E15 -> 77464120
B14: =B13+1 -> 10 | C14: Mesin | D14: Panel Genset / Kabel Dll | E14: 37257 | F14: 70900000 | J14: =J13+1 -> 10 | K14: Mesin | L14: ='5. Mesin'!B19 -> Panel Genset / Kabel Dll | M14: ='5. Mesin'!C19 -> 37257 | N14: ='5. Mesin'!E19 -> 70900000
B15: =B14+1 -> 11 | C15: Mesin | D15: Genset 500 KVA Mercy | E15: 38353 | F15: 441100000 | J15: =J14+1 -> 11 | K15: Mesin | L15: ='5. Mesin'!B20 -> Genset 500 KVA Mercy | M15: ='5. Mesin'!C20 -> 38353 | N15: ='5. Mesin'!E20 -> 441100000
B16: =B15+1 -> 12 | C16: Mesin | D16: Genset MWM 500 KVA | E16: 40909 | F16: 176900000 | J16: =J15+1 -> 12 | K16: Mesin | L16: ='5. Mesin'!B21 -> Genset MWM 500 KVA | M16: ='5. Mesin'!C21 -> 40909 | N16: ='5. Mesin'!E21 -> 176900000
B17: =B16+1 -> 13 | C17: Mesin | D17: Water Treatment Machine | E17: 37257 | F17: 1400000 | J17: =J16+1 -> 13 | K17: Mesin | L17: ='5. Mesin'!B23 -> Water Treatment Machine | M17: ='5. Mesin'!C23 -> 37257 | N17: ='5. Mesin'!E23 -> 1400000
B18: =B17+1 -> 14 | C18: Mesin | D18: Water Treatment Machine | E18: 38353 | F18: 2600000 | J18: =J17+1 -> 14 | K18: Mesin | L18: ='5. Mesin'!B24 -> Water Treatment Machine | M18: ='5. Mesin'!C24 -> 38353 | N18: ='5. Mesin'!E24 -> 2600000
B19: =B18+1 -> 15 | C19: Mesin | D19: Compresor (Budiono) | E19: 37257 | F19: 52800000 | J19: =J18+1 -> 15 | K19: Mesin | L19: ='5. Mesin'!B28 -> Compresor (Budiono) | M19: ='5. Mesin'!C28 -> 37257 | N19: ='5. Mesin'!E28 -> 52800000
B20: =B19+1 -> 16 | C20: Mesin | D20: Compressor (Grasco) | E20: 37257 | F20: 252600000 | J20: =J19+1 -> 16 | K20: Mesin | L20: ='5. Mesin'!B29 -> Compressor (Grasco) | M20: ='5. Mesin'!C29 -> 37257 | N20: ='5. Mesin'!E29 -> 252600000
B21: =B20+1 -> 17 | C21: Mesin | D21: Asesoris Compressor | E21: 37622 | F21: 74900000 | J21: =J20+1 -> 17 | K21: Mesin | L21: ='5. Mesin'!B30 -> Asesoris Compressor | M21: ='5. Mesin'!C30 -> 37622 | N21: ='5. Mesin'!E30 -> 74900000
B22: =B21+1 -> 18 | C22: Mesin | D22: Compressor Mycom | E22: 38353 | F22: 86200000 | J22: =J21+1 -> 18 | K22: Mesin | L22: ='5. Mesin'!B31 -> Compressor Mycom | M22: ='5. Mesin'!C31 -> 38353 | N22: ='5. Mesin'!E31 -> 86200000
B23: =B22+1 -> 19 | C23: Mesin | D23: Cylinder Liner Comp. Grasso | E23: 39448 | F23: 4600000 | J23: =J22+1 -> 19 | K23: Mesin | L23: ='5. Mesin'!B32 -> Cylinder Liner Comp. Grasso | M23: ='5. Mesin'!C32 -> 39448 | N23: ='5. Mesin'!E32 -> 4600000
B24: =B23+1 -> 20 | C24: Mesin | D24: Compressor Mycom-Djunisanu | E24: 39448 | F24: 155200000 | J24: =J23+1 -> 20 | K24: Mesin | L24: ='5. Mesin'!B33 -> Compressor Mycom-Djunisanu | M24: ='5. Mesin'!C33 -> 39448 | N24: ='5. Mesin'!E33 -> 155200000
B25: =B24+1 -> 21 | C25: Mesin | D25: Conveyor | E25: 39083 | F25: 168100000 | J25: =J24+1 -> 21 | K25: Mesin | L25: ='5. Mesin'!B37 -> Conveyor | M25: ='5. Mesin'!C37 -> 39083 | N25: ='5. Mesin'!E37 -> 168100000
B26: =B25+1 -> 22 | C26: Mesin | D26: Material Inter Cooler | E26: 39448 | F26: 39300000 | J26: =J25+1 -> 22 | K26: Mesin | L26: ='5. Mesin'!B38 -> Material Inter Cooler | M26: ='5. Mesin'!C38 -> 39448 | N26: ='5. Mesin'!E38 -> 39300000
B27: =B26+1 -> 23 | C27: Mesin | D27: Siku Conveyor | E27: 39448 | F27: 20800000 | J27: =J26+1 -> 23 | K27: Mesin | L27: ='5. Mesin'!B39 -> Siku Conveyor | M27: ='5. Mesin'!C39 -> 39448 | N27: ='5. Mesin'!E39 -> 20800000
B28: =B27+1 -> 24 | C28: Mesin | D28: Besi Conveyor | E28: 39448 | F28: 10500000 | J28: =J27+1 -> 24 | K28: Mesin | L28: ='5. Mesin'!B40 -> Besi Conveyor | M28: ='5. Mesin'!C40 -> 39448 | N28: ='5. Mesin'!E40 -> 10500000
B29: =B28+1 -> 25 | C29: Mesin | D29: Wayer Pompa Grundfos | E29: 39814 | F29: 7900000 | J29: =J28+1 -> 25 | K29: Mesin | L29: ='5. Mesin'!B41 -> Wayer Pompa Grundfos | M29: ='5. Mesin'!C41 -> 39814 | N29: ='5. Mesin'!E41 -> 7900000
B30: =B29+1 -> 26 | C30: Mesin | D30: Shrimp Cutter Machine | E30: 39814 | F30: 97100000 | J30: =J29+1 -> 26 | K30: Mesin | L30: ='5. Mesin'!B42 -> Shrimp Cutter Machine | M30: ='5. Mesin'!C42 -> 39814 | N30: ='5. Mesin'!E42 -> 97100000
B31: =B30+1 -> 27 | C31: Mesin | D31: Mesin Foot Impulse Sealer | E31: 40544 | F31: 4800000 | J31: =J30+1 -> 27 | K31: Mesin | L31: ='5. Mesin'!B43 -> Mesin Foot Impulse Sealer | M31: ='5. Mesin'!C43 -> 40544 | N31: ='5. Mesin'!E43 -> 4800000
B32: =B31+1 -> 28 | C32: Mesin | D32: Meteran Solar 1 1/2" | E32: 40909 | F32: 5000000 | J32: =J31+1 -> 28 | K32: Mesin | L32: ='5. Mesin'!B44 -> Meteran Solar 1 1/2" | M32: ='5. Mesin'!C44 -> 40909 | N32: ='5. Mesin'!E44 -> 5000000
B33: =B32+1 -> 29 | C33: Mesin | D33: Steam Boiler Miura | E33: 40909 | F33: 248145455 | J33: =J32+1 -> 29 | K33: Mesin | L33: ='5. Mesin'!B45 -> Steam Boiler Miura | M33: ='5. Mesin'!C45 -> 40909 | N33: ='5. Mesin'!E45 -> 248145455
B34: =B33+1 -> 30 | C34: Mesin | D34: Inverter LS 20 HP | E34: 41275 | F34: 9200000 | J34: =J33+1 -> 30 | K34: Mesin | L34: ='5. Mesin'!B46 -> Inverter LS 20 HP | M34: ='5. Mesin'!C46 -> 41275 | N34: ='5. Mesin'!E46 -> 9200000
B35: =B34+1 -> 31 | C35: Mesin | D35: Tangki Amoniak | E35: 41275 | F35: 36200000 | J35: =J34+1 -> 31 | K35: Mesin | L35: ='5. Mesin'!B47 -> Tangki Amoniak | M35: ='5. Mesin'!C47 -> 41275 | N35: ='5. Mesin'!E47 -> 36200000
B36: =B35+1 -> 32 | C36: Mesin | D36: Blower Impeler | E36: 41275 | F36: 28000000 | J36: =J35+1 -> 32 | K36: Mesin | L36: ='5. Mesin'!B48 -> Blower Impeler | M36: ='5. Mesin'!C48 -> 41275 | N36: ='5. Mesin'!E48 -> 28000000
... B45: =B44+1 -> 41 | C45: Mesin | D45: Mesin Pompa Air | E45: 42247 | F45: 5300000 | J45: =J44+1 -> 41 | K45: Mesin | L45: ='5. Mesin'!B57 -> Mesin Pompa Air | M45: ='5. Mesin'!C57 -> 42247 | N45: ='5. Mesin'!E57 -> 5300000
B46: =B45+1 -> 42 | C46: Mesin | D46: Pompa Submersible HCP @ 1 uit | E46: 42594 | F46: 8600000 | J46: =J45+1 -> 42 | K46: Mesin | L46: ='5. Mesin'!B73 -> Steam Boiler Cold Storage 2 | M46: ='5. Mesin'!C73 -> 39448 | N46: ='5. Mesin'!E73 -> 26600000
B47: =B46+1 -> 43 | C47: Mesin | D47: Inventer | E47: 42630 | F47: 15925000 | J47: =J46+1 -> 43 | K47: Mesin | L47: ='5. Mesin'!B74 -> Roller Chains 40x1 | M47: ='5. Mesin'!C74 -> 39814 | N47: ='5. Mesin'!E74 -> 3200000
B48: =B47+1 -> 44 | C48: Mesin | D48: Steam Boiler Cold Storage 2 | E48: 39448 | F48: 26600000 | J48: =J47+1 -> 44 | K48: Mesin | L48: ='5. Mesin'!B75 -> Sproket SS RS 40x60 | M48: ='5. Mesin'!C75 -> 39814 | N48: ='5. Mesin'!E75 -> 5700000
B49: =B48+1 -> 45 | C49: Mesin | D49: Roller Chains 40x1 | E49: 39814 | F49: 3200000 | J49: =J48+1 -> 45 | K49: Mesin | L49: ='5. Mesin'!B77 -> Mesin Cutter Zeppelin & Shrimp Cutter Machine | M49: ='5. Mesin'!C77 -> 40179 | N49: ='5. Mesin'!E77 -> 111400000
B50: =B49+1 -> 46 | C50: Mesin | D50: Sproket SS RS 40x60 | E50: 39814 | F50: 5700000 | J50: =J49+1 -> 46 | K50: Mesin | L50: ='5. Mesin'!B79 -> Mesin NH3 (Hermetic) / Pompa Amoniak | M50: ='5. Mesin'!C79 -> 40544 | N50: ='5. Mesin'!E79 -> 18600000
B51: =B50+1 -> 47 | C51: Mesin | D51: Mesin Cutter Zeppelin & Shrimp Cutter Machine | E51: 40179 | F51: 111400000 | J51: =J50+1 -> 47 | K51: Mesin | L51: ='5. Mesin'!B81 -> Conveyor | M51: ='5. Mesin'!C81 -> 40544 | N51: ='5. Mesin'!E81 -> 116100000
B52: =B51+1 -> 48 | C52: Mesin | D52: Mesin NH3 (Hermetic) / Pompa Amoniak | E52: 40544 | F52: 18600000 | J52: =J51+1 -> 48 | K52: Mesin | L52: ='5. Mesin'!B83 -> Mesin CPF | M52: ='5. Mesin'!C83 -> 40544 | N52: ='5. Mesin'!E83 -> 14300000
B53: =B52+1 -> 49 | C53: Mesin | D53: Conveyor | E53: 40544 | F53: 116100000 | J53: =J52+1 -> 49 | K53: Mesin | L53: ='5. Mesin'!B84 -> Mesin Sortir : | M53: ='5. Mesin'!C84 -> 40544 | N53: ='5. Mesin'!E84 -> 15900000
B54: =B53+1 -> 50 | C54: Mesin | D54: Mesin CPF | E54: 40544 | F54: 14300000 | J54: =J53+1 -> 50 | K54: Mesin | L54: ='5. Mesin'!B85 -> Cold Room Baru Div.ISP2 | M54: ='5. Mesin'!C85 -> 40544 | N54: ='5. Mesin'!E85 -> 287200000
B55: =B54+1 -> 51 | C55: Mesin | D55: Mesin Sortir : | E55: 40544 | F55: 15900000 | J55: =J54+1 -> 51 | K55: Mesin | L55: ='5. Mesin'!B86 -> Double Chamber | M55: ='5. Mesin'!C86 -> 40909 | N55: ='5. Mesin'!E86 -> 92500000
B56: =B55+1 -> 52 | C56: Mesin | D56: Cold Room Baru Div.ISP2 | E56: 40544 | F56: 287200000 | J56: =J55+1 -> 52 | K56: Mesin | L56: ='5. Mesin'!B91 -> Mesin Tambak | M56: ='5. Mesin'!C91 -> 38353 | N56: ='5. Mesin'!E91 -> 70800000
B57: =B56+1 -> 53 | C57: Mesin | D57: Double Chamber | E57: 40909 | F57: 92500000 | J57: =J56+1 -> 53 | K57: Mesin | L57: ='5. Mesin'!B92 -> Mesin Genset | M57: ='5. Mesin'!C92 -> 38353 | N57: ='5. Mesin'!E92 -> 30700000
B58: =B57+1 -> 54 | C58: Mesin | D58: Mesin Tambak | E58: 38353 | F58: 70800000 | J58: =J57+1 -> 54 | K58: Mesin | L58: ='5. Mesin'!B93 -> Kapasitor MG 60 KVA | M58: ='5. Mesin'!C93 -> 38353 | N58: ='5. Mesin'!E93 -> 7500000
B59: =B58+1 -> 55 | C59: Mesin | D59: Mesin Genset | E59: 38353 | F59: 30700000 | J59: =J58+1 -> 55 | K59: Mesin | L59: ='5. Mesin'!B94 -> NFB MG 3Phase 100A | M59: ='5. Mesin'!C94 -> 38353 | N59: ='5. Mesin'!E94 -> 1200000
B60: =B59+1 -> 56 | C60: Mesin | D60: Kapasitor MG 60 KVA | E60: 38353 | F60: 7500000 | J60: =J59+1 -> 56 | K60: Mesin | L60: ='5. Mesin'!B96 -> Kabel Eterna NYAF | M60: ='5. Mesin'!C96 -> 38353 | N60: ='5. Mesin'!E96 -> 2400000
B61: =B60+1 -> 57 | C61: Mesin | D61: NFB MG 3Phase 100A | E61: 38353 | F61: 1200000 | J61: =J60+1 -> 57 | K61: Mesin | L61: ='5. Mesin'!B97 -> Magnetic Kontraktor + Scun SC 70mm + Volt Meter GAE 400A | M61: ='5. Mesin'!C97 -> 38353 | N61: ='5. Mesin'!E97 -> 1100000
B62: =B61+1 -> 58 | C62: Mesin | D62: Kabel Eterna NYAF | E62: 38353 | F62: 2400000 | J62: =J61+1 -> 58 | K62: Mesin | L62: ='5. Mesin'!B99 -> CT GAE 400/5A | M62: ='5. Mesin'!C99 -> 38353 | N62: ='5. Mesin'!E99 -> 700000
B63: =B62+1 -> 59 | C63: Mesin | D63: Magnetic Kontraktor + Scun SC 70mm + Volt Meter GAE 400A | E63: 38353 | F63: 1100000 | J63: =J62+1 -> 59 | K63: Mesin | L63: ='5. Mesin'!B101 -> MCB MG 3Phase 4A | M63: ='5. Mesin'!C101 -> 38353 | N63: ='5. Mesin'!E101 -> 7300000
B64: =B63+1 -> 60 | C64: Mesin | D64: CT GAE 400/5A | E64: 38353 | F64: 700000 | J64: =J63+1 -> 60 | K64: Mesin | L64: ='5. Mesin'!B102 -> Prequency Meter GAE 48-52H | M64: ='5. Mesin'!C102 -> 38353 | N64: ='5. Mesin'!E102 -> 600000
B65: =B64+1 -> 61 | C65: Mesin | D65: MCB MG 3Phase 4A | E65: 38353 | F65: 7300000 | J65: =J64+1 -> 61 | K65: Mesin | L65: ='5. Mesin'!B103 -> NFB MG 3Phase 400A | M65: ='5. Mesin'!C103 -> 38353 | N65: ='5. Mesin'!E103 -> 1500000
B66: =B65+1 -> 62 | C66: Mesin | D66: Prequency Meter GAE 48-52H | E66: 38353 | F66: 600000 | J66: =J65+1 -> 62 | K66: Mesin | L66: ='5. Mesin'!B104 -> Accu N-120 | M66: ='5. Mesin'!C104 -> 38353 | N66: ='5. Mesin'!E104 -> 8200000
B67: =B66+1 -> 63 | C67: Mesin | D67: NFB MG 3Phase 400A | E67: 38353 | F67: 1500000 | J67: =J66+1 -> 63 | K67: Mesin | L67: ='5. Mesin'!B105 -> Mesin Gerinda Tangan Hitachi | M67: ='5. Mesin'!C105 -> 39448 | N67: ='5. Mesin'!E105 -> 1000000
B68: =B67+1 -> 64 | C68: Mesin | D68: Accu N-120 | E68: 38353 | F68: 8200000 | J68: =J67+1 -> 64 | K68: Mesin | L68: ='5. Mesin'!B106 -> Accu N-100 | M68: ='5. Mesin'!C106 -> 39448 | N68: ='5. Mesin'!E106 -> 2000000
B69: =B68+1 -> 65 | C69: Mesin | D69: Mesin Gerinda Tangan Hitachi | E69: 39448 | F69: 1000000 | J69: =J68+1 -> 65 | K69: Mesin | L69: ='5. Mesin'!B107 -> Pompa Submersible | M69: ='5. Mesin'!C107 -> 39448 | N69: ='5. Mesin'!E107 -> 228800000
B70: =B69+1 -> 66 | C70: Mesin | D70: Accu N-100 | E70: 39448 | F70: 2000000 | J70: =J69+1 -> 66 | K70: Mesin | L70: ='5. Mesin'!B108 -> NFB MG 250 A 3Phase | M70: ='5. Mesin'!C108 -> 39814 | N70: ='5. Mesin'!E108 -> 4900000
B71: =B70+1 -> 67 | C71: Mesin | D71: Pompa Submersible | E71: 39448 | F71: 228800000 | J71: =J70+1 -> 67 | K71: Mesin | L71: ='5. Mesin'!B109 -> Kabel NYY Jumbo 1 x 95 mm | M71: ='5. Mesin'!C109 -> 39814 | N71: ='5. Mesin'!E109 -> 9300000
B72: =B71+1 -> 68 | C72: Mesin | D72: NFB MG 250 A 3Phase | E72: 39814 | F72: 4900000 | J72: =J71+1 -> 68 | K72: Mesin | L72: ='5. Mesin'!B110 -> Kabel eterna NYY 3 x 2 1/2 mm | M72: ='5. Mesin'!C110 -> 39814 | N72: ='5. Mesin'!E110 -> 25300000
B73: =B72+1 -> 69 | C73: Mesin | D73: Kabel NYY Jumbo 1 x 95 mm | E73: 39814 | F73: 9300000 | J73: =J72+1 -> 69 | K73: Mesin | L73: ='5. Mesin'!B111 -> Pompa Panasonic | M73: ='5. Mesin'!C111 -> 39814 | N73: ='5. Mesin'!E111 -> 1000000
B74: =B73+1 -> 70 | C74: Mesin | D74: Kabel eterna NYY 3 x 2 1/2 mm | E74: 39814 | F74: 25300000 | J74: =J73+1 -> 70 | K74: Mesin | L74: ='5. Mesin'!B112 -> Pompa Submersible 5 HP | M74: ='5. Mesin'!C112 -> 39814 | N74: ='5. Mesin'!E112 -> 53400000
... B116: =B115+1 -> 112 | C116: Mesin | D116: Generator Leroy | E116: 41640 | F116: 183300000 | J116: =J115+1 -> 112 | K116: Mesin | L116: ='5. Mesin'!B154 -> Terminition Outdoor | M116: ='5. Mesin'!C154 -> 41640 | N116: ='5. Mesin'!E154 -> 5300000
B117: =B116+1 -> 113 | C117: Mesin | D117: Pompa Submersible KS 332 | E117: 41640 | F117: 15800000 | J117: =J116+1 -> 113 | K117: Mesin | L117: ='5. Mesin'!B157 -> Kincir 2014 | M117: ='5. Mesin'!C157 -> 41640 | N117: ='5. Mesin'!E157 -> 105000000
B118: =B117+1 -> 114 | C118: Mesin | D118: Terminition Outdoor | E118: 41640 | F118: 5300000 | J118: =J117+1 -> 114 | K118: Mesin | L118: ='5. Mesin'!B158 -> Pompa SS 8" KL-732 N | M118: ='5. Mesin'!C158 -> 41640 | N118: ='5. Mesin'!E158 -> 76900000
B119: =B118+1 -> 115 | C119: Mesin | D119: Kincir 2014 | E119: 41640 | F119: 105000000 | J119: =J118+1 -> 115 | K119: Mesin | L119: ='5. Mesin'!B163 -> Pompa Submersible 2 HP | M119: ='5. Mesin'!C163 -> 41640 | N119: ='5. Mesin'!E163 -> 32900000
B120: =B119+1 -> 116 | C120: Mesin | D120: Pompa SS 8" KL-732 N | E120: 41640 | F120: 76900000 | J120: =J119+1 -> 116 | K120: Mesin | L120: ='5. Mesin'!B164 -> Stamper Tanada | M120: ='5. Mesin'!C164 -> 41640 | N120: ='5. Mesin'!E164 -> 8600000
B121: =B120+1 -> 117 | C121: Mesin | D121: Pompa Submersible 2 HP | E121: 41640 | F121: 32900000 | J121: =J120+1 -> 117 | K121: Mesin | L121: ='5. Mesin'!B166 -> Mesin Genset 8m20 | M121: ='5. Mesin'!C166 -> 41640 | N121: ='5. Mesin'!E166 -> 64000000
B122: =B121+1 -> 118 | C122: Mesin | D122: Stamper Tanada | E122: 41640 | F122: 8600000 | J122: =J121+1 -> 118 | K122: Mesin | L122: ='5. Mesin'!B168 -> Mesin Sugu + Mesin Cut Off (Potong Besi) | M122: ='5. Mesin'!C168 -> 41640 | N122: ='5. Mesin'!E168 -> 2100000
B123: =B122+1 -> 119 | C123: Mesin | D123: Mesin Genset 8m20 | E123: 41640 | F123: 64000000 | J123: =J122+1 -> 119 | K123: Mesin | L123: ='5. Mesin'!B169 -> Radiator | M123: ='5. Mesin'!C169 -> 41640 | N123: ='5. Mesin'!E169 -> 16400000
B124: =B123+1 -> 120 | C124: Mesin | D124: Mesin Sugu + Mesin Cut Off (Potong Besi) | E124: 41640 | F124: 2100000 | J124: =J123+1 -> 120 | K124: Mesin | L124: ='5. Mesin'!B170 -> Gearbox Futigal | M124: ='5. Mesin'!C170 -> 41640 | N124: ='5. Mesin'!E170 -> 10400000
B125: =B124+1 -> 121 | C125: Mesin | D125: Radiator | E125: 41640 | F125: 16400000 | J125: =J124+1 -> 121 | K125: Mesin | L125: ='5. Mesin'!B171 -> Plat Stainless | M125: ='5. Mesin'!C171 -> 41640 | N125: ='5. Mesin'!E171 -> 4900000
B126: =B125+1 -> 122 | C126: Mesin | D126: Gearbox Futigal | E126: 41640 | F126: 10400000 | J126: =J125+1 -> 122 | K126: Mesin | L126: ='5. Mesin'!B173 -> Kincir 1HP Futigal + Kipas Kincir | M126: ='5. Mesin'!C173 -> 42005 | N126: ='5. Mesin'!E173 -> 1.0573364e+09
B127: =B126+1 -> 123 | C127: Mesin | D127: Plat Stainless | E127: 41640 | F127: 4900000 | J127: =J126+1 -> 123 | K127: Mesin | L127: ='5. Mesin'!B174 -> Dinamo CMG | M127: ='5. Mesin'!C174 -> 42005 | N127: ='5. Mesin'!E174 -> 26708707
B128: =B127+1 -> 124 | C128: Mesin | D128: Kincir 1HP Futigal + Kipas Kincir | E128: 42005 | F128: 1.0573364e+09 | J128: =J127+1 -> 124 | K128: Mesin | L128: ='5. Mesin'!B175 -> GerindaTangan | M128: ='5. Mesin'!C175 -> 42005 | N128: ='5. Mesin'!E175 -> 750000
B129: =B128+1 -> 125 | C129: Mesin | D129: Dinamo CMG | E129: 42005 | F129: 26708707 | J129: =J128+1 -> 125 | K129: Mesin | L129: ='5. Mesin'!B176 -> Radiator | M129: ='5. Mesin'!C176 -> 42005 | N129: ='5. Mesin'!E176 -> 46400000
B130: =B129+1 -> 126 | C130: Mesin | D130: GerindaTangan | E130: 42005 | F130: 750000 | J130: =J129+1 -> 126 | K130: Mesin | L130: ='5. Mesin'!B177 -> Travo Las | M130: ='5. Mesin'!C177 -> 42005 | N130: ='5. Mesin'!E177 -> 3600000
B131: =B130+1 -> 127 | C131: Mesin | D131: Radiator | E131: 42005 | F131: 46400000 | J131: =J130+1 -> 127 | K131: Mesin | L131: ='5. Mesin'!B178 -> Dinamo Starter RE-10 | M131: ='5. Mesin'!C178 -> 42005 | N131: ='5. Mesin'!E178 -> 4300000
B132: =B131+1 -> 128 | C132: Mesin | D132: Travo Las | E132: 42005 | F132: 3600000 | J132: =J131+1 -> 128 | K132: Mesin | L132: ='5. Mesin'!B179 -> Pompa Submersible 2015 | M132: ='5. Mesin'!C179 -> 42005 | N132: ='5. Mesin'!E179 -> 44400000
B133: =B132+1 -> 129 | C133: Mesin | D133: Dinamo Starter RE-10 | E133: 42005 | F133: 4300000 | J133: =J132+1 -> 129 | K133: Mesin | L133: ='5. Mesin'!B180 -> Pompa Submersible 2015 | M133: ='5. Mesin'!C180 -> 42005 | N133: ='5. Mesin'!E180 -> 85100000
B134: =B133+1 -> 130 | C134: Mesin | D134: Pompa Submersible 2015 | E134: 42005 | F134: 44400000 | J134: =J133+1 -> 130 | K134: Mesin | L134: ='5. Mesin'!B181 -> Pompa Submersible 5" 2015 | M134: ='5. Mesin'!C181 -> 42005 | N134: ='5. Mesin'!E181 -> 5500000
B135: =B134+1 -> 131 | C135: Mesin | D135: Pompa Submersible 2015 | E135: 42005 | F135: 85100000 | J135: =J134+1 -> 131 | K135: Mesin | L135: ='5. Mesin'!B182 -> Pompa Submersible 6" 2015 | M135: ='5. Mesin'!C182 -> 42005 | N135: ='5. Mesin'!E182 -> 5500000
B136: =B135+1 -> 132 | C136: Mesin | D136: Pompa Submersible 5" 2015 | E136: 42005 | F136: 5500000 | J136: =J135+1 -> 132 | K136: Mesin | L136: ='5. Mesin'!B183 -> Pompa Submersible 8" 2015 | M136: ='5. Mesin'!C183 -> 42005 | N136: ='5. Mesin'!E183 -> 22200000
B137: =B136+1 -> 133 | C137: Mesin | D137: Pompa Submersible 6" 2015 | E137: 42005 | F137: 5500000 | J137: =J136+1 -> 133 | K137: Mesin | L137: ='5. Mesin'!B184 -> Pompa Submersible KS | M137: ='5. Mesin'!C184 -> 42370 | N137: ='5. Mesin'!E184 -> 43225000
B138: =B137+1 -> 134 | C138: Mesin | D138: Pompa Submersible 8" 2015 | E138: 42005 | F138: 22200000 | J138: =J137+1 -> 134 | K138: Mesin | L138: ='5. Mesin'!B185 -> Pompa Show Fou 4" | M138: ='5. Mesin'!C185 -> 42370 | N138: ='5. Mesin'!E185 -> 27675000
B139: =B138+1 -> 135 | C139: Mesin | D139: Pompa Submersible KS | E139: 42370 | F139: 43225000 | J139: =J138+1 -> 135 | K139: Mesin | L139: ='5. Mesin'!B188 -> Pompa Submersible | M139: ='5. Mesin'!C188 -> 42370 | N139: ='5. Mesin'!E188 -> 42312000
B140: =B139+1 -> 136 | C140: Mesin | D140: Pompa Show Fou 4" | E140: 42370 | F140: 27675000 | J140: =J139+1 -> 136 | K140: Mesin | L140: ='5. Mesin'!B191 -> Pompa TAY YIH SUN | M140: ='5. Mesin'!C191 -> 42370 | N140: ='5. Mesin'!E191 -> 309296000
B141: =B140+1 -> 137 | C141: Mesin | D141: Pompa Submersible | E141: 42370 | F141: 42312000 | J141: =J140+1 -> 137 | K141: Mesin | L141: ='5. Mesin'!B192 -> Kincir Dragon Mode FT | M141: ='5. Mesin'!C192 -> 42370 | N141: ='5. Mesin'!E192 -> 57750000
B142: =B141+1 -> 138 | C142: Mesin | D142: Pompa TAY YIH SUN | E142: 42370 | F142: 309296000 | J142: =J141+1 -> 138 | K142: Mesin | L142: ='5. Mesin'!B193 -> Kincir 1 HP Dragon FT | M142: ='5. Mesin'!C193 -> 42370 | N142: ='5. Mesin'!E193 -> 385000000
B143: =B142+1 -> 139 | C143: Mesin | D143: Kincir Dragon Mode FT | E143: 42370 | F143: 57750000 | J143: =J142+1 -> 139 | K143: Kendaraan | L143: ='7. Kendaraan'!B5 -> Mitsubishi FE349 | M143: ='7. Kendaraan'!C5 -> 37257 | N143: ='7. Kendaraan'!E5 -> 108000000
B144: =B143+1 -> 140 | C144: Mesin | D144: Kincir 1 HP Dragon FT | E144: 42370 | F144: 385000000 | J144: =J143+1 -> 140 | K144: Kendaraan | L144: ='7. Kendaraan'!B6 -> Mitsubishi FE349 | M144: ='7. Kendaraan'!C6 -> 37257 | N144: ='7. Kendaraan'!E6 -> 108000000
B145: =B144+1 -> 141 | C145: Mesin | D145: Pompa TAY YIH SUN H-150 | E145: 42736 | F145: 43600000 | J145: =J144+1 -> 141 | K145: Kendaraan | L145: ='7. Kendaraan'!B7 -> Avanza 1.3 G | M145: ='7. Kendaraan'!C7 -> 37987 | N145: ='7. Kendaraan'!E7 -> 84000000
B146: =B145+1 -> 142 | C146: Mesin | D146: Kincir 1 HP Futigal Aerator | E146: 42736 | F146: 204545454 | J146: =J145+1 -> 142 | K146: Kendaraan | L146: ='7. Kendaraan'!B8 -> XENIA | M146: ='7. Kendaraan'!C8 -> 37987 | N146: ='7. Kendaraan'!E8 -> 69000000
B147: =B146+1 -> 143 | C147: Mesin | D147: Mesin Twinny 230V/2900W | E147: 42736 | F147: 125000000 | J147: =J146+1 -> 143 | K147: Kendaraan | L147: ='7. Kendaraan'!B9 -> BUS PS 100 | M147: ='7. Kendaraan'!C9 -> 37987 | N147: ='7. Kendaraan'!E9 -> 94000000
B148: =B147+1 -> 144 | C148: Mesin | D148: Kincir Padle Whell Aerator | E148: 42736 | F148: 511363650 | J148: =J147+1 -> 144 | K148: Kendaraan | L148: ='7. Kendaraan'!B10 -> TOYOTA DYNA 115ST | M148: ='7. Kendaraan'!C10 -> 38353 | N148: ='7. Kendaraan'!E10 -> 77000000
B149: =B148+1 -> 145 | C149: Mesin | D149: Kincir Padle Whell Aerator | E149: 42736 | F149: 3.2386364e+08 | J149: =J148+1 -> 145 | K149: Kendaraan | L149: ='7. Kendaraan'!B11 -> TOYOTA DYNA 115ST | M149: ='7. Kendaraan'!C11 -> 38353 | N149: ='7. Kendaraan'!E11 -> 77000000
B150: =B149+1 -> 146 | C150: Mesin | D150: Kincir Padle Whell Aerator | E150: 42736 | F150: 1.875e+08 | J150: =J149+1 -> 146 | K150: Kendaraan | L150: ='7. Kendaraan'!B12 -> MITSUBISHI FE 74 | M150: ='7. Kendaraan'!C12 -> 39448 | N150: ='7. Kendaraan'!E12 -> 165000000
...

Sheet Disclosure Aset DES 24
B2: WS
B3: 45627
B4: Saldo Awal | D4: Penambahan | F4: Pengurangan | H4: Reklasifikasi | J4: Saldo Akhir
A6: Nilai Perolehan
A7: Tanah | B7: ='Disclosure Aset'!K9 -> 0 | J7: =B7+D7+F7+H7 -> 0
A8: Bangunan | B8: ='Disclosure Aset'!K10 -> 3.7188156e+10 | J8: =B8+D8+F8+H8 -> 3.7188156e+10
A9: Sumur Bor | B9: ='Disclosure Aset'!K11 -> 445059500 | J9: =B9+D9+F9+H9 -> 445059500
A10: Sarana dan Prasarana | B10: ='Disclosure Aset'!K12 -> 6200217370 | J10: =B10+D10+F10+H10 -> 6200217370
A11: Mesin | B11: ='Disclosure Aset'!K13 -> 3.7618136e+10 | D11: ='5. Mesin'!F330 -> 170000000 | J11: =B11+D11+F11+H11 -> 3.7788136e+10
A12: Instalasi Elektrik | B12: ='Disclosure Aset'!K14 -> 1452280000 | J12: =B12+D12+F12+H12 -> 1452280000
A13: Kendaraan | B13: ='Disclosure Aset'!K15 -> 8462660000 | J13: =B13+D13+F13+H13 -> 8462660000
A14: Peralatan dan Perlengkapan | B14: ='Disclosure Aset'!K16 -> 1303269796 | J14: =B14+D14+F14+H14 -> 1303269796
A15: Infrastruktur | B15: ='Disclosure Aset'!K17 -> 1.1170379e+10 | J15: =B15+D15+F15+H15 -> 1.1170379e+10
A17: Sub-Jumlah | B17: =SUM(B7:B15) -> 1.0384016e+11 | D17: =SUM(D7:D15) -> 170000000 | F17: =SUM(F7:F15) -> 0 | H17: =SUM(H8:H15) -> 0 | J17: =SUM(J7:J15) -> 1.0401016e+11
A19: Aset Tetap Dalam Pembangunan | F19: 0 | H19: 0 | J19: =B19+D19-F19+H19 -> 0
A21: Jumlah | B21: =B17+B19 -> 1.0384016e+11 | D21: =D17+D19 -> 170000000 | F21: =F17+F19 -> 0 | H21: =SUM(H12:H19) -> 0 | J21: =J17+J19 -> 1.0401016e+11
B22: =B3 -> 45627
A23: Akumulasi Penyusutan
A24: Bangunan | B24: ='Disclosure Aset'!K26 -> 1.1072665e+10 | D24: ='2. Bangunan'!AW115 -> 1.8603735e+09 | J24: =B24+D24+F24+H24 -> 1.2933039e+10
A25: Sumur Bor | B25: ='Disclosure Aset'!K27 -> 412066000 | D25: ='3. Sumur Bor'!AZ40 -> 8569937.5 | J25: =B25+D25+F25+H25 -> 4.2063594e+08
A26: Sarana dan Prasarana | B26: ='Disclosure Aset'!K28 -> 3.7454524e+09 | D26: ='4. Sarana & Prasarana'!AZ29 -> 306845625 | J26: =B26+D26+F26+H26 -> 4.052298e+09
A27: Mesin | B27: ='Disclosure Aset'!K29 -> 2.1363854e+10 | D27: ='5. Mesin'!AV315 -> 2.392046e+09 | J27: =B27+D27+F27+H27 -> 2.37559e+10
A28: Instalasi Elektrik | B28: ='Disclosure Aset'!K30 -> 469792000 | D28: ='6. Instalasi Elektrik'!AV43 -> 72614000 | J28: =B28+D28+F28+H28 -> 542406000
A29: Kendaraan | B29: ='Disclosure Aset'!K31 -> 8.32891e+09 | D29: ='7. Kendaraan'!AV69 -> 43750000 | J29: =B29+D29+F29+H29 -> 8.37266e+09
A30: Peralatan dan Perlengkapan | B30: ='Disclosure Aset'!K32 -> 1.2387915e+09 | D30: ='8 Peralatan & Perlengkapan'!AV149 -> 23811021 | J30: =B30+D30+F30+H30 -> 1262602546
A31: Infrastruktur | B31: ='Disclosure Aset'!K33 -> 1.0397886e+10 | D31: ='9. Infrastruktur'!AV50 -> 5.9548081e+08 | J31: =B31+D31+F31+H31 -> 1.0993367e+10
A33: Jumlah | B33: =SUM(B24:B32) -> 5.7029418e+10 | D33: =SUM(D24:D32) -> 5.3034909e+09 | F33: =SUM(F24:F32) -> 0 | H33: =SUM(H24:H32) -> 0 | J33: =SUM(J24:J32) -> 6.2332909e+10
A35: Nilai Buku | B35: =B21-B33 -> 4.6810741e+10 | J35: =J21-J33 -> 4.167725e+10
B39: WS
B40: 45536
B41: Saldo Awal | D41: Penambahan | F41: Pengurangan | H41: Reklasifikasi | J41: Saldo Akhir
A43: Nilai Perolehan
A44: Tanah | B44: ='Disclosure Aset'!K9 -> 0 | J44: =B44+D44+F44+H44 -> 0
A45: Bangunan | B45: ='Disclosure Aset'!K10 -> 3.7188156e+10 | J45: =B45+D45+F45+H45 -> 3.7188156e+10
A46: Sumur Bor | B46: ='Disclosure Aset'!K11 -> 445059500 | J46: =B46+D46+F46+H46 -> 445059500
A47: Sarana dan Prasarana | B47: ='Disclosure Aset'!K12 -> 6200217370 | J47: =B47+D47+F47+H47 -> 6200217370
A48: Mesin | B48: ='Disclosure Aset'!K13 -> 3.7618136e+10 | J48: =B48+D48+F48+H48 -> 3.7618136e+10
A49: Instalasi Elektrik | B49: ='Disclosure Aset'!K14 -> 1452280000 | J49: =B49+D49+F49+H49 -> 1452280000
A50: Kendaraan | B50: ='Disclosure Aset'!K15 -> 8462660000 | J50: =B50+D50+F50+H50 -> 8462660000
A51: Peralatan dan Perlengkapan | B51: ='Disclosure Aset'!K16 -> 1303269796 | J51: =B51+D51+F51+H51 -> 1303269796
A52: Infrastruktur | B52: ='Disclosure Aset'!K17 -> 1.1170379e+10 | J52: =B52+D52+F52+H52 -> 1.1170379e+10
A54: Sub-Jumlah | B54: =SUM(B44:B52) -> 1.0384016e+11 | D54: =SUM(D44:D52) -> 0 | F54: =SUM(F44:F52) -> 0 | H54: =SUM(H45:H52) -> 0 | J54: =SUM(J44:J52) -> 1.0384016e+11
A56: Aset Tetap Dalam Pembangunan | F56: 0 | H56: 0 | J56: =B56+D56-F56+H56 -> 0
A58: Jumlah | B58: =B54+B56 -> 1.0384016e+11 | D58: =D54+D56 -> 0 | F58: =F54+F56 -> 0 | H58: =SUM(H49:H56) -> 0 | J58: =J54+J56 -> 1.0384016e+11
B59: =B40 -> 45536
A60: Akumulasi Penyusutan
A61: Bangunan | B61: ='Disclosure Aset'!K26 -> 1.1072665e+10 | D61: ='2. Bangunan'!AT115 -> 1.3952801e+09 | J61: =B61+D61+F61+H61 -> 1.2467945e+10 | K61: -11227696407 | L61: =J61+K61 -> 1.240249e+09 | N61: 155031125 | O61: =D61-N61 -> 1.240249e+09 | P61: 1.3952801e+09 | Q61: =D61-P61 -> 0 | R61: -1.2467945e+10 | S61: =J61+R61 -> 0
A62: Sumur Bor | B62: ='Disclosure Aset'!K27 -> 412066000 | D62: ='3. Sumur Bor'!AT40 -> 6427453.1 | J62: =B62+D62+F62+H62 -> 4.1849345e+08 | K62: -417779292 | L62: =J62+K62 -> 714161.12 | N62: 5713291 | O62: =D62-N62 -> 714162.12 | P62: 6427453 | Q62: =D62-P62 -> 0.125 | R62: -4.1849345e+08 | S62: =J62+R62 -> -0.375
A63: Sarana dan Prasarana | B63: ='Disclosure Aset'!K28 -> 3.7454524e+09 | D63: ='4. Sarana & Prasarana'!AT29 -> 2.3013422e+08 | J63: =B63+D63+F63+H63 -> 3.9755866e+09 | K63: -3771022839 | L63: =J63+K63 -> 2.0456375e+08 | N63: 25570469 | O63: =D63-N63 -> 2.0456375e+08 | P63: 2.3013422e+08 | Q63: =D63-P63 -> 4.7683716e-07 | R63: -3.9755866e+09 | S63: =J63+R63 -> 0
A64: Mesin | B64: ='Disclosure Aset'!K29 -> 2.1363854e+10 | D64: ='5. Mesin'!AS315 -> 1.7730099e+09 | J64: =B64+D64+F64+H64 -> 2.3136864e+10 | K64: -21562885847 | L64: =J64+K64 -> 1.5739785e+09 | N64: 199031396 | O64: =D64-N64 -> 1.5739785e+09 | P64: 1.7730099e+09 | Q64: =D64-P64 -> 0.15833879 | R64: -2.3136864e+10 | S64: =J64+R64 -> 0
A65: Instalasi Elektrik | B65: ='Disclosure Aset'!K30 -> 469792000 | D65: ='6. Instalasi Elektrik'!AS43 -> 54460500 | J65: =B65+D65+F65+H65 -> 524252500 | K65: -475843167 | L65: =J65+K65 -> 48409333 | N65: 6051167 | O65: =D65-N65 -> 48409333 | P65: 54460500 | Q65: =D65-P65 -> 0 | R65: -524252500 | S65: =J65+R65 -> 0
A66: Kendaraan | B66: ='Disclosure Aset'!K31 -> 8.32891e+09 | D66: ='7. Kendaraan'!AS69 -> 32812500 | J66: =B66+D66+F66+H66 -> 8.3617225e+09 | K66: -8332555834 | L66: =J66+K66 -> 29166666 | N66: 3645834 | O66: =D66-N66 -> 29166666 | P66: 32812500 | Q66: =D66-P66 -> 0 | R66: -8361722500 | S66: =J66+R66 -> 0.5
A67: Peralatan dan Perlengkapan | B67: ='Disclosure Aset'!K32 -> 1.2387915e+09 | D67: ='8 Peralatan & Perlengkapan'!AS149 -> 18238396 | J67: =B67+D67+F67+H67 -> 1257029921 | K67: -1240977192 | L67: =J67+K67 -> 16052729 | N67: 2185667 | O67: =D67-N67 -> 16052729 | P67: 18238396 | Q67: =D67-P67 -> -0.46666662 | R67: -1257029921 | S67: =J67+R67 -> 0
A68: Infrastruktur | B68: ='Disclosure Aset'!K33 -> 1.0397886e+10 | D68: ='9. Infrastruktur'!AS50 -> 4.4661061e+08 | J68: =B68+D68+F68+H68 -> 1.0844497e+10 | K68: -10447509479 | L68: =J68+K68 -> 3.9698721e+08 | N68: 49623401 | O68: =D68-N68 -> 3.9698721e+08 | P68: 446610609 | Q68: =D68-P68 -> 0.28125 | R68: -1.0844497e+10 | S68: =J68+R68 -> 0.53125
A70: Jumlah | B70: =SUM(B61:B69) -> 5.7029418e+10 | D70: =SUM(D61:D69) -> 3.9569738e+09 | F70: =SUM(F61:F69) -> 0 | H70: =SUM(H61:H69) -> 0 | J70: =SUM(J61:J69) -> 6.0986391e+10
A72: Nilai Buku | B72: =B58-B70 -> 4.6810741e+10 | J72: =J58-J70 -> 4.2853767e+10
B77: WS
B78: 45170
B79: Saldo Awal | D79: Penambahan | F79: Pengurangan | H79: Reklasifikasi | J79: Saldo Akhir
A81: Nilai Perolehan
A82: Tanah | B82: 0 | J82: =B82+D82+F82+H82 -> 0
A83: Bangunan | B83: 3.7188156e+10 | J83: =B83+D83+F83+H83 -> 3.7188156e+10
A84: Sumur Bor | B84: 445059500 | J84: =B84+D84+F84+H84 -> 445059500
A85: Sarana dan Prasarana | B85: 6200217370 | J85: =B85+D85+F85+H85 -> 6200217370
A86: Mesin | B86: 3.7618136e+10 | J86: =B86+D86+F86+H86 -> 3.7618136e+10
A87: Instalasi Elektrik | B87: 1452280000 | J87: =B87+D87+F87+H87 -> 1452280000
A88: Kendaraan | B88: 8342660000 | D88: ='7. Kendaraan'!F82 -> 120000000 | J88: =B88+D88+F88+H88 -> 8462660000
A89: Peralatan dan Perlengkapan | B89: 1274154796 | D89: ='8 Peralatan & Perlengkapan'!F162 -> 29115000 | J89: =B89+D89+F89+H89 -> 1303269796
A90: Infrastruktur | B90: 1.1170379e+10 | J90: =B90+D90+F90+H90 -> 1.1170379e+10
A92: Sub-Jumlah | B92: =SUM(B82:B90) -> 1.0369104e+11 | D92: =SUM(D82:D90) -> 149115000 | F92: =SUM(F82:F90) -> 0 | H92: =SUM(H83:H90) -> 0 | I92: =SUM(I83:I90) -> 0 | J92: =SUM(J82:J90) -> 1.0384016e+11
A94: Aset Tetap Dalam Pembangunan | B94: =J132 -> 0 | F94: 0 | H94: 0 | J94: =B94+D94-F94+H94 -> 0
A96: Jumlah | B96: =B92+B94 -> 1.0369104e+11 | D96: =D92+D94 -> 149115000 | F96: =F92+F94 -> 0 | H96: =SUM(H87:H94) -> 0 | I96: =SUM(I87:I94) -> 0 | J96: =J92+J94 -> 1.0384016e+11
B98: =B78 -> 45170
A99: Akumulasi Penyusutan
A100: Bangunan | B100: 9.2122918e+09 | D100: ='2. Bangunan'!AN115 -> 1.3952801e+09 | F100: 0 | H100: 0 | J100: =B100+D100+F100+H100 -> 1.0607572e+10 | P100: -10607571905 | Q100: =J100+P100 -> -0.13378906 | R100: 1.3952801e+09 | S100: =D100-R100 -> 0
A101: Sumur Bor | B101: 3.5855856e+08 | D101: ='3. Sumur Bor'!AN40 -> 40130578 | F101: 0 | J101: =B101+D101+F101+H101 -> 3.9868914e+08 | P101: -398689141 | Q101: =J101+P101 -> -0.375 | R101: 40130577 | S101: =D101-R101 -> 1.125
A102: Sarana dan Prasarana | B102: 3.3669626e+09 | D102: ='4. Sarana & Prasarana'!AN29 -> 2.8386731e+08 | F102: 0 | J102: =B102+D102+F102+H102 -> 3.6508299e+09 | P102: -3650829932 | Q102: =J102+P102 -> 0.49999952 | R102: 283867312 | S102: =D102-R102 -> 0.5
A103: Mesin | B103: 1.8146072e+10 | D103: ='5. Mesin'!AM315 -> 2.4014635e+09 | F103: 0 | J103: =B103+D103+F103+H103 -> 2.0547536e+10 | P103: -20547535712 | Q103: =J103+P103 -> -0.030216217 | R103: 2401463530 | S103: =D103-R103 -> -0.16354322
A104: Instalasi Elektrik | B104: 397178000 | D104: ='6. Instalasi Elektrik'!AM43 -> 54460500 | F104: 0 | J104: =B104+D104+F104+H104 -> 451638500 | P104: -451638500 | Q104: =J104+P104 -> 0 | R104: 54460503 | S104: =D104-R104 -> -3
A105: Kendaraan | B105: 7346435000 | D105: ='7. Kendaraan'!AM69 -> 736856250 | F105: 0 | H105: 0 | J105: =B105+D105+F105+H105 -> 8083291250 | P105: -8083291250 | Q105: =J105+P105 -> 0 | R105: 736856250 | S105: =D105-R105 -> 0
A106: Peralatan dan Perlengkapan | B106: 1.1746927e+09 | D106: ='8 Peralatan & Perlengkapan'!AM149 -> 56870177 | F106: 0 | H106: 0 | J106: =B106+D106+F106+H106 -> 1.2315629e+09 | P106: -1231562859 | Q106: =J106+P106 -> -0.5 | R106: 56870177 | S106: =D106-R106 -> 0.20833334
A107: Infrastruktur | B107: 9.0731326e+09 | D107: ='9. Infrastruktur'!AM50 -> 9.9356512e+08 | F107: 0 | H107: 0 | J107: =B107+D107+F107+H107 -> 1.0066698e+10 | P107: -10066697705 | Q107: =J107+P107 -> 0.049999237 | R107: 993565120 | S107: =D107-R107 -> -0.10000002
A109: Jumlah | B109: =SUM(B100:B108) -> 4.9075323e+10 | D109: =SUM(D100:D108) -> 5.9624936e+09 | F109: =SUM(F100:F108) -> 0 | H109: =SUM(H100:H108) -> 0 | J109: =SUM(J100:J108) -> 5.5037817e+10
A111: Nilai Buku | B111: =B96-B109 -> 5.461572e+10 | J111: =J96-J109 -> 4.8802342e+10

Sheet 1. Tanah
A1: No | B1: Fixed Asset | C1: Tahun | D1: Harga | E1: Total
C2: Perolehan | D2: Perolehan
A3: Tanah Cold Storage
A4: 1 | B4: Tanah Divisi Cold Storage 1 | C4: 2002 | D4: =AT!K13 -> 655809273
A5: 2 | B5: Tanah Divisi Cold Storage 2 | C5: 2002 | D5: =AT!K14 -> 200000000
A6: 3 | B6: Tanah SHM NO.776,777,778 | C6: 2002 | D6: =AT!K15 -> 226850626
E7: =SUM(D4:D6)*0 -> 0 | F7: Uang ISP
A8: Tanah Gebang
A9: 1 | B9: Tanah Gebang | C9: 2005 | D9: 2538567500
E10: =D9*0 -> 0 | F10: Uang ISP
A11: Tanah Holding
A12: 1 | B12: Tanah Divisi Holding | C12: 2008 | D12: 1533972000
A13: 2 | B13: Tanah Divisi Maringgai | C13: 2002 | D13: 202373350
E14: =SUM(D12:D13)*0 -> 0 | F14: Uang ISP
A15: Tanah Ketapang
A16: 1 | B16: Tanah Divisi Ketapang | C16: 2002 | D16: =3436245000*0 -> 0
E17: =D16 -> 0 | G17: Audit 2021
E18: =SUM(E7:E17) -> 0 | G18: =AT!K35 -> 8793817749
C19: Aset Hak Guna | D19: =SUM(D4:D6)+SUM(D9)+SUM(D12:D13) -> 5357572749
A23: SHM
A25: 1. | B25: Coldstorage
B26: Jenis | C26: No | D26: Tanggal Sertifikat | E26: Luas (M2) | G26: Lokasi | H26: Sisa Luas (M2) | I26: Keterangan
B27: Hak Milik | C27: 112 | D27: 32483 | E27: 14215 | F27: Usman Saleh | G27: Ds. Sukanegara Kec. Tanjung Bintang Lampung Selatan
B28: Hak Milik | C28: 151 | D28: 33436 | E28: 8250 | F28: Usman Saleh | G28: Ds. Sukanegara Kec. Tanjung Bintang Lampung Selatan
B29: Hak Milik | C29: 197 | D29: 34967 | E29: 15912 | F29: Usman Saleh | G29: Ds. Sukanegara Kec. Tanjung Bintang Lampung Selatan
B30: Hak Milik | C30: 244 | D30: 36781 | E30: =E32+H32 -> 14838 | F30: Saimi Saleh | G30: Ds. Sukanegara Kec. Tanjung Bintang Lampung Selatan
B31: Hak Milik | C31: 244 | D31: 36781 | F31: Saimi Saleh | G31: Ds. Sukanegara Kec. Tanjung Bintang Lampung Selatan | I31: Penyesuaian Tol
B32: Hak Milik | C32: 1868 | D32: 43643 | E32: 10324 | F32: Saimi Saleh | G32: Ds. Sukanegara Kec. Tanjung Bintang Lampung Selatan | H32: 4514
B33: Hak Milik | C33: 0775 | D33: 40135 | E33: 4994 | F33: Saimi Saleh | G33: Ds. Sukanegara Kec. Tanjung Bintang Lampung Selatan
B34: Hak Milik | C34: 776 | D34: 40135 | F34: Saimi Saleh | G34: Ds. Sukanegara Kec. Tanjung Bintang Lampung Selatan | H34: 1555 | I34: Penyesuaian Tol
B35: Hak Milik | C35: 01870 | D35: 43643 | E35: 5941 | F35: Saimi Saleh | G35: Ds. Sukanegara Kec. Tanjung Bintang Lampung Selatan
B36: Hak Milik | C36: 776 | D36: 40135 | E36: =E35+H34 -> 7496 | F36: Saimi Saleh | G36: Ds. Sukanegara Kec. Tanjung Bintang Lampung Selatan
B37: Hak Milik | C37: 0777 | D37: 40135 | E37: 15635 | F37: Saimi Saleh | G37: Ds. Sukanegara Kec. Tanjung Bintang Lampung Selatan
B38: Hak Milik | C38: 0777 | D38: 40135 | E38: 15108 | F38: Saimi Saleh | G38: Ds. Sukanegara Kec. Tanjung Bintang Lampung Selatan | H38: 527 | I38: Penyesuaian Tol
B39: Hak Milik | C39: 01867 | D39: 43643 | E39: 527 | F39: Saimi Saleh | G39: Ds. Sukanegara Kec. Tanjung Bintang Lampung Selatan
B40: Hak Milik | C40: 0778 | D40: 40135 | E40: =E41+E42 -> 17242 | F40: Saimi Saleh | G40: Ds. Sukanegara Kec. Tanjung Bintang Lampung Selatan
B41: Hak Milik | C41: 0778 | D41: 40135 | E41: 4014 | F41: Saimi Saleh | G41: Ds. Sukanegara Kec. Tanjung Bintang Lampung Selatan
B42: Hak Milik | C42: 01869 | D42: 43643 | E42: 13228 | F42: Saimi Saleh | G42: Ds. Sukanegara Kec. Tanjung Bintang Lampung Selatan
A44: 2. | B44: Tambak Gebang
B45: Jenis | C45: No | D45: Tanggal Sertifikat | E45: Luas (M2) | G45: Lokasi | H45: Sisa Luas (M2) | I45: Keterangan
B46: Hak Milik | C46: 162 | D46: 38651 | E46: 100000 | F46: Ishak Saleh | G46: Ds. Gebang Kec. Padang Cermin Lampung Selatan
B47: Hak Milik | C47: 175 | D47: 38842 | E47: 19485 | F47: Saimi Saleh | G47: Ds. Gebang Kec. Padang Cermin Lampung Selatan
B48: Hak Milik | C48: 176 | D48: 38842 | E48: 20000 | F48: Saimi Saleh | G48: Ds. Gebang Kec. Padang Cermin Lampung Selatan
B49: Hak Milik | C49: 36 | D49: 29824 | E49: 60000 | F49: Ishak Saleh | G49: Ds. Gebang Kec. Padang Cermin Lampung Selatan
B50: Hak Milik | C50: 153 | D50: 38384 | E50: 20000 | F50: Ir. Bahar | G50: Ds. Gebang Kec. Padang Cermin Lampung Selatan
B51: Hak Milik | C51: 154 | D51: 38384 | E51: 20000 | F51: Ir. Bahar | G51: Ds. Gebang Kec. Padang Cermin Lampung Selatan
B52: Hak Milik | C52: 155 | D52: 38384 | E52: 19500 | F52: Ishak Saleh | G52: Ds. Gebang Kec. Padang Cermin Lampung Selatan
B53: Hak Milik | C53: 156 | D53: 38384 | E53: 12770 | F53: Ismit Saleh | G53: Ds. Gebang Kec. Padang Cermin Lampung Selatan
B54: Hak Milik | C54: 157 | D54: 38384 | E54: 11070 | F54: Ir. Bahar | G54: Ds. Gebang Kec. Padang Cermin Lampung Selatan
B55: Hak Milik | C55: 158 | D55: 38397 | E55: 10290 | F55: Ishak Saleh | G55: Ds. Gebang Kec. Padang Cermin Lampung Selatan
B56: Hak Milik | C56: 159 | D56: 38651 | E56: 29080 | F56: Usman Saleh | G56: Ds. Gebang Kec. Padang Cermin Lampung Selatan
B57: Hak Milik | C57: 160 | D57: 38651 | E57: 43400 | F57: Usman Saleh | G57: Ds. Gebang Kec. Padang Cermin Lampung Selatan
... B62: Hak Milik | C62: 178 | D62: 38840 | E62: 20000 | F62: Usman Saleh | G62: Ds. Gebang Kec. Padang Cermin Lampung Selatan
A64: 2. | B64: Tambak Ketapang
B65: Jenis | C65: No | D65: Tanggal Sertifikat | E65: Luas (M2) | G65: Lokasi | H65: Sisa Luas (M2) | I65: Keterangan
B66: Hak Milik | C66: 14 | D66: 40001 | E66: 14961 | F66: Ishak Saleh | G66: Ds. Sumber Nadi Kec. Ketapang Lampung Selatan
B67: Hak Milik | C67: 23 | D67: 40001 | E67: 20000 | F67: Rico Damona Usman | G67: Ds. Sumber Nadi Kec. Ketapang Lampung Selatan
B68: Hak Milik | C68: 32 | D68: 40001 | E68: 4988 | F68: Ismit Saleh | G68: Ds. Sumber Nadi Kec. Ketapang Lampung Selatan
B69: Hak Milik | C69: 40 | D69: 40001 | E69: 20000 | F69: Rima Rahmawati | G69: Ds. Sumber Nadi Kec. Ketapang Lampung Selatan
B70: Hak Milik | C70: 47 | D70: 40001 | E70: 20000 | F70: Sustinah | G70: Ds. Sumber Nadi Kec. Ketapang Lampung Selatan
B71: Hak Milik | C71: 56 | D71: 40001 | E71: 19999 | F71: Yusnaya Adisti | G71: Ds. Sumber Nadi Kec. Ketapang Lampung Selatan
B72: Hak Milik | C72: 63 | D72: 40001 | E72: 19999 | F72: Yubahar | G72: Ds. Sumber Nadi Kec. Ketapang Lampung Selatan
B73: Hak Milik | C73: 71 | D73: 40001 | E73: 15961 | F73: Usman Saleh | G73: Ds. Sumber Nadi Kec. Ketapang Lampung Selatan
B74: Hak Milik | C74: 80 | D74: 40001 | E74: 14869 | F74: Usman Saleh | G74: Ds. Sumber Nadi Kec. Ketapang Lampung Selatan
B75: Hak Milik | C75: 88 | D75: 40001 | E75: 19999 | F75: Sustinah | G75: Ds. Sumber Nadi Kec. Ketapang Lampung Selatan

Sheet 2. Bangunan
B1: Perubahan umur Ekonomis
B2: Gabung
A3: No | B3: Fixed Asset | C3: Tahun | D3: Umur | E3: Harga | F3: Penyusutan | G3: Penambahan Aset | H3: TOTAL PENYUSUTAN TAHUN 2014 | I3: AK . PENY | J3: NILAI BUKU | K3: TOTAL PENYUSUTAN TAHUN 2015 | L3: AK . PENY | M3: NILAI BUKU | N3: TOTAL PENYUSUTAN TAHUN 2016 | O3: AK . PENY | P3: NILAI BUKU | Q3: TOTAL PENYUSUTAN TAHUN 2017 | R3: AK . PENY | S3: NILAI BUKU | T3: TOTAL PENYUSUTAN TAHUN 2018 | U3: AK . PENY | V3: NILAI BUKU | W3: TOTAL PENY 2019 | X3: AK . PENY | Y3: NILAI BUKU | Z3: SPT BADAN | AA3: SPT BADAN | AB3: TOTAL PENY 2020 | AC3: AK . PENY | AD3: NILAI BUKU | AE3: TOTAL PENY 2021 | AF3: AK . PENY | AG3: NILAI BUKU | AH3: TOTAL PENY 2022 | AI3: AK . PENY | AJ3: NILAI BUKU | AK3: TOTAL PENY JAN 2023 | AL3: AK . PENY | AM3: NILAI BUKU | AN3: TOTAL PENY SEPT 2023 | AO3: AK . PENY | AP3: NILAI BUKU | AQ3: TOTAL PENY 2023 | AR3: AK . PENY | AS3: NILAI BUKU | AT3: TOTAL PENY SEPT 2024 | AU3: AK . PENY | AV3: NILAI BUKU | AW3: TOTAL PENY 2024 | AX3: AK . PENY | AY3: NILAI BUKU
C4: Perolehan | D4: Ekonomis | E4: Perolehan | F4: Pertahun | G4: 2005-2014 | I4: S/D TH 2014 | J4: AKHIR 2014 | L4: S/D TH 2015 | M4: AKHIR 2015 | O4: S/D TH 2016 | P4: AKHIR 2016 | R4: S/D TH 2017 | S4: AKHIR 2017 | U4: S/D TH 2018 | V4: AKHIR 2018 | X4: S/D TH 2019 | Y4: AKHIR 2019 | Z4: Akm Peny 2019 | AA4: NBV 2019 | AC4: S/D TH 2020 | AD4: AKHIR 2020 | AF4: S/D TH 2021 | AG4: AKHIR 2021 | AI4: S/D TH 2022 | AJ4: AKHIR 2022 | AL4: S/D TH JAN 2023 | AM4: AKHIR JAN 2023 | AO4: S/D TH SEPT 2023 | AP4: AKHIR SEPT 2023 | AR4: S/D TH 2023 | AS4: AKHIR 2023 | AU4: S/D TH SEPT 2024 | AV4: AKHIR SEPT 2024 | AX4: S/D TH 2024 | AY4: AKHIR 2024
A5: Bangunan Cold Storage | BD5: 3926666.7 | BE5: =AG5-BD5 -> -3926666.7
A6: 1.1 | B6: Divisi ISP 1 | BD6: 13309392 | BE6: =AG6-BD6 -> -13309392 | BF6: =F6/12 -> 0 | BG6: =BE6-BF6 -> -13309392
A7: 1 | B7: Bangunan ISP 1 | C7: 38353 | D7: 20 | E7: 5564855579 | F7: =E7/D7 -> 2.7824278e+08 | G7: =E7 -> 5564855579 | I7: =H7 -> 0 | J7: =G7-I7 -> 5564855579 | L7: =I7+K7 -> 0 | M7: =E7-L7 -> 5564855579 | N7: =(F7/12)*12 -> 2.7824278e+08 | O7: =N7+L7 -> 2.7824278e+08 | P7: =E7-O7 -> 5.2866128e+09 | Q7: =(F7/12)*12 -> 2.7824278e+08 | R7: =Q7+O7 -> 5.5648556e+08 | S7: =E7-R7 -> 5.00837e+09 | T7: =(F7/12)*12 -> 2.7824278e+08 | U7: =R7+T7 -> 8.3472834e+08 | V7: =E7-U7 -> 4.7301272e+09 | W7: =(F7/12)*12 -> 2.7824278e+08 | X7: =U7+W7 -> 1.1129711e+09 | Y7: =E7-X7 -> 4.4518845e+09 | Z7: 1.0869302e+09 | AA7: =E7-Z7 -> 4.4779254e+09 | AB7: =(F7/12)*12 -> 2.7824278e+08 | AC7: =X7+AB7 -> 1.3912139e+09 | AD7: =E7-AC7 -> 4.1736417e+09 | AE7: =(F7/12)*12 -> 2.7824278e+08 | AF7: =AC7+AE7 -> 1.6694567e+09 | AG7: =E7-AF7 -> 3.8953989e+09 | AH7: =(F7/12)*12 -> 2.7824278e+08 | AI7: =AF7+AH7 -> 1.9476995e+09 | AJ7: =E7-AI7 -> 3.6171561e+09 | AK7: =(F7/12)*1 -> 23186898 | AL7: =AI7+AK7 -> 1.9708864e+09 | AM7: =E7-AL7 -> 3.5939692e+09 | AN7: =(F7/12)*9 -> 2.0868208e+08 | AO7: =AI7+AN7 -> 2.1563815e+09 | AP7: =E7-AO7 -> 3.408474e+09 | AQ7: =(F7/12)*12 -> 2.7824278e+08 | AR7: =AI7+AQ7 -> 2.2259422e+09 | AS7: =E7-AR7 -> 3.3389133e+09 | AT7: =(F7/12)*9 -> 2.0868208e+08 | AU7: =AR7+AT7 -> 2.4346243e+09 | AV7: =E7-AU7 -> 3.1302313e+09 | AW7: =(F7/12)*12 -> 2.7824278e+08 | AX7: =AR7+AW7 -> 2.504185e+09 | AY7: =E7-AX7 -> 3.0606706e+09 | BB7: =E7-AX7-AY7 -> 0
A8: =A7+1 -> 2 | B8: Bangunan Pos Satpam | C8: 38353 | D8: 20 | E8: 39450000 | F8: =E8/D8 -> 1972500 | G8: =E8 -> 39450000 | I8: =H8 -> 0 | J8: =G8-I8 -> 39450000 | L8: =I8+K8 -> 0 | M8: =E8-L8 -> 39450000 | N8: =(F8/12)*12 -> 1972500 | O8: =N8+L8 -> 1972500 | P8: =E8-O8 -> 37477500 | Q8: =(F8/12)*12 -> 1972500 | R8: =Q8+O8 -> 3945000 | S8: =E8-R8 -> 35505000 | T8: =(F8/12)*12 -> 1972500 | U8: =R8+T8 -> 5917500 | V8: =E8-U8 -> 33532500 | W8: =(F8/12)*12 -> 1972500 | X8: =U8+W8 -> 7890000 | Y8: =E8-X8 -> 31560000 | Z8: 7890000 | AA8: =E8-Z8 -> 31560000 | AB8: =(F8/12)*12 -> 1972500 | AC8: =X8+AB8 -> 9862500 | AD8: =E8-AC8 -> 29587500 | AE8: =(F8/12)*12 -> 1972500 | AF8: =AC8+AE8 -> 11835000 | AG8: =E8-AF8 -> 27615000 | AH8: =(F8/12)*12 -> 1972500 | AI8: =AF8+AH8 -> 13807500 | AJ8: =E8-AI8 -> 25642500 | AK8: =(F8/12)*1 -> 164375 | AL8: =AI8+AK8 -> 13971875 | AM8: =E8-AL8 -> 25478125 | AN8: =(F8/12)*9 -> 1479375 | AO8: =AI8+AN8 -> 15286875 | AP8: =E8-AO8 -> 24163125 | AQ8: =(F8/12)*12 -> 1972500 | AR8: =AI8+AQ8 -> 15780000 | AS8: =E8-AR8 -> 23670000 | AT8: =(F8/12)*9 -> 1479375 | AU8: =AR8+AT8 -> 17259375 | AV8: =E8-AU8 -> 22190625 | AW8: =(F8/12)*12 -> 1972500 | AX8: =AR8+AW8 -> 17752500 | AY8: =E8-AX8 -> 21697500 | BB8: =E8-AX8-AY8 -> 0
A9: =A8+1 -> 3 | B9: Bangunan Genset | C9: 38353 | D9: 20 | E9: 742420000 | F9: =E9/D9 -> 37121000 | G9: =E9 -> 742420000 | I9: =H9 -> 0 | J9: =G9-I9 -> 742420000 | L9: =I9+K9 -> 0 | M9: =E9-L9 -> 742420000 | N9: =(F9/12)*12 -> 37121000 | O9: =N9+L9 -> 37121000 | P9: =E9-O9 -> 705299000 | Q9: =(F9/12)*12 -> 37121000 | R9: =Q9+O9 -> 74242000 | S9: =E9-R9 -> 668178000 | T9: =(F9/12)*12 -> 37121000 | U9: =R9+T9 -> 111363000 | V9: =E9-U9 -> 631057000 | W9: =(F9/12)*12 -> 37121000 | X9: =U9+W9 -> 148484000 | Y9: =E9-X9 -> 593936000 | Z9: 148484000 | AA9: =E9-Z9 -> 593936000 | AB9: =(F9/12)*12 -> 37121000 | AC9: =X9+AB9 -> 185605000 | AD9: =E9-AC9 -> 556815000 | AE9: =(F9/12)*12 -> 37121000 | AF9: =AC9+AE9 -> 222726000 | AG9: =E9-AF9 -> 519694000 | AH9: =(F9/12)*12 -> 37121000 | AI9: =AF9+AH9 -> 259847000 | AJ9: =E9-AI9 -> 482573000 | AK9: =(F9/12)*1 -> 3093416.7 | AL9: =AI9+AK9 -> 2.6294042e+08 | AM9: =E9-AL9 -> 4.7947958e+08 | AN9: =(F9/12)*9 -> 27840750 | AO9: =AI9+AN9 -> 287687750 | AP9: =E9-AO9 -> 454732250 | AQ9: =(F9/12)*12 -> 37121000 | AR9: =AI9+AQ9 -> 296968000 | AS9: =E9-AR9 -> 445452000 | AT9: =(F9/12)*9 -> 27840750 | AU9: =AR9+AT9 -> 324808750 | AV9: =E9-AU9 -> 417611250 | AW9: =(F9/12)*12 -> 37121000 | AX9: =AR9+AW9 -> 334089000 | AY9: =E9-AX9 -> 408331000 | BB9: =E9-AX9-AY9 -> 0
A10: =A9+1 -> 4 | B10: KM/WC | C10: 38353 | D10: 20 | E10: =8100000*0 -> 0 | F10: =E10/D10 -> 0 | G10: =E10 -> 0 | H10: =((F10/12)*(13-IF(C10="","",MONTH(C10))))*10 -> 0 | I10: =H10 -> 0 | J10: =G10-I10 -> 0 | K10: =(F10/12)*12 -> 0 | L10: =I10+K10 -> 0 | M10: =E10-L10 -> 0 | N10: =(F10/12)*12 -> 0 | O10: =N10+L10 -> 0 | P10: =E10-O10 -> 0 | Q10: =(F10/12)*12 -> 0 | R10: =Q10+O10 -> 0 | S10: =E10-R10 -> 0 | T10: =(F10/12)*12 -> 0 | U10: =R10+T10 -> 0 | V10: =E10-U10 -> 0 | W10: =(F10/12)*12 -> 0 | X10: =U10+W10 -> 0 | Y10: =E10-X10 -> 0 | Z10: =1620000*0 -> 0 | AA10: =E10-Z10 -> 0 | AB10: =(F10/12)*12 -> 0 | AC10: =Z10+AB10 -> 0 | AD10: =E10-AC10 -> 0 | AE10: =(F10/12)*12 -> 0 | AF10: =AC10+AE10 -> 0 | AG10: =E10-AF10 -> 0 | AH10: =(F10/12)*12 -> 0 | AI10: =AF10+AH10 -> 0 | AJ10: =E10-AI10 -> 0 | AQ10: =(F10/12)*7 -> 0 | AR10: =AI10+AQ10 -> 0 | AS10: =E10-AR10 -> 0 | BB10: =E10-AR10-AS10 -> 0
A11: =A10+1 -> 5 | B11: Kantor 1 | C11: 38718 | D11: 20 | E11: 203210000 | F11: =E11/D11 -> 10160500 | G11: =E11 -> 203210000 | I11: =H11 -> 0 | J11: =G11-I11 -> 203210000 | L11: =I11+K11 -> 0 | M11: =E11-L11 -> 203210000 | N11: =(F11/12)*12 -> 10160500 | O11: =N11+L11 -> 10160500 | P11: =E11-O11 -> 193049500 | Q11: =(F11/12)*12 -> 10160500 | R11: =Q11+O11 -> 20321000 | S11: =E11-R11 -> 182889000 | T11: =(F11/12)*12 -> 10160500 | U11: =R11+T11 -> 30481500 | V11: =E11-U11 -> 172728500 | W11: =(F11/12)*12 -> 10160500 | X11: =U11+W11 -> 40642000 | Y11: =E11-X11 -> 162568000 | Z11: 40642000 | AA11: =E11-Z11 -> 162568000 | AB11: =(F11/12)*12 -> 10160500 | AC11: =X11+AB11 -> 50802500 | AD11: =E11-AC11 -> 152407500 | AE11: =(F11/12)*12 -> 10160500 | AF11: =AC11+AE11 -> 60963000 | AG11: =E11-AF11 -> 142247000 | AH11: =(F11/12)*12 -> 10160500 | AI11: =AF11+AH11 -> 71123500 | AJ11: =E11-AI11 -> 132086500 | AK11: =(F11/12)*1 -> 846708.33 | AL11: =AI11+AK11 -> 71970208 | AM11: =E11-AL11 -> 1.3123979e+08 | AN11: =(F11/12)*9 -> 7620375 | AO11: =AI11+AN11 -> 78743875 | AP11: =E11-AO11 -> 124466125 | AQ11: =(F11/12)*12 -> 10160500 | AR11: =AI11+AQ11 -> 81284000 | AS11: =E11-AR11 -> 121926000 | AT11: =(F11/12)*9 -> 7620375 | AU11: =AR11+AT11 -> 88904375 | AV11: =E11-AU11 -> 114305625 | AW11: =(F11/12)*12 -> 10160500 | AX11: =AR11+AW11 -> 91444500 | AY11: =E11-AX11 -> 111765500 | BB11: =E11-AX11-AY11 -> 0
A12: =A11+1 -> 6 | B12: Kantin & KM/WC | C12: 40179 | D12: 20 | E12: 262080000 | F12: =E12/D12 -> 13104000 | G12: =E12 -> 262080000 | I12: =H12 -> 0 | J12: =G12-I12 -> 262080000 | L12: =I12+K12 -> 0 | M12: =E12-L12 -> 262080000 | N12: =(F12/12)*12 -> 13104000 | O12: =N12+L12 -> 13104000 | P12: =E12-O12 -> 248976000 | Q12: =(F12/12)*12 -> 13104000 | R12: =Q12+O12 -> 26208000 | S12: =E12-R12 -> 235872000 | T12: =(F12/12)*12 -> 13104000 | U12: =R12+T12 -> 39312000 | V12: =E12-U12 -> 222768000 | W12: =(F12/12)*12 -> 13104000 | X12: =U12+W12 -> 52416000 | Y12: =E12-X12 -> 209664000 | Z12: 52416000 | AA12: =E12-Z12 -> 209664000 | AB12: =(F12/12)*12 -> 13104000 | AC12: =X12+AB12 -> 65520000 | AD12: =E12-AC12 -> 196560000 | AE12: =(F12/12)*12 -> 13104000 | AF12: =AC12+AE12 -> 78624000 | AG12: =E12-AF12 -> 183456000 | AH12: =(F12/12)*12 -> 13104000 | AI12: =AF12+AH12 -> 91728000 | AJ12: =E12-AI12 -> 170352000 | AK12: =(F12/12)*1 -> 1092000 | AL12: =AI12+AK12 -> 92820000 | AM12: =E12-AL12 -> 169260000 | AN12: =(F12/12)*9 -> 9828000 | AO12: =AI12+AN12 -> 101556000 | AP12: =E12-AO12 -> 160524000 | AQ12: =(F12/12)*12 -> 13104000 | AR12: =AI12+AQ12 -> 104832000 | AS12: =E12-AR12 -> 157248000 | AT12: =(F12/12)*9 -> 9828000 | AU12: =AR12+AT12 -> 114660000 | AV12: =E12-AU12 -> 147420000 | AW12: =(F12/12)*12 -> 13104000 | AX12: =AR12+AW12 -> 117936000 | AY12: =E12-AX12 -> 144144000 | BB12: =E12-AX12-AY12 -> 0
A13: =A12+1 -> 7 | B13: Mushola | C13: 40179 | D13: 20 | E13: 194080000 | F13: =E13/D13 -> 9704000 | G13: =E13 -> 194080000 | I13: =H13 -> 0 | J13: =G13-I13 -> 194080000 | L13: =I13+K13 -> 0 | M13: =E13-L13 -> 194080000 | N13: =(F13/12)*12 -> 9704000 | O13: =N13+L13 -> 9704000 | P13: =E13-O13 -> 184376000 | Q13: =(F13/12)*12 -> 9704000 | R13: =Q13+O13 -> 19408000 | S13: =E13-R13 -> 174672000 | T13: =(F13/12)*12 -> 9704000 | U13: =R13+T13 -> 29112000 | V13: =E13-U13 -> 164968000 | W13: =(F13/12)*12 -> 9704000 | X13: =U13+W13 -> 38816000 | Y13: =E13-X13 -> 155264000 | Z13: 38816000 | AA13: =E13-Z13 -> 155264000 | AB13: =(F13/12)*12 -> 9704000 | AC13: =X13+AB13 -> 48520000 | AD13: =E13-AC13 -> 145560000 | AE13: =(F13/12)*12 -> 9704000 | AF13: =AC13+AE13 -> 58224000 | AG13: =E13-AF13 -> 135856000 | AH13: =(F13/12)*12 -> 9704000 | AI13: =AF13+AH13 -> 67928000 | AJ13: =E13-AI13 -> 126152000 | AK13: =(F13/12)*1 -> 808666.67 | AL13: =AI13+AK13 -> 68736667 | AM13: =E13-AL13 -> 1.2534333e+08 | AN13: =(F13/12)*9 -> 7278000 | AO13: =AI13+AN13 -> 75206000 | AP13: =E13-AO13 -> 118874000 | AQ13: =(F13/12)*12 -> 9704000 | AR13: =AI13+AQ13 -> 77632000 | AS13: =E13-AR13 -> 116448000 | AT13: =(F13/12)*9 -> 7278000 | AU13: =AR13+AT13 -> 84910000 | AV13: =E13-AU13 -> 109170000 | AW13: =(F13/12)*12 -> 9704000 | AX13: =AR13+AW13 -> 87336000 | AY13: =E13-AX13 -> 106744000 | BB13: =E13-AX13-AY13 -> 0
A14: =A13+1 -> 8 | B14: Cafetaria | C14: 40179 | D14: 20 | E14: 313090000 | F14: =E14/D14 -> 15654500 | G14: =E14 -> 313090000 | I14: =H14 -> 0 | J14: =G14-I14 -> 313090000 | L14: =I14+K14 -> 0 | M14: =E14-L14 -> 313090000 | N14: =(F14/12)*12 -> 15654500 | O14: =N14+L14 -> 15654500 | P14: =E14-O14 -> 297435500 | Q14: =(F14/12)*12 -> 15654500 | R14: =Q14+O14 -> 31309000 | S14: =E14-R14 -> 281781000 | T14: =(F14/12)*12 -> 15654500 | U14: =R14+T14 -> 46963500 | V14: =E14-U14 -> 266126500 | W14: =(F14/12)*12 -> 15654500 | X14: =U14+W14 -> 62618000 | Y14: =E14-X14 -> 250472000 | Z14: 62618000 | AA14: =E14-Z14 -> 250472000 | AB14: =(F14/12)*12 -> 15654500 | AC14: =X14+AB14 -> 78272500 | AD14: =E14-AC14 -> 234817500 | AE14: =(F14/12)*12 -> 15654500 | AF14: =AC14+AE14 -> 93927000 | AG14: =E14-AF14 -> 219163000 | AH14: =(F14/12)*12 -> 15654500 | AI14: =AF14+AH14 -> 109581500 | AJ14: =E14-AI14 -> 203508500 | AK14: =(F14/12)*1 -> 1304541.7 | AL14: =AI14+AK14 -> 1.1088604e+08 | AM14: =E14-AL14 -> 2.0220396e+08 | AN14: =(F14/12)*9 -> 11740875 | AO14: =AI14+AN14 -> 121322375 | AP14: =E14-AO14 -> 191767625 | AQ14: =(F14/12)*12 -> 15654500 | AR14: =AI14+AQ14 -> 125236000 | AS14: =E14-AR14 -> 187854000 | AT14: =(F14/12)*9 -> 11740875 | AU14: =AR14+AT14 -> 136976875 | AV14: =E14-AU14 -> 176113125 | AW14: =(F14/12)*12 -> 15654500 | AX14: =AR14+AW14 -> 140890500 | AY14: =E14-AX14 -> 172199500 | BB14: =E14-AX14-AY14 -> 0
A15: =A14+1 -> 9 | B15: Panggung Ekspor | C15: 40179 | D15: 20 | E15: 23340000 | F15: =E15/D15 -> 1167000 | G15: =E15 -> 23340000 | I15: =H15 -> 0 | J15: =G15-I15 -> 23340000 | L15: =I15+K15 -> 0 | M15: =E15-L15 -> 23340000 | N15: =(F15/12)*12 -> 1167000 | O15: =N15+L15 -> 1167000 | P15: =E15-O15 -> 22173000 | Q15: =(F15/12)*12 -> 1167000 | R15: =Q15+O15 -> 2334000 | S15: =E15-R15 -> 21006000 | T15: =(F15/12)*12 -> 1167000 | U15: =R15+T15 -> 3501000 | V15: =E15-U15 -> 19839000 | W15: =(F15/12)*12 -> 1167000 | X15: =U15+W15 -> 4668000 | Y15: =E15-X15 -> 18672000 | Z15: 4668000 | AA15: =E15-Z15 -> 18672000 | AB15: =(F15/12)*12 -> 1167000 | AC15: =X15+AB15 -> 5835000 | AD15: =E15-AC15 -> 17505000 | AE15: =(F15/12)*12 -> 1167000 | AF15: =AC15+AE15 -> 7002000 | AG15: =E15-AF15 -> 16338000 | AH15: =(F15/12)*12 -> 1167000 | AI15: =AF15+AH15 -> 8169000 | AJ15: =E15-AI15 -> 15171000 | AK15: =(F15/12)*1 -> 97250 | AL15: =AI15+AK15 -> 8266250 | AM15: =E15-AL15 -> 15073750 | AN15: =(F15/12)*9 -> 875250 | AO15: =AI15+AN15 -> 9044250 | AP15: =E15-AO15 -> 14295750 | AQ15: =(F15/12)*12 -> 1167000 | AR15: =AI15+AQ15 -> 9336000 | AS15: =E15-AR15 -> 14004000 | AT15: =(F15/12)*9 -> 875250 | AU15: =AR15+AT15 -> 10211250 | AV15: =E15-AU15 -> 13128750 | AW15: =(F15/12)*12 -> 1167000 | AX15: =AR15+AW15 -> 10503000 | AY15: =E15-AX15 -> 12837000 | BB15: =E15-AX15-AY15 -> 0
A16: =A15+1 -> 10 | B16: Bangunan Receiver | C16: 40179 | D16: 20 | E16: 66130000 | F16: =E16/D16 -> 3306500 | G16: =E16 -> 66130000 | I16: =H16 -> 0 | J16: =G16-I16 -> 66130000 | L16: =I16+K16 -> 0 | M16: =E16-L16 -> 66130000 | N16: =(F16/12)*12 -> 3306500 | O16: =N16+L16 -> 3306500 | P16: =E16-O16 -> 62823500 | Q16: =(F16/12)*12 -> 3306500 | R16: =Q16+O16 -> 6613000 | S16: =E16-R16 -> 59517000 | T16: =(F16/12)*12 -> 3306500 | U16: =R16+T16 -> 9919500 | V16: =E16-U16 -> 56210500 | W16: =(F16/12)*12 -> 3306500 | X16: =U16+W16 -> 13226000 | Y16: =E16-X16 -> 52904000 | Z16: 13226000 | AA16: =E16-Z16 -> 52904000 | AB16: =(F16/12)*12 -> 3306500 | AC16: =X16+AB16 -> 16532500 | AD16: =E16-AC16 -> 49597500 | AE16: =(F16/12)*12 -> 3306500 | AF16: =AC16+AE16 -> 19839000 | AG16: =E16-AF16 -> 46291000 | AH16: =(F16/12)*12 -> 3306500 | AI16: =AF16+AH16 -> 23145500 | AJ16: =E16-AI16 -> 42984500 | AK16: =(F16/12)*1 -> 275541.67 | AL16: =AI16+AK16 -> 23421042 | AM16: =E16-AL16 -> 42708958 | AN16: =(F16/12)*9 -> 2479875 | AO16: =AI16+AN16 -> 25625375 | AP16: =E16-AO16 -> 40504625 | AQ16: =(F16/12)*12 -> 3306500 | AR16: =AI16+AQ16 -> 26452000 | AS16: =E16-AR16 -> 39678000 | AT16: =(F16/12)*9 -> 2479875 | AU16: =AR16+AT16 -> 28931875 | AV16: =E16-AU16 -> 37198125 | AW16: =(F16/12)*12 -> 3306500 | AX16: =AR16+AW16 -> 29758500 | AY16: =E16-AX16 -> 36371500 | BB16: =E16-AX16-AY16 -> 0
A17: =A16+1 -> 11 | B17: Kantor 3 (3lt) | C17: 40179 | D17: 20 | E17: 753420000 | F17: =E17/D17 -> 37671000 | G17: =E17 -> 753420000 | I17: =H17 -> 0 | J17: =G17-I17 -> 753420000 | L17: =I17+K17 -> 0 | M17: =E17-L17 -> 753420000 | N17: =(F17/12)*12 -> 37671000 | O17: =N17+L17 -> 37671000 | P17: =E17-O17 -> 715749000 | Q17: =(F17/12)*12 -> 37671000 | R17: =Q17+O17 -> 75342000 | S17: =E17-R17 -> 678078000 | T17: =(F17/12)*12 -> 37671000 | U17: =R17+T17 -> 113013000 | V17: =E17-U17 -> 640407000 | W17: =(F17/12)*12 -> 37671000 | X17: =U17+W17 -> 150684000 | Y17: =E17-X17 -> 602736000 | Z17: 150684000 | AA17: =E17-Z17 -> 602736000 | AB17: =(F17/12)*12 -> 37671000 | AC17: =X17+AB17 -> 188355000 | AD17: =E17-AC17 -> 565065000 | AE17: =(F17/12)*12 -> 37671000 | AF17: =AC17+AE17 -> 226026000 | AG17: =E17-AF17 -> 527394000 | AH17: =(F17/12)*12 -> 37671000 | AI17: =AF17+AH17 -> 263697000 | AJ17: =E17-AI17 -> 489723000 | AK17: =(F17/12)*1 -> 3139250 | AL17: =AI17+AK17 -> 266836250 | AM17: =E17-AL17 -> 486583750 | AN17: =(F17/12)*9 -> 28253250 | AO17: =AI17+AN17 -> 291950250 | AP17: =E17-AO17 -> 461469750 | AQ17: =(F17/12)*12 -> 37671000 | AR17: =AI17+AQ17 -> 301368000 | AS17: =E17-AR17 -> 452052000 | AT17: =(F17/12)*9 -> 28253250 | AU17: =AR17+AT17 -> 329621250 | AV17: =E17-AU17 -> 423798750 | AW17: =(F17/12)*12 -> 37671000 | AX17: =AR17+AW17 -> 339039000 | AY17: =E17-AX17 -> 414381000 | BB17: =E17-AX17-AY17 -> 0
A18: =A17+1 -> 12 | B18: Parkir Terbuka | C18: 40179 | D18: 20 | E18: 73630000 | F18: =E18/D18 -> 3681500 | G18: =E18 -> 73630000 | I18: =H18 -> 0 | J18: =G18-I18 -> 73630000 | L18: =I18+K18 -> 0 | M18: =E18-L18 -> 73630000 | N18: =(F18/12)*12 -> 3681500 | O18: =N18+L18 -> 3681500 | P18: =E18-O18 -> 69948500 | Q18: =(F18/12)*12 -> 3681500 | R18: =Q18+O18 -> 7363000 | S18: =E18-R18 -> 66267000 | T18: =(F18/12)*12 -> 3681500 | U18: =R18+T18 -> 11044500 | V18: =E18-U18 -> 62585500 | W18: =(F18/12)*12 -> 3681500 | X18: =U18+W18 -> 14726000 | Y18: =E18-X18 -> 58904000 | Z18: 14726000 | AA18: =E18-Z18 -> 58904000 | AB18: =(F18/12)*12 -> 3681500 | AC18: =X18+AB18 -> 18407500 | AD18: =E18-AC18 -> 55222500 | AE18: =(F18/12)*12 -> 3681500 | AF18: =AC18+AE18 -> 22089000 | AG18: =E18-AF18 -> 51541000 | AH18: =(F18/12)*12 -> 3681500 | AI18: =AF18+AH18 -> 25770500 | AJ18: =E18-AI18 -> 47859500 | AK18: =(F18/12)*1 -> 306791.67 | AL18: =AI18+AK18 -> 26077292 | AM18: =E18-AL18 -> 47552708 | AN18: =(F18/12)*9 -> 2761125 | AO18: =AI18+AN18 -> 28531625 | AP18: =E18-AO18 -> 45098375 | AQ18: =(F18/12)*12 -> 3681500 | AR18: =AI18+AQ18 -> 29452000 | AS18: =E18-AR18 -> 44178000 | AT18: =(F18/12)*9 -> 2761125 | AU18: =AR18+AT18 -> 32213125 | AV18: =E18-AU18 -> 41416875 | AW18: =(F18/12)*12 -> 3681500 | AX18: =AR18+AW18 -> 33133500 | AY18: =E18-AX18 -> 40496500 | BB18: =E18-AX18-AY18 -> 0
A19: =A18+1 -> 13 | B19: Gudang Trafo (2 unit) | C19: 41640 | D19: 20 | E19: 50330000 | F19: =E19/D19 -> 2516500 | G19: =E19 -> 50330000 | I19: =H19 -> 0 | J19: =G19-I19 -> 50330000 | L19: =I19+K19 -> 0 | M19: =E19-L19 -> 50330000 | N19: =(F19/12)*12 -> 2516500 | O19: =N19+L19 -> 2516500 | P19: =E19-O19 -> 47813500 | Q19: =(F19/12)*12 -> 2516500 | R19: =Q19+O19 -> 5033000 | S19: =E19-R19 -> 45297000 | T19: =(F19/12)*12 -> 2516500 | U19: =R19+T19 -> 7549500 | V19: =E19-U19 -> 42780500 | W19: =(F19/12)*12 -> 2516500 | X19: =U19+W19 -> 10066000 | Y19: =E19-X19 -> 40264000 | Z19: 10066000 | AA19: =E19-Z19 -> 40264000 | AB19: =(F19/12)*12 -> 2516500 | AC19: =X19+AB19 -> 12582500 | AD19: =E19-AC19 -> 37747500 | AE19: =(F19/12)*12 -> 2516500 | AF19: =AC19+AE19 -> 15099000 | AG19: =E19-AF19 -> 35231000 | AH19: =(F19/12)*12 -> 2516500 | AI19: =AF19+AH19 -> 17615500 | AJ19: =E19-AI19 -> 32714500 | AK19: =(F19/12)*1 -> 209708.33 | AL19: =AI19+AK19 -> 17825208 | AM19: =E19-AL19 -> 32504792 | AN19: =(F19/12)*9 -> 1887375 | AO19: =AI19+AN19 -> 19502875 | AP19: =E19-AO19 -> 30827125 | AQ19: =(F19/12)*12 -> 2516500 | AR19: =AI19+AQ19 -> 20132000 | AS19: =E19-AR19 -> 30198000 | AT19: =(F19/12)*9 -> 1887375 | AU19: =AR19+AT19 -> 22019375 | AV19: =E19-AU19 -> 28310625 | AW19: =(F19/12)*12 -> 2516500 | AX19: =AR19+AW19 -> 22648500 | AY19: =E19-AX19 -> 27681500 | BB19: =E19-AX19-AY19 -> 0
A20: =A19+1 -> 14 | B20: Bangunan ATM | C20: 42005 | D20: 10 | E20: 9720000 | F20: =E20/D20 -> 972000 | J20: =G20-I20 -> 0 | K20: =(F20/12)*0 -> 0 | L20: =I20+K20 -> 0 | M20: =E20-L20 -> 9720000 | N20: =(F20/12)*12 -> 972000 | O20: =N20+L20 -> 972000 | P20: =E20-O20 -> 8748000 | Q20: =(F20/12)*12 -> 972000 | R20: =Q20+O20 -> 1944000 | S20: =E20-R20 -> 7776000 | T20: =(F20/12)*12 -> 972000 | U20: =R20+T20 -> 2916000 | V20: =E20-U20 -> 6804000 | W20: =(F20/12)*12 -> 972000 | X20: =U20+W20 -> 3888000 | Y20: =E20-X20 -> 5832000 | Z20: 1944000 | AA20: =E20-Z20 -> 7776000 | AB20: =(F20/12)*12 -> 972000 | AC20: =X20+AB20 -> 4860000 | AD20: =E20-AC20 -> 4860000 | AE20: =(F20/12)*12 -> 972000 | AF20: =AC20+AE20 -> 5832000 | AG20: =E20-AF20 -> 3888000 | AH20: =(F20/12)*12 -> 972000 | AI20: =AF20+AH20 -> 6804000 | AJ20: =E20-AI20 -> 2916000 | AK20: =(F20/12)*1 -> 81000 | AL20: =AI20+AK20 -> 6885000 | AM20: =E20-AL20 -> 2835000 | AN20: =(F20/12)*9 -> 729000 | AO20: =AI20+AN20 -> 7533000 | AP20: =E20-AO20 -> 2187000 | AQ20: =(F20/12)*12 -> 972000 | AR20: =AI20+AQ20 -> 7776000 | AS20: =E20-AR20 -> 1944000 | AT20: =(F20/12)*9 -> 729000 | AU20: =AR20+AT20 -> 8505000 | AV20: =E20-AU20 -> 1215000 | AW20: =(F20/12)*12 -> 972000 | AX20: =AR20+AW20 -> 8748000 | AY20: =E20-AX20 -> 972000 | BB20: =E20-AX20-AY20 -> 0
A21: =A20+1 -> 15 | B21: Bangunan Baru | C21: 43708 | D21: 20 | E21: 3.9492779e+09 | F21: =E21/D21 -> 1.9746389e+08 | J21: =G21-I21 -> 0 | O21: =N21+L21 -> 0 | W21: =(F21/12)*5 -> 82276622 | X21: =U21+W21 -> 82276622 | Y21: =E21-X21 -> 3.8670012e+09 | Z21: 65821298 | AA21: =E21-Z21 -> 3.8834566e+09 | AB21: =(F21/12)*12 -> 1.9746389e+08 | AC21: =X21+AB21 -> 2.7974052e+08 | AD21: =E21-AC21 -> 3.6695373e+09 | AE21: =(F21/12)*12 -> 1.9746389e+08 | AF21: =AC21+AE21 -> 4.7720441e+08 | AG21: =E21-AF21 -> 3.4720735e+09 | AH21: =(F21/12)*12 -> 1.9746389e+08 | AI21: =AF21+AH21 -> 6.746683e+08 | AJ21: =E21-AI21 -> 3.2746096e+09 | AK21: =(F21/12)*1 -> 16455324 | AL21: =AI21+AK21 -> 6.9112363e+08 | AM21: =E21-AL21 -> 3.2581542e+09 | AN21: =(F21/12)*9 -> 1.4809792e+08 | AO21: =AI21+AN21 -> 8.2276622e+08 | AP21: =E21-AO21 -> 3.1265116e+09 | AQ21: =(F21/12)*12 -> 1.9746389e+08 | AR21: =AI21+AQ21 -> 8.7213219e+08 | AS21: =E21-AR21 -> 3.0771457e+09 | AT21: =(F21/12)*9 -> 1.4809792e+08 | AU21: =AR21+AT21 -> 1.0202301e+09 | AV21: =E21-AU21 -> 2.9290477e+09 | AW21: =(F21/12)*12 -> 1.9746389e+08 | AX21: =AR21+AW21 -> 1.0695961e+09 | AY21: =E21-AX21 -> 2.8796818e+09 | BB21: =E21-AX21-AY21 -> 0
A22: =A21+1 -> 16 | B22: Bangunan Renovasi | C22: 44561 | D22: 20 | E22: =8926795238.26-72371732 -> 8.8544235e+09 | F22: =E22/D22 -> 4.4272118e+08 | J22: =G22-I22 -> 0 | O22: =N22+L22 -> 0 | AE22: =(F22/12) -> 36893431 | AF22: =AC22+AE22 -> 36893431 | AG22: =E22-AF22 -> 8.8175301e+09 | AH22: =(F22/12)*12 -> 4.4272118e+08 | AI22: =AF22+AH22 -> 4.7961461e+08 | AJ22: =E22-AI22 -> 8.3748089e+09 | AK22: =(F22/12)*1 -> 36893431 | AL22: =AI22+AK22 -> 5.1650804e+08 | AM22: =E22-AL22 -> 8.3379155e+09 | AN22: =(F22/12)*9 -> 3.3204088e+08 | AO22: =AI22+AN22 -> 8.1165549e+08 | AP22: =E22-AO22 -> 8.042768e+09 | AQ22: =(F22/12)*12 -> 4.4272118e+08 | AR22: =AI22+AQ22 -> 9.2233578e+08 | AS22: =E22-AR22 -> 7.9320877e+09 | AT22: =(F22/12)*9 -> 3.3204088e+08 | AU22: =AR22+AT22 -> 1.2543767e+09 | AV22: =E22-AU22 -> 7.6000468e+09 | AW22: =(F22/12)*12 -> 4.4272118e+08 | AX22: =AR22+AW22 -> 1.365057e+09 | AY22: =E22-AX22 -> 7.4893665e+09 | BB22: =E22-AX22-AY22 -> 0
A23: 1.2 | B23: DIVISI ISP 2 | BB23: =E23-AX23-AY23 -> 0
A24: 1 | B24: Mess 2 | C24: 38353 | D24: 20 | E24: 0 | F24: =E24/D24 -> 0 | G24: =E24 -> 0 | H24: =((F24/12)*(13-IF(C24="","",MONTH(C24))))*10 -> 0 | J24: =G24-I24 -> 0 | K24: =(F24/12)*12 -> 0 | Q24: =(F24/12)*12 -> 0 | T24: =(F24/12)*12 -> 0 | U24: =R24+T24 -> 0 | V24: =E24-U24 -> 0 | W24: =(F24/12)*12 -> 0 | X24: =U24+W24 -> 0 | Y24: =E24-X24 -> 0 | Z24: 0 | AA24: =E24-Z24 -> 0 | AB24: =(F24/12)*12 -> 0 | AC24: =Z24+AB24 -> 0 | AD24: =E24-AC24 -> 0 | AE24: =(F24/12)*12 -> 0 | AF24: =AC24+AE24 -> 0 | AG24: =E24-AF24 -> 0 | AH24: =(F24/12)*12 -> 0 | AI24: =AF24+AH24 -> 0 | AJ24: =E24-AI24 -> 0 | AQ24: =(F24/12)*7 -> 0 | AR24: =AI24+AQ24 -> 0 | AS24: =E24-AR24 -> 0 | BB24: =E24-AR24-AS24 -> 0 | BD24: 28414110 | BE24: =AG24-BD24 -> -28414110 | BF24: =F24/12 -> 0 | BG24: =BE24-BF24 -> -28414110
A25: =A24+1 -> 2 | B25: Kantor 2 | C25: 40179 | D25: 20 | E25: 128910000 | F25: =E25/D25 -> 6445500 | G25: =E25 -> 128910000 | I25: =H25 -> 0 | J25: =G25-I25 -> 128910000 | L25: =I25+K25 -> 0 | M25: =E25-L25 -> 128910000 | N25: =(F25/12)*12 -> 6445500 | O25: =N25+L25 -> 6445500 | P25: =E25-O25 -> 122464500 | Q25: =(F25/12)*12 -> 6445500 | R25: =Q25+O25 -> 12891000 | S25: =E25-R25 -> 116019000 | T25: =(F25/12)*12 -> 6445500 | U25: =R25+T25 -> 19336500 | V25: =E25-U25 -> 109573500 | W25: =(F25/12)*12 -> 6445500 | X25: =U25+W25 -> 25782000 | Y25: =E25-X25 -> 103128000 | Z25: 25782000 | AA25: =E25-Z25 -> 103128000 | AB25: =(F25/12)*12 -> 6445500 | AC25: =X25+AB25 -> 32227500 | AD25: =E25-AC25 -> 96682500 | AE25: =(F25/12)*12 -> 6445500 | AF25: =AC25+AE25 -> 38673000 | AG25: =E25-AF25 -> 90237000 | AH25: =(F25/12)*12 -> 6445500 | AI25: =AF25+AH25 -> 45118500 | AJ25: =E25-AI25 -> 83791500 | AK25: =(F25/12)*1 -> 537125 | AL25: =AI25+AK25 -> 45655625 | AM25: =E25-AL25 -> 83254375 | AN25: =(F25/12)*9 -> 4834125 | AO25: =AI25+AN25 -> 49952625 | AP25: =E25-AO25 -> 78957375 | AQ25: =(F25/12)*12 -> 6445500 | AR25: =AI25+AQ25 -> 51564000 | AS25: =E25-AR25 -> 77346000 | AT25: =(F25/12)*9 -> 4834125 | AU25: =AR25+AT25 -> 56398125 | AV25: =E25-AU25 -> 72511875 | AW25: =(F25/12)*12 -> 6445500 | AX25: =AR25+AW25 -> 58009500 | AY25: =E25-AX25 -> 70900500 | BB25: =E25-AX25-AY25 -> 0 | BD25: 7475000 | BE25: =AG25-BD25 -> 82762000 | BF25: =F25/12 -> 537125 | BG25: =BE25-BF25 -> 82224875
A26: =A25+1 -> 3 | B26: Bangunan ISP 2 | C26: 40544 | D26: 20 | E26: 9.4432849e+09 | F26: =E26/D26 -> 4.7216424e+08 | G26: =E26 -> 9.4432849e+09 | I26: =H26 -> 0 | J26: =G26-I26 -> 9.4432849e+09 | L26: =I26+K26 -> 0 | M26: =E26-L26 -> 9.4432849e+09 | N26: =(F26/12)*12 -> 4.7216424e+08 | O26: =N26+L26 -> 4.7216424e+08 | P26: =E26-O26 -> 8.9711206e+09 | Q26: =(F26/12)*12 -> 4.7216424e+08 | R26: =Q26+O26 -> 9.4432849e+08 | S26: =E26-R26 -> 8.4989564e+09 | T26: =(F26/12)*12 -> 4.7216424e+08 | U26: =R26+T26 -> 1.4164927e+09 | V26: =E26-U26 -> 8.0267921e+09 | W26: =(F26/12)*12 -> 4.7216424e+08 | X26: =U26+W26 -> 1.888657e+09 | Y26: =E26-X26 -> 7.5546279e+09 | Z26: 1.6944685e+09 | AA26: =E26-Z26 -> 7.7488164e+09 | AB26: =(F26/12)*12 -> 4.7216424e+08 | AC26: =X26+AB26 -> 2.3608212e+09 | AD26: =E26-AC26 -> 7.0824637e+09 | AE26: =(F26/12)*12 -> 4.7216424e+08 | AF26: =AC26+AE26 -> 2.8329855e+09 | AG26: =E26-AF26 -> 6.6102994e+09 | AH26: =(F26/12)*12 -> 4.7216424e+08 | AI26: =AF26+AH26 -> 3.3051497e+09 | AJ26: =E26-AI26 -> 6.1381352e+09 | AK26: =(F26/12)*1 -> 39347020 | AL26: =AI26+AK26 -> 3.3444967e+09 | AM26: =E26-AL26 -> 6.0987882e+09 | AN26: =(F26/12)*9 -> 3.5412318e+08 | AO26: =AI26+AN26 -> 3.6592729e+09 | AP26: =E26-AO26 -> 5.784012e+09 | AQ26: =(F26/12)*12 -> 4.7216424e+08 | AR26: =AI26+AQ26 -> 3.777314e+09 | AS26: =E26-AR26 -> 5.6659709e+09 | AT26: =(F26/12)*9 -> 3.5412318e+08 | AU26: =AR26+AT26 -> 4.1314371e+09 | AV26: =E26-AU26 -> 5.3118477e+09 | AW26: =(F26/12)*12 -> 4.7216424e+08 | AX26: =AR26+AW26 -> 4.2494782e+09 | AY26: =E26-AX26 -> 5.1938067e+09 | BB26: =E26-AX26-AY26 -> 0 | BD26: 1.3461879e+08 | BE26: =AG26-BD26 -> 6.4756806e+09 | BF26: =F26/12 -> 39347020 | BG26: =BE26-BF26 -> 6.4363336e+09
A27: 1.3 | B27: PABRIK ROTI | BB27: =E27-AX27-AY27 -> 0
A28: 1 | B28: Kantor | C28: 40909 | D28: 20 | E28: 0 | F28: =E28/D28 -> 0 | G28: =E28 -> 0 | J28: =G28-I28 -> 0 | K28: =(F28/12)*12 -> 0 | M28: =E28-L28 -> 0 | O28: =N28+L28 -> 0 | P28: =E28-O28 -> 0 | Q28: =(F28/12)*12 -> 0 | T28: =(F28/12)*12 -> 0 | U28: =R28+T28 -> 0 | V28: =E28-U28 -> 0 | W28: =(F28/12)*12 -> 0 | X28: =U28+W28 -> 0 | Y28: =E28-X28 -> 0 | AB28: =(F28/12)*12 -> 0 | AC28: =X28+AB28 -> 0 | AD28: =E28-AC28 -> 0 | AE28: =(F28/12)*12 -> 0 | AF28: =AC28+AE28 -> 0 | AG28: =E28-AF28 -> 0 | AH28: =(F28/12)*12 -> 0 | AI28: =AF28+AH28 -> 0 | AJ28: =E28-AI28 -> 0 | AQ28: =(F28/12)*7 -> 0 | AR28: =AI28+AQ28 -> 0 | AS28: =E28-AR28 -> 0 | BB28: =E28-AR28-AS28 -> 0
A29: =A28+1 -> 2 | B29: Gudang Roti | C29: 40909 | D29: 20 | E29: 0 | F29: =E29/D29 -> 0 | G29: =E29 -> 0 | J29: =G29-I29 -> 0 | K29: =(F29/12)*12 -> 0 | M29: =E29-L29 -> 0 | O29: =N29+L29 -> 0 | P29: =E29-O29 -> 0 | Q29: =(F29/12)*12 -> 0 | T29: =(F29/12)*12 -> 0 | U29: =R29+T29 -> 0 | V29: =E29-U29 -> 0 | W29: =(F29/12)*12 -> 0 | X29: =U29+W29 -> 0 | Y29: =E29-X29 -> 0 | AB29: =(F29/12)*12 -> 0 | AC29: =X29+AB29 -> 0 | AD29: =E29-AC29 -> 0 | AE29: =(F29/12)*12 -> 0 | AF29: =AC29+AE29 -> 0 | AG29: =E29-AF29 -> 0 | AH29: =(F29/12)*12 -> 0 | AI29: =AF29+AH29 -> 0 | AJ29: =E29-AI29 -> 0 | AQ29: =(F29/12)*7 -> 0 | AR29: =AI29+AQ29 -> 0 | AS29: =E29-AR29 -> 0 | BB29: =E29-AR29-AS29 -> 0
BB30: =E30-AX30-AY30 -> 0
A31: Bangunan Gebang | BB31: =E31-AX31-AY31 -> 0
A32: 2.1 | B32: Bangunan Umum Tambak 1000 | BB32: =E32-AX32-AY32 -> 0
A33: 1 | B33: Pos Satpam | C33: 38353 | D33: 20 | E33: =10960000*0 -> 0 | F33: =E33/D33 -> 0 | G33: =E33 -> 0 | H33: =((F33/12)*(13-IF(C33="","",MONTH(C33))))*10 -> 0 | I33: =H33 -> 0 | J33: =G33-I33 -> 0 | K33: =(F33/12)*12 -> 0 | L33: =I33+K33 -> 0 | M33: =E33-L33 -> 0 | N33: =(F33/12)*12 -> 0 | O33: =N33+L33 -> 0 | P33: =E33-O33 -> 0 | Q33: =(F33/12)*12 -> 0 | R33: =Q33+O33 -> 0 | S33: =E33-R33 -> 0 | T33: =(F33/12)*12 -> 0 | U33: =R33+T33 -> 0 | V33: =E33-U33 -> 0 | W33: =(F33/12)*12 -> 0 | X33: =U33+W33 -> 0 | Y33: =E33-X33 -> 0 | Z33: =1644000*0 -> 0 | AA33: =E33-Z33 -> 0 | AB33: =(F33/12)*12 -> 0 | AC33: =Z33+AB33 -> 0 | AD33: =E33-AC33 -> 0 | AE33: =(F33/12)*12 -> 0 | AF33: =AC33+AE33 -> 0 | AG33: =E33-AF33 -> 0 | AH33: =(F33/12)*12 -> 0 | AI33: =AF33+AH33 -> 0 | AJ33: =E33-AI33 -> 0 | AQ33: =(F33/12)*7 -> 0 | AR33: =AI33+AQ33 -> 0 | AS33: =E33-AR33 -> 0 | BB33: =E33-AR33-AS33 -> 0
A34: =A33+1 -> 2 | B34: Kantor, Mess, Logistik & Lab | C34: 38353 | D34: 20 | E34: =596230000+10960000 -> 607190000 | F34: =E34/D34 -> 30359500 | G34: =E34 -> 607190000 | I34: =H34 -> 0 | J34: =G34-I34 -> 607190000 | L34: =I34+K34 -> 0 | M34: =E34-L34 -> 607190000 | N34: =(F34/12)*12 -> 30359500 | O34: =N34+L34 -> 30359500 | P34: =E34-O34 -> 576830500 | Q34: =(F34/12)*12 -> 30359500 | R34: =Q34+O34 -> 60719000 | S34: =E34-R34 -> 546471000 | T34: =(F34/12)*12 -> 30359500 | U34: =R34+T34 -> 91078500 | V34: =E34-U34 -> 516111500 | W34: =(F34/12)*12 -> 30359500 | X34: =U34+W34 -> 121438000 | Y34: =E34-X34 -> 485752000 | Z34: =89434500+1644000 -> 91078500 | AA34: =E34-Z34 -> 516111500 | AB34: =(F34/12)*12 -> 30359500 | AC34: =X34+AB34 -> 151797500 | AD34: =E34-AC34 -> 455392500 | AE34: =(F34/12)*12 -> 30359500 | AF34: =AC34+AE34 -> 182157000 | AG34: =E34-AF34 -> 425033000 | AH34: =(F34/12)*12 -> 30359500 | AI34: =AF34+AH34 -> 212516500 | AJ34: =E34-AI34 -> 394673500 | AK34: =(F34/12)*1 -> 2529958.3 | AL34: =AI34+AK34 -> 2.1504646e+08 | AM34: =E34-AL34 -> 3.9214354e+08 | AN34: =(F34/12)*9 -> 22769625 | AO34: =AI34+AN34 -> 235286125 | AP34: =E34-AO34 -> 371903875 | AQ34: =(F34/12)*12 -> 30359500 | AR34: =AI34+AQ34 -> 242876000 | AS34: =E34-AR34 -> 364314000 | AT34: =(F34/12)*9 -> 22769625 | AU34: =AR34+AT34 -> 265645625 | AV34: =E34-AU34 -> 341544375 | AW34: =(F34/12)*12 -> 30359500 | AX34: =AR34+AW34 -> 273235500 | AY34: =E34-AX34 -> 333954500 | BB34: =E34-AX34-AY34 -> 0
A35: =A34+1 -> 3 | B35: Mess Umum | C35: 40544 | D35: 20 | E35: 97760000 | F35: =E35/D35 -> 4888000 | G35: =E35 -> 97760000 | I35: =H35 -> 0 | J35: =G35-I35 -> 97760000 | L35: =I35+K35 -> 0 | M35: =E35-L35 -> 97760000 | N35: =(F35/12)*12 -> 4888000 | O35: =N35+L35 -> 4888000 | P35: =E35-O35 -> 92872000 | Q35: =(F35/12)*12 -> 4888000 | R35: =Q35+O35 -> 9776000 | S35: =E35-R35 -> 87984000 | T35: =(F35/12)*12 -> 4888000 | U35: =R35+T35 -> 14664000 | V35: =E35-U35 -> 83096000 | W35: =(F35/12)*12 -> 4888000 | X35: =U35+W35 -> 19552000 | Y35: =E35-X35 -> 78208000 | Z35: 14664000 | AA35: =E35-Z35 -> 83096000 | AB35: =(F35/12)*12 -> 4888000 | AC35: =X35+AB35 -> 24440000 | AD35: =E35-AC35 -> 73320000 | AE35: =(F35/12)*12 -> 4888000 | AF35: =AC35+AE35 -> 29328000 | AG35: =E35-AF35 -> 68432000 | AH35: =(F35/12)*12 -> 4888000 | AI35: =AF35+AH35 -> 34216000 | AJ35: =E35-AI35 -> 63544000 | AK35: =(F35/12)*1 -> 407333.33 | AL35: =AI35+AK35 -> 34623333 | AM35: =E35-AL35 -> 63136667 | AN35: =(F35/12)*9 -> 3666000 | AO35: =AI35+AN35 -> 37882000 | AP35: =E35-AO35 -> 59878000 | AQ35: =(F35/12)*12 -> 4888000 | AR35: =AI35+AQ35 -> 39104000 | AS35: =E35-AR35 -> 58656000 | AT35: =(F35/12)*9 -> 3666000 | AU35: =AR35+AT35 -> 42770000 | AV35: =E35-AU35 -> 54990000 | AW35: =(F35/12)*12 -> 4888000 | AX35: =AR35+AW35 -> 43992000 | AY35: =E35-AX35 -> 53768000 | BB35: =E35-AX35-AY35 -> 0
A36: =A35+1 -> 4 | B36: Bengkel +Mess | C36: 40544 | D36: 20 | E36: 131970000 | F36: =E36/D36 -> 6598500 | G36: =E36 -> 131970000 | I36: =H36 -> 0 | J36: =G36-I36 -> 131970000 | L36: =I36+K36 -> 0 | M36: =E36-L36 -> 131970000 | N36: =(F36/12)*12 -> 6598500 | O36: =N36+L36 -> 6598500 | P36: =E36-O36 -> 125371500 | Q36: =(F36/12)*12 -> 6598500 | R36: =Q36+O36 -> 13197000 | S36: =E36-R36 -> 118773000 | T36: =(F36/12)*12 -> 6598500 | U36: =R36+T36 -> 19795500 | V36: =E36-U36 -> 112174500 | W36: =(F36/12)*12 -> 6598500 | X36: =U36+W36 -> 26394000 | Y36: =E36-X36 -> 105576000 | Z36: 19795500 | AA36: =E36-Z36 -> 112174500 | AB36: =(F36/12)*12 -> 6598500 | AC36: =X36+AB36 -> 32992500 | AD36: =E36-AC36 -> 98977500 | AE36: =(F36/12)*12 -> 6598500 | AF36: =AC36+AE36 -> 39591000 | AG36: =E36-AF36 -> 92379000 | AH36: =(F36/12)*12 -> 6598500 | AI36: =AF36+AH36 -> 46189500 | AJ36: =E36-AI36 -> 85780500 | AK36: =(F36/12)*1 -> 549875 | AL36: =AI36+AK36 -> 46739375 | AM36: =E36-AL36 -> 85230625 | AN36: =(F36/12)*9 -> 4948875 | AO36: =AI36+AN36 -> 51138375 | AP36: =E36-AO36 -> 80831625 | AQ36: =(F36/12)*12 -> 6598500 | AR36: =AI36+AQ36 -> 52788000 | AS36: =E36-AR36 -> 79182000 | AT36: =(F36/12)*9 -> 4948875 | AU36: =AR36+AT36 -> 57736875 | AV36: =E36-AU36 -> 74233125 | AW36: =(F36/12)*12 -> 6598500 | AX36: =AR36+AW36 -> 59386500 | AY36: =E36-AX36 -> 72583500 | BB36: =E36-AX36-AY36 -> 0
A37: =A36+1 -> 5 | B37: Dapur + Kantin | C37: 40544 | D37: 20 | E37: 98820000 | F37: =E37/D37 -> 4941000 | G37: =E37 -> 98820000 | I37: =H37 -> 0 | J37: =G37-I37 -> 98820000 | L37: =I37+K37 -> 0 | M37: =E37-L37 -> 98820000 | N37: =(F37/12)*12 -> 4941000 | O37: =N37+L37 -> 4941000 | P37: =E37-O37 -> 93879000 | Q37: =(F37/12)*12 -> 4941000 | R37: =Q37+O37 -> 9882000 | S37: =E37-R37 -> 88938000 | T37: =(F37/12)*12 -> 4941000 | U37: =R37+T37 -> 14823000 | V37: =E37-U37 -> 83997000 | W37: =(F37/12)*12 -> 4941000 | X37: =U37+W37 -> 19764000 | Y37: =E37-X37 -> 79056000 | Z37: 14823000 | AA37: =E37-Z37 -> 83997000 | AB37: =(F37/12)*12 -> 4941000 | AC37: =X37+AB37 -> 24705000 | AD37: =E37-AC37 -> 74115000 | AE37: =(F37/12)*12 -> 4941000 | AF37: =AC37+AE37 -> 29646000 | AG37: =E37-AF37 -> 69174000 | AH37: =(F37/12)*12 -> 4941000 | AI37: =AF37+AH37 -> 34587000 | AJ37: =E37-AI37 -> 64233000 | AK37: =(F37/12)*1 -> 411750 | AL37: =AI37+AK37 -> 34998750 | AM37: =E37-AL37 -> 63821250 | AN37: =(F37/12)*9 -> 3705750 | AO37: =AI37+AN37 -> 38292750 | AP37: =E37-AO37 -> 60527250 | AQ37: =(F37/12)*12 -> 4941000 | AR37: =AI37+AQ37 -> 39528000 | AS37: =E37-AR37 -> 59292000 | AT37: =(F37/12)*9 -> 3705750 | AU37: =AR37+AT37 -> 43233750 | AV37: =E37-AU37 -> 55586250 | AW37: =(F37/12)*12 -> 4941000 | AX37: =AR37+AW37 -> 44469000 | AY37: =E37-AX37 -> 54351000 | BB37: =E37-AX37-AY37 -> 0
A38: =A37+1 -> 6 | B38: Gudang Barang | C38: 40544 | D38: 20 | E38: 89000000 | F38: =E38/D38 -> 4450000 | G38: =E38 -> 89000000 | I38: =H38 -> 0 | J38: =G38-I38 -> 89000000 | L38: =I38+K38 -> 0 | M38: =E38-L38 -> 89000000 | N38: =(F38/12)*12 -> 4450000 | O38: =N38+L38 -> 4450000 | P38: =E38-O38 -> 84550000 | Q38: =(F38/12)*12 -> 4450000 | R38: =Q38+O38 -> 8900000 | S38: =E38-R38 -> 80100000 | T38: =(F38/12)*12 -> 4450000 | U38: =R38+T38 -> 13350000 | V38: =E38-U38 -> 75650000 | W38: =(F38/12)*12 -> 4450000 | X38: =U38+W38 -> 17800000 | Y38: =E38-X38 -> 71200000 | Z38: 13350000 | AA38: =E38-Z38 -> 75650000 | AB38: =(F38/12)*12 -> 4450000 | AC38: =X38+AB38 -> 22250000 | AD38: =E38-AC38 -> 66750000 | AE38: =(F38/12)*12 -> 4450000 | AF38: =AC38+AE38 -> 26700000 | AG38: =E38-AF38 -> 62300000 | AH38: =(F38/12)*12 -> 4450000 | AI38: =AF38+AH38 -> 31150000 | AJ38: =E38-AI38 -> 57850000 | AK38: =(F38/12)*1 -> 370833.33 | AL38: =AI38+AK38 -> 31520833 | AM38: =E38-AL38 -> 57479167 | AN38: =(F38/12)*9 -> 3337500 | AO38: =AI38+AN38 -> 34487500 | AP38: =E38-AO38 -> 54512500 | AQ38: =(F38/12)*12 -> 4450000 | AR38: =AI38+AQ38 -> 35600000 | AS38: =E38-AR38 -> 53400000 | AT38: =(F38/12)*9 -> 3337500 | AU38: =AR38+AT38 -> 38937500 | AV38: =E38-AU38 -> 50062500 | AW38: =(F38/12)*12 -> 4450000 | AX38: =AR38+AW38 -> 40050000 | AY38: =E38-AX38 -> 48950000 | BB38: =E38-AX38-AY38 -> 0
A39: =A38+1 -> 7 | B39: Gudang Trafo | C39: 41640 | D39: 20 | E39: 51410000 | F39: =E39/D39 -> 2570500 | G39: =E39 -> 51410000 | I39: =H39 -> 0 | J39: =G39-I39 -> 51410000 | L39: =I39+K39 -> 0 | M39: =E39-L39 -> 51410000 | N39: =(F39/12)*12 -> 2570500 | O39: =N39+L39 -> 2570500 | P39: =E39-O39 -> 48839500 | Q39: =(F39/12)*12 -> 2570500 | R39: =Q39+O39 -> 5141000 | S39: =E39-R39 -> 46269000 | T39: =(F39/12)*12 -> 2570500 | U39: =R39+T39 -> 7711500 | V39: =E39-U39 -> 43698500 | W39: =(F39/12)*12 -> 2570500 | X39: =U39+W39 -> 10282000 | Y39: =E39-X39 -> 41128000 | Z39: 7711500 | AA39: =E39-Z39 -> 43698500 | AB39: =(F39/12)*12 -> 2570500 | AC39: =X39+AB39 -> 12852500 | AD39: =E39-AC39 -> 38557500 | AE39: =(F39/12)*12 -> 2570500 | AF39: =AC39+AE39 -> 15423000 | AG39: =E39-AF39 -> 35987000 | AH39: =(F39/12)*12 -> 2570500 | AI39: =AF39+AH39 -> 17993500 | AJ39: =E39-AI39 -> 33416500 | AK39: =(F39/12)*1 -> 214208.33 | AL39: =AI39+AK39 -> 18207708 | AM39: =E39-AL39 -> 33202292 | AN39: =(F39/12)*9 -> 1927875 | AO39: =AI39+AN39 -> 19921375 | AP39: =E39-AO39 -> 31488625 | AQ39: =(F39/12)*12 -> 2570500 | AR39: =AI39+AQ39 -> 20564000 | AS39: =E39-AR39 -> 30846000 | AT39: =(F39/12)*9 -> 1927875 | AU39: =AR39+AT39 -> 22491875 | AV39: =E39-AU39 -> 28918125 | AW39: =(F39/12)*12 -> 2570500 | AX39: =AR39+AW39 -> 23134500 | AY39: =E39-AX39 -> 28275500 | BB39: =E39-AX39-AY39 -> 0
A40: =A39+1 -> 8 | B40: KM/WC | C40: 41640 | D40: 20 | E40: =24700000*0 -> 0 | F40: =E40/D40 -> 0 | G40: =E40 -> 0 | H40: =((F40/12)*(13-IF(C40="","",MONTH(C40)))) -> 0 | I40: =H40 -> 0 | J40: =G40-I40 -> 0 | K40: =(F40/12)*12 -> 0 | L40: =I40+K40 -> 0 | M40: =E40-L40 -> 0 | N40: =(F40/12)*12 -> 0 | O40: =N40+L40 -> 0 | P40: =E40-O40 -> 0 | Q40: =(F40/12)*12 -> 0 | R40: =Q40+O40 -> 0 | S40: =E40-R40 -> 0 | T40: =(F40/12)*12 -> 0 | U40: =R40+T40 -> 0 | V40: =E40-U40 -> 0 | W40: =(F40/12)*12 -> 0 | X40: =U40+W40 -> 0 | Y40: =E40-X40 -> 0 | AA40: =E40-Z40 -> 0 | AB40: =(F40/12)*12 -> 0 | AC40: =Z40+AB40 -> 0 | AD40: =E40-AC40 -> 0 | AE40: =(F40/12)*12 -> 0 | AF40: =AC40+AE40 -> 0 | AG40: =E40-AF40 -> 0 | AH40: =(F40/12)*12 -> 0 | AI40: =AF40+AH40 -> 0 | AJ40: =E40-AI40 -> 0 | AQ40: =(F40/12)*7 -> 0 | AR40: =AI40+AQ40 -> 0 | AS40: =E40-AR40 -> 0 | BB40: =E40-AR40-AS40 -> 0
A41: =A40+1 -> 9 | B41: Mushola + KM/WC | C41: 41640 | D41: 20 | E41: =65020000+24700000 -> 89720000 | F41: =E41/D41 -> 4486000 | G41: =E41 -> 89720000 | I41: =H41 -> 0 | J41: =G41-I41 -> 89720000 | L41: =I41+K41 -> 0 | M41: =E41-L41 -> 89720000 | N41: =(F41/12)*12 -> 4486000 | O41: =N41+L41 -> 4486000 | P41: =E41-O41 -> 85234000 | Q41: =(F41/12)*12 -> 4486000 | R41: =Q41+O41 -> 8972000 | S41: =E41-R41 -> 80748000 | T41: =(F41/12)*12 -> 4486000 | U41: =R41+T41 -> 13458000 | V41: =E41-U41 -> 76262000 | W41: =(F41/12)*12 -> 4486000 | X41: =U41+W41 -> 17944000 | Y41: =E41-X41 -> 71776000 | Z41: =9753000+3705000 -> 13458000 | AA41: =E41-Z41 -> 76262000 | AB41: =(F41/12)*12 -> 4486000 | AC41: =X41+AB41 -> 22430000 | AD41: =E41-AC41 -> 67290000 | AE41: =(F41/12)*12 -> 4486000 | AF41: =AC41+AE41 -> 26916000 | AG41: =E41-AF41 -> 62804000 | AH41: =(F41/12)*12 -> 4486000 | AI41: =AF41+AH41 -> 31402000 | AJ41: =E41-AI41 -> 58318000 | AK41: =(F41/12)*1 -> 373833.33 | AL41: =AI41+AK41 -> 31775833 | AM41: =E41-AL41 -> 57944167 | AN41: =(F41/12)*9 -> 3364500 | AO41: =AI41+AN41 -> 34766500 | AP41: =E41-AO41 -> 54953500 | AQ41: =(F41/12)*12 -> 4486000 | AR41: =AI41+AQ41 -> 35888000 | AS41: =E41-AR41 -> 53832000 | AT41: =(F41/12)*9 -> 3364500 | AU41: =AR41+AT41 -> 39252500 | AV41: =E41-AU41 -> 50467500 | AW41: =(F41/12)*12 -> 4486000 | AX41: =AR41+AW41 -> 40374000 | AY41: =E41-AX41 -> 49346000 | BB41: =E41-AX41-AY41 -> 0
A42: 2.2 | B42: Bangunan Tambak Blok A-C | BB42: =E42-AX42-AY42 -> 0
A43: 1 | B43: Rumah Genset Blok A-C | C43: 38353 | D43: 20 | E43: 185540000 | F43: =E43/D43 -> 9277000 | G43: =E43 -> 185540000 | I43: =H43 -> 0 | J43: =G43-I43 -> 185540000 | L43: =I43+K43 -> 0 | M43: =E43-L43 -> 185540000 | N43: =(F43/12)*12 -> 9277000 | O43: =N43+L43 -> 9277000 | P43: =E43-O43 -> 176263000 | Q43: =(F43/12)*12 -> 9277000 | R43: =Q43+O43 -> 18554000 | S43: =E43-R43 -> 166986000 | T43: =(F43/12)*12 -> 9277000 | U43: =R43+T43 -> 27831000 | V43: =E43-U43 -> 157709000 | W43: =(F43/12)*12 -> 9277000 | X43: =U43+W43 -> 37108000 | Y43: =E43-X43 -> 148432000 | Z43: 27831000 | AA43: =E43-Z43 -> 157709000 | AB43: =(F43/12)*12 -> 9277000 | AC43: =X43+AB43 -> 46385000 | AD43: =E43-AC43 -> 139155000 | AE43: =(F43/12)*12 -> 9277000 | AF43: =AC43+AE43 -> 55662000 | AG43: =E43-AF43 -> 129878000 | AH43: =(F43/12)*12 -> 9277000 | AI43: =AF43+AH43 -> 64939000 | AJ43: =E43-AI43 -> 120601000 | AK43: =(F43/12)*1 -> 773083.33 | AL43: =AI43+AK43 -> 65712083 | AM43: =E43-AL43 -> 1.1982792e+08 | AN43: =(F43/12)*9 -> 6957750 | AO43: =AI43+AN43 -> 71896750 | AP43: =E43-AO43 -> 113643250 | AQ43: =(F43/12)*12 -> 9277000 | AR43: =AI43+AQ43 -> 74216000 | AS43: =E43-AR43 -> 111324000 | AT43: =(F43/12)*9 -> 6957750 | AU43: =AR43+AT43 -> 81173750 | AV43: =E43-AU43 -> 104366250 | AW43: =(F43/12)*12 -> 9277000 | AX43: =AR43+AW43 -> 83493000 | AY43: =E43-AX43 -> 102047000 | BB43: =E43-AX43-AY43 -> 0
A44: =A43+1 -> 2 | B44: Bak Colling Tower | C44: 38353 | D44: 20 | E44: =24330000*0 -> 0 | F44: =E44/D44 -> 0 | G44: =E44 -> 0 | H44: =((F44/12)*(13-IF(C44="","",MONTH(C44))))*10 -> 0 | I44: =H44 -> 0 | J44: =G44-I44 -> 0 | K44: =(F44/12)*12 -> 0 | L44: =I44+K44 -> 0 | M44: =E44-L44 -> 0 | N44: =(F44/12)*12 -> 0 | O44: =N44+L44 -> 0 | P44: =E44-O44 -> 0 | Q44: =(F44/12)*12 -> 0 | R44: =Q44+O44 -> 0 | S44: =E44-R44 -> 0 | T44: =(F44/12)*12 -> 0 | U44: =R44+T44 -> 0 | V44: =E44-U44 -> 0 | W44: =(F44/12)*12 -> 0 | X44: =U44+W44 -> 0 | Y44: =E44-X44 -> 0 | Z44: =3649500*0 -> 0 | AA44: =E44-Z44 -> 0 | AB44: =(F44/12)*12 -> 0 | AC44: =Z44+AB44 -> 0 | AD44: =E44-AC44 -> 0 | AE44: =(F44/12)*12 -> 0 | AF44: =AC44+AE44 -> 0 | AG44: =E44-AF44 -> 0 | AH44: =(F44/12)*12 -> 0 | AI44: =AF44+AH44 -> 0 | AJ44: =E44-AI44 -> 0 | AQ44: =(F44/12)*7 -> 0 | AR44: =AI44+AQ44 -> 0 | AS44: =E44-AR44 -> 0 | BB44: =E44-AR44-AS44 -> 0
A45: =A44+1 -> 3 | B45: Mess Proses Blok C + KM/WC | C45: 38353 | D45: 20 | E45: 64480000 | F45: =E45/D45 -> 3224000 | G45: =E45 -> 64480000 | I45: =H45 -> 0 | J45: =G45-I45 -> 64480000 | L45: =I45+K45 -> 0 | M45: =E45-L45 -> 64480000 | N45: =(F45/12)*12 -> 3224000 | O45: =N45+L45 -> 3224000 | P45: =E45-O45 -> 61256000 | Q45: =(F45/12)*12 -> 3224000 | R45: =Q45+O45 -> 6448000 | S45: =E45-R45 -> 58032000 | T45: =(F45/12)*12 -> 3224000 | U45: =R45+T45 -> 9672000 | V45: =E45-U45 -> 54808000 | W45: =(F45/12)*12 -> 3224000 | X45: =U45+W45 -> 12896000 | Y45: =E45-X45 -> 51584000 | Z45: 9672000 | AA45: =E45-Z45 -> 54808000 | AB45: =(F45/12)*12 -> 3224000 | AC45: =X45+AB45 -> 16120000 | AD45: =E45-AC45 -> 48360000 | AE45: =(F45/12)*12 -> 3224000 | AF45: =AC45+AE45 -> 19344000 | AG45: =E45-AF45 -> 45136000 | AH45: =(F45/12)*12 -> 3224000 | AI45: =AF45+AH45 -> 22568000 | AJ45: =E45-AI45 -> 41912000 | AK45: =(F45/12)*1 -> 268666.67 | AL45: =AI45+AK45 -> 22836667 | AM45: =E45-AL45 -> 41643333 | AN45: =(F45/12)*9 -> 2418000 | AO45: =AI45+AN45 -> 24986000 | AP45: =E45-AO45 -> 39494000 | AQ45: =(F45/12)*12 -> 3224000 | AR45: =AI45+AQ45 -> 25792000 | AS45: =E45-AR45 -> 38688000 | AT45: =(F45/12)*9 -> 2418000 | AU45: =AR45+AT45 -> 28210000 | AV45: =E45-AU45 -> 36270000 | AW45: =(F45/12)*12 -> 3224000 | AX45: =AR45+AW45 -> 29016000 | AY45: =E45-AX45 -> 35464000 | BB45: =E45-AX45-AY45 -> 0
A46: =A45+1 -> 4 | B46: Mess Assisten + kantin Blok C dan Blok A | C46: 40544 | D46: 20 | E46: =149230000+26170000 -> 175400000 | F46: =E46/D46 -> 8770000 | G46: =E46 -> 175400000 | I46: =H46 -> 0 | J46: =G46-I46 -> 175400000 | L46: =I46+K46 -> 0 | M46: =E46-L46 -> 175400000 | N46: =(F46/12)*12 -> 8770000 | O46: =N46+L46 -> 8770000 | P46: =E46-O46 -> 166630000 | Q46: =(F46/12)*12 -> 8770000 | R46: =Q46+O46 -> 17540000 | S46: =E46-R46 -> 157860000 | T46: =(F46/12)*12 -> 8770000 | U46: =R46+T46 -> 26310000 | V46: =E46-U46 -> 149090000 | W46: =(F46/12)*12 -> 8770000 | X46: =U46+W46 -> 35080000 | Y46: =E46-X46 -> 140320000 | Z46: 26310000 | AA46: =E46-Z46 -> 149090000 | AB46: =(F46/12)*12 -> 8770000 | AC46: =X46+AB46 -> 43850000 | AD46: =E46-AC46 -> 131550000 | AE46: =(F46/12)*12 -> 8770000 | AF46: =AC46+AE46 -> 52620000 | AG46: =E46-AF46 -> 122780000 | AH46: =(F46/12)*12 -> 8770000 | AI46: =AF46+AH46 -> 61390000 | AJ46: =E46-AI46 -> 114010000 | AK46: =(F46/12)*1 -> 730833.33 | AL46: =AI46+AK46 -> 62120833 | AM46: =E46-AL46 -> 1.1327917e+08 | AN46: =(F46/12)*9 -> 6577500 | AO46: =AI46+AN46 -> 67967500 | AP46: =E46-AO46 -> 107432500 | AQ46: =(F46/12)*12 -> 8770000 | AR46: =AI46+AQ46 -> 70160000 | AS46: =E46-AR46 -> 105240000 | AT46: =(F46/12)*9 -> 6577500 | AU46: =AR46+AT46 -> 76737500 | AV46: =E46-AU46 -> 98662500 | AW46: =(F46/12)*12 -> 8770000 | AX46: =AR46+AW46 -> 78930000 | AY46: =E46-AX46 -> 96470000 | BB46: =E46-AX46-AY46 -> 0
A47: =A46+1 -> 5 | B47: Mess Assisten Blok A | C47: 40544 | D47: 20 | E47: =26170000*0 -> 0 | F47: =E47/D47 -> 0 | G47: =E47 -> 0 | H47: =((F47/12)*(13-IF(C47="","",MONTH(C47))))*4 -> 0 | I47: =H47 -> 0 | J47: =G47-I47 -> 0 | K47: =(F47/12)*12 -> 0 | L47: =I47+K47 -> 0 | M47: =E47-L47 -> 0 | N47: =(F47/12)*12 -> 0 | O47: =N47+L47 -> 0 | P47: =E47-O47 -> 0 | Q47: =(F47/12)*12 -> 0 | R47: =Q47+O47 -> 0 | S47: =E47-R47 -> 0 | T47: =(F47/12)*12 -> 0 | U47: =R47+T47 -> 0 | V47: =E47-U47 -> 0 | W47: =(F47/12)*12 -> 0 | X47: =U47+W47 -> 0 | Y47: =E47-X47 -> 0 | AA47: =E47-Z47 -> 0 | AB47: =(F47/12)*12 -> 0 | AC47: =Z47+AB47 -> 0 | AD47: =E47-AC47 -> 0 | AE47: =(F47/12)*12 -> 0 | AF47: =AC47+AE47 -> 0 | AG47: =E47-AF47 -> 0 | AH47: =(F47/12)*12 -> 0 | AI47: =AF47+AH47 -> 0 | AJ47: =E47-AI47 -> 0 | AQ47: =(F47/12)*7 -> 0 | AR47: =AI47+AQ47 -> 0 | AS47: =E47-AR47 -> 0 | BB47: =E47-AR47-AS47 -> 0
A48: =A47+1 -> 6 | B48: Mess Feeder (14 Unit) | C48: 40544 | D48: 20 | E48: 109140000 | F48: =E48/D48 -> 5457000 | G48: =E48 -> 109140000 | I48: =H48 -> 0 | J48: =G48-I48 -> 109140000 | L48: =I48+K48 -> 0 | M48: =E48-L48 -> 109140000 | N48: =(F48/12)*12 -> 5457000 | O48: =N48+L48 -> 5457000 | P48: =E48-O48 -> 103683000 | Q48: =(F48/12)*12 -> 5457000 | R48: =Q48+O48 -> 10914000 | S48: =E48-R48 -> 98226000 | T48: =(F48/12)*12 -> 5457000 | U48: =R48+T48 -> 16371000 | V48: =E48-U48 -> 92769000 | W48: =(F48/12)*12 -> 5457000 | X48: =U48+W48 -> 21828000 | Y48: =E48-X48 -> 87312000 | Z48: 16371000 | AA48: =E48-Z48 -> 92769000 | AB48: =(F48/12)*12 -> 5457000 | AC48: =X48+AB48 -> 27285000 | AD48: =E48-AC48 -> 81855000 | AE48: =(F48/12)*12 -> 5457000 | AF48: =AC48+AE48 -> 32742000 | AG48: =E48-AF48 -> 76398000 | AH48: =(F48/12)*12 -> 5457000 | AI48: =AF48+AH48 -> 38199000 | AJ48: =E48-AI48 -> 70941000 | AK48: =(F48/12)*1 -> 454750 | AL48: =AI48+AK48 -> 38653750 | AM48: =E48-AL48 -> 70486250 | AN48: =(F48/12)*9 -> 4092750 | AO48: =AI48+AN48 -> 42291750 | AP48: =E48-AO48 -> 66848250 | AQ48: =(F48/12)*12 -> 5457000 | AR48: =AI48+AQ48 -> 43656000 | AS48: =E48-AR48 -> 65484000 | AT48: =(F48/12)*9 -> 4092750 | AU48: =AR48+AT48 -> 47748750 | AV48: =E48-AU48 -> 61391250 | AW48: =(F48/12)*12 -> 5457000 | AX48: =AR48+AW48 -> 49113000 | AY48: =E48-AX48 -> 60027000 | BB48: =E48-AX48-AY48 -> 0
A49: =A48+1 -> 7 | B49: Gudang Pakan ( 4 Unit) | C49: 40544 | D49: 20 | E49: 48450000 | F49: =E49/D49 -> 2422500 | G49: =E49 -> 48450000 | I49: =H49 -> 0 | J49: =G49-I49 -> 48450000 | L49: =I49+K49 -> 0 | M49: =E49-L49 -> 48450000 | N49: =(F49/12)*12 -> 2422500 | O49: =N49+L49 -> 2422500 | P49: =E49-O49 -> 46027500 | Q49: =(F49/12)*12 -> 2422500 | R49: =Q49+O49 -> 4845000 | S49: =E49-R49 -> 43605000 | T49: =(F49/12)*12 -> 2422500 | U49: =R49+T49 -> 7267500 | V49: =E49-U49 -> 41182500 | W49: =(F49/12)*12 -> 2422500 | X49: =U49+W49 -> 9690000 | Y49: =E49-X49 -> 38760000 | Z49: 7267500 | AA49: =E49-Z49 -> 41182500 | AB49: =(F49/12)*12 -> 2422500 | AC49: =X49+AB49 -> 12112500 | AD49: =E49-AC49 -> 36337500 | AE49: =(F49/12)*12 -> 2422500 | AF49: =AC49+AE49 -> 14535000 | AG49: =E49-AF49 -> 33915000 | AH49: =(F49/12)*12 -> 2422500 | AI49: =AF49+AH49 -> 16957500 | AJ49: =E49-AI49 -> 31492500 | AK49: =(F49/12)*1 -> 201875 | AL49: =AI49+AK49 -> 17159375 | AM49: =E49-AL49 -> 31290625 | AN49: =(F49/12)*9 -> 1816875 | AO49: =AI49+AN49 -> 18774375 | AP49: =E49-AO49 -> 29675625 | AQ49: =(F49/12)*12 -> 2422500 | AR49: =AI49+AQ49 -> 19380000 | AS49: =E49-AR49 -> 29070000 | AT49: =(F49/12)*9 -> 1816875 | AU49: =AR49+AT49 -> 21196875 | AV49: =E49-AU49 -> 27253125 | AW49: =(F49/12)*12 -> 2422500 | AX49: =AR49+AW49 -> 21802500 | AY49: =E49-AX49 -> 26647500 | BB49: =E49-AX49-AY49 -> 0
A50: =A49+1 -> 8 | B50: Kantin Blok A | C50: 40544 | D50: 20 | E50: 83160000 | F50: =E50/D50 -> 4158000 | G50: =E50 -> 83160000 | I50: =H50 -> 0 | J50: =G50-I50 -> 83160000 | L50: =I50+K50 -> 0 | M50: =E50-L50 -> 83160000 | N50: =(F50/12)*12 -> 4158000 | O50: =N50+L50 -> 4158000 | P50: =E50-O50 -> 79002000 | Q50: =(F50/12)*12 -> 4158000 | R50: =Q50+O50 -> 8316000 | S50: =E50-R50 -> 74844000 | T50: =(F50/12)*12 -> 4158000 | U50: =R50+T50 -> 12474000 | V50: =E50-U50 -> 70686000 | W50: =(F50/12)*12 -> 4158000 | X50: =U50+W50 -> 16632000 | Y50: =E50-X50 -> 66528000 | Z50: 12474000 | AA50: =E50-Z50 -> 70686000 | AB50: =(F50/12)*12 -> 4158000 | AC50: =X50+AB50 -> 20790000 | AD50: =E50-AC50 -> 62370000 | AE50: =(F50/12)*12 -> 4158000 | AF50: =AC50+AE50 -> 24948000 | AG50: =E50-AF50 -> 58212000 | AH50: =(F50/12)*12 -> 4158000 | AI50: =AF50+AH50 -> 29106000 | AJ50: =E50-AI50 -> 54054000 | AK50: =(F50/12)*1 -> 346500 | AL50: =AI50+AK50 -> 29452500 | AM50: =E50-AL50 -> 53707500 | AN50: =(F50/12)*9 -> 3118500 | AO50: =AI50+AN50 -> 32224500 | AP50: =E50-AO50 -> 50935500 | AQ50: =(F50/12)*12 -> 4158000 | AR50: =AI50+AQ50 -> 33264000 | AS50: =E50-AR50 -> 49896000 | AT50: =(F50/12)*9 -> 3118500 | AU50: =AR50+AT50 -> 36382500 | AV50: =E50-AU50 -> 46777500 | AW50: =(F50/12)*12 -> 4158000 | AX50: =AR50+AW50 -> 37422000 | AY50: =E50-AX50 -> 45738000 | BB50: =E50-AX50-AY50 -> 0
A51: =A50+1 -> 9 | B51: Rumah Proses | C51: 40544 | D51: 20 | E51: 90770000 | F51: =E51/D51 -> 4538500 | G51: =E51 -> 90770000 | I51: =H51 -> 0 | J51: =G51-I51 -> 90770000 | L51: =I51+K51 -> 0 | M51: =E51-L51 -> 90770000 | N51: =(F51/12)*12 -> 4538500 | O51: =N51+L51 -> 4538500 | P51: =E51-O51 -> 86231500 | Q51: =(F51/12)*12 -> 4538500 | R51: =Q51+O51 -> 9077000 | S51: =E51-R51 -> 81693000 | T51: =(F51/12)*12 -> 4538500 | U51: =R51+T51 -> 13615500 | V51: =E51-U51 -> 77154500 | W51: =(F51/12)*12 -> 4538500 | X51: =U51+W51 -> 18154000 | Y51: =E51-X51 -> 72616000 | Z51: 13615500 | AA51: =E51-Z51 -> 77154500 | AB51: =(F51/12)*12 -> 4538500 | AC51: =X51+AB51 -> 22692500 | AD51: =E51-AC51 -> 68077500 | AE51: =(F51/12)*12 -> 4538500 | AF51: =AC51+AE51 -> 27231000 | AG51: =E51-AF51 -> 63539000 | AH51: =(F51/12)*12 -> 4538500 | AI51: =AF51+AH51 -> 31769500 | AJ51: =E51-AI51 -> 59000500 | AK51: =(F51/12)*1 -> 378208.33 | AL51: =AI51+AK51 -> 32147708 | AM51: =E51-AL51 -> 58622292 | AN51: =(F51/12)*9 -> 3403875 | AO51: =AI51+AN51 -> 35173375 | AP51: =E51-AO51 -> 55596625 | AQ51: =(F51/12)*12 -> 4538500 | AR51: =AI51+AQ51 -> 36308000 | AS51: =E51-AR51 -> 54462000 | AT51: =(F51/12)*9 -> 3403875 | AU51: =AR51+AT51 -> 39711875 | AV51: =E51-AU51 -> 51058125 | AW51: =(F51/12)*12 -> 4538500 | AX51: =AR51+AW51 -> 40846500 | AY51: =E51-AX51 -> 49923500 | BB51: =E51-AX51-AY51 -> 0
A52: =A51+1 -> 10 | B52: Mess Karyawan Blok A + WC | C52: 41640 | D52: 20 | E52: 88740000 | F52: =E52/D52 -> 4437000 | G52: =E52 -> 88740000 | I52: =H52 -> 0 | J52: =G52-I52 -> 88740000 | L52: =I52+K52 -> 0 | M52: =E52-L52 -> 88740000 | N52: =(F52/12)*12 -> 4437000 | O52: =N52+L52 -> 4437000 | P52: =E52-O52 -> 84303000 | Q52: =(F52/12)*12 -> 4437000 | R52: =Q52+O52 -> 8874000 | S52: =E52-R52 -> 79866000 | T52: =(F52/12)*12 -> 4437000 | U52: =R52+T52 -> 13311000 | V52: =E52-U52 -> 75429000 | W52: =(F52/12)*12 -> 4437000 | X52: =U52+W52 -> 17748000 | Y52: =E52-X52 -> 70992000 | Z52: 13311000 | AA52: =E52-Z52 -> 75429000 | AB52: =(F52/12)*12 -> 4437000 | AC52: =X52+AB52 -> 22185000 | AD52: =E52-AC52 -> 66555000 | AE52: =(F52/12)*12 -> 4437000 | AF52: =AC52+AE52 -> 26622000 | AG52: =E52-AF52 -> 62118000 | AH52: =(F52/12)*12 -> 4437000 | AI52: =AF52+AH52 -> 31059000 | AJ52: =E52-AI52 -> 57681000 | AK52: =(F52/12)*1 -> 369750 | AL52: =AI52+AK52 -> 31428750 | AM52: =E52-AL52 -> 57311250 | AN52: =(F52/12)*9 -> 3327750 | AO52: =AI52+AN52 -> 34386750 | AP52: =E52-AO52 -> 54353250 | AQ52: =(F52/12)*12 -> 4437000 | AR52: =AI52+AQ52 -> 35496000 | AS52: =E52-AR52 -> 53244000 | AT52: =(F52/12)*9 -> 3327750 | AU52: =AR52+AT52 -> 38823750 | AV52: =E52-AU52 -> 49916250 | AW52: =(F52/12)*12 -> 4437000 | AX52: =AR52+AW52 -> 39933000 | AY52: =E52-AX52 -> 48807000 | BB52: =E52-AX52-AY52 -> 0
A53: =A52+1 -> 11 | B53: Mess Baru Blok C | C53: 41640 | D53: 20 | E53: 553010000 | F53: =E53/D53 -> 27650500 | G53: =E53 -> 553010000 | I53: =H53 -> 0 | J53: =G53-I53 -> 553010000 | L53: =I53+K53 -> 0 | M53: =E53-L53 -> 553010000 | N53: =(F53/12)*12 -> 27650500 | O53: =N53+L53 -> 27650500 | P53: =E53-O53 -> 525359500 | Q53: =(F53/12)*12 -> 27650500 | R53: =Q53+O53 -> 55301000 | S53: =E53-R53 -> 497709000 | T53: =(F53/12)*12 -> 27650500 | U53: =R53+T53 -> 82951500 | V53: =E53-U53 -> 470058500 | W53: =(F53/12)*12 -> 27650500 | X53: =U53+W53 -> 110602000 | Y53: =E53-X53 -> 442408000 | Z53: 82951500 | AA53: =E53-Z53 -> 470058500 | AB53: =(F53/12)*12 -> 27650500 | AC53: =X53+AB53 -> 138252500 | AD53: =E53-AC53 -> 414757500 | AE53: =(F53/12)*12 -> 27650500 | AF53: =AC53+AE53 -> 165903000 | AG53: =E53-AF53 -> 387107000 | AH53: =(F53/12)*12 -> 27650500 | AI53: =AF53+AH53 -> 193553500 | AJ53: =E53-AI53 -> 359456500 | AK53: =(F53/12)*1 -> 2304208.3 | AL53: =AI53+AK53 -> 1.9585771e+08 | AM53: =E53-AL53 -> 3.5715229e+08 | AN53: =(F53/12)*9 -> 20737875 | AO53: =AI53+AN53 -> 214291375 | AP53: =E53-AO53 -> 338718625 | AQ53: =(F53/12)*12 -> 27650500 | AR53: =AI53+AQ53 -> 221204000 | AS53: =E53-AR53 -> 331806000 | AT53: =(F53/12)*9 -> 20737875 | AU53: =AR53+AT53 -> 241941875 | AV53: =E53-AU53 -> 311068125 | AW53: =(F53/12)*12 -> 27650500 | AX53: =AR53+AW53 -> 248854500 | AY53: =E53-AX53 -> 304155500 | BB53: =E53-AX53-AY53 -> 0
A54: 2.3 | B54: Bangunan Tambak Blok D & E | BB54: =E54-AX54-AY54 -> 0
A55: 1 | B55: Bak Colling Tower | C55: 38353 | D55: 20 | E55: =19950000*0 -> 0 | F55: =E55/D55 -> 0 | G55: =E55 -> 0 | H55: =((F55/12)*(13-IF(C55="","",MONTH(C55))))*10 -> 0 | I55: =H55 -> 0 | J55: =G55-I55 -> 0 | K55: =(F55/12)*12 -> 0 | L55: =I55+K55 -> 0 | M55: =E55-L55 -> 0 | N55: =(F55/12)*12 -> 0 | O55: =N55+L55 -> 0 | P55: =E55-O55 -> 0 | Q55: =(F55/12)*12 -> 0 | R55: =Q55+O55 -> 0 | S55: =E55-R55 -> 0 | T55: =(F55/12)*12 -> 0 | U55: =R55+T55 -> 0 | V55: =E55-U55 -> 0 | W55: =(F55/12)*12 -> 0 | X55: =U55+W55 -> 0 | Y55: =E55-X55 -> 0 | Z55: =2992500*0 -> 0 | AA55: =E55-Z55 -> 0 | AB55: =(F55/12)*12 -> 0 | AC55: =Z55+AB55 -> 0 | AD55: =E55-AC55 -> 0 | AE55: =(F55/12)*12 -> 0 | AF55: =AC55+AE55 -> 0 | AG55: =E55-AF55 -> 0 | AH55: =(F55/12)*12 -> 0 | AI55: =AF55+AH55 -> 0 | AJ55: =E55-AI55 -> 0 | AQ55: =(F55/12)*7 -> 0 | AR55: =AI55+AQ55 -> 0 | AS55: =E55-AR55 -> 0 | BB55: =E55-AR55-AS55 -> 0
A56: =A55+1 -> 2 | B56: Mess Asisten + Tempat Kultur + Wc | C56: 38353 | D56: 20 | E56: =84240000*0 -> 0 | F56: =E56/D56 -> 0 | G56: =E56 -> 0 | H56: =((F56/12)*(13-IF(C56="","",MONTH(C56))))*10 -> 0 | I56: =H56 -> 0 | J56: =G56-I56 -> 0 | K56: =(F56/12)*12 -> 0 | L56: =I56+K56 -> 0 | M56: =E56-L56 -> 0 | N56: =(F56/12)*12 -> 0 | O56: =N56+L56 -> 0 | P56: =E56-O56 -> 0 | Q56: =(F56/12)*12 -> 0 | R56: =Q56+O56 -> 0 | S56: =E56-R56 -> 0 | T56: =(F56/12)*12 -> 0 | U56: =R56+T56 -> 0 | V56: =E56-U56 -> 0 | W56: =(F56/12)*12 -> 0 | X56: =U56+W56 -> 0 | Y56: =E56-X56 -> 0 | AA56: =E56-Z56 -> 0 | AB56: =(F56/12)*12 -> 0 | AC56: =Z56+AB56 -> 0 | AD56: =E56-AC56 -> 0 | AE56: =(F56/12)*12 -> 0 | AF56: =AC56+AE56 -> 0 | AG56: =E56-AF56 -> 0 | AH56: =(F56/12)*12 -> 0 | AI56: =AF56+AH56 -> 0 | AJ56: =E56-AI56 -> 0 | AQ56: =(F56/12)*7 -> 0 | AR56: =AI56+AQ56 -> 0 | AS56: =E56-AR56 -> 0 | BB56: =E56-AR56-AS56 -> 0
A57: =A56+1 -> 3 | B57: Rumah Genset Blok D & E | C57: 40544 | D57: 20 | E57: 150150000 | F57: =E57/D57 -> 7507500 | G57: =E57 -> 150150000 | I57: =H57 -> 0 | J57: =G57-I57 -> 150150000 | L57: =I57+K57 -> 0 | M57: =E57-L57 -> 150150000 | N57: =(F57/12)*12 -> 7507500 | O57: =N57+L57 -> 7507500 | P57: =E57-O57 -> 142642500 | Q57: =(F57/12)*12 -> 7507500 | R57: =Q57+O57 -> 15015000 | S57: =E57-R57 -> 135135000 | T57: =(F57/12)*12 -> 7507500 | U57: =R57+T57 -> 22522500 | V57: =E57-U57 -> 127627500 | W57: =(F57/12)*12 -> 7507500 | X57: =U57+W57 -> 30030000 | Y57: =E57-X57 -> 120120000 | Z57: 22522500 | AA57: =E57-Z57 -> 127627500 | AB57: =(F57/12)*12 -> 7507500 | AC57: =X57+AB57 -> 37537500 | AD57: =E57-AC57 -> 112612500 | AE57: =(F57/12)*12 -> 7507500 | AF57: =AC57+AE57 -> 45045000 | AG57: =E57-AF57 -> 105105000 | AH57: =(F57/12)*12 -> 7507500 | AI57: =AF57+AH57 -> 52552500 | AJ57: =E57-AI57 -> 97597500 | AK57: =(F57/12)*1 -> 625625 | AL57: =AI57+AK57 -> 53178125 | AM57: =E57-AL57 -> 96971875 | AN57: =(F57/12)*9 -> 5630625 | AO57: =AI57+AN57 -> 58183125 | AP57: =E57-AO57 -> 91966875 | AQ57: =(F57/12)*12 -> 7507500 | AR57: =AI57+AQ57 -> 60060000 | AS57: =E57-AR57 -> 90090000 | AT57: =(F57/12)*9 -> 5630625 | AU57: =AR57+AT57 -> 65690625 | AV57: =E57-AU57 -> 84459375 | AW57: =(F57/12)*12 -> 7507500 | AX57: =AR57+AW57 -> 67567500 | AY57: =E57-AX57 -> 82582500 | BB57: =E57-AX57-AY57 -> 0
A58: =A57+1 -> 4 | B58: Mess Asisten + Tempat Kultur + Wc + Kantin + mess feeder (11u) + Gudang Pakan (2 unit) | C58: 40544 | D58: 20 | E58: =104895000+84240000+40800000+19950000 -> 249885000 | F58: =E58/D58 -> 12494250 | G58: =E58 -> 249885000 | I58: =H58 -> 0 | J58: =G58-I58 -> 249885000 | L58: =I58+K58 -> 0 | M58: =E58-L58 -> 249885000 | N58: =(F58/12)*12 -> 12494250 | O58: =N58+L58 -> 12494250 | P58: =E58-O58 -> 237390750 | Q58: =(F58/12)*12 -> 12494250 | R58: =Q58+O58 -> 24988500 | S58: =E58-R58 -> 224896500 | T58: =(F58/12)*12 -> 12494250 | U58: =R58+T58 -> 37482750 | V58: =E58-U58 -> 212402250 | W58: =(F58/12)*12 -> 12494250 | X58: =U58+W58 -> 49977000 | Y58: =E58-X58 -> 199908000 | Z58: 37482750 | AA58: =E58-Z58 -> 212402250 | AB58: =(F58/12)*12 -> 12494250 | AC58: =X58+AB58 -> 62471250 | AD58: =E58-AC58 -> 187413750 | AE58: =(F58/12)*12 -> 12494250 | AF58: =AC58+AE58 -> 74965500 | AG58: =E58-AF58 -> 174919500 | AH58: =(F58/12)*12 -> 12494250 | AI58: =AF58+AH58 -> 87459750 | AJ58: =E58-AI58 -> 162425250 | AK58: =(F58/12)*1 -> 1041187.5 | AL58: =AI58+AK58 -> 88500938 | AM58: =E58-AL58 -> 1.6138406e+08 | AN58: =(F58/12)*9 -> 9370687.5 | AO58: =AI58+AN58 -> 96830438 | AP58: =E58-AO58 -> 1.5305456e+08 | AQ58: =(F58/12)*12 -> 12494250 | AR58: =AI58+AQ58 -> 99954000 | AS58: =E58-AR58 -> 149931000 | AT58: =(F58/12)*9 -> 9370687.5 | AU58: =AR58+AT58 -> 1.0932469e+08 | AV58: =E58-AU58 -> 1.4056031e+08 | AW58: =(F58/12)*12 -> 12494250 | AX58: =AR58+AW58 -> 112448250 | AY58: =E58-AX58 -> 137436750 | BB58: =E58-AX58-AY58 -> 0
