Workbook

Sheet AJE CAJE Juni 23
B2: Account No. | C2: Date | D2: Account Name | F2: WP Reff | G2: Balance Sheet | I2: PL | K2: Description
G3: Debit | H3: Credit | I3: Debit | J3: Credit
B5: CAJE 1 | D5: Akum. Peny. Mesin | G5: =J9 -> 2999996 | K5: Adj menyamakan nilai Peny
B6: CAJE 1 | D6: Akum. Peny. Peralatan Kantor | G6: =J10 -> 33313.229 | K6: =K5 -> Adj menyamakan nilai Peny
B7: CAJE 1 | D7: Penyusutan Bangunan | I7: 9784354.4 | K7: =K6 -> Adj menyamakan nilai Peny
B8: CAJE 1 | E8: Akum. Peny. Sumur Bor | H8: =I11 -> 3 | K8: =K7 -> Adj menyamakan nilai Peny
B9: =B7 -> CAJE 1 | E9: Penyusutan Mesin-Mesin | J9: 2999996 | K9: =K8 -> Adj menyamakan nilai Peny
B10: =B9 -> CAJE 1 | E10: Penyusutan Peralatan Kantor | J10: 33313.229 | K10: =K9 -> Adj menyamakan nilai Peny
B11: =B10 -> CAJE 1 | D11: Penyusutan Sumur Bor | I11: 3 | K11: =K10 -> Adj menyamakan nilai Peny
B12: =B11 -> CAJE 1 | E12: Akum Peny. Bangunan | G12: 4090645.9 | K12: =K11 -> Adj menyamakan nilai Peny
B13: =B12 -> CAJE 1 | E13: Akum. Peny. Kendaraan | H13: 2 | K13: =K12 -> Adj menyamakan nilai Peny
B14: =B13 -> CAJE 1 | D14: Akum. Peny. Peralatan Produksi | G14: 1 | K14: =K13 -> Adj menyamakan nilai Peny
B15: =B14 -> CAJE 1 | D15: Rumah Tangga Kantor | J15: 13874999 | K15: =K14 -> Adj menyamakan nilai Peny
B17: RKLS 1 | D17: Depreciation | I17: =SUM(J18:J23) -> 1.1571403e+09 | K17: Reklas Beban Peny GA ke COGS
B18: =B17 -> RKLS 1 | E18: Penyusutan Bangunan | J18: 616777705 | K18: =K17 -> Reklas Beban Peny GA ke COGS
B19: =B18 -> RKLS 1 | E19: Penyusutan Mesin-Mesin | J19: 389528236 | K19: =K18 -> Reklas Beban Peny GA ke COGS
B20: =B19 -> RKLS 1 | E20: Penyusutan Kendaraan | J20: 1.0188992e+08 | K20: =K19 -> Reklas Beban Peny GA ke COGS
B21: =B20 -> RKLS 1 | E21: Penyusutan Peralatan Produksi | J21: 22060056 | K21: =K20 -> Reklas Beban Peny GA ke COGS
B22: =B21 -> RKLS 1 | E22: Penyusutan Sumur Bor | J22: 13009413 | K22: =K21 -> Reklas Beban Peny GA ke COGS
E23: Penyusutan Electricity Instalasi | J23: 13875000 | K23: =K22 -> Reklas Beban Peny GA ke COGS
B25: CAJE 2 | D25: PT Indokom Samudra Persada - Utang | G25: 7919262741 | K25: Adj Menyamakan Utang Piutang Afiliasi IAS-ISP Jun 23
B26: =B25 -> CAJE 2 | E26: PT Indokom Samudra Persada - Piutang | H26: =G25 -> 7919262741 | K26: =K25 -> Adj Menyamakan Utang Piutang Afiliasi IAS-ISP Jun 23
B28: CAJE 3 | D28: Pajak Lain-Lain | I28: =H29-G30 -> 10621125 | K28: Adj atas Pemb Pajak PPh 21 & 23
B29: =B28 -> CAJE 3 | E29: Utang PPh 21 | H29: 10621147 | K29: =K28 -> Adj atas Pemb Pajak PPh 21 & 23
B30: CAJE 3 | E30: Utang PPh 23 | G30: 22 | K30: =K29 -> Adj atas Pemb Pajak PPh 21 & 23
B32: CAJE 4 | D32: Materai, Koran & Majalah | I32: 2335000 | K32: Adj angka minus
B33: =B32 -> CAJE 4 | D33: Surat-Surat Perizinan | I33: 873540 | K33: =K32 -> Adj angka minus
B34: =B33 -> CAJE 4 | E34: BYMH | H34: =SUM(I32:I33) -> 3208540 | K34: =K33 -> Adj angka minus
B36: CAJE 5 | D36: BYMH | G36: =SUM(H37:H39) -> 2443062
B37: =B36 -> CAJE 5 | E37: Utang PPh 21 | H37: 2443062
B38: =B37 -> CAJE 5 | E38: Utang Pph 22 | H38: =49398282*0 -> 0
B39: =B38 -> CAJE 5 | E39: Utang Pph 23 | H39: =33436121*0 -> 0
B41: CAJE 6 | D41: BYMH
B42: =B41 -> CAJE 6 | E42: Gaji
B45: CAJE 7 | D45: Aset dalam Pembangunan | G45: 168752996
B46: =B45 -> CAJE 7 | D46: Mesin Dalam Pelaksanaan | G46: 192000000
B47: =B46 -> CAJE 7 | E47: CV Kanian Persada | H47: =SUM(G45:G46) -> 360752996
D48: (Adj Aset dalam Proses ke Piutang CV Kanian)
B50: CAJE 8 | D50: Beban Pajak Kini | I50: =SUM(H51:H53) -> 301219820 | K50: Perhitungan Pajak Badan Juni 2023
B51: =B50 -> CAJE 8 | E51: Prepaid PPh 25 | H51: 55018816 | K51: =K50 -> Perhitungan Pajak Badan Juni 2023
B52: =B51 -> CAJE 8 | E52: Prepaid PPh 22 | H52: 65023075 | K52: =K51 -> Perhitungan Pajak Badan Juni 2023
B53: =B52 -> CAJE 8 | E53: Utang Pph 29 | H53: 181177929 | K53: =K52 -> Perhitungan Pajak Badan Juni 2023

Sheet AJE CAJE Juni 24
B3: Account No. | C3: Date | D3: Account Name | F3: WP Reff | G3: Balance Sheet | I3: PL | K3: Description
G4: Debit | H4: Credit | I4: Debit | J4: Credit
B6: CAJE 1 | D6: Akum. Peny. Kendaraan | G6: 12187500 | K6: Adj menyamakan nilai Peny
B7: =B6 -> CAJE 1 | E7: Akum. Peny. Kendaraan Alat Berat | H7: =G6 -> 12187500 | K7: =K6 -> Adj menyamakan nilai Peny
B9: CAJE 2 | E9: Akum Peny. Bangunan | H9: 2 | K9: Adj menyamakan nilai Peny
B10: =B9 -> CAJE 2 | D10: Akum. Peny. Mesin | G10: 2 | K10: =K9 -> Adj menyamakan nilai Peny
B11: =B10 -> CAJE 2 | E11: Akum. Peny. Peralatan Kantor | H11: 1 | K11: =K10 -> Adj menyamakan nilai Peny
B12: =B11 -> CAJE 2 | E12: Akum. Peny. Peralatan Produksi | H12: 1 | K12: =K11 -> Adj menyamakan nilai Peny
B13: =B12 -> CAJE 2 | E13: Akum. Peny. Sumur Bor | H13: 3 | K13: =K12 -> Adj menyamakan nilai Peny
B14: =B13 -> CAJE 2 | D14: Penyusutan Peralatan Kantor | I14: 1 | K14: =K13 -> Adj menyamakan nilai Peny
B15: =B14 -> CAJE 2 | D15: Penyusutan Bangunan | I15: 1 | K15: =K14 -> Adj menyamakan nilai Peny
B16: =B15 -> CAJE 2 | E16: Penyusutan Mesin-Mesin | J16: 2 | K16: =K15 -> Adj menyamakan nilai Peny
B17: =B16 -> CAJE 2 | D17: Penyusutan Peralatan Produksi | I17: 1 | K17: =K16 -> Adj menyamakan nilai Peny
B18: =B17 -> CAJE 2 | D18: Penyusutan Sumur Bor | I18: 3 | K18: =K17 -> Adj menyamakan nilai Peny
B20: RKLS 1 | D20: Depreciation | I20: =SUM(J21:J25) -> 1040987145 | K20: Reklas Beban Peny GA ke COGS
B21: =B20 -> RKLS 1 | E21: Penyusutan Bangunan | J21: 616777705 | K21: =K20 -> Reklas Beban Peny GA ke COGS
B22: =B21 -> RKLS 1 | E22: Penyusutan Mesin-Mesin | J22: 389528236 | K22: =K21 -> Reklas Beban Peny GA ke COGS
B23: =B22 -> RKLS 1 | E23: Penyusutan Kendaraan | J23: 12187500 | K23: =K22 -> Reklas Beban Peny GA ke COGS
B24: =B23 -> RKLS 1 | E24: Penyusutan Peralatan Produksi | J24: 9484291 | K24: =K23 -> Reklas Beban Peny GA ke COGS
B25: =B24 -> RKLS 1 | E25: Penyusutan Sumur Bor | J25: 13009413 | K25: =K24 -> Reklas Beban Peny GA ke COGS
B27: CAJE 3 | D27: Eastern Fish Company LLC | G27: 1451616400 | K27: Adj Penj exp dari bulan selanjutnya
B28: =B27 -> CAJE 3 | D28: Censea Inc | G28: 19756663414 | K28: =K27 -> Adj Penj exp dari bulan selanjutnya
B29: =B28 -> CAJE 3 | E29: Udang-Exp | J29: =SUM(G27:G28) -> 21208279814 | K29: =K28 -> Adj Penj exp dari bulan selanjutnya
B31: CAJE 4 | D31: Biaya yang masih dibayar | G31: 15000000 | K31: Adj atas Beban Sewa yang sdh di akui di 2023
B32: =B31 -> CAJE 4 | E32: Biaya Sewa IPAL | J32: =G31 -> 15000000 | K32: =K31 -> Adj atas Beban Sewa yang sdh di akui di 2023
B34: CAJE 5 | D34: PT Indokom Samudra Persada - Utang | G34: 4045423564 | K34: Adj Menyamakan Utang Piutang Afiliasi IAS-ISP Jun 24
B35: =B34 -> CAJE 5 | E35: PT Indokom Samudra Persada - Piutang | H35: =G34 -> 4045423564 | K35: =K34 -> Adj Menyamakan Utang Piutang Afiliasi IAS-ISP Jun 24
B37: CAJE 6 | D37: Pajak Lain-Lain | I37: 26704968 | K37: Adj atas Pemb Pajak PPh 21
B38: =B37 -> CAJE 6 | E38: Utang PPh 21 | H38: =I37 -> 26704968 | K38: =K37 -> Adj atas Pemb Pajak PPh 21
B40: CAJE 7 | D40: Prepaid PPh 22 | G40: =H41 -> 15505370 | K40: Adj atas Pemb Pajak PPh 22
B41: =B40 -> CAJE 7 | E41: Utang Pph 22 | H41: 15505370 | K41: =K40 -> Adj atas Pemb Pajak PPh 22
B43: CAJE 8 | D43: Prepaid 25 | G43: 158105967 | K43: Adj atas Pemb Pajak PPh 25
B44: =B43 -> CAJE 8 | E44: Utang Pph 25 | H44: =G43 -> 158105967 | K44: =K43 -> Adj atas Pemb Pajak PPh 25
B46: CAJE 9 | D46: Utang Pph 23 | G46: 1 | K46: Adj atas Pemb Pajak PPh 23
B47: =B46 -> CAJE 9 | E47: Pajak Lain-Lain | J47: 1 | K47: =K46 -> Adj atas Pemb Pajak PPh 23
B49: CAJE 10 | D49: BYMH | G49: =SUM(H50:H53) -> 90033000 | K49: Reklas atas utang Pajak
B50: =B49 -> CAJE 10 | E50: Utang Pph 25 | H50: 52701989 | K50: =K49 -> Reklas atas utang Pajak
B51: =B50 -> CAJE 10 | E51: Utang PPh 21 | H51: 3477203 | K51: =K50 -> Reklas atas utang Pajak
B52: =B51 -> CAJE 10 | E52: Utang Pph 22 | H52: 13312446 | K52: =K51 -> Reklas atas utang Pajak
B53: =B52 -> CAJE 10 | E53: Utang Pph 23 | H53: 20541362 | K53: =K52 -> Reklas atas utang Pajak
B55: CAJE 11 | D55: BYMH | G55: 19982271 | K55: Reklas atas utang Gaji
B56: =B55 -> CAJE 11 | E56: Gaji | H56: =G55 -> 19982271 | K56: =K55 -> Reklas atas utang Gaji
B58: CAJE 12 | D58: Beban Pajak Kini | I58: =SUM(H59:H61) -> 301219820 | K58: Perhitungan Pajak Badan Juni 2024
B59: =B58 -> CAJE 12 | E59: Prepaid PPh 22 | H59: 15505370 | K59: =K58 -> Perhitungan Pajak Badan Juni 2024
B60: =B59 -> CAJE 12 | E60: Prepaid PPh 25 | H60: 158105967 | K60: =K59 -> Perhitungan Pajak Badan Juni 2024
B61: =B60 -> CAJE 12 | E61: Utang Pph 29 | H61: 1.2760848e+08 | K61: =K60 -> Perhitungan Pajak Badan Juni 2024
B63: CAJE 13 | D63: ARF BTPN | G63: =SUM(H64:H65) -> 11822413897 | K63: Adj Piutang ke Hutang Bank
B64: =B63 -> CAJE 13 | E64: Chensea | H64: 10370797497 | K64: =K63 -> Adj Piutang ke Hutang Bank
B65: =B64 -> CAJE 13 | E65: Eastern fish | H65: 1451616400 | K65: =K64 -> Adj Piutang ke Hutang Bank

Sheet AJE CAJE Sept 23
B2: Account No. | C2: Date | D2: Account Name | F2: WP Reff | G2: Balance Sheet | I2: PL | K2: Description
G3: Debit | H3: Credit | I3: Debit | J3: Credit
B5: CAJE 1 | D5: Akum. Peny. Mesin | G5: =J9 -> 5999994 | K5: Adj menyamakan nilai Peny
B6: CAJE 1 | D6: Akum. Peny. Peralatan Kantor | G6: =J10 -> 133252.23 | K6: =K5 -> Adj menyamakan nilai Peny
B7: CAJE 1 | E7: Penyusutan Bangunan | J7: 8181288.9 | K7: =K6 -> Adj menyamakan nilai Peny
B8: CAJE 1 | E8: Akum. Peny. Sumur Bor | H8: =I11 -> 3.75 | K8: =K7 -> Adj menyamakan nilai Peny
B9: =B7 -> CAJE 1 | E9: Penyusutan Mesin-Mesin | J9: 5999994 | K9: =K8 -> Adj menyamakan nilai Peny
B10: =B9 -> CAJE 1 | E10: Penyusutan Peralatan Kantor | J10: 133252.23 | K10: =K9 -> Adj menyamakan nilai Peny
B11: =B10 -> CAJE 1 | D11: Penyusutan Sumur Bor | I11: 3.75 | K11: =K10 -> Adj menyamakan nilai Peny
B12: =B11 -> CAJE 1 | E12: Akum Peny. Bangunan | G12: =J7 -> 8181288.9 | K12: =K11 -> Adj menyamakan nilai Peny
B13: =B12 -> CAJE 1 | D13: Akum. Peny. Peralatan Produksi | G13: =J14 -> 0.5625 | K13: =K12 -> Adj menyamakan nilai Peny
B14: =B13 -> CAJE 1 | E14: Penyusutan Peralatan Produksi | J14: 0.5625 | K14: =K13 -> Adj menyamakan nilai Peny
B16: RKLS 1 | D16: Depreciation | I16: =SUM(J17:J22) -> 1696263520 | K16: Reklas Beban Peny GA ke COGS
B17: =B16 -> RKLS 1 | E17: Penyusutan Bangunan | J17: 904354058 | K17: =K16 -> Reklas Beban Peny GA ke COGS
B18: =B17 -> RKLS 1 | E18: Penyusutan Mesin-Mesin | J18: 584292354 | K18: =K17 -> Reklas Beban Peny GA ke COGS
B19: =B18 -> RKLS 1 | E19: Penyusutan Kendaraan | J19: 134200406 | K19: =K18 -> Reklas Beban Peny GA ke COGS
B20: =B19 -> RKLS 1 | E20: Penyusutan Peralatan Produksi | J20: 33090083 | K20: =K19 -> Reklas Beban Peny GA ke COGS
B21: =B20 -> RKLS 1 | E21: Penyusutan Sumur Bor | J21: 19514119 | K21: =K20 -> Reklas Beban Peny GA ke COGS
B22: =B21 -> RKLS 1 | E22: Penyusutan Electricity Instalasi | J22: 20812500 | K22: =K21 -> Reklas Beban Peny GA ke COGS
B24: CAJE 2 | D24: PT Indokom Samudra Persada - Utang | G24: 8.9856203e+09 | K24: Adj Menyamakan Utang Piutang Afiliasi IAS-ISP Jun 23
B25: =B24 -> CAJE 2 | E25: PT Indokom Samudra Persada - Piutang | H25: =G24 -> 8.9856203e+09 | K25: =K24 -> Adj Menyamakan Utang Piutang Afiliasi IAS-ISP Jun 23
B27: CAJE 3 | D27: Pajak Lain-Lain | I27: =SUM(H28:H29)-G29 -> 14980428 | K27: Adj atas Pemb Pajak PPh 21 & 23
B28: =B27 -> CAJE 3 | E28: Utang PPh 21 | H28: 14980451 | K28: =K27 -> Adj atas Pemb Pajak PPh 21 & 23
B29: CAJE 3 | E29: Utang PPh 23 | G29: 23 | K29: =K28 -> Adj atas Pemb Pajak PPh 21 & 23
B31: CAJE 4 | D31: Materai, Koran & Majalah | I31: 3620000 | K31: Adj angka minus
B32: =B31 -> CAJE 4 | D32: Surat-Surat Perizinan | I32: 21493790 | K32: =K31 -> Adj angka minus
B33: =B32 -> CAJE 4 | E33: BYMH | H33: =SUM(I31:I32) -> 25113790 | K33: =K32 -> Adj angka minus
B35: CAJE 5 | D35: BYMH | G35: =SUM(H36:H38) -> 47192104 | K35: Reklas atas utang Pajak
B36: =B35 -> CAJE 5 | E36: Utang PPh 21 | H36: 2479613 | K36: =K35 -> Reklas atas utang Pajak
B37: =B36 -> CAJE 5 | E37: Utang Pph 22 | H37: 30384164 | K37: =K36 -> Reklas atas utang Pajak
B38: =B37 -> CAJE 5 | E38: Utang Pph 23 | H38: 14328327 | K38: =K37 -> Reklas atas utang Pajak
B40: CAJE 7 | D40: Aset dalam Pembangunan | G40: 168752996
B41: =B40 -> CAJE 7 | D41: Mesin Dalam Pelaksanaan | G41: 192000000
B42: =B41 -> CAJE 7 | E42: CV Kanian Persada | H42: =SUM(G40:G41) -> 360752996
D43: (Adj Aset dalam Proses ke Piutang CV Kanian)
B45: RLKS 2 | D45: PT Irian Marine Product Development | G45: 2e+08 | K45: Reklas Atas Piutang Irian Marine
B46: =B45 -> RLKS 2 | E46: PT Irian Marine Product Development | H46: =G45 -> 2e+08 | K46: =K45 -> Reklas Atas Piutang Irian Marine
B49: RLKS 3 | D49: Akum. Peny. Kendaraan | G49: 18281250 | K49: Reklas akm penyusutan Aset
B50: =B49 -> RLKS 3 | E50: Akum. Peny. Kendaraan Alat Berat | H50: =G49 -> 18281250 | K50: =K49 -> Reklas akm penyusutan Aset
B52: CAJE 8 | D52: Rumah Tangga Kantor | G52: =H53 -> 2 | K52: Adj Akm Penyusutan
B53: =B52 -> CAJE 8 | E53: Akum. Peny. Kendaraan | H53: 2 | K53: =K52 -> Adj Akm Penyusutan
B55: CAJE 9 | D55: Prepaid PPh 22 | G55: =H56 -> 25660083 | K55: Adj atas Pemb Pajak PPh 22
B56: CAJE 9 | E56: Utang Pph 22 | H56: 25660083 | K56: Adj atas Pemb Pajak PPh 22
B58: CAJE 10 | D58: Prepaid PPh 25 | G58: 41264112 | K58: Adj atas Pemb Pajak PPh 25
B59: CAJE 10 | E59: Utang Pph 25 | H59: =G58 -> 41264112 | K59: =K58 -> Adj atas Pemb Pajak PPh 25
B61: CAJE 11 | D61: Penjualan Lain-Lain | I61: 11038330 | K61: Adj Penjualan Lainnya
B62: =B61 -> CAJE 11 | E62: Pendapatan Lainnya | J62: =I61 -> 11038330 | K62: =K61 -> Adj Penjualan Lainnya
B64: CAJE 12 | D64: Slade Gorton,,Inc | G64: 15262058 | K64: Adj atas Utang Usaha
B65: =B64 -> CAJE 12 | E65: Lain-lain (masing-masing di bawah Rp 20.000.000) | H65: =G64 -> 15262058 | K65: =K64 -> Adj atas Utang Usaha
B67: CAJE 13 | D67: Beban Pajak Kini | I67: =SUM(H68:H70) -> 299497000 | K67: Perhitungan Pajak Badan Sept 2023
B68: =B67 -> CAJE 13 | E68: Prepaid PPh 25 | H68: 41264112 | K68: =K67 -> Perhitungan Pajak Badan Sept 2023
B69: =B68 -> CAJE 13 | E69: Prepaid PPh 22 | H69: 25660083 | K69: =K68 -> Perhitungan Pajak Badan Sept 2023
B70: =B69 -> CAJE 13 | E70: Utang Pph 29 | H70: ='SPT Badan'!F48 -> 232572805 | K70: =K69 -> Perhitungan Pajak Badan Sept 2023
B72: CAJE 14 | D72: Imbalan Pasca Kerja | I72: 81714215
B73: =B72 -> CAJE 14 | E73: Liabilitas imbalan pasca kerja | H73: =I72 -> 81714215

Sheet AJE CAJE Sept 24
B3: Account No. | C3: Date | D3: Account Name | F3: WP Reff | G3: Balance Sheet | I3: PL | K3: Description
G4: Debit | H4: Credit | I4: Debit | J4: Credit
B6: CAJE 1 | D6: Akum. Peny. Kendaraan | G6: 13076156 | K6: Adj menyamakan nilai Peny
B7: =B6 -> CAJE 1 | D7: Penyusutan Kendaraan | I7: =H8-G6 -> 5205094.1 | K7: Adj menyamakan nilai Peny
B8: =B6 -> CAJE 1 | E8: Akum. Peny. Kendaraan Alat Berat | H8: 18281250 | K8: =K6 -> Adj menyamakan nilai Peny
B10: CAJE 2 | E10: Akum Peny. Bangunan | H10: 3 | K10: Adj menyamakan nilai Peny
B11: =B10 -> CAJE 2 | D11: Akum. Peny. Mesin | H11: =63019280.937499-3 -> 63019278 | K11: =K10 -> Adj menyamakan nilai Peny
B12: =B11 -> CAJE 2 | D12: Akum. Peny. Peralatan Kantor | G12: 340165.67 | K12: =K11 -> Adj menyamakan nilai Peny
B13: =B12 -> CAJE 2 | D13: Akum. Peny. Peralatan Produksi | G13: 2364210.8 | K13: =K12 -> Adj menyamakan nilai Peny
B14: =B13 -> CAJE 2 | E14: Akum. Peny. Sumur Bor | H14: 4 | K14: =K13 -> Adj menyamakan nilai Peny
B15: =B14 -> CAJE 2 | E15: Penyusutan Peralatan Kantor | J15: =G12 -> 340165.67 | K15: =K14 -> Adj menyamakan nilai Peny
B16: =B15 -> CAJE 2 | D16: Penyusutan Bangunan | I16: =H10-0.01800537109375 -> 2.9819946 | K16: =K15 -> Adj menyamakan nilai Peny
B17: =B16 -> CAJE 2 | E17: Penyusutan Mesin-Mesin | I17: =H11 -> 63019278 | J17: =G11 -> 0 | K17: =K16 -> Adj menyamakan nilai Peny
B18: =B17 -> CAJE 2 | E18: Penyusutan Peralatan Produksi | J18: =G13 -> 2364210.8 | K18: =K17 -> Adj menyamakan nilai Peny
B19: =B18 -> CAJE 2 | D19: Penyusutan Sumur Bor | I19: =H14 -> 4 | K19: =K18 -> Adj menyamakan nilai Peny
B21: RKLS 1 | D21: Depreciation | I21: =SUM(J22:J26) -> 1.622489e+09 | K21: Reklas Beban Peny GA ke COGS
B22: =B21 -> RKLS 1 | E22: Penyusutan Bangunan | J22: =925166558.1+0.881 -> 9.2516656e+08 | K22: =K21 -> Reklas Beban Peny GA ke COGS
B23: =B22 -> RKLS 1 | E23: Penyusutan Mesin-Mesin | J23: 6.4731163e+08 | K23: =K22 -> Reklas Beban Peny GA ke COGS
B24: =B23 -> RKLS 1 | E24: Penyusutan Kendaraan | J24: 18634480 | K24: =K23 -> Reklas Beban Peny GA ke COGS
B25: =B24 -> RKLS 1 | E25: Penyusutan Peralatan Produksi | J25: 11862224 | K25: =K24 -> Reklas Beban Peny GA ke COGS
B26: =B25 -> RKLS 1 | E26: Penyusutan Sumur Bor | J26: 19514119 | K26: =K25 -> Reklas Beban Peny GA ke COGS
B28: CAJE 3 | D28: Eastern Fish Company LLC | K28: Adj Penj exp dari bulan selanjutnya
B29: =B28 -> CAJE 3 | D29: Censea Inc | K29: =K28 -> Adj Penj exp dari bulan selanjutnya
B30: =B29 -> CAJE 3 | E30: Udang-Exp | K30: =K29 -> Adj Penj exp dari bulan selanjutnya
B32: CAJE 4 | D32: Biaya yang masih dibayar | G32: 15000000 | K32: Adj atas Beban Sewa yang sdh di akui di 2023
B33: =B32 -> CAJE 4 | E33: Biaya Sewa IPAL | J33: =G32 -> 15000000 | K33: =K32 -> Adj atas Beban Sewa yang sdh di akui di 2023
B35: CAJE 5 | D35: PT Indokom Samudra Persada - Utang | G35: 2.760129e+10 | K35: Adj Menyamakan Utang Piutang Afiliasi IAS-ISP Jun 24
B36: =B35 -> CAJE 5 | E36: PT Indokom Samudra Persada - Piutang | H36: =G35 -> 2.760129e+10 | K36: =K35 -> Adj Menyamakan Utang Piutang Afiliasi IAS-ISP Jun 24
B38: CAJE 6 | D38: Pajak Lain-Lain | K38: Adj atas Pemb Pajak PPh 21
B39: =B38 -> CAJE 6 | E39: Utang PPh 21 | K39: =K38 -> Adj atas Pemb Pajak PPh 21
B41: CAJE 7 | D41: Prepaid PPh 22 | G41: 24522154 | K41: Adj atas Pemb Pajak PPh 22
B42: =B41 -> CAJE 7 | E42: Utang Pph 22 | H42: =G41 -> 24522154 | K42: =K41 -> Adj atas Pemb Pajak PPh 22
B44: CAJE 8 | D44: Prepaid 25 | G44: 316211934 | K44: Adj atas Pemb Pajak PPh 25
B45: =B44 -> CAJE 8 | E45: Utang Pph 25 | H45: =G44 -> 316211934 | K45: =K44 -> Adj atas Pemb Pajak PPh 25
B47: CAJE 9 | D47: Utang Pph 23 | K47: Adj atas Pemb Pajak PPh 23
B48: =B47 -> CAJE 9 | E48: Pajak Lain-Lain | K48: =K47 -> Adj atas Pemb Pajak PPh 23
B50: CAJE 10 | D50: BYMH | G50: =SUM(H51:H54) -> 165770757 | K50: Reklas atas utang Pajak
B51: =B50 -> CAJE 10 | E51: Utang Pph 25 | H51: 52701989 | K51: =K50 -> Reklas atas utang Pajak
B52: =B51 -> CAJE 10 | E52: Utang PPh 21 | H52: 4471644 | K52: =K51 -> Reklas atas utang Pajak
B53: =B52 -> CAJE 10 | E53: Utang Pph 22 | H53: 88055762 | K53: =K52 -> Reklas atas utang Pajak
B54: =B53 -> CAJE 10 | E54: Utang Pph 23 | H54: 20541362 | K54: =K53 -> Reklas atas utang Pajak
B56: CAJE 11 | D56: BYMH | G56: 219882092 | K56: Reklas atas utang Gaji
B57: =B56 -> CAJE 11 | E57: Gaji | H57: =G56 -> 219882092 | K57: =K56 -> Reklas atas utang Gaji
B59: CAJE 12 | D59: Beban Pajak Kini | I59: =SUM(H60:H62) -> 1066942140 | K59: Perhitungan Pajak Badan September 2024
B60: =B59 -> CAJE 12 | E60: Prepaid PPh 22 | H60: 24522154 | K60: =K59 -> Perhitungan Pajak Badan September 2024
B61: =B60 -> CAJE 12 | E61: Prepaid PPh 25 | H61: 316211934 | K61: =K60 -> Perhitungan Pajak Badan September 2024
B62: =B61 -> CAJE 12 | E62: Utang Pph 29 | H62: ='SPT Badan'!D48 -> 7.2620805e+08 | K62: =K61 -> Perhitungan Pajak Badan September 2024
B64: CAJE 13 | D64: Uang Muka Pembelian Bahan Baku | G64: 1.1680623e+09 | K64: Adj atas Uang Muka Pembelian Bahan Baku-Udang
B65: =B64 -> CAJE 13 | E65: Shaka Bahari Abadi, PT | H65: =G64 -> 1.1680623e+09 | K65: =K64 -> Adj atas Uang Muka Pembelian Bahan Baku-Udang
B67: CAJE 14 | D67: Pembelian Udang | I67: =H70 -> 9055934 | K67: Pembelian Bahan Baku
B68: =B67 -> CAJE 14 | D68: Bahan Baku & Pembantunya | I68: =H69+H71+H72 -> 133305163 | K68: Pembelian Bahan Pembantu
B69: =B68 -> CAJE 14 | E69: Mitra Lestari Mandiri | H69: 72788250 | K69: Bahan Pembantu
B70: =B69 -> CAJE 14 | E70: Grahamakmur Ciptapratama | H70: 9055934 | K70: Bahan Baku
B71: =B70 -> CAJE 14 | E71: PT Gemilang Primajaya Trimandiri | H71: 48965375 | K71: Bahan Pembantu
B72: =B71 -> CAJE 14 | E72: Nusa Jaya | H72: 11551538 | K72: Bahan Pembantu
B74: RLKS 2 | D74: Denda Pajak | I74: =J75 -> 0 | K74: Pajak atas PPH 25 Badan atas pengungkapan ketidak benaran masa Des 2018 atas Surat Nomor: S-II/HPBP/WPJ.28/2024 | L74: 2085951250
B75: =B74 -> RLKS 2 | E75: Pajak Lain-Lain | J75: =2085951250*0 -> 0 | K75: =K74 -> Pajak atas PPH 25 Badan atas pengungkapan ketidak benaran masa Des 2018 atas Surat Nomor: S-II/HPBP/WPJ.28/2024
B77: CAJE 15 | D77: Censea Inc | G77: 2304857600 | K77: Censea (PO. 71389)
B78: =B77 -> CAJE 15 | D78: Censea Inc | G78: =1769550400*0 -> 0 | K78: Censea (PO. 71390)
B79: =B78 -> CAJE 15 | D79: Slade Gorton,,Inc | G79: 1783098720 | K79: Slade Gorton (PO. 309485)
B80: =B79 -> CAJE 15 | D80: Censea Inc | G80: 1998078000 | K80: Censea (PO. 71226)
B81: =B80 -> CAJE 15 | D81: Censea Inc | G81: 1930996000 | K81: Censea (PO. 71658)
B82: =B81 -> CAJE 15 | E82: Udang - Exp | J82: =SUM(G77:G81) -> 8017030320
D83: (Adj tarik penjualan dari bulan selanjutnya)
B85: CAJE 16 | D85: Angkut | G85: =J89 -> 235926918
B86: =B85 -> CAJE 16 | D86: BYMH | G86: =J88 -> 203119924
B88: =B86 -> CAJE 16 | E88: Rumah Tangga Kantor | J88: 203119924
B89: =B88 -> CAJE 16 | E89: Pengiriman | J89: 235926918
B91: CAJE 17 | D91: PT Indonesia Makan Udang | G91: =J92 -> 804952539
B92: =B91 -> CAJE 17 | E92: Pembelian Udang | J92: 804952539
B94: ACJE 18 | D94: Biaya Emisi Saham | G94: =H95 -> 3115944915
B95: =B94 -> ACJE 18 | E95: Biaya Pra IPO | H95: 3115944915
D96: (Adj atas Biaya Pra IPO ke Biaya Emisi Saham)
B98: =B99 -> AJE 19 | D98: Tenaga Ahli / Konsultan | G98: =H99 -> 32500000
B99: AJE 19 | E99: Biaya Pra IPO | H99: 32500000
D100: (Adj atas Biaya Consultant)
B102: AJE 20 | D102: Pengiriman | I102: =1062458672.87 -> 1.0624587e+09 | K102: =I102-J102 -> 1.0624587e+09 | O102: 1.1556056e+09
B103: =B102 -> AJE 20 | E103: Angkut | H103: =I102 -> 1.0624587e+09 | N103: =O102 -> 1.1556056e+09
B105: CAJE 21 | D105: Andalan Traiding Mina, CV | G105: =390700399.72 -> 3.907004e+08 | M105: 3.907004e+08
B106: CAJE 21 | D106: Nerimo Ing Pandum, CV | G106: =200753868.45 -> 2.0075387e+08
B107: CAJE 21 | E107: Pembelian Udang | J107: =SUM(G105:G106) -> 5.9145427e+08 | P107: =SUM(M105:M105) -> 3.907004e+08
B109: CAJE 22 | D109: Imbalan Pasca Kerja | I109: 209687496 | O109: 209687496
B110: =B109 -> CAJE 22 | E110: Liabilitas imbalan pasca kerja | H110: =I109 -> 209687496 | N110: =O109 -> 209687496

Sheet AJE CAJE Des 24
A2: Account No. | B2: Date | C2: Account Name | E2: WP Reff | F2: Balance Sheet | H2: PL | J2: Description
F3: Debit | G3: Credit | H3: Debit | I3: Credit
H4: 0.25
A5: CAJE 1 | C5: Akum. Peny. Sumur Bor | F5: =I16 -> 5655776 | J5: Adj menyamakan nilai Peny
A6: =A5 -> CAJE 1 | C6: Akum. Peny. Peralatan Produksi | F6: =I15 -> 5036130.8 | J6: Adj menyamakan nilai Peny
A7: =A6 -> CAJE 1 | C7: Akum. Peny. Mesin | F7: =I14 -> 4.473959 | J7: Adj menyamakan nilai Peny
A8: =A7 -> CAJE 1 | C8: Akum. Peny. Peralatan Kantor | F8: =I13 -> 2289582 | J8: Adj menyamakan nilai Peny
A9: =A8 -> CAJE 1 | C9: Akum. Peny. Kendaraan | F9: =I12 -> 6093750 | J9: Adj menyamakan nilai Peny
A10: =A9 -> CAJE 1 | D10: Akum Peny. Bangunan | G10: =H11 -> 3.2833338 | J10: Adj menyamakan nilai Peny
A11: CAJE 1 | C11: Penyusutan Bangunan | H11: =2.80000019073486+0.483333587646484 -> 3.2833338 | J11: Adj menyamakan nilai Peny
A12: =A11 -> CAJE 1 | D12: Penyusutan Kendaraan | I12: =6093749.5+0.5 -> 6093750 | J12: Adj menyamakan nilai Peny
A13: =A12 -> CAJE 1 | D13: Penyusutan Peralatan Kantor | I13: 2289582 | J13: Adj menyamakan nilai Peny
A14: =A13 -> CAJE 1 | D14: Penyusutan Mesin-Mesin | I14: =4+0.473958969116211 -> 4.473959 | J14: Adj menyamakan nilai Peny
A15: =A14 -> CAJE 1 | D15: Penyusutan Peralatan Produksi | I15: =5036131.14583333-0.312499761581421 -> 5036130.8 | J15: Adj menyamakan nilai Peny
A16: =A15 -> CAJE 1 | D16: Penyusutan Sumur Bor | I16: =5655776.25-0.25 -> 5655776 | J16: Adj menyamakan nilai Peny
A18: RLKS 1 | C18: Akum. Peny. Kendaraan | F18: =G19 -> 18281250
A19: RLKS 1 | D19: Akum. Peny. Kendaraan Alat Berat | G19: =ROUND(18281250,0) -> 18281250
A22: CAJE 2 | C22: Depreciation | H22: =SUM(I23:I27) -> 2.2689685e+09 | J22: Reklas Beban Peny GA ke COGS
A23: =A22 -> CAJE 2 | D23: Penyusutan Bangunan | I23: 1.2335554e+09 | J23: Reklas Beban Peny GA ke COGS
A24: =A23 -> CAJE 2 | D24: Penyusutan Mesin-Mesin | I24: 7.7905647e+08 | J24: Reklas Beban Peny GA ke COGS
A25: =A24 -> CAJE 2 | D25: Penyusutan Kendaraan | I25: 222061098 | J25: Reklas Beban Peny GA ke COGS
A26: =A25 -> CAJE 2 | D26: Penyusutan Peralatan Produksi | I26: 13932449 | J26: Reklas Beban Peny GA ke COGS
A27: =A26 -> CAJE 2 | D27: Penyusutan Sumur Bor | I27: 20363044 | J27: Reklas Beban Peny GA ke COGS
A29: CAJE 3 | C29: Biaya Emisi Saham | F29: =G30 -> 3115944915
A30: =A29 -> CAJE 3 | D30: Biaya Pra IPO | G30: 3115944915
C31: (Adj atas Biaya Pra IPO ke Biaya Emisi Saham)
A33: CAJE 4 | C33: Accrued Expanse - Angkut | F33: =1288005813.6*0 -> 0 | J33: PT Rahayu Perdana Trans
A34: CAJE 4 | C34: Accrued Expanse - Angkut | F34: =1186562411.6*0 -> 0 | J34: PT Samudera Naga Global
A35: CAJE 4 | C35: Accrued Expanse - Angkut | F35: =651018689.4*0 -> 0 | J35: PT Samudera Naga Global
A36: CAJE 4 | C36: Accrued Expanse - Angkut | F36: =630543008*0 -> 0 | J36: PT Samudera Naga Global
A37: CAJE 4 | C37: Accrued Expanse - Angkut | F37: =531954338*0 -> 0 | J37: PT Harmoni Prima Indonesia
A38: CAJE 4 | D38: Beban Pengiriman | I38: =SUM(F33:F37) -> 0 | J38: Beban Pingiriman
C39: (Adj atas Accrued Beban Pengiriman)
A41: CAJE 5 | C41: Accrued Expanse - Angkut | F41: =I42 -> 0 | J41: New York Custom Brokers, Inc
A42: =A41 -> CAJE 5 | D42: Duty | I42: =555106934.74*0 -> 0 | J42: New York Custom Brokers, Inc
C43: (Adj atas Accrued Beban Duty)
A45: RLKS 1 | C45: Uang Muka Pembelian Bahan Baku | F45: =SUM(G46:G49) -> 2.7862788e+10 | J45: Reklas atas Uang Muka
A46: =A45 -> RLKS 1 | D46: Shaka Bahari Abadi, PT | G46: 9.3474967e+09 | J46: =J45 -> Reklas atas Uang Muka
A47: =A46 -> RLKS 1 | D47: Marubeni Indonesia, PT | G47: =206460000 -> 206460000 | J47: =J46 -> Reklas atas Uang Muka
A48: =A47 -> RLKS 1 | D48: Hendro Hariyanto | G48: 5.8396535e+09 | J48: =J47 -> Reklas atas Uang Muka | K48: Uang Muka Info Pak Nanda
A49: =A48 -> RLKS 1 | D49: Yeremia Sukamto | G49: 1.2469178e+10 | J49: =J48 -> Reklas atas Uang Muka
C50: (Reklas atas Uang Muka)
A52: CAJE 6 | C52: Gatot Eko Andoyo | F52: =1010550926*0 -> 0 | J52: Pembelian Bahan Baku
A53: CAJE 6 | C53: Sedulur Bertiga Jaya, PT | F53: =680234425*0 -> 0 | J53: Pembelian Bahan Baku
A54: CAJE 6 | C54: PT Indonesia Makan Udang | F54: =1207767461*0 -> 0 | J54: Pembelian Bahan Baku
A55: CAJE 6 | D55: Pembelian Udang | G55: =SUM(F52:F54) -> 0 | J55: Pembelian Bahan Baku
C56: (Adj atas Pembelian Baku Udang)
A58: CAJE 7 | C58: Prepaid PPh 22 | F58: =G59 -> 5967292.1
A59: =A58 -> CAJE 7 | D59: Utang Pph 22 | G59: =5967292.09000003 -> 5967292.1
C60: (Adj atas Prepaid PPh 22)
A62: CAJE 8 | C62: Prepaid 25 | F62: =G63 -> 421615912
A63: =A62 -> CAJE 8 | D63: Utang Pph 25 | G63: 421615912
C64: (Adj atas Prepaid PPh 25)
A66: CAJE 9 | C66: Biaya yang masih dibayar | F66: 15000000 | J66: Adj atas Beban Sewa yang sdh di akui di 2023
A67: =A66 -> CAJE 9 | D67: Biaya Sewa IPAL | I67: =F66 -> 15000000 | J67: =J66 -> Adj atas Beban Sewa yang sdh di akui di 2023
A70: CAJE 10 | C70: Sunnyvale | F70: =1870337280*0 -> 0 | J70: SUNNYVALE PO 67591
A71: CAJE 10 | C71: Censea Inc | F71: =2080881200*0 -> 0 | J71: CENSEA PO 71246
A72: CAJE 10 | C72: Alpha Trading Co. Ltd | F72: =1368248970*0 -> 0 | J72: ALPHA TRADING PO IAS ALT/005
A73: CAJE 10 | C73: Sunnyvale | F73: =1838575600*0 -> 0 | J73: SUNNYVALE PO 67592
A74: CAJE 10 | C74: Censea Inc | F74: =2449251200*0 -> 0 | J74: CENSEA PO 71857
A75: CAJE 10 | C75: Censea Inc | F75: =2066146400*0 -> 0 | J75: CENSEA PO 71468
A76: CAJE 10 | C76: Ael Seafood Enterprises, LLC | F76: =1920435600*0 -> 0 | J76: AEL SEAFOOD
A77: CAJE 10 | C77: Censea Inc | F77: =2003932800*0 -> 0 | J77: CENSEA 72082
D78: Penjualan Expor | I78: =SUM(F70:F77) -> 0
C79: (Adj Penjualan Exp Sementara)
A81: CAJE 11 | C81: Pendapatan Lain-Lain | H81: =G82 -> 9055934
A82: CAJE 11 | D82: Grahamakmur Ciptapratama | G82: 9055934
C83: (Adj Kelebihan Pembayaran)
A85: CAJE 12 | C85: Prepaid PPh 22 | F85: =G89 -> 28121848
A86: CAJE 12 | C86: Utang Pph 23 | F86: 4
A87: CAJE 12 | C87: Prepaid PPh 21 | F87: 3806151
A88: CAJE 12 | C88: Utang Pph 21 | F88: 4659147
A89: CAJE 12 | D89: Utang PPh 22 | G89: 28121848
A90: CAJE 12 | D90: Pajak Lain-Lain | I90: =SUM(F86:F88) -> 8465302
C91: (Adj Utang Pajak)
C93: Pendapatan Lain-Lain | H93: =33+787 -> 820
C94: PT Bank Mandiri (Persero) Tbk - USD | F94: 3.2
C95: PT Bank Negara Indonesia (Persero) Tbk - USD | F95: 11.77
C96: Bank JTRUST (1100024149) - USD | F96: 8.4
C97: PT Bank BTPN - USD | F97: 51.9
D98: Bank Mega Syariah (1000236601) - USD | G98: 0.66
D99: Bank Mandiri Rp A/c 114.0004692854 | G99: 786.61
D100: Bank JTRUST Rp A/c 2100596827 | G100: 40
D101: PT Bank Mega Syariah | G101: 0.52
D102: PT Bank BTPN | G102: 65
D103: Bank BRI (0285-02-000022-30-5) - USD | G103: 1.68
C104: (Adj Saldo Rek Bank)
A106: CAJE 13 | C106: Cadangan Kerugian Penurunan Nilai | F106: 8.2419978e+08
A107: =A106 -> CAJE 13 | D107: Beban Cadangan kerugian Penurunan Nilai | I107: =F106 -> 8.2419978e+08
C108: (Adj Perhitungan CKPN 2024)
A110: CAJE 14 | C110: Beban Pajak Kini | H110: =SUM(G111:G113) -> 1135531100
A111: CAJE 14 | D111: Prepaid PPh 25 | G111: =-'SPT Badan'!B42 -> 421615912
A112: CAJE 14 | D112: Prepaid PPh 22 | G112: =-'SPT Badan'!B41 -> 34089140
D113: Utang Pajak PPh 29 | G113: ='SPT Badan'!B48 -> 6.7982605e+08
C114: (Adj Perhitungan Pajak Kini 2024)
A116: CAJE 15 | C116: Penjualan Lokal | H116: 873000
A117: =A116 -> CAJE 15 | D117: Pendapatan Lainnya | I117: =H116 -> 873000
C118: (Adj Penjualan Polybag CV Kanian)
A120: CAJE 16 | C120: Utang Lain-Lain dibawah 20 juta | F120: 15153928
A121: =A120 -> CAJE 16 | D121: Slade Gorton,,Inc | G121: =F120 -> 15153928
...

Sheet WS
A4: Note
A7: KONSOLIDASI PT INDO AMERICAN SEAFOODS & PT INDOKOM SAMUDRA PERSADA | C7: =C159 -> 3.0114393e+11 | E7: =E159 -> 3.0013417e+11 | J7: =J159 -> 3.2571294e+11 | N7: =N159 -> 3.0114393e+11 | P7: =P159 -> 3.2494132e+11 | U7: =U159 -> 3.0331116e+11 | W7: =W159 -> 3.0114393e+11 | X7: 3.0114393e+11 | AA7: =AA159 -> 1.7661193e+11 | AC7: =AC159 -> 2.9063231e+11 | AH7: =AH159 -> 281676261822 | AJ7: =AJ159 -> 1.7661193e+11 | AK7: 1.7661193e+11 | AN7: =AN159 -> 1.5390316e+11
A8: WORKING BALANCE SHEETS AND PROFIT OR LOSS | C8: =C329 -> 3.0114393e+11 | E8: =E329 -> 3.0013417e+11 | J8: =J329 -> 3.2571294e+11 | N8: =N329 -> 3.0114393e+11 | P8: =P329 -> 3.2494132e+11 | U8: =U329 -> 3.0331116e+11 | W8: =W329 -> 3.0114393e+11 | X8: 3.0114393e+11 | AA8: =AA329 -> 1.7661193e+11 | AC8: =AC329 -> 2.9063231e+11 | AH8: =AH329 -> 281676261822 | AJ8: =AJ329 -> 1.7661193e+11 | AK8: 1.7661193e+11 | AN8: =AN329 -> 1.5390316e+11
A9: UNTUK TAHUN YANG BERAKHIR 31 DES 2023, 2022 & 31 DES 2021 | C9: =C7-C8 -> 0.99450684 | E9: =E7-E8 -> -0.31549072 | J9: =J7-J8 -> 0.484375 | N9: =N7-N8 -> 0.99450684 | P9: =P7-P8 -> 0.067871094 | U9: =U7-U8 -> 0.049926758 | W9: =W7-W8 -> 0.99450684 | X9: 0.9944458 | AA9: =AA7-AA8 -> -0.12997437 | AC9: =AC7-AC8 -> -0.13000488 | AH9: =AH7-AH8 -> 0 | AJ9: =AJ7-AJ8 -> -0.12997437 | AK9: -0.080047607 | AN9: =AN7-AN8 -> 0.18997192
A11: No Account | B11: Description | C11: Audited PT IAS | D11: Mutasi (Jan-Des) | E11: Unaudited | F11: Auditor AJE/ RJE/ CAJE | J11: Audited | L11: 16162 | N11: Audited PT IAS | O11: Mutasi (Jan-Sept) | P11: Unaudited | Q11: Auditor AJE/ RJE/ CAJE | U11: Audited | W11: Audited PT IAS | X11: Audited Update | AA11: Audited PT IAS | AB11: Mutasi (Jan-Sept) | AC11: Unaudited | AD11: Auditor AJE/ RJE/ CAJE | AH11: Audited | AJ11: Audited PT IAS | AK11: Audited Update | AN11: Audited PT IAS
C12: 31 Desember 2023 | D12: =SUM(D18:D503) -> -0.31002235 | E12: 31 Desember 2024 | F12: Reff | G12: Dr | H12: Reff | I12: Cr | J12: =E12 -> 31 Desember 2024 | K12: Bukti | L12: IDR (Kurs) | M12: Note | N12: 31 Desember 2023 | O12: =SUM(O18:O503) -> 0.073485374 | P12: 30 Sept 2024 | Q12: Reff | R12: Dr | S12: Reff | T12: Cr | U12: =P12 -> 30 Sept 2024 | W12: 31 Desember 2023 | X12: 31 Desember 2023 | AA12: 31 Desember 2022 | AB12: =SUM(AB18:AB503) -> -9.5367432e-07 | AC12: 31 Sept 2023 | AD12: Reff | AE12: Dr | AF12: Reff | AG12: Cr | AH12: =AC12 -> 31 Sept 2023 | AJ12: 31 Desember 2022 | AK12: 31 Desember 2022 | AN12: 31 Desember 2021
A14: ASSETS
A15: Current Assets
A16: Cash
A17: Kas Besar
B18: Kas in Lampung | C18: =W18 -> 52356867 | D18: 1.2038949e+08 | E18: =C18+D18 -> 1.7274635e+08 | J18: =E18+G18-I18 -> 1.7274635e+08 | N18: =W18 -> 52356867 | O18: 1.6936066e+08 | P18: =N18+O18 -> 2.2171753e+08 | U18: =P18+R18-T18 -> 2.2171753e+08 | W18: 52356867 | X18: 52356867 | Y18: =W18-X18 -> 0 | AA18: =AJ18 -> 48995723 | AB18: 11311239 | AC18: =AA18+AB18 -> 60306962 | AH18: =ROUND(AC18+AE18-AG18,0) -> 60306962 | AJ18: 48995723 | AK18: 48995723 | AL18: =AJ18-AK18 -> -0.42001343 | AN18: 19218284
A19: Kas Kecil
B20: Kas in Lampung (Petty Cash) | C20: =W20 -> 685258 | D20: -685258 | E20: =C20+D20 -> 0 | J20: =E20+G20-I20 -> 0 | N20: =W20 -> 685258 | O20: -685258 | P20: =N20+O20 -> 0 | U20: =P20+R20-T20 -> 0 | W20: 685258 | X20: 685258 | Y20: =W20-X20 -> 0 | AA20: =AJ20 -> 685258 | AC20: =AA20+AB20 -> 685258 | AH20: =ROUND(AC20+AE20-AG20,0) -> 685258 | AJ20: 685258 | AK20: 685258 | AL20: =AJ20-AK20 -> 0 | AN20: 928838
B21: Total Cash | C21: =SUM(C18:C20) -> 53042125 | E21: =SUM(E18:E20) -> 1.7274635e+08 | J21: =SUM(J18:J20) -> 1.7274635e+08 | N21: =SUM(N18:N20) -> 53042125 | P21: =SUM(P18:P20) -> 2.2171753e+08 | U21: =SUM(U18:U20) -> 2.2171753e+08 | W21: =SUM(W18:W20) -> 53042125 | X21: 53042125 | Y21: =W21-X21 -> 0 | AA21: =SUM(AA18:AA20) -> 49680981 | AC21: =SUM(AC18:AC20) -> 60992220 | AH21: =SUM(AH18:AH20) -> 60992220 | AJ21: =SUM(AJ18:AJ20) -> 49680981 | AK21: 49680981 | AL21: =AJ21-AK21 -> -0.42001343 | AN21: =SUM(AN18:AN20) -> 20147122
A22: BANK
A23: Bank IDR
B24: Bank Mandiri Rp A/c 114.0031009999 | C24: =W24 -> 0 | E24: =C24+D24 -> 0 | J24: =E24+G24-I24 -> 0 | N24: =W24 -> 0 | P24: =N24+O24 -> 0 | U24: =P24+R24-T24 -> 0 | AA24: =AJ24 -> 3297318 | AB24: -2475000 | AC24: =AA24+AB24 -> 822318 | AH24: =ROUND(AC24+AE24-AG24,0) -> 822318 | AJ24: 3297318 | AK24: 3297318 | AN24: 4103681
B25: Bank Mandiri Rp A/c 114.0004692854 | C25: =W25 -> 2265171 | D25: 2169096.8 | E25: =C25+D25 -> 4434267.8 | I25: ='AJE CAJE Des 24'!G99 -> 786.61 | J25: =E25+G25-I25 -> 4433481.2 | K25: 4433481.2 | M25: =J25-K25 -> 0 | N25: =W25 -> 2265171 | O25: 8478266.9 | P25: =N25+O25 -> 10743438 | U25: =P25+R25-T25 -> 10743438 | W25: 2265171 | X25: 0 | Y25: =W25-X26 -> 0 | AA25: =AJ25 -> 364262986 | AB25: -3.1575321e+08 | AC25: =AA25+AB25 -> 48509780 | AH25: =ROUND(AC25+AE25-AG25,0) -> 48509780 | AJ25: 364262986 | AK25: 364262986 | AN25: 2105276
B26: Bank BNI Rp A/c 111-559-9552 | C26: =W26 -> 0 | D26: 15129380 | E26: =C26+D26 -> 15129380 | J26: =E26+G26-I26 -> 15129380 | K26: 15129380 | M26: =J26-K26 -> 0 | O26: 8.1921479e+09 | P26: =N26+O26 -> 8.1921479e+09 | U26: =P26+R26-T26 -> 8.1921479e+09 | X26: 2265171 | AA26: =AJ26 -> 0 | AC26: =AA26+AB26 -> 0 | AH26: =ROUND(AC26+AE26-AG26,0) -> 0 | AK26: 4306134
B27: Bank BNI Rp A/c 115-599-4474 | C27: =W27 -> 1432417 | D27: -191691 | E27: =C27+D27 -> 1240726 | J27: =E27+G27-I27 -> 1240726 | K27: 1240726 | M27: =J27-K27 -> 0 | N27: =W27 -> 1432417 | O27: 5984165 | P27: =N27+O27 -> 7416582 | U27: =P27+R27-T27 -> 7416582 | W27: 1432417 | X27: 1432417 | AA27: =AJ27 -> 4306134 | AB27: -3301285 | AC27: =AA27+AB27 -> 1004849 | AH27: =ROUND(AC27+AE27-AG27,0) -> 1004849 | AJ27: 4306134 | AK27: 1129932080 | AN27: 9386921
B28: Bank JTRUST Rp A/c 1100024132 | C28: =W28 -> 4766585 | D28: -852937 | E28: =C28+D28 -> 3913648 | J28: =E28+G28-I28 -> 3913648 | K28: 3913648 | M28: =J28-K28 -> 0 | N28: =W28 -> 4766585 | O28: -708074 | P28: =N28+O28 -> 4058511 | U28: =P28+R28-T28 -> 4058511 | W28: 4766585 | X28: 4766585 | AA28: =AJ28 -> 1129932080 | AB28: -1072076414 | AC28: =AA28+AB28 -> 57855666 | AH28: =ROUND(AC28+AE28-AG28,0) -> 57855666 | AJ28: 1129932080 | AK28: 1362643218 | AN28: 17089985
B29: Bank JTRUST Rp A/c 2100596827 | C29: =W29 -> 1056635 | D29: -330000 | E29: =C29+D29 -> 726635 | I29: ='AJE CAJE Des 24'!G100 -> 40 | J29: =E29+G29-I29 -> 726595 | K29: 726595 | M29: =J29-K29 -> 0 | N29: =W29 -> 1056635 | O29: -240000 | P29: =N29+O29 -> 816635 | U29: =P29+R29-T29 -> 816635 | W29: 1056635 | X29: 1056635 | AA29: =AJ29 -> 1362643218 | AB29: -809947 | AC29: =AA29+AB29 -> 1361833271 | AH29: =ROUND(AC29+AE29-AG29,0) -> 1361833271 | AJ29: 1362643218 | AK29: 3003977 | AN29: 1372702466
B30: PT Bank Mega Syariah | C30: =W30 -> 2098047 | D30: -1414425.5 | E30: =C30+D30 -> 683621.48 | I30: ='AJE CAJE Des 24'!G101 -> 0.52 | J30: =E30+G30-I30 -> 683620.96 | K30: 683620.96 | M30: =J30-K30 -> 0 | N30: =W30 -> 2098047 | O30: -1328468.1 | P30: =N30+O30 -> 769578.89 | U30: =P30+R30-T30 -> 769578.89 | W30: 2098047 | X30: 2098047 | AA30: =AJ30 -> 3003977 | AB30: -631407.01 | AC30: =AA30+AB30 -> 2372570 | AH30: =ROUND(AC30+AE30-AG30,0) -> 2372570 | AJ30: 3003977 | AK30: 5000000 | AN30: 3233855
B31: PT Bank BTPN | C31: =W31 -> 30768284 | D31: 36445715 | E31: =C31+D31 -> 67213999 | I31: ='AJE CAJE Des 24'!G102 -> 65 | J31: =E31+G31-I31 -> 67213934 | K31: 67213934 | M31: =J31-K31 -> 0 | N31: =W31 -> 30768284 | O31: 15737742 | P31: =N31+O31 -> 46506026 | U31: =P31+R31-T31 -> 46506026 | W31: 30768284 | X31: 30768284 | AA31: =AJ31 -> 5000000 | AB31: 161397714 | AC31: =AA31+AB31 -> 166397714 | AH31: =ROUND(AC31+AE31-AG31,0) -> 166397714 | AJ31: 5000000 | AN31: 0
B32: Bank BRI Rp A/c 0285-01-220000-30-7 | C32: =W32 -> 794277 | D32: -794277 | E32: =C32+D32 -> 0 | J32: =E32+G32-I32 -> 0 | M32: =J32-K32 -> 0 | N32: =W32 -> 794277 | O32: -794277 | P32: =N32+O32 -> 0 | U32: =P32+R32-T32 -> 0 | W32: 794277 | X32: 0 | AA32: =AJ32 -> 0 | AB32: 3002177 | AC32: =AA32+AB32 -> 3002177 | AH32: =ROUND(AC32+AE32-AG32,0) -> 3002177
B33: Bank BRI Rp A/c 0652-01-111111-301 | D33: 50621267 | E33: =C33+D33 -> 50621267 | J33: =E33+G33-I33 -> 50621267 | K33: 50621267 | M33: =J33-K33 -> 0 | O33: 609796408 | P33: =N33+O33 -> 609796408 | U33: =P33+R33-T33 -> 609796408 | X33: 794277
A34: Bank USD | E34: =C34+D34 -> 0 | J34: =E34+G34-I34 -> 0 | P34: =N34+O34 -> 0 | U34: =P34+R34-T34 -> 0 | AC34: =AA34+AB34 -> 0 | AH34: =ROUND(AC34+AE34-AG34,0) -> 0 | AK34: 52754538
B35: PT Bank Mandiri (Persero) Tbk | C35: =W35 -> 3820389 | D35: 8286562 | E35: =C35+D35 -> 12106951 | G35: ='AJE CAJE Des 24'!F94 -> 3.2 | J35: =E35+G35-I35 -> 12106954 | K35: 749.1 | L35: =K35*L11 -> 12106954 | M35: =J35-L35 -> 0 | N35: =W35 -> 3820389 | O35: -2112523 | P35: =N35+O35 -> 1707866 | U35: =P35+R35-T35 -> 1707866 | W35: 3820389 | X35: 3820389 | AA35: =AJ35 -> 52754538 | AB35: -37521674 | AC35: =AA35+AB35 -> 15232864 | AH35: =ROUND(AC35+AE35-AG35,0) -> 15232864 | AJ35: 52754538 | AN35: 13023877
B36: Bank Mandiri $ (114.002.744.8284) USD | C36: =W36 -> 1927000 | D36: -1927000 | E36: =C36+D36 -> 0 | J36: =E36+G36-I36 -> 0 | N36: =W36 -> 1927000 | O36: -1927000 | P36: =N36+O36 -> 0 | U36: =P36+R36-T36 -> 0 | W36: 1927000 | X36: 1927000 | AA36: =AJ36 -> 0 | AC36: =AA36+AB36 -> 0 | AH36: =ROUND(AC36+AE36-AG36,0) -> 0 | AK36: 60924433 | AN36: 0
B37: PT Bank Negara Indonesia (Persero) Tbk $ | C37: =W37 -> 8054849 | D37: 12640257 | E37: =C37+D37 -> 20695106 | G37: ='AJE CAJE Des 24'!F95 -> 11.77 | J37: =E37+G37-I37 -> 20695118 | K37: 1280.48 | L37: =K37*L11 -> 20695118 | M37: =J37-L37 -> 0 | N37: =W37 -> 8054849 | O37: 537619.9 | P37: =N37+O37 -> 8592468.9 | U37: =P37+R37-T37 -> 8592468.9 | W37: 8054849 | X37: 8054849 | AA37: =AJ37 -> 60924433 | AB37: -43887455 | AC37: =AA37+AB37 -> 17036978 | AH37: =ROUND(AC37+AE37-AG37,0) -> 17036978 | AJ37: 60924433 | AK37: 23270396 | AN37: 1126429101
B38: Bank JTRUST (1100024149) | C38: =W38 -> 9044094 | D38: -668469.14 | E38: =C38+D38 -> 8375624.9 | G38: ='AJE CAJE Des 24'!F96 -> 8.4 | J38: =E38+G38-I38 -> 8375633.3 | K38: 518.23 | L38: =K38*L11 -> 8375633.3 | M38: =J38-L38 -> 0 | N38: =W38 -> 9044094 | O38: -901222.14 | P38: =N38+O38 -> 8142871.9 | U38: =P38+R38-T38 -> 8142871.9 | W38: 9044094 | X38: 9044094 | AA38: =AJ38 -> 23270396 | AB38: -12235452 | AC38: =AA38+AB38 -> 11034944 | AH38: =ROUND(AC38+AE38-AG38,0) -> 11034944 | AJ38: 23270396 | AK38: 14629830 | AN38: 1927119772
B39: Bank Mega Syariah (1000236601) | C39: =W39 -> 13411920 | D39: -6259103 | E39: =C39+D39 -> 7152817 | I39: ='AJE CAJE Des 24'!G98 -> 0.66 | J39: =E39+G39-I39 -> 7152816.3 | K39: 442.57 | L39: =K39*L11 -> 7152816.3 | M39: =J39-L39 -> 0 | N39: =W39 -> 13411920 | O39: -6394397 | P39: =N39+O39 -> 7017523 | U39: =P39+R39-T39 -> 7017523 | W39: 13411920 | X39: 13411920 | AA39: =AJ39 -> 14629830 | AB39: -889320 | AC39: =AA39+AB39 -> 13740510 | AH39: =ROUND(AC39+AE39-AG39,0) -> 13740510 | AJ39: 14629830 | AK39: 7865500 | AN39: 14126310
B40: PT Bank BTPN | C40: =W40 -> 2023630252 | D40: -1969448007 | E40: =C40+D40 -> 54182245 | G40: ='AJE CAJE Des 24'!F97 -> 51.9 | J40: =E40+G40-I40 -> 54182297 | K40: 3352.45 | L40: =K40*L11 -> 54182297 | M40: =J40-L40 -> 0 | N40: =W40 -> 2023630252 | O40: 253139290 | P40: =N40+O40 -> 2276769542 | U40: =P40+R40-T40 -> 2276769542 | W40: 2023630252 | X40: 2023630252 | AA40: =AJ40 -> 7865500 | AB40: 15743485 | AC40: =AA40+AB40 -> 23608985 | AH40: =ROUND(AC40+AE40-AG40,0) -> 23608985 | AJ40: 7865500 | AN40: 0
B41: Bank BRI (0285-02-000022-30-5) USD | C41: =W41 -> 3242911 | D41: -1782511 | E41: =C41+D41 -> 1460400 | I41: ='AJE CAJE Des 24'!G103 -> 1.68 | J41: =E41+G41-I41 -> 1460398.3 | K41: 90.36 | L41: =K41*L11 -> 1460398.3 | M41: =J41-L41 -> 0 | N41: =W41 -> 3242911 | O41: -1420900 | P41: =N41+O41 -> 1822011 | U41: =P41+R41-T41 -> 1822011 | W41: 3242911 | X41: 3242911 | AA41: =AJ41 -> 0 | AB41: 15455357 | AC41: =AA41+AB41 -> 15455357 | AH41: =ROUND(AC41+AE41-AG41,0) -> 15455357 | AK41: 0 | AN41: 0
B42: Total Bank | C42: =SUM(C24:C41) -> 2106312831 | E42: =SUM(E24:E41) -> 2.4793669e+08 | J42: =SUM(J24:J41) -> 2.4793587e+08 | N42: =SUM(N24:N41) -> 2106312831 | P42: =SUM(P24:P41) -> 1.1176307e+10 | U42: =SUM(U24:U41) -> 1.1176307e+10 | W42: =SUM(W24:W41) -> 2106312831 | X42: 2106312831 | Y42: =W42-X42 -> 0 | AA42: =SUM(AA24:AA41) -> 3.0318904e+09 | AC42: =SUM(AC24:AC41) -> 1.737908e+09 | AH42: =SUM(AH24:AH41) -> 1737907983 | AJ42: =SUM(AJ24:AJ41) -> 3.0318904e+09 | AK42: 3.0318904e+09 | AL42: =AJ42-AK42 -> 0 | AN42: =SUM(AN24:AN41) -> 4489321244
B43: Total Cash and Cash Equivalents | C43: =C21+C42 -> 2159354956 | E43: =E21+E42 -> 4.2068304e+08 | J43: =J21+J42 -> 4.2068222e+08 | N43: =N21+N42 -> 2159354956 | P43: =P21+P42 -> 1.1398025e+10 | U43: =U21+U42 -> 1.1398025e+10 | W43: =W21+W42 -> 2159354956 | X43: 2159354956 | Y43: =W43-X43 -> 0 | AA43: =AA21+AA42 -> 3.0815714e+09 | AC43: =AC21+AC42 -> 1.7989002e+09 | AH43: =AH21+AH42 -> 1798900203 | AJ43: =AJ21+AJ42 -> 3.0815714e+09 | AK43: 3.0815714e+09 | AL43: =AJ43-AK43 -> -0.42001343 | AN43: =AN21+AN42 -> 4509468366
A44: Trade Receivable
B45: Piutang Usaha - IDR | X45: 0 | AK45: 0
B46: CV Kanian Persada | C46: =W46 -> 211054410 | D46: 182881020 | E46: =C46+D46 -> 393935430 | J46: =E46+G46-I46 -> 393935430 | N46: =W46 -> 211054410 | O46: 128840071 | P46: =N46+O46 -> 339894481 | U46: =P46+R46-T46 -> 339894481 | W46: 211054410 | X46: 211054410 | Y46: =W46-X46 -> 0 | AA46: =AJ46 -> 338387925 | AB46: 1.4448648e+08 | AC46: =AA46+AB46 -> 4.8287441e+08 | AH46: =ROUND(AC46+AE46-AG46,0) -> 482874409 | AJ46: 338387925 | AK46: 338387925 | AL46: =AJ46-AK46 -> 0 | AN46: 174380445
B47: Mochamad Riduwan | C47: =W47 -> 0 | E47: =C47+D47 -> 0 | J47: =E47+G47-I47 -> 0 | N47: =W47 -> 0 | P47: =N47+O47 -> 0 | U47: =P47+R47-T47 -> 0 | W47: 0 | X47: 0 | AA47: =AJ47 -> 14980 | AC47: =AA47+AB47 -> 14980 | AH47: =ROUND(AC47+AE47-AG47,0) -> 14980 | AJ47: 14980 | AK47: 14980 | AL47: =AJ47-AK47 -> 0 | AN47: 14980
B48: UD, Slamet | C48: =W48 -> 0 | E48: =C48+D48 -> 0 | J48: =E48+G48-I48 -> 0 | N48: =W48 -> 0 | P48: =N48+O48 -> 0 | U48: =P48+R48-T48 -> 0 | W48: 0 | X48: 0 | AA48: =AJ48 -> 29870000 | AB48: -15220660 | AC48: =AA48+AB48 -> 14649340 | AH48: =ROUND(AC48+AE48-AG48,0) -> 14649340 | AJ48: 29870000 | AK48: 29870000 | AL48: =AJ48-AK48 -> 0 | AN48: 0
B49: Roda Jaya, Toko | C49: =W49 -> 0 | E49: =C49+D49 -> 0 | J49: =E49+G49-I49 -> 0 | N49: =W49 -> 0 | P49: =N49+O49 -> 0 | U49: =P49+R49-T49 -> 0 | W49: 0 | X49: 0 | AA49: =AJ49 -> 520000 | AC49: =AA49+AB49 -> 520000 | AH49: =ROUND(AC49+AE49-AG49,0) -> 520000 | AJ49: 520000 | AK49: 520000 | AL49: =AJ49-AK49 -> 0 | AN49: 0
B50: Piutang Karyawan | C50: =W50 -> 1480185 | D50: -1480185 | E50: =C50+D50 -> 0 | J50: =E50+G50-I50 -> 0 | N50: =W50 -> 1480185 | O50: -1480185 | P50: =N50+O50 -> 0 | U50: =P50+R50-T50 -> 0 | W50: 1480185 | X50: 1480185 | Y50: =W50-X50 -> 0 | AA50: =AJ50 -> 0 | AC50: =AA50+AB50 -> 0 | AH50: =ROUND(AC50+AE50-AG50,0) -> 0 | AJ50: 0 | AK50: 0 | AN50: 4950900
B51: Jaduk Prayogi | C51: =W51 -> 0 | E51: =C51+D51 -> 0 | J51: =E51+G51-I51 -> 0 | N51: =W51 -> 0 | P51: =N51+O51 -> 0 | U51: =P51+R51-T51 -> 0 | AA51: =AJ51 -> 0 | AC51: =AA51+AB51 -> 0 | AH51: =ROUND(AC51+AE51-AG51,0) -> 0 | AJ51: 0 | AN51: 4800000
C52: =W52 -> 0 | J52: =E52+G52-I52 -> 0 | N52: =W52 -> 0 | U52: =P52+R52-T52 -> 0 | X52: 0 | AA52: =AJ52 -> 0 | AH52: =ROUND(AC52+AE52-AG52,0) -> 0 | AK52: 0
B53: Piutang Usaha - USD | C53: =W53 -> 0 | J53: =E53+G53-I53 -> 0 | N53: =W53 -> 0 | U53: =P53+R53-T53 -> 0 | AA53: =AJ53 -> 0 | AH53: =ROUND(AC53+AE53-AG53,0) -> 0
B54: Alpha Trading Co. Ltd | C54: =W54 -> 0 | D54: 3.2383862e+09 | E54: =C54+D54 -> 3.2383862e+09 | F54: ='AJE CAJE Des 24'!A72 -> CAJE 10 | G54: ='AJE CAJE Des 24'!F72 -> 0 | J54: =E54+G54-I54 -> 3.2383862e+09 | N54: =W54 -> 0 | P54: =N54+O54 -> 0 | U54: =P54+R54-T54 -> 0 | W54: 0 | X54: 0 | AA54: =AJ54 -> 1154639669 | AB54: -1154639669 | AC54: =AA54+AB54 -> 0 | AH54: =ROUND(AC54+AE54-AG54,0) -> 0 | AJ54: 1154639669 | AK54: 1154639669 | AL54: =AJ54-AK54 -> 0 | AN54: 1095202826
B55: Censea Inc | C55: =W55 -> 8062429256 | D55: 1.5130416e+10 | E55: =C55+D55 -> 2.3192845e+10 | F55: ='AJE CAJE Des 24'!A71 -> CAJE 10 | G55: ='AJE CAJE Des 24'!F71+'AJE CAJE Des 24'!F74+'AJE CAJE Des 24'!F75+'AJE CAJE Des 24'!F77 -> 0 | J55: =E55+G55-I55 -> 2.3192845e+10 | N55: =W55 -> 8062429256 | O55: 2.3765842e+09 | P55: =N55+O55 -> 1.0439013e+10 | Q55: ='AJE CAJE Sept 24'!B77 -> CAJE 15 | R55: ='AJE CAJE Sept 24'!G77+'AJE CAJE Sept 24'!G78+'AJE CAJE Sept 24'!G80+'AJE CAJE Sept 24'!G81 -> 6233931600 | U55: =P55+R55-T55 -> 1.6672945e+10 | W55: 8062429256 | X55: 8062429256 | Y55: =W55-X55 -> 0 | AA55: =AJ55 -> 23090276420 | AB55: -21308667920 | AC55: =AA55+AB55 -> 1781608500 | AH55: =ROUND(AC55+AE55-AG55,0) -> 1781608500 | AJ55: 23090276420 | AK55: 23090276420 | AL55: =AJ55-AK55 -> 0 | AN55: 6135670000
B56: Choice Canning Company Inc, | C56: =W56 -> 0 | E56: =C56+D56 -> 0 | J56: =E56+G56-I56 -> 0 | P56: =N56+O56 -> 0 | U56: =P56+R56-T56 -> 0 | X56: 0 | AA56: =AJ56 -> 0 | AC56: =AA56+AB56 -> 0 | AH56: =ROUND(AC56+AE56-AG56,0) -> 0
B57: Crystal Cove Seafoods Corp | C57: =W57 -> 0 | E57: =C57+D57 -> 0 | J57: =E57+G57-I57 -> 0 | N57: =W57 -> 0 | P57: =N57+O57 -> 0 | U57: =P57+R57-T57 -> 0 | W57: 0 | X57: 0 | AA57: =AJ57 -> 0 | AC57: =AA57+AB57 -> 0 | AH57: =ROUND(AC57+AE57-AG57,0) -> 0 | AJ57: 0 | AK57: 0 | AN57: 1414842695
B58: Ael Seafood Enterprises, LLC | C58: =W58 -> 0 | D58: 5727524400 | E58: =C58+D58 -> 5727524400 | F58: ='AJE CAJE Des 24'!A76 -> CAJE 10 | G58: ='AJE CAJE Des 24'!F76 -> 0 | J58: =E58+G58-I58 -> 5727524400 | N58: =W58 -> 0 | P58: =N58+O58 -> 0 | U58: =P58+R58-T58 -> 0 | W58: 0 | X58: 0 | AA58: =AJ58 -> 0 | AC58: =AA58+AB58 -> 0 | AH58: =ROUND(AC58+AE58-AG58,0) -> 0 | AJ58: 0 | AK58: 0 | AN58: 2037613200
B59: Eastern Fish Company LLC | C59: =W59 -> 1661844800 | D59: -1661844800 | E59: =C59+D59 -> 0 | J59: =E59+G59-I59 -> 0 | N59: =W59 -> 1661844800 | O59: -308204860 | P59: =N59+O59 -> 1353639940 | U59: =P59+R59-T59 -> 1353639940 | W59: 1661844800 | X59: 1661844800 | Y59: =W59-X59 -> 0 | AA59: =AJ59 -> 5.6587553e+09 | AB59: -3794672708 | AC59: =AA59+AB59 -> 1.8640826e+09 | AH59: =ROUND(AC59+AE59-AG59,0) -> 1864082613 | AJ59: 5.6587553e+09 | AK59: 5.6587553e+09 | AL59: =AJ59-AK59 -> 0 | AN59: 5174510160
B60: Eiger Co. Ltd | C60: =W60 -> 550050588 | D60: -5.5005059e+08 | E60: =C60+D60 -> 0.5 | J60: =E60+G60-I60 -> 0.5 | N60: =W60 -> 550050588 | O60: -5.5005059e+08 | P60: =N60+O60 -> 0.5 | U60: =P60+R60-T60 -> 0.5 | W60: 550050588 | X60: 550050588 | Y60: =W60-X60 -> 0 | AA60: =AJ60 -> 1.4692754e+09 | AB60: -389286840 | AC60: =AA60+AB60 -> 1.0799886e+09 | AH60: =ROUND(AC60+AE60-AG60,0) -> 1079988560 | AJ60: 1.4692754e+09 | AK60: 1.4692754e+09 | AL60: =AJ60-AK60 -> 0 | AN60: 0
B61: Export Packer Co., Ltd | C61: =W61 -> 0 | E61: =C61+D61 -> 0 | J61: =E61+G61-I61 -> 0 | N61: =W61 -> 0 | P61: =N61+O61 -> 0 | U61: =P61+R61-T61 -> 0 | W61: 0 | X61: 0 | AA61: =AJ61 -> 3.9848212e+08 | AB61: -3.9848212e+08 | AC61: =AA61+AB61 -> 0 | AH61: =ROUND(AC61+AE61-AG61,0) -> 0 | AJ61: 3.9848212e+08 | AK61: 3.9848212e+08 | AL61: =AJ61-AK61 -> 0 | AN61: 0
B62: Monarch Trading, LLC | C62: =W62 -> 0 | E62: =C62+D62 -> 0 | J62: =E62+G62-I62 -> 0 | N62: =W62 -> 0 | P62: =N62+O62 -> 0 | U62: =P62+R62-T62 -> 0 | W62: 0 | X62: 0 | AA62: =AJ62 -> 0 | AC62: =AA62+AB62 -> 0 | AH62: =ROUND(AC62+AE62-AG62,0) -> 0 | AJ62: 0 | AK62: 0 | AN62: 5278388480
B63: San Sugar Co, , Ltd | C63: =W63 -> 2028899760 | D63: -2028899760 | E63: =C63+D63 -> 0 | J63: =E63+G63-I63 -> 0 | N63: =W63 -> 2028899760 | O63: -2028899760 | P63: =N63+O63 -> 0 | U63: =P63+R63-T63 -> 0 | W63: 2028899760 | X63: 890274000 | Y63: =W63-X65 -> 0 | AA63: =AJ63 -> 1060584019 | AB63: -1060584019 | AC63: =AA63+AB63 -> 0 | AH63: =ROUND(AC63+AE63-AG63,0) -> 0 | AJ63: 1060584019 | AK63: 1060584019 | AL63: =AJ63-AK63 -> 0 | AN63: 2374932359
B64: Slade Gorton,,Inc | C64: =W64 -> 0 | D64: 2035005528 | E64: =C64+D64 -> 2035005528 | H64: ='AJE CAJE Des 24'!A121 -> CAJE 16 | I64: ='AJE CAJE Des 24'!G121 -> 15153928 | J64: =E64+G64-I64 -> 2019851600 | N64: =W64 -> 0 | O64: 1739932234 | P64: =N64+O64 -> 1739932234 | Q64: ='AJE CAJE Sept 24'!B79 -> CAJE 15 | R64: ='AJE CAJE Sept 24'!G79 -> 1783098720 | U64: =P64+R64-T64 -> 3523030954 | W64: 0 | X64: 0 | Y64: =W65-X66 -> 0 | AA64: =AJ64 -> 1678812320 | AB64: -1694074378 | AC64: =AA64+AB64 -> -15262058 | AD64: ='AJE CAJE Sept 23'!B64 -> CAJE 12 | AE64: ='AJE CAJE Sept 23'!G64 -> 15262058 | AH64: =ROUND(AC64+AE64-AG64,0) -> 0 | AJ64: 1678812320 | AK64: 1678812320 | AL64: =AJ64-AK64 -> 0 | AN64: 0
B65: Yachiyo Corporation | C65: =W65 -> 624270920 | D65: 127892398 | E65: =C65+D65 -> 752163318 | J65: =E65+G65-I65 -> 752163318 | N65: =W65 -> 624270920 | O65: -624270920 | P65: =N65+O65 -> 0 | U65: =P65+R65-T65 -> 0 | W65: 624270920 | X65: 2028899760 | AA65: =AJ65 -> 0 | AC65: =AA65+AB65 -> 0 | AH65: =ROUND(AC65+AE65-AG65,0) -> 0 | AJ65: 0 | AN65: 0
B66: Hohsui Corporation | C66: =W66 -> 890274000 | D66: 506174248 | E66: =C66+D66 -> 1396448248 | J66: =E66+G66-I66 -> 1396448248 | N66: =W66 -> 890274000 | O66: -890274000 | P66: =N66+O66 -> 0 | U66: =P66+R66-T66 -> 0 | W66: 890274000 | X66: 624270920 | Y66: =W66-X63 -> 0 | AA66: =AJ66 -> 0 | AC66: =AA66+AB66 -> 0 | AH66: =ROUND(AC66+AE66-AG66,0) -> 0 | AJ66: 0 | AN66: 0
B67: H & T SEAFOODS INC | C67: =W67 -> 0 | E67: =C67+D67 -> 0 | J67: =E67+G67-I67 -> 0 | O67: 1981564200 | P67: =N67+O67 -> 1981564200 | U67: =P67+R67-T67 -> 1981564200 | AK67: 0
B68: Ssc Inc Sunnyvale Seafood, | D68: 7981424880 | E68: =C68+D68 -> 7981424880 | J68: =E68+G68-I68 -> 7981424880
B70: Total Trade Receivable | C70: =SUM(C46:C66) -> 14030303919 | E70: =SUM(E46:E68) -> 4.4717733e+10 | J70: =SUM(J46:J68) -> 4.4702579e+10 | N70: =SUM(N46:N66) -> 14030303919 | P70: =SUM(P46:P67) -> 15854044275 | U70: =SUM(U46:U67) -> 23871074595 | W70: =SUM(W46:W66) -> 14030303919 | X70: 14030303919 | Y70: =W70-X70 -> 0 | AA70: =SUM(AA46:AA66) -> 3.4879618e+10 | AC70: =SUM(AC46:AC66) -> 5.2084763e+09 | AH70: =SUM(AH46:AH66) -> 5223738402 | AJ70: =SUM(AJ46:AJ66) -> 3.4879618e+10 | AK70: 3.4879618e+10 | AL70: =AJ70-AK70 -> 0 | AN70: =SUM(AN46:AN66) -> 23695306045
A71: Related Receivable
B72: PT Irian Marine Product Development | C72: =W72 -> 0 | E72: =C72+D72 -> 0 | J72: =E72+G72-I72 -> 0 | N72: =W72 -> 0 | P72: =N72+O72 -> 0 | U72: =P72+R72-T72 -> 0 | W72: 0 | AA72: =AJ72 -> 1.3907884e+09 | AB72: -1590788402 | AC72: =AA72+AB72 -> -2e+08 | AD72: ='AJE CAJE Sept 23'!B45 -> RLKS 2 | AE72: ='AJE CAJE Sept 23'!G45 -> 2e+08 | AH72: =ROUND(AC72+AE72-AG72,0) -> 0 | AJ72: 1.3907884e+09 | AK72: 1.3907884e+09 | AL72: =AJ72-AK72 -> 0 | AN72: 1.3915385e+09
B73: PT Indokom Samudra Persada | C73: =W73 -> 8079657361 | E73: =C73+D73 -> 8079657361 | J73: =E73+G73-I73 -> 8079657361 | N73: =W73 -> 8079657361 | O73: 2.2158723e+10 | P73: =N73+O73 -> 3.0238381e+10 | S73: ='AJE CAJE Sept 24'!B36 -> CAJE 5 | T73: ='AJE CAJE Sept 24'!H36 -> 2.760129e+10 | U73: =P73+R73-T73 -> 2.6370908e+09 | W73: 8079657361 | X73: 8079657361 | Y73: =W73-X73 -> 0 | AA73: =AJ73 -> 15427025986 | AC73: =AA73+AB73 -> 15427025986 | AF73: ='AJE CAJE Sept 23'!B25 -> CAJE 2 | AG73: ='AJE CAJE Sept 23'!H25 -> 8.9856203e+09 | AH73: =ROUND(AC73+AE73-AG73,0) -> 6441405695 | AJ73: 15427025986 | AK73: 15427025986 | AL73: =AJ73-AK73 -> 0 | AN73: 11901358695
X74: 0 | AK74: 0
B75: Total Related Receivable | C75: =SUM(C72:C73) -> 8079657361 | E75: =SUM(E72:E73) -> 8079657361 | J75: =SUM(J72:J73) -> 8079657361 | N75: =SUM(N72:N73) -> 8079657361 | P75: =SUM(P72:P73) -> 3.0238381e+10 | U75: =SUM(U72:U73) -> 2.6370908e+09 | W75: =SUM(W72:W73) -> 8079657361 | X75: 8079657361 | Y75: =W75-X75 -> 0 | AA75: =SUM(AA72:AA73) -> 1.6817814e+10 | AC75: =SUM(AC72:AC73) -> 1.5227026e+10 | AH75: =SUM(AH72:AH73) -> 6441405695 | AJ75: =SUM(AJ72:AJ73) -> 1.6817814e+10 | AK75: 1.6817814e+10 | AL75: =AJ75-AK75 -> 0 | AN75: =SUM(AN72:AN73) -> 1.3292897e+10
A76: CKPN
B77: Cadangan Kerugian Penurunan Nilai | C77: =W77 -> -907026824 | E77: =C77+D77 -> -907026824 | F77: ='AJE CAJE Des 24'!A106 -> CAJE 13 | G77: ='AJE CAJE Des 24'!F106 -> 8.2419978e+08 | J77: =E77+G77-I77 -> -82827046 | N77: =W77 -> -907026824 | P77: =N77+O77 -> -907026824 | U77: =P77+R77-T77 -> -907026824 | W77: -907026824 | X77: -907026824 | Y77: =W77-X77 -> 0 | AA77: =AJ77 -> -7.8772276e+08 | AC77: =AA77+AB77 -> -7.8772276e+08 | AH77: =ROUND(AC77+AE77-AG77,0) -> -787722760 | AJ77: -7.8772276e+08 | AK77: -7.8772276e+08 | AL77: =AJ77-AK77 -> 0 | AN77: -4.0860257e+08
B79: Total CKPN | C79: =C77 -> -907026824 | E79: =E77 -> -907026824 | J79: =J77 -> -82827046 | N79: =N77 -> -907026824 | P79: =P77 -> -907026824 | U79: =U77 -> -907026824 | W79: =W77 -> -907026824 | X79: -907026824 | Y79: =W79-X79 -> 0 | AA79: =AA77 -> -7.8772276e+08 | AC79: =AC77 -> -7.8772276e+08 | AH79: =AH77 -> -787722760 | AJ79: =AJ77 -> -7.8772276e+08 | AK79: -7.8772276e+08 | AL79: =AJ79-AK79 -> 0 | AN79: =AN77 -> -4.0860257e+08
A80: Other Receivable
A81: Trade Receivable
A82: Related Receivable | X82: 0
B83: PT Indokom Samudra Persada (Keuangan) | C83: =W83 -> 132646777153 | D83: -41694205602 | E83: =C83+D83 -> 90952571551 | J83: =E83+G83-I83 -> 90952571551 | N83: =W83 -> 132646777153 | O83: -37683078731 | P83: =N83+O83 -> 94963698422 | U83: =P83+R83-T83 -> 94963698422 | W83: 132646777153 | X83: 132646777153 | Y83: =W83-X83 -> 0 | AA83: =AJ83 -> 19472460196 | AB83: 103939262852 | AC83: =AA83+AB83 -> 123411723048 | AH83: =ROUND(AC83+AE83-AG83,0) -> 123411723048 | AJ83: 19472460196 | AK83: 19472460196 | AL83: =AJ83-AK83 -> 0 | AN83: 21357353770
B84: PT Irian Marine Product Development | C84: =W84 -> 0 | D84: 222225120 | E84: =C84+D84 -> 222225120 | J84: =E84+G84-I84 -> 222225120 | N84: =W84 -> 0 | P84: =N84+O84 -> 0 | U84: =P84+R84-T84 -> 0 | W84: 0 | X84: 0 | AA84: =AJ84 -> 200000000 | AC84: =AA84+AB84 -> 200000000 | AF84: ='AJE CAJE Sept 23'!B46 -> RLKS 2 | AG84: ='AJE CAJE Sept 23'!H46 -> 2e+08 | AH84: =ROUND(AC84+AE84-AG84,0) -> 0 | AJ84: 200000000 | AK84: 200000000 | AL84: =AJ84-AK84 -> 0 | AN84: 200000000
B85: CV Kanian Persada | C85: =W85 -> 512207423 | D85: -512207423 | E85: =C85+D85 -> 0 | J85: =E85+G85-I85 -> 0 | N85: =W85 -> 512207423 | O85: -512207423 | P85: =N85+O85 -> 0 | U85: =P85+R85-T85 -> 0 | W85: 512207423 | X85: 512207423 | Y85: =W85-X85 -> 0 | AA85: =AJ85 -> 4.8694321e+08 | AB85: 512207423 | AC85: =AA85+AB85 -> 9.9915063e+08 | AF85: ='AJE CAJE Sept 23'!B42 -> CAJE 7 | AG85: ='AJE CAJE Sept 23'!H42 -> 360752996 | AH85: =ROUND(AC85+AE85-AG85,0) -> 638397634 | AJ85: 4.8694321e+08 | AK85: 486943207 | AL85: =AJ85-AK85 -> 0.080048025 | AN85: 126190211
B86: Indo American Food, PT Piutang | Y86: =W86-X89 -> 0 | AB86: 100000 | AC86: =AA86+AB86 -> 100000 | AH86: =ROUND(AC86+AE86-AG86,0) -> 100000
A87: TBC | B87: Piutang Lain-Lain (PPN Jasa LN) | C87: =W87 -> 0 | E87: =C87+D87 -> 0 | J87: =E87+G87-I87 -> 0 | N87: =W87 -> 0 | P87: =N87+O87 -> 0 | U87: =P87+R87-T87 -> 0 | AA87: =AJ87 -> 0 | AC87: =AA87+AB87 -> 0 | AH87: =ROUND(AC87+AE87-AG87,0) -> 0 | AJ87: 0 | AN87: 0
B88: Piutang Lain-Lain | E88: =C88+D88 -> 0 | J88: =E88+G88-I88 -> 0 | AB88: 88924000 | AC88: =AA88+AB88 -> 88924000 | AH88: =ROUND(AC88+AE88-AG88,0) -> 88924000
E89: =C89+D89 -> 0 | J89: =E89+G89-I89 -> 0 | P89: =N89+O89 -> 0 | U89: =P89+R89-T89 -> 0 | X89: 0 | AC89: =AA89+AB89 -> 0 | AH89: =ROUND(AC89+AE89-AG89,0) -> 0 | AK89: 0
B90: Total Other Receivable | C90: =SUM(C83:C89) -> 133158984576 | E90: =SUM(E83:E89) -> 91174796671 | J90: =SUM(J83:J89) -> 91174796671 | N90: =SUM(N83:N89) -> 133158984576 | P90: =SUM(P83:P89) -> 94963698422 | U90: =SUM(U83:U89) -> 94963698422 | W90: =SUM(W83:W89) -> 133158984576 | X90: 133158984576 | Y90: =W90-X90 -> 0 | AA90: =SUM(AA83:AA89) -> 2.0159403e+10 | AC90: =SUM(AC83:AC89) -> 1.246999e+11 | AH90: =SUM(AH83:AH89) -> 124139144682 | AJ90: =SUM(AJ83:AJ89) -> 2.0159403e+10 | AK90: 20159403403 | AL90: =AJ90-AK90 -> 0.080047607 | AN90: =SUM(AN83:AN89) -> 21683543981
A91: Inventory
B92: Bahan Pembantu | C92: =W92 -> 16305238543 | E92: 16305238543 | J92: =E92+G92-I92 -> 16305238543 | N92: =W92 -> 16305238543 | P92: 2.0674774e+10 | U92: =P92+R92-T92 -> 2.0674774e+10 | W92: 16305238543 | X92: 16305238543 | Y92: =W92-X92 -> 0 | AA92: =AJ92 -> 1.2890765e+10 | AC92: 1.7383013e+10 | AH92: =ROUND(AC92+AE92-AG92,0) -> 17383013044 | AJ92: 1.2890765e+10 | AK92: 1.2890765e+10 | AL92: =AJ92-AK92 -> 0 | AN92: 10637571304
B93: Bahan Bakar | C93: =W93 -> 76848942 | E93: 76848942 | J93: =E93+G93-I93 -> 76848942 | N93: =W93 -> 76848942 | P93: 34860373 | U93: =P93+R93-T93 -> 34860373 | W93: 76848942 | X93: 76848942 | Y93: =W93-X93 -> 0 | AA93: =AJ93 -> 96562754 | AC93: 84387986 | AH93: =ROUND(AC93+AE93-AG93,0) -> 84387986 | AJ93: 96562754 | AK93: 96562754 | AL93: =AJ93-AK93 -> 0 | AN93: 131498449
B94: Persediaan Udang (Barang Jadi) | C94: =W94 -> 88132546606 | E94: =88132546606+8931966487 -> 97064513093 | J94: =E94+G94-I94 -> 97064513093 | N94: =W94 -> 88132546606 | P94: 1.0849051e+11 | U94: =P94+R94-T94 -> 1.0849051e+11 | W94: 88132546606 | X94: 88132546606 | Y94: =W94-X94 -> 0 | AA94: =AJ94 -> 50061246940 | AC94: 8.7174436e+10 | AH94: =ROUND(AC94+AE94-AG94,0) -> 87174436355 | AJ94: 50061246940 | AK94: 50061246940 | AL94: =AJ94-AK94 -> 0 | AN94: 37360346019
B95: Persediaan Breaded (Barang Jadi) | C95: =W95 -> 3808188569 | E95: 3808188569 | J95: =E95+G95-I95 -> 3808188569 | N95: =W95 -> 3808188569 | P95: 6.1299385e+09 | U95: =P95+R95-T95 -> 6.1299385e+09 | W95: 3808188569 | X95: 3808188569 | Y95: =W95-X95 -> 0 | AA95: =AJ95 -> 4118553810 | AC95: 4.7204653e+09 | AH95: =ROUND(AC95+AE95-AG95,0) -> 4720465278 | AJ95: 4118553810 | AK95: 4118553810 | AL95: =AJ95-AK95 -> 0 | AN95: 3819276495
B97: Total Inventory | C97: =SUM(C92:C95) -> 108322822660 | E97: =SUM(E92:E95) -> 117254789147 | J97: =SUM(J92:J95) -> 117254789147 | N97: =SUM(N92:N95) -> 108322822660 | P97: =SUM(P92:P95) -> 1.3533008e+11 | U97: =SUM(U92:U95) -> 1.3533008e+11 | W97: =SUM(W92:W95) -> 108322822660 | X97: 108322822660 | Y97: =W97-X97 -> 0 | AA97: =SUM(AA92:AA95) -> 6.7167128e+10 | AC97: =SUM(AC92:AC95) -> 1.093623e+11 | AH97: =SUM(AH92:AH95) -> 109362302663 | AJ97: =SUM(AJ92:AJ95) -> 6.7167128e+10 | AK97: 6.7167128e+10 | AL97: =AJ97-AK97 -> 0.29000092 | AN97: =SUM(AN92:AN95) -> 51948692267
A98: Prepaid Tax
B99: PPN Masukan | C99: =W99 -> 6709080953 | D99: 1.5777169e+09 | E99: =C99+D99 -> 8.2867979e+09 | J99: =E99+G99-I99 -> 8.2867979e+09 | N99: =W99 -> 6709080953 | O99: 1.1965596e+09 | P99: =N99+O99 -> 7.9056405e+09 | U99: =P99+R99-T99 -> 7.9056405e+09 | W99: 6709080953 | X99: 6709080953 | Y99: =W99-X99 -> 0 | AA99: =AJ99 -> 5242697364 | AB99: 1.1688742e+09 | AC99: =AA99+AB99 -> 6.4115716e+09 | AH99: =ROUND(AC99+AE99-AG99,0) -> 6411571554 | AJ99: 5242697364 | AK99: 5242697364 | AL99: =AJ99-AK99 -> 0 | AN99: 7180061865
B100: PPN KMS | C100: =W100 -> 98344793 | E100: =C100+D100 -> 98344793 | J100: =E100+G100-I100 -> 98344793 | N100: =W100 -> 98344793 | P100: =N100+O100 -> 98344793 | U100: =P100+R100-T100 -> 98344793 | W100: 98344793 | X100: 98344793 | Y100: =W100-X100 -> 0 | AA100: =AJ100 -> 102056637 | AB100: -3711844 | AC100: =AA100+AB100 -> 98344793 | AH100: =ROUND(AC100+AE100-AG100,0) -> 98344793 | AJ100: 102056637 | AK100: 102056637 | AL100: =AJ100-AK100 -> 0 | AN100: 0
B101: Prepaid PPh 25 | C101: =W101 -> 0 | E101: =C101+D101 -> 0 | F101: ='AJE CAJE Des 24'!A62 -> CAJE 8 | G101: ='AJE CAJE Des 24'!F62 -> 421615912 | H101: ='AJE CAJE Des 24'!A111 -> CAJE 14 | I101: ='AJE CAJE Des 24'!G111 -> 421615912 | J101: =E101+G101-I101 -> 0 | M101: Cek SPT | N101: =W101 -> 0 | P101: =N101+O101 -> 0 | Q101: ='AJE CAJE Sept 24'!B44 -> CAJE 8 | R101: ='AJE CAJE Sept 24'!G44 -> 316211934 | S101: ='AJE CAJE Sept 24'!B60 -> CAJE 12 | T101: ='AJE CAJE Sept 24'!H61 -> 316211934 | U101: =P101+R101-T101 -> 0 | W101: 0 | X101: 0 | AA101: =AJ101 -> 0 | AC101: =AA101+AB101 -> 0 | AD101: ='AJE CAJE Sept 23'!B58 -> CAJE 10 | AE101: ='AJE CAJE Sept 23'!G58 -> 41264112 | AF101: ='AJE CAJE Sept 23'!B68 -> CAJE 13 | AG101: ='AJE CAJE Sept 23'!H68 -> 41264112 | AH101: =ROUND(AC101+AE101-AG101,0) -> 0 | AJ101: 0 | AK101: 0 | AN101: 0
B102: Prepaid PPh 22 | C102: =W102 -> 0 | E102: =C102+D102 -> 0 | F102: ='AJE CAJE Des 24'!A58 -> CAJE 7 | G102: ='AJE CAJE Des 24'!F58+'AJE CAJE Des 24'!F85 -> 34089140 | H102: ='AJE CAJE Des 24'!A112 -> CAJE 14 | I102: ='AJE CAJE Des 24'!G112 -> 34089140 | J102: =E102+G102-I102 -> 0 | M102: Cek SPT | N102: =W102 -> 0 | P102: =N102+O102 -> 0 | Q102: ='AJE CAJE Sept 24'!B41 -> CAJE 7 | R102: ='AJE CAJE Sept 24'!G41 -> 24522154 | S102: ='AJE CAJE Sept 24'!B61 -> CAJE 12 | T102: ='AJE CAJE Sept 24'!H60 -> 24522154 | U102: =P102+R102-T102 -> 0 | W102: 0 | X102: 0 | AA102: =AJ102 -> 0 | AC102: =AA102+AB102 -> 0 | AD102: ='AJE CAJE Sept 23'!B55 -> CAJE 9 | AE102: ='AJE CAJE Sept 23'!G55 -> 25660083 | AF102: ='AJE CAJE Sept 23'!B69 -> CAJE 13 | AG102: ='AJE CAJE Sept 23'!H69 -> 25660083 | AH102: =ROUND(AC102+AE102-AG102,0) -> 0 | AJ102: 0 | AK102: 0 | AN102: 0
B103: Prepaid PPh 23 | C103: =W103 -> 0 | E103: =C103+D103 -> 0 | J103: =E103+G103-I103 -> 0 | N103: =W103 -> 0 | P103: =N103+O103 -> 0 | U103: =P103+R103-T103 -> 0 | W103: 0 | X103: 0 | AA103: =AJ103 -> 0 | AC103: =AA103+AB103 -> 0 | AH103: =ROUND(AC103+AE103-AG103,0) -> 0 | AJ103: 0 | AK103: 0 | AN103: 0
B104: Prepaid PPh 21 | F104: ='AJE CAJE Des 24'!A87 -> CAJE 12 | G104: ='AJE CAJE Des 24'!F87 -> 3806151 | J104: =E104+G104-I104 -> 3806151 | K104: -3806151 | M104: =J104+K104 -> 0
A105: Prepaid Expense | X105: 0 | AK105: 0
B106: Asuransi Dibayar Dimuka | C106: =W106 -> 0 | D106: 10093167 | E106: =C106+D106 -> 10093167 | J106: =E106+G106-I106 -> 10093167 | N106: =W106 -> 0 | O106: 40372668 | P106: =N106+O106 -> 40372668 | U106: =P106+R106-T106 -> 40372668 | W106: 0 | AA106: =AJ106 -> 137236872 | AB106: -1.1023646e+08 | AC106: =AA106+AB106 -> 27000417 | AH106: =ROUND(AC106+AE106-AG106,0) -> 27000417 | AJ106: 137236872 | AK106: 137236872 | AL106: =AJ106-AK106 -> 0 | AN106: 116757300
X107: 0 | AK107: 0
A108: Uang Muka Pembelian | X108: 0
B109: Biaya Pra IPO | C109: =W109 -> 897473228 | D109: 2218471687 | E109: =C109+D109 -> 3115944915 | H109: ='AJE CAJE Des 24'!A29 -> CAJE 3 | I109: ='AJE CAJE Des 24'!G30 -> 3115944915 | J109: =E109+G109-I109 -> 0 | N109: =W109 -> 897473228 | O109: 2250971687 | P109: =N109+O109 -> 3148444915 | S109: ACJE 18 & 19 | T109: ='AJE CAJE Sept 24'!H95+'AJE CAJE Sept 24'!H99 -> 3148444915 | U109: =P109+R109-T109 -> 0 | W109: 897473228 | X109: 897473228 | Y109: =W109-X109 -> 0 | AA109: =AJ109 -> 0 | AB109: 897473228 | AC109: =AA109+AB109 -> 897473228 | AH109: =ROUND(AC109+AE109-AG109,0) -> 897473228 | AJ109: 0 | AN109: 0
B110: Uang Muka Pembelian Bahan Baku | F110: ='AJE CAJE Des 24'!A45 -> RLKS 1 | G110: ='AJE CAJE Des 24'!F45 -> 2.7862788e+10 | J110: =E110+G110-I110 -> 2.7862788e+10 | Q110: ='AJE CAJE Sept 24'!B64 -> CAJE 13 | R110: ='AJE CAJE Sept 24'!G64 -> 1.1680623e+09 | U110: =P110+R110-T110 -> 1.1680623e+09
...

Sheet BS
A1: PT INDO AMERICAN SEAFOODS
A2: LAPORAN POSISI KEUANGAN
A3: Tanggal 31 Desember 2024 dan 2023
A4: (Disajikan dalam Rupiah, kecuali dinyatakan lain)
F6: Catatan/
F7: CATATAN
F10: Notes | H10: 2024 | J10: 45536 | L10: 2023
A12: ASET | N12: ASSETS
A13: ASET LANCAR | N13: CURRENT ASSETS
A14: Kas dan Bank | F14: 4 | H14: =WS!J43 -> 4.2068222e+08 | J14: =WS!U43 -> 1.1398025e+10 | L14: =WS!W43 -> 2159354956 | N14: Cash on Hand and in Banks
A15: Piutang Usaha | N15: Trade Accounts Receivable
B16: Pihak Berelasi | F16: 5 | H16: =WS!J75 -> 8079657361 | J16: =WS!U75 -> 2.6370908e+09 | L16: =WS!W75 -> 8079657361 | O16: Related Parties
B17: Pihak Ketiga | F17: 5 | H17: =WS!J70+WS!J79 -> 4.4619752e+10 | J17: =WS!U70+WS!U79 -> 22964047771 | L17: =WS!W70+WS!W79 -> 13123277095 | O17: Third Parties
A18: Piutang Lain-lain dari Pihak Berelasi | F18: 6 | H18: =WS!J90 -> 91174796671 | J18: =WS!U90 -> 94963698422 | L18: =WS!W90 -> 133158984576 | N18: Other Receivables from Related Parties
A19: Persediaan | F19: 7 | H19: =WS!J97 -> 117254789147 | J19: =WS!U97 -> 1.3533008e+11 | L19: =WS!W97 -> 108322822660 | N19: Inventories
A20: Pajak Dibayar Dimuka | F20: 14a | H20: =SUM(WS!J99:J104) -> 8.3889488e+09 | J20: =SUM(WS!U99:U103) -> 8.0039853e+09 | L20: =SUM(WS!W99:W103) -> 6807425746 | N20: Prepaid Taxes
A21: Biaya Dibayar Dimuka | H21: =SUM(WS!J106:J111) -> 2.9458466e+10 | J21: =SUM(WS!U106:U110) -> 1.2084349e+09 | L21: =SUM(WS!W106:W109) -> 897473228 | N21: Prepaid Expenses
A23: Jumlah Aset Lancar | H23: =SUM(H14:H21) -> 2.9939709e+11 | J23: =SUM(J14:J21) -> 2.7650536e+11 | L23: =SUM(L14:L21) -> 272548995622 | N23: Total Current Assets
A25: ASET TIDAK LANCAR | N25: Non-Current Assets
A26: Aset Tetap | N26: Property, Plant and Equipment
A27: Aset Dalam Proses | F27: 8 | N27: Work in Process
B28: (Setelah dikurangi akumulasi | O28: (Net of accumulated
B29: penyusutan sebesar | O29: depreciation of
B30: Rp 18.960.855.664 | O30: Rp 18.960.855.664
B31: dan Rp 16.681.774.940 | O31: and Rp 16.681.774.940
B32: masing-masing pada | O32: as of December 31, 2024
B33: 31 Desember 2024 dan 2023) | F33: 9 | H33: =WS!J124-WS!J134+WS!J138 -> 2.5023283e+10 | J33: =WS!U124-WS!U134+WS!U138 -> 2.5513227e+10 | L33: =WS!W124-WS!W134+WS!W138-1 -> 27302363571 | O33: and 2023 respectively)
A34: Investasi | H34: =WS!J143 -> 1050000000 | J34: =WS!U143 -> 1050000000 | L34: =WS!W143 -> 1050000000 | N34: Investment
A35: Aset Pajak Tangguhan | F35: 14d | H35: =SUM(WS!J145:J146)-WS!J148 -> 2.4256979e+08 | J35: =SUM(WS!U145:U146)-WS!U148 -> 2.4256979e+08 | L35: =SUM(WS!W145:W146)-WS!W148 -> 2.4256979e+08 | N35: Deferred Tax Assets
A37: Jumlah Aset Tidak Lancar | H37: =SUM(H27:H35) -> 2.6315853e+10 | J37: =SUM(J27:J35) -> 2.6805796e+10 | L37: =SUM(L27:L35) -> 2.8594933e+10 | N37: Total Non-Current Assets
A39: JUMLAH ASET | H39: =H23+H37 -> 3.2571294e+11 | J39: =J23+J37 -> 3.0331116e+11 | L39: =L23+L37 -> 3.0114393e+11 | N39: TOTAL ASSETS
F42: Catatan/
F43: Notes | H43: 2024 | J43: =J10 -> 45536 | L43: 2023
A44: LIABILITAS DAN EKUITAS | N44: LIABILITIES AND EQUITY
A45: LIABILITAS | N45: LIABILITIES
A46: LIABILITAS JANGKA PENDEK | N46: CURRENT LIABILITIES
A47: Utang Usaha | N47: Trade Accounts Payable
B48: Pihak Berelasi | F48: 10 | H48: =WS!J241 -> 3.3114818e+10 | J48: =WS!U241 -> 3.4916763e+10 | L48: =WS!W241 -> 62518053072 | O48: Related Parties
B49: Pihak Ketiga | F49: 10 | H49: =WS!J237 -> 4.2917358e+09 | J49: =WS!U237 -> 3.7095089e+09 | L49: =WS!W237 -> 12029137713 | O49: Third Parties
A50: Utang Lain-lain | N50: Other Payables
B51: Pihak Berelasi | F51: 11 | H51: =WS!J248-H52 -> 0 | J51: =WS!U248-J52 -> -451584604 | L51: =WS!W248-L52 -> 0 | O51: Related Parties
B52: Pihak Ketiga | F52: 11 | H52: =WS!J243 -> 0 | J52: =WS!U243 -> 0 | L52: =WS!W243 -> 41000000 | O52: Third Parties
A53: Utang Bank | F53: 15 | H53: =WS!J175 -> 126612232871 | J53: =WS!U175 -> 100164739154 | L53: =WS!W175 -> 135768265866 | N53: Bank Loans
A54: Beban Akrual | F54: 12 | H54: =WS!J278-H59 -> 1.5639524e+09 | J54: =WS!U278-J59 -> 2.3091817e+09 | L54: =WS!W278-L59 -> 937337041 | N54: Accrued Expenses
A55: Utang Pajak | F55: 14b | H55: =WS!J266 -> 7.3139746e+08 | J55: =WS!U266 -> 4.0638813e+09 | L55: =WS!W266 -> 1.6996817e+09 | N55: Taxes Payable
A56: Bagian Lancar | N56: Current Portion of
B57: Utang Jangka Panjang | O57: Current Liabilities
B58: Utang Bank | F58: 15 | H58: =WS!J285 -> 0 | J58: =WS!U285 -> 0 | L58: =WS!W285 -> 0 | O58: Bank Loans
B59: Utang Pembelian Aset Tetap | F59: 13 | H59: =WS!J274 -> 0 | J59: =WS!U274 -> 19446177 | L59: =WS!W274 -> 76360023 | O59: Purchase of Fixed Assets Liabilities
B60: Utang Pembiayaan Konsumen | H60: =[1]WBS!AO324 -> 0 | J60: =[1]WBS!AQ324 -> 0 | L60: =[1]WBS!AU324 -> 0 | O60: Consumer Financing Debt
A63: Jumlah Liabilitas Jangka Pendek | H63: =SUM(H48:H60) -> 1.6631414e+11 | J63: =SUM(J48:J60) -> 1.4473194e+11 | L63: =SUM(L48:L60) -> 2.1306984e+11 | N63: Total Current Liabilities
A65: LIABILITAS JANGKA PANJANG | N65: NON-CURRENT LIABILITIES
A66: Liabiltas Jangka Panjang - Setelah | N66: Long-Term Liabilities
A67: Dikurangi Bagian Lancar | N67: Less Cureent Portion
B68: Utang Bank | F68: 15 | H68: =WS!J304-WS!J295 -> 0 | J68: =WS!U304-WS!U295 -> 0 | L68: =WS!W304-WS!W295 -> 0 | O68: Bank Loans
B69: Utang Pembelian Aset Tetap | F69: 13 | H69: =WS!J295 -> 0 | J69: =WS!U295 -> 0 | L69: =WS!W295 -> 0 | O69: Purchase of Fixed Assets Liabilities
A70: Liabilitas Imbalan Pascakerja | F70: 16 | H70: =WS!J292 -> 2647745936 | J70: =WS!U292 -> 2857433432 | L70: =WS!W292 -> 2647745936 | N70: Post-Employment Benefits Liabilities
A72: Utang Lain-lain | H72: 0 | J72: 0 | L72: 0 | N72: Other Liability
A73: Jumlah Liabilitas Jangka Panjang | H73: =SUM(H68:H72) -> 2647745936 | J73: =SUM(J68:J72) -> 2857433432 | L73: =SUM(L68:L72) -> 2647745936 | N73: Total Non-Current Liabilities
A75: JUMLAH LIABILITAS | H75: =H63+H73 -> 1.6896188e+11 | J75: =J63+J73 -> 1.4758937e+11 | L75: =L63+L73 -> 2.1571758e+11 | N75: TOTAL LIABILITIES
A77: EKUITAS | N77: EQUITY
A78: Modal Saham - Nilai Nominal | N78: Share capital
A79: Rp 50,- per Saham | N79: Par value Rp 50 per share,
B80: Modal Dasar Sebesar 3.200.000.000 Saham | O80: Authorized Capital 3,200,000,000 shares
B81: pada 31 Desember 2024 dan 800.000.000 | O81: as of December 31, 2024 and 800,000,000
B82: saham pada 31 Desember 2023 | O82: Shares as of December, 31 2023
B83: Modal Ditempatkan dan Disetor Penuh | O83: Subscribed and Paid-up - Capital
B84: 1.390.000.000 lembar pada | O84: 1,390,000,000 shares
B85: 27 Juni 2024, | O85: as of Juni 27, 2024
B86: 1.100.000.000 pada Tahun 2023 | F86: 17a | H86: =SUM(WS!J309:J310) -> 69500000000 | J86: =SUM(WS!U309:U310) -> 69500000000 | L86: =WS!W309 -> 40000000000 | O86: 1,100,000,000 shares as of December 2023
A87: Tambahan Modal Disetor | F87: 18 | H87: =SUM(WS!J311:J313) -> 80755745754 | J87: =SUM(WS!U311:U313) -> 80755745754 | L87: =WS!W311 -> 25871690669 | N87: Additional paid-in capital
A88: Deviden | N88: Deviden
A89: Penghasilan Komprehensif lain | F89: 25 | H89: =WS!J326 -> -4.8278619e+08 | J89: =WS!U326 -> -4.8278619e+08 | L89: =WS!W326 -> -4.8278619e+08 | N89: Other comprehensive income
A90: Saldo Laba | N90: Retained earnings
A91: Ditentukan Penggunaannya | F91: 17b | H91: =WS!J309*1% -> 550000000 | J91: =WS!W309*1% -> 400000000 | L91: =L86*1% -> 400000000 | N91: Appropriated
A92: Saldo Laba Ditahan | H92: =WS!J316-H91 -> 4.4874432e+09 | J92: =WS!U316-J91 -> 4.6374432e+09 | L92: =WS!W316-L91 -> 1.8237503e+10 | N92: Retained earnings
A93: Laba Tahun Berjalan | H93: =WS!J317 -> 1.9406587e+09 | J93: =WS!U317 -> 9.1138744e+08 | L93: =WS!W317 -> 1.3999403e+09 | N93: Net Income For The Year
A94: Tidak Ditentukan Penggunaannya | F94: 17b | H94: =(WS!S319-H91)*0 -> 0 | J94: =(WS!U319-J91)*0 -> 0 | L94: =(WS!W319-L91)*0 -> 0 | N94: Unappropriated
A96: JUMLAH EKUITAS | H96: =SUM(H80:H94) -> 1.5675106e+11 | J96: =SUM(J80:J94) -> 1.5572179e+11 | L96: =SUM(L80:L94) -> 8.5426348e+10 | N96: TOTAL EQUITY
A98: JUMLAH LIABILITAS DAN EKUITAS | H98: =H75+H96 -> 3.2571294e+11 | J98: =J75+J96 -> 3.0331116e+11 | L98: =L75+L96 -> 3.0114393e+11 | N98: TOTAL LIABILITIES AND EQUITY
A100: *) Disajikan Kembali (Catatan 35) | N100: *) As Restated (Note 35)
C102: Ctrl | H102: =H98-H39 -> -0.48443604 | J102: =J98-J39 -> -0.049865723 | L102: =L98-L39 -> 0.0054931641

Sheet PL
A1: PT INDO AMERICAN SEAFOODS
A2: LAPORAN LABA RUGI DAN PENGHASILAN KOMPREHENSIF LAIN
A3: UNTUK TAHUN YANG BERAKHIR PADA TANGGAL-TANGGAL
A4: 31 Desember 2024 dan 2023
A5: (Disajikan dalam Rupiah, kecuali dinyatakan lain)
D7: Catatan/ | V7: Gross Margin
D8: Notes | F8: 2024 | H8: 45536 | J8: 45170 | L8: 2023 | N8: 2022 | P8: 2021*) | W8: 45627 | X8: 45536 | Y8: 45536 | Z8: 45170 | AA8: 45261
A10: PENJUALAN | D10: 19 | F10: =WS!J338 -> 1.8249335e+11 | H10: =WS!U338 -> 1.0029508e+11 | J10: =WS!AH338 -> 145641937120 | L10: =WS!W338 -> 189007036121 | N10: =WS!AJ338 -> 245651809706 | P10: =WS!AN338 -> 212866021082 | S10: SALES | W10: =F13/F10 -> 0.23621948 | X10: =F13/F10 -> 0.23621948 | Y10: =H13/H10 -> 0.29503238 | Z10: =J13/J10 -> 0.17903335 | AA10: =L13/L10 -> 0.17190125
A11: BEBAN POKOK PENJUALAN | D11: 20 | F11: =-WS!J399 -> -1.3938487e+11 | H11: =-WS!U399 -> -7.0704787e+10 | J11: =-WS!AH399 -> -119567172509 | L11: =-WS!W399 -> -156516490239 | N11: =-WS!AJ399 -> -2.0108262e+11 | P11: =-WS!AN399 -> -1.7815083e+11 | S11: COST OF GOODS SOLD
A13: LABA KOTOR | F13: =ROUND(F10+F11,0) -> 43108483705 | H13: =ROUND(H10+H11,0) -> 29590297673 | J13: =ROUND(J10+J11,0) -> 26074764611 | L13: =ROUND(L10+L11,0) -> 32490545882 | N13: =ROUND(N10+N11,0) -> 44569188164 | P13: =ROUND(P10+P11,0) -> 34715189205 | S13: GROSS PROFIT
A14: Beban Penjualan | D14: 21 | F14: =-WS!J416 -> -1.4110744e+10 | H14: =-WS!U416 -> -9.3927967e+09 | J14: =-WS!AH416 -> -12120734220 | L14: =-WS!W416 -> -11943842250 | N14: =-WS!AJ416 -> -1.9921262e+10 | P14: =-WS!AN416 -> -1.6958316e+10 | S14: Selling Expenses | W14: =-F14/F10 -> 0.077321963 | X14: =-F14/F10 -> 0.077321963 | Y14: =-H14/H10 -> 0.093651615 | Z14: =-J14/J10 -> 0.08322283 | AA14: =-L14/$L$10 -> 0.06319258
A15: Beban Umum dan Administrasi | D15: 22 | F15: =-WS!J465 -> -1.4884752e+10 | H15: =-WS!U465 -> -1.3159815e+10 | J15: =-WS!AH465 -> -6007580878 | L15: =-WS!W465 -> -8581798722 | N15: =-WS!AJ465 -> -1.0213045e+10 | P15: =-WS!AN465 -> -8.7014883e+09 | S15: General and Administration Expenses | W15: =-F15/F10 -> 0.081563256 | X15: =-F15/F10 -> 0.081563256 | Y15: =-H15/H10 -> 0.13121097 | Z15: =-J15/J10 -> 0.041248977 | AA15: =-L15/$L$10 -> 0.045404652
A16: Pendapatan (Beban) Lain-lain - Bersih | D16: 23 | F16: =WS!J474 -> -1.612506e+09 | H16: =WS!U474 -> 1.6476179e+09 | J16: =WS!AH474 -> -693108623 | L16: =WS!W474 -> -601084731 | N16: =WS!AJ474 -> -1.1384742e+09 | P16: =WS!AN474 -> -1.2463122e+08 | S16: Other Income (Charges) - Net
A17: Beban Bunga dan Keuangan | D17: 24 | F17: =-WS!J485 -> -9.4242921e+09 | H17: =-WS!U485 -> -6.7069744e+09 | J17: =-WS!AH485 -> -6430690329 | L17: =-WS!W485 -> -9.3523807e+09 | N17: =-WS!AJ485 -> -6651524107 | P17: =-WS!AN485 -> -4810236291 | S17: Interest and Finance Cost
A19: Sub Jumlah | F19: =SUM(F14:F17) -> -4.0032294e+10 | H19: =SUM(H14:H17) -> -2.7611968e+10 | J19: =SUM(J14:J17) -> -25252114050 | L19: =SUM(L14:L17) -> -3.0479106e+10 | N19: =SUM(N14:N17) -> -3.7924305e+10 | P19: =SUM(P14:P17) -> -3.0594672e+10 | S19: Sub Total
A21: LABA SEBELUM PAJAK PENGHASILAN | F21: =F13+F19 -> 3.0761898e+09 | H21: =H13+H19 -> 1.9783296e+09 | J21: =J13+J19 -> 822650561 | L21: =L13+L19 -> 2.0114394e+09 | N21: =N13+N19 -> 6.6448833e+09 | P21: =P13+P19 -> 4.120517e+09 | S21: PROFIT INCOME BEFORE TAX
A22: Manfaat (Beban) Pajak Penghasilan: | S22: Income Tax Benefit (Expenses)
B23: Pajak Kini | D23: 14c | F23: =-WS!J489 -> -1135531100 | H23: =-WS!U489 -> -1066942140 | J23: =-WS!AH489 -> -299497000 | L23: =-WS!W489 -> -6.7332782e+08 | N23: =-WS!AJ489 -> -1515553820 | P23: =-WS!AN489 -> -8.7911142e+08 | T23: Current Income Tax
B24: Pajak Tangguhan | D24: 14c | F24: =-WS!J492 -> 0 | H24: =-WS!U492 -> 0 | J24: =-WS!AH492 -> 0 | L24: =-WS!W492 -> 61828681 | N24: =-WS!AJ492 -> 81839521 | P24: =WS!AN492 -> 93846379 | T24: Deferred Tax
A26: LABA BERSIH TAHUN BERJALAN | F26: =F21+F24+F23 -> 1.9406587e+09 | H26: =H21+H24+H23 -> 9.1138744e+08 | J26: =J21+J24+J23 -> 523153561 | L26: =L21+L24+L23 -> 1.3999403e+09 | N26: =N21+N24+N23 -> 5.211169e+09 | P26: =P21+P24+P23 -> 3.335252e+09 | S26: NET INCOME FOR THE YEAR
A27: Pengukuran Kembali Imbalan Pasti | D27: 25 | F27: =WS!J498 -> 0 | H27: =WS!U498 -> 0 | J27: =WS!AH498 -> 0 | L27: =WS!W498 -> -5379083 | N27: =WS!AJ498 -> 156702531 | P27: =WS!AN498 -> 27264083 | S27: Remeasurement of Defined Benefit
A28: Pajak Penghasilan Terkait | D28: 25 | F28: =-WS!J501 -> 0 | H28: =-WS!U501 -> 0 | J28: =-WS!AH501 -> 0 | L28: =-WS!W501 -> 1183398.3 | N28: =-WS!AJ501 -> -34474557 | P28: =-WS!AN501 -> -5998098 | S28: Income Tax Related
A30: LABA KOMPREHENSIF | S30: COMPREHENSIVE INCOME
A31: TAHUN BERJALAN | F31: =F26+F27+F28 -> 1.9406587e+09 | H31: =H26+H27+H28 -> 9.1138744e+08 | J31: =J26+J27+J28 -> 523153561 | L31: =L26+L27+L28 -> 1.3957446e+09 | N31: =N26+N27+N28 -> 5.333397e+09 | P31: =P26+P27+P28 -> 3.356518e+09 | S31: FOR THE YEAR
A33: LABA PER SAHAM DASAR | D33: 26 | L33: 1.7446805 | N33: 6.5139613 | P33: 4.169065 | S33: BASIC EARNINGS PER SHARE
L35: =L27*22% -> -1183398.3 | N35: =N27*22% -> 34474557 | P35: =P27*22% -> 5998098.3
D37: Ctrl | F37: =F31-WS!J503 -> 0.30603027 | H37: =H31-WS!U503 -> 0.11767387 | J37: =J31-WS!AH503 -> 0 | L37: =L31-WS!W503 -> 0 | N37: =N31-[1]WBS!BX535 -> -0.35416031 | P37: =P31-[1]WBS!CE535 -> -0.12252998
A71: Penghasilan Komprehensif Lain

Sheet LPE
A1: =[2]PL!A1 -> PT INDO AMERICAN SEAFOODS
A2: LAPORAN PERUBAHAN EKUITAS INTERIM
A3: UNTUK TAHUN YANG BERAKHIR PADA ENAM BULAN
A4: 30 September 2024 dan 2023
A5: (Disajikan dalam Rupiah, kecuali dinyatakan lain)
I12: Tambahan | K12: Penghasilan | N12: Saldo Laba/ Retained Earning | R12: Surplus Revaluasi
I13: Modal Disetor | K13: Komprehensif Lain/ | N13: Ditentukan | P13: Tidak Ditentukan | R13: Aset tetap
E14: Catatan/ | F14: Modal Saham/ | I14: Additional | K14: Other Comprehensive | N14: Penggunaannya/ | P14: Penggunaannya/ | R14: Asset Revalution | T14: Jumlah Ekuitas/
E15: Notes | F15: Share Capital | I15: Paid-in-Capital | K15: Income | N15: Appropriated | P15: Unappropriated | R15: Surplus | T15: Total Equity
A18: Saldo 1 Januari 2020 | F18: 40000000000 | I18: 25871690669 | K18: -893983003 | N18: 0 | P18: 7.6832486e+09 | R18: =[2]BS!AL90 -> 0 | T18: =SUM(F18:R18) -> 7.2660956e+10 | V18: Balance as of January 1, 2020
A19: Pengukuran Kembali Program | V19: Remeasurement of
A20: Imbalan Pasti | K20: 2.7189854e+08 | N20: 0 | P20: 0 | R20: 0 | T20: =SUM(F20:P20) -> 2.7189854e+08 | V20: Defined Benefit
A21: Laba Tahun Berjalan | F21: 0 | I21: 0 | K21: 0 | N21: 0 | P21: =2407833315.7075+1 -> 2.4078333e+09 | R21: 0 | T21: =SUM(F21:P21) -> 2.4078333e+09 | V21: Profit for The Year
A23: Penyajian Kembali sesuai PSAK 26 | F23: 0 | I23: 0 | K23: 0 | P23: ='[2]AJE CAJE 2020'!G46*0 -> 0 | R23: 0 | T23: =P23 -> 0 | V23: Restatement in accordance with PSAK 26
A25: Saldo 31 Desember 2020 | F25: =[2]WBS!CL346 -> 40000000000 | I25: =[2]WBS!CL347 -> 25871690669 | K25: =SUM(K18:K21) -> -6.2208447e+08 | N25: =[2]WBS!CK354 -> 0 | P25: =SUM(P18:P21)+P23+1 -> 1.0091082e+10 | R25: =SUM(R18:R21) -> 0 | T25: =T18+T20+T21+T23+1 -> 7.5340688e+10 | V25: Balance as of December 31, 2020
A27: Pengukuran Kembali Program | V27: Remeasurement of
A28: Imbalan Pasti | F28: 0 | I28: 0 | K28: 21265985 | N28: 0 | P28: 0 | R28: 0 | T28: =SUM(F28:R28) -> 21265985 | V28: Defined Benefit
A29: Laba Tahun Berjalan | F29: 0 | I29: 0 | K29: 0 | N29: 0 | P29: =[3]PL!N26-1 -> 3.335252e+09 | R29: 0 | T29: =SUM(F29:R29) -> 3.335252e+09 | V29: Profit for The Year
A31: Saldo 31 Desember 2021 | F31: =SUM(F25:F29) -> 40000000000 | I31: =SUM(I25:I29) -> 25871690669 | K31: =SUM(K25:K29) -> -6.0081848e+08 | N31: =SUM(N25:N29) -> 0 | P31: =SUM(P25:P29) -> 1.3426334e+10 | R31: =R25 -> 0 | T31: =SUM(T25:T29) -> 7.8697206e+10 | V31: Balance as of December 31, 2021
A33: Pengukuran Kembali Program | V33: Remeasurement of
A34: Imbalan Pasti | F34: 0 | I34: 0 | K34: 1.2222797e+08 | N34: 0 | P34: 0 | R34: 0 | T34: =SUM(F34:R34) -> 1.2222797e+08 | V34: Defined Benefit
A35: Laba Tahun Berjalan | F35: 0 | I35: 0 | K35: 0 | N35: 0 | P35: 5.211169e+09 | R35: 0 | T35: =SUM(F35:R35) -> 5.211169e+09 | V35: Profit for The Year
A36: Cadangan Umum | F36: 0 | I36: 0 | K36: 0 | N36: 400000000 | P36: -400000000 | T36: =SUM(F36:R36) -> 0 | V36: General Reserves
A38: Saldo 1 Januari 2023 | F38: =SUM(F31:F37) -> 40000000000 | I38: =SUM(I31:I37) -> 25871690669 | K38: =SUM(K31:K37) -> -4.7859051e+08 | N38: =SUM(N31:N37) -> 400000000 | P38: =SUM(P31:P37) -> 1.8237503e+10 | R38: =SUM(R31:R37) -> 0 | T38: =SUM(T31:T37) -> 8.4030603e+10 | V38: Balance as of January 1, 2023
A40: Pengukuran Kembali Program | V40: Remeasurement of
A41: Imbalan Pasti | F41: 0 | I41: 0 | K41: =WS!W324 -> -4195684.7 | N41: 0 | P41: 0 | R41: 0 | T41: =SUM(F41:R41) -> -4195684.7 | V41: Defined Benefit
A42: Laba Tahun Berjalan | F42: 0 | I42: 0 | N42: 0 | P42: =PL!L26 -> 1.3999403e+09 | R42: 0 | T42: =SUM(F42:R42) -> 1.3999403e+09 | V42: Profit for The Year
A43: Cadangan Umum | F43: 0 | I43: 0 | K43: 0 | N43: 0 | P43: 0 | T43: =SUM(F43:R43) -> 0 | V43: General Reserves
A45: Laba Tahun Berjalan | F45: 0 | I45: 0 | K45: 0 | N45: 0 | P45: =PL!J26 -> 523153561 | R45: 0 | T45: =SUM(F45:R45) -> 523153561 | V45: Profit for The Year
A47: Saldo 30 September 2023 | F47: =F38+F45 -> 40000000000 | I47: =I38+I45 -> 25871690669 | K47: =K38+K45 -> -4.7859051e+08 | N47: =N38+N45 -> 400000000 | P47: =P38+P45 -> 1.8760656e+10 | R47: =SUM(R40:R46) -> 0 | T47: =T38+T45 -> 8.4553757e+10 | V47: Balance as of September 30, 2023
A49: Saldo 31 Desember 2023 | F49: =F38+SUM(F40:F43) -> 40000000000 | I49: =I38+SUM(I40:I43) -> 25871690669 | K49: =K38+SUM(K40:K43) -> -4.8278619e+08 | N49: =N38+SUM(N40:N43) -> 400000000 | P49: =P38+SUM(P41:P43)-1 -> 1.9637443e+10 | R49: =SUM(R37:R43) -> 0 | T49: =T38+SUM(T41:T43)-1 -> 8.5426348e+10 | V49: Balance as of December 31, 2023
A51: Setoran Modal | F51: =-WS!O309 -> 15000000000 | P51: =-WS!O316 -> -15000000000 | T51: =SUM(F51:R51) -> 0 | V51: Paid up Capital
A52: Pengukuran Kembali Program | V52: Remeasurement of
A53: Imbalan Pasti | F53: 0 | I53: 0 | J53: 0 | K53: 0 | L53: 0 | M53: 0 | N53: 0 | P53: 0 | R53: 0 | T53: =SUM(F53:R53) -> 0 | V53: Defined Benefit
A54: Tambahan Modal Disetor | F54: 0 | I54: =SUM(WS!U312:U313) -> 54884055085 | K54: 0 | N54: 0 | P54: 0 | T54: =SUM(F54:R54) -> 54884055085 | V54: Additional Paid-in Capital | X54: Blm dikurangi biaya emisi
A55: Setoran Modal | F55: =WS!U310 -> 14500000000 | I55: 0 | K55: 0 | N55: 0 | P55: 0 | T55: =SUM(F55:R55) -> 14500000000 | V55: Paid-up Capital
A56: Laba Tahun Berjalan | F56: 0 | I56: 0 | K56: 0 | N56: 0 | P56: =PL!H26 -> 9.1138744e+08 | R56: 0 | T56: =SUM(F56:R56) -> 9.1138744e+08 | V56: Profit for The Year
A57: Cadangan Umum | F57: 0 | I57: 0 | K57: 0 | P57: =-N57 -> 0 | T57: =SUM(F57:R57) -> 0 | V57: General Reserves | X57: apakah 1% lgsg disesuaikan dengan Modal nya?
A59: Saldo 30 September 2024 | F59: =F49+SUM(F51:F57) -> 69500000000 | I59: =I49+SUM(I51:I57) -> 80755745754 | K59: =K49+SUM(K51:K57) -> -4.8278619e+08 | N59: =N49+SUM(N51:N57) -> 400000000 | P59: =P49+SUM(P51:P57) -> 5.5488306e+09 | R59: =SUM(R51:R57) -> 0 | T59: =T49+SUM(T51:T57) -> 1.5572179e+11 | V59: Balance as of September 30, 2024
A61: Setoran Modal | F61: =-WS!D309 -> 15000000000 | P61: =-WS!D326 -> 0 | T61: =SUM(F61:R61) -> 15000000000 | V61: Paid up Capital
A62: Pengukuran Kembali Program | V62: Remeasurement of
A63: Imbalan Pasti | F63: 0 | I63: 0 | J63: 0 | K63: 0 | L63: 0 | M63: 0 | N63: 0 | P63: 0 | R63: 0 | T63: =SUM(F63:R63) -> 0 | V63: Defined Benefit
A64: Tambahan Modal Disetor | F64: 0 | I64: =SUM(WS!J312:J313) -> 54884055085 | K64: 0 | N64: 0 | P64: 0 | T64: =SUM(F64:R64) -> 54884055085 | V64: Additional Paid-in Capital
A65: Setoran Modal | F65: =WS!J310 -> 14500000000 | I65: 0 | K65: 0 | N65: 0 | P65: 0 | T65: =SUM(F65:R65) -> 14500000000 | V65: Paid-up Capital
A66: Laba Tahun Berjalan | F66: 0 | I66: 0 | K66: 0 | N66: 0 | P66: =PL!F26 -> 1.9406587e+09 | R66: 0 | T66: =SUM(F66:R66) -> 1.9406587e+09 | V66: Profit for The Year
A67: Cadangan Umum | F67: 0 | I67: 0 | K67: 0 | P67: =-N67 -> 0 | T67: =SUM(F67:R67) -> 0 | V67: General Reserves | X67: apakah 1% lgsg disesuaikan dengan Modal nya?
A69: Saldo 31 Desember 2024 | F69: =F49+SUM(F61:F67) -> 69500000000 | I69: =I49+SUM(I61:I67) -> 80755745754 | K69: =K49+SUM(K61:K67) -> -4.8278619e+08 | N69: =N49+SUM(N61:N67) -> 400000000 | P69: =P49+SUM(P61:P67) -> 2.1578102e+10 | R69: =SUM(R61:R67) -> 0 | T69: =T49+SUM(T61:T67) -> 1.7175106e+11 | V69: Balance as of December 31, 2024
D72: 45627 | F72: =F69-BS!H86 -> 0 | I72: =I69-BS!H87 -> 0 | K72: =K69-BS!H89 -> 0 | N72: =N69-BS!H91 -> -150000000 | P72: =P69-BS!H92-BS!H93 -> 1.515e+10 | T72: =T69-BS!H96 -> 1.5e+10
D74: 45261 | F74: =F49-WS!W309 -> 0 | I74: =I49-WS!W311 -> 0 | K74: =K49-BS!L89 -> 0 | N74: =(WS!W309*1%)-N49 -> 0 | P74: =(P49-WS!W319)+N49 -> -0.19541168 | T74: =T49-WS!W328 -> -0.19540405
D77: 2023 | F77: =F49-[2]WBS!AU346 -> 0 | I77: =I49-[2]WBS!AU347 -> 0 | K77: =K49-[2]WBS!AU361 -> 0 | N77: =N49-[2]BS!T94 -> 0 | P77: =P49-[3]BS!J88 -> -0.19541168 | T77: =T49-[3]BS!J90 -> -0.19540405
D82: 2021 | K82: =[2]BS!AF92-K31 -> 0 | P82: =P31-[2]BS!AF95 -> 0.15871429 | R82: =R31-[2]BS!AF95 -> -1.3426334e+10 | T82: =T25-[2]BS!AL97 -> 1.28125
D85: 2020 | K85: =[2]BS!AL92-K25 -> 0 | P85: =P25-[2]BS!AL95 -> 1.2812443 | R85: =R31-[2]BS!AF95 -> -1.3426334e+10 | T85: =[2]BS!AL97-[2]LPE!T25 -> -0.28125
A127: Catatan atas laporan keuangan merupakan bagian
A128: yang tidak terpisahkan dari laporan keuangan secara keseluruhan.

Sheet CF
A1: PT INDO AMERICAN SEAFOODS TBK
A2: LAPORAN ARUS KAS
A3: Untuk Tahun-tahun yang Berakhir pada 31 Desember 2024 dan 2023
A4: (Disajikan dalam Rupiah, kecuali Dinyatakan Lain)
D6: Catatan/
D7: Notes | F7: 2024 | H7: 2023
A9: ARUS KAS DARI AKTIVITAS | K9: CASH FLOWS FROM OPERATING
A10: OPERASI | K10: ACTIVITIES
A11: Penerimaan Kas dari Pelanggan | D11: 4,5,20 | F11: ='CF 2024'!B11 -> 150996874613 | H11: =ROUND('CF 2023'!B11,0) -> 218713811464 | K11: Cash Receipts from Customers
A13: Pembayaran Kepada Pemasok | D13: 6,7,10,11,13,15 | F13: ='CF 2024'!B12 -> -181964095253 | H13: =ROUND('CF 2023'!B12,0) -> -248400274278 | K13: Cash Paid to Supplier
A14: Pembayaran Kepada Karyawan | D14: 21.23 | F14: ='CF 2024'!B13 -> -5127549818 | H14: ='CF 2023'!B13 -> -5127549818 | K14: Cash Paid to Employees
A16: Pembayaran Beban Operasional Lainnya | D16: 15,17,22,23 | F16: ='CF 2024'!B14 -> -15194741148 | H16: =ROUNDDOWN('CF 2023'!B14,0)+1 -> -11291352070 | K16: Cash Paid for Other Operating Expenses
A17: Pembayaran Kepada Karyawan | F17: 0 | H17: 0 | K17: Payment to Employees
A18: Pembayaran Beban Lainnya
A20: Kas Dihasilkan dari Operasi | F20: =SUM(F11:F18) -> -51289511606 | H20: =SUM(H11:H18) -> -46105364702 | K20: Cash Generated from Operating
A21: Penerimaan bunga | D21: 22 | K21: Interest Received
A22: Pembayaran Pajak Penghasilan | D22: 15 | F22: ='CF 2024'!B20 -> -1135531100 | H22: =ROUND('CF 2023'!B20,0) -> -673327820 | K22: Cash Paid for Income Taxes Paid
A24: Pembayaran Beban Bunga dan Keuangan | D24: 25 | F24: ='CF 2024'!B19 -> -9424292095 | H24: =ROUND('CF 2023'!B19,0) -> -9352380745 | K24: Payment of Interest and Finance Costs
A28: Kas Bersih Digunakan untuk | K28: Net Cash Used in
A29: Aktivitas Operasi | F29: =SUM(F20:F24) -> -61849334801 | H29: =SUM(H20:H24) -> -56131073267 | K29: Operating Expenses
A32: ARUS KAS DARI AKTIVITAS
A33: INVESTASI | K33: CASH FLOWS FROM INVESTING
A34: Hasil Penjualan Aset Tetap
A35: Penempatan Invetasi pada Entitas Asosiasi | D35: 9 | F35: ='CF 2024'!B28 -> 0 | H35: ='CF 2023'!B28 -> -1050000000 | K35: Placement of Investment in Association Entities
A36: Aset Tetap | D36: 8 | F36: 0 | H36: 0 | K36: Property, Plant and Equipment
K37: Acquisition of Property, Plant
A38: Penambahan Aset Tetap | D38: 10 | F38: ='CF 2024'!B27 -> 0 | H38: ='CF 2023'!B27 -> 0 | K38: Acquisition of Fixed Assets
A39: Perolehan Aset Hak Guna
A42: Kas Bersih Digunakan untuk | K42: Net Cash Used for Obtained from
A43: dari Aktivitas Investasi | F43: =SUM(F34:F39) -> 0 | H43: =SUM(H34:H39) -> -1050000000 | K43: Investment Activities
A46: ARUS KAS DARI AKTIVITAS
A47: PENDANAAN | K47: CASH FLOWS FROM FINANCING
A48: Utang Bank | K48: Bank Loan
A49: Penerimaan | D49: 16 | F49: ='CF 2024'!B36 -> -9156032995 | H49: 366674261027 | K49: Proceeds
A50: Pembayaran | D50: 16 | F50: ='CF 2024'!B37 -> 0 | H50: -310030333899 | K50: Payments
A51: Utang Pembelian Aset Tetap | K51: Liabilities for Purchase of Fixed Asset
B52: Pembayaran | D52: 14 | F52: ='CF 2024'!B39 -> -76360023 | H52: ='CF 2023'!B39 -> -67475296 | K52: Payments
A53: Modal Disetor dari Penawaran Umum | K53: Paid-Up Capital from Initial
A54: Perdana Saham | F54: ='CF 2024'!B43 -> 14500000000 | H54: 0 | K54: Public Offering of Share
A55: Agio Saham atas Penawaran Umum | K55: Premium on Capital Stock Initial
A56: Saham Perdana | F56: ='CF 2024'!B44 -> 58000000000 | H56: 0 | K56: Public Offering
A57: Biaya Emisi atas Penawaran Umum | K57: Emission Costs for Initial
A58: Saham Perdana | F58: ='CF 2024'!B45 -> -3115944915 | H58: 0 | K58: Public Offering of Shares
A59: Utang Lain-Lain Kepada Pihak Berelasi | K59: Other Payable from Related Parties
B60: Penerimaan | F60: 0 | H60: 0 | L60: Proceed
B61: Pembayaran | D61: 12 | F61: ='CF 2024'!B47 -> -41000000 | H61: ='CF 2023'!B42 -> -317595000 | L61: Payments
A65: Kas Bersih Diperoleh dari | K65: Net Cash Provided by
A66: Aktivitas Pendanaan | F66: =SUM(F49:F63) -> 60110662067 | H66: =SUM(H49:H63) -> 56258856832 | K66: Financing Activities
A69: PENURUNAN BERSIH KAS | K69: NET DECREASE IN CASH ON HAND
A70: DAN BANK | F70: =F66+F43+F29 -> -1738672734 | H70: =H66+H43+H29 -> -922216435 | K70: AND CASH IN BANKS
A72: SALDO KAS DAN BANK | K72: CASH ON HAND AND IN BANKS
A74: AWAL TAHUN | F74: =H78 -> 2.159355e+09 | H74: =WS!AJ43 -> 3.0815714e+09 | K74: AT BEGINNING OF YEAR
A76: SALDO KAS DAN BANK | K76: CASH ON HAND AND IN BANK
A78: AKHIR TAHUN | F78: =F70+F74 -> 4.2068222e+08 | H78: =H70+H74 -> 2.159355e+09 | K78: AT END OF YEAR
C81: CONTROL | F81: =BS!H14 -> 4.2068222e+08 | H81: =BS!L14 -> 2159354956
C82: DIFF | F82: =F78-F81 -> -0.0099879503 | H82: =H78-H81 -> -0.30000019

Sheet CF 2024
C1: =SUM(C7:L7) -> 3.0114393e+11 | F1: 153903160236
C2: =SUM(N7:AD7) -> -3.0114393e+11
C3: =C1+C2 -> -0.0054931641
C4: Kas dan Bank | D4: Piutang Usaha Kepada Pihak Ketiga | E4: Piutang Usaha Kepada Pihak Berelasi | F4: Piutang Lain-Lain | G4: Persediaan | H4: Prepaid Tax | I4: Prepaid | J4: Investasi pada Entitas Asosias | K4: Aset Tetap | L4: Aset Pajak Tangguhan | M4: Biaya Pra IPO | N4: Short Term Bank Loans | O4: Bank Loan - Short part of long | P4: Utang Usaha Pihak Berelasi | Q4: Utang Usaha Pihak Ketiga | R4: Biaya Yang Masih Harus Dibayar | S4: Utang Lain2 Pihak Ketiga | T4: Utang Lembaga Pembiayaan | U4: Utang Bank & Leasing | V4: Utang Pajak | W4: Imbalan Pasca Kerja | X4: Modal Saham | Y4: Tambahan Modal Disetor | Z4: Masyarakat Saham Baru | AA4: Agio Saham | AB4: Biaya Emisi | AC4: Penghasilan Komprehensif Lainnya | AD4: Saldo Laba | AE4: Pendapatan Usaha | AF4: Beban Pokok Pendapatan Usaha | AG4: Beban Penjualan | AH4: Beban Umum dan Administrasi | AI4: Beban(Pendapatan) Lain-lain | AJ4: Beban Bunga dan Keuangan | AK4: Income Tax | AL4: Income Tax | AM4: Other Comprehensive Income | AN4: 17999087818 | AO4: =AN4-AN6 -> 1.7999088e+10
B6: December 31, 2024 | C6: =BS!H14 -> 4.2068222e+08 | D6: =BS!H17 -> 4.4619752e+10 | E6: =BS!H16 -> 8079657361 | F6: =BS!H18 -> 91174796671 | G6: =BS!H19 -> 117254789147 | H6: =BS!H20 -> 8.3889488e+09 | I6: =BS!H21 -> 2.9458466e+10 | J6: =BS!H34 -> 1050000000 | K6: =BS!H33 -> 2.5023283e+10 | L6: =BS!H35 -> 2.4256979e+08 | M6: 0 | N6: =-BS!H53 -> -126612232871 | O6: 0 | P6: =-BS!H48 -> -3.3114818e+10 | Q6: =-(BS!H49+BS!H51) -> -4.2917358e+09 | R6: =-BS!H54 -> -1.5639524e+09 | S6: =-BS!H52 -> 0 | T6: =-BS!H59 -> 0 | U6: 0 | V6: =-BS!H55 -> -7.3139746e+08 | W6: =-BS!H70 -> -2647745936 | X6: =-BS!H86+(WS!J310) -> -55000000000 | Y6: =Y7 -> -25871690669 | Z6: =-WS!J310 -> -14500000000 | AA6: =-WS!J312 -> -58000000000 | AB6: =-WS!J313 -> 3115944915 | AC6: =-BS!H89 -> 4.8278619e+08 | AD6: =AD7+WS!D316 -> -5.0374432e+09 | AE6: =-PL!F10 -> -1.8249335e+11 | AF6: =-PL!F11 -> 1.3938487e+11 | AG6: =-PL!F14 -> 1.4110744e+10 | AH6: =-PL!F15 -> 1.4884752e+10 | AI6: =-PL!F16 -> 1.612506e+09 | AJ6: =-PL!F17 -> 9.4242921e+09 | AK6: =-PL!F24 -> 0 | AL6: =-PL!F23 -> 1135531100 | AM6: 0 | AN6: =SUM(C6:AM6) -> 0.48443413
B7: 45291 | C7: =BS!L14 -> 2159354956 | D7: =BS!L17 -> 13123277095 | E7: =BS!L16 -> 8079657361 | F7: =BS!L18 -> 133158984576 | G7: =BS!L19 -> 108322822660 | H7: =BS!L20 -> 6807425746 | I7: =BS!L21 -> 897473228 | J7: =BS!L34 -> 1050000000 | K7: =BS!L33 -> 27302363571 | L7: =BS!L35 -> 2.4256979e+08 | M7: 0 | N7: =-BS!L53 -> -135768265866 | O7: 0 | P7: =-BS!L48 -> -62518053072 | Q7: =-(BS!L49+BS!L51) -> -12029137713 | R7: =-BS!L54 -> -937337041 | S7: =-BS!L52 -> -41000000 | T7: =-BS!L59 -> -76360023 | U7: 0 | V7: =-BS!L55 -> -1.6996817e+09 | W7: =-BS!L70 -> -2647745936 | X7: =-BS!L86 -> -40000000000 | Y7: =-BS!L87 -> -25871690669 | AC7: =-BS!L89 -> 4.8278619e+08 | AD7: =-(BS!L92+BS!L93+BS!L91) -> -2.0037443e+10 | AN7: =SUM(C7:AM7) -> -0.0054931641 | AO7: =AN7/2 -> -0.002746582
B8: Selisih | C8: =C6-C7 -> -1.7386727e+09 | D8: =D6-D7 -> 3.1496475e+10 | E8: =E6-E7 -> 0 | F8: =F6-F7 -> -41984187905 | G8: =G6-G7 -> 8931966487 | H8: =H6-H7 -> 1.5815231e+09 | I8: =I6-I7 -> 2.8560992e+10 | J8: =J6-J7 -> 0 | ... AM8: =AM6-AM7 -> 0 | AN8: =SUM(C8:AM8) -> 0.48998833 | AO8: =AN8/2 -> 0.24499416 | AP8: =AO8/2 -> 0.12249708
B9: Movement
A10: ARUS KAS DARI AKTIVITAS OPERASI
A11: Penerimaan Kas dari Pelanggan | B11: =ROUND(SUM(D11:AM11),0) -> 150996874613 | D11: =-D8 -> -3.1496475e+10 | E11: =-E8 -> 0 | AE11: =-AE8 -> 1.8249335e+11
A12: Pembayaran Kepada Pemasok | B12: =ROUND(SUM(D12:AM12),0) -> -181964095253 | F12: =-F8 -> 41984187905 | G12: =-G8 -> -8931966487 | H12: =-H8 -> -1.5815231e+09 | I12: =-I8 -> -2.8560992e+10 | K12: =-K8-K27 -> 2.2790807e+09 | M12: =-M8 -> 0 | P12: =-P8 -> -2.9403235e+10 | Q12: =-Q8 -> -7.737402e+09 | R12: =-R8 -> 6.2661534e+08 | AC12: =-AC8-AC28 -> 0 | AF12: =-AF8-AF13 -> -1.391434e+11 | AH12: =-AH8-AH13-AH14 -> -9.8829513e+09 | AI12: =-(AI8+AI14+AI19) -> -1.612506e+09 | AK12: =-(AK8-AL16) -> 0 | AM12: =-AM20-AM8 -> 0
A13: Pembayaran Kepada Karyawan | B13: =SUM(D13:AM13) -> -5127549818 | AF13: -241462283 | AH13: -4886087535
A14: Pembayaran Beban Operasional Lainnya | B14: =ROUND(SUM(D14:AM14),0) -> -15194741148 | L14: =-L8 -> 0 | V14: =-V8 -> -9.6828422e+08 | W14: =-W8 -> 0 | AG14: =-AG8 -> -1.4110744e+10 | AH14: -115712938
A15: Penerimaan Bunga | B15: =SUM(D15:AM15) -> 0
A16: Deferred tax | B16: =SUM(D16:AM16) -> 0 | AM16: 0
A17: Employee benefit | B17: =SUM(D17:AM17) -> 0
A18: Pembayaran Deviden | B18: =SUM(D18:AM18) -> 0
A19: Pembayaran Bunga | B19: =ROUND(SUM(D19:AM19),0) -> -9424292095 | AJ19: =-AJ8 -> -9.4242921e+09
A20: Pembayaran Pajak Penghasilan | B20: =SUM(D20:AM20) -> -1135531100 | AL20: =-AL8 -> -1135531100
A21: Kas diperoleh dari (digunakan untuk) operasi | B21: =SUM(B11:B20) -> -61849334801
A24: Kas Bersih Diperoleh dari Aktivitas Operasi
A26: ARUS KAS DARI AKTIVITAS INVESTASI
A27: Penambahan Aset Tetap | B27: =SUM(D27:AM27) -> 0
A28: Penempatan Investasi pada Ventura Bersama | B28: =SUM(D28:AM28) -> 0 | J28: =-J8 -> 0
A29: Penambahan Aset Tersedia untuk dijual | B29: =SUM(D29:AM29) -> 0
A30: Penambahan PI | B30: =SUM(D30:AM30) -> 0
A31: Penerimaan Piutang lain-lain dari Pihak Berelasi | B31: =SUM(D31:AM31) -> 0
A32: Pinjaman kepada Entitas Berelasi | B32: =SUM(D32:AM32) -> 0
A33: Kas Bersih Diperoleh dari (Digunakan untuk) Aktivitas Investasi | B33: =SUM(B27:B32) -> 0
A35: ARUS KAS DARI AKTIVITAS PENDANAAN
A36: Penerimaan Pinjaman dari Bank | B36: =SUM(D36:AM36) -> -9156032995 | N36: =-N8 -> -9156032995 | O36: =-O8 -> 0
A37: Pembayaran Pinjaman Bank | B37: =SUM(D37:AM37) -> 0 | U37: =-U8 -> 0
A38: Pinjaman kepada Koperasi | B38: =SUM(D38:AM38) -> 0
A39: Lembaga Pembiayaan | B39: =SUM(D39:AM39) -> -76360023 | T39: =-T8 -> -76360023
A40: Setoran Laba | B40: =SUM(D40:AM40) -> 0 | X40: =-X8 -> 15000000000 | AD40: =-AD8 -> -15000000000
A41: pembayaran Deviden | B41: =SUM(D41:AM41) -> 0
A42: Pembayaran Pembelian Aset Tetap | B42: =SUM(D42:AM42) -> 0
A43: Modal Disetor dari Penawaran Umum Perdana Saham | B43: =SUM(D43:AM43) -> 14500000000 | Z43: =-Z8 -> 14500000000
A44: Agio Saham atas Penawaran Umum Perdana Saham | B44: =SUM(D44:AM44) -> 58000000000 | AA44: =-AA8 -> 58000000000
A45: Biaya Emisi atas Penawaran Umum Perdana Saham | B45: =SUM(D45:AM45) -> -3115944915 | AB45: =-AB8 -> -3115944915
A46: Penerimaan dari Pemegang Saham | B46: =SUM(D46:AM46) -> 0
A47: Penerimaan dari Pemegang Saham | B47: =SUM(D47:AM47) -> -41000000 | S47: =-S8 -> -41000000
A48: Kas Bersih Diperoleh dari Aktivitas Pendanaan | B48: =SUM(B36:B47) -> 60110662067
A50: Dampak Kenaikan Selisih Kurs
A53: Kenaikan Bersih Kas & Bank | B53: =B48+B33+B21 -> -1738672734
A55: Saldo Bank Awal Tahun | B55: =C7 -> 2159354956
A57: Saldo Bank Akhir Tahun | B57: =B53+B55 -> 420682222
C58: =SUM(C8:C57) -> -1.7386727e+09 | D58: =SUM(D8:D57) -> 0 | E58: =SUM(E8:E57) -> 0 | F58: =SUM(F8:F57) -> 0 | G58: =SUM(G8:G57) -> 0 | H58: =SUM(H8:H57) -> 0 | I58: =SUM(I8:I57) -> 0 | K58: =SUM(K8:K57) -> 0 | L58: =SUM(L8:L57) -> 0 | M58: =SUM(M8:M57) -> 0 | N58: =SUM(N8:N57) -> 0 | P58: =SUM(P8:P57) -> 0 | Q58: =SUM(Q8:Q57) -> 0 | R58: =SUM(R8:R57) -> 0 | S58: =SUM(S8:S57) -> 0 | T58: =SUM(T8:T57) -> 0 | U58: =SUM(U8:U57) -> 0 | V58: =SUM(V8:V57) -> 0 | W58: =SUM(W8:W57) -> 0 | ... Y58: =SUM(Y8:Y57) -> 0 | AC58: =SUM(AC8:AC57) -> 0 | AD58: =SUM(AD8:AD57) -> 0 | AE58: =SUM(AE8:AE57) -> 0 | AF58: =SUM(AF8:AF57) -> 0 | AH58: =SUM(AH8:AH57) -> 0 | AI58: =SUM(AI8:AI57) -> 0 | AK58: =SUM(AK8:AK57) -> 0 | AL58: =SUM(AL8:AL57) -> 0 | AM58: =SUM(AM8:AM57) -> 0 | AN58: =SUM(D58:AM58) -> 0
B61: =ROUND(C6,0) -> 420682222
A62: CONTROL | B62: =B61-B57 -> 0

Sheet CF 2023
B1: 1.7661193e+11 | C1: =SUM(C7:L7) -> 1.7661193e+11 | F1: 153903160236
A2: =C3/2 -> 0 | C2: =SUM(N7:AA7) -> -1.7661193e+11
C3: =C1+C2 -> 0
C4: Kas dan Bank | D4: Piutang Usaha Kepada Pihak Ketiga | E4: Piutang Usaha Kepada Pihak Berelasi | F4: Piutang Lain-Lain | G4: Persediaan | H4: Prepaid Tax | I4: Prepaid | J4: Investasi pada Entitas Asosias | K4: Aset Tetap | L4: Aset Pajak Tangguhan | M4: Biaya Pra IPO | N4: Short Term Bank Loans | O4: Bank Loan - Short part of long | P4: Utang Usaha Pihak Berelasi | Q4: Utang Usaha Pihak Ketiga | R4: Biaya Yang Masih Harus Dibayar | S4: Utang Lain2 Pihak Ketiga | T4: Utang Lembaga Pembiayaan | U4: Utang Bank & Leasing | V4: Utang Pajak | W4: Imbalan Pasca Kerja | X4: Modal Saham | Y4: Tambahan Modal Disetor | Z4: Penghasilan Komprehensif Lainnya | AA4: Saldo Laba | AB4: Pendapatan Usaha | AC4: Beban Pokok Pendapatan Usaha | AD4: Beban Penjualan | AE4: Beban Umum dan Administrasi | AF4: Beban(Pendapatan) Lain-lain | AG4: Beban Bunga dan Keuangan | AH4: Income Tax | AI4: Income Tax | AJ4: Other Comprehensive Income | AK4: 17999087818 | AL4: =AK4-AK6 -> 1.7999088e+10
B6: December 31, 2023 | C6: =BS!L14 -> 2159354956 | D6: =BS!L17 -> 13123277095 | E6: =BS!L16 -> 8079657361 | F6: =BS!L18 -> 133158984576 | G6: =BS!L19 -> 108322822660 | H6: =BS!L20 -> 6807425746 | I6: =BS!L21 -> 897473228 | J6: =BS!L34 -> 1050000000 | K6: =BS!L33 -> 27302363571 | L6: =BS!L35 -> 2.4256979e+08 | M6: 0 | N6: =-BS!L53 -> -135768265866 | O6: 0 | P6: =-BS!L48 -> -62518053072 | Q6: =-(BS!L49+BS!L51) -> -12029137713 | R6: =-BS!L54 -> -937337041 | S6: =-BS!L52 -> -41000000 | T6: =-BS!L59 -> -76360023 | U6: 0 | V6: =-BS!L55 -> -1.6996817e+09 | W6: =-BS!L70 -> -2647745936 | X6: =-BS!L86 -> -40000000000 | Y6: =-BS!L87 -> -25871690669 | Z6: =-BS!L89 -> 4.8278619e+08 | AA6: =AA7 -> -1.8637503e+10 | AB6: =-PL!L10 -> -189007036121 | AC6: =-PL!L11 -> 156516490239 | AD6: =-PL!L14 -> 11943842250 | AE6: =-PL!L15 -> 8581798722 | AF6: =-PL!L16 -> 601084731 | AG6: =-PL!L17 -> 9.3523807e+09 | AH6: =-PL!L24 -> -61828681 | AI6: =-PL!L23 -> 6.7332782e+08 | AJ6: 0 | AK6: =SUM(C6:AJ6) -> -0.0055334568
B7: 44926 | C7: 3.0815714e+09 | D7: 3.4091895e+10 | E7: 1.6817814e+10 | F7: 2.0159403e+10 | G7: 6.7167128e+10 | H7: 5344754001 | I7: 137236872 | J7: 0 | K7: 2.9632564e+10 | L7: 1.7955771e+08 | M7: 0 | N7: -72317072070 | O7: -3403633332 | P7: -2552178138 | Q7: -4.7552577e+09 | R7: -2.1309058e+09 | S7: -358595000 | T7: -143835319 | U7: -3403633336 | V7: -1.1534289e+09 | W7: -2362783525 | X7: -40000000000 | Y7: -25871690669 | Z7: 4.7859051e+08 | AA7: -1.8637503e+10 | AK7: =SUM(C7:AJ7) -> 0 | AL7: =AK7/2 -> 0
B8: Selisih | C8: =C6-C7 -> -9.2221644e+08 | D8: =D6-D7 -> -2.0968618e+10 | E8: =E6-E7 -> -8.738157e+09 | F8: =F6-F7 -> 1.1299958e+11 | G8: =G6-G7 -> 4.1155694e+10 | H8: =H6-H7 -> 1462671745 | I8: =I6-I7 -> 760236356 | J8: =J6-J7 -> 1050000000 | ... AJ8: =AJ6-AJ7 -> 0 | AK8: =SUM(C8:AJ8) -> -0.0055639744 | AL8: =AK8/2 -> -0.0027819872 | AM8: =AL8/2 -> -0.0013909936
B9: Movement
A10: ARUS KAS DARI AKTIVITAS OPERASI
A11: Penerimaan Kas dari Pelanggan | B11: =SUM(D11:AJ11) -> 2.1871381e+11 | D11: =-D8 -> 2.0968618e+10 | E11: =-E8 -> 8.738157e+09 | AB11: =-AB8 -> 189007036121
A12: Pembayaran Kepada Pemasok | B12: =SUM(D12:AJ12) -> -2.4840027e+11 | F12: =-F8 -> -1.1299958e+11 | G12: =-G8 -> -4.1155694e+10 | H12: =-H8 -> -1462671745 | I12: =-I8 -> -760236356 | K12: =-K8-K27 -> 2.3302009e+09 | M12: =-M8 -> 0 | P12: =-P8 -> 59965874934 | Q12: =-Q8 -> 7.27388e+09 | R12: =-R8 -> -1.1935688e+09 | Z12: =-Z8-Z28 -> -4195684.7 | AC12: =-AC8-AC13 -> -156275027956 | AE12: =-AE8-AE13-AE14 -> -3579998249 | AF12: =-(AF8+AF14+AF19) -> -601084731 | AH12: =-(AH8-AI16) -> 61828681 | AJ12: =-AJ20-AJ8 -> 0
A13: Pembayaran Kepada Karyawan | B13: =SUM(D13:AJ13) -> -5127549818 | AC13: -241462283 | AE13: -4886087535
A14: Pembayaran Beban Operasional Lainnya | B14: =SUM(D14:AJ14) -> -1.1291352e+10 | L14: =-L8 -> -63012079 | V14: =-V8 -> 5.4625278e+08 | W14: =-W8 -> 284962411 | AD14: =-AD8 -> -11943842250 | AE14: -115712938
A15: Penerimaan Bunga | B15: =SUM(D15:AJ15) -> 0
A16: Deferred tax | B16: =SUM(D16:AJ16) -> 0 | AJ16: 0
A17: Employee benefit | B17: =SUM(D17:AJ17) -> 0
A18: Pembayaran Deviden | B18: =SUM(D18:AJ18) -> 0 | X18: =-X8 -> 0
A19: Pembayaran Bunga | B19: =SUM(D19:AJ19) -> -9.3523807e+09 | AG19: =-AG8 -> -9.3523807e+09
A20: Pembayaran Pajak Penghasilan | B20: =SUM(D20:AJ20) -> -6.7332782e+08 | AI20: =-AI8 -> -6.7332782e+08 | AK20: 613433271
A21: Kas diperoleh dari (digunakan untuk) operasi | B21: =SUM(B11:B20) -> -5.6131073e+10
A24: Kas Bersih Diperoleh dari Aktivitas Operasi
A26: ARUS KAS DARI AKTIVITAS INVESTASI
A27: Penambahan Aset Tetap | B27: =SUM(D27:AJ27) -> 0 | AA27: =-AA8 -> 0
A28: Penempatan Investasi pada Ventura Bersama | B28: =SUM(D28:AJ28) -> -1050000000 | J28: =-J8 -> -1050000000
A29: Penambahan Aset Tersedia untuk dijual | B29: =SUM(D29:AJ29) -> 0
A30: Penambahan PI | B30: =SUM(D30:AJ30) -> 0
A31: Penerimaan Piutang lain-lain dari Pihak Berelasi | B31: =SUM(D31:AJ31) -> 0
A32: Pinjaman kepada Entitas Berelasi | B32: =SUM(D32:AJ32) -> 0
A33: Kas Bersih Diperoleh dari (Digunakan untuk) Aktivitas Investasi | B33: =SUM(B27:B32) -> -1050000000
A35: ARUS KAS DARI AKTIVITAS PENDANAAN
A36: Penerimaan Pinjaman dari Bank | B36: =SUM(D36:AJ36) -> 60047560464 | N36: =-N8 -> 63451193796 | O36: =-O8 -> -3403633332
A37: Pembayaran Pinjaman Bank | B37: =SUM(D37:AJ37) -> -3403633336 | U37: =-U8 -> -3403633336
A38: Pinjaman kepada Koperasi | B38: =SUM(D38:AJ38) -> 0
A39: Lembaga Pembiayaan | B39: =SUM(D39:AJ39) -> -67475296 | T39: =-T8 -> -67475296
A40: pembayaran Deviden | B40: =SUM(D40:AJ40) -> 0
A41: Pembayaran Pembelian Aset Tetap | B41: =SUM(D41:AJ41) -> 0
A42: Penerimaan dari Pemegang Saham | B42: =SUM(D42:AJ42) -> -317595000 | S42: =-S8 -> -317595000
A43: Kas Bersih Diperoleh dari Aktivitas Pendanaan | B43: =SUM(B36:B42) -> 56258856832
A45: Dampak Kenaikan Selisih Kurs
A48: Kenaikan Bersih Kas & Bank | B48: =B43+B33+B21 -> -9.2221644e+08
A50: Saldo Bank Awal Tahun | B50: =C7 -> 3.0815714e+09
A52: Saldo Bank Akhir Tahun | B52: =B48+B50 -> 2.159355e+09
C53: =SUM(C8:C52) -> -9.2221644e+08 | D53: =SUM(D8:D52) -> 0 | E53: =SUM(E8:E52) -> 0 | F53: =SUM(F8:F52) -> 0 | G53: =SUM(G8:G52) -> 0 | H53: =SUM(H8:H52) -> 0 | I53: =SUM(I8:I52) -> 0 | K53: =SUM(K8:K52) -> 0 | L53: =SUM(L8:L52) -> 0 | M53: =SUM(M8:M52) -> 0 | N53: =SUM(N8:N52) -> 0 | P53: =SUM(P8:P52) -> 0 | Q53: =SUM(Q8:Q52) -> 0 | R53: =SUM(R8:R52) -> 0 | S53: =SUM(S8:S52) -> 0 | T53: =SUM(T8:T52) -> 0 | U53: =SUM(U8:U52) -> 0 | V53: =SUM(V8:V52) -> 0 | W53: =SUM(W8:W52) -> 0 | ... AC53: =SUM(AC8:AC52) -> 0 | AE53: =SUM(AE8:AE52) -> 0 | AF53: =SUM(AF8:AF52) -> 0 | AH53: =SUM(AH8:AH52) -> 0 | AI53: =SUM(AI8:AI52) -> 0 | AJ53: =SUM(AJ8:AJ52) -> 0 | AK53: =SUM(D53:AJ53) -> 0
B56: =C6 -> 2159354956
A57: CONTROL | B57: =B56-B52 -> -0.0055112839

Sheet COGS
A2: COGS
S6: Ctrl
E7: 31 Desember 2024 / | G7: 30 September 2024 / | I7: 30 September 2023 / | K7: 31 Desember 2023 /
E8: December, 31 2024 | G8: September, 30 2024 | I8: September, 30 2023 | K8: December, 31 2023 | U8: 45627 | W8: 45536 | Y8: 45170 | AA8: 45261
C9: Beban Pokok Penjualan Udang | N9: Cost of Goods Sold Shrimp
C10: =WS!B341 -> Saldo Awal Udang | E10: =WS!J341 -> 88132546606 | G10: =WS!U341 -> 88132546606 | I10: =WS!AH341 -> 50061246940 | K10: =WS!W341 -> 50061246940 | N10: Beginning Balance | S10: Saldo Awal | U10: =E10-WS!W94 -> 0 | W10: =G10-WS!W94 -> 0 | Y10: =I10-WS!AJ94 -> 0 | AA10: =K10-WS!AJ94 -> 0
C11: ='AJE CAJE Sept 24'!D67 -> Pembelian Udang | E11: =WS!J342 -> 1.24514e+11 | G11: =WS!U342 -> 7.9684646e+10 | I11: =WS!AH342 -> 140612836909 | K11: =WS!W342 -> 170720757691 | N11: Purchase | U11: =WS!J342-E11 -> 0 | W11: =WS!U342-G11 -> 0 | Y11: =WS!AH342-I11 -> 0
C13: Barang Tersedia Untuk Dijual | E13: =SUM(E10:E11)-E14 -> 2.1264654e+11 | G13: =SUM(G10:G11)-G14 -> 1.5710798e+11 | I13: =SUM(I10:I11)-I14 -> 182710412926 | K13: =SUM(K10:K11)-K14 -> 214800452636 | N13: Goods Available for Sale
C14: Barang Tersedia Untuk Produksi (Breaded) | E14: =WS!J344 -> 0 | G14: =WS!U344 -> 1.0709215e+10 | I14: =WS!AH344 -> 7963670923 | K14: =WS!W344 -> 5981551995 | N14: Goods Available for Production (Breaded)
C16: Sub Jumlah | E16: =SUM(E13:E14) -> 2.1264654e+11 | G16: =SUM(G13:G14) -> 1.6781719e+11 | I16: =SUM(I13:I14) -> 190674083849 | K16: =SUM(K13:K14) -> 220782004631 | N16: Sub Total
C18: Persediaan Akhir Udang | E18: =WS!J346 -> -97064513093 | G18: =WS!U346 -> -1.0849051e+11 | I18: =WS!AH346 -> -87174436355 | K18: =WS!W346 -> -88132546606 | N18: Ending Inventory Shrimp | S18: Saldo Akhir | U18: =E18+WS!J94 -> 0 | W18: =G18+WS!U94 -> 0 | Y18: =I18+WS!AH94 -> 0 | AA18: =K18+WS!W94 -> 0
C20: Beban Produksi Udang | E20: =SUM(E16:E18) -> 1.1558203e+11 | G20: =SUM(G16:G18) -> 5.9326684e+10 | I20: =SUM(I16:I18) -> 103499647494 | K20: =SUM(K16:K18) -> 132649458025 | N20: Cost of Production Shrimp
C22: Tersedia untui dijual | E22: =WS!J348 -> 0 | G22: =WS!U348 -> -1.0709215e+10 | I22: =WS!AH348 -> -7963670923 | K22: =WS!W348 -> -5981551995 | N22: Available for Sale
C24: Total Beban Pokok Penjualan Udang | E24: =SUM(E20:E22) -> 1.1558203e+11 | G24: =SUM(G20:G22) -> 4.8617469e+10 | I24: =SUM(I20:I22) -> 95535976571 | K24: =SUM(K20:K22) -> 126667906030 | N24: Total Cost of Goods Sold Shrimp | U24: =E24-WS!J349 -> 0 | W24: =G24-WS!U349 -> 0 | Y24: =I24-WS!AH349 -> 0 | AA24: =K24-WS!W349 -> 0
C26: Beban Pokok Breaded | N26: COGS Breaded
C27: Saldo Awal | E27: =WS!J352 -> 3808188569 | G27: =WS!U352 -> 3808188569 | I27: =WS!AH352 -> 4118553810 | K27: =WS!W352 -> 4118553810 | N27: Beginning Balance | S27: Saldo Awal | U27: =E27-WS!W95 -> 0 | W27: =G27-WS!W95 -> 0 | Y27: =I27-WS!AJ95 -> 0
C28: Transfer dari Udang | E28: =WS!J353 -> 0 | G28: =WS!U353 -> 1.0709215e+10 | I28: =WS!AH353 -> 7963670923 | K28: =WS!W353 -> 5981551995 | N28: Transfer of Shrimp | U28: =WS!J353-E28 -> 0 | W28: =WS!U353-G28 -> 0 | Y28: =WS!AH353-I28 -> 0
C30: Barang Tersedia untuk dijual | E30: =SUM(E27:E28) -> 3808188569 | G30: =SUM(G27:G28) -> 1.4517404e+10 | I30: =SUM(I27:I28) -> 12082224733 | K30: =SUM(K27:K28) -> 10100105805 | N30: Goods Available for sale
C31: Persediaan Akhir Breaded | E31: =WS!J355 -> -3808188569 | G31: =WS!U355 -> -6.1299385e+09 | I31: =WS!AH355 -> -4720465278 | K31: =WS!W355 -> -3808188569 | N31: Ending Inventory Breaded
C33: Beban Produksi Pembelian Udang (Breaded) | E33: =SUM(E30:E31) -> 0 | G33: =SUM(G30:G31) -> 8.3874655e+09 | I33: =SUM(I30:I31) -> 7361759455 | K33: =SUM(K30:K31) -> 6291917236 | N33: Cost of Production Shrimp Purchase (Breaded) | U33: =E33-WS!J356 -> 0 | W33: =G33-WS!U356 -> 0 | Y33: =I33-WS!AH356 -> 0 | AA33: =K33-WS!W356 -> 0
C35: Bahan Pembantu | E35: =WS!J360+WS!J361 -> 9.3506526e+09 | G35: =WS!U360+WS!U361 -> 7.8853158e+09 | I35: =WS!AH360+WS!AH361 -> 10041531808 | K35: =WS!W360+WS!W361 -> 12507303567 | N35: Supplementary Materials
C37: Saldo Awal | N37: Beginning Balance
C38: Bahan Pembantu | E38: =WS!J367 -> 16305238543 | G38: =WS!U367 -> 16305238543 | I38: =WS!AH367 -> 12890764983 | K38: =WS!W367 -> 12890764983 | N38: Supplementary Materials | S38: Saldo Awal | U38: =E38-WS!W92 -> 0 | W38: =G38-WS!W92 -> 0 | Y38: =I38-WS!AJ92 -> -0.30999947
C39: Solar | E39: =WS!J368 -> 76848942 | G39: =WS!U368 -> 76848942 | I39: =WS!AH368 -> 96562754 | K39: =WS!W368 -> 96562754 | N39: Diesel Fuel | S39: Saldo Awal | U39: =E39-WS!W93 -> 0 | W39: =G39-WS!W93 -> 0 | Y39: =I39-WS!AJ93 -> 0
C41: Saldo Akhir | N41: Ending Balance
C42: Bahan Pembantu | E42: =-WS!J371 -> -16305238543 | G42: =-WS!U371 -> -2.0674774e+10 | I42: =-WS!AH371 -> -17383013044 | K42: =-WS!W371 -> -16305238543 | N42: Supplementary Materials | S42: Saldo Akhir | U42: =WS!J371+E42 -> 0 | W42: =WS!U371+G42 -> 0 | Y42: =WS!AH371+I42 -> 0
C43: Solar | E43: =-WS!J372 -> -76848942 | G43: =-WS!U372 -> -34860373 | I43: =-WS!AH372 -> -84387986 | K43: =-WS!W372 -> -76848942 | N43: Diesel Fuel | S43: Saldo Akhir | U43: =WS!J372+E43 -> 0 | W43: =WS!U372+G43 -> 0 | Y43: =WS!AH372+I43 -> 0
C45: Beban Pokok Bahan Pembantu | E45: =E35+SUM(E38:E39)+SUM(E42:E43) -> 9.3506526e+09 | G45: =G35+SUM(G38:G39)+SUM(G42:G43) -> 3.5577694e+09 | I45: =I35+SUM(I38:I39)+SUM(I42:I43) -> 5561458515 | K45: =K35+SUM(K38:K39)+SUM(K42:K43) -> 9112543819 | N45: Cost of Supplementary Materials | U45: =WS!J373-E45 -> 0 | W45: =WS!U373-G45 -> 0 | Y45: =I45-WS!AH373 -> 0
C47: Beban Langsung Biaya Tenaga Kerja Langsung | E47: =WS!J379+WS!J380+WS!#REF!+WS!J381+WS!J382+WS!J383+WS!J384+WS!J385+WS!J386+WS!J387 -> #REF! | G47: =WS!U379+WS!U380+WS!#REF!+WS!U381+WS!U382+WS!U383+WS!U384+WS!U385+WS!U386+WS!U387 -> #REF! | I47: =WS!AH379+WS!AH380+WS!#REF!+WS!AH381+WS!AH382+WS!AH383+WS!AH384+WS!AH385+WS!AH386+WS!AH387 -> #REF! | K47: =WS!W379+WS!W380+WS!#REF!+WS!W381+WS!W382+WS!W383+WS!W384+WS!W385+WS!W386+WS!W387 -> #REF! | N47: Cost of Supplementary Direct Labour Cost | U47: =E47-SUM(WS!J379:J387) -> #REF! | W47: =G47-SUM(WS!U379:U387) -> #REF! | Y47: =I47-SUM(WS!AH379:AH387) -> #REF! | AA47: =K47-SUM(WS!W379:W387) -> #REF!
C49: Biaya Overhead Pabrik | N49: Direct Labor Cost
C50: Listrik | E50: =WS!J393 -> 3088453537 | G50: =WS!U393 -> 2153355677 | I50: =WS!AH393 -> 2300707763 | K50: =WS!W393 -> 3096554794 | N50: Electricity
C51: Penyusutan | E51: =WS!J390 -> 2.2689685e+09 | G51: =WS!U390 -> 1.622489e+09 | I51: =WS!AH390 -> 1696263520 | K51: =WS!W390 -> 2107125819 | N51: Depreciation
C52: Perlengkapan Sarana Produksi | E52: =WS!J395 -> 123006069 | G52: =WS!U395 -> 72898009 | I52: =WS!AH395 -> 134103819 | K52: =WS!W395 -> 154739169 | N52: Production Supplies
C53: Perbaikan Pemeliharaan Sarana Produksi | E53: =WS!J394 -> 64008793 | G53: =WS!U394 -> 31664255 | I53: =WS!AH394 -> 122076750 | K53: =WS!W394 -> 137666155 | N53: Repairs and Maintenance
C54: Lainnya | E54: =WS!J389+WS!J391+WS!J392+WS!J396 -> 112220707 | G54: =WS!U389+WS!U391+WS!U392+WS!U396 -> 84579248 | I54: =WS!AH389+WS!AH391+WS!AH392+WS!AH396 -> 22029794 | K54: =WS!W389+WS!W391+WS!W392+WS!W396 -> 50525457 | N54: Others
C56: Total Harga Pokok Produksi | E56: =SUM(E47:E54) -> #REF! | G56: =SUM(G47:G54) -> #REF! | I56: =SUM(I47:I54) -> #REF! | K56: =SUM(K47:K54) -> #REF! | N56: Total Cost of Goods Manufactured | U56: =E56-WS!J398 -> #REF! | W56: =G56-WS!U398 -> #REF! | Y56: =I56-WS!AH398 -> #REF! | AA56: =K56-WS!W398 -> #REF!
C58: Total Harga Pokok Penjualan | E58: =E24+E33+E45+E56 -> #REF! | G58: =G24+G33+G45+G56 -> #REF! | I58: =I24+I33+I45+I56 -> #REF! | K58: =K24+K33+K45+K56 -> #REF! | N58: Total Cost of Goods Sold
C61: Ctrl | E61: =WS!J399 -> 1.3938487e+11 | G61: =WS!U399 -> 7.0704787e+10 | I61: =WS!AH399 -> 119567172509 | K61: =WS!W399 -> 156516490239

Sheet Korfis IAS Des 24
F1: Lampiran II | N1: Lampiran II | V1: Lampiran II | AE1: Lampiran II | AM1: Lampiran II
A2: PT INDO AMERICAN SEAFOODS | I2: PT INDO AMERICAN SEAFOODS | Q2: PT INDO AMERICAN SEAFOODS | Z2: PT INDO AMERICAN SEAFOODS | AH2: PT INDO AMERICAN SEAFOODS
A3: Laporan Laba Rugi Fiskal | I3: Laporan Laba Rugi Fiskal | Q3: Laporan Laba Rugi Fiskal | Z3: Laporan Laba Rugi Fiskal | AH3: Laporan Laba Rugi Fiskal
A4: Untuk Tahun Yang Berakhir Pada 31 Desember 2024 | I4: Untuk Tahun Yang Berakhir Pada 30 September 2024 | Q4: Untuk Tahun Yang Berakhir Pada 30 September 2023 | Z4: Untuk Tahun Yang Berakhir Pada 30 Juni 2024 | AH4: Untuk Tahun Yang Berakhir Pada 30 Juni 2023
A5: (dalam Rupiah) | I5: (dalam Rupiah) | Q5: (dalam Rupiah) | Z5: (dalam Rupiah) | AH5: (dalam Rupiah)
A7: KETERANGAN | C7: KOMERSIAL | D7: KOREKSI FISKAL | F7: FISKAL | I7: KETERANGAN | K7: KOMERSIAL | L7: KOREKSI FISKAL | N7: FISKAL | Q7: KETERANGAN | S7: KOMERSIAL | T7: KOREKSI FISKAL | V7: FISKAL | Z7: KETERANGAN | AB7: KOMERSIAL | AC7: KOREKSI FISKAL | AE7: FISKAL | AH7: KETERANGAN | AJ7: KOMERSIAL | AK7: KOREKSI FISKAL | AM7: FISKAL
D8: POSITIF | E8: NEGATIF | L8: POSITIF | M8: NEGATIF | T8: POSITIF | U8: NEGATIF | AC8: POSITIF | AD8: NEGATIF | AK8: POSITIF | AL8: NEGATIF
A10: Pendapatan | I10: Pendapatan | Q10: Pendapatan | Z10: Pendapatan | AH10: Pendapatan
B11: Ekspor | C11: =WS!J332 -> 1.6593558e+11 | F11: =C11+D11-E11 -> 1.6593558e+11 | J11: Ekspor | K11: =WS!U332 -> 8.7688651e+10 | N11: =K11+L11-M11 -> 8.7688651e+10 | R11: Ekspor | S11: =WS!AH332 -> 134989855636 | V11: =S11+T11-U11 -> 134989855636 | AA11: Ekspor | AB11: =WS!#REF! -> #REF! | AE11: =AB11+AC11-AD11 -> #REF! | AI11: Ekspor | AJ11: =WS!#REF! -> #REF! | AM11: =AJ11+AK11-AL11 -> #REF!
B12: Lokal | C12: =WS!J335 -> 1.655777e+10 | F12: =C12+D12-E12 -> 1.655777e+10 | J12: Lokal | K12: =WS!U335 -> 1.2606433e+10 | N12: =K12+L12-M12 -> 1.2606433e+10 | R12: Lokal | S12: =WS!AH335 -> 10652081484 | V12: =S12+T12-U12 -> 10652081484 | AA12: Lokal | AB12: =WS!#REF! -> #REF! | AE12: =AB12+AC12-AD12 -> #REF! | AI12: Lokal | AJ12: =WS!#REF! -> #REF! | AM12: =AJ12+AK12-AL12 -> #REF!
A14: Harga Pokok Penjualan | I14: Harga Pokok Penjualan | Q14: Harga Pokok Penjualan | Z14: Harga Pokok Penjualan | AH14: Harga Pokok Penjualan
B15: HPP Udang | C15: =WS!J349 -> 1.1558203e+11 | E15: =C15*6.2%*0 -> 0 | F15: =C15-D15+E15 -> 1.1558203e+11 | J15: HPP Udang | K15: =WS!U349 -> 4.8617469e+10 | M15: =K15*6.2%*0 -> 0 | N15: =K15-L15+M15 -> 4.8617469e+10 | R15: HPP Udang | S15: =WS!AH349 -> 95535976571 | U15: =S15*6.2%*0 -> 0 | V15: =S15-T15+U15 -> 95535976571 | AA15: HPP Udang | AB15: =WS!#REF! -> #REF! | AD15: =AB15*6.2%*0 -> #REF! | AE15: =AB15-AC15+AD15 -> #REF! | AI15: HPP Udang | AJ15: =WS!#REF! -> #REF! | AL15: =AJ15*6.2%*0 -> #REF! | AM15: =AJ15-AK15+AL15 -> #REF!
B16: HPP Breaded | C16: =WS!J356 -> 0 | F16: =C16-D16+E16 -> 0 | J16: HPP Breaded | K16: =WS!U356 -> 8.3874655e+09 | N16: =K16-L16+M16 -> 8.3874655e+09 | R16: HPP Breaded | S16: =WS!AH356 -> 7361759455 | V16: =S16-T16+U16 -> 7361759455 | AA16: HPP Breaded | AB16: =WS!#REF! -> #REF! | AE16: =AB16-AC16+AD16 -> #REF! | AI16: HPP Breaded | AJ16: =WS!#REF! -> #REF! | AM16: =AJ16-AK16+AL16 -> #REF!
B17: HPP Bahan Pembantu | C17: =WS!J373 -> 9.3506526e+09 | F17: =C17-D17+E17 -> 9.3506526e+09 | J17: HPP Bahan Pembantu | K17: =WS!U373 -> 3.5577694e+09 | N17: =K17-L17+M17 -> 3.5577694e+09 | R17: HPP Bahan Pembantu | S17: =WS!AH373 -> 5561458515 | V17: =S17-T17+U17 -> 5561458515 | AA17: HPP Bahan Pembantu | AB17: =WS!#REF! -> #REF! | AE17: =AB17-AC17+AD17 -> #REF! | AI17: HPP Bahan Pembantu | AJ17: =WS!#REF! -> #REF! | AM17: =AJ17-AK17+AL17 -> #REF!
B18: HPP Produksi | C18: =WS!J398-C19 -> 12183215883 | F18: =C18-D18+E18 -> 12183215883 | J18: HPP Produksi | K18: =WS!U398-K19 -> 8.5195941e+09 | N18: =K18-L18+M18 -> 8.5195941e+09 | R18: HPP Produksi | S18: =WS!AH398-S19 -> 9411714448 | V18: =S18-T18+U18 -> 9411714448 | AA18: HPP Produksi | AB18: =WS!#REF!-AB19 -> #REF! | AE18: =AB18-AC18+AD18 -> #REF! | AI18: HPP Produksi | AJ18: =WS!#REF!-AJ19 -> #REF! | AM18: =AJ18-AK18+AL18 -> #REF!
B19: Depreciation | C19: =WS!J390 -> 2.2689685e+09 | F19: =C19-D19+E19 -> 2.2689685e+09 | J19: Depreciation | K19: =WS!U390 -> 1.622489e+09 | N19: =K19-L19+M19 -> 1.622489e+09 | R19: Depreciation | S19: =WS!AH390 -> 1696263520 | U19: 88385951 | V19: =S19-T19+U19 -> 1.7846495e+09 | AA19: Depreciation | AB19: =WS!#REF! -> #REF! | AD19: 58923967 | AE19: =AB19-AC19+AD19 -> #REF! | AI19: Depreciation | AJ19: =WS!#REF! -> #REF! | AL19: 58923967 | AM19: =AJ19-AK19+AL19 -> #REF!
B21: Jumlah Harga Pokok Penjualan | C21: =SUM(C15:C19) -> 1.3938487e+11 | F21: =SUM(F15:F19) -> 1.3938487e+11 | J21: Jumlah Harga Pokok Penjualan | K21: =SUM(K15:K19) -> 7.0704787e+10 | N21: =SUM(N15:N19) -> 7.0704787e+10 | R21: Jumlah Harga Pokok Penjualan | S21: =SUM(S15:S19) -> 119567172509 | V21: =SUM(V15:V19) -> 1.1965556e+11 | AA21: Jumlah Harga Pokok Penjualan | AB21: =SUM(AB15:AB19) -> #REF! | AE21: =SUM(AE15:AE19) -> #REF! | AI21: Jumlah Harga Pokok Penjualan | AJ21: =SUM(AJ15:AJ19) -> #REF! | AM21: =SUM(AM15:AM19) -> #REF!
A23: Laba Kotor | C23: =(C11+C12)-C21 -> 4.3108484e+10 | F23: =(F11+F12)-F21 -> 4.3108484e+10 | I23: Laba Kotor | K23: =(K11+K12)-K21 -> 2.9590298e+10 | N23: =(N11+N12)-N21 -> 2.9590298e+10 | Q23: Laba Kotor | S23: =(S11+S12)-S21 -> 26074764611 | V23: =(V11+V12)-V21 -> 2.5986379e+10 | Z23: Laba Kotor | AB23: =(AB11+AB12)-AB21 -> #REF! | AE23: =(AE11+AE12)-AE21 -> #REF! | AH23: Laba Kotor | AJ23: =(AJ11+AJ12)-AJ21 -> #REF! | AM23: =(AM11+AM12)-AM21 -> #REF!
A25: Beban Penjualan | I25: Beban Penjualan | Q25: Beban Penjualan | Z25: Beban Penjualan | AH25: Beban Penjualan
B26: Pengiriman | C26: =WS!J403 -> 9.137801e+09 | D26: =C26*2%*0 -> 0 | F26: =C26-D26+E26 -> 9.137801e+09 | J26: Pengiriman | K26: =WS!U403 -> 7.3811238e+09 | L26: =K26*2%*0 -> 0 | N26: =K26-L26+M26 -> 7.3811238e+09 | R26: Pengiriman | S26: =WS!AH403 -> 10791530434 | T26: =S26*2%*0 -> 0 | V26: =S26-T26+U26 -> 10791530434 | AA26: Pengiriman | AB26: =WS!#REF! -> #REF! | AC26: =AB26*2%*0 -> #REF! | AE26: =AB26-AC26+AD26 -> #REF! | AI26: Pengiriman | AJ26: =WS!#REF! -> #REF! | AK26: =AJ26*2%*0 -> #REF! | AM26: =AJ26-AK26+AL26 -> #REF!
B27: Klaim | C27: =WS!J404 -> 130843300 | F27: =C27-D27+E27 -> 130843300 | J27: Klaim | K27: =WS!U404 -> 76968600 | N27: =K27-L27+M27 -> 76968600 | R27: Klaim | S27: =WS!AH404 -> 611722178 | V27: =S27-T27+U27 -> 611722178 | AA27: Klaim | AB27: =WS!#REF! -> #REF! | AE27: =AB27-AC27+AD27 -> #REF! | AI27: Klaim | AJ27: =WS!#REF! -> #REF! | AM27: =AJ27-AK27+AL27 -> #REF!
B28: Administrasi | C28: =WS!J405 -> 0 | F28: =C28-D28+E28 -> 0 | J28: Administrasi | K28: =WS!U405 -> 0 | N28: =K28-L28+M28 -> 0 | R28: Administrasi | S28: =WS!AH405 -> 0 | V28: =S28-T28+U28 -> 0 | AA28: Administrasi | AB28: =WS!#REF! -> #REF! | AE28: =AB28-AC28+AD28 -> #REF! | AI28: Administrasi | AJ28: =WS!#REF! -> #REF! | AM28: =AJ28-AK28+AL28 -> #REF!
B29: Analisis dan tes | C29: =WS!J406 -> 158102500 | F29: =C29-D29+E29 -> 158102500 | J29: Analisis dan tes | K29: =WS!U406 -> 118426500 | N29: =K29-L29+M29 -> 118426500 | R29: Analisis dan tes | S29: =WS!AH406 -> 148529000 | V29: =S29-T29+U29 -> 148529000 | AA29: Analisis dan tes | AB29: =WS!#REF! -> #REF! | AE29: =AB29-AC29+AD29 -> #REF! | AI29: Analisis dan tes | AJ29: =WS!#REF! -> #REF! | AM29: =AJ29-AK29+AL29 -> #REF!
B30: Keanggotaan | C30: =WS!J407 -> 325461602 | F30: =C30-D30+E30 -> 325461602 | J30: Keanggotaan | K30: =WS!U407 -> 275521602 | N30: =K30-L30+M30 -> 275521602 | R30: Keanggotaan | S30: =WS!AH407 -> 207767704 | V30: =S30-T30+U30 -> 207767704 | AA30: Keanggotaan | AB30: =WS!#REF! -> #REF! | AE30: =AB30-AC30+AD30 -> #REF! | AI30: Keanggotaan | AJ30: =WS!#REF! -> #REF! | AM30: =AJ30-AK30+AL30 -> #REF!
B31: Beban Bongkar Muat Eskpor | C31: =WS!J408 -> 22344010 | F31: =C31-D31+E31 -> 22344010 | J31: Beban Bongkar Muat Eskpor | K31: =WS!U408 -> 15164370 | N31: =K31-L31+M31 -> 15164370 | R31: Beban Bongkar Muat Eskpor | S31: =WS!AH408 -> 29878940 | V31: =S31-T31+U31 -> 29878940 | AA31: Beban Bongkar Muat Eskpor | AB31: =WS!#REF! -> #REF! | AE31: =AB31-AC31+AD31 -> #REF! | AI31: Beban Bongkar Muat Eskpor | AJ31: =WS!#REF! -> #REF! | AM31: =AJ31-AK31+AL31 -> #REF!
B32: Beban Dokumen Ekspor | C32: =WS!J409 -> 61172281 | F32: =C32-D32+E32 -> 61172281 | J32: Beban Dokumen Ekspor | K32: =WS!U409 -> 40627257 | N32: =K32-L32+M32 -> 40627257 | R32: Beban Dokumen Ekspor | S32: =WS!AH409 -> 91621530 | V32: =S32-T32+U32 -> 91621530 | AA32: Beban Dokumen Ekspor | AB32: =WS!#REF! -> #REF! | AE32: =AB32-AC32+AD32 -> #REF! | AI32: Beban Dokumen Ekspor | AJ32: =WS!#REF! -> #REF! | AM32: =AJ32-AK32+AL32 -> #REF!
B33: Beban EMKL | C33: =WS!J410 -> 3.9878929e+08 | F33: =C33-D33+E33 -> 3.9878929e+08 | J33: Beban EMKL | K33: =WS!U410 -> 3.2500388e+08 | N33: =K33-L33+M33 -> 3.2500388e+08 | R33: Beban EMKL | S33: =WS!AH410 -> 133097587 | V33: =S33-T33+U33 -> 133097587 | AA33: Beban EMKL | AB33: =WS!#REF! -> #REF! | AE33: =AB33-AC33+AD33 -> #REF! | AI33: Beban EMKL | AJ33: =WS!#REF! -> #REF! | AM33: =AJ33-AK33+AL33 -> #REF!
B34: Beban Komisi | C34: =WS!J411 -> 71339220 | F34: =C34-D34+E34 -> 71339220 | J34: Beban Komisi | K34: =WS!U411 -> 16228200 | N34: =K34-L34+M34 -> 16228200 | R34: Beban Komisi | S34: =WS!AH411 -> 40946661 | V34: =S34-T34+U34 -> 40946661 | AA34: Beban Komisi | AB34: =WS!#REF! -> #REF! | AE34: =AB34-AC34+AD34 -> #REF! | AI34: Beban Komisi | AJ34: =WS!#REF! -> #REF! | AM34: =AJ34-AK34+AL34 -> #REF!
B35: Beban Sample | C35: =WS!J412 -> 9095000 | F35: =C35-D35+E35 -> 9095000 | J35: Beban Sample | K35: =WS!U412 -> 7750000 | N35: =K35-L35+M35 -> 7750000 | R35: Beban Sample | S35: =WS!AH412 -> 6140000 | V35: =S35-T35+U35 -> 6140000 | AA35: Beban Sample | AB35: =WS!#REF! -> #REF! | AE35: =AB35-AC35+AD35 -> #REF! | AI35: Beban Sample | AJ35: =WS!#REF! -> #REF! | AM35: =AJ35-AK35+AL35 -> #REF!
B36: Surveyor | C36: =WS!J413 -> 12600000 | F36: =C36-D36+E36 -> 12600000 | J36: Surveyor | K36: =WS!U413 -> 6300000 | N36: =K36-L36+M36 -> 6300000 | R36: Surveyor | S36: =WS!AH413 -> 6450000 | V36: =S36-T36+U36 -> 6450000 | AA36: Surveyor | AB36: =WS!#REF! -> #REF! | AE36: =AB36-AC36+AD36 -> #REF! | AI36: Surveyor | AJ36: =WS!#REF! -> #REF! | AM36: =AJ36-AK36+AL36 -> #REF!
B37: Pameran | C37: =WS!J414 -> 63110969 | D37: =C37*2%*0 -> 0 | F37: =C37-D37+E37 -> 63110969 | J37: Pameran | K37: =WS!U414 -> 47749920 | L37: =K37*2%*0 -> 0 | N37: =K37-L37+M37 -> 47749920 | R37: Pameran | S37: =WS!AH414 -> 53050186 | T37: =S37*2%*0 -> 0 | V37: =S37-T37+U37 -> 53050186 | AA37: Pameran | AB37: =WS!#REF! -> #REF! | AC37: =AB37*2%*0 -> #REF! | AE37: =AB37-AC37+AD37 -> #REF! | AI37: Pameran | AJ37: =WS!#REF! -> #REF! | AK37: =AJ37*2%*0 -> #REF! | AM37: =AJ37-AK37+AL37 -> #REF!
B38: Beban Lain-lain | C38: 0 | F38: =C38-D38+E38 -> 0 | J38: Beban Lain-lain | K38: 0 | N38: =K38-L38+M38 -> 0 | R38: Beban Lain-lain | S38: 0 | V38: =S38-T38+U38 -> 0 | AA38: Beban Lain-lain | AB38: 0 | AE38: =AB38-AC38+AD38 -> 0 | AI38: Beban Lain-lain | AJ38: 0 | AM38: =AJ38-AK38+AL38 -> 0
B39: Duty | C39: =WS!J415 -> 3.7200848e+09 | F39: =C39-D39+E39 -> 3.7200848e+09 | J39: Duty | K39: =WS!U415 -> 1.0819326e+09 | N39: =K39-L39+M39 -> 1.0819326e+09
A40: Umum dan Administrasi | I40: Umum dan Administrasi | Q40: Umum dan Administrasi | Z40: Umum dan Administrasi | AH40: Umum dan Administrasi
A41: Gaji dan Tunjangan Karyawan | I41: Gaji dan Tunjangan Karyawan | Q41: Gaji dan Tunjangan Karyawan | Z41: Gaji dan Tunjangan Karyawan | AH41: Gaji dan Tunjangan Karyawan
B42: BPJS/ Jamsostek | C42: =WS!J419 -> 313949059 | F42: =C42-D42+E42 -> 313949059 | J42: BPJS/ Jamsostek | K42: =WS!U419 -> 270332060 | N42: =K42-L42+M42 -> 270332060 | R42: BPJS/ Jamsostek | S42: =WS!AH419 -> 255023239 | V42: =S42-T42+U42 -> 255023239 | AA42: BPJS/ Jamsostek | AB42: =WS!#REF! -> #REF! | AE42: =AB42-AC42+AD42 -> #REF! | AI42: BPJS/ Jamsostek | AJ42: =WS!#REF! -> #REF! | AM42: =AJ42-AK42+AL42 -> #REF!
B43: Gaji Karyawan Kantor | C43: =WS!J420 -> 3962378187 | F43: =C43-D43+E43 -> 3962378187 | J43: Gaji Karyawan Kantor | K43: =WS!U420 -> 2892243979 | N43: =K43-L43+M43 -> 2892243979 | R43: Gaji Karyawan Kantor | S43: =WS!AH420 -> 2965790410 | V43: =S43-T43+U43 -> 2965790410 | AA43: Gaji Karyawan Kantor | AB43: =WS!#REF! -> #REF! | AE43: =AB43-AC43+AD43 -> #REF! | AI43: Gaji Karyawan Kantor | AJ43: =WS!#REF! -> #REF! | AM43: =AJ43-AK43+AL43 -> #REF!
B44: Tunjangan Hari Raya | C44: =WS!J421 -> 332597853 | F44: =C44-D44+E44 -> 332597853 | J44: Tunjangan Hari Raya | K44: =WS!U421 -> 332597853 | N44: =K44-L44+M44 -> 332597853 | R44: Tunjangan Hari Raya | S44: =WS!AH421 -> 341934529 | V44: =S44-T44+U44 -> 341934529 | AA44: Tunjangan Hari Raya | AB44: =WS!#REF! -> #REF! | AE44: =AB44-AC44+AD44 -> #REF! | AI44: Tunjangan Hari Raya | AJ44: =WS!#REF! -> #REF! | AM44: =AJ44-AK44+AL44 -> #REF!
B45: Tunjangan Karyawan | C45: =WS!J422 -> 432045000 | F45: =C45-D45+E45 -> 432045000 | J45: Tunjangan Karyawan | K45: =WS!U422 -> 339109000 | N45: =K45-L45+M45 -> 339109000 | R45: Tunjangan Karyawan | S45: =WS!AH422 -> 287526000 | V45: =S45-T45+U45 -> 287526000 | AA45: Tunjangan Karyawan | AB45: =WS!#REF! -> #REF! | AE45: =AB45-AC45+AD45 -> #REF! | AI45: Tunjangan Karyawan | AJ45: =WS!#REF! -> #REF! | AM45: =AJ45-AK45+AL45 -> #REF!
B46: Pesangon | C46: =WS!J423 -> 0 | F46: =C46-D46+E46 -> 0 | J46: Pesangon | K46: =WS!U423 -> 0 | N46: =K46-L46+M46 -> 0 | R46: Pesangon | S46: =WS!AH423 -> 0 | V46: =S46-T46+U46 -> 0 | AA46: Pesangon | AB46: =WS!#REF! -> #REF! | AE46: =AB46-AC46+AD46 -> #REF! | AI46: Pesangon | AJ46: =WS!#REF! -> #REF! | AM46: =AJ46-AK46+AL46 -> #REF!
A48: Beban Administrasi Dan Umum | I48: Beban Administrasi Dan Umum | Q48: Beban Administrasi Dan Umum | Z48: Beban Administrasi Dan Umum | AH48: Beban Administrasi Dan Umum
B49: Administrasi & Umum Lainnya | C49: =WS!J425 -> 1343058 | D49: =C49 -> 1343058 | F49: =C49-D49+E49 -> 0 | J49: Administrasi & Umum Lainnya | K49: =WS!U425 -> 1293058 | L49: =K49 -> 1293058 | N49: =K49-L49+M49 -> 0 | R49: Administrasi & Umum Lainnya | S49: =WS!AH425 -> 25000 | T49: =S49 -> 25000 | V49: =S49-T49+U49 -> 0 | AA49: Administrasi & Umum Lainnya | AB49: =WS!#REF! -> #REF! | AC49: =AB49 -> #REF! | AE49: =AB49-AC49+AD49 -> #REF! | AI49: Administrasi & Umum Lainnya | AJ49: =WS!#REF! -> #REF! | AK49: =AJ49 -> #REF! | AM49: =AJ49-AK49+AL49 -> #REF!
B50: Alat Tulis Kantor | C50: =WS!J426 -> 20121300 | F50: =C50-D50+E50 -> 20121300 | J50: Alat Tulis Kantor | K50: =WS!U426 -> 16530500 | N50: =K50-L50+M50 -> 16530500 | R50: Alat Tulis Kantor | S50: =WS!AH426 -> 20495300 | V50: =S50-T50+U50 -> 20495300 | AA50: Alat Tulis Kantor | AB50: =WS!#REF! -> #REF! | AE50: =AB50-AC50+AD50 -> #REF! | AI50: Alat Tulis Kantor | AJ50: =WS!#REF! -> #REF! | AM50: =AJ50-AK50+AL50 -> #REF!
B51: Asuransi | C51: =WS!J427 -> 111024837 | F51: =C51-D51+E51 -> 111024837 | J51: Asuransi | K51: =WS!U427 -> 80745336 | N51: =K51-L51+M51 -> 80745336 | R51: Asuransi | S51: =WS!AH427 -> 110236455 | V51: =S51-T51+U51 -> 110236455 | AA51: Asuransi | AB51: =WS!#REF! -> #REF! | AE51: =AB51-AC51+AD51 -> #REF! | AI51: Asuransi | AJ51: =WS!#REF! -> #REF! | AM51: =AJ51-AK51+AL51 -> #REF!
B52: BBM Kendaraan Kantor | C52: =WS!J428 -> 144047264 | D52: =C52*50% -> 72023632 | F52: =C52-D52+E52 -> 72023632 | J52: BBM Kendaraan Kantor | K52: =WS!U428 -> 105481619 | L52: =K52*50% -> 52740810 | N52: =K52-L52+M52 -> 52740810 | R52: BBM Kendaraan Kantor | S52: =WS!AH428 -> 94549815 | T52: =S52*50%*0 -> 0 | V52: =S52-T52+U52 -> 94549815 | AA52: BBM Kendaraan Kantor | AB52: =WS!#REF! -> #REF! | AE52: =AB52-AC52+AD52 -> #REF! | AI52: BBM Kendaraan Kantor | AJ52: =WS!#REF! -> #REF! | AK52: =AJ52*50% -> #REF! | AM52: =AJ52-AK52+AL52 -> #REF!
B53: Entertainment & Sumbangan | C53: =WS!J429 -> 1750000 | F53: =C53-D53+E53 -> 1750000 | J53: Entertainment & Sumbangan | K53: =WS!U429 -> 1750000 | N53: =K53-L53+M53 -> 1750000 | R53: Entertainment & Sumbangan | S53: =WS!AH429 -> 3550000 | V53: =S53-T53+U53 -> 3550000 | AA53: Entertainment & Sumbangan | AB53: =WS!#REF! -> #REF! | AE53: =AB53-AC53+AD53 -> #REF! | AI53: Entertainment & Sumbangan | AJ53: =WS!#REF! -> #REF! | AM53: =AJ53-AK53+AL53 -> #REF!
B54: Keamanan/Outsourcing | C54: =WS!J430 -> 494527864 | F54: =C54-D54+E54 -> 494527864 | J54: Keamanan/Outsourcing | K54: =WS!U430 -> 370520898 | N54: =K54-L54+M54 -> 370520898 | R54: Keamanan/Outsourcing | S54: =WS!AH430 -> 365402292 | V54: =S54-T54+U54 -> 365402292 | AA54: Keamanan/Outsourcing | AB54: =WS!#REF! -> #REF! | AE54: =AB54-AC54+AD54 -> #REF! | AI54: Keamanan/Outsourcing | AJ54: =WS!#REF! -> #REF! | AM54: =AJ54-AK54+AL54 -> #REF!
B55: Materai, Koran & Majalah | C55: =WS!J431 -> 1985000 | F55: =C55-D55+E55 -> 1985000 | J55: Materai, Koran & Majalah | K55: =WS!U431 -> 2690000 | N55: =K55-L55+M55 -> 2690000 | R55: Materai, Koran & Majalah | S55: =WS!AH431 -> 0 | V55: =S55-T55+U55 -> 0 | AA55: Materai, Koran & Majalah | AB55: =WS!#REF! -> #REF! | AE55: =AB55-AC55+AD55 -> #REF! | AI55: Materai, Koran & Majalah | AJ55: =WS!#REF! -> #REF! | AM55: =AJ55-AK55+AL55 -> #REF!
B56: Meals Traveling | C56: =WS!J432 -> 66151774 | F56: =C56-D56+E56 -> 66151774 | J56: Meals Traveling | K56: =WS!U432 -> 45624644 | N56: =K56-L56+M56 -> 45624644 | R56: Meals Traveling | S56: =WS!AH432 -> 43166473 | V56: =S56-T56+U56 -> 43166473 | AA56: Meals Traveling | AB56: =WS!#REF! -> #REF! | AE56: =AB56-AC56+AD56 -> #REF! | AI56: Meals Traveling | AJ56: =WS!#REF! -> #REF! | AM56: =AJ56-AK56+AL56 -> #REF!
B57: Ongkos Angkut | C57: =WS!J433 -> 95443972 | F57: =C57-D57+E57 -> 95443972 | J57: Ongkos Angkut | K57: =WS!U433 -> 70172940 | N57: =K57-L57+M57 -> 70172940 | R57: Ongkos Angkut | S57: =WS!AH433 -> 75479450 | V57: =S57-T57+U57 -> 75479450 | AA57: Ongkos Angkut | AB57: =WS!#REF! -> #REF! | AE57: =AB57-AC57+AD57 -> #REF! | AI57: Ongkos Angkut | AJ57: =WS!#REF! -> #REF! | AM57: =AJ57-AK57+AL57 -> #REF!
B58: Pajak Lain-Lain | C58: =WS!J434 -> 5869396531 | D58: =2085951250+52408559 -> 2138359809 | F58: =C58-D58+E58 -> 3731036722 | G58: pokok yg dibebankan | J58: Pajak Lain-Lain | K58: =WS!U434 -> 5.8645545e+09 | L58: =2085951250 -> 2085951250 | N58: =K58-L58+M58 -> 3.7786032e+09 | O58: pokok yg dibebankan | R58: Pajak Lain-Lain | S58: =WS!AH434 -> 54336906 | V58: =S58-T58+U58 -> 54336906 | AA58: Pajak Lain-Lain | AB58: =WS!#REF! -> #REF! | AE58: =AB58-AC58+AD58 -> #REF! | AI58: Pajak Lain-Lain | AJ58: =WS!#REF! -> #REF! | AM58: =AJ58-AK58+AL58 -> #REF!
B59: Parkir Tol Fee Dll | C59: =WS!J435 -> 48008000 | F59: =C59-D59+E59 -> 48008000 | G59: Pajak PPh 21: 52.408.559 | J59: Parkir Tol Fee Dll | K59: =WS!U435 -> 36022500 | N59: =K59-L59+M59 -> 36022500 | R59: Parkir Tol Fee Dll | S59: =WS!AH435 -> 17523000 | V59: =S59-T59+U59 -> 17523000 | AA59: Parkir Tol Fee Dll | AB59: =WS!#REF! -> #REF! | AE59: =AB59-AC59+AD59 -> #REF! | AI59: Parkir Tol Fee Dll | AJ59: =WS!#REF! -> #REF! | AM59: =AJ59-AK59+AL59 -> #REF!
B60: Pendidikan & Pelatihan | C60: =WS!J436 -> 9081632.2 | F60: =C60-D60+E60 -> 9081632.2 | J60: Pendidikan & Pelatihan | K60: =WS!U436 -> 0 | N60: =K60-L60+M60 -> 0 | R60: Pendidikan & Pelatihan | S60: =WS!AH436 -> 0 | V60: =S60-T60+U60 -> 0 | AA60: Pendidikan & Pelatihan | AB60: =WS!#REF! -> #REF! | AE60: =AB60-AC60+AD60 -> #REF! | AI60: Pendidikan & Pelatihan | AJ60: =WS!#REF! -> #REF! | AM60: =AJ60-AK60+AL60 -> #REF!
B61: Pengobatan | C61: =WS!J437 -> 0 | F61: =C61-D61+E61 -> 0 | J61: Pengobatan | K61: =WS!U437 -> 0 | N61: =K61-L61+M61 -> 0 | R61: Pengobatan | S61: =WS!AH437 -> 0 | V61: =S61-T61+U61 -> 0 | AA61: Pengobatan | AB61: =WS!#REF! -> #REF! | AE61: =AB61-AC61+AD61 -> #REF! | AI61: Pengobatan | AJ61: =WS!#REF! -> #REF! | AM61: =AJ61-AK61+AL61 -> #REF!
B62: Peralatan & Perlengkapan Kantor | C62: =WS!J438 -> 29120505 | F62: =C62-D62+E62 -> 29120505 | J62: Peralatan & Perlengkapan Kantor | K62: =WS!U438 -> 23213065 | N62: =K62-L62+M62 -> 23213065 | R62: Peralatan & Perlengkapan Kantor | S62: =WS!AH438 -> 18194800 | V62: =S62-T62+U62 -> 18194800 | AA62: Peralatan & Perlengkapan Kantor | AB62: =WS!#REF! -> #REF! | AE62: =AB62-AC62+AD62 -> #REF! | AI62: Peralatan & Perlengkapan Kantor | AJ62: =WS!#REF! -> #REF! | AM62: =AJ62-AK62+AL62 -> #REF!
B63: Perdin, Hotel, Tiket, Akomodasi | C63: =WS!J439 -> 1940000 | F63: =C63-D63+E63 -> 1940000 | J63: Perdin, Hotel, Tiket, Akomodasi | K63: =WS!U439 -> 1940000 | N63: =K63-L63+M63 -> 1940000 | R63: Perdin, Hotel, Tiket, Akomodasi | S63: =WS!AH439 -> 50000 | V63: =S63-T63+U63 -> 50000 | AA63: Perdin, Hotel, Tiket, Akomodasi | AB63: =WS!#REF! -> #REF! | AE63: =AB63-AC63+AD63 -> #REF! | AI63: Perdin, Hotel, Tiket, Akomodasi | AJ63: =WS!#REF! -> #REF! | AM63: =AJ63-AK63+AL63 -> #REF!
B64: Rumah Tangga Kantor | C64: =WS!J440 -> 708567754 | F64: =C64-D64+E64 -> 708567754 | J64: Rumah Tangga Kantor | K64: =WS!U440 -> 399285816 | N64: =K64-L64+M64 -> 399285816 | R64: Rumah Tangga Kantor | S64: =WS!AH440 -> 493818136 | V64: =S64-T64+U64 -> 493818136 | AA64: Rumah Tangga Kantor | AB64: =WS!#REF! -> #REF! | AE64: =AB64-AC64+AD64 -> #REF! | AI64: Rumah Tangga Kantor | AJ64: =WS!#REF! -> #REF! | AM64: =AJ64-AK64+AL64 -> #REF!
B65: Surat-Surat Kendaraan Kantor | C65: =WS!J441 -> 18004700 | F65: =C65-D65+E65 -> 18004700 | J65: Surat-Surat Kendaraan Kantor | K65: =WS!U441 -> 10757450 | N65: =K65-L65+M65 -> 10757450 | R65: Surat-Surat Kendaraan Kantor | S65: =WS!AH441 -> 37163000 | V65: =S65-T65+U65 -> 37163000 | AA65: Surat-Surat Kendaraan Kantor | AB65: =WS!#REF! -> #REF! | AE65: =AB65-AC65+AD65 -> #REF! | AI65: Surat-Surat Kendaraan Kantor | AJ65: =WS!#REF! -> #REF! | AM65: =AJ65-AK65+AL65 -> #REF!
B66: Surat-Surat Perizinan | C66: =WS!J442 -> 986155206 | F66: =C66-D66+E66 -> 986155206 | J66: Surat-Surat Perizinan | K66: =WS!U442 -> 933155206 | N66: =K66-L66+M66 -> 933155206 | R66: Surat-Surat Perizinan | S66: =WS!AH442 -> 0 | V66: =S66-T66+U66 -> 0 | AA66: Surat-Surat Perizinan | AB66: =WS!#REF! -> #REF! | AE66: =AB66-AC66+AD66 -> #REF! | AI66: Surat-Surat Perizinan | AJ66: =WS!#REF! -> #REF! | AM66: =AJ66-AK66+AL66 -> #REF!
B67: Telephone | C67: =WS!J443 -> 20197065 | D67: =C67*50% -> 10098532 | F67: =C67-D67+E67 -> 10098532 | J67: Telephone | K67: =WS!U443 -> 14677914 | L67: =K67 -> 14677914 | N67: =K67-L67+M67 -> 0 | R67: Telephone | S67: =WS!AH443 -> 16408319 | T67: =S67*50% -> 8204159.5 | V67: =S67-T67+U67 -> 8204159.5 | AA67: Telephone | AB67: =WS!#REF! -> #REF! | AC67: =AB67*50% -> #REF! | AE67: =AB67-AC67+AD67 -> #REF! | AI67: Telephone | AJ67: =WS!#REF! -> #REF! | AK67: =AJ67*50% -> #REF! | AM67: =AJ67-AK67+AL67 -> #REF!
B68: Tenaga Ahli / Konsultan | C68: =WS!J444 -> 634079028 | F68: =C68-D68+E68 -> 634079028 | J68: Tenaga Ahli / Konsultan | K68: =WS!U444 -> 574668461 | N68: =K68-L68+M68 -> 574668461 | R68: Tenaga Ahli / Konsultan | S68: =WS!AH444 -> 293940084 | V68: =S68-T68+U68 -> 293940084 | AA68: Tenaga Ahli / Konsultan | AB68: =WS!#REF! -> #REF! | AE68: =AB68-AC68+AD68 -> #REF! | AI68: Tenaga Ahli / Konsultan | AJ68: =WS!#REF! -> #REF! | AM68: =AJ68-AK68+AL68 -> #REF!
B69: Imbalan Pasca Kerja | C69: =WS!J445 -> 0 | F69: =C69-D69+E69 -> 0 | J69: Imbalan Pasca Kerja | K69: =WS!U445 -> 209687496 | N69: =K69-L69+M69 -> 209687496 | R69: Imbalan Pasca Kerja | S69: =WS!AH445 -> 81714215 | V69: =S69-T69+U69 -> 81714215 | AA69: Imbalan Pasca Kerja | AB69: =WS!#REF! -> #REF! | AE69: =AB69-AC69+AD69 -> #REF! | AI69: Imbalan Pasca Kerja | AJ69: =WS!#REF! -> #REF! | AM69: =AJ69-AK69+AL69 -> #REF!
B70: Transportasi, Akomodasi | C70: =WS!J446 -> 405000 | F70: =C70-D70+E70 -> 405000 | J70: Transportasi, Akomodasi | K70: =WS!U446 -> 305000 | N70: =K70-L70+M70 -> 305000 | R70: Transportasi, Akomodasi | S70: =WS!AH446 -> 140000 | V70: =S70-T70+U70 -> 140000 | AA70: Transportasi, Akomodasi | AB70: =WS!#REF! -> #REF! | AE70: =AB70-AC70+AD70 -> #REF! | AI70: Transportasi, Akomodasi | AJ70: =WS!#REF! -> #REF! | AM70: =AJ70-AK70+AL70 -> #REF!
B71: Biaya PPh 21 | C71: =WS!J447 -> 0 | F71: =C71-D71+E71 -> 0 | J71: Biaya PPh 21 | K71: =WS!U447 -> 0 | N71: =K71-L71+M71 -> 0 | R71: Biaya PPh 21 | S71: =WS!AH447 -> 0 | V71: =S71-T71+U71 -> 0 | AA71: Biaya PPh 21 | AB71: =WS!#REF! -> #REF! | AE71: =AB71-AC71+AD71 -> #REF! | AI71: Biaya PPh 21 | AJ71: =WS!#REF! -> #REF! | AM71: =AJ71-AK71+AL71 -> #REF!
B72: Biaya Lain-lain | C72: =WS!J448 -> 0 | F72: =C72-D72+E72 -> 0 | J72: Biaya Lain-lain | K72: =WS!U448 -> 0 | N72: =K72-L72+M72 -> 0 | R72: Biaya Lain-lain | S72: =WS!AH448 -> 0 | V72: =S72-T72+U72 -> 0 | AA72: Biaya Lain-lain | AB72: =WS!#REF! -> #REF! | AE72: =AB72-AC72+AD72 -> #REF! | AI72: Biaya Lain-lain | AJ72: =WS!#REF! -> #REF! | AM72: =AJ72-AK72+AL72 -> #REF!
A74: Beban Perbaikan Dan Pemeliharaan | I74: Beban Perbaikan Dan Pemeliharaan | Q74: Beban Perbaikan Dan Pemeliharaan | Z74: Beban Perbaikan Dan Pemeliharaan | AH74: Beban Perbaikan Dan Pemeliharaan
B75: Perbaikan & Pemeliharaan Bangunan | C75: =WS!J449 -> 1230000 | F75: =C75-D75+E75 -> 1230000 | J75: Perbaikan & Pemeliharaan Bangunan | K75: =WS!U449 -> 1230000 | N75: =K75-L75+M75 -> 1230000 | R75: Perbaikan & Pemeliharaan Bangunan | S75: =WS!AH449 -> 50000 | V75: =S75-T75+U75 -> 50000 | AA75: Perbaikan & Pemeliharaan Bangunan | AB75: =WS!#REF! -> #REF! | AE75: =AB75-AC75+AD75 -> #REF! | AI75: Perbaikan & Pemeliharaan Bangunan | AJ75: =WS!#REF! -> #REF! | AM75: =AJ75-AK75+AL75 -> #REF!
B76: Perbaikan & Pemeliharaan Infrastruktur | C76: =WS!J450 -> 75826976 | F76: =C76-D76+E76 -> 75826976 | J76: Perbaikan & Pemeliharaan Infrastruktur | K76: =WS!U450 -> 40209876 | N76: =K76-L76+M76 -> 40209876 | R76: Perbaikan & Pemeliharaan Infrastruktur | S76: =WS!AH450 -> 56612666 | V76: =S76-T76+U76 -> 56612666 | AA76: Perbaikan & Pemeliharaan Infrastruktur | AB76: =WS!#REF! -> #REF! | AE76: =AB76-AC76+AD76 -> #REF! | AI76: Perbaikan & Pemeliharaan Infrastruktur | AJ76: =WS!#REF! -> #REF! | AM76: =AJ76-AK76+AL76 -> #REF!
B77: Perbaikan & Pemeliharaan Kendaraan Kantor | C77: =WS!J451 -> 116254721 | F77: =C77-D77+E77 -> 116254721 | J77: Perbaikan & Pemeliharaan Kendaraan Kantor | K77: =WS!U451 -> 104199521 | N77: =K77-L77+M77 -> 104199521 | R77: Perbaikan & Pemeliharaan Kendaraan Kantor | S77: =WS!AH451 -> 42577015 | V77: =S77-T77+U77 -> 42577015 | AA77: Perbaikan & Pemeliharaan Kendaraan Kantor | AB77: =WS!#REF! -> #REF! | AE77: =AB77-AC77+AD77 -> #REF! | AI77: Perbaikan & Pemeliharaan Kendaraan Kantor | AJ77: =WS!#REF! -> #REF! | AM77: =AJ77-AK77+AL77 -> #REF!
B78: Perbaikan & Pemeliharaan Kendaraan Pabrik | C78: =WS!J452 -> 3815000 | F78: =C78-D78+E78 -> 3815000 | J78: Perbaikan & Pemeliharaan Kendaraan Pabrik | K78: =WS!U452 -> 3815000 | N78: =K78-L78+M78 -> 3815000 | R78: Perbaikan & Pemeliharaan Kendaraan Pabrik | S78: =WS!AH452 -> 1150000 | V78: =S78-T78+U78 -> 1150000 | AA78: Perbaikan & Pemeliharaan Kendaraan Pabrik | AB78: =WS!#REF! -> #REF! | AE78: =AB78-AC78+AD78 -> #REF! | AI78: Perbaikan & Pemeliharaan Kendaraan Pabrik | AJ78: =WS!#REF! -> #REF! | AM78: =AJ78-AK78+AL78 -> #REF!
B79: Perbaikan & Pemeliharaan Mesin | C79: =WS!J453 -> 369131259 | F79: =C79-D79+E79 -> 369131259 | J79: Perbaikan & Pemeliharaan Mesin | K79: =WS!U453 -> 242979329 | N79: =K79-L79+M79 -> 242979329 | R79: Perbaikan & Pemeliharaan Mesin | S79: =WS!AH453 -> 273933689 | V79: =S79-T79+U79 -> 273933689 | AA79: Perbaikan & Pemeliharaan Mesin | AB79: =WS!#REF! -> #REF! | AE79: =AB79-AC79+AD79 -> #REF! | AI79: Perbaikan & Pemeliharaan Mesin | AJ79: =WS!#REF! -> #REF! | AM79: =AJ79-AK79+AL79 -> #REF!
B80: Perbaikan & Pemeliharaan Peralatan Kantor | C80: =WS!J454 -> 6061000 | F80: =C80-D80+E80 -> 6061000 | J80: Perbaikan & Pemeliharaan Peralatan Kantor | K80: =WS!U454 -> 3374000 | N80: =K80-L80+M80 -> 3374000 | R80: Perbaikan & Pemeliharaan Peralatan Kantor | S80: =WS!AH454 -> 5034363 | V80: =S80-T80+U80 -> 5034363 | AA80: Perbaikan & Pemeliharaan Peralatan Kantor | AB80: =WS!#REF! -> #REF! | AE80: =AB80-AC80+AD80 -> #REF! | AI80: Perbaikan & Pemeliharaan Peralatan Kantor | AJ80: =WS!#REF! -> #REF! | AM80: =AJ80-AK80+AL80 -> #REF!
A82: Beban Depresiasi Dan Amortisasi | I82: Beban Depresiasi Dan Amortisasi | Q82: Beban Depresiasi Dan Amortisasi | Z82: Beban Depresiasi Dan Amortisasi | AH82: Beban Depresiasi Dan Amortisasi
B83: Penyusutan Peralatan Kantor | C83: =WS!J456 -> 10112250 | F83: =C83-D83+E83 -> 10112250 | J83: Penyusutan Peralatan Kantor | K83: =WS!U456 -> 8961208.3 | N83: =K83-L83+M83 -> 8961208.3 | R83: Penyusutan Peralatan Kantor | S83: =WS!AH456 -> 14839992 | V83: =S83-T83+U83 -> 14839992 | AA83: Penyusutan Peralatan Kantor | AB83: =WS!#REF! -> #REF! | AE83: =AB83-AC83+AD83 -> #REF! | AI83: Penyusutan Peralatan Kantor | AJ83: =WS!#REF! -> #REF! | AM83: =AJ83-AK83+AL83 -> #REF!
B84: Penyusutan Kendaraan | C84: =WS!J460 -> 0 | F84: =C84-D84+E84 -> 0 | J84: Penyusutan Kendaraan | K84: =WS!U460 -> 157686750 | N84: =K84-L84+M84 -> 157686750 | R84: Penyusutan Kendaraan | S84: =WS!AH460 -> 36915730 | V84: =S84-T84+U84 -> 36915730 | AA84: Penyusutan Kendaraan | AB84: =WS!#REF! -> #REF! | AE84: =AB84-AC84+AD84 -> #REF! | AI84: Penyusutan Kendaraan | AJ84: =WS!#REF! -> #REF! | AM84: =AJ84-AK84+AL84 -> #REF!
A86: TOTAL BEBAN USAHA | C86: =SUM(C26:C84) -> 2.8995496e+10 | E86: =SUM(E26:E85) -> 0 | F86: =SUM(F26:F84) -> 2.6773671e+10 | I86: TOTAL BEBAN USAHA | K86: =SUM(K26:K84) -> 2.2552612e+10 | N86: =SUM(N26:N84) -> 2.0397949e+10 | Q86: TOTAL BEBAN USAHA | S86: =SUM(S26:S84) -> 18128315098 | V86: =SUM(V26:V84) -> 1.8120086e+10 | Z86: TOTAL BEBAN USAHA | AB86: =SUM(AB26:AB84) -> #REF! | AE86: =SUM(AE26:AE84) -> #REF! | AH86: TOTAL BEBAN USAHA | AJ86: =SUM(AJ26:AJ84) -> #REF! | AM86: =SUM(AM26:AM84) -> #REF!
A87: Laba (Rugi) Usaha | C87: =C23-C86 -> 1.4112988e+10 | E87: =E23-E86 -> 0 | F87: =F23-F86 -> 1.6334813e+10 | I87: Laba (Rugi) Usaha | K87: =K23-K86 -> 7.0376861e+09 | N87: =N23-N86 -> 9.1923491e+09 | Q87: Laba (Rugi) Usaha | S87: =S23-S86 -> 7946449513 | V87: =V23-V86 -> 7.8662927e+09 | Z87: Laba (Rugi) Usaha | AB87: =AB23-AB86 -> #REF! | AE87: =AE23-AE86 -> #REF! | AH87: Laba (Rugi) Usaha | AJ87: =AJ23-AJ86 -> #REF! | AM87: =AM23-AM86 -> #REF!
A89: Pendapatan (Biaya) Lain-lain | I89: Pendapatan (Biaya) Lain-lain | Q89: Pendapatan (Biaya) Lain-lain | Z89: Pendapatan (Biaya) Lain-lain | AH89: Pendapatan (Biaya) Lain-lain
B90: Pendapatan Bunga | C90: =WS!J470 -> 70634245 | E90: =C90 -> 70634245 | F90: =C90+D90-E90 -> 0 | J90: Pendapatan Bunga | K90: =WS!U470 -> 69022353 | M90: =K90 -> 69022353 | N90: =K90+L90-M90 -> 0 | R90: Pendapatan Bunga | S90: =WS!AH470 -> 47280776 | U90: =S90 -> 47280776 | V90: =S90+T90-U90 -> 0 | AA90: =[1]WBS!C500 -> Pendapatan Bunga | AB90: =WS!#REF! -> #REF! | AD90: =AB90 -> #REF! | AE90: =AB90+AC90-AD90 -> #REF! | AI90: Pendapatan Bunga | AJ90: =WS!#REF! -> #REF! | AL90: =AJ90 -> #REF! | AM90: =AJ90+AK90-AL90 -> #REF!
B91: Laba (Rugi) Selisih Kurs - Neto | C91: =WS!J471 -> -1.6749565e+09 | F91: =C91+D91-E91 -> -1.6749565e+09 | J91: Laba (Rugi) Selisih Kurs - Neto | K91: =WS!U471 -> 1.5785955e+09 | N91: =K91+L91-M91 -> 1.5785955e+09 | R91: Laba (Rugi) Selisih Kurs - Neto | S91: =WS!AH471 -> -751427729 | V91: =S91+T91-U91 -> -751427729 | AA91: =[1]WBS!C501 -> Laba (Rugi) Selisih Kurs - Neto | AB91: =WS!#REF! -> #REF! | AE91: =AB91+AC91-AD91 -> #REF! | AI91: Laba (Rugi) Selisih Kurs - Neto | AJ91: =WS!#REF! -> #REF! | AM91: =AJ91+AK91-AL91 -> #REF!
B92: Pendapatan Lain-Lain | C92: =WS!J473 -> -8183754 | F92: =C92+D92-E92 -> -8183754 | J92: Pendapatan Lain-Lain | K92: =WS!U473 -> 0 | N92: =K92+L92-M92 -> 0 | R92: Pendapatan Lain-Lain | S92: =WS!AH473 -> 11038330 | V92: =S92+T92-U92 -> 11038330 | AA92: =[1]WBS!C502 -> Pendapatan Lain-Lain | AB92: =WS!#REF! -> #REF! | AE92: =AB92+AC92-AD92 -> #REF! | AI92: Pendapatan Lain-Lain | AJ92: =WS!#REF! -> #REF! | AM92: =AJ92+AK92-AL92 -> #REF!
B93: Beban (Pendapatan) Cadangan kerugian Penurunan Nilai | C93: =-WS!J483 -> 8.2419978e+08 | E93: =C93 -> 8.2419978e+08 | F93: =C93+D93-E93 -> 0 | J93: Beban Cadangan kerugian Penurunan Nilai | K93: =WS!U472 -> 0 | N93: =K93-L93+M93 -> 0 | R93: Beban Cadangan kerugian Penurunan Nilai | S93: =WS!AH4472 -> 0 | V93: =S93-T93+U93 -> 0 | AA93: =[1]WBS!C504 -> Beban Cadangan kerugian Penurunan Nilai | AB93: =WS!#REF! -> #REF! | AE93: =AB93-AC93+AD93 -> #REF! | AI93: Beban Cadangan kerugian Penurunan Nilai | AJ93: =WS!#REF! -> #REF! | AM93: =AJ93-AK93+AL93 -> #REF!
B94: Beban Administrasi Bank | C94: =WS!J476 -> 74572923 | F94: =C94-D94+E94 -> 74572923 | J94: Beban Administrasi Bank | K94: =WS!U476 -> 49376357 | N94: =K94-L94+M94 -> 49376357 | R94: Beban Administrasi Bank | S94: =WS!AH476 -> 114713721 | V94: =S94-T94+U94 -> 114713721 | AA94: =[1]WBS!C508 -> Beban Administrasi Bank | AB94: =WS!#REF! -> #REF! | AE94: =AB94-AC94+AD94 -> #REF! | AI94: Beban Administrasi Bank | AJ94: =WS!#REF! -> #REF! | AM94: =AJ94-AK94+AL94 -> #REF!
B95: Beban Pajak Jasa Giro | C95: =WS!J477 -> 14686913 | D95: =C95 -> 14686913 | F95: =C95-D95+E95 -> 0 | J95: Beban Pajak Jasa Giro | K95: =WS!U477 -> 14108709 | L95: =K95 -> 14108709 | N95: =K95-L95+M95 -> 0 | R95: Beban Pajak Jasa Giro | S95: =WS!AH477 -> 9605268 | T95: =S95 -> 9605268 | V95: =S95-T95+U95 -> 0 | AA95: =[1]WBS!C509 -> Beban Pajak Jasa Giro | AB95: =WS!#REF! -> #REF! | AC95: =AB95 -> #REF! | AE95: =AB95-AC95+AD95 -> #REF! | AI95: Beban Pajak Jasa Giro | AJ95: =WS!#REF! -> #REF! | AK95: =AJ95 -> #REF! | AM95: =AJ95-AK95+AL95 -> #REF!
B96: Beban Provisi Bank | C96: =WS!J478 -> 169215000 | F96: =C96-D96+E96 -> 169215000 | J96: Beban Provisi Bank | K96: =WS!U478 -> 0 | N96: =K96-L96+M96 -> 0 | R96: Beban Provisi Bank | S96: =WS!AH478 -> 0 | V96: =S96-T96+U96 -> 0 | AA96: =[1]WBS!C510 -> Beban Provisi Bank | AB96: =WS!#REF! -> #REF! | AE96: =AB96-AC96+AD96 -> #REF! | AI96: Beban Provisi Bank | AJ96: =WS!#REF! -> #REF! | AM96: =AJ96-AK96+AL96 -> #REF!
B97: Denda Angsuran Bank, Biaya | C97: =WS!J479 -> 0 | F97: =C97-D97+E97 -> 0 | J97: Denda Angsuran Bank, Biaya | K97: =WS!U479 -> 0 | N97: =K97-L97+M97 -> 0 | R97: Denda Angsuran Bank, Biaya | S97: =WS!AH479 -> 0 | V97: =S97-T97+U97 -> 0 | AA97: =[1]WBS!C511 -> Denda Angsuran Bank, Biaya | AB97: =WS!#REF! -> #REF! | AE97: =AB97-AC97+AD97 -> #REF! | AI97: Denda Angsuran Bank, Biaya | AJ97: =WS!#REF! -> #REF! | AM97: =AJ97-AK97+AL97 -> #REF!
B98: Denda Pajak | C98: =WS!J480 -> 0 | F98: =C98-D98+E98 -> 0 | J98: Denda Pajak | K98: =WS!U480 -> 0 | N98: =K98-L98+M98 -> 0 | R98: Denda Pajak | S98: =WS!AH480 -> 0 | V98: =S98-T98+U98 -> 0 | AA98: =[1]WBS!C512 -> Estimasi Denda Pajak | AB98: =WS!#REF! -> #REF! | AE98: =AB98-AC98+AD98 -> #REF! | AI98: Estimasi Denda Pajak | AJ98: =WS!#REF! -> #REF! | AM98: =AJ98-AK98+AL98 -> #REF!
B99: Beban Bunga/Keuangan | C99: =WS!J481 -> 9984777061 | F99: =C99-D99+E99 -> 9984777061 | J99: Beban Bunga/Keuangan | K99: =WS!U481 -> 6639200650 | N99: =K99-L99+M99 -> 6639200650 | R99: Beban Bunga/Keuangan | S99: =WS!AH481 -> 6294987446 | V99: =S99-T99+U99 -> 6294987446 | AA99: =[1]WBS!C513 -> Beban Bunga/Keuangan | AB99: =WS!#REF! -> #REF! | AE99: =AB99-AC99+AD99 -> #REF! | AI99: Beban Bunga/Keuangan | AJ99: =WS!#REF! -> #REF! | AM99: =AJ99-AK99+AL99 -> #REF!
B100: Beban Bunga Leasing | C100: =WS!J482 -> 5239977 | F100: =C100-D100+E100 -> 5239977 | J100: Beban Bunga Leasing | K100: =WS!U482 -> 4288654 | N100: =K100-L100+M100 -> 4288654 | R100: Beban Bunga Leasing | S100: =WS!AH482 -> 11383894 | V100: =S100-T100+U100 -> 11383894 | AA100: =[1]WBS!C514 -> Beban Bunga Leasing | AB100: =WS!#REF! -> #REF! | AE100: =AB100-AC100+AD100 -> #REF! | AI100: Beban Bunga Leasing | AJ100: =WS!#REF! -> #REF! | AM100: =AJ100-AK100+AL100 -> #REF!
F101: =C101-D101+E101 -> 0 | N101: =K101-L101+M101 -> 0 | V101: =S101-T101+U101 -> 0 | AE101: =AB101-AC101+AD101 -> 0 | AM101: =AJ101-AK101+AL101 -> 0
B103: Jumlah Pendapatan (Biaya) Lain-lain | C103: =SUM(C90:C93)-SUM(C94:C101) -> -1.1036798e+10 | D103: =SUM(D9:D102) -> 2.2365119e+09 | E103: =-SUM(E9:E102) -> -8.9483402e+08 | F103: =SUM(F90:F93)-SUM(F94:F101) -> -1.1916945e+10 | J103: Jumlah Pendapatan (Biaya) Lain-lain | K103: =SUM(K90:K93)-SUM(K94:K101) -> -5.0593565e+09 | L103: =-SUM(L90:L102) -> -14108709 | M103: =-SUM(M90:M102) -> -69022353 | N103: =SUM(N90:N93)-SUM(N94:N101) -> -5.1142701e+09 | R103: Jumlah Pendapatan (Biaya) Lain-lain | S103: =SUM(S90:S93)-SUM(S94:S101) -> -7123798952 | T103: =-SUM(T90:T102) -> -9605268 | U103: =-SUM(U90:U102) -> -47280776 | V103: =SUM(V90:V93)-SUM(V94:V101) -> -7161474460 | AA103: Jumlah Pendapatan (Biaya) Lain-lain | AB103: =SUM(AB90:AB93)-SUM(AB94:AB101) -> #REF! | AC103: =-SUM(AC90:AC102) -> #REF! | AD103: =-SUM(AD90:AD102) -> #REF! | AE103: =SUM(AE90:AE93)-SUM(AE94:AE101) -> #REF! | AI103: Jumlah Pendapatan (Biaya) Lain-lain | AJ103: =SUM(AJ90:AJ93)-SUM(AJ94:AJ101) -> #REF! | AK103: =-SUM(AK90:AK102) -> #REF! | AL103: =-SUM(AL90:AL102) -> #REF! | AM103: =SUM(AM90:AM93)-SUM(AM94:AM101) -> #REF!
A105: Laba (Rugi) Bersih Sebelum Pajak | C105: =C87+C103 -> 3.0761898e+09 | D105: =D87+D103 -> 2.2365119e+09 | E105: =E87+E103 -> -8.9483402e+08 | F105: =F87+F103 -> 4.4178677e+09 | I105: Laba (Rugi) Bersih Sebelum Pajak | K105: =K87+K103 -> 1.9783296e+09 | L105: =L87+L103 -> -14108709 | M105: =M87+M103 -> -69022353 | N105: =N87+N103 -> 4.078079e+09 | Q105: Laba (Rugi) Bersih Sebelum Pajak | S105: =S87+S103 -> 822650561 | T105: =T87+T103 -> -9605268 | U105: =U87+U103 -> -47280776 | V105: =V87+V103 -> 7.0481826e+08 | Z105: Laba (Rugi) Bersih Sebelum Pajak | AB105: =AB87+AB103 -> #REF! | AC105: =AC87+AC103 -> #REF! | AD105: =AD87+AD103 -> #REF! | AE105: =AE87+AE103 -> #REF! | AH105: Laba (Rugi) Bersih Sebelum Pajak | AJ105: =AJ87+AJ103 -> #REF! | AK105: =AK87+AK103 -> #REF! | AL105: =AL87+AL103 -> #REF! | AM105: =AM87+AM103 -> #REF!
A107: Pajak Penghasilan | D107: =C107 -> 0 | E107: 0 | F107: 0 | I107: Pajak Penghasilan | L107: =K107 -> 0 | M107: 0 | N107: 0 | Q107: Pajak Penghasilan | T107: =S107 -> 0 | U107: 0 | V107: 0 | Z107: Pajak Penghasilan | AC107: =AB107 -> 0 | AD107: 0 | AE107: 0 | AH107: Pajak Penghasilan | AK107: =AJ107 -> 0 | AL107: 0 | AM107: 0
A109: LABA (RUGI) SETELAH PAJAK TANGGUHAN | C109: =C105-C107 -> 3.0761898e+09 | D109: =D105-D107 -> 2.2365119e+09 | E109: =E105-E107 -> -8.9483402e+08 | F109: =F105-F107 -> 4.4178677e+09 | I109: LABA (RUGI) SETELAH PAJAK TANGGUHAN | K109: =K105-K107 -> 1.9783296e+09 | L109: =L105-L107 -> -14108709 | M109: =M105-M107 -> -69022353 | N109: =N105-N107 -> 4.078079e+09 | Q109: LABA (RUGI) SETELAH PAJAK TANGGUHAN | S109: =S105-S107 -> 822650561 | T109: =T105-T107 -> -9605268 | U109: =U105-U107 -> -47280776 | V109: =V105-V107 -> 7.0481826e+08 | Z109: LABA (RUGI) SETELAH PAJAK TANGGUHAN | AB109: =AB105-AB107 -> #REF! | AC109: =AC105-AC107 -> #REF! | AD109: =AD105-AD107 -> #REF! | AE109: =AE105-AE107 -> #REF! | AH109: LABA (RUGI) SETELAH PAJAK TANGGUHAN | AJ109: =AJ105-AJ107 -> #REF! | AK109: =AK105-AK107 -> #REF! | AL109: =AL105-AL107 -> #REF! | AM109: =AM105-AM107 -> #REF!
C110: =WS!J487 -> 3.0761898e+09 | D110: =D109+E109 -> 1.3416779e+09 | K110: =WS!U487 -> 1.9783296e+09 | L110: =L109+M109 -> -83131062 | S110: =WS!AH503 -> 523153561 | T110: =T109+U109 -> -56886044 | AB110: =WS!#REF! -> #REF! | AC110: =AC109+AD109 -> #REF! | AJ110: =WS!#REF! -> #REF! | AK110: =AK109+AL109 -> #REF!
C111: =C109-C110 -> 0 | K111: =K109-K110 -> 0.56349564 | S111: =S109-S110 -> 299497000 | AB111: =AB109-AB110 -> #REF! | AJ111: =AJ109-AJ110 -> #REF!
A114: 1. | B114: Peredaran Bruto | I114: 1. | J114: Peredaran Bruto | Q114: 1. | R114: Peredaran Bruto | Z114: 1. | AA114: Peredaran Bruto | AH114: 1. | AI114: Peredaran Bruto
B115: a. Dari Kegiatan Usaha | F115: =F12 -> 1.655777e+10 | J115: a. Dari Kegiatan Usaha | N115: =N12 -> 1.2606433e+10 | R115: a. Dari Kegiatan Usaha | V115: =V12 -> 10652081484 | AA115: a. Dari Kegiatan Usaha | AE115: =AE12 -> #REF! | AI115: a. Dari Kegiatan Usaha | AM115: =AM12 -> #REF!
B116: b. Dari Luar Kegiatan Usaha | J116: b. Dari Luar Kegiatan Usaha | R116: b. Dari Luar Kegiatan Usaha | AA116: b. Dari Luar Kegiatan Usaha | AI116: b. Dari Luar Kegiatan Usaha
B117: c. Dari Luar Negeri | F117: =F11 -> 1.6593558e+11 | J117: c. Dari Luar Negeri | N117: =N11 -> 8.7688651e+10 | R117: c. Dari Luar Negeri | V117: =V11 -> 134989855636 | AA117: c. Dari Luar Negeri | AE117: =AE11 -> #REF! | AI117: c. Dari Luar Negeri | AM117: =AM11 -> #REF!
...

Sheet SPT Badan
B2: Des-24 | D2: 45536 | F2: 45170 | H2: Juni-2024 | J2: Juni-2023 | L2: 45536 | N2: Des-23
A4: Entitas Induk
A5: Laba sebelum pajak | B5: =PL!F21 -> 3.0761898e+09 | D5: =PL!H21 -> 1.9783296e+09 | F5: =PL!J21 -> 822650561 | H5: =PL!#REF! -> #REF! | J5: =PL!#REF! -> #REF! | L5: 2.1554332e+09 | N5: 2011439434
A7: Beda Temporer:
A8: Imbalan kerja | B8: =WS!J445 -> 0 | D8: =WS!U445 -> 209687496 | F8: 0 | H8: 0 | J8: 0 | L8: 0 | N8: 279583328
A9: Penyusutan aset tetap | D9: 0 | F9: =-'Korfis IAS Des 24'!U19 -> -88385951 | H9: =-'Korfis IAS Des 24'!AD19 -> -58923967 | J9: =-'Korfis IAS Des 24'!AL19 -> -58923967 | L9: 0 | N9: -117847934
A10: Beban Kerugian
A11: Penurunan Piutang
A12: Usaha | B12: 0 | D12: 0 | F12: 0 | H12: 0 | J12: 0 | L12: 0 | N12: 119304064
A14: Beda Permanen:
A15: Penyusutan aset
A16: Pengampunan pajak | B16: 743637653 | D16: 5.6197008e+08 | F16: 5.6197008e+08 | H16: 749293434 | J16: 749293434 | L16: 5.6197008e+08 | N16: 749293434
A17: Beban Pajak Jasa Giro | B17: ='Korfis IAS Des 24'!D95 -> 14686913 | D17: ='Korfis IAS Des 24'!L95 -> 14108709 | F17: ='Korfis IAS Des 24'!T95 -> 9605268 | H17: ='Korfis IAS Des 24'!AC95 -> #REF! | J17: ='Korfis IAS Des 24'!AK95 -> #REF! | L17: 14108709 | N17: 13516147
A18: Telephone | B18: ='Korfis IAS Des 24'!D67 -> 10098532 | D18: ='Korfis IAS Des 24'!L67 -> 14677914 | F18: ='Korfis IAS Des 24'!T67 -> 8204159.5 | H18: ='Korfis IAS Des 24'!AC67 -> #REF! | J18: ='Korfis IAS Des 24'!AK67 -> #REF! | L18: 14677914
A19: Administrasi dan Umum | N19: 59045957 | O19: Pajak Giro
A20: Lainnya | B20: ='Korfis IAS Des 24'!D49 -> 1343058 | D20: ='Korfis IAS Des 24'!L49 -> 1293058 | F20: ='Korfis IAS Des 24'!T49 -> 25000 | H20: ='Korfis IAS Des 24'!AC49 -> #REF! | J20: ='Korfis IAS Des 24'!AK49 -> #REF! | L20: 1293058 | N20: 11336931
A21: Pendapatan yang telah
A22: dikenakan pajak
A23: bersifat Final
A24: Lainnya | B24: =('Korfis IAS Des 24'!D52+'Korfis IAS Des 24'!D58+'Korfis IAS Des 24'!D26+'Korfis IAS Des 24'!D37+'Korfis IAS Des 24'!D98) -> 2210383441 | D24: ='Korfis IAS Des 24'!L52+'Korfis IAS Des 24'!L58+'Korfis IAS Des 24'!L26+'Korfis IAS Des 24'!L37+'Korfis IAS Des 24'!L98 -> 2.1386921e+09 | L24: 4.2246433e+09 | N24: 570000
A25: Pendapatan Lain-lain | B25: 0 | D25: 0 | F25: ='Korfis IAS Des 24'!U92 -> 0 | H25: 0 | J25: 0 | L25: 0
A26: Cadangan Kerugian Piutang | B26: =-'Korfis IAS Des 24'!E93 -> -8.2419978e+08
A27: Pendapatan Bunga | B27: =-'Korfis IAS Des 24'!E90 -> -70634245 | D27: =-'Korfis IAS Des 24'!M90 -> -69022353 | F27: ='Korfis IAS Des 24'!U90 -> 47280776 | H27: =-'Korfis IAS Des 24'!AD90 -> #REF! | J27: =-'Korfis IAS Des 24'!AL90 -> #REF! | L27: -69022353 | N27: -65659825
A29: Jumlah Koreksi
A30: Fiskal - Bersih | B30: =SUM(B8:B27) -> 2.0853156e+09 | D30: =SUM(D8:D27) -> 2.871407e+09 | F30: =SUM(F8:F27) -> 5.3869933e+08 | H30: =SUM(H8:H27) -> #REF! | J30: =SUM(J8:J27) -> #REF! | L30: 4.7476707e+09 | N30: =SUM(N8:N27) -> 1049142102
A32: Taksiran penghasilan
A33: kena pajak | B33: =B30+B5 -> 5.1615054e+09 | D33: =D30+D5 -> 4.8497365e+09 | F33: =F30+F5 -> 1.3613499e+09 | H33: =H30+H5 -> #REF! | J33: =J30+J5 -> #REF! | L33: 6.9031039e+09 | N33: =N30+N5 -> 3060581536
A35: Pembulatan | B35: =ROUND(B33,-3) -> 5161505000 | D35: =ROUND(D33,-3) -> 4849737000 | F35: =ROUND(F33,-3) -> 1361350000 | H35: 1369181000 | J35: 1369181000 | L35: 6903104000 | N35: =ROUND(N33,-3) -> 3060582000
A37: Beban pajak kini (22%) | B37: =B35*22% -> 1135531100 | D37: =D35*22% -> 1066942140 | F37: =F35*22% -> 299497000 | H37: =H35*22% -> 301219820 | J37: =J35*22% -> 301219820 | L37: 1518682880 | N37: =N35*22% -> 673328040
A39: Dikurangi - pajak
A40: dibayar di muka :
A41: Pasal 22 | B41: -34089140 | D41: -24522154 | F41: -25660083 | H41: -15505370 | J41: -55018816 | L41: -24522154
A42: Pasal 25 | B42: -421615912 | D42: -316211934 | F42: -41264112 | H42: -158105967 | J42: -65023075 | L42: -316211934
A44: Jumlah Pajak
A45: Penghasilan Dibayar
A46: Dimuka | B46: =SUM(B41:B42) -> -4.5570505e+08 | D46: =SUM(D41:D42) -> -3.4073409e+08 | F46: =SUM(F41:F42) -> -66924195 | H46: =SUM(H41:H42) -> -1.7361134e+08 | J46: =SUM(J41:J42) -> -120041891 | L46: -3.4073409e+08
A48: Taksiran utang pajak | B48: =B37+B46 -> 6.7982605e+08 | D48: =D37+D46 -> 7.2620805e+08 | F48: =F37+F46 -> 232572805 | H48: =H37+H46 -> 1.2760848e+08 | J48: =J37+J46 -> 181177929 | L48: 1.1779488e+09
A49: penghasilan pasal 29

Sheet Kas dan Bank
A2: KAS DAN SETARA BANK
E6: 31 Desember 2024 / | G6: 30 September 2024 / | I6: 31 Desember 2023 /
E7: December, 31 2024 | G7: September, 30 2024 | I7: December, 31 2023
C9: Kas | E9: =WS!J21 -> 1.7274635e+08 | G9: =WS!U21 -> 2.2171753e+08 | I9: =WS!W21 -> 53042125 | K9: Cash
C11: Bank | K11: Cash In Bank
C12: Rupiah | K12: Rupiah
C13: Bank Mandiri | E13: =WS!J24+WS!J25 -> 4433481.2 | G13: =WS!U24+WS!U25 -> 10743438 | I13: =WS!W24+WS!W25 -> 2265171 | K13: Bank Mandiri
C14: Bank Negara Indonesia | E14: =WS!J26+WS!J27 -> 16370106 | G14: =WS!U26+WS!U27 -> 8.1995645e+09 | I14: =WS!W26+WS!W27 -> 1432417 | K14: Bank Negara Indonesia
C15: Bank Jtrust Indonesia | E15: =WS!J28+WS!J29 -> 4640243 | G15: =WS!U28+WS!U29 -> 4875146 | I15: =WS!W28+WS!W29 -> 5823220 | K15: Bank Jtrust Indonesia
C16: Bank Mega Syariah | E16: =WS!J30 -> 683620.96 | G16: =WS!U30 -> 769578.89 | I16: =WS!W30 -> 2098047 | K16: Bank Mega Syariah
C17: Bank BTPN | E17: =WS!J31 -> 67213934 | G17: =WS!U31 -> 46506026 | I17: =WS!W31 -> 30768284 | K17: Bank BTPN
C18: Bank Rakyat Indonesia | E18: =WS!J32 -> 0 | G18: =WS!U32+WS!U33 -> 609796408 | I18: =WS!W32 -> 794277 | K18: Bank Rakyat Indonesia
C20: Sub Jumlah | E20: =SUM(E13:E18) -> 93341385 | G20: =SUM(G13:G18) -> 8.872255e+09 | I20: =SUM(I13:I18) -> 43181416 | K20: Sub Total
C22: Dolar Amerika Serikat | K22: US Dollar
C23: Bank Mandiri | E23: =WS!J35+WS!J36 -> 12106954 | G23: =WS!U35+WS!U36 -> 1707866 | I23: =WS!W35+WS!W36 -> 5747389 | K23: Bank Mandiri
C24: Bank Negara Indonesia | E24: =WS!J37 -> 20695118 | G24: =WS!U37 -> 8592468.9 | I24: =WS!W37 -> 8054849 | K24: Bank Negara Indonesia
C25: Bank Jtrust Indonesia | E25: =WS!J38 -> 8375633.3 | G25: =WS!U38 -> 8142871.9 | I25: =WS!W38 -> 9044094 | K25: Bank Jtrust Indonesia
C26: Bank Mega Syariah | E26: =WS!J39 -> 7152816.3 | G26: =WS!U39 -> 7017523 | I26: =WS!W39 -> 13411920 | K26: Bank Mega Syariah
C27: Bank BTPN | E27: =WS!J40 -> 54182297 | G27: =WS!U40 -> 2276769542 | I27: =WS!W40 -> 2023630252 | K27: Bank BTPN
C28: Bank Rakyat Indonesia | E28: =WS!J41 -> 1460398.3 | G28: =WS!U41 -> 1822011 | I28: =WS!W41 -> 3242911 | K28: Bank Rakyat Indonesia
C30: Sub Jumlah | E30: =SUM(E23:E28) -> 1.0397322e+08 | G30: =SUM(G23:G28) -> 2.3040523e+09 | I30: =SUM(I23:I28) -> 2063131415 | K30: Sub Total
C32: Jumlah | E32: =E9+E20+E30 -> 3.7006095e+08 | G32: =G9+G20+G30 -> 1.1398025e+10 | I32: =I9+I20+I30 -> 2159354956 | K32: Total
C34: Deposito Berjangka | E34: - | G34: - | I34: - | K34: Time Deposit
C35: Deposito Berjangka | E35: - | G35: - | I35: - | K35: Time Deposit
C37: Sub Jumlah
C41: Total Sept 24 | E41: =E9+E20+E30 -> 3.7006095e+08 | G41: =G9+G20+G30 -> 1.1398025e+10 | I41: Total Des 23 | K41: =I9+I20+I30 -> 2159354956
C42: Ctrl | E42: =WS!J43 -> 4.2068222e+08 | G42: =WS!U43 -> 1.1398025e+10 | I42: Ctrl | K42: =WS!W43 -> 2159354956
E43: =E41-E42 -> -50621267 | G43: =G41-G42 -> 0 | K43: =K41-K42 -> 0
C45: Total Des 24 | E45: =E32 -> 3.7006095e+08
C46: Ctrl | E46: =WS!J43 -> 4.2068222e+08

Sheet Piutang Usaha
A2: PIUTANG USAHA
E6: 30 September 2024 / | G6: 31 Desember 2023 /
E7: September, 30 2024 | G7: December, 31 2023
C9: Pihak Berelasi (catatan 34) | I9: Related Party (Note 34)
C10: Rupiah | I10: Rupiah
C11: CV Kanian Persada | E11: =WS!U46 -> 339894481 | G11: =WS!W46 -> 211054410 | I11: CV Kanian Persada
C12: Mochamad Riduwan | E12: =WS!U47 -> 0 | G12: =WS!W47 -> 0 | I12: Mochamad Riduwan
C13: UD, Slamet | E13: =WS!U48 -> 0 | G13: =WS!W48 -> 0 | I13: UD, Slamet
C14: Roda Jaya, Toko | E14: =WS!U49 -> 0 | G14: =WS!W49 -> 0 | I14: Roda Jaya, Toko
C15: Piutang Karyawan | E15: =WS!U50 -> 0 | G15: =WS!W50 -> 1480185 | I15: Piutang Karyawan
C16: Jaduk Prayogi | E16: =WS!U51 -> 0 | G16: =WS!W51 -> 0 | I16: Jaduk Prayogi
C18: Sub Jumlah | E18: =SUM(E11:E16) -> 339894481 | G18: =SUM(G11:G16) -> 212534595 | I18: Sub Total
E21: 30 September 2024 / | G21: 31 Desember 2023 /
E22: September, 30 2024 | G22: December, 31 2023
C24: Dollar Amerika Serikat | I24: US Dollar
C25: Alpha Trading Co. Ltd | E25: =WS!U54 -> 0 | G25: =WS!W54 -> 0 | I25: Alpha Trading Co. Ltd
C26: Censea Inc | E26: =WS!U55 -> 1.6672945e+10 | G26: =WS!W55 -> 8062429256 | I26: Censea Inc
C27: Choice Canning Company Inc, | E27: =WS!U56 -> 0 | G27: =WS!W56 -> 0 | I27: Choice Canning Company Inc,
C28: Crystal Cove Seafoods Corp | E28: =WS!U57 -> 0 | G28: =WS!W57 -> 0 | I28: Crystal Cove Seafoods Corp
C29: Ael Seafood Enterprises, LLC | E29: =WS!U58 -> 0 | G29: =WS!W58 -> 0 | I29: Ael Seafood Enterprises, LLC
C30: Eastern Fish Company LLC | E30: =WS!U59 -> 1353639940 | G30: =WS!W59 -> 1661844800 | I30: Eastern Fish Company LLC
C31: Eiger Co. Ltd | E31: =WS!U60 -> 0.5 | G31: =WS!W60 -> 550050588 | I31: Eiger Co. Ltd
C32: Export Packer Co., Ltd | E32: =WS!U61 -> 0 | G32: =WS!W61 -> 0 | I32: Export Packer Co., Ltd
C33: Monarch Trading, LLC | E33: =WS!U62 -> 0 | G33: =WS!W62 -> 0 | I33: Monarch Trading, LLC
C34: San Sugar Co, , Ltd | E34: =WS!U63 -> 0 | G34: =WS!W63 -> 2028899760 | I34: San Sugar Co, , Ltd
C35: Slade Gorton,,Inc | E35: =WS!U64 -> 3523030954 | G35: =WS!W64 -> 0 | I35: Slade Gorton,,Inc
C36: Yachiyo Corporation | E36: =WS!U65 -> 0 | G36: =WS!W65 -> 624270920 | I36: Yachiyo Corporation
C37: Hohsui Corporation | E37: =WS!U66 -> 0 | G37: =WS!W66 -> 890274000 | I37: Hohsui Corporation
C39: Sub Jumlah | E39: =SUM(E25:E37) -> 21549615914 | G39: =SUM(G25:G37) -> 13817769324 | I39: Sub Total
C41: Jumlah | E41: =E18+E39 -> 21889510395 | G41: =G18+G39 -> 14030303919 | I41: Total
C43: Cadangan Kerugian
C44: Penurunan Nilai | E44: =WS!U77 -> -907026824 | G44: =WS!W77 -> -907026824 | I44: Allowance For Impaiment Losses
C46: Jumlah Bersih | E46: =E41+E44 -> 20982483571 | G46: =G41+G44 -> 13123277095 | I46: Total - Net
C50: Total Sept 24 | E50: =E41 -> 21889510395 | G50: Total Des 23 | I50: =G41 -> 14030303919
C51: Ctrl | E51: =WS!U70 -> 23871074595 | G51: Ctrl | I51: =WS!W70 -> 14030303919
E52: =E50-E51 -> -1981564200 | I52: =I50-I51 -> 0

Sheet Piutang Lain-lain
A2: PIUTANG LAIN-LAIN
E5: 31 Desember 2024 / | G5: 30 September 2024 / | I5: 31 Desember 2023 /
E6: December, 30 2024 | G6: September, 30 2024 | I6: December, 31 2023
C7: Jangka Panjang | K7: Long - Term
C8: Pihak Berelasi | K8: Related Parties
C10: PT Indokom Samudra Persada (Keuangan) | E10: =WS!J83 -> 90952571551 | G10: =WS!U83 -> 94963698422 | I10: =WS!W83 -> 132646777153 | K10: PT Indokom Samudra Persada (Finance)
C11: PT Irian Marine Product Development | E11: =WS!J84 -> 222225120 | G11: =WS!U84 -> 0 | I11: =WS!W84 -> 0 | K11: PT Irian Marine Product Development
C12: CV Kanian Persada | E12: =WS!J85 -> 0 | G12: =WS!U85 -> 0 | I12: =WS!W85 -> 512207423 | K12: CV Kanian Persada
C13: Piutang Lain-Lain (PPN Jasa LN) | E13: =WS!J87 -> 0 | G13: =WS!U87 -> 0 | I13: =WS!W87 -> 0 | K13: Piutang Lain-Lain (PPN Jasa LN)
C14: Jumlah Bersih | E14: =SUM(E10:E13) -> 91174796671 | G14: =SUM(G10:G13) -> 94963698422 | I14: =SUM(I10:I13) -> 133158984576 | K14: Sub Total
C18: Total Sept 24 | E18: =E14 -> 91174796671 | G18: =G14 -> 94963698422 | I18: Total Des 23 | K18: =I14 -> 133158984576
C19: Ctrl | E19: =WS!J90 -> 91174796671 | G19: =WS!U90 -> 94963698422 | I19: Ctrl | K19: =WS!W90 -> 133158984576
E20: =E18-E19 -> 0 | G20: =G18-G19 -> 0 | K20: =K18-K19 -> 0
C22: Total Des 24 | E22: =E14 -> 91174796671
C23: Ctrl | E23: =WS!J90 -> 91174796671
E24: =E22-E23 -> 0

Sheet Persediaan
A2: PERSEDIAAN
E5: 31 Desember 2024 / | G5: 30 September 2024 / | I5: 31 Desember 2023 /
E6: December, 31 2024 | G6: September, 30 2024 | I6: December, 31 2023
C8: Bahan Pembantu | E8: =WS!J92 -> 16305238543 | G8: =WS!U92 -> 2.0674774e+10 | I8: =WS!W92 -> 16305238543 | K8: Supplementary Materials
C9: Bahan Bakar | E9: =WS!J93 -> 76848942 | G9: =WS!U93 -> 34860373 | I9: =WS!W93 -> 76848942 | K9: Fuels
C10: Persediaan Udang (Barang Jadi) | E10: =WS!J94 -> 97064513093 | G10: =WS!U94 -> 1.0849051e+11 | I10: =WS!W94 -> 88132546606 | K10: Inventories Shrimp
C11: Persediaan Breaded (Barang Jadi) | E11: =WS!J95 -> 3808188569 | G11: =WS!U95 -> 6.1299385e+09 | I11: =WS!W95 -> 3808188569 | K11: Inventories Breaded
C13: Jumlah | E13: =SUM(E8:E11) -> 117254789147 | G13: =SUM(G8:G11) -> 1.3533008e+11 | I13: =SUM(I8:I11) -> 108322822660
C17: Total Sept 24 | E17: =E13 -> 117254789147 | G17: =G13 -> 1.3533008e+11 | I17: Total Des 23 | K17: =I13 -> 108322822660
C18: Ctrl | E18: =WS!J97 -> 117254789147 | G18: =WS!U97 -> 1.3533008e+11 | I18: Ctrl | K18: =WS!W97 -> 108322822660
E19: =E17-E18 -> 0 | G19: =G17-G18 -> 0 | K19: =K17-K18 -> 0
C21: Total Des 24 | E21: =E13 -> 117254789147
C22: Ctrl | E22: =WS!J97 -> 117254789147
E23: =E21-E22 -> 0

Sheet Investasi Pada Entitas Asosiasi
A2: INVESTASI PADA ENTITAS ASOSIASI
E5: 31 Desember 2024 / | G5: 30 September 2024 / | I5: 31 Desember 2023 /
E6: December, 31 2024 | G6: September, 30 2024 | I6: December, 31 2023
C7: PT Indokom Samudra Persada | E7: =WS!JP141 -> 0 | G7: =WS!U141 -> 1050000000 | I7: =WS!W141 -> 1050000000 | K7: PT Indokom Samudra Persada
C9: Jumlah | E9: =E7 -> 0 | G9: =G7 -> 1050000000 | I9: =I7 -> 1050000000 | K9: Total

Sheet Utang Usaha
A2: UTANG USAHA
E4: 31 December 2024 / | G4: 30 September 2024 / | I4: 31 Desember 2023 /
E5: December, 31 2024 | G5: September, 30 2024 | I5: December, 31 2023
C6: PT Anesta Agung | E6: =WS!J177 -> 4.9440145e+08 | G6: =WS!U177 -> 2.8762729e+08 | I6: =WS!W177 -> 0 | K6: PT Anesta Agung
C7: Choice Canning Company Inc, | E7: =WS!J178 -> 0 | G7: =WS!U178 -> 0 | I7: =WS!W178 -> 1356603529 | K7: Choice Canning Company Inc,
C8: PT Anugerah Berkah Usaha | E8: =WS!J179 -> 0 | G8: =WS!U179 -> 0 | I8: =WS!W179 -> 0 | K8: PT Anugerah Berkah Usaha
C9: PT Delos Rantai Maritim | E9: =WS!J180 -> 0 | G9: =WS!U180 -> 0 | I9: =WS!W180 -> 0 | K9: PT Delos Rantai Maritim
C10: PT International Packaging Manufacturing | E10: =WS!J181 -> 0 | G10: =WS!U181 -> 0 | I10: =WS!W181 -> 668830500 | K10: PT International Packaging Manufacturing
C11: Tn. Agus Sujono | E11: =WS!J182 -> 0 | G11: =WS!U182 -> 0 | I11: =WS!W182 -> 0 | K11: Tn. Agus Sujono
C12: PT Konverta Mitra Abadi | E12: =WS!J183 -> 3.381468e+08 | G12: =WS!U183 -> 5.0030583e+08 | I12: =WS!W183 -> 304771930 | K12: PT Konverta Mitra Abadi
C13: CV Mekar Karya Mulia | E13: =WS!J184 -> 0 | G13: =WS!U184 -> 0 | I13: =WS!W184 -> 0 | K13: CV Mekar Karya Mulia
C14: Prima Larvae, PT | E14: =WS!J185 -> 0 | G14: =WS!U185 -> 0 | I14: =WS!W185 -> 0 | K14: Prima Larvae, PT
C15: RBFood Manufaktur Indonesia, PT | E15: =WS!J186 -> 0 | G15: =WS!U186 -> 0 | I15: =WS!W186 -> 0 | K15: RBFood Manufaktur Indonesia, PT
C16: PT RBFood Supply Indonesia | E16: =WS!J187 -> 0 | G16: =WS!U187 -> 64380000 | I16: =WS!W187 -> 0 | K16: PT RBFood Supply Indonesia
C17: Mitra Lestari Mandiri | E17: =WS!J188 -> 0 | G17: =WS!U188 -> 0 | I17: =WS!W188 -> 0 | K17: Mitra Lestari Mandiri
... C47: Ahmad Heriyadi | E47: =WS!J218 -> 0 | G47: =WS!U218 -> 0 | I47: =WS!W218 -> 0 | K47: Ahmad Heriyadi
C48: Global Babel Maritim, PT | E48: =WS!J220 -> 0 | G48: =WS!U220 -> 0 | I48: =WS!W220 -> 0 | K48: Global Babel Maritim, PT
C49: Maju Tambak Sumur, PT | E49: =WS!J221 -> 1.9958524e+08 | G49: =WS!U221 -> 4.710044e+08 | I49: =WS!W221 -> 0 | K49: Maju Tambak Sumur, PT
C50: Mekar Karya Mulia, CV | E50: =WS!J222 -> 0 | G50: =WS!U222 -> 0 | I50: =WS!W222 -> 0 | K50: Mekar Karya Mulia, CV
C51: Multi Daya Teknologi Nusantara, PT | E51: =WS!J223 -> 0 | G51: =WS!U223 -> 0 | I51: =WS!W223 -> 0 | K51: Multi Daya Teknologi Nusantara, PT
C52: Optimis Group, CV | E52: =WS!J224 -> 0 | G52: =WS!U224 -> 0 | I52: =WS!W224 -> 0 | K52: Optimis Group, CV
C53: Sedulur Bertiga Jaya, PT | E53: =WS!J225 -> 0 | G53: =WS!U225 -> 0 | I53: =WS!W225 -> 0 | K53: Sedulur Bertiga Jaya, PT
C54: Lain-lain (masing-masing di bawah Rp 20.000.000) | E54: =WS!J235 -> 154256572 | G54: =WS!U235 -> 560155511 | I54: =WS!W235 -> 657394820 | K54: Lain-lain (masing-masing di bawah Rp 20.000.000)
C56: Jumlah | E56: =SUM(E6:E54) -> 3.4877215e+09 | G56: =SUM(G6:G54) -> 3.265335e+09 | I56: =SUM(I6:I54) -> 12029137713 | K56: Total
C62: Total Sept 24 | E62: =E56 -> 3.4877215e+09 | G62: =G56 -> 3.265335e+09 | I62: Total Des 23 | K62: =I56 -> 12029137713
C63: Ctrl | E63: =WS!J237 -> 4.2917358e+09 | G63: =WS!U237 -> 3.7095089e+09 | I63: Ctrl | K63: =WS!W237 -> 12029137713
E64: =E62-E63 -> -8.0401424e+08 | G64: =G62-G63 -> -4.4417388e+08 | K64: =K62-K63 -> 0
C66: Total Des 24 | E66: =E56 -> 3.4877215e+09
C67: Ctrl | E67: =WS!J237 -> 4.2917358e+09
E68: =E66-E67 -> -8.0401424e+08

Sheet Utang Lain-lain
A2: UTANG LAIN-LAIN
E5: 31 Desember 2024 / | G5: 30 September 2024 / | I5: 31 Desember 2023 /
E6: December, 31 2024 | G6: September, 30 2024 | I6: December, 31 2023
C7: Liabilitas Jangka Panjang
C8: Pihak Berelasi
C9: PT Indo American Food | E9: =WS!J246 -> 0 | G9: =WS!U246 -> 0 | I9: =WS!W246 -> 0 | K9: PT Indo American Food
C10: Ibnu Syena Alfitra | E10: =WS!J247 -> 0 | G10: =WS!U247 -> 0 | I10: =WS!W247 -> 0 | K10: Ibnu Syena Alfitra
C12: Sub Jumlah | E12: =SUM(E9+E10) -> 0 | G12: =SUM(G9+G10) -> 0 | I12: =I9+I10 -> 0 | K12: Sub Total

Sheet Beban Akrual
A2: BEBAN AKRUAL
E6: 31 Desember 2024 / | G6: 30 September 2024 / | I6: 31 Desember 2023 /
E7: December, 31 2024 | G7: September, 30 2024 | I7: December, 31 2023
C8: Angkut | E8: =WS!J268 -> 9.712638e+08 | G8: =WS!U268 -> 1.4550929e+09 | I8: =WS!W268 -> 218666237 | K8: Freight
C9: Gaji | E9: =WS!J273+WS!J272 -> 176024983 | G9: =WS!U273+WS!U272 -> 353778404 | I9: =WS!W272+WS!W273 -> 251154963 | K9: Salaries Expenses
C10: Utilitas | E10: =WS!J269 -> 285002677 | G10: =WS!U269 -> 360602937 | I10: =WS!W269 -> 295442667 | K10: Utilities
C11: Jasa Profesional | E11: =WS!J271 -> 107888220 | G11: =WS!U271 -> 106838220 | I11: =WS!W271 -> 149562738 | K11: Professional Fees
C12: Analisa/Uji | E12: =WS!J270 -> 0 | G12: =WS!U270 -> 3330000 | I12: =WS!W270 -> 349650 | K12: Analysis/Test
C13: Pemeliharaan & Perbaikan | E13: =WS!J275 -> 5365000 | G13: =WS!U275 -> 11520000 | I13: =WS!W275 -> 3865000 | K13: Maintenance & Repair
C14: Lain-lain | E14: =WS!J276 -> 18407701 | G14: =WS!U276 -> 18019201 | I14: =WS!W276 -> 18295786 | K14: Others
C16: Jumlah | E16: =SUM(E8:E14) -> 1.5639524e+09 | G16: =SUM(G8:G14) -> 2.3091817e+09 | I16: =SUM(I8:I14) -> 937337041 | K16: Total
C19: Total Sept 24 | E19: =E16 -> 1.5639524e+09 | G19: =G16 -> 2.3091817e+09 | I19: Total Des 23 | K19: =I16 -> 937337041
C20: Ctrl | E20: =WS!J278-WS!J274 -> 1.5639524e+09 | G20: =WS!U278-WS!U274 -> 2.3091817e+09 | I20: Ctrl | K20: =WS!W278-WS!W274 -> 937337041
E21: =E19-E20 -> 0 | G21: =G19-G20 -> 0 | K21: =K19-K20 -> 0
C23: Total Des 24 | E23: =E16 -> 1.5639524e+09
C24: Ctrl | E24: =WS!J278-WS!J274 -> 1.5639524e+09
E25: =E23-E24 -> 0

Sheet Pajak
A2: PERPAJAKAN
C4: a. Pajak Dibayar Dimuka
E6: 31 Desember 2024 / | G6: 30 September 2024 / | I6: 31 Desember 2023 /
E7: December, 31 2024 | G7: September, 30 2024 | I7: December, 31 2023
C8: Pajak Pertambahan | K8: Vallue Added Tax-Net
C9: Nilai-Bersih | E9: =WS!J99 -> 8.2867979e+09 | G9: =WS!U99 -> 7.9056405e+09 | I9: =WS!W99 -> 6709080953
C11: Jumlah | E11: =E9 -> 8.2867979e+09 | G11: =G9 -> 7.9056405e+09 | I11: =I9 -> 6709080953 | K11: Total
C13: b. Utang Pajak
E14: 31 Desember 2024 / | G14: 30 September 2024 / | I14: 31 Desember 2023 /
E15: December, 31 2024 | G15: September, 30 2024 | I15: December, 31 2023
C16: Entitas Induk : | K16: Parent Entity
C17: Pajak Penghasilan : | K17: Income Tax :
C18: Pasal 21 | E18: =WS!J250 -> 0 | G18: =WS!U250 -> 4471644 | I18: =WS!W250 -> 2811914 | K18: Article 21
C19: Pasal 22 | E19: =WS!J252 -> 28121848 | G19: =WS!U252 -> 88055762 | I19: =WS!W252 -> 32841996 | K19: Article 22
C20: Pasal 23 | E20: =WS!J253 -> 21674006 | G20: =WS!U253 -> 20541362 | I20: =WS!W253 -> 8898796 | K20: Article 23
C21: Pasal 25 | E21: =WS!J254 -> 0 | G21: =WS!U254 -> 52701989 | I21: =WS!W254 -> 13754704 | K21: Article 25
C22: Pasal 4 (2) | E22: =WS!J255 -> 1775555.1 | G22: =WS!U255 -> 0 | I22: =WS!W255 -> 0 | K22: Article 4(2)
C23: Pasal 29 : | K23: Article 29:
C24: Tahun 2021 | E24: =WS!J262 -> 0 | G24: =WS!U262 -> 0 | I24: =WS!W262 -> 0 | K24: Year 2021
C25: Tahun 2022 | E25: =WS!J263 -> 0 | G25: =WS!U263 -> 0 | I25: =WS!W263 -> 1063969216 | K25: Year 2022
C26: Tahun 2023 | E26: =WS!J264 -> 0 | G26: =WS!U264 -> 0 | I26: =WS!W264 -> 5.7740505e+08 | K26: Year 2023
C27: September 2024 | K27: September 2024
C28: (Estimasi) | K28: (Estimate)
C30: Jumlah | E30: =SUM(E18:E27) -> 51571409 | G30: =SUM(G18:G27) -> 165770757 | I30: =SUM(I18:I27) -> 1.6996817e+09 | K30: Total
C33: c. Beban Pajak Penghasilan - Bersih
E34: 31 Desember 2024 / | G34: 30 September 2024 / | I34: 31 Desember 2023 /
E35: December, 31 2024 | G35: September, 30 2024 | I35: December, 31 2023
C36: Beban Pajak Kini | E36: =WS!J489 -> 1135531100 | G36: =WS!U489 -> 1066942140 | I36: =WS!W489 -> 6.7332782e+08 | K36: Current Tax Expense
C37: Manfaat Pajak | K37: Deffered Tax
C38: Tangguhan | E38: =WS!J492 -> 0 | G38: =WS!U492 -> 0 | I38: =WS!W492 -> -61828681 | K38: Benefit
C40: Jumlah | E40: =SUM(E36:E38) -> 1135531100 | G40: =SUM(G36:G38) -> 1066942140 | I40: =SUM(I36:I38) -> 6.1149914e+08 | K40: Total
C44: Total Sept 24 (a) | E44: =E11 -> 8.2867979e+09 | G44: =G11 -> 7.9056405e+09 | I44: Total Des 23 | K44: =I11 -> 6709080953
C45: Ctrl | E45: =WS!U99 -> 7.9056405e+09 | G45: =WS!W99 -> 6709080953 | I45: Ctrl | K45: =WS!W99 -> 6709080953
E46: =E44-E45 -> 3.8115736e+08 | G46: =G44-G45 -> 1.1965596e+09 | K46: =K44-K45 -> 0
C48: Total Sept 24 (b) | E48: =E30 -> 51571409 | G48: =G30 -> 165770757 | I48: Total Des 23 | K48: =I30 -> 1.6996817e+09
C49: Ctrl | E49: =WS!U266 -> 4.0638813e+09 | G49: =WS!W266 -> 1.6996817e+09 | I49: Ctrl | K49: =WS!W266 -> 1.6996817e+09
E50: =E48-E49 -> -4.0123099e+09 | G50: =G48-G49 -> -1.5339109e+09 | K50: =K48-K49 -> 0
C52: Total Sept 24 (c) | E52: =E40 -> 1135531100 | G52: =G40 -> 1066942140 | I52: Total Des 23 | K52: =I40 -> 6.1149914e+08
C53: Ctrl | E53: =WS!S493 -> 0 | G53: =WS!U493 -> 1066942140 | I53: Ctrl | K53: =WS!W493 -> 6.1149914e+08
E54: =E52-E53 -> 1135531100 | G54: =G52-G53 -> 0 | K54: =K52-K53 -> 0
C55: Total Des 24 (a) | E55: =E30 -> 51571409
C56: Ctrl | E56: =WS!J266 -> 7.3139746e+08
E57: =E55-E56 -> -6.7982605e+08
C59: Total Des 24 (b) | E59: =E30 -> 51571409
C60: Ctrl | E60: =WS!J266 -> 7.3139746e+08
E61: =E59-E60 -> -6.7982605e+08
C63: Total Des 24 (c) | E63: =E40 -> 1135531100
C64: Ctrl

Sheet Utang Bank
A2: UTANG BANK
C5: a. Utang Bank Jangka Pendek
C7: Entitas Induk
E9: 31 Desember 2024 / | G9: 30 September 2024 / | I9: 31 Desember 2023 /
E10: December, 31 2024 | G10: September, 30 2024 | I10: December, 31 2023
C11: APF IDR BTPN | E11: =WS!J169 -> 44349698871 | G11: =WS!U169 -> 24548186154 | I11: =WS!W169 -> 27745785208 | K11: APF IDR BTPN
C12: APF IDR BTPN TO | E12: =WS!J170 -> 0 | G12: =WS!U170 -> 0 | I12: =WS!W170 -> 33713322258 | K12: APF IDR BTPN TO
C13: APF USD BTPN TO | E13: =WS!J171 -> 0 | G13: =WS!U171 -> 0 | I13: =WS!W171 -> 29290400000 | K13: APF USD BTPN TO
C14: ARF BTPN | E14: =WS!J172 -> 27588534000 | G14: =WS!U172 -> 30967888000 | I14: =WS!W172 -> 15924728000 | K14: ARF BTPN
C15: PSF USD BTPN | E15: =WS!J173 -> 32324000000 | G15: =WS!U173 -> 22648665000 | I15: =WS!W173 -> 20494030400 | K15: PSF USD BTPN
C16: RCF IDR BTPN | E16: =WS!J174 -> 22350000000 | G16: =WS!U174 -> 22000000000 | I16: =WS!W174 -> 8600000000 | K16: RCF IDR BTPN
C18: Sub Jumlah | E18: =SUM(E11:E16) -> 126612232871 | G18: =SUM(G11:G16) -> 100164739154 | I18: =SUM(I11:I16) -> 135768265866 | K18: Sub Total
C21: Total Sept 24 | E21: =E18 -> 126612232871 | G21: =G18 -> 100164739154 | I21: Total Des 23 | K21: =I18 -> 135768265866
C22: Ctrl | E22: =WS!S175 -> 0 | G22: =WS!U175 -> 100164739154 | I22: Ctrl | K22: =WS!W175 -> 135768265866
E23: =E21-E22 -> 126612232871 | G23: =G21-G22 -> 0
C25: Total Des 24 | E25: =E18 -> 126612232871
C26: Ctrl | E26: =WS!J175 -> 126612232871
E27: =E25-E26 -> 0

Sheet Pajak Tangguhan
A2: PAJAK TANGGUHAN
E6: 31 Desember 2024 / | G6: 30 September 2024 / | I6: 31 Desember 2023 /
E7: December, 31 2024 | G7: September, 30 2024 | I7: December, 31 2023
C8: Imbalan Kerja | E8: =WS!J146 -> 1.435029e+08 | G8: =WS!U146 -> 1.435029e+08 | I8: =WS!W146 -> 1.435029e+08 | K8: Employee Benefits
C9: Cadangan Kerugian Piutanng Penyusutan | E9: =WS!J145 -> 1.5052986e+08 | G9: =WS!U145 -> 1.5052986e+08 | I9: =WS!W145 -> 1.5052986e+08 | K9: Allowance for Impairment Losses
C10: Penyusutan | E10: =-WS!J148 -> -51462970 | G10: =-WS!U148 -> -51462970 | I10: =-WS!W148 -> -51462970 | K10: Depreciation
C12: Aset Pajak Tangguhan | E12: =SUM(E8:E9)+E10 -> 2.4256979e+08 | G12: =SUM(G8:G9)+G10 -> 2.4256979e+08 | I12: =SUM(I8:I9)+I10 -> 2.4256979e+08 | K12: Deferred Tax Assets
C16: Total Sept 24 | E16: =E12 -> 2.4256979e+08 | G16: =G12 -> 2.4256979e+08 | I16: Total Des 23 | K16: =I12 -> 2.4256979e+08
C17: Ctrl | E17: =WS!S149 -> 0 | G17: =WS!U149 -> 2.4256979e+08 | I17: Ctrl | K17: =WS!W149 -> 2.4256979e+08
E18: =E16-E17 -> 2.4256979e+08 | G18: =G16-G17 -> 0 | K18: =K16-K17 -> 0
C20: Total Des 24 | E20: =E12 -> 2.4256979e+08
C21: Ctrl | E21: =WS!J149 -> 2.4256979e+08
E22: =E20-E21 -> 0

Sheet Beban Umum & Administrasi
A2: BEBAN UMUM DAN ADMINISTRASI
E5: 31 Desember 2024 / | G5: 30 September 2024 / | I5: 31 Desember 2023 /
E6: December, 31 2024 | G6: September, 30 2024 | I6: December, 31 2023
C7: Gaji dan Tunjangan | K7: Salaries and benefits
C8: BPJS/ Jamsostek | E8: =WS!J419 -> 313949059 | G8: =WS!U419 -> 270332060 | I8: =WS!W419 -> 326651463 | K8: BPJS/ Jamsostek
C9: Gaji Karyawan Kantor | E9: =WS!J420 -> 3962378187 | G9: =WS!U420 -> 2892243979 | I9: =WS!W420 -> 3836346543 | K9: Office Employee Salaries
C10: Tunjangan Hari Raya | E10: =WS!J421 -> 332597853 | G10: =WS!U421 -> 332597853 | I10: =WS!W421 -> 341934529 | K10: Holiday Allowance
C11: Tunjangan Karyawan | E11: =WS!J422 -> 432045000 | G11: =WS!U422 -> 339109000 | I11: =WS!W422 -> 381155000 | K11: Employee Benefits
C12: Pesangon | E12: =WS!J423 -> 0 | G12: =WS!U423 -> 0 | I12: =WS!W423 -> 0 | K12: Severance Pay
C13: Penyusutan | E13: =WS!J456+WS!J457+WS!J458+WS!J459+WS!J460+WS!J461+WS!J462+WS!J463+WS!J464 -> 10112250 | G13: =WS!U456+WS!U457+WS!U458+WS!U459+WS!U460+WS!U461+WS!U462+WS!U463+WS!U464 -> 1.6664796e+08 | I13: =WS!W456+WS!W457+WS!W458+WS!W459+WS!W460+WS!W461+WS!W462+WS!W463+WS!W464 -> 223075091 | K13: Depreciation
C14: Administrasi & Umum Lainnya | E14: =WS!J425 -> 1343058 | G14: =WS!U425 -> 1293058 | I14: =WS!W425 -> 570000 | K14: General and Administrative
C15: Pemeliharaan dan Perbaikan | E15: =WS!S449+WS!S450+WS!S451+WS!S452+WS!S453+WS!S454 -> 0 | G15: =WS!U449+WS!U450+WS!U451+WS!U452+WS!U453+WS!U454 -> 395807726 | I15: =WS!W449+WS!W450+WS!W451+WS!W452+WS!W453+WS!W454 -> 537341899 | K15: Maintenance and Repair
C16: Alat Tulis Kantor | E16: =WS!J426 -> 20121300 | G16: =WS!U426 -> 16530500 | I16: =WS!W426 -> 27120300 | K16: Office Stationery
C17: Asuransi | E17: =WS!J427 -> 111024837 | G17: =WS!U427 -> 80745336 | I17: =WS!W427 -> 137236872 | K17: Insurance
C18: BBM Kendaraan Kantor | E18: =WS!J428 -> 144047264 | G18: =WS!U428 -> 105481619 | I18: =WS!W428 -> 138181751 | K18: Office Vehicle Fuel
C19: Entertainment & Sumbangan | E19: =WS!J429 -> 1750000 | G19: =WS!U429 -> 1750000 | I19: =WS!W429 -> 4610000 | K19: Entertainment and Donations
C20: Keamanan/Outsourcing | E20: =WS!J430 -> 494527864 | G20: =WS!U430 -> 370520898 | I20: =WS!W430 -> 487203054 | K20: Outsourcing
C21: Materai, Koran & Majalah | E21: =WS!J431 -> 1985000 | G21: =WS!U431 -> 2690000 | I21: =WS!W431 -> 0 | K21: Stamps, Newspapers and Magazines
C22: Meals Traveling | E22: =WS!J432 -> 66151774 | G22: =WS!U432 -> 45624644 | I22: =WS!W432 -> 60574758 | K22: Meals Traveling
C23: Ongkos Angkut | E23: =WS!J433 -> 95443972 | G23: =WS!U433 -> 70172940 | I23: =WS!W433 -> 114566201 | K23: Freight Costs
C24: Pajak Lain-Lain | E24: =WS!J434 -> 5869396531 | G24: =WS!U434 -> 5.8645545e+09 | I24: =WS!W434 -> 59045957 | K24: Others Tax
C25: Parkir Tol Fee Dll | E25: =WS!J435 -> 48008000 | G25: =WS!U435 -> 36022500 | I25: =WS!W435 -> 27965250 | K25: Parking Toll Fees etc
C26: Pendidikan & Pelatihan | E26: =WS!J436 -> 9081632.2 | G26: =WS!U436 -> 0 | I26: =WS!W436 -> 0 | K26: Education and Training
C27: Pengobatan | E27: =WS!J437 -> 0 | G27: =WS!U437 -> 0 | I27: =WS!W437 -> 0 | K27: Medical
... C37: Biaya Lain-lain | E37: =WS!J447 -> 0 | G37: =WS!U447 -> 0 | I37: =WS!W447 -> 0 | K37: Cost Others
C39: Jumlah | E39: =SUM(E8:E37) -> 1.4312433e+10 | G39: =SUM(G8:G37) -> 1.3159815e+10 | I39: =SUM(I8:I37) -> 8581798722 | K39: Total
C43: Total Sept 24 | E43: =E39 -> 1.4312433e+10 | G43: =G39 -> 1.3159815e+10 | I43: Total Des 23 | K43: =I39 -> 8581798722
C44: Ctrl | E44: =WS!S465 -> 0 | G44: =WS!U465 -> 1.3159815e+10 | I44: Ctrl | K44: =WS!W465 -> 8581798722
E45: =E43-E44 -> 1.4312433e+10 | G45: =G43-G44 -> 0 | K45: =K43-K44 -> 0
C47: Total Des 24 | E47: =E39 -> 1.4312433e+10
C48: Ctrl

Sheet Beban Bunga dan Keuangan
A2: BEBAN BUNGA DAN KEUANGAN
E6: 31 Desember 2024 / | G6: 30 September 2024 / | I6: 31 Desember 2023 /
E7: December, 31 2024 | G7: September, 30 2024 | I7: December, 31 2023
C8: Beban Administrasi Bank | E8: =WS!J476 -> 74572923 | G8: =WS!U476 -> 49376357 | I8: =WS!W476 -> 1.8032211e+08 | K8: Bank Administrative
C9: Beban Pajak Jasa Giro | E9: =WS!J477 -> 14686913 | G9: =WS!U477 -> 14108709 | I9: =WS!W477 -> 13516147 | K9: Tax Expenses Profit (Loss) from Exchange
C10: Beban Provisi Bank | E10: =WS!J478 -> 169215000 | G10: =WS!U478 -> 0 | I10: =WS!W478 -> 0 | K10: Bank Provision Expenses
C11: Denda | E11: =WS!J479 -> 0 | G11: =WS!U479 -> 0 | I11: =WS!W479 -> 0 | K11: Fine
C12: Estimasi Denda Pajak | E12: =WS!J480 -> 0 | G12: =WS!U480 -> 0 | I12: =WS!W480 -> 0 | K12: Estimated Tax Penalties
C13: Beban Bunga/Keuangan | E13: =WS!J481 -> 9984777061 | G13: =WS!U481 -> 6639200650 | I13: =WS!W481 -> 9144417786 | K13: Interest/Finance Expenses
C14: Beban Bunga Leasing | E14: =WS!J482 -> 5239977 | G14: =WS!U482 -> 4288654 | I14: =WS!W482 -> 14124706 | K14: Leasing Interest Expense
C15: Beban Cadangan kerugian Penurunan Nilai | E15: =WS!J483 -> -8.2419978e+08 | G15: =WS!U483 -> 0 | I15: =WS!W483 -> 0 | K15: Allowance for Inventroy Decline to markert Expense
C16: Lain-Lain - Neto | E16: =WS!J484 -> 0 | G16: =WS!U484 -> 0 | I16: =WS!W484 -> 0 | K16: Net Others
C18: Jumlah | E18: =SUM(E8:E16) -> 9.4242921e+09 | G18: =SUM(G8:G16) -> 6.7069744e+09 | I18: =SUM(I8:I16) -> 9.3523807e+09 | K18: Total
C21: Total Sept 24 | E21: =E18 -> 9.4242921e+09 | G21: =G18 -> 6.7069744e+09 | I21: Total Des 23 | K21: =I18 -> 9.3523807e+09
C22: Ctrl | E22: =WS!S485 -> 0 | G22: =WS!U485 -> 6.7069744e+09 | I22: Ctrl | K22: =WS!W485 -> 9.3523807e+09
E23: =E21-E22 -> 9.4242921e+09 | G23: =G21-G22 -> 0 | K23: =K21-K22 -> 0
C26: Total Des 24 | E26: =E18 -> 9.4242921e+09
C27: Ctrl

Sheet Pendapatan
A2: PENDAPATAN
E4: 31 Desember 2024 / | G4: 30 September 2024 / | I4: 31 Desember 2023 /
E5: December, 31 2024 | G5: September, 30 2024 | I5: December, 31 2023
C6: Pendapatan Bunga | E6: =WS!J470 -> 70634245 | G6: =WS!U470 -> 69022353 | I6: =WS!W470 -> 65659825 | K6: Interest Income
C7: Laba (Rugi) Selisih Kurs - Neto | E7: =WS!J471 -> -1.6749565e+09 | G7: =WS!U471 -> 1.5785955e+09 | I7: =WS!W471 -> -566637806 | K7: Rate Differences - Net
C8: Beban Cadangan kerugian Penurunan Nilai | E8: =WS!J472 -> 0 | G8: =WS!U472 -> 0 | I8: =WS!W472 -> -119304064 | K8: Allowence for Impairment Losses Cost
C9: Pendapatan Lain-Lain | E9: =WS!J473 -> -8183754 | G9: =WS!U473 -> 0 | I9: =WS!W473 -> 19197314 | K9: Other Income
C11: Jumlah | E11: =SUM(E6:E9) -> -1.612506e+09 | G11: =SUM(G6:G9) -> 1.6476179e+09 | I11: =SUM(I6:I9) -> -601084731
C15: Total Sept 24 | E15: =E11 -> -1.612506e+09 | G15: =G11 -> 1.6476179e+09 | I15: Total Des 23 | K15: =I11 -> -601084731
C16: Ctrl | E16: =WS!S474 -> 0 | G16: =WS!U474 -> 1.6476179e+09 | I16: Ctrl | K16: =WS!W474 -> -601084731
E17: =E15-E16 -> -1.612506e+09 | G17: =G15-G16 -> 0 | K17: =K15-K16 -> 0
C19: Total Des 24 | E19: =E11 -> -1.612506e+09
C20: Ctrl

Sheet Liabilitas Imbalan PascaKerja
A2: LIABILITAS IMBALAN PASKA KERJA
E6: 31 Desember 2024 / | G6: 30 September 2024 / | I6: 31 Desember 2023 /
E7: December, 31 2024 | G7: September, 30 2024 | I7: December, 31 2023
C8: Liabilitas Imbalan Paska Kerja | E8: =WS!J291 -> 2647745936 | G8: =WS!U291 -> 2857433432 | I8: =WS!W291 -> 2647745936 | K8: Post Employment Benefits Liabilities
C10: Saldo Akhir Liabilitas | E10: =E8 -> 2647745936 | G10: =G8 -> 2857433432 | I10: =I8 -> 2647745936 | K10: Ending Balance of Liabilities

Sheet Penghasilan Komprehensif Lain
A2: PENGHASILAN KOMPREHENSIF LAIN
E6: 31 Desember 2024 / | G6: 30 September 2024 / | I6: 31 Desember 2023 /
E7: December, 31 2024 | G7: September, 30 2024 | I7: December, 31 2023
C9: =WS!B325 -> Pengukuran Kembali Program Imbalan Pasti | E9: =WS!J325 -> -478590506 | G9: =WS!U325 -> -478590506 | I9: =WS!W325 -> -478590506 | K9: Remeasurement of Defined Benefit
C10: =WS!B324 -> Penghasilan Komprehensif Lain Surplus Revaluasi Aset Tetap | E10: =WS!J324 -> -4195684.7 | G10: =WS!U324 -> -4195684.7 | I10: =WS!W324 -> -4195684.7 | K10: Other Comprehensive Income Fixed Asset Revaluation Surplus
C12: Jumlah | E12: =SUM(E9:E10) -> -4.8278619e+08 | G12: =SUM(G9:G10) -> -4.8278619e+08 | I12: =SUM(I9:I10) -> -4.8278619e+08 | K12: Total
C16: Total Des 24 | D16: =E12 -> -4.8278619e+08
C17: Ctrl | D17: =WS!J326 -> -4.8278619e+08
D18: =D16-D17 -> 0
C20: Total Sept 24 | D20: =G12 -> -4.8278619e+08
C21: Ctrl | D21: =WS!U326 -> -4.8278619e+08
D22: =D20-D21 -> 0
C24: Total Des 23 | D24: =I12 -> -4.8278619e+08
C25: Ctrl | D25: =WS!W326 -> -4.8278619e+08
D26: =D24-D25 -> 0
