Workbook
Name \a: [1]JUL!#REF!
Name \APR: #REF!
Name \AUG: #REF!
Name \b: [2]T.B!#REF!
Name \BCYTD: '[3]CF WORKSHEET'!#REF!
Name \BRYTD: #REF!
Name \BSYTD: #REF!
Name \BTWO: #REF!
Name \BUYTD: #REF!
Name \C: #REF!
Name \CTWO: #REF!
Name \d: [2]T.B!#REF!
Name \DEC: #REF!
Name \DTWO: #REF!
Name \E: [4]SMITH!#REF!
Name \F: [4]SMITH!#REF!
Name \FEB: #REF!
Name \JAN: #REF!
Name \m: [2]T.B!#REF!
Name \MAR: #REF!
Name \MAY: #REF!
Name \NOV: #REF!
Name \OCT: #REF!
Name \p: #REF!
Name \r: #REF!
Name \s: #REF!
Name \SEP: #REF!
Name \T: '[3]CF WORKSHEET'!#REF!
Name \T2: '[5]ban-ling'!#REF!
Name \u: #REF!
Name \Z: #REF!
Name ___________DAT1: [6]K.6DEPOSIT!#REF!
Name __________DAT1: [6]K.6DEPOSIT!#REF!
Name __________xlnm.Print_Titles_1: #REF!
Name _________DAT1: [6]K.6DEPOSIT!#REF!
Name _________KD1: #REF!
Name _________KD2: #REF!
Name _________KD3: #REF!
Name _________KD4: #REF!
Name _________KD5: #REF!
Name _________KE1: #REF!
Name _________KE2: #REF!
Name _________KE3: #REF!
Name _________KE4: #REF!
Name _________KE5: #REF!
Name _________KF1: #REF!
Name _________KF2: #REF!
Name _________KF3: #REF!
Name _________KF4: #REF!
Name _________KF5: #REF!
Name _________KG1: #REF!
Name _________KG2: #REF!
Name _________KG3: #REF!
Name _________KG4: #REF!
Name _________KG5: #REF!
Name _________mm02: #REF!
Name _________mm2: #REF!
Name _________PL1: #REF!
Name _________PL2: #REF!
Name _________PL3: #REF!

Sheet ELIM Juni 23
A1: Konsolidasi Juni 2023
A4: Account No. | B4: Date | C4: Account Name | E4: WP Reff | F4: Balance Sheet | H4: PL | J4: Description
F5: Debit | G5: Credit | H5: Debit | I5: Credit
A7: ELIM 1 | C7: PT Indo American Seafoods (Keuangan) | F7: 97221191334 | J7: Eleminasi Utang Piutang Keuangan
A8: =A7 -> ELIM 1 | D8: PT Indokom Samudra Persada (Keuangan) | G8: =F7 -> 97221191334 | J8: =J7 -> Eleminasi Utang Piutang Keuangan
A10: ELIM 2 | C10: PT Indokom Samudra Persada | F10: 39815441380 | J10: Eleminasi Utang Piutang
A11: =A10 -> ELIM 2 | D11: PT Indo American Seafoods | G11: =F10 -> 39815441380 | J11: =J10 -> Eleminasi Utang Piutang
A13: ELIM 3 | C13: PT Indo American Seafoods | F13: 7507763245 | J13: Eleminasi Utang Piutang
A14: =A13 -> ELIM 3 | D14: PT Indokom Samudra Persada | G14: =F13 -> 7507763245 | J14: =J13 -> Eleminasi Utang Piutang
A16: ELIM 4 | C16: Penjualan Lokal ISP to IAS | H16: 52200380108 | J16: Eleminasi Penjualan ISP to IAS
A17: =A16 -> ELIM 4 | C17: Pendapatan Lain-Lain | H17: 311335980 | J17: =J16 -> Eleminasi Penjualan ISP to IAS
A18: =A17 -> ELIM 4 | C18: Penjualan Roti | H18: 919030200 | J18: =J17 -> Eleminasi Penjualan ISP to IAS
A19: =A18 -> ELIM 4 | D19: Pembelian to IAS | I19: 52200380108 | J19: =J18 -> Eleminasi Penjualan ISP to IAS
A20: =A19 -> ELIM 4 | D20: Pembelian Lain-lain | I20: 1230366180 | J20: =J19 -> Eleminasi Penjualan ISP to IAS
A22: ELIM 5 | C22: Penjualan IAS | H22: 7575726102 | J22: Eleminasi Penjualan IAS to ISP
A23: =A22 -> ELIM 5 | D23: Pembelian Bahan Baku to ISP | I23: 7526189302 | J23: =J22 -> Eleminasi Penjualan IAS to ISP
D24: Pembelian Bahan Pembantu to ISP | I24: 49536800
A26: ELIM 7 | C26: LABA DITAHAN | H26: 5868638298
A27: =A26 -> ELIM 7 | D27: Tambahan Modal Disetor (Tax Amnesty) | I27: =H26 -> 5868638298

Sheet ELIM & CAJE Juni 24
B1: JURNAL ELIMINASI
B2: Konsolidasi Juni 2024
B5: Account No. | C5: Date | D5: Account Name | F5: WP Reff | G5: Balance Sheet | I5: PL | K5: Description
G6: Debit | H6: Credit | I6: Debit | J6: Credit
B8: ELIM 1 | D8: PT Indo American Seafoods (Keuangan) | G8: =H9 -> 101208651861 | K8: Eleminasi Utang Piutang Keuangan
B9: =B8 -> ELIM 1 | E9: PT Indokom Samudra Persada (Keuangan) | H9: 101208651861 | K9: =K8 -> Eleminasi Utang Piutang Keuangan
B11: ELIM 2 | D11: PT Indokom Samudra Persada | G11: 58472629508 | K11: Eleminasi Utang Piutang
B12: =B11 -> ELIM 2 | E12: PT Indo American Seafoods | H12: =G11 -> 58472629508 | K12: =K11 -> Eleminasi Utang Piutang
B14: ELIM 3 | D14: PT Indo American Seafoods | G14: =H15 -> 2563261534 | K14: Eleminasi Utang Piutang
B15: =B14 -> ELIM 3 | E15: PT Indokom Samudra Persada | H15: 2563261534 | K15: =K14 -> Eleminasi Utang Piutang
B17: ELIM 4 | D17: Indo American Seafoods, PT (Saham) | G17: 1050000000 | K17: Eleminasi IAS Investasi pada Anak
B18: =B17 -> ELIM 4 | E18: PT Indo American Seafoods (Modal) | H18: =G17 -> 1050000000 | K18: =K17 -> Eleminasi IAS Investasi pada Anak
B21: ELIM 5 | D21: Penjualan Lokal ISP to IAS | I21: 12316866928 | K21: Eleminasi Penjualan ISP to IAS
B22: ELIM 5 | D22: Pendapatan Lain-Lain | I22: 194016790 | K22: =K21 -> Eleminasi Penjualan ISP to IAS
B23: ELIM 5 | D23: Penjualan Roti | I23: 1056351000 | K23: =K22 -> Eleminasi Penjualan ISP to IAS
B24: ELIM 5 | E24: Pembelian to IAS | J24: 12316866928 | K24: =K23 -> Eleminasi Penjualan ISP to IAS
B25: ELIM 5 | E25: Pembelian Lain-lain | J25: 1250367790 | K25: =K24 -> Eleminasi Penjualan ISP to IAS
B27: ELIM 6 | D27: Penjualan IAS | I27: 6225265015 | K27: Eleminasi Penjualan IAS to ISP
B28: ELIM 6 | E28: Pembelian ISP | J28: =I27 -> 6225265015 | K28: =K27 -> Eleminasi Penjualan IAS to ISP
B30: ELIM 7 | D30: LABA DITAHAN | I30: 5868638298
B31: =B30 -> ELIM 7 | E31: Tambahan Modal Disetor (Tax Amnesty) | J31: =I30 -> 5868638298
B34: CAJE 1 | E34: LABA DITAHAN | H34: 2
B35: =B34 -> CAJE 1 | D35: Piutang Lain-lain di bawah Rp 20.000.000,- | G35: 2
D36: (Adj atas Ctrl)

Sheet ELIM & CAJE Sept 23
A1: Konsolidasi September 2023
A4: Account No. | B4: Date | C4: Account Name | E4: WP Reff | F4: Balance Sheet | H4: PL | J4: Description
F5: Debit | G5: Credit | H5: Debit | I5: Credit
A7: ELIM 1 | C7: PT Indo American Seafoods (Keuangan) | F7: 123411723048 | J7: Eleminasi Utang Piutang Keuangan
A8: =A7 -> ELIM 1 | D8: PT Indokom Samudra Persada (Keuangan) | G8: =F7 -> 123411723048 | J8: =J7 -> Eleminasi Utang Piutang Keuangan
A10: ELIM 2 | C10: PT Indokom Samudra Persada | F10: 6441405695 | J10: Eleminasi Utang Piutang
A11: =A10 -> ELIM 2 | D11: PT Indo American Seafoods | G11: =F10 -> 6441405695 | J11: =J10 -> Eleminasi Utang Piutang
A13: ELIM 3 | C13: PT Indo American Seafoods | F13: 55459611170 | J13: Eleminasi Utang Piutang
A14: =A13 -> ELIM 3 | D14: PT Indokom Samudra Persada | G14: =F13 -> 55459611170 | J14: =J13 -> Eleminasi Utang Piutang
A16: ELIM 4 | C16: Penjualan Lokal ISP to IAS | H16: 71326250958 | J16: Eleminasi Penjualan ISP to IAS
A17: =A16 -> ELIM 4 | C17: Pendapatan Lain-Lain | H17: 497965132 | J17: =J16 -> Eleminasi Penjualan ISP to IAS
A18: =A17 -> ELIM 4 | C18: Penjualan Roti | H18: 1148410200 | J18: =J17 -> Eleminasi Penjualan ISP to IAS
A19: =A18 -> ELIM 4 | D19: Pembelian to IAS | I19: 10264188776 | J19: =J18 -> Eleminasi Penjualan ISP to IAS
A20: =A19 -> ELIM 4 | D20: Pembelian Lain-lain | I20: 65549600 | J20: =J19 -> Eleminasi Penjualan ISP to IAS
A22: ELIM 5 | C22: Penjualan IAS | H22: 10329738376 | J22: Eleminasi Penjualan IAS to ISP
A23: =A22 -> ELIM 5 | D23: Pembelian Bahan Baku to ISP | I23: 71326250958 | J23: =J22 -> Eleminasi Penjualan IAS to ISP
A24: =A23 -> ELIM 5 | D24: Pembelian Bahan Pembantu to ISP | I24: 1646375332 | J24: =J23 -> Eleminasi Penjualan IAS to ISP
A26: ELIM 7 | C26: LABA DITAHAN | H26: 5868638298
A27: =A26 -> ELIM 7 | D27: Tambahan Modal Disetor (Tax Amnesty) | I27: =H26 -> 5868638298

Sheet LPK Analysis
A1: PT INDO AMERICAN SEAFOODS DAN ENTAS ANAK
A2: Laporan Posisi Keuangan
A3: Tanggal 30 September 2024, 31 Desember 2023, 2022 dan 2021
A6: Keterangan | B6: 45565 | C6: 31 Desember | I6: Difference | N6: % Growth
B7: 2024 | C7: 2024 | D7: 2023 | E7: 2022 | F7: 2021 | I7: 45536 | J7: 45627 | K7: 45261 | L7: 44896 | N7: 45536 | O7: 45627 | P7: 45261 | Q7: 44896
A8: ASET
A9: Aset Lancar
A10: Kas dan Setara Kas | B10: ='BS Konsol-Des 24'!I11 -> 13187388399 | C10: ='BS Konsol-Des 24'!G11 -> 918209485 | D10: 2570121355 | E10: 4920468963 | F10: 4972845584 | H10: =D10-E10 -> -2350347608 | I10: =B10-D10 -> 10617267044 | J10: =C10-D10 -> -1651911870 | K10: =D10-E10 -> -2350347608 | L10: =E10-F10 -> -52376621 | N10: =I10/D10 -> 4.1310372 | O10: =J10/D10 -> -0.64273691 | P10: =K10/E10 -> -0.4776674 | Q10: =L10/F10 -> -0.010532525
A11: Piutang Usaha dari Pihak Ketiga - Bersih | B11: ='BS Konsol-Des 24'!I14 -> 37856978018 | C11: ='BS Konsol-Des 24'!G14 -> 94399254849 | D11: 19981020112 | E11: 53102808880 | F11: 38673285818 | I11: =B11-D11 -> 17875957906 | J11: =C11-D11 -> 74418234737 | K11: =D11-E11 -> -33121788768 | L11: =E11-F11 -> 14429523062 | N11: =I11/D11 -> 0.89464691 | O11: =J11/D11 -> 3.7244462 | P11: =K11/E11 -> -0.62372951 | Q11: =L11/F11 -> 0.37311345
A12: Piutang Usaha dari Pihak Berelasi | B12: ='BS Konsol-Des 24'!I13 -> 339894481 | C12: ='BS Konsol-Des 24'!G13 -> 393935430 | D12: 211054410 | E12: 1729176327 | F12: 1565918952 | I12: =B12-D12 -> 128840071 | J12: =C12-D12 -> 182881020 | K12: =D12-E12 -> -1518121917 | L12: =E12-F12 -> 163257375 | N12: =I12/D12 -> 0.61045903 | O12: =J12/D12 -> 0.86651125 | P12: =K12/E12 -> -0.87794512 | Q12: =L12/F12 -> 0.10425659
A13: Piutang Lain-lain dari Pihak Ketiga | B13: ='BS Konsol-Des 24'!I15 -> 510634104 | C13: ='BS Konsol-Des 24'!G15 -> 697232257 | D13: 510634104 | E13: 549732399 | F13: 466154019 | I13: =B13-D13 -> 0 | J13: =C13-D13 -> 186598153 | K13: =D13-E13 -> -39098295 | L13: =E13-F13 -> 83578380 | N13: =I13/D13 -> 0 | O13: =J13/D13 -> 0.36542438 | P13: =K13/E13 -> -0.071122414 | Q13: =L13/F13 -> 0.17929349
A14: Piutang lain-lain dari pihak berelasi | B14: =0 -> 0 | C14: =0 -> 0 | D14: 7022707423 | E14: 7197443207 | F14: 6836690211 | I14: =B14-D14 -> -7022707423 | J14: =C14-D14 -> -7022707423 | K14: =D14-E14 -> -174735784 | L14: =E14-F14 -> 360752996 | N14: =I14/D14 -> -1 | O14: =J14/D14 -> -1 | P14: =K14/E14 -> -0.02427748 | Q14: =L14/F14 -> 0.052767199
A15: Persediaan | B15: ='BS Konsol-Des 24'!I16 -> 262102659717 | C15: ='BS Konsol-Des 24'!G16 -> 217742151701 | D15: 218071396362 | E15: 137179893500 | F15: 95865646086 | I15: =B15-D15 -> 44031263355 | J15: =C15-D15 -> -329244661 | K15: =D15-E15 -> 80891502862 | L15: =E15-F15 -> 41314247414 | N15: =I15/D15 -> 0.20191214 | O15: =J15/D15 -> -0.0015098021 | P15: =K15/E15 -> 0.58967463 | Q15: =L15/F15 -> 0.43095988
A16: Aset Biologis | B16: ='BS Konsol-Des 24'!I17 -> 3489807904 | C16: ='BS Konsol-Des 24'!G17 -> 913803984 | D16: 2415719386 | E16: 651253829 | F16: 871760289 | H16: =E16-D16 -> -1764465557 | I16: =B16-D16 -> 1074088518 | J16: =C16-D16 -> -1501915402 | K16: =D16-E16 -> 1764465557 | L16: =E16-F16 -> -220506460 | N16: =I16/D16 -> 0.4446247 | O16: =J16/D16 -> -0.62172594 | P16: =K16/E16 -> 2.7093362 | Q16: =L16/F16 -> -0.25294391
A17: Pajak Dibayar di Muka | B17: ='BS Konsol-Des 24'!I18 -> 11345112342 | C17: ='BS Konsol-Des 24'!G18 -> 9035601705 | D17: 9663458887 | E17: 8035438770 | F17: 8635897222 | H17: =E17-D17 -> -1628020117 | I17: =B17-D17 -> 1681653455 | J17: =C17-D17 -> -627857182 | K17: =D17-E17 -> 1628020117 | L17: =E17-F17 -> -600458452 | N17: =I17/D17 -> 0.1740219 | O17: =J17/D17 -> -0.064972303 | P17: =K17/E17 -> 0.20260501 | Q17: =L17/F17 -> -0.069530523
A18: Biaya Dibayar di Muka | B18: 0 | C18: 0 | D18: 0 | E18: 0 | F18: 0 | I18: =B18-D18 -> 0 | J18: =C18-D18 -> 0 | K18: =D18-E18 -> 0 | L18: =E18-F18 -> 0 | N18: =I18/D18 -> #DIV/0! | O18: =J18/D18 -> #DIV/0! | P18: =K18/E18 -> #DIV/0! | Q18: =L18/F18 -> #DIV/0!
A19: Uang Muka | B19: ='BS Konsol-Des 24'!I20 -> 1488682854 | C19: ='BS Konsol-Des 24'!G20 -> 33893674735 | D19: 1104447053 | E19: 349309986 | F19: 227462120 | I19: =B19-D19 -> 384235801 | J19: =C19-D19 -> 32789227682 | K19: =D19-E19 -> 755137067 | L19: =E19-F19 -> 121847866 | N19: =I19/D19 -> 0.3478988 | O19: =J19/D19 -> 29.688365 | P19: =K19/E19 -> 2.1617964 | Q19: =L19/F19 -> 0.53568421
A20: Jumlah Aset Lancar | B20: =SUM(B10:B19) -> 330321157819 | C20: =SUM(C10:C19) -> 357993864146 | D20: =SUM(D10:D19) -> 261550559092 | E20: =SUM(E10:E19) -> 213715525861 | F20: =SUM(F10:F19) -> 158115660301 | H20: =D20-E20 -> 47835033231 | I20: =B20-D20 -> 68770598727 | J20: =C20-D20 -> 96443305054 | K20: =D20-E20 -> 47835033231 | L20: =E20-F20 -> 55599865560 | N20: =I20/D20 -> 0.26293424 | O20: =J20/D20 -> 0.36873676 | P20: =K20/E20 -> 0.22382573 | Q20: =L20/F20 -> 0.35164047
A21: Aset Tidak Lancar
A22: Aset Tetap – setelah dikurangi akumulasi Penyusutan | B22: ='BS Konsol-Des 24'!I29 -> 68366993855 | C22: ='BS Konsol-Des 24'!G29 -> 66637513685 | D22: ='[188]BS Konsol'!I37 -> 74113104582 | E22: ='[188]BS Konsol'!K37 -> 84248284795 | F22: ='BS Konsol-Des 24'!U29 -> 94612283276 | I22: =B22-D22 -> -5746110727 | J22: =C22-D22 -> -7475590897 | K22: =D22-E22 -> -10135180213 | L22: =E22-F22 -> -10363998481 | N22: =I22/D22 -> -0.077531642 | O22: =J22/D22 -> -0.10086733 | P22: =K22/E22 -> -0.12030132 | Q22: =L22/F22 -> -0.10954179
A23: Aset Hak-Guna – setelah dikurangi akumulasi penyusutan | B23: ='BS Konsol-Des 24'!I33 -> 7635332866 | C23: ='BS Konsol-Des 24'!G33 -> 7556618094 | D23: ='[188]BS Konsol'!I46 -> 7871477182 | E23: ='[188]BS Konsol'!K46 -> 8186336269 | F23: ='BS Konsol-Des 24'!U33 -> 8501195356 | I23: =B23-D23 -> -236144316 | J23: =C23-D23 -> -314859088 | K23: =D23-E23 -> -314859087 | L23: =E23-F23 -> -314859087 | N23: =I23/D23 -> -0.03 | O23: =J23/D23 -> -0.04 | P23: =K23/E23 -> -0.038461538 | Q23: =L23/F23 -> -0.037037037
A24: Aset Pajak Tangguhan | B24: ='BS Konsol'!H45 -> 1790182139 | C24: ='BS Konsol-Des 24'!G37 -> 1848977778 | D24: ='[188]BS Konsol'!I48 -> 1790182139 | E24: ='[188]BS Konsol'!K48 -> 1508277305 | F24: ='BS Konsol-Des 24'!U37 -> 1486561645 | I24: =B24-D24 -> 0 | J24: =C24-D24 -> 58795639 | K24: =D24-E24 -> 281904834 | L24: =E24-F24 -> 21715660 | N24: =I24/D24 -> 0 | O24: =J24/D24 -> 0.032843384 | P24: =K24/E24 -> 0.18690518 | Q24: =L24/F24 -> 0.014607978
A25: Jumlah Aset Tidak Lancar | B25: =SUM(B22:B24) -> 77792508860 | C25: =SUM(C22:C24) -> 76043109557 | D25: =SUM(D22:D24) -> 83774763903 | E25: =SUM(E22:E24) -> 93942898369 | F25: =SUM(F22:F24) -> 104600040277 | I25: =B25-D25 -> -5982255043 | J25: =C25-D25 -> -7731654346 | K25: =D25-E25 -> -10168134466 | L25: =E25-F25 -> -10657141908 | N25: =I25/D25 -> -0.071408796 | O25: =J25/D25 -> -0.092290971 | P25: =K25/E25 -> -0.10823739 | Q25: =L25/F25 -> -0.10188468
A26: JUMLAH ASET | B26: =B20+B25 -> 408113666679 | C26: =C20+C25 -> 434036973703 | D26: =D20+D25 -> 345325322995 | E26: =E20+E25 -> 307658424230 | F26: =F20+F25 -> 262715700578 | I26: =B26-D26 -> 62788343684 | J26: =C26-D26 -> 88711650708 | K26: =D26-E26 -> 37666898765 | L26: =E26-F26 -> 44942723652 | N26: =I26/D26 -> 0.18182375 | O26: =J26/D26 -> 0.25689298 | P26: =K26/E26 -> 0.1224309 | Q26: =L26/F26 -> 0.1710698
A28: LIABILITAS DAN EKUITAS
A29: Liabilitas Jangka Pendek
A30: Utang Usaha kepada Pihak Ketiga | B30: ='BS Konsol-Des 24'!I52 -> 10645094570 | C30: ='BS Konsol-Des 24'!G52 -> 10364486466 | D30: 20407901137 | E30: 12347357380 | F30: 14116621585 | I30: =B30-D30 -> -9762806567 | J30: =C30-D30 -> -10043414671 | K30: =D30-E30 -> 8060543757 | L30: =E30-F30 -> -1769264205 | N30: =I30/D30 -> -0.47838367 | O30: =J30/D30 -> -0.49213364 | P30: =K30/E30 -> 0.6528153 | Q30: =L30/F30 -> -0.12533199
A31: Utang Lain-lain kepada Pihak Berelasi | D31: 0 | E31: 0 | F31: 0 | I31: =B31-D31 -> 0 | K31: =D31-E31 -> 0 | L31: =E31-F31 -> 0 | N31: =I31/D31 -> #DIV/0! | O31: =J31/D31 -> #DIV/0! | P31: =K31/E31 -> #DIV/0! | Q31: =L31/F31 -> #DIV/0!
A32: Utang Lain-lain kepada Pihak Ketiga | D32: 0 | E32: 0 | F32: 0 | I32: =B32-D32 -> 0 | K32: =D32-E32 -> 0 | L32: =E32-F32 -> 0 | N32: =IFERROR(I32/D32,0) -> 0 | O32: =J32/D32 -> #DIV/0! | P32: =IFERROR(K32/E32,0) -> 0 | Q32: =IFERROR(L32/F32,0) -> 0
A33: Utang Bank | B33: ='BS Konsol-Des 24'!I55 -> 196870184183 | C33: ='BS Konsol-Des 24'!G55 -> 231271837921 | D33: 195441714689 | E33: 155339616431 | F33: 110815447741 | I33: =B33-D33 -> 1428469494 | J33: =C33-D33 -> 35830123232 | K33: =D33-E33 -> 40102098258 | L33: =E33-F33 -> 44524168690 | N33: =IFERROR(I33/D33,0) -> 0.0073089284 | O33: =J33/D33 -> 0.18332894 | P33: =IFERROR(K33/E33,0) -> 0.25815757 | Q33: =IFERROR(L33/F33,0) -> 0.40178666
A34: Beban Akrual | B34: ='BS Konsol-Des 24'!I56 -> 4949487657 | C34: ='BS Konsol-Des 24'!G56 -> 4970839301 | D34: 2870843988 | E34: 5031429971 | F34: 5655591014 | I34: =B34-D34 -> 2078643669 | J34: =C34-D34 -> 2099995313 | K34: =D34-E34 -> -2160585983 | L34: =E34-F34 -> -624161043 | N34: =I34/D34 -> 0.72405316 | O34: =J34/D34 -> 0.73149057 | P34: =K34/E34 -> -0.42941788 | Q34: =L34/F34 -> -0.11036177
A35: Utang Pajak | B35: ='BS Konsol-Des 24'!I57 -> 4409068751 | C35: ='BS Konsol-Des 24'!G57 -> 1467515499 | D35: 2863697915 | E35: 2152621331 | F35: 712242589 | I35: =B35-D35 -> 1545370836 | J35: =C35-D35 -> -1396182416 | K35: =D35-E35 -> 711076584 | L35: =E35-F35 -> 1440378742 | N35: =I35/D35 -> 0.53964171 | O35: =J35/D35 -> -0.48754528 | P35: =K35/E35 -> 0.33033055 | Q35: =L35/F35 -> 2.0223148
A36: Utang Jangka Pendek
A37: yang Jatuh Tempo dalam
A38: Satu Tahun
A39: Utang Pembelian Aset Tetap | B39: ='BS Konsol-Des 24'!I61 -> 19446177 | C39: ='BS Konsol-Des 24'!G61 -> 0 | D39: 76360023 | E39: 67475296 | F39: ='[188]BS Konsol'!M75 -> 0 | I39: =B39-D39 -> -56913846 | J39: =C39-D39 -> -76360023 | K39: =D39-E39 -> 8884727 | L39: =E39-F39 -> 67475296 | N39: =I39/D39 -> -0.74533563 | O39: =J39/D39 -> -1 | P39: =K39/E39 -> 0.13167378 | Q39: =L39/F39 -> #DIV/0!
A40: Liabilitas Sewa kepada Pihak Berelasi | B40: ='BS Konsol'!H68 -> 0 | C40: ='BS Konsol-Des 24'!G63 -> 0 | D40: 624277457 | E40: 3539216266 | F40: 0 | I40: =B40-D40 -> -624277457 | J40: =C40-D40 -> -624277457 | K40: =D40-E40 -> -2914938809 | L40: =E40-F40 -> 3539216266 | N40: =I40/D40 -> -1 | O40: =J40/D40 -> -1 | P40: =K40/E40 -> -0.82361138 | Q40: =L40/F40 -> #DIV/0!
A41: Utang Bank | B41: ='BS Konsol-Des 24'!I64 -> 900894064 | C41: ='BS Konsol-Des 24'!G64 -> 0 | D41: 3807894064 | E41: 3403633332 | F41: 3403633332 | I41: =B41-D41 -> -2907000000 | J41: =C41-D41 -> -3807894064 | K41: =D41-E41 -> 404260732 | L41: =E41-F41 -> 0 | N41: =IFERROR(I41/D41,0) -> -0.76341409 | O41: =J41/D41 -> -1 | P41: =IFERROR(K41/E41,0) -> 0.11877329 | Q41: =IFERROR(L41/F41,0) -> 0
A42: Jumlah Liabilitas Jangka Pendek | B42: =SUM(B29:B41) -> 217794175402 | C42: =SUM(C29:C41) -> 248074679187 | D42: =SUM(D29:D41) -> 226092689273 | E42: =SUM(E29:E41) -> 181881350007 | F42: =SUM(F29:F41) -> 134703536261 | I42: =B42-D42 -> -8298513871 | J42: =C42-D42 -> 21981989914 | K42: =D42-E42 -> 44211339266 | L42: =E42-F42 -> 47177813746 | N42: =I42/D42 -> -0.036704035 | O42: =J42/D42 -> 0.097225567 | P42: =K42/E42 -> 0.24307791 | Q42: =L42/F42 -> 0.35023441
A43: Liabilitas Jangka Panjang
A44: Liabilitas Jangka Panjang dikurangi Bagian yang
A45: Pihak Berelasi | B45: ='BS Konsol-Des 24'!M71 -> 0 | C45: ='BS Konsol-Des 24'!G71 -> 0 | D45: 595676695 | E45: 533174595 | F45: 137349400 | I45: =B45-D45 -> -595676695 | J45: =C45-D45 -> -595676695 | K45: =D45-E45 -> 62502100 | L45: =E45-F45 -> 395825195 | N45: =I45/D45 -> -1 | O45: =J45/D45 -> -1 | P45: =K45/E45 -> 0.11722633 | Q45: =L45/F45 -> 2.8818851
A46: Utang Lain-lain Pihak Ketiga | B46: ='BS Konsol-Des 24'!M72 -> 0 | C46: ='BS Konsol-Des 24'!G72 -> 0 | D46: 41000000 | E46: 41000000 | F46: 41000000 | I46: =B46-D46 -> -41000000 | J46: =C46-D46 -> -41000000 | K46: =D46-E46 -> 0 | L46: =E46-F46 -> 0 | N46: =I46/D46 -> -1 | O46: =J46/D46 -> -1 | P46: =K46/E46 -> 0 | Q46: =L46/F46 -> 0
A47: Jatuh Tempo dalam Satu Tahun | I47: =B47-D47 -> 0 | J47: =C47-D47 -> 0 | K47: =D47-E47 -> 0 | L47: =E47-F47 -> 0
A48: Utang Bank | B48: 0 | C48: 0 | D48: 0 | E48: 8526229378 | F48: 14285076353 | I48: =B48-D48 -> 0 | J48: =C48-D48 -> 0 | K48: =D48-E48 -> -8526229378 | L48: =E48-F48 -> -5758846975 | N48: =I48/D48 -> #DIV/0! | O48: =J48/D48 -> #DIV/0! | P48: =K48/E48 -> -1 | Q48: =L48/F48 -> -0.40313729
A49: Utang Pembelian Aset Tetap | B49: 0 | C49: 0 | D49: 0 | E49: 76360023 | F49: 0 | I49: =B49-D49 -> 0 | J49: =C49-D49 -> 0 | K49: =D49-E49 -> -76360023 | L49: =E49-F49 -> 76360023 | N49: =I49/D49 -> #DIV/0! | O49: =J49/D49 -> #DIV/0! | P49: =K49/E49 -> -1 | Q49: =L49/F49 -> #DIV/0!
A50: Liabilitas Sewa kepada Pihak Berelasi | B50: 0 | C50: 0 | D50: 0 | E50: 624277457 | F50: ='BS Konsol-Des 24'!U75 -> 4125675035 | I50: =B50-D50 -> 0 | J50: =C50-D50 -> 0 | K50: =D50-E50 -> -624277457 | L50: =E50-F50 -> -3501397578 | N50: =IFERROR(I50/D50,0) -> 0 | O50: =J50/D50 -> #DIV/0! | P50: =IFERROR(K50/E50,0) -> -1 | Q50: =IFERROR(L50/F50,0) -> -0.84868477
A51: Liabilitas Imbalan Pascakerja | B51: ='BS Konsol-Des 24'!I76 -> 9955987332 | C51: ='BS Konsol-Des 24'!G76 -> 10104541472 | D51: 9301883257 | E51: 8419134989 | F51: 8346918827 | I51: =B51-D51 -> 654104075 | J51: =C51-D51 -> 802658215 | K51: =D51-E51 -> 882748268 | L51: =E51-F51 -> 72216162 | N51: =I51/D51 -> 0.070319532 | O51: =J51/D51 -> 0.086289861 | P51: =K51/E51 -> 0.10485023 | Q51: =L51/F51 -> 0.0086518347
A52: Jumlah Liabilitas Jangka Panjang | B52: =SUM(B45:B51) -> 9955987332 | C52: =SUM(C45:C51) -> 10104541472 | D52: =SUM(D45:D51) -> 9938559952 | E52: =SUM(E45:E51) -> 18220176442 | F52: =SUM(F45:F51) -> 26936019615 | I52: =B52-D52 -> 17427380 | J52: =C52-D52 -> 165981520 | K52: =D52-E52 -> -8281616490 | L52: =E52-F52 -> -8715843173 | N52: =I52/D52 -> 0.0017535116 | O52: =J52/D52 -> 0.016700762 | P52: =K52/E52 -> -0.45452998 | Q52: =L52/F52 -> -0.32357577
A53: JUMLAH LIABILITAS | B53: =B42+B52 -> 227750162734 | C53: =C42+C52 -> 258179220659 | D53: =D42+D52 -> 236031249225 | E53: =E42+E52 -> 200101526449 | F53: =F42+F52 -> 161639555876 | I53: =B53-D53 -> -8281086491 | J53: =C53-D53 -> 22147971434 | K53: =D53-E53 -> 35929722776 | L53: =E53-F53 -> 38461970573 | N53: =I53/D53 -> -0.035084704 | O53: =J53/D53 -> 0.093834912 | P53: =K53/E53 -> 0.17955746 | Q53: =L53/F53 -> 0.237949
A55: Ekuitas
A56: Modal Saham | B56: ='BS Konsol-Des 24'!I98 -> 69500000000 | C56: ='BS Konsol-Des 24'!G98 -> 69500000000 | D56: ='[188]BS Konsol'!I108 -> 40000000000 | E56: ='[188]BS Konsol'!K108 -> 40000000000 | F56: ='[188]BS Konsol'!M108 -> 40000000000 | I56: =B56-D56 -> 29500000000 | J56: =C56-D56 -> 29500000000 | K56: =D56-E56 -> 0 | L56: =E56-F56 -> 0 | N56: =I56/D56 -> 0.7375 | O56: =J56/D56 -> 0.7375 | P56: =K56/E56 -> 0 | Q56: =L56/F56 -> 0
A57: Tambahan Modal Disetor | B57: ='BS Konsol-Des 24'!I99 -> 104623471870 | C57: ='BS Konsol-Des 24'!G99 -> 104623471870 | D57: ='[188]BS Konsol'!I109 -> 49739416785 | E57: ='[188]BS Konsol'!K109 -> 25871690669 | F57: ='[188]BS Konsol'!M109 -> 25871690669 | I57: =B57-D57 -> 54884055085 | J57: =C57-D57 -> 54884055085 | K57: =D57-E57 -> 23867726116 | L57: =E57-F57 -> 0 | N57: =I57/D57 -> 1.1034318 | O57: =J57/D57 -> 1.1034318 | P57: =K57/E57 -> 0.92254219 | Q57: =L57/F57 -> 0
A58: Proforma Ekuitas | B58: 0 | C58: 0 | D58: 0 | E58: ='[188]BS Konsol'!K110 -> 2.3406502e+10 | F58: ='[188]BS Konsol'!M110 -> 2.2389615e+10 | I58: =B58-D58 -> 0 | J58: =C58-D58 -> 0 | K58: =D58-E58 -> -2.3406502e+10 | L58: =E58-F58 -> 1.0168862e+09 | N58: =I58/D58 -> #DIV/0! | O58: =J58/D58 -> #DIV/0! | P58: =K58/E58 -> -1 | Q58: =L58/F58 -> 0.045417761
A59: Penghasilan Komprehensif Lain | B59: ='BS Konsol-Des 24'!I102 -> -377072852 | C59: ='BS Konsol-Des 24'!G102 -> -313784867 | D59: ='[188]BS Konsol'!I111 -> -377072852 | E59: ='[188]BS Konsol'!K111 -> -368797440 | F59: ='[188]BS Konsol'!M111 -> -611495277 | I59: =B59-D59 -> 0 | J59: =C59-D59 -> 63287985 | K59: =D59-E59 -> -8275412 | L59: =E59-F59 -> 242697837 | N59: =I59/D59 -> 0 | O59: =J59/D59 -> -0.16784021 | P59: =K59/E59 -> 0.022438908 | Q59: =L59/F59 -> -0.39689241
A60: Saldo Laba
A61: Ditentukan Penggunaannya | B61: ='BS Konsol-Des 24'!I104 -> 410000000 | C61: ='BS Konsol-Des 24'!G104 -> 410000000 | D61: ='[188]BS Konsol'!I113 -> 410000000 | E61: ='[188]BS Konsol'!K113 -> 410000000 | F61: ='[188]BS Konsol'!M113 -> 0 | I61: =B61-D61 -> 0 | J61: =C61-D61 -> 0 | K61: =D61-E61 -> 0 | L61: =E61-F61 -> 410000000 | N61: =IFERROR(I61/D61,0) -> 0 | O61: =J61/D61 -> 0 | P61: =IFERROR(K61/E61,0) -> 0 | Q61: =IFERROR(L61/F61,0) -> 0
A62: Tidak Ditentukan Penggunaannya | B62: ='BS Konsol-Des 24'!I105 -> 6207104927 | C62: ='BS Konsol-Des 24'!G105 -> 4870466041 | D62: ='[188]BS Konsol'!I114 -> 1.952173e+10 | E62: ='[188]BS Konsol'!K114 -> 1.8237503e+10 | F62: ='[188]BS Konsol'!M114 -> 1.3426334e+10 | I62: =B62-D62 -> -1.3314625e+10 | J62: =C62-D62 -> -1.4651264e+10 | K62: =D62-E62 -> 1.284227e+09 | L62: =E62-F62 -> 4.811169e+09 | N62: =I62/D62 -> -0.68204124 | O62: =J62/D62 -> -0.75051053 | P62: =K62/E62 -> 0.07041682 | Q62: =L62/F62 -> 0.35833825
A65: JUMLAH EKUITAS | B65: =SUM(B55:B64) -> 180363503945 | C65: =SUM(C55:C64) -> 179090153044 | D65: =SUM(D55:D64) -> 1.0929407e+11 | E65: =SUM(E55:E64) -> 107556897781 | F65: =SUM(F55:F64) -> 101076144702 | I65: =B65-D65 -> 7.106943e+10 | J65: =C65-D65 -> 6.9796079e+10 | K65: =D65-E65 -> 1.737176e+09 | L65: =E65-F65 -> 6480753079 | N65: =I65/D65 -> 0.65025877 | O65: =J65/D65 -> 0.63860809 | P65: =K65/E65 -> 0.016151228 | Q65: =L65/F65 -> 0.064117533
A66: JUMLAH LIABILITAS DAN EKUITAS | B66: =B53+B65 -> 408113666679 | C66: =C53+C65 -> 437269373703 | D66: =D53+D65 -> 3.4532532e+11 | E66: =E53+E65 -> 307658424230 | F66: =F53+F65 -> 262715700578 | I66: =B66-D66 -> 6.2788344e+10 | J66: =C66-D66 -> 9.1944051e+10 | K66: =D66-E66 -> 3.7666899e+10 | L66: =E66-F66 -> 44942723652 | N66: =I66/D66 -> 0.18182375 | O66: =J66/D66 -> 0.26625343 | P66: =K66/E66 -> 0.1224309 | Q66: =L66/F66 -> 0.1710698
A67: *) Tidak Konsolidasian
B71: =B26-B66 -> 0 | C71: =C26-C66 -> -3232400000 | D71: =D26-D66 -> 0.5 | E71: =E26-E66 -> 0 | F71: =F26-F66 -> 0

Sheet PL-Analysis
A1: PT INDO AMERICAN SEAFOODS DAN ENTAS ANAK
A2: Laporan Laba Rugi dan Penghasilan Komprehensif Lain
A3: Tanggal 31 Desember 2024, 2023, 2022 dan 2021
A7: Keterangan | D7: 31 Desember
B8: 45565 | C8: 45565 | D8: 2024*) | E8: 2023*) | F8: 2022*) | G8: 2021*) | J8: Difference | O8: % Growth
B9: 2024 | C9: 2024 | D9: (12 Bulan) | E9: (12 Bulan) | F9: (12 Bulan) | G9: (12 Bulan) | J9: September | K9: 45627 | L9: 45261 | M9: 44896 | O9: September | P9: 45627 | Q9: 45261 | R9: 44896
A10: PENJUALAN DAN PENDAPATAN USAHA | B10: ='PL Konsol'!F11 -> 160540499628 | C10: ='PL Konsol'!H11 -> 149774869471 | D10: ='PL Konsol'!M11 -> 3.2256021e+11 | E10: 199222794205 | F10: 382316276945 | G10: 303872116071 | J10: =B10-C10 -> 10765630157 | K10: =D10-E10 -> 1.2333742e+11 | L10: =E10-F10 -> -183093482740 | M10: =F10-G10 -> 78444160874 | O10: =J10/C10 -> 0.071878748 | P10: =K10/E10 -> 0.61909291 | Q10: =L10/F10 -> -0.4789058 | R10: =M10/G10 -> 0.2581486
A11: BEBAN POKOK PENJUALAN | B11: ='PL Konsol'!F12 -> -107535872927 | C11: ='PL Konsol'!H12 -> -97141890286 | D11: ='PL Konsol'!M12 -> -2.4693474e+11 | E11: -134214335812 | F11: -298009655959 | G11: -235513908676 | J11: =B11-C11 -> -10393982641 | K11: =D11-E11 -> -1.127204e+11 | L11: =E11-F11 -> 163795320147 | M11: =F11-G11 -> -62495747283 | O11: =J11/C11 -> 0.10699795 | P11: =K11/E11 -> 0.83985367 | Q11: =L11/F11 -> -0.54963092 | R11: =M11/G11 -> 0.26535905
A12: LABA BRUTO | B12: =B10+B11 -> 53004626701 | C12: =C10+C11 -> 52632979185 | D12: =D10+D11 -> 7.5625474e+10 | E12: =E10+E11 -> 65008458393 | F12: =F10+F11 -> 84306620986 | G12: =G10+G11 -> 68358207395 | J12: =B12-C12 -> 371647516 | K12: =D12-E12 -> 1.0617016e+10 | L12: =E12-F12 -> -19298162593 | M12: =F12-G12 -> 15948413591 | O12: =J12/C12 -> 0.0070611149 | P12: =K12/E12 -> 0.16331746 | Q12: =L12/F12 -> -0.22890447 | R12: =M12/G12 -> 0.23330649
A13: Beban Penjualan | B13: ='PL Konsol'!F16 -> -13450215380 | C13: ='PL Konsol'!H16 -> -18108262146 | D13: ='PL Konsol'!M16 -> -16258997299 | E13: -17958725423 | F13: -33826918356 | G13: -26521142401 | J13: =B13-C13 -> 4658046766 | K13: =D13-E13 -> 1699728124 | L13: =E13-F13 -> 15868192933 | M13: =F13-G13 -> -7305775955 | O13: =J13/C13 -> -0.25723323 | P13: =K13/E13 -> -0.094646367 | Q13: =L13/F13 -> -0.46909957 | R13: =M13/G13 -> 0.27546988
A14: Beban Umum dan Administrasi | B14: ='PL Konsol'!F17 -> -26167728635 | C14: ='PL Konsol'!H17 -> -20819164640 | D14: ='PL Konsol'!M17 -> -36246687170 | E14: -27733745691 | F14: -28248056723 | G14: -26942834062 | J14: =B14-C14 -> -5348563995 | K14: =D14-E14 -> -8512941479 | L14: =E14-F14 -> 514311032 | M14: =F14-G14 -> -1305222661 | O14: =J14/C14 -> 0.25690579 | P14: =K14/E14 -> 0.30695246 | Q14: =L14/F14 -> -0.018206953 | R14: =M14/G14 -> 0.048444149
A15: Pendapatan (Beban) Lain-Lain - Bersih | B15: ='PL Konsol'!F18 -> 2273092655 | C15: ='PL Konsol'!H18 -> -906733107 | D15: ='PL Konsol'!M18 -> -2610994654 | E15: -1084534135 | F15: -602810576 | G15: 112244184 | J15: =B15-C15 -> 3179825762 | K15: =D15-E15 -> -1526460519 | L15: =E15-F15 -> -481723559 | M15: =F15-G15 -> -715054760 | O15: =J15/C15 -> -3.5069038 | P15: =K15/E15 -> 1.4074804 | Q15: =L15/F15 -> 0.79912924 | R15: =M15/G15 -> -6.3705284
A16: Beban bunga dan Keuangan | B16: ='PL Konsol'!F19 -> -12487102791 | C16: ='PL Konsol'!H19 -> -11466799581 | D16: ='PL Konsol'!M19 -> -18184572249 | E16: -15677499788 | F16: -13403963086 | G16: -9352093192 | J16: =B16-C16 -> -1020303210 | K16: =D16-E16 -> -2507072461 | L16: =E16-F16 -> -2273536702 | M16: =F16-G16 -> -4051869894 | O16: =J16/C16 -> 0.0889789 | P16: =K16/E16 -> 0.15991532 | Q16: =L16/F16 -> 0.16961675 | R16: =M16/G16 -> 0.43325808
A17: Laba Sebelum Pajak Penghasilan | B17: =SUM(B12:B16) -> 3172672550 | C17: =SUM(C12:C16) -> 1332019711 | D17: =SUM(D12:D16) -> 2.324223e+09 | E17: =SUM(E12:E16) -> 2553953356 | F17: =SUM(F12:F16) -> 8224872245 | G17: =SUM(G12:G16) -> 5654381924 | J17: =B17-C17 -> 1840652839 | K17: =D17-E17 -> -2.2973031e+08 | L17: =E17-F17 -> -5670918889 | M17: =F17-G17 -> 2570490321 | O17: =J17/C17 -> 1.3818511 | P17: =K17/E17 -> -0.089950862 | Q17: =L17/E17 -> -2.2204473 | R17: =M17/G17 -> 0.45460147
A18: Manfaat (Beban) Pajak Penghasilan:
A19: Pajak Kini | B19: ='PL Konsol'!F25 -> -1487297460 | C19: ='PL Konsol'!H25 -> -518727440 | D19: ='PL Konsol'!M25 -> -2052132941 | E19: -1088072700 | F19: -2076985900 | G19: -1421390520 | J19: =B19-C19 -> -968570020 | K19: =D19-E19 -> -964060241 | L19: =E19-F19 -> 988913200 | M19: =F19-G19 -> -655595380 | O19: =J19/C19 -> 1.8672041 | P19: =K19/E19 -> 0.88602558 | Q19: =L19/E19 -> -0.90886684 | R19: =M19/G19 -> 0.46123523
A20: Pajak Tangguhan | B20: 0 | C20: 0 | D20: ='PL Konsol'!M26 -> 76646095 | E20: 279570745 | F20: 90168897 | G20: 1446845971 | J20: =B20-C20 -> 0 | K20: =D20-E20 -> -202924650 | L20: =E20-F20 -> 189401848 | M20: =F20-G20 -> -1356677074 | O20: 0 | P20: =K20/E20 -> -0.72584365 | Q20: =L20/E20 -> 0.67747378 | R20: =M20/G20 -> -0.93767899
A21: LABA PERIODE / TAHUN BERJALAN | B21: =SUM(B17:B20) -> 1685375090 | C21: =SUM(C17:C20) -> 813292271
A22: SEBELUM DAMPAK PENYESUAIAN PROFORMA | B22: 0 | C22: 0 | D22: =SUM(D17:D20) -> 3.487362e+08 | E22: =SUM(E17:E20) -> 1745451401 | F22: =SUM(F17:F20) -> 6238055242 | G22: =SUM(G17:G20) -> 5679837375 | J22: =B22-C22 -> 0 | K22: =D22-E22 -> -1.3967152e+09 | L22: =E22-F22 -> -4492603841 | M22: =F22-G22 -> 558217867 | O22: 0 | P22: =K22/E22 -> -0.80020286 | Q22: =L22/E23 -> #DIV/0! | R22: =M22/G23 -> -0.23808809
A23: DAMPAK PENYESUAIAN PROFORMA | D23: 0 | E23: 0 | F23: -1.0268862e+09 | G23: -2.3445854e+09 | J23: =B23+E23 -> 0 | K23: =D23+E23 -> 0 | L23: =E23+F23 -> -1.0268862e+09 | M23: =F23-G23 -> 1.3176992e+09 | O23: 0 | P23: =K23/E23 -> #DIV/0! | Q23: =L23/E23 -> #DIV/0! | R23: =M23/G23 -> -0.562018
A24: LABA PERIODE / TAHUN BERJALAN
A25: SETELAH DAMPAK PENYESUAIAN PROFORMA | B25: =B22+B23 -> 0 | C25: =C22+C23 -> 0 | D25: =D22+D23 -> 3.487362e+08 | E25: =E22+E23 -> 1745451401 | F25: =F22+F23 -> 5.211169e+09 | G25: =G22+G23 -> 3.335252e+09 | J25: =B25-C25 -> 0 | K25: =D25-E25 -> -1.3967152e+09 | L25: =E25+F25 -> 6.9566204e+09 | M25: =F25-G25 -> 1.8759171e+09 | O25: 0 | P25: =K25/E25 -> -0.80020286 | Q25: =L25/E25 -> 3.985571 | R25: =M25/G25 -> 0.56245138
A26: Pengukuran Kembali Imbalan Pasti | B26: =0 -> 0 | C26: =0 -> 0 | D26: ='PL Konsol'!M41 -> 81138444 | E26: -10609502 | F26: 311151073 | G26: 21039938 | J26: =B26-C26 -> 0 | K26: =D26-E26 -> 91747946 | L26: =E26+F26 -> 300541571 | M26: =F26-G26 -> 290111135 | O26: 0 | P26: =K26/E26 -> -8.6477147 | Q26: =L26/E26 -> -28.327585 | R26: =M26/G26 -> 13.788593
A27: Pajak Penghasilan Terkait | B27: 0 | C27: 0 | D27: ='PL Konsol'!M42 -> -17850458 | E27: 2334090 | F27: -68453236 | G27: -4628786 | J27: =B27-C27 -> 0 | K27: =D27-E27 -> -20184548 | L27: =E27+F27 -> -66119146 | M27: =F27-G27 -> -63824450 | O27: 0 | P27: =K27/E27 -> -8.6477162 | Q27: =L27/E27 -> -28.327591 | R27: =M27/G27 -> 13.788594
A28: JUMLAH PENGHASILAN KOMPREHENSIF LAIN | B28: =B26+B27+'WS Konsol'!W759+'WS Konsol'!W762 -> 0 | C28: =C26+C27+'WS Konsol'!AT759+'WS Konsol'!AT762 -> 0 | D28: =SUM(D26:D27) -> 63287986 | E28: =SUM(E26:E27) -> -8275412 | F28: =SUM(F26:F27) -> 242697837 | G28: =SUM(G26:G27) -> 16411152 | J28: =B28-C28 -> 0 | K28: =D28-E28 -> 71563398 | L28: =E28-F28 -> -250973249 | M28: =F28-G28 -> 226286685 | O28: 0 | P28: =K28/E28 -> -8.6477142 | Q28: =L28/E28 -> 30.327584 | R28: =M28/G28 -> 13.788592
A29: DAMPAK PENYESUAIAN PROFORMA | D29: 0 | E29: 0 | F29: 1.8842722e+08 | G29: -7593457.1 | J29: =B29-C29 -> 0 | K29: =D29-E29 -> 0 | L29: =E29-F29 -> -1.8842722e+08 | M29: =F29-G29 -> 1.9602068e+08 | O29: 0 | P29: =K29/E29 -> #DIV/0! | Q29: =L29/E29 -> #DIV/0! | R29: =M29/G29 -> -25.814418
A30: LABA KOMPREHENSIF PERIODE / TAHUN BERJALAN | B30: =B25+B28+B29 -> 0 | C30: =C25+C28+C29 -> 0 | D30: =D25+D28+D29 -> 4.1202419e+08 | E30: =E25+E28+E29+309 -> 1737176298 | F30: =F25+F28+F29+1262 -> 5.6422953e+09 | G30: =G25+G28+G29+1140 -> 3.3440708e+09 | J30: =B30-C30 -> 0 | K30: =D30-E30 -> -1.3251521e+09 | L30: =E30-F30 -> -3.9051191e+09 | M30: =F30-G30 -> 2.2982245e+09 | O30: 0 | P30: =K30/E30 -> -0.76281959 | Q30: =L30/E30 -> -2.2479693 | R30: =M30/G30 -> 0.68725355
A31: Laba per saham dasar | E31: 2.1818143 | F31: 6.5139613 | G31: 4.169065 | J31: =B31-E31 -> -2.1818143 | K31: =D31-E31 -> -2.1818143 | L31: =E31-F31 -> -4.332147 | M31: =F31-G31 -> 2.3448963 | O31: 0 | P31: =K31/E31 -> -1 | Q31: =L31/E31 -> -1.985571 | R31: =M31/G31 -> 0.56245138
A32: *) Konsolidasian

Sheet CF Analysis
A1: PT INDO AMERICAN SEAFOODS DAN ENTAS ANAK
A2: Laporan Arus Kas
A3: Tanggal 31 Desember 2024, 2023, 2022 dan 2021
A7: Keterangan | D7: 31 Desember
B8: 45565 | C8: 45565 | D8: 2024*) | E8: 2023*) | F8: 2022*) | G8: 2021*) | J8: Difference | O8: % Growth
B9: 2024 | C9: 2023 | D9: (12 Bulan) | E9: (12 Bulan) | F9: (12 Bulan) | G9: (12 Bulan) | J9: September | K9: 45627 | L9: 45261 | M9: 44896 | O9: September | P9: 45627 | Q9: 45261 | R9: 44896
A11: ARUS KAS AKTIVITAS OPERASI
A12: Arus Kas Bersih Diperoleh dari (Digunakan untuk) Aktivitas Operasi | B12: ='CF Konsol'!H22 -> -60184010806 | C12: ='CF Konsol'!J22 -> -7.132382e+09 | D12: ='CF Konsol'!F22 -> -1.0861459e+11 | E12: -3.0698923e+10 | F12: -38731871094 | G12: -2.2046803e+09 | J12: =B12-C12 -> -5.3051629e+10 | K12: =D12-E12 -> -7.7915667e+10 | L12: =E12-F12 -> 8.0329486e+09 | M12: =F12-G12 -> -3.6527191e+10 | O12: =C12/J12 -> 0.13444228 | P12: =K12/E12 -> 2.5380587 | Q12: =L12/F12 -> -0.20739893 | R12: =M12/G12 -> 16.568021
A14: ARUS KAS AKTIVITAS INVESTASI
A15: Arus Kas Bersih digunakan untuk Aktivitas Investasi | B15: ='CF Konsol'!H37 -> 7022707423 | C15: ='CF Konsol'!J37 -> -149115000 | D15: ='CF Konsol'!F37 -> 6852707423 | E15: -149115000 | F15: -337817118 | G15: -1.7752124e+10 | J15: =B15-C15 -> 7171822423 | K15: =D15-E15 -> 7001822423 | L15: =E15-F15 -> 188702118 | M15: =F15-G15 -> 1.7414307e+10 | O15: =C15/J15 -> -0.020791786 | P15: =K15/E15 -> -46.955856 | Q15: =L15/F15 -> -0.55859253 | R15: =M15/G15 -> -0.98097033
A17: ARUS KAS AKTIVITAS PENDANAAN
A18: Arus Kas Bersih digunakan untuk Aktivitas Pendanaan | B18: ='CF Konsol'!H61 -> 63778570427 | C18: ='CF Konsol'!J61 -> 5175401254 | D18: ='CF Konsol'!F61 -> 100109970078 | E18: 28497689903 | F18: 39017311591 | G18: 19415033454 | J18: =B18-C18 -> 58603169173 | K18: =D18-E18 -> 71612280175 | L18: =E18-F18 -> -10519621688 | M18: =F18-G18 -> 19602278137 | O18: =C18/J18 -> 0.088312651 | P18: =K18/E18 -> 2.5129153 | Q18: =L18/F18 -> -0.26961421 | R18: =M18/G18 -> 1.0096443
A20: KENAIKAN (PENURUNAN) BERSIH KAS DAN BANK | B20: ='CF Konsol'!H65 -> 10617267044 | C20: ='CF Konsol'!J65 -> -2.1060957e+09 | D20: ='CF Konsol'!F65 -> -1.6519119e+09 | E20: -2.3503476e+09 | F20: -52376621 | G20: -541770942 | J20: =B20-C20 -> 1.2723363e+10 | K20: =D20-E20 -> 6.9843574e+08 | L20: =E20-F20 -> -2.297971e+09 | M20: =F20-G20 -> 489394321 | O20: =C20/J20 -> -0.1655298 | P20: =K20/E20 -> -0.29716274 | Q20: =L20/F20 -> 43.873983 | R20: =M20/G20 -> -0.90332331
A22: SALDO KAS DAN BANK AWAL TAHUN | B22: ='CF Konsol'!H69 -> 2570121355 | C22: ='CF Konsol'!J69 -> 4920468963 | D22: ='CF Konsol'!F69 -> 2570121355 | E22: 4.920469e+09 | F22: 4.9728456e+09 | G22: 5.5146165e+09 | J22: =B22-C22 -> -2350347608 | K22: =D22-E22 -> -2.3503476e+09 | L22: =E22-F22 -> -52376621 | M22: =F22-G22 -> -541770942 | O22: =C22/J22 -> -2.0935069 | P22: =K22/E22 -> -0.4776674 | Q22: =L22/F22 -> -0.010532525 | R22: =M22/G22 -> -0.098242723
A24: SALDO KAS DAN BANK AKHIR TAHUN | B24: ='CF Konsol'!H73 -> 13187388399 | C24: ='CF Konsol'!J73 -> 2.8143732e+09 | D24: ='CF Konsol'!F73 -> 918209485 | E24: 2.5701214e+09 | F24: 4.920469e+09 | G24: 4.9728456e+09 | J24: =B24-C24 -> 1.0373015e+10 | K24: =D24-E24 -> -1.6519119e+09 | L24: =E24-F24 -> -2.3503476e+09 | M24: =F24-G24 -> -52376621 | O24: =C24/J24 -> 0.2713168 | P24: =K24/E24 -> -0.64273691 | Q24: =L24/F24 -> -0.4776674 | R24: =M24/G24 -> -0.010532525
A26: *) Konsolidasian

Sheet RASIO KEUANGAN
B1: PT INDO AMERICAN SEAFOODS DAN ENTAS ANAK
B2: RASIO-RASIO KEUANGAN PENTING
B4: Keterangan | C4: 31 Desember
C5: 2024 | D5: 2023 | E5: 2022 | F5: 2021
B6: Profitabilitas
B7: Laba (Rugi) Neto Tahun Berjalan terhadap Jumlah Aset | C7: ='PL-Analysis'!D25/'LPK Analysis'!C26 -> 0.00080347119 | D7: ='PL-Analysis'!E25/'LPK Analysis'!D26 -> 0.0050545132 | E7: ='PL-Analysis'!F25/'LPK Analysis'!E26 -> 0.016938165 | F7: ='PL-Analysis'!G25/'LPK Analysis'!F26 -> 0.01269529
B8: Laba (Rugi) Neto Tahun Berjalan terhadap Jumlah Ekuitas | C8: ='PL-Analysis'!D25/'LPK Analysis'!C65 -> 0.0019472662 | D8: ='PL-Analysis'!E25/'LPK Analysis'!D65 -> 0.015970229 | E8: ='PL-Analysis'!F25/'LPK Analysis'!E65 -> 0.048450347 | F8: ='PL-Analysis'!G25/'LPK Analysis'!F65 -> 0.03299742
B9: Laba (Rugi) Neto Tahun Berjalan terhadap Penjualan Bersih | C9: ='PL-Analysis'!D25/'PL-Analysis'!D10 -> 0.0010811507 | D9: ='PL-Analysis'!E25/'PL-Analysis'!E10 -> 0.0087613037 | E9: ='PL-Analysis'!F25/'PL-Analysis'!F10 -> 0.013630518 | F9: ='PL-Analysis'!G25/'PL-Analysis'!G10 -> 0.010975841
B10: Laba (Rugi) Bruto terhadap Pendapatan Usaha | C10: ='PL-Analysis'!D12/'PL-Analysis'!D10 -> 0.23445382 | D10: ='PL-Analysis'!E12/'PL-Analysis'!E10 -> 0.32631034 | E10: ='PL-Analysis'!F12/'PL-Analysis'!F10 -> 0.22051538 | F10: ='PL-Analysis'!G12/'PL-Analysis'!G10 -> 0.22495716
B11: Laba (Rugi) Usaha terhadap Pendapatan Usaha | C11: ='PL-Analysis'!D25/'PL-Analysis'!D10 -> 0.0010811507 | D11: ='PL-Analysis'!E25/'PL-Analysis'!E10 -> 0.0087613037 | E11: ='PL-Analysis'!F25/'PL-Analysis'!F10 -> 0.013630518 | F11: ='PL-Analysis'!G25/'PL-Analysis'!G10 -> 0.010975841
B12: EBITDA terhadap Penjualan | C12: ='Rasio DSCR'!B23 -> 0.088497869 | D12: ='Rasio DSCR'!C23 -> 0.14611871 | E12: ='Rasio DSCR'!D23 -> 0.082938642 | F12: ='Rasio DSCR'!E23 -> 0.077944212
B14: Solvabilitas
B15: Liabilitas terhadap Aset | C15: ='LPK Analysis'!C53/'LPK Analysis'!C26 -> 0.59483232 | D15: ='LPK Analysis'!D53/'LPK Analysis'!D26 -> 0.68350403 | E15: ='LPK Analysis'!E53/'LPK Analysis'!E26 -> 0.65040158 | F15: ='LPK Analysis'!F53/'LPK Analysis'!F26 -> 0.61526416
B16: Liabilitas terhadap Ekuitas | C16: ='LPK Analysis'!C53/'LPK Analysis'!C65 -> 1.4416159 | D16: ='LPK Analysis'!D53/'LPK Analysis'!D65 -> 2.1595979 | E16: ='LPK Analysis'!E53/'LPK Analysis'!E65 -> 1.8604249 | F16: ='LPK Analysis'!F53/'LPK Analysis'!F65 -> 1.599186
B17: DSCR | C17: ='Rasio DSCR'!B10 -> 0.025346307 | D17: ='Rasio DSCR'!C10 -> 0.036221536 | E17: ='Rasio DSCR'!D10 -> 0.052715429 | F17: ='Rasio DSCR'!E10 -> 0.040564103
B18: ICR | C18: ='Rasio DSCR'!B11 -> 1.1320278 | D18: ='Rasio DSCR'!C11 -> 1.1807383 | E18: ='Rasio DSCR'!D11 -> 1.5437313 | F18: ='Rasio DSCR'!E11 -> 1.508618
B21: Likuiditas
B22: Aset Lancar terhadap Liabilitas Jangka Pendek | C22: ='LPK Analysis'!C20/'LPK Analysis'!C42 -> 1.4430891 | D22: ='LPK Analysis'!D20/'LPK Analysis'!D42 -> 1.1568289 | E22: ='LPK Analysis'!E20/'LPK Analysis'!E42 -> 1.1750272 | F22: ='LPK Analysis'!F20/'LPK Analysis'!F42 -> 1.1738048 | G22: Rasio Lancar
B23: Kas terhadap Liabilitas Jangka Pendek | C23: ='LPK Analysis'!C10/'LPK Analysis'!C42 -> 0.003701343 | D23: ='LPK Analysis'!D10/'LPK Analysis'!D42 -> 0.011367556 | E23: ='LPK Analysis'!E10/'LPK Analysis'!E42 -> 0.02705318 | F23: ='LPK Analysis'!F10/'LPK Analysis'!F42 -> 0.036916964
B26: Pertumbuhan
B27: Pendapatan Usaha | C27: =('PL-Analysis'!D10-'PL-Analysis'!E10)/'PL-Analysis'!E10 -> 0.61909291 | D27: =('PL-Analysis'!E10-'PL-Analysis'!F10)/'PL-Analysis'!F10 -> -0.4789058 | E27: =('PL-Analysis'!F10-'PL-Analysis'!G10)/'PL-Analysis'!G10 -> 0.2581486
B28: Laba (Rugi) Bruto | C28: =('PL-Analysis'!D12-'PL-Analysis'!E12)/'PL-Analysis'!E12 -> 0.16331746 | D28: =('PL-Analysis'!E12-'PL-Analysis'!F12)/'PL-Analysis'!F12 -> -0.22890447 | E28: =('PL-Analysis'!F12-'PL-Analysis'!G12)/'PL-Analysis'!G12 -> 0.23330649
B29: Laba Bersih | C29: =('PL-Analysis'!D25-'PL-Analysis'!E25)/'PL-Analysis'!E25 -> -0.80020286 | D29: =('PL-Analysis'!E25-'PL-Analysis'!F25)/'PL-Analysis'!F25 -> -0.66505569 | E29: =('PL-Analysis'!F25-'PL-Analysis'!G25)/'PL-Analysis'!G25 -> 0.56245138
B30: Aset | C30: =('LPK Analysis'!C26-'LPK Analysis'!D26)/'LPK Analysis'!D26 -> 0.25689298 | D30: =('LPK Analysis'!D26-'LPK Analysis'!E26)/'LPK Analysis'!E26 -> 0.1224309 | E30: =('LPK Analysis'!E26-'LPK Analysis'!F26)/'LPK Analysis'!F26 -> 0.1710698
B31: Liabilitas | C31: =('LPK Analysis'!C53-'LPK Analysis'!D53)/'LPK Analysis'!D53 -> 0.093834912 | D31: =('LPK Analysis'!D53-'LPK Analysis'!E53)/'LPK Analysis'!E53 -> 0.17955746 | E31: =('LPK Analysis'!E53-'LPK Analysis'!F53)/'LPK Analysis'!F53 -> 0.237949

Sheet Rasio DSCR
A1: PT INDO AMERICAN SEAFOODS DAN ENTAS ANAK
A2: PERHITUNGAN DSCR DAN ICR
A4: Keterangan | B4: 31 Desember
B5: 2024 | C5: 2023*) | D5: 2022*) | E5: 2021*)
B6: (12 Bulan) | C6: (12 Bulan) | D6: (12 Bulan) | E6: (12 Bulan)
A7: EBIT | B7: =B13 -> 2.0585441e+10 | C7: =C13 -> 18511023889 | D7: =D13 -> 2.0692118e+10 | E7: =E13 -> 1.4108736e+10
A8: Bunga Bank | B8: =B16 -> 18184572249 | C8: =C16 -> 15677499788 | D8: =D16 -> 13403963086 | E8: =E16 -> 9352093192
A9: Total Pembayaran Utang | B9: =-'CF Konsol'!F43 -> 793982710777 | C9: =-'CF Konsol'!P43 -> 495372719131 | D9: =-'CF Konsol'!R43 -> 379120929829 | E9: =-'CF Konsol'!T43 -> 338461235558
A10: DSCR | B10: =B7/(B8+B9) -> 0.025346307 | C10: =C7/(C8+C9) -> 0.036221536 | D10: =D7/(D8+D9) -> 0.052715429 | E10: =E7/(E8+E9) -> 0.040564103
A11: ICR | B11: =B7/B8 -> 1.1320278 | C11: =C7/C8 -> 1.1807383 | D11: =D7/D8 -> 1.5437313 | E11: =E7/E8 -> 1.508618
A13: EBIT = Laba Bersih + Bunga + Pajak | B13: =SUM(B15:B17) -> 2.0585441e+10 | C13: =SUM(C15:C17) -> 18511023889 | D13: =SUM(D15:D17) -> 2.0692118e+10 | E13: =SUM(E15:E17) -> 1.4108736e+10
A14: EBITDA = | B14: =B13+B18+B19 -> 2.8545891e+10 | C14: =C13+C18+C19 -> 29110178188 | D14: =D13+D18+D19 -> 3.1708793e+10 | E14: =E13+E18+E19 -> 2.3685073e+10
A15: Laba Bersih | B15: ='PL-Analysis'!D25 -> 3.487362e+08 | C15: ='PL-Analysis'!E25 -> 1745451401 | D15: ='PL-Analysis'!F25 -> 5.211169e+09 | E15: ='PL-Analysis'!G25 -> 3.335252e+09
A16: Beban Bunga | B16: =-'PL-Analysis'!D16 -> 18184572249 | C16: =-'PL-Analysis'!E16 -> 15677499788 | D16: =-'PL-Analysis'!F16 -> 13403963086 | E16: =-'PL-Analysis'!G16 -> 9352093192
A17: Beban Pajak Penghasilan Badan | B17: =-'PL-Analysis'!D19 -> 2052132941 | C17: =-'PL-Analysis'!E19 -> 1088072700 | D17: =-'PL-Analysis'!F19 -> 2076985900 | E17: =-'PL-Analysis'!G19 -> 1421390520
A18: Amortisasi | B18: ='WS Konsol'!M619+'WS Konsol'!M715 -> 314859088 | C18: ='WS Konsol'!AI619+'WS Konsol'!AI715 -> 314859087 | D18: ='WS Konsol'!BF619+'WS Konsol'!BF715 -> 314859086 | E18: ='WS Konsol'!BH619+'WS Konsol'!BH715 -> 314859087
A19: Depresiasi | B19: =SUM('WS Konsol'!M707:M714)+'WS Konsol'!M623+'WS Konsol'!M618 -> 7645590897 | C19: =SUM('WS Konsol'!AI707:AI714)+'WS Konsol'!AI623+'WS Konsol'!AI618 -> 10284295212 | D19: ='WS Konsol'!BF718+SUM('WS Konsol'!BF707:BF714)+'WS Konsol'!BF623+'WS Konsol'!BF618 -> 10701815600 | E19: ='WS Konsol'!BH718+SUM('WS Konsol'!BH707:BH714)+'WS Konsol'!BH623+'WS Konsol'!BH618 -> 9261477767
A22: Ebitda thd pendapatan (%) | B22: ='PL-Analysis'!D10 -> 3.2256021e+11 | C22: ='PL-Analysis'!E10 -> 199222794205 | D22: ='PL-Analysis'!F10 -> 382316276945 | E22: ='PL-Analysis'!G10 -> 303872116071
B23: =B14/B22 -> 0.088497869 | C23: =C14/C22 -> 0.14611871 | D23: =D14/D22 -> 0.082938642 | E23: =E14/E22 -> 0.077944212
A25: Total Aset | B25: ='LPK Analysis'!C26 -> 434036973703 | C25: ='LPK Analysis'!D26 -> 345325322995 | D25: ='LPK Analysis'!E26 -> 307658424230 | E25: ='LPK Analysis'!F26 -> 262715700578
B26: =B15/B25 -> 0.00080347119 | C26: =C15/C25 -> 0.0050545132 | D26: =D15/D25 -> 0.016938165 | E26: =E15/E25 -> 0.01269529
A28: Total Ekuitas | B28: ='LPK Analysis'!C65 -> 179090153044 | C28: ='LPK Analysis'!D65 -> 1.0929407e+11 | D28: ='LPK Analysis'!E65 -> 107556897781 | E28: ='LPK Analysis'!F65 -> 101076144702
B29: =B15/B28 -> 0.0019472662 | C29: =C15/C28 -> 0.015970229 | D29: =D15/D28 -> 0.048450347 | E29: =E15/E28 -> 0.03299742

Sheet Sheet1
C3: 71587587813
B4: 0.9 | C4: =C3*B4 -> 6.4428829e+10 | D4: Pembelian Bahan Baku
B5: 0.05 | C5: =C3*B5 -> 3.5793794e+09 | D5: Biaya Penjualan
B6: 0.0485 | C6: =B6*C3 -> 3.471998e+09 | D6: Perawatan & utilitas
B7: =100%-SUM(B4:B6) -> 0.0015 | C7: =B7*C3 -> 1.0738138e+08 | D7: Keperluan Kantor

Sheet KK CF Konsol Juni 24
A1: Aset | B1: =SUM(C7:V7) -> 347660437458 | C1: ='BS Konsol'!H48-B1 -> 0
A2: Liabilities | B2: =SUM(X7:AK7) -> -237494444229 | C2: =B2+'BS Konsol'!H87 -> 0
A3: Ekuitas | B3: =SUM(AL7:BC7) -> -110165993229 | C3: =B3+'BS Konsol'!H107 -> 0
C4: Kas dan Bank | D4: Piutang Usaha Kepada Pihak Ketiga | E4: Piutang Usaha Kepada Pihak Berelasi | F4: CKPN | G4: Piutang dari Karyawan | H4: Piutang Lain-Lain | I4: Piutang Lain - Lain dari Pihak Ketiga | J4: Persediaan | K4: Uang Muka | L4: Aset Biologis | M4: Prepaid Tax | N4: Prepaid | O4: Project In Progress | P4: Uang Muka Pembelian | Q4: Pajak Dibayar Dimuka | R4: Aset Tetap | S4: Uang Muka Pembelian Aset Tetap | T4: Investasi | U4: Aset Hak Guna | V4: Aset Pajak Tangguhan | W4: Biaya pra IPO | X4: Short Term Bank Loans | Y4: Bank Loan - Short part of long | Z4: Utang Usaha Pihak Berelasi | AA4: Utang Usaha Pihak Ketiga | AB4: Uang Muka Pelangan | AC4: Biaya Yang Masih Harus Dibayar | AD4: Utang Lain2 Pihak Ketiga | AE4: Utang Lain2 Pihak Berelasi | AF4: Liabilitas Sewa Jangka pendek | AG4: Liabilitas Sewa Jangka Panjang | AH4: Utang Bank & Leasing | AI4: Utang Pajak | AJ4: Utang pembelian aset tetap jangka pendek | AK4: Imbalan Pasca Kerja | AL4: Modal Saham | AM4: Tambahan Modal Disetor | AN4: Surplus | AO4: Penghasilan Komprehensif Lainnya | AP4: Koreksi Auditor | AQ4: Ditentukan Penggunaannya | AR4: Dividen | AS4: Proforma Ekuitas | AT4: Saldo Laba | AU4: Pendapatan Usaha | AV4: Beban Pokok Pendapatan Usaha | AW4: Beban Penjualan | AX4: Beban Umum dan Administrasi | AY4: Beban(Pendapatan) Lain-lain | AZ4: Beban Bunga dan Keuangan | BA4: Income Tax | BB4: Penyesuain Audit | BC4: Other Comprehensive Income
H5: Pihak Berelasi | N5: Expenses
B7: 45473 | C7: ='BS Konsol'!H11 -> 565886797 | D7: ='BS Konsol'!H14 -> 26199584563 | E7: ='BS Konsol'!H13 -> 422639675 | H7: ='BS Konsol'!H26 -> 0 | I7: ='BS Konsol'!H16 -> 510634104 | J7: ='BS Konsol'!H17 -> 224990831176 | K7: ='BS Konsol'!H20 -> 2074112410 | L7: ='BS Konsol'!H18 -> 2649404556 | M7: ='BS Konsol'!H19 -> 10425187749 | N7: 0 | R7: ='BS Konsol'!H34 -> 70317926651 | U7: ='BS Konsol'!H43 -> 7714047638 | V7: ='BS Konsol'!H45 -> 1790182139 | X7: =-'BS Konsol'!H61 -> -207371015601 | Y7: =-'BS Konsol'!H69 -> -1869894064 | Z7: 0 | AA7: =-'BS Konsol'!H58 -> -14186291754 | AC7: =-'BS Konsol'!H62 -> -4322494743 | AD7: 0 | AE7: 0 | AF7: 0 | AG7: 0 | AH7: 0 | AI7: =-'BS Konsol'!H63 -> -404042742 | AJ7: =-'BS Konsol'!H66 -> -38822068 | AK7: =-'BS Konsol'!H81 -> -9301883257 | AL7: =-'BS Konsol'!H97 -> -55000000000 | AM7: =-'BS Konsol'!H99 -> -49739416785 | AN7: 0 | AO7: =-'BS Konsol'!H102 -> 377072852 | AQ7: =-'BS Konsol'!H104 -> -410000000 | AR7: 15000000000 | AS7: 0 | AT7: =AT8 -> -19521729837 | AU7: =-'PL Konsol'!J11 -> -106697349798 | AV7: =-'PL Konsol'!J12 -> 69221185606 | AW7: =-'PL Konsol'!J16 -> 8866046154 | AX7: =-'PL Konsol'!J17 -> 13412401091 | AY7: =-'PL Konsol'!J18 -> 4496948237 | AZ7: =-'PL Konsol'!J19 -> 9308297571 | BA7: =-'PL Konsol'!J25 -> 520551680 | BD7: =SUM(C7:BC7) -> 0 | BE7: =BD7/2 -> 0 | BF7: =BE7/2 -> 0
B8: 45291 | C8: ='BS Konsol'!L11 -> 2570121355 | D8: ='BS Konsol'!L14 -> 19981020112 | E8: ='BS Konsol'!L13 -> 211054410 | H8: ='BS Konsol'!L26 -> 7022707423 | I8: ='BS Konsol'!L16 -> 510634104 | J8: ='BS Konsol'!L17 -> 218071396362 | K8: ='BS Konsol'!L20 -> 1104447053 | L8: ='BS Konsol'!L18 -> 2415719386 | M8: ='BS Konsol'!L19 -> 9663458887 | N8: 0 | R8: ='BS Konsol'!L34 -> 74113104582 | U8: ='BS Konsol'!L43 -> 7871477182 | V8: ='BS Konsol'!L45 -> 1790182139 | X8: =-'BS Konsol'!L61 -> -195441714689 | Y8: =-'BS Konsol'!L69 -> -3807894064 | Z8: 0 | AA8: =-'BS Konsol'!L58 -> -20407901137 | AC8: =-'BS Konsol'!L62 -> -2870843988 | AD8: =-'BS Konsol'!L77 -> -41000000 | AE8: =-'BS Konsol'!L76 -> -595676695 | AF8: =-'BS Konsol'!L68 -> -624277457 | AG8: 0 | AH8: 0 | AI8: =-'BS Konsol'!L63 -> -2863697915 | AJ8: =-'BS Konsol'!L66 -> -76360023 | AK8: =-'BS Konsol'!L81 -> -9301883257 | AL8: =-'BS Konsol'!L97 -> -40000000000 | AM8: =-'BS Konsol'!L99 -> -49739416785 | AN8: 0 | AO8: =-'BS Konsol'!L102 -> 377072852 | AP8: =-6464981.73071289 -> -6464981.7 | AQ8: =-'BS Konsol'!L104-'KK CF Konsol Juni 24'!AP8 -> -4.0353502e+08 | AS8: 0 | AT8: =-'BS Konsol'!L105 -> -19521729837 | BD8: =SUM(C8:BC8) -> 0
B9: Selisih | C9: =C7-C8 -> -2004234558 | D9: =D7-D8 -> 6218564451 | E9: =E7-E8 -> 211585265 | F9: =F7-F8 -> 0 | G9: =G7-G8 -> 0 | H9: =H7-H8 -> -7022707423 | I9: =I7-I8 -> 0 | J9: =J7-J8 -> 6919434814 | ... N9: =N7-N8 -> 0 | P9: =P7-P8 -> 0 | Q9: =Q7-Q8 -> 0 | R9: =R7-R8 -> -3795177931 | S9: =S7-S8 -> 0 | T9: =T7-T8 -> 0 | U9: =U7-U8 -> -157429544 | V9: =V7-V8 -> 0 | W9: =W7-W8 -> 0 | ... BC9: =BC7-BC8 -> 0 | BD9: =SUM(C9:BC9) -> 0 | BE9: =BD9/2 -> 0 | BF9: =BE9/2 -> 0
B10: Movement
A11: ARUS KAS DARI AKTIVITAS OPERASI
A12: Penerimaan Kas dari Pelanggan | B12: =SUM(D12:BC12) -> 100267200082 | D12: =-D9 -> -6218564451 | E12: =-E9 -> -211585265 | F12: =-F9 -> 0 | AB12: =-AB9 -> 0 | AU12: =-AU9 -> 106697349798
A13: Pembayaran Kepada Pemasok | B13: =SUM(D13:BC13) -> -73323475715 | H13: =-H9 -> 7022707423 | I13: =-I9 -> 0 | J13: =-J9 -> -6919434814 | K13: =-K9 -> -969665357 | N13: =-N9 -> 0 | P13: =-P9 -> 0 | Q13: =-Q9 -> 0 | W13: =-W9 -> 0 | Z13: =-Z9 -> 0 | AA13: =-AA9 -> -6221609383 | AC13: =-AC9 -> 1451650755 | AD13: =-AD9 -> -41000000 | AF13: =-AF9-AF40 -> 0 | AH13: =-AH9 -> 0 | AJ13: =-AJ9 -> -37537955 | AO13: =-AO9-AO29 -> 0 | AV13: =-AV9-AV14-AV15 -> -58462757120 | AX13: =-AX9-AX14-AX15 -> -4648881027 | AY13: =-(AY9+AY15+AY20) -> -4496948237 | BB13: =-2767717677.36858*0 -> 0 | BC13: =-BC9 -> 0
A14: Pembayaran Kepada Karyawan | B14: =SUM(D14:BC14) -> -15569341077 | G14: =-G9 -> 0 | AP14: =-AP9 -> -6464981.7 | AQ14: =-AQ9 -> 6464981.7 | AV14: =-(SUM('WS Konsol'!AF609:AF614)+'WS Konsol'!AF617+'WS Konsol'!AF620) -> -7409494527 | AX14: =-'WS Konsol'!AH665 -> -8159846550
A15: Pembayaran Beban Operasional Lainnya | B15: =SUM(D15:BC15) -> -7910563784 | L15: =-L9 -> -233685170 | M15: =-M9 -> -761728862 | R15: =-R9 -> 3795177931 | U15: =-U9 -> 157429544 | V15: =-V9 -> 0 | X15: =-X9-X37-X38 -> 1938000000 | AG15: =-AG9 -> 0 | AI15: =-AI9-AI21 -> 533448080 | AK15: =-AK9 -> 0 | AV15: =-('WS Konsol'!AF618+'WS Konsol'!AF619+'WS Konsol'!AF623) -> -3348933959 | AW15: =-AW9 -> -8866046154 | AX15: =-SUM('WS Konsol'!AF707:AF718) -> -603673514 | AY15: =68879296*0 -> 0 | BA15: =-BA9 -> -520551680
A16: Penerimaan Bunga | B16: =SUM(D16:BC16) -> 0
A17: Deferred tax | B17: =SUM(D17:BC17) -> 0 | BC17: 0
A18: Employee benefit | B18: =SUM(D18:BC18) -> 0
A19: Pembayaran Deviden | B19: =SUM(D19:BC19) -> 0 | BF19: 2993103253
A20: Pembayaran Bunga | B20: =SUM(D20:BC20) -> -9308297571 | AZ20: =-AZ9 -> -9308297571 | BE20: Beban Pajak Kini Juni 24 | BF20: =-BA21 -> 0
A21: Pembayaran Pajak Penghasilan | B21: =SUM(D21:BC21) -> -2993103253 | AI21: -2993103253 | BE21: Selisih | BF21: =BF19-BF20 -> 2993103253
A22: Kas diperoleh dari (digunakan untuk) operasi | B22: =SUM(B12:B21) -> -8837581318
BE23: Utang Pajak IAS 23 | BF23: 1699681675
BE24: Utang Pajak ISP 23 | BF24: 1164016240
A25: Kas Bersih Diperoleh dari Aktivitas Operasi | BE25: Total | BF25: =SUM(BF23:BF24) -> 2863697915
BE26: Selisih | BF26: =BF19-BF25 -> 129405338
A27: ARUS KAS DARI AKTIVITAS INVESTASI
A28: Penambahan Aset Tetap | B28: =SUM(D28:BC28) -> 0 | R28: 0 | S28: =-S9 -> 0 | AS28: 0 | AT28: =-AT9 -> 0 | BE28: Utang Pajak PPh 29 ISP 22-23 | BF28: 464326518
A29: Penempatan Investasi pada Ventura Bersama | B29: =SUM(D29:BC29) -> 0 | BF29: 478730259
A30: Penambahan Aset Tersedia untuk dijual | B30: =SUM(D30:BC30) -> 0 | BF30: 97162281
A31: Penambahan PI | B31: =SUM(D31:BC31) -> 0 | BE31: Total Utang Pajak PPh 29 ISP 21-23 | BF31: =SUM(BF28:BF30) -> 1040219058
A32: Penerimaan Piutang lain-lain dari Pihak Berelasi | B32: =SUM(D32:BC32) -> 0
A33: Pinjaman kepada Entitas Berelasi | B33: =SUM(D33:BC33) -> 0 | BE33: Utang Pajak PPh 29 IAS 22-23 | BF33: 1063969216
A34: Kas Bersih Diperoleh dari (Digunakan untuk) Aktivitas Investasi | B34: =SUM(B28:B33) -> 0 | BF34: 577405049
BE35: Total Utang Pajak PPh 29 IAS 22-23 | BF35: =SUM(BF33:BF34) -> 1641374265
A36: ARUS KAS DARI AKTIVITAS PENDANAAN | BE36: Total Utang Pajak PPh 29 IAS ISP | BF36: =BF35+BF31 -> 2681593323
A37: Penerimaan Pinjaman dari Bank | B37: =SUM(E37:BC37) -> 369706236685 | X37: 369706236685 | BE37: Selisih | BF37: =BF36-BF21 -> -311509930
A38: Pembayaran Pinjaman Bank | B38: =SUM(E38:BC38) -> -361652935773 | X38: -359714935773 | Y38: =-Y9 -> -1938000000 | BF38: =BF26-BF37 -> 440915268
A39: Pinjaman kepada Koperasi | B39: =SUM(D39:BC39) -> 0
A40: Lembaga Pembiayaan | B40: =SUM(D40:BC40) -> -624277457 | AF40: =-'BS Konsol'!L68 -> -624277457
A41: Setoran Modal | B41: =SUM(D41:BC41) -> 0 | AL41: =-AL9 -> 15000000000 | AR41: =-AR9 -> -15000000000
A42: Pembayaran Pembelian Aset Tetap | B42: =SUM(D42:BC42) -> 0
A43: Penerimaan dari Pemegang Saham | B43: =SUM(D43:BC43) -> -595676695 | AE43: =-AE9 -> -595676695
A44: Kas Bersih Diperoleh dari Aktivitas Pendanaan | B44: =SUM(B37:B43) -> 6833346760
A46: Dampak Kenaikan Selisih Kurs
A49: Kenaikan Bersih Kas & Bank | B49: =B44+B34+B22 -> -2004234558
A51: Saldo Bank Awal Tahun | B51: =C8 -> 2570121355
A53: Saldo Bank Akhir Tahun | B53: =B49+B51 -> 565886797
C54: =SUM(C9:C53) -> -2004234558 | D54: =SUM(D9:D53) -> 0 | E54: =SUM(E9:E53) -> 0 | F54: =SUM(F9:F53) -> 0 | G54: =SUM(G9:G53) -> 0 | H54: =SUM(H9:H53) -> 0 | I54: =SUM(I9:I53) -> 0 | J54: =SUM(J9:J53) -> 0 | ... X54: =SUM(X9:X53) -> 0 | Z54: =SUM(Z9:Z53) -> 0 | AA54: =SUM(AA9:AA53) -> 0 | AB54: =SUM(AB9:AB53) -> 0 | AC54: =SUM(AC9:AC53) -> 0 | AD54: =SUM(AD9:AD53) -> 0 | AE54: =SUM(AE9:AE53) -> 0 | AF54: =SUM(AF9:AF53) -> 0 | AG54: =SUM(AG9:AG53) -> 0 | ... AO54: =SUM(AO9:AO53) -> 0 | AS54: =SUM(AS9:AS53) -> 0 | AT54: =SUM(AT9:AT53) -> 0 | AU54: =SUM(AU9:AU53) -> 0 | AV54: =SUM(AV9:AV53) -> 0 | AX54: =SUM(AX9:AX53) -> 0 | AY54: =SUM(AY9:AY53) -> 0 | BA54: =SUM(BA9:BA53) -> 0 | BB54: =SUM(BB9:BB53) -> 0 | BC54: =SUM(BC9:BC53) -> 0 | BD54: =SUM(D54:BC54) -> 0
B57: ='BS Konsol'!H11 -> 565886797
A58: CONTROL | B58: =B57-B53 -> 0

Sheet ELIM & CAJE Des 24
A1: JURNAL ELIMINASI | F1: Diff | G1: =G2-H2 -> 0.11999512
A2: Konsolidasi Desember 2024 | F2: Kontrol | G2: =F3+H3 -> 1.7481431e+11 | H2: =G3+I3 -> 1.7481431e+11
F3: =SUM(F8:F48) -> 1.2777847e+11 | G3: =SUM(G8:G48) -> 1.2777847e+11 | H3: =SUM(H8:H48) -> 4.7035845e+10 | I3: =SUM(I8:I48) -> 4.7035845e+10
A5: Account No. | B5: Date | C5: Account Name | E5: WP Reff | F5: Balance Sheet | H5: PL | J5: Description
F6: Debit | G6: Credit | H6: Debit | I6: Credit
A8: ELIM 1 | C8: PT Indo American Seafoods (Keuangan) | F8: 86709426551 | J8: Eleminasi Utang Piutang Keuangan
A9: =A8 -> ELIM 1 | D9: PT Indokom Samudra Persada (Keuangan) | G9: =F8 -> 86709426551 | J9: =J8 -> Eleminasi Utang Piutang Keuangan
A11: ELIM 2 | C11: PT Indokom Samudra Persada | F11: 29592782261 | J11: Eleminasi Utang Piutang
A12: =A11 -> ELIM 2 | D12: PT Indo American Seafoods | G12: =F11 -> 29592782261 | J12: =J11 -> Eleminasi Utang Piutang
A14: ELIM 3 | C14: PT Indo American Seafoods | F14: 4557621225 | J14: Eleminasi Utang Piutang
A15: =A14 -> ELIM 3 | D15: PT Indokom Samudra Persada | G15: =F14 -> 4557621225 | J15: =J14 -> Eleminasi Utang Piutang
A17: ELIM 4 | C17: Indo American Seafoods, PT (Saham) | F17: 1050000000 | J17: Eleminasi IAS Investasi pada Anak
A18: =A17 -> ELIM 4 | D18: PT Indo American Seafoods (Modal) | G18: =F17 -> 1050000000 | J18: =J17 -> Eleminasi IAS Investasi pada Anak
A21: ELIM 5 | C21: Penjualan Lokal ISP to IAS | H21: 2.9814768e+10 | J21: Eleminasi Penjualan ISP to IAS
A22: ELIM 5 | C22: Pendapatan Lain-Lain | H22: 390631231 | J22: =J21 -> Eleminasi Penjualan ISP to IAS
A23: ELIM 5 | C23: Penjualan Roti | H23: 1744087000 | J23: =J22 -> Eleminasi Penjualan ISP to IAS
A24: ELIM 5 | D24: Pembelian Bahan Baku to IAS | I24: 2.9814768e+10 | J24: =J23 -> Eleminasi Penjualan ISP to IAS
A25: ELIM 5 | D25: Pembelian Baku Pembantunya | I25: 2134718228 | J25: =J24 -> Eleminasi Penjualan ISP to IAS
A27: ELIM 6 | C27: Penjualan IAS | H27: 1.5071359e+10 | J27: Eleminasi Penjualan IAS to ISP
A28: ELIM 6 | D28: Pembelian ISP | I28: =14960074583+111284000 -> 15071358583 | J28: =J27 -> Eleminasi Penjualan IAS to ISP
A30: ELIM 7 | C30: LABA DITAHAN | F30: =4762924959.34294+105713339 -> 4.8686383e+09
A31: =A30 -> ELIM 7 | D31: Tambahan Modal Disetor (Tax Amnesty) | G31: =F30 -> 4.8686383e+09
A33: ELIM 8 | C33: Modal Disetor (ISP) | F33: 1000000000
A34: =A33 -> ELIM 8 | D34: Tambahan Modal Disetor (Tax Amnesty) | G34: =F33 -> 1000000000
C35: (Mengeliminasi modal disetor ISP selain kepemilikan IAS menjadi tambahan modal disetor atas kombinasi bisnis entitas sepengendali)
A37: =A38 -> CAJE 1 | C37: Pendapatan Lain-Lain | F37: =G38 -> 2
A38: CAJE 1 | D38: LABA DITAHAN | G38: 2
C39: (Adj atas Ctrl)
A41: ELIM 8 | C41: Pendapatan Lain-Lain | H41: 15000000
A42: =A41 -> ELIM 8 | D42: Sewa IPAL | I42: =H41 -> 15000000
C43: (Eleminasi Sewa IPAL 2024)

Sheet ELIM & CAJE Sept 24
B1: JURNAL ELIMINASI
B2: Konsolidasi September 2024
B5: Account No. | C5: Date | D5: Account Name | F5: WP Reff | G5: Balance Sheet | I5: PL | K5: Description
G6: Debit | H6: Credit | I6: Debit | J6: Credit
B8: ELIM 1 | D8: PT Indo American Seafoods (Keuangan) | G8: =H9 -> 94963698422 | K8: Eleminasi Utang Piutang Keuangan
B9: =B8 -> ELIM 1 | E9: PT Indokom Samudra Persada (Keuangan) | H9: 94963698422 | K9: =K8 -> Eleminasi Utang Piutang Keuangan
B11: ELIM 2 | D11: PT Indokom Samudra Persada | G11: 34916763132 | K11: Eleminasi Utang Piutang
B12: =B11 -> ELIM 2 | E12: PT Indo American Seafoods | H12: =G11 -> 34916763132 | K12: =K11 -> Eleminasi Utang Piutang
B14: ELIM 3 | D14: PT Indo American Seafoods | G14: 2637090788 | K14: Eleminasi Utang Piutang
B15: =B14 -> ELIM 3 | E15: PT Indokom Samudra Persada | H15: =G14 -> 2637090788 | K15: =K14 -> Eleminasi Utang Piutang
B17: ELIM 4 | D17: Indo American Seafoods, PT (Saham) | G17: 1050000000 | K17: Eleminasi IAS Investasi pada Anak
B18: =B17 -> ELIM 4 | E18: PT Indo American Seafoods (Modal) | H18: =G17 -> 1050000000 | K18: =K17 -> Eleminasi IAS Investasi pada Anak
B21: ELIM 5 | D21: Penjualan Lokal ISP to IAS | I21: 19246827883 | K21: Eleminasi Penjualan ISP to IAS
B22: ELIM 5 | D22: Pendapatan Lain-Lain | I22: 271648678 | K22: =K21 -> Eleminasi Penjualan ISP to IAS
B23: ELIM 5 | D23: Penjualan Roti | I23: 1388066000 | K23: =K22 -> Eleminasi Penjualan ISP to IAS
B24: ELIM 5 | E24: Pembelian to IAS | J24: 19246827883 | K24: =K23 -> Eleminasi Penjualan ISP to IAS
B25: ELIM 5 | E25: Pembelian Lain-lain | J25: 1659714678 | K25: =K24 -> Eleminasi Penjualan ISP to IAS
B27: ELIM 6 | D27: Penjualan IAS | I27: 11201885196 | K27: Eleminasi Penjualan IAS to ISP
B28: ELIM 6 | E28: Pembelian ISP | J28: 11201885196 | K28: =K27 -> Eleminasi Penjualan IAS to ISP
B30: ELIM 7 | D30: LABA DITAHAN | I30: 5868638298
B31: =B30 -> ELIM 7 | E31: Tambahan Modal Disetor (Tax Amnesty) | J31: =I30 -> 5868638298
B34: CAJE 1 | E34: LABA DITAHAN | H34: 2
B35: =B34 -> CAJE 1 | D35: Piutang Lain-lain di bawah Rp 20.000.000,- | G35: =H34 -> 2
D36: (Adj atas Ctrl)

Sheet DTA Konsol
H3: Dibebankan ke
H4: Penghasilan
H5: komprehensif
D6: 1 Januari | F6: Dikreditkan | H6: lain/ | J6: 31 Desember
D7: 2024/ | F7: ke laba rugi/ | H7: Charged to | J7: 2024/
D8: January 1, | F8: Credited to | H8: other | J8: December 31,
D9: 2024 | F9: Profit or loss | H9: comprehensive | J9: 2024
C11: Imbalan kerja | D11: =J28 -> 2045497897 | F11: ='DTA ISP'!F12+'DTA IAS'!F11 -> 1.9443526e+08 | G11: ='DTA ISP'!F12+'DTA IAS'!F11 -> 1.9443526e+08 | H11: ='DTA IAS'!H11+'DTA ISP'!H12 -> 4867315.9 | J11: =D11+F11+H11 -> 2.2448005e+09 | K11: Employee benefits
C12: Cadangan Kerugian Piutang | D12: =J29 -> 352336430 | F12: ='DTA ISP'!F13+'DTA IAS'!F12 -> -77205942 | H12: 0 | J12: =SUM(D12:H12) -> 2.7513049e+08 | K12: Allowance for Impairment Losses
C13: Penyusutan Aset Tetap | D13: =J30 -> -607652187 | F13: ='DTA IAS'!F13 -> 0 | H13: 0 | J13: =SUM(D13:H13) -> -607652187 | K13: Depreciation
C15: Aset pajak tangguhan | D15: =SUM(D11:D13) -> 1790182140 | F15: =SUM(F11:F13) -> 1.1722932e+08 | H15: =SUM(H11:H13) -> 4867315.9 | J15: =SUM(J11:J13) -> 1.9122788e+09 | K15: Deferred tax assets
D16: ='BS Konsol-Des 24'!Q37 -> 1790182140 | F16: ='PL Konsol'!M26 -> 76646095 | H16: ='PL Konsol'!M42 -> -17850458 | J16: ='BS Konsol-Des 24'!G37 -> 1848977778
D17: =D15-D16 -> 0 | F17: =F15+F16 -> 1.9387542e+08 | H17: =H15-H16 -> 22717774 | J17: =J15-J16 -> 63301001
H20: Dibebankan ke
H21: Penghasilan
H22: komprehensif
D23: 1 Januari | F23: Dikreditkan | H23: lain/ | J23: 31 Desember
D24: 2023/ | F24: ke laba rugi/ | H24: Charged to | J24: 2023/
D25: January 1, | F25: Credited to | H25: other | J25: December 31,
D26: 2023 | F26: Profit or loss | H26: comprehensive | J26: 2023
C28: Imbalan kerja | D28: 1818231019 | F28: 224932788 | H28: 2334090 | J28: 2045497897 | K28: Employee benefits
C29: Cadangan Kerugian Piutang | D29: 249921940 | F29: 102414490 | H29: - | J29: 352336430 | K29: Allowance for Impairment Losses
C30: Penyusutan | D30: -559875653 | F30: -47776534 | H30: - | J30: -607652187 | K30: Depreciation
C32: Aset Pajak Tangguhan | D32: =SUM(D28:D30) -> 1508277306 | F32: =SUM(F28:F30) -> 279570744 | H32: =SUM(H28:H30) -> 2334090 | J32: =SUM(J28:J30) -> 1790182140 | K32: Deferred tax assets
D38: Desember 2023 | F38: Desember 2024
C39: Beban Imbalan Pasca kerja | D39: ='WS Konsol'!AI693 -> 872138766 | F39: ='WS Konsol'!M693 -> 883796658
C40: Utang Imbalan Pasca Kerja | D40: ='BS Konsol-Des 24'!Q76 -> 9301883257 | F40: ='BS Konsol-Des 24'!G76 -> 10104541472
C41: OCI IPK | D41: ='WS Konsol'!AI758 -> -10609502 | F41: ='WS Konsol'!M758 -> 81138443
C42: Beban CKPN | D42: ='WS Konsol'!AI727 -> -119304064 | F42: ='WS Konsol'!M727 -> -417767101
C43: Penyusutan Aset Tetap | D43: ='WS Konsol'!BK705*50% -> 2.0761029e+08 | F43: ='WS Konsol'!BJ705*50% -> 724750431

Sheet DTA ISP
H4: Dibebankan ke
H5: Penghasilan
H6: komprehensif
D7: 1 Januari | F7: Dikreditkan | H7: lain/ | J7: 31 Desember
D8: 2024/ | F8: ke laba rugi/ | H8: Charged to | J8: 2024/
D9: January 1, | F9: Credited to | H9: other | J9: December 31,
D10: 2024 | F10: Profit or loss | H10: comprehensive | J10: 2024
C12: Imbalan kerja | D12: 1462993790 | F12: 130595067 | H12: -6491571 | J12: =SUM(D12:H12) -> 1587097286 | K12: Employee benefits
C13: Cadangan Kerugian Piutang | D13: 152790529 | F13: -117789170 | H13: 0 | J13: =SUM(D13:H13) -> 35001359 | K13: Allowance for Impairment Losses
C14: Aset Hak Guna | D14: -68171964 | F14: 0 | H14: 0 | J14: =SUM(D14:H14) -> -68171964 | K14: Depreciation
C16: Aset pajak tangguhan | D16: =SUM(D12:D14) -> 1547612355 | F16: =SUM(F12:F14) -> 12805897 | H16: =SUM(H12:H14) -> -6491571 | J16: =SUM(J12:J14) -> 1553926681 | K16: Deferred tax assets

Sheet DTA IAS
H3: Dibebankan ke
H4: Penghasilan
H5: komprehensif
D6: 1 Januari | F6: Dikreditkan | H6: lain/ | J6: 31 Desember
D7: 2024/ | F7: ke laba rugi/ | H7: Charged to | J7: 2024/
D8: January 1, | F8: Credited to | H8: other | J8: December 31,
D9: 2024 | F9: Profit or loss | H9: comprehensive | J9: 2024
C11: Imbalan kerja | D11: =J28 -> 582504106 | F11: 63840198 | H11: ='[189]AJE-CAJE-Des Audit'!J21 -> 11358887 | J11: =SUM(D11:H11) -> 6.5770319e+08 | K11: Employee benefits
C12: Cadangan Kerugian Piutang | D12: =J29 -> 199545901 | F12: 40583228 | J12: =SUM(D12:H12)+1 -> 2.4012913e+08 | K12: Allowance for Impairment Losses
C13: Penyusutan | D13: =J30 -> -539480223 | F13: ='[189]AJE-CAJE-Des Audit'!I29 -> 0 | J13: =SUM(D13:H13) -> -539480223 | K13: Depreciation
C15: Aset pajak tangguhan | D15: =SUM(D11:D13) -> 242569784 | F15: =SUM(F11:F13) -> 1.0442343e+08 | H15: =SUM(H11:H13) -> 11358887 | J15: =SUM(J11:J13) -> 3.583521e+08 | K15: Deferred tax assets
F16: 1.0442343e+08 | H16: =[190]PL!$F$28 -> 11358887 | J16: 3.583521e+08
F17: =F15-F16 -> 0 | H17: =H15-H16 -> 0 | J17: =J15-J16 -> -0.032033086
H20: Dibebankan ke
H21: Penghasilan
H22: komprehensif
D23: 1 Januari | F23: Dikreditkan | H23: lain/ | J23: 31 Desember
D24: 2023/ | F24: ke laba rugi/ | H24: Charged to | J24: 2023/
D25: January 1, | F25: Credited to | H25: other | J25: December 31,
D26: 2023 | F26: Profit or loss | H26: comprehensive | J26: 2023
C28: Imbalan kerja | D28: 519812376 | F28: 61508332 | H28: 1183398 | J28: =SUM(D28:H28) -> 582504106 | K28: Employee benefits
C29: Cadangan Kerugian Piutang | D29: 173299007 | F29: 26246894 | H29: - | J29: =SUM(D29:H29) -> 199545901 | K29: Allowance for Impairment Losses
C30: Penyusutan | D30: -513553677 | F30: -25926546 | H30: - | J30: =SUM(D30:H30) -> -539480223 | K30: Depreciation
C32: Aset Pajak Tangguhan | D32: =SUM(D28:D30) -> 179557706 | F32: =SUM(F28:F30) -> 61828680 | H32: =SUM(H28:H30) -> 1183398 | J32: =SUM(J28:J30) -> 242569784 | K32: Deferred tax assets
D38: Desember 2023 | F38: Desember 2024
C39: Beban Imbalan Pasca kerja | D39: =[189]WS!AB446 -> 279583328 | F39: =[189]WS!Q446 -> 290182718
C40: Utang Imbalan Pasca Kerja | D40: =[189]BS!L65 -> 2647745936 | F40: =[189]BS!H65 -> 2886297350
C41: OCI IPK | D41: =[189]WS!AB499 -> -5379083 | F41: =[189]WS!Q499 -> 51631304
C42: Beban CKPN | D42: =[189]WS!AB484 -> 0 | F42: =[189]WS!Q484 -> -8.2428015e+08
C43: Penyusutan Aset Tetap | D43: =[189]WS!AB457 -> 19295242 | F43: =[189]WS!Q457 -> 10112250

Sheet IPK IAS
D5: 2024 | F5: 2023
C7: Saldo awal | D7: =F16 -> 2647745936 | F7: 2362783525
C8: Beban imbalan paska kerja
C9: selama tahun berjalan | D9: 290182718 | F9: 279583328
C10: Pengukuran kembali atas
C11: liabilitas diestimasi atas
C12: imbalan kerja karyawan | D12: -51631304 | F12: 5379083 | I12: =F16 -> 2647745936 | J12: Saldo awal ipk des 23 | K12: liabilitas
C13: Pembayaran Imbalan Pasca | I13: =D23 -> 107488248 | J13: Biaya Jasa Kini | K13: beban opex
C14: Kerja pada tahun berjalan | F14: 0 | I14: =D24 -> 182694470 | J14: Biaya Bunga | K14: beban opex
C16: Saldo Akhir Liabilitas | D16: =SUM(D7:D14) -> 2886297350 | F16: =SUM(F7:F14) -> 2647745936 | I16: =D12 -> -51631304 | J16: Pendapatan oci berjalan | K16: oci pl
I18: =SUM(I12:I16) -> 2886297350 | J18: Saldo akhir ipk des 24 | K18: liabilitas
C19: Total beban imbalan paska kerja karyawan adalah sebagai berikut:
I20: jurnal
D21: 2024 | F21: 2023 | I21: =I14+I13 -> 290182718 | J21: beban ipk (opex)
J22: =I16 -> -51631304 | K22: oci pl berjalan ipk
C23: Biaya Jasa Kini | D23: 107488248 | F23: 104737347 | J23: =I21+J22 -> 238551414
C24: Biaya Bunga | D24: 182694470 | F24: 174845981
C25: Biaya Jasa Lalu 1 | D25: 0 | F25: 0
C26: Biaya Jasa Lalu 2 | D26: 0 | F26: 0
C27: Pembayaran Imbalan Pasca
C28: Kerja pada tahun berjalan | D28: 0 | F28: 0
C30: Jumlah Beban Imbalan Pasca Kerja Karyawan | D30: =SUM(D23:D28) -> 290182718 | F30: =SUM(F23:F28) -> 279583328
C33: Persentase perubahan kenaikan atau penurunan 1% terhadap tingkat diskonto
C35: 2024
D36: Nilai Kini
D37: Liabilitas/ | F37: Biaya Jasa
D38: Present Value | F38: Kini/
D39: of Benefit | F39: Current Service
C40: Deskripsi | D40: Liabilities | F40: Cost
C42: Sesuai Laporan Aktuaris 7,1% | D42: 2886297350 | F42: 107488248
C43: Penurunan 1% atas Tingkat Diskonto | D43: 3225007620 | F43: 125663793
C44: Kenaikan 1% atas Tingkat Diskonto | D44: 2596080895 | F44: 92260142
C49: Persentase perubahan kenaikan atau penurunan 1% terhadap tingkat kenaikan gaji.
C51: 2024
D52: Nilai Kini
D53: Liabilitas/ | F53: Biaya Jasa
D54: Present Value | F54: Kini/
D55: of Benefit | F55: Current Service
C56: Deskripsi | D56: Liabilities | F56: Cost
C58: Sesuai Laporan Aktuaris 7,1% | D58: 2886297350 | F58: 107488248
C59: Penurunan 1% atas Tingkat Kenaikan Gaji | D59: 2579747194 | F59: 92247118
C60: Kenaikan 1% atas Tingkat Kenaikan Gaji | D60: 3239602623 | F60: 125918312

Sheet WS Konsol
B1: KONSOLIDASI PT INDO AMERICAN SEAFOODS & PT INDOKOM SAMUDRA PERSADA (ISEA) | AK1: Aset ISP Baru 2023 | AL1: Penyusutan
B2: WORKING BALANCE SHEETS AND PROFIT OR LOSS | H2: 1 | AI2: -346216346 | AK2: 120000000 | AL2: -15000000
B3: UNTUK TAHUN YANG BERAKHIR 31 DES 2024, 2023, 2022 & 31 DES 2021 | AH3: =M437+M439+M438 -> 157970005
D4: =D255 -> 3.2247185e+11 | E4: =E255 -> 2.3670736e+11 | H4: =H255 -> 559179203740 | J4: =M512 -> 49739416785 | M4: =M255 -> 437269373703 | P4: =P255 -> 303311159346 | Q4: =Q255 -> 238370059673 | R4: =R255 -> 541681219019 | W4: =W255 -> 408113666679 | Y4: =Y255 -> 264940920774 | Z4: =Z255 -> 246014059585 | AA4: =AA255 -> 510954980359 | AF4: =AF255 -> 347660437458 | AH4: 1063969216 | AI4: =AI255 -> 345325322995 | AK4: 29115000 | AL4: -7278750 | AM4: =AM255 -> 281676261822 | AN4: =AN255 -> 234780115544 | AO4: =AO255 -> 516456377366 | AT4: =AT255 -> 331143637453 | AV4: =AV255 -> 274636437821 | AW4: =AW255 -> 226439584572 | AX4: =AX255 -> 501076022393 | BC4: =BC255 -> 356531626434 | BF4: =BF255 -> 307658424230 | BH4: =BH255 -> 262715700578
D5: =D539 -> 3.2247185e+11 | E5: =E539+1.82748413085937 -> 2.3670736e+11 | H5: =H539 -> 559179203740 | J5: =AI512 -> 49739416785 | M5: =M539 -> 437269373703 | P5: =P539 -> 3.0331116e+11 | Q5: =Q539 -> 2.3837006e+11 | R5: =R539 -> 541681219019 | W5: =W539 -> 408113666679 | Y5: =Y539 -> 264940920774 | Z5: =Z539 -> 246014059585 | AA5: =AA539 -> 510954980359 | AF5: =AF539 -> 347660437458 | AH5: 577405049 | AI5: =AI539 -> 345325322995 | AM5: =AM539 -> 281676261822 | AN5: =AN539 -> 234780115544 | AO5: =AO539 -> 516456377366 | AT5: =AT539 -> 331143637453 | AV5: =AV539 -> 274636437821 | AW5: =AW539 -> 226439584572 | AX5: =AX539 -> 501076022393 | BC5: =BC539 -> 356531626434 | BF5: =BF539 -> 307658424229 | BH5: =BH539 -> 262715700580
D6: =D4-D5 -> -1.7800293 | E6: =E4-E5 -> 0.42999268 | H6: =H4-H5 -> 0 | J6: =J4-J5 -> 0 | M6: =M4-M5 -> 0 | P6: =P4-P5 -> 0.5 | Q6: =Q4-Q5 -> 0.5 | R6: =R4-R5 -> 0 | W6: =W4-W5 -> 0 | Y6: =Y4-Y5 -> 0 | Z6: =Z4-Z5 -> 0 | AA6: =AA4-AA5 -> 0 | AF6: =AF4-AF5 -> 0 | AI6: =AI4-AI5 -> 0 | AM6: =AM4-AM5 -> 0 | AN6: =AN4-AN5 -> 0 | AO6: =AO4-AO5 -> 0 | AT6: =AT4-AT5 -> 0 | AV6: =AV4-AV5 -> 0 | AW6: =AW4-AW5 -> 0 | AX6: =AX4-AX5 -> 0 | BC6: =BC4-BC5 -> 0 | BF6: =BF4-BF5 -> 1 | BH6: =BH4-BH5 -> -2
F7: =SUM(F15:F764) -> #REF! | G7: =SUM(G15:G764) -> #REF! | J7: =SUM(J10:J1048576) -> 1.7481431e+11 | L7: =SUM(L10:L1048576) -> 1.7481431e+11
B8: No Account | C8: Description | D8: Audited PT IAS | E8: Audited PT ISP | H8: Audited Combine | I8: Eliminasi | M8: Audited Aggregated | P8: Audited PT IAS | Q8: Audited PT ISP | R8: Audited Konsol | S8: Eliminasi | W8: Audited Konsol | Y8: Audited PT IAS | Z8: Audited PT ISP | AA8: Audited Konsol | AB8: Eliminasi | AF8: Audited Konsol | AI8: Audited Konsol | AM8: Audited PT IAS | AN8: Audited PT ISP | AO8: Audited Konsol | AP8: Eliminasi | AT8: Audited Konsol | AV8: Audited PT IAS | AW8: Audited PT ISP | AX8: Audited Konsol | AY8: Eliminasi | BC8: Audited Konsol | BF8: Audited Konsol | BH8: Audited Konsol
D9: 31 Desember 2024 | E9: =D9 -> 31 Desember 2024 | H9: =E9 -> 31 Desember 2024 | I9: Reff | J9: Dr | K9: Reff | L9: Cr | M9: =H9 -> 31 Desember 2024 | P9: 30 Sept 2024 | Q9: =P9 -> 30 Sept 2024 | R9: =Q9 -> 30 Sept 2024 | S9: Reff | T9: Dr | U9: Reff | V9: Cr | W9: =R9 -> 30 Sept 2024 | Y9: 30 Juni 2024 | Z9: =Y9 -> 30 Juni 2024 | AA9: =Z9 -> 30 Juni 2024 | AB9: Reff | AC9: Dr | AD9: Reff | AE9: Cr | AF9: =AA9 -> 30 Juni 2024 | AI9: 31 Desember 2023 | AM9: 30 Sept 2023 | AN9: =AM9 -> 30 Sept 2023 | AO9: =AN9 -> 30 Sept 2023 | AP9: Reff | AQ9: Dr | AR9: Reff | AS9: Cr | AT9: =AO9 -> 30 Sept 2023 | AV9: 30 Juni 2023 | AW9: =AV9 -> 30 Juni 2023 | AX9: =AW9 -> 30 Juni 2023 | AY9: Reff | AZ9: Dr | BA9: Reff | BB9: Cr | BC9: =AX9 -> 30 Juni 2023 | BF9: 31 Desember 2022 | BH9: 31 Desember 2021
B11: ASSETS
B12: Current Assets
B13: Cash
B14: Kas Besar
C15: Kas in Lampung | D15: =ROUND(172746352.799988,0) -> 172746353 | E15: 59534151 | F15: =D15+E15 -> 232280504 | G15: =F15-H15 -> 0 | H15: =ROUND((D15+E15),0) -> 232280504 | M15: =ROUND((H15+J15-L15),0) -> 232280504 | P15: =ROUND(221717531.800003,0) -> 221717532 | Q15: 113360187 | R15: =ROUND((P15+Q15),0) -> 335077719 | W15: =ROUND((R15+T15-V15),0) -> 335077719 | Y15: =15178251 -> 15178251 | Z15: 87032612 | AA15: =ROUND((Y15+Z15),0) -> 102210863 | AF15: =ROUND((AA15+AC15-AE15),0) -> 102210863 | AI15: 161176676 | AM15: 60306962 | AN15: 106061959 | AO15: =ROUND((AM15+AN15),0) -> 166368921 | AT15: =ROUND((AO15+AQ15-AS15),0) -> 166368921 | AV15: 67573611 | AW15: 165787403 | AX15: =ROUND((AV15+AW15),0) -> 233361014 | BC15: =ROUND((AX15+AZ15-BB15),0) -> 233361014 | BF15: 155449063 | BH15: 160295840
B16: Kas Kecil | G16: =F16-H16 -> 0
C17: Kas in Lampung (Petty Cash) | G17: =F17-H17 -> 0 | H17: =ROUND((D17+E17),0) -> 0 | M17: =ROUND((H17+J17-L17),0) -> 0 | R17: =ROUND((P17+Q17),0) -> 0 | W17: =ROUND((R17+T17-V17),0) -> 0 | AA17: =ROUND((Y17+Z17),0) -> 0 | AF17: =ROUND((AA17+AC17-AE17),0) -> 0 | AI17: 685258 | AM17: 685258 | AO17: =ROUND((AM17+AN17),0) -> 685258 | AT17: =ROUND((AO17+AQ17-AS17),0) -> 685258 | AV17: 685258 | AW17: =0 -> 0 | AX17: =ROUND((AV17+AW17),0) -> 685258 | BC17: =ROUND((AX17+AZ17-BB17),0) -> 685258 | BF17: 685258 | BH17: 928838
C18: Total Cash | D18: =SUM(D15:D17) -> 172746353 | E18: =SUM(E15:E17) -> 59534151 | F18: =D18+E18 -> 232280504 | G18: =F18-H18 -> 0 | H18: =SUM(H15:H17) -> 232280504 | M18: =SUM(M15:M17) -> 232280504 | P18: =SUM(P15:P17) -> 221717532 | Q18: =SUM(Q15:Q17) -> 113360187 | R18: =SUM(R15:R17) -> 335077719 | W18: =SUM(W15:W17) -> 335077719 | Y18: =SUM(Y15:Y17) -> 15178251 | Z18: =SUM(Z15:Z17) -> 87032612 | AA18: =SUM(AA15:AA17) -> 102210863 | AF18: =SUM(AF15:AF17) -> 102210863 | AI18: =SUM(AI15:AI17) -> 161861934 | AM18: =SUM(AM15:AM17) -> 60992220 | AN18: =SUM(AN15:AN17) -> 106061959 | AO18: =SUM(AO15:AO17) -> 167054179 | AT18: =SUM(AT15:AT17) -> 167054179 | AV18: =SUM(AV15:AV17) -> 68258869 | AW18: =SUM(AW15:AW17) -> 165787403 | AX18: =SUM(AX15:AX17) -> 234046272 | BC18: =SUM(BC15:BC17) -> 234046272 | BF18: =SUM(BF15:BF17) -> 156134321 | BH18: =SUM(BH15:BH17) -> 161224678
B19: BANK | F19: =D19+E19 -> 0 | G19: =F19-H19 -> 0
B20: Bank IDR | F20: =D20+E20 -> 0 | G20: =F20-H20 -> 0
C21: Bank Mandiri Rp A/c 114.0031009999 | D21: 0 | F21: =D21+E21 -> 0 | G21: =F21-H21 -> 0 | M21: =ROUND((H21+J21-L21),0) -> 0 | W21: =ROUND((R21+T21-V21),0) -> 0 | Y21: 0 | AF21: =ROUND((AA21+AC21-AE21),0) -> 0 | AI21: 0 | AM21: 822318 | AO21: =ROUND((AM21+AN21),0) -> 822318 | AT21: =ROUND((AO21+AQ21-AS21),0) -> 822318 | AV21: 1647318 | AX21: =ROUND((AV21+AW21),0) -> 1647318 | BC21: =ROUND((AX21+AZ21-BB21),0) -> 1647318 | BF21: 3297318 | BH21: 22051764
C22: Bank Mandiri Rp A/c 114.0004692854 | D22: 4433481 | F22: =D22+E22 -> 4433481 | G22: =F22-H22 -> 0 | H22: =ROUND((D22+E22),0) -> 4433481 | M22: =ROUND((H22+J22-L22),0) -> 4433481 | P22: =ROUND(10743437.9000015,0) -> 10743438 | R22: =ROUND((P22+Q22),0) -> 10743438 | W22: =ROUND((R22+T22-V22),0) -> 10743438 | Y22: 6953129 | AA22: =ROUND((Y22+Z22),0) -> 6953129 | AF22: =ROUND((AA22+AC22-AE22),0) -> 6953129 | AI22: 2265171 | AM22: 48509780 | AO22: =ROUND((AM22+AN22),0) -> 48509780 | AT22: =ROUND((AO22+AQ22-AS22),0) -> 48509780 | AV22: 3367106 | AX22: =ROUND((AV22+AW22),0) -> 3367106 | BC22: =ROUND((AX22+AZ22-BB22),0) -> 3367106 | BF22: 364262986 | BH22: 2105276
C23: Bank BNI Rp A/c 111-559-9552 | D23: 15129380 | F23: =D23+E23 -> 15129380 | G23: =F23-H23 -> 0 | H23: =ROUND((D23+E23),0) -> 15129380 | M23: =ROUND((H23+J23-L23),0) -> 15129380 | P23: =ROUND(8192147868.13,0) -> 8192147868 | R23: =ROUND((P23+Q23),0) -> 8192147868 | W23: =ROUND((R23+T23-V23),0) -> 8192147868 | Y23: 2000000 | AA23: =ROUND((Y23+Z23),0) -> 2000000 | AF23: =ROUND((AA23+AC23-AE23),0) -> 2000000 | AO23: =ROUND((AM23+AN23),0) -> 0 | AT23: =ROUND((AO23+AQ23-AS23),0) -> 0 | AV23: 0 | AX23: =ROUND((AV23+AW23),0) -> 0 | BC23: =ROUND((AX23+AZ23-BB23),0) -> 0
C24: Bank BNI Rp A/c 115-599-4474 | D24: 1240726 | F24: =D24+E24 -> 1240726 | G24: =F24-H24 -> 0 | H24: =ROUND((D24+E24),0) -> 1240726 | M24: =ROUND((H24+J24-L24),0) -> 1240726 | P24: 7416582 | R24: =ROUND((P24+Q24),0) -> 7416582 | W24: =ROUND((R24+T24-V24),0) -> 7416582 | Y24: 2889324 | AA24: =ROUND((Y24+Z24),0) -> 2889324 | AF24: =ROUND((AA24+AC24-AE24),0) -> 2889324 | AI24: 1432417 | AM24: 1004849 | AO24: =ROUND((AM24+AN24),0) -> 1004849 | AT24: =ROUND((AO24+AQ24-AS24),0) -> 1004849 | AV24: 3435278 | AX24: =ROUND((AV24+AW24),0) -> 3435278 | BC24: =ROUND((AX24+AZ24-BB24),0) -> 3435278 | BF24: 4306134 | BH24: 9386921
C25: Bank JTRUST Rp A/c 1100024132 | D25: 3913648 | F25: =D25+E25 -> 3913648 | G25: =F25-H25 -> 0 | H25: =ROUND((D25+E25),0) -> 3913648 | M25: =ROUND((H25+J25-L25),0) -> 3913648 | P25: 4058511 | R25: =ROUND((P25+Q25),0) -> 4058511 | W25: =ROUND((R25+T25-V25),0) -> 4058511 | Y25: 4203129 | AA25: =ROUND((Y25+Z25),0) -> 4203129 | AF25: =ROUND((AA25+AC25-AE25),0) -> 4203129 | AI25: 4766585 | AM25: 57855666 | AO25: =ROUND((AM25+AN25),0) -> 57855666 | AT25: =ROUND((AO25+AQ25-AS25),0) -> 57855666 | AV25: 1075248406 | AX25: =ROUND((AV25+AW25),0) -> 1075248406 | BC25: =ROUND((AX25+AZ25-BB25),0) -> 1075248406 | BF25: 1129932080 | BH25: 17089985
C26: Bank JTRUST Rp A/c 2100596827 | D26: 726595 | F26: =D26+E26 -> 726595 | G26: =F26-H26 -> 0 | H26: =ROUND((D26+E26),0) -> 726595 | M26: =ROUND((H26+J26-L26),0) -> 726595 | P26: 816635 | R26: =ROUND((P26+Q26),0) -> 816635 | W26: =ROUND((R26+T26-V26),0) -> 816635 | Y26: 901635 | AA26: =ROUND((Y26+Z26),0) -> 901635 | AF26: =ROUND((AA26+AC26-AE26),0) -> 901635 | AI26: 1056635 | AM26: 1361833271 | AO26: =ROUND((AM26+AN26),0) -> 1361833271 | AT26: =ROUND((AO26+AQ26-AS26),0) -> 1361833271 | AV26: 1361249451 | AX26: =ROUND((AV26+AW26),0) -> 1361249451 | BC26: =ROUND((AX26+AZ26-BB26),0) -> 1361249451 | BF26: 1362643218 | BH26: 1372702466
B27: IAS-ISP | C27: PT Bank Mega Syariah | D27: 683621 | E27: =ROUND(212809.72,0) -> 212810 | F27: =D27+E27 -> 896431 | G27: =F27-H27 -> 0 | H27: =ROUND((D27+E27),0) -> 896431 | M27: =ROUND((H27+J27-L27),0) -> 896431 | P27: =ROUND(769578.893472222,0) -> 769579 | Q27: =ROUND(301158.865138889,0) -> 301159 | R27: =ROUND((P27+Q27),0) -> 1070738 | W27: =ROUND((R27+T27-V27),0) -> 1070738 | Y27: 862330 | Z27: 392159 | AA27: =ROUND((Y27+Z27),0) -> 1254489 | AF27: =ROUND((AA27+AC27-AE27),0) -> 1254489 | AI27: 2669146 | AM27: 2372570 | AN27: 660422 | AO27: =ROUND((AM27+AN27),0) -> 3032992 | AT27: =ROUND((AO27+AQ27-AS27),0) -> 3032992 | AV27: 2663885 | AW27: 749649 | AX27: =ROUND((AV27+AW27),0) -> 3413534 | BC27: =ROUND((AX27+AZ27-BB27),0) -> 3413534 | BF27: 3931829 | BH27: 5089373
B28: IAS-ISP | C28: PT Bank BTPN | D28: 67213934 | E28: =ROUND(43547299,0) -> 43547299 | F28: =D28+E28 -> 110761233 | G28: =F28-H28 -> 0 | H28: =ROUND((D28+E28),0) -> 110761233 | M28: =ROUND((H28+J28-L28),0) -> 110761233 | P28: 46506026 | Q28: =ROUND(20375141.1199951,0) -> 20375141 | R28: =ROUND((P28+Q28),0) -> 66881167 | W28: =ROUND((R28+T28-V28),0) -> 66881167 | Y28: 205777386 | Z28: 86009417 | AA28: =ROUND((Y28+Z28),0) -> 291786803 | AF28: =ROUND((AA28+AC28-AE28),0) -> 291786803 | AI28: 42918157 | AM28: 166397714 | AN28: 578492495 | AO28: =ROUND((AM28+AN28),0) -> 744890209 | AT28: =ROUND((AO28+AQ28-AS28),0) -> 744890209 | AV28: 5738942 | AW28: 250931552 | AX28: =ROUND((AV28+AW28),0) -> 256670494 | BC28: =ROUND((AX28+AZ28-BB28),0) -> 256670494 | BF28: 414748648 | BH28: 0
C29: Bank BRI Rp A/c 0285-01-220000-30-7 | D29: 0 | F29: =D29+E29 -> 0 | G29: =F29-H29 -> 0 | M29: =ROUND((H29+J29-L29),0) -> 0 | W29: =ROUND((R29+T29-V29),0) -> 0 | Z29: 0 | AF29: =ROUND((AA29+AC29-AE29),0) -> 0 | AI29: 794277 | AM29: 3002177 | AO29: =ROUND((AM29+AN29),0) -> 3002177 | AT29: =ROUND((AO29+AQ29-AS29),0) -> 3002177 | AV29: 2635177 | AX29: =ROUND((AV29+AW29),0) -> 2635177 | BC29: =ROUND((AX29+AZ29-BB29),0) -> 2635177
B30: ISP | C30: PT Bank Mandiri (Persero) Tbk-1140002150616 | E30: =ROUND(1781824.72,0) -> 1781825 | F30: =D30+E30 -> 1781825 | G30: =F30-H30 -> 0 | H30: =ROUND((D30+E30),0) -> 1781825 | M30: =ROUND((H30+J30-L30),0) -> 1781825 | Q30: =ROUND(16383216.0399933,0) -> 16383216 | R30: =ROUND((P30+Q30),0) -> 16383216 | W30: =ROUND((R30+T30-V30),0) -> 16383216 | Z30: 16374959 | AA30: =ROUND((Y30+Z30),0) -> 16374959 | AF30: =ROUND((AA30+AC30-AE30),0) -> 16374959 | AI30: 8242078 | AN30: 53444464 | AO30: =ROUND((AM30+AN30),0) -> 53444464 | AT30: =ROUND((AO30+AQ30-AS30),0) -> 53444464 | AW30: 119906147 | AX30: =ROUND((AV30+AW30),0) -> 119906147 | BC30: =ROUND((AX30+AZ30-BB30),0) -> 119906147 | BF30: 626284375 | BH30: 0
B31: ISP | C31: Bank Panin | F31: =D31+E31 -> 0 | G31: =F31-H31 -> 0 | H31: =ROUND((D31+E31),0) -> 0 | M31: =ROUND((H31+J31-L31),0) -> 0 | R31: =ROUND((P31+Q31),0) -> 0 | W31: =ROUND((R31+T31-V31),0) -> 0 | AF31: =ROUND((AA31+AC31-AE31),0) -> 0 | AI31: 0 | AO31: =ROUND((AM31+AN31),0) -> 0 | AT31: =ROUND((AO31+AQ31-AS31),0) -> 0 | AX31: =ROUND((AV31+AW31),0) -> 0 | BC31: =ROUND((AX31+AZ31-BB31),0) -> 0 | BF31: 0 | BH31: 0
B32: ISP | C32: PT Bank Danamon Indonesia, Tbk - Tabungan | F32: =D32+E32 -> 0 | G32: =F32-H32 -> 0 | H32: =ROUND((D32+E32),0) -> 0 | M32: =ROUND((H32+J32-L32),0) -> 0 | R32: =ROUND((P32+Q32),0) -> 0 | W32: =ROUND((R32+T32-V32),0) -> 0 | AF32: =ROUND((AA32+AC32-AE32),0) -> 0 | AI32: 0 | AO32: =ROUND((AM32+AN32),0) -> 0 | AT32: =ROUND((AO32+AQ32-AS32),0) -> 0 | AX32: =ROUND((AV32+AW32),0) -> 0 | BC32: =ROUND((AX32+AZ32-BB32),0) -> 0 | BF32: 0 | BH32: 253436672
C33: Bank BRI Rp A/c 0652-01-111111-301 | D33: 50621267 | F33: =D33+E33 -> 50621267 | G33: =F33-H33 -> 0 | H33: =ROUND((D33+E33),0) -> 50621267 | M33: =ROUND((H33+J33-L33),0) -> 50621267 | P33: 609796408 | R33: =ROUND((P33+Q33),0) -> 609796408 | W33: =ROUND((R33+T33-V33),0) -> 609796408
B34: Bank USD | F34: =D34+E34 -> 0 | G34: =F34-H34 -> 0
B35: IAS-ISP | C35: PT Bank Mandiri (Persero) Tbk | D35: 12106954 | F35: =D35+E35 -> 12106954 | G35: =F35-H35 -> 0 | H35: =ROUND((D35+E35),0) -> 12106954 | M35: =ROUND((H35+J35-L35),0) -> 12106954 | P35: 1707866 | Q35: =ROUND(1061022.81,0) -> 1061023 | R35: =ROUND((P35+Q35),0) -> 2768889 | W35: =ROUND((R35+T35-V35),0) -> 2768889 | Y35: 1852614 | Z35: 1150948 | AA35: =ROUND((Y35+Z35),0) -> 3003562 | AF35: =ROUND((AA35+AC35-AE35),0) -> 3003562 | AI35: 6596656 | AM35: 15232864 | AN35: 2956139 | AO35: =ROUND((AM35+AN35),0) -> 18189003 | AT35: =ROUND((AO35+AQ35-AS35),0) -> 18189003 | AV35: 18614806 | AW35: 32864868 | AX35: =ROUND((AV35+AW35),0) -> 51479674 | BC35: =ROUND((AX35+AZ35-BB35),0) -> 51479674 | BF35: 65953790 | BH35: 55262684
C36: Bank Mandiri $ (114,002,744,8284) USD | D36: 0 | F36: =D36+E36 -> 0 | G36: =F36-H36 -> 0 | H36: =ROUND((D36+E36),0) -> 0 | M36: =ROUND((H36+J36-L36),0) -> 0 | R36: =ROUND((P36+Q36),0) -> 0 | W36: =ROUND((R36+T36-V36),0) -> 0 | Y36: 656840 | Z36: 0 | AA36: =ROUND((Y36+Z36),0) -> 656840 | AF36: =ROUND((AA36+AC36-AE36),0) -> 656840 | AI36: 1927000 | AO36: =ROUND((AM36+AN36),0) -> 0 | AT36: =ROUND((AO36+AQ36-AS36),0) -> 0 | AV36: 0 | AX36: =ROUND((AV36+AW36),0) -> 0 | BC36: =ROUND((AX36+AZ36-BB36),0) -> 0 | BF36: 0 | BH36: 0
C37: PT Bank Negara Indonesia (Persero) Tbk $ | D37: 20695118 | F37: =D37+E37 -> 20695118 | G37: =F37-H37 -> 0 | H37: =ROUND((D37+E37),0) -> 20695118 | M37: =ROUND((H37+J37-L37),0) -> 20695118 | P37: =ROUND(8592468.89999962,0) -> 8592469 | R37: =ROUND((P37+Q37),0) -> 8592469 | W37: =ROUND((R37+T37-V37),0) -> 8592469 | Y37: 15297299 | Z37: 0 | AA37: =ROUND((Y37+Z37),0) -> 15297299 | AF37: =ROUND((AA37+AC37-AE37),0) -> 15297299 | AI37: 8054849 | AM37: 17036978 | AO37: =ROUND((AM37+AN37),0) -> 17036978 | AT37: =ROUND((AO37+AQ37-AS37),0) -> 17036978 | AV37: 733933691 | AX37: =ROUND((AV37+AW37),0) -> 733933691 | BC37: =ROUND((AX37+AZ37-BB37),0) -> 733933691 | BF37: 60924433 | BH37: 1126429101
C38: Bank JTRUST (1100024149) | D38: 8375633 | F38: =D38+E38 -> 8375633 | G38: =F38-H38 -> 0 | H38: =ROUND((D38+E38),0) -> 8375633 | M38: =ROUND((H38+J38-L38),0) -> 8375633 | P38: =ROUND(8142871.86,0) -> 8142872 | R38: =ROUND((P38+Q38),0) -> 8142872 | W38: =ROUND((R38+T38-V38),0) -> 8142872 | Y38: 9155353 | Z38: 0 | AA38: =ROUND((Y38+Z38),0) -> 9155353 | AF38: =ROUND((AA38+AC38-AE38),0) -> 9155353 | AI38: 9044094 | AM38: 11034944 | AO38: =ROUND((AM38+AN38),0) -> 11034944 | AT38: =ROUND((AO38+AQ38-AS38),0) -> 11034944 | AV38: 1592294698 | AX38: =ROUND((AV38+AW38),0) -> 1592294698 | BC38: =ROUND((AX38+AZ38-BB38),0) -> 1592294698 | BF38: 23270396 | BH38: 1927119772
C39: Bank Mega Syariah (1000236601) | D39: 7152816 | F39: =D39+E39 -> 7152816 | G39: =F39-H39 -> 0 | H39: =ROUND((D39+E39),0) -> 7152816 | M39: =ROUND((H39+J39-L39),0) -> 7152816 | P39: 7017523 | R39: =ROUND((P39+Q39),0) -> 7017523 | W39: =ROUND((R39+T39-V39),0) -> 7017523 | Y39: 7957124 | Z39: 0 | AA39: =ROUND((Y39+Z39),0) -> 7957124 | AF39: =ROUND((AA39+AC39-AE39),0) -> 7957124 | AI39: 13411920 | AM39: 13740510 | AO39: =ROUND((AM39+AN39),0) -> 13740510 | AT39: =ROUND((AO39+AQ39-AS39),0) -> 13740510 | AV39: 13523400 | AX39: =ROUND((AV39+AW39),0) -> 13523400 | BC39: =ROUND((AX39+AZ39-BB39),0) -> 13523400 | BF39: 14629830 | BH39: 14126310
B40: IAS-ISP | C40: PT Bank BTPN | D40: 54182297 | E40: 375720277 | F40: =D40+E40 -> 429902574 | G40: =F40-H40 -> 0 | H40: =ROUND((D40+E40),0) -> 429902574 | M40: =ROUND((H40+J40-L40),0) -> 429902574 | P40: 2276769542 | Q40: 1620910112 | R40: =ROUND((P40+Q40),0) -> 3897679654 | W40: =ROUND((R40+T40-V40),0) -> 3897679654 | Y40: 54773209 | Z40: 24997662 | AA40: =ROUND((Y40+Z40),0) -> 79770871 | AF40: =ROUND((AA40+AC40-AE40),0) -> 79770871 | AI40: 2027642112 | AM40: 23608985 | AN40: 5421215 | AO40: =ROUND((AM40+AN40),0) -> 29030200 | AT40: =ROUND((AO40+AQ40-AS40),0) -> 29030200 | AV40: 9670580 | AW40: 6041203 | AX40: =ROUND((AV40+AW40),0) -> 15711783 | BC40: =ROUND((AX40+AZ40-BB40),0) -> 15711783 | BF40: 433951591 | BH40: 0
C41: Bank BRI (0285-02-000022-30-5) USD | D41: 1460398 | F41: =D41+E41 -> 1460398 | G41: =F41-H41 -> 0 | H41: =ROUND((D41+E41),0) -> 1460398 | M41: =ROUND((H41+J41-L41),0) -> 1460398 | P41: 1822011 | R41: =ROUND((P41+Q41),0) -> 1822011 | W41: =ROUND((R41+T41-V41),0) -> 1822011 | Y41: 2469063 | Z41: 0 | AA41: =ROUND((Y41+Z41),0) -> 2469063 | AF41: =ROUND((AA41+AC41-AE41),0) -> 2469063 | AI41: 3242911 | AM41: 15455357 | AO41: =ROUND((AM41+AN41),0) -> 15455357 | AT41: =ROUND((AO41+AQ41-AS41),0) -> 15455357 | AV41: 9211689 | AX41: =ROUND((AV41+AW41),0) -> 9211689 | BC41: =ROUND((AX41+AZ41-BB41),0) -> 9211689 | BF41: 0 | BH41: 0
B42: ISP | C42: PT Bank Bukopin, Tbk | F42: =D42+E42 -> 0 | G42: =F42-H42 -> 0 | M42: =ROUND((H42+J42-L42),0) -> 0 | W42: =ROUND((R42+T42-V42),0) -> 0 | Z42: 0 | AF42: =ROUND((AA42+AC42-AE42),0) -> 0 | AI42: 0 | AO42: =ROUND((AM42+AN42),0) -> 0 | AT42: =ROUND((AO42+AQ42-AS42),0) -> 0 | AX42: =ROUND((AV42+AW42),0) -> 0 | BC42: =ROUND((AX42+AZ42-BB42),0) -> 0 | BF42: 0 | BH42: 0
B43: ISP | C43: PT Bank Mega Syariah | E43: 3652612 | F43: =D43+E43 -> 3652612 | G43: =F43-H43 -> 0 | H43: =ROUND((D43+E43),0) -> 3652612 | M43: =ROUND((H43+J43-L43),0) -> 3652612 | Q43: 3739086 | R43: =ROUND((P43+Q43),0) -> 3739086 | W43: =ROUND((R43+T43-V43),0) -> 3739086 | Z43: 4400828 | AA43: =ROUND((Y43+Z43),0) -> 4400828 | AF43: =ROUND((AA43+AC43-AE43),0) -> 4400828 | AI43: 4778960 | AN43: 5139106 | AO43: =ROUND((AM43+AN43),0) -> 5139106 | AT43: =ROUND((AO43+AQ43-AS43),0) -> 5139106 | AW43: 5289152 | AX43: =ROUND((AV43+AW43),0) -> 5289152 | BC43: =ROUND((AX43+AZ43-BB43),0) -> 5289152 | BF43: 6198014 | BH43: 6820582
B44: ISP | C44: Bank Mandiri $ - A/c 114,0027152647 | E44: 13078290 | F44: =D44+E44 -> 13078290 | G44: =F44-H44 -> 0 | H44: =ROUND((D44+E44),0) -> 13078290 | M44: =ROUND((H44+J44-L44),0) -> 13078290 | Q44: 13233613 | R44: =ROUND((P44+Q44),0) -> 13233613 | W44: =ROUND((R44+T44-V44),0) -> 13233613 | Z44: 14601526 | AA44: =ROUND((Y44+Z44),0) -> 14601526 | AF44: =ROUND((AA44+AC44-AE44),0) -> 14601526 | AI44: 19416453 | AN44: 13297243 | AO44: =ROUND((AM44+AN44),0) -> 13297243 | AT44: =ROUND((AO44+AQ44-AS44),0) -> 13297243 | AX44: =ROUND((AV44+AW44),0) -> 0 | BC44: =ROUND((AX44+AZ44-BB44),0) -> 0 | BF44: 0 | BH44: 0
B45: Deposito Berjangka | F45: =D45+E45 -> 0 | G45: =F45-H45 -> 0 | Z45: 0 | AI45: 0 | BF45: 0
C46: Deposito | F46: =D46+E46 -> 0 | G46: =F46-H46 -> 0 | H46: 0 | M46: =ROUND((H46+J46-L46),0) -> 0 | R46: 0 | W46: =ROUND((R46+T46-V46),0) -> 0 | Z46: 0 | AA46: 0 | AF46: =ROUND((AA46+AC46-AE46),0) -> 0 | AI46: 0 | AO46: =ROUND((AM46+AN46),0) -> 0 | AT46: =ROUND((AO46+AQ46-AS46),0) -> 0 | AX46: =ROUND((AV46+AW46),0) -> 0 | BC46: =ROUND((AX46+AZ46-BB46),0) -> 0 | BF46: 0 | BH46: 0
C47: PT Bank BNI (Deposito) | F47: =D47+E47 -> 0 | G47: =F47-H47 -> 0 | H47: 0 | M47: =ROUND((H47+J47-L47),0) -> 0 | R47: 0 | W47: =ROUND((R47+T47-V47),0) -> 0 | Z47: 0 | AA47: 0 | AF47: =ROUND((AA47+AC47-AE47),0) -> 0 | AI47: 250000000 | AN47: 250000000 | AO47: =ROUND((AM47+AN47),0) -> 250000000 | AT47: =ROUND((AO47+AQ47-AS47),0) -> 250000000 | AW47: 250000000 | AX47: =ROUND((AV47+AW47),0) -> 250000000 | BC47: =ROUND((AX47+AZ47-BB47),0) -> 250000000 | BF47: 250000000 | BH47: 0
C48: Total Bank | D48: =SUM(D19:D47) -> 247935868 | E48: =SUM(E19:E47) -> 437993113 | F48: =D48+E48 -> 685928981 | G48: =F48-H48 -> 0 | H48: =SUM(H19:H47) -> 685928981 | M48: =SUM(M19:M47) -> 685928981 | P48: =SUM(P19:P47) -> 11176307330 | Q48: =SUM(Q19:Q47) -> 1676003350 | R48: =SUM(R19:R47) -> 12852310680 | W48: =SUM(W19:W47) -> 12852310680 | Y48: =SUM(Y19:Y47) -> 315748435 | Z48: =SUM(Z19:Z47) -> 147927499 | AA48: =SUM(AA19:AA47) -> 463675934 | AF48: =SUM(AF19:AF47) -> 463675934 | AI48: =SUM(AI19:AI47) -> 2408259421 | AM48: =SUM(AM19:AM47) -> 1737907983 | AN48: =SUM(AN19:AN47) -> 909411084 | AO48: =SUM(AO19:AO47) -> 2647319067 | AT48: =SUM(AT19:AT47) -> 2647319067 | AV48: =SUM(AV19:AV47) -> 4833234427 | AW48: =SUM(AW19:AW47) -> 665782571 | AX48: =SUM(AX19:AX47) -> 5499016998 | BC48: =SUM(BC19:BC47) -> 5499016998 | BF48: =SUM(BF19:BF47) -> 4764334642 | BH48: =SUM(BH19:BH47) -> 4811620906
B49: Deposito | F49: =D49+E49 -> 0 | G49: =F49-H49 -> 0
D50: =#REF!+#REF!-#REF! -> #REF! | E50: =#REF!+#REF!-#REF! -> #REF! | F50: =D50+E50 -> #REF! | G50: =F50-H50 -> #REF! | H50: =#REF!+#REF!-#REF! -> #REF! | M50: =#REF!+#REF!-#REF! -> #REF! | P50: =#REF!+#REF!-#REF! -> #REF! | Q50: =#REF!+#REF!-#REF! -> #REF! | R50: =#REF!+#REF!-#REF! -> #REF! | W50: =#REF!+#REF!-#REF! -> #REF! | Y50: =#REF!+#REF!-#REF! -> #REF! | Z50: =#REF!+#REF!-#REF! -> #REF! | AA50: =#REF!+#REF!-#REF! -> #REF! | AF50: =#REF!+#REF!-#REF! -> #REF! | AI50: =#REF!+#REF!-#REF! -> #REF! | AM50: =#REF!+#REF!-#REF! -> #REF! | AN50: =#REF!+#REF!-#REF! -> #REF! | AO50: =#REF!+#REF!-#REF! -> #REF! | AT50: =#REF!+#REF!-#REF! -> #REF! | AV50: =#REF!+#REF!-#REF! -> #REF! | AW50: =#REF!+#REF!-#REF! -> #REF! | AX50: =#REF!+#REF!-#REF! -> #REF! | BC50: =#REF!+#REF!-#REF! -> #REF! | BF50: =#REF!+#REF!-#REF! -> #REF! | BH50: =#REF!+#REF!-#REF! -> #REF!
C51: Total Deposito | D51: =SUM(D49:D50) -> #REF! | E51: =SUM(E49:E50) -> #REF! | F51: =D51+E51 -> #REF! | G51: =F51-H51 -> #REF! | H51: =SUM(H49:H50) -> #REF! | M51: =SUM(M49:M50) -> #REF! | P51: =SUM(P49:P50) -> #REF! | Q51: =SUM(Q49:Q50) -> #REF! | R51: =SUM(R49:R50) -> #REF! | W51: =SUM(W49:W50) -> #REF! | Y51: =SUM(Y49:Y50) -> #REF! | Z51: =SUM(Z49:Z50) -> #REF! | AA51: =SUM(AA49:AA50) -> #REF! | AF51: =SUM(AF49:AF50) -> #REF! | AI51: =SUM(AI49:AI50) -> #REF! | AM51: =SUM(AM49:AM50) -> #REF! | AN51: =SUM(AN49:AN50) -> #REF! | AO51: =SUM(AO49:AO50) -> #REF! | AT51: =SUM(AT49:AT50) -> #REF! | AV51: =SUM(AV49:AV50) -> #REF! | AW51: =SUM(AW49:AW50) -> #REF! | AX51: =SUM(AX49:AX50) -> #REF! | BC51: =SUM(BC49:BC50) -> #REF! | BF51: =SUM(BF49:BF50) -> #REF! | BH51: =SUM(BH49:BH50) -> #REF!
C52: Total Cash and Cash Equivalents | D52: =D18+D48 -> 420682221 | E52: =E18+E48 -> 497527264 | F52: =D52+E52 -> 918209485 | G52: =F52-H52 -> 0 | H52: =ROUND(H18+H48,0) -> 918209485 | M52: =M18+M48 -> 918209485 | N52: ok | P52: =P18+P48 -> 11398024862 | Q52: =Q18+Q48 -> 1789363537 | R52: =ROUND(R18+R48,0) -> 13187388399 | W52: =W18+W48 -> 13187388399 | Y52: =Y18+Y48 -> 330926686 | Z52: =Z18+Z48 -> 234960111 | AA52: =AA18+AA48 -> 565886797 | AF52: =AF18+AF48 -> 565886797 | AH52: ok | AI52: =AI48+AI18 -> 2570121355 | AM52: =AM18+AM48 -> 1798900203 | AN52: =AN18+AN48 -> 1015473043 | AO52: =AO18+AO48 -> 2814373246 | AT52: =AT18+AT48 -> 2814373246 | AV52: =AV18+AV48 -> 4901493296 | AW52: =AW18+AW48 -> 831569974 | AX52: =AX18+AX48 -> 5733063270 | BC52: =BC18+BC48 -> 5733063270 | BE52: ok | BF52: =BF18+BF48 -> 4920468963 | BH52: =BH18+BH48 -> 4972845584
B53: Trade Receivable | F53: =D53+E53 -> 0 | G53: =F53-H53 -> 0
C54: Piutang Usaha - IDR | F54: =D54+E54 -> 0 | G54: =F54-H54 -> 0 | AI54: 0 | BF54: 0
C55: Piutang Karyawan | F55: =D55+E55 -> 0 | G55: =F55-H55 -> 0 | H55: =ROUND((D55+E55),0) -> 0 | M55: =ROUND((H55+J55-L55),0) -> 0 | R55: =ROUND((P55+Q55),0) -> 0 | W55: =ROUND((R55+T55-V55),0) -> 0 | AA55: =ROUND((Y55+Z55),0) -> 0 | AF55: =ROUND((AA55+AC55-AE55),0) -> 0 | AO55: =ROUND((AM55+AN55),0) -> 0 | AT55: =ROUND((AO55+AQ55-AS55),0) -> 0 | AX55: =ROUND((AV55+AW55),0) -> 0 | BC55: =ROUND((AX55+AZ55-BB55),0) -> 0
C56: CV Kanian Persada | D56: 393935430 | F56: =D56+E56 -> 393935430 | G56: =F56-H56 -> 0 | H56: =ROUND((D56+E56),0) -> 393935430 | M56: =ROUND((H56+J56-L56),0) -> 393935430 | N56: Piutang usaha Pihak Berelasi | P56: 339894481 | R56: =ROUND((P56+Q56),0) -> 339894481 | W56: =ROUND((R56+T56-V56),0) -> 339894481 | Y56: 422639675 | AA56: =ROUND((Y56+Z56),0) -> 422639675 | AF56: =ROUND((AA56+AC56-AE56),0) -> 422639675 | AH56: ok | AI56: 211054410 | AM56: 482874409 | AO56: =ROUND((AM56+AN56),0) -> 482874409 | AT56: =ROUND((AO56+AQ56-AS56),0) -> 482874409 | AV56: 392409005 | AW56: 180375 | AX56: =ROUND((AV56+AW56),0) -> 392589380 | BC56: =ROUND((AX56+AZ56-BB56),0) -> 392589380 | BF56: 338387925 | BH56: 174380445 | BJ56: =M56 -> 393935430
B57: ISP | C57: Nichia Trading Inc. | F57: =D57+E57 -> 0 | G57: =F57-H57 -> 0 | H57: =ROUND((D57+E57),0) -> 0 | M57: =ROUND((H57+J57-L57),0) -> 0 | R57: =ROUND((P57+Q57),0) -> 0 | W57: =ROUND((R57+T57-V57),0) -> 0 | AA57: =ROUND((Y57+Z57),0) -> 0 | AF57: =ROUND((AA57+AC57-AE57),0) -> 0 | AI57: 0 | AO57: =ROUND((AM57+AN57),0) -> 0 | AT57: =ROUND((AO57+AQ57-AS57),0) -> 0 | AX57: =ROUND((AV57+AW57),0) -> 0 | BC57: =ROUND((AX57+AZ57-BB57),0) -> 0 | BF57: 0 | BH57: 0
B58: ISP | C58: PT Maju Tambak Sumur | E58: 15960000 | F58: =D58+E58 -> 15960000 | G58: =F58-H58 -> 0 | H58: =ROUND((D58+E58),0) -> 15960000 | M58: =ROUND((H58+J58-L58),0) -> 15960000 | N58: Piutang usaha Pihak Ketiga (IDR) | R58: =ROUND((P58+Q58),0) -> 0 | W58: =ROUND((R58+T58-V58),0) -> 0 | Z58: 46200000 | AA58: =ROUND((Y58+Z58),0) -> 46200000 | AF58: =ROUND((AA58+AC58-AE58),0) -> 46200000 | AI58: 48300000 | AN58: 53760000 | AO58: =ROUND((AM58+AN58),0) -> 53760000 | AT58: =ROUND((AO58+AQ58-AS58),0) -> 53760000 | AW58: 26040000 | AX58: =ROUND((AV58+AW58),0) -> 26040000 | BC58: =ROUND((AX58+AZ58-BB58),0) -> 26040000 | BF58: 88430000 | BH58: 11840000
B59: ISP | C59: PT Tambak Udang Baba Rafi | F59: =D59+E59 -> 0 | G59: =F59-H59 -> 0 | H59: =ROUND((D59+E59),0) -> 0 | M59: =ROUND((H59+J59-L59),0) -> 0 | R59: =ROUND((P59+Q59),0) -> 0 | W59: =ROUND((R59+T59-V59),0) -> 0 | Z59: 0 | AA59: =ROUND((Y59+Z59),0) -> 0 | AF59: =ROUND((AA59+AC59-AE59),0) -> 0 | AI59: 0 | AO59: =ROUND((AM59+AN59),0) -> 0 | AT59: =ROUND((AO59+AQ59-AS59),0) -> 0 | AX59: =ROUND((AV59+AW59),0) -> 0 | BC59: =ROUND((AX59+AZ59-BB59),0) -> 0 | BF59: 0 | BH59: 0
B60: ISP | C60: Bapak Iwan-Es | E60: 79850000 | F60: =D60+E60 -> 79850000 | G60: =F60-H60 -> 0 | H60: =ROUND((D60+E60),0) -> 79850000 | M60: =ROUND((H60+J60-L60),0) -> 79850000 | N60: Piutang usaha Pihak Ketiga (IDR) | Q60: 42280000 | R60: =ROUND((P60+Q60),0) -> 42280000 | W60: =ROUND((R60+T60-V60),0) -> 42280000 | Z60: 47050000 | AA60: =ROUND((Y60+Z60),0) -> 47050000 | AF60: =ROUND((AA60+AC60-AE60),0) -> 47050000 | AI60: 108320000 | AN60: 148130000 | AO60: =ROUND((AM60+AN60),0) -> 148130000 | AT60: =ROUND((AO60+AQ60-AS60),0) -> 148130000 | AW60: 164330000 | AX60: =ROUND((AV60+AW60),0) -> 164330000 | BC60: =ROUND((AX60+AZ60-BB60),0) -> 164330000 | BF60: 90935000 | BH60: 36235000 | BJ60: =M60+M58+M73 -> 116340775
B61: ISP | C61: Chandra Irwanto, Bp | F61: =D61+E61 -> 0 | G61: =F61-H61 -> 0 | H61: =ROUND((D61+E61),0) -> 0 | M61: =ROUND((H61+J61-L61),0) -> 0 | R61: =ROUND((P61+Q61),0) -> 0 | W61: =ROUND((R61+T61-V61),0) -> 0 | AA61: =ROUND((Y61+Z61),0) -> 0 | AF61: =ROUND((AA61+AC61-AE61),0) -> 0 | AI61: 0 | AO61: =ROUND((AM61+AN61),0) -> 0 | AT61: =ROUND((AO61+AQ61-AS61),0) -> 0 | AX61: =ROUND((AV61+AW61),0) -> 0 | BC61: =ROUND((AX61+AZ61-BB61),0) -> 0 | BF61: 0 | BH61: 0
B62: ISP | C62: Indofood Sukses Makmur Tbk, PT | F62: =D62+E62 -> 0 | G62: =F62-H62 -> 0 | H62: =ROUND((D62+E62),0) -> 0 | M62: =ROUND((H62+J62-L62),0) -> 0 | R62: =ROUND((P62+Q62),0) -> 0 | W62: =ROUND((R62+T62-V62),0) -> 0 | AA62: =ROUND((Y62+Z62),0) -> 0 | AF62: =ROUND((AA62+AC62-AE62),0) -> 0 | AI62: 0 | AO62: =ROUND((AM62+AN62),0) -> 0 | AT62: =ROUND((AO62+AQ62-AS62),0) -> 0 | AX62: =ROUND((AV62+AW62),0) -> 0 | BC62: =ROUND((AX62+AZ62-BB62),0) -> 0 | BF62: 0 | BH62: 0
B63: ISP | C63: Nur Indah Gypsum | F63: =D63+E63 -> 0 | G63: =F63-H63 -> 0 | H63: =ROUND((D63+E63),0) -> 0 | M63: =ROUND((H63+J63-L63),0) -> 0 | R63: =ROUND((P63+Q63),0) -> 0 | W63: =ROUND((R63+T63-V63),0) -> 0 | AA63: =ROUND((Y63+Z63),0) -> 0 | AF63: =ROUND((AA63+AC63-AE63),0) -> 0 | AI63: 0 | AO63: =ROUND((AM63+AN63),0) -> 0 | AT63: =ROUND((AO63+AQ63-AS63),0) -> 0 | AX63: =ROUND((AV63+AW63),0) -> 0 | BC63: =ROUND((AX63+AZ63-BB63),0) -> 0 | BF63: 0 | BH63: 0
C64: Mochamad Riduwan | D64: 0 | F64: =D64+E64 -> 0 | G64: =F64-H64 -> 0 | H64: =ROUND((D64+E64),0) -> 0 | M64: =ROUND((H64+J64-L64),0) -> 0 | R64: =ROUND((P64+Q64),0) -> 0 | W64: =ROUND((R64+T64-V64),0) -> 0 | AA64: =ROUND((Y64+Z64),0) -> 0 | AF64: =ROUND((AA64+AC64-AE64),0) -> 0 | AI64: 0 | AM64: 14980 | AO64: =ROUND((AM64+AN64),0) -> 14980 | AT64: =ROUND((AO64+AQ64-AS64),0) -> 14980 | AV64: 14980 | AX64: =ROUND((AV64+AW64),0) -> 14980 | BC64: =ROUND((AX64+AZ64-BB64),0) -> 14980 | BF64: 14980 | BH64: 14980
C65: Bp Suherman | F65: =D65+E65 -> 0 | G65: =F65-H65 -> 0 | H65: =ROUND((D65+E65),0) -> 0 | M65: =ROUND((H65+J65-L65),0) -> 0 | R65: =ROUND((P65+Q65),0) -> 0 | W65: =ROUND((R65+T65-V65),0) -> 0 | AA65: =ROUND((Y65+Z65),0) -> 0 | AF65: =ROUND((AA65+AC65-AE65),0) -> 0 | AI65: 0 | AO65: =ROUND((AM65+AN65),0) -> 0 | AT65: =ROUND((AO65+AQ65-AS65),0) -> 0 | AX65: =ROUND((AV65+AW65),0) -> 0 | BC65: =ROUND((AX65+AZ65-BB65),0) -> 0 | BF65: 0 | BH65: 0
C66: Bp Ronald De Fretes | F66: =D66+E66 -> 0 | G66: =F66-H66 -> 0 | H66: =ROUND((D66+E66),0) -> 0 | M66: =ROUND((H66+J66-L66),0) -> 0 | R66: =ROUND((P66+Q66),0) -> 0 | W66: =ROUND((R66+T66-V66),0) -> 0 | AA66: =ROUND((Y66+Z66),0) -> 0 | AF66: =ROUND((AA66+AC66-AE66),0) -> 0 | AI66: 0 | AO66: =ROUND((AM66+AN66),0) -> 0 | AT66: =ROUND((AO66+AQ66-AS66),0) -> 0 | AX66: =ROUND((AV66+AW66),0) -> 0 | BC66: =ROUND((AX66+AZ66-BB66),0) -> 0 | BF66: 0 | BH66: 0
C67: UD, Slamet | D67: 0 | F67: =D67+E67 -> 0 | G67: =F67-H67 -> 0 | H67: =ROUND((D67+E67),0) -> 0 | M67: =ROUND((H67+J67-L67),0) -> 0 | R67: =ROUND((P67+Q67),0) -> 0 | W67: =ROUND((R67+T67-V67),0) -> 0 | AA67: =ROUND((Y67+Z67),0) -> 0 | AF67: =ROUND((AA67+AC67-AE67),0) -> 0 | AI67: 0 | AM67: 14649340 | AO67: =ROUND((AM67+AN67),0) -> 14649340 | AT67: =ROUND((AO67+AQ67-AS67),0) -> 14649340 | AV67: 29870000 | AX67: =ROUND((AV67+AW67),0) -> 29870000 | BC67: =ROUND((AX67+AZ67-BB67),0) -> 29870000 | BF67: 29870000 | BH67: 0
C68: Roda Jaya, Toko | D68: 0 | F68: =D68+E68 -> 0 | G68: =F68-H68 -> 0 | H68: =ROUND((D68+E68),0) -> 0 | M68: =ROUND((H68+J68-L68),0) -> 0 | R68: =ROUND((P68+Q68),0) -> 0 | W68: =ROUND((R68+T68-V68),0) -> 0 | AA68: =ROUND((Y68+Z68),0) -> 0 | AF68: =ROUND((AA68+AC68-AE68),0) -> 0 | AI68: 0 | AM68: 520000 | AO68: =ROUND((AM68+AN68),0) -> 520000 | AT68: =ROUND((AO68+AQ68-AS68),0) -> 520000 | AV68: 520000 | AX68: =ROUND((AV68+AW68),0) -> 520000 | BC68: =ROUND((AX68+AZ68-BB68),0) -> 520000 | BF68: 520000 | BH68: 0
C69: Piutang Karyawan | D69: 0 | F69: =D69+E69 -> 0 | G69: =F69-H69 -> 0 | H69: =ROUND((D69+E69),0) -> 0 | M69: =ROUND((H69+J69-L69),0) -> 0 | N69: Piutang usaha Pihak Ketiga (IDR) | R69: =ROUND((P69+Q69),0) -> 0 | W69: =ROUND((R69+T69-V69),0) -> 0 | AA69: =ROUND((Y69+Z69),0) -> 0 | AF69: =ROUND((AA69+AC69-AE69),0) -> 0 | AI69: 1480185 | AO69: =ROUND((AM69+AN69),0) -> 0 | AT69: =ROUND((AO69+AQ69-AS69),0) -> 0 | AX69: =ROUND((AV69+AW69),0) -> 0 | BC69: =ROUND((AX69+AZ69-BB69),0) -> 0 | BF69: 0 | BH69: 4950900
C70: Jaduk Prayogi | D70: 0 | F70: =D70+E70 -> 0 | G70: =F70-H70 -> 0 | H70: =ROUND((D70+E70),0) -> 0 | M70: =ROUND((H70+J70-L70),0) -> 0 | R70: =ROUND((P70+Q70),0) -> 0 | W70: =ROUND((R70+T70-V70),0) -> 0 | AA70: =ROUND((Y70+Z70),0) -> 0 | AF70: =ROUND((AA70+AC70-AE70),0) -> 0 | AI70: 0 | AO70: =ROUND((AM70+AN70),0) -> 0 | AT70: =ROUND((AO70+AQ70-AS70),0) -> 0 | AX70: =ROUND((AV70+AW70),0) -> 0 | BC70: =ROUND((AX70+AZ70-BB70),0) -> 0 | BF70: 0 | BH70: 4800000
C71: Surya Sukses Makmur | E71: 0 | F71: =D71+E71 -> 0 | G71: =F71-H71 -> 0 | H71: =ROUND((D71+E71),0) -> 0 | M71: =ROUND((H71+J71-L71),0) -> 0
B72: ISP | C72: Deska / WMM Es -IDR | F72: =D72+E72 -> 0 | G72: =F72-H72 -> 0 | H72: =ROUND((D72+E72),0) -> 0 | M72: =ROUND((H72+J72-L72),0) -> 0 | Q72: 15120000 | R72: =ROUND((P72+Q72),0) -> 15120000 | W72: =ROUND((R72+T72-V72),0) -> 15120000 | Y72: 0 | AA72: =ROUND((Y72+Z72),0) -> 0 | AF72: =ROUND((AA72+AC72-AE72),0) -> 0 | AI72: 49140000 | AL72: 12379750576 | AN72: 6300000 | AO72: =ROUND((AM72+AN72),0) -> 6300000 | AT72: =ROUND((AO72+AQ72-AS72),0) -> 6300000 | AX72: =ROUND((AV72+AW72),0) -> 0 | BC72: =ROUND((AX72+AZ72-BB72),0) -> 0 | BE72: 7594460218
B73: ISP | C73: Piutang Lain-lain di bawah Rp 20.000.000,- IDR | E73: 20530775 | F73: =D73+E73 -> 20530775 | G73: =F73-H73 -> 0 | H73: =ROUND((D73+E73),0) -> 20530775 | M73: =ROUNDUP((H73+J73-L73),0) -> 20530775 | N73: Piutang usaha Pihak Ketiga (IDR) | Q73: 28090775 | R73: =ROUND((P73+Q73),0) -> 28090775 | T73: ='ELIM & CAJE Sept 24'!G35 -> 2 | W73: =ROUNDUP((R73+T73-V73),0) -> 28090777 | Y73: 0 | Z73: =22200776 -> 22200776 | AA73: =ROUND((Y73+Z73),0) -> 22200776 | AC73: ='ELIM & CAJE Juni 24'!G35 -> 2 | AF73: =ROUNDUP((AA73+AC73-AE73),0) -> 22200778 | AI73: 21427997 | AN73: 20950775 | AO73: =ROUND((AM73+AN73),0) -> 20950775 | AT73: =ROUND((AO73+AQ73-AS73),0) -> 20950775 | AW73: 23534400 | AX73: =ROUND((AV73+AW73),0) -> 23534400 | BC73: =ROUND((AX73+AZ73-BB73),0) -> 23534400 | BE73: 57222 | BF73: 19754400 | BH73: 17869962
F74: =D74+E74 -> 0 | G74: =F74-H74 -> 0 | BH74: 0
C75: Piutang Usaha - USD | F75: =D75+E75 -> 0 | G75: =F75-H75 -> 0 | BH75: 0
C76: Alpha Trading Co. Ltd | D76: 3.1790315e+09 | F76: =D76+E76 -> 3.1790315e+09 | G76: =F76-H76 -> -0.40000057 | H76: =ROUND((D76+E76),0) -> 3179031461 | M76: =ROUND((H76+J76-L76),0) -> 3179031461 | N76: Piutang usaha Pihak Ketiga (USD) | O76: ok | R76: =ROUND((P76+Q76),0) -> 0 | W76: =ROUND((R76+T76-V76),0) -> 0 | AA76: =ROUND((Y76+Z76),0) -> 0 | AF76: =ROUND((AA76+AC76-AE76),0) -> 0 | AI76: 0 | AO76: =ROUND((AM76+AN76),0) -> 0 | AT76: =ROUND((AO76+AQ76-AS76),0) -> 0 | AX76: =ROUND((AV76+AW76),0) -> 0 | BC76: =ROUND((AX76+AZ76-BB76),0) -> 0 | BF76: 1154639669 | BH76: 1095202826
C77: Censea Inc | D77: 2.3711222e+10 | E77: 6.0408707e+09 | F77: =D77+E77 -> 2.9752092e+10 | G77: =F77-H77 -> -0.010002136 | H77: =ROUND((D77+E77),0) -> 29752092454 | M77: =ROUND((H77+J77-L77),0) -> 29752092454 | N77: Piutang usaha Pihak Ketiga (USD) | O77: ok | P77: =ROUND(16672945019.5,0) -> 16672945020 | Q77: 7083443636 | R77: =ROUND((P77+Q77),0) -> 23756388656 | W77: =ROUND((R77+T77-V77),0) -> 23756388656 | Y77: 9385865917 | Z77: 10893104718 | AA77: =ROUND((Y77+Z77),0) -> 20278970635 | AF77: =ROUND((AA77+AC77-AE77),0) -> 20278970635 | AI77: 8062429256 | AM77: 1781608500 | AO77: =ROUND((AM77+AN77),0) -> 1781608500 | AT77: =ROUND((AO77+AQ77-AS77),0) -> 1781608500 | AV77: 6159157400 | AW77: 6070577986 | AX77: =ROUND((AV77+AW77),0) -> 12229735386 | BC77: =ROUND((AX77+AZ77-BB77),0) -> 12229735386 | BF77: 30444649539 | BH77: 12905039466
C78: Crystal Cove Seafoods Corp | D78: 0 | E78: 6.5667014e+09 | F78: =D78+E78 -> 6.5667014e+09 | G78: =F78-H78 -> -0.5 | H78: =ROUND((D78+E78),0) -> 6566701410 | M78: =ROUND((H78+J78-L78),0) -> 6566701410 | N78: Piutang usaha Pihak Ketiga (USD) | O78: ok | R78: =ROUND((P78+Q78),0) -> 0 | W78: =ROUND((R78+T78-V78),0) -> 0 | Y78: 0 | Z78: 1717455969 | AA78: =ROUND((Y78+Z78),0) -> 1717455969 | AF78: =ROUND((AA78+AC78-AE78),0) -> 1717455969 | AI78: 3270427320 | AO78: =ROUND((AM78+AN78),0) -> 0 | AT78: =ROUND((AO78+AQ78-AS78),0) -> 0 | AV78: 1109144190 | AX78: =ROUND((AV78+AW78),0) -> 1109144190 | BC78: =ROUND((AX78+AZ78-BB78),0) -> 1109144190 | BF78: 1498694731 | BH78: 1414842695
B79: ISP | C79: Honsui Corporation | F79: =D79+E79 -> 0 | G79: =F79-H79 -> 0 | H79: =ROUND((D79+E79),0) -> 0 | M79: =ROUND((H79+J79-L79),0) -> 0 | Q79: =ROUND(2725814421.57,0) -> 2725814422 | R79: =ROUND((P79+Q79),0) -> 2725814422 | W79: =ROUND((R79+T79-V79),0) -> 2725814422 | Y79: 0 | Z79: 1811698562 | AA79: =ROUND((Y79+Z79),0) -> 1811698562 | AF79: =ROUND((AA79+AC79-AE79),0) -> 1811698562 | AI79: 0 | AN79: 1686790125 | AO79: =ROUND((AM79+AN79),0) -> 1686790125 | AT79: =ROUND((AO79+AQ79-AS79),0) -> 1686790125 | AX79: =ROUND((AV79+AW79),0) -> 0 | BC79: =ROUND((AX79+AZ79-BB79),0) -> 0 | BF79: 1924366936 | BH79: 2179230314
B80: ISP | C80: Khyo Co. Ltd. | F80: =D80+E80 -> 0 | G80: =F80-H80 -> 0 | H80: =ROUND((D80+E80),0) -> 0 | M80: =ROUND((H80+J80-L80),0) -> 0 | R80: =ROUND((P80+Q80),0) -> 0 | W80: =ROUND((R80+T80-V80),0) -> 0 | Y80: 0 | AA80: =ROUND((Y80+Z80),0) -> 0 | AF80: =ROUND((AA80+AC80-AE80),0) -> 0 | AI80: 0 | AO80: =ROUND((AM80+AN80),0) -> 0 | AT80: =ROUND((AO80+AQ80-AS80),0) -> 0 | AX80: =ROUND((AV80+AW80),0) -> 0 | BC80: =ROUND((AX80+AZ80-BB80),0) -> 0 | BF80: 0 | BH80: 0
C81: Ael Seafood Enterprises, LLC | D81: 3791605200 | F81: =D81+E81 -> 3791605200 | G81: =F81-H81 -> 0 | H81: =ROUND((D81+E81),0) -> 3791605200 | M81: =ROUND((H81+J81-L81),0) -> 3791605200 | N81: Piutang usaha Pihak Ketiga (USD) | O81: ok | R81: =ROUND((P81+Q81),0) -> 0 | W81: =ROUND((R81+T81-V81),0) -> 0 | Y81: 0 | AA81: =ROUND((Y81+Z81),0) -> 0 | AF81: =ROUND((AA81+AC81-AE81),0) -> 0 | AI81: 0 | AO81: =ROUND((AM81+AN81),0) -> 0 | AT81: =ROUND((AO81+AQ81-AS81),0) -> 0 | AX81: =ROUND((AV81+AW81),0) -> 0 | BC81: =ROUND((AX81+AZ81-BB81),0) -> 0 | BF81: 0 | BH81: 2037613200
C82: Eastern Fish Company LLC | D82: 0 | F82: =D82+E82 -> 0 | G82: =F82-H82 -> 0 | H82: =ROUND((D82+E82),0) -> 0 | M82: =ROUND((H82+J82-L82),0) -> 0 | N82: Piutang usaha Pihak Ketiga (USD) | O82: ok | P82: 1353639940 | R82: =ROUND((P82+Q82),0) -> 1353639940 | W82: =ROUND((R82+T82-V82),0) -> 1353639940 | Y82: 1514886513 | AA82: =ROUND((Y82+Z82),0) -> 1514886513 | AF82: =ROUND((AA82+AC82-AE82),0) -> 1514886513 | AI82: 1661844801 | AM82: 1864082613 | AO82: =ROUND((AM82+AN82),0) -> 1864082613 | AT82: =ROUND((AO82+AQ82-AS82),0) -> 1864082613 | AV82: 6587398401 | AX82: =ROUND((AV82+AW82),0) -> 6587398401 | BC82: =ROUND((AX82+AZ82-BB82),0) -> 6587398401 | BF82: 9670160321 | BH82: 8722639700
B83: ISP | C83: Great American Seafoods Imports Co. | E83: 1895802600 | F83: =D83+E83 -> 1895802600 | G83: =F83-H83 -> 0 | H83: =ROUND((D83+E83),0) -> 1895802600 | M83: =ROUND((H83+J83-L83),0) -> 1895802600 | N83: Piutang usaha Pihak Ketiga (USD) | O83: ok | R83: =ROUND((P83+Q83),0) -> 0 | W83: =ROUND((R83+T83-V83),0) -> 0 | Y83: 0 | AA83: =ROUND((Y83+Z83),0) -> 0 | AF83: =ROUND((AA83+AC83-AE83),0) -> 0 | AI83: 0 | AM83: 1079988560 | AO83: =ROUND((AM83+AN83),0) -> 1079988560 | AT83: =ROUND((AO83+AQ83-AS83),0) -> 1079988560 | AX83: =ROUND((AV83+AW83),0) -> 0 | BC83: =ROUND((AX83+AZ83-BB83),0) -> 0 | BF83: 0 | BH83: 1989098600
C84: Choice Canning Company Inc. | F84: =D84+E84 -> 0 | G84: =F84-H84 -> 0 | H84: =ROUND((D84+E84),0) -> 0 | M84: =ROUND((H84+J84-L84),0) -> 0 | R84: =ROUND((P84+Q84),0) -> 0 | W84: =ROUND((R84+T84-V84),0) -> 0 | Y84: 0 | AA84: =ROUND((Y84+Z84),0) -> 0 | AF84: =ROUND((AA84+AC84-AE84),0) -> 0 | AI84: 0 | AO84: =ROUND((AM84+AN84),0) -> 0 | AT84: =ROUND((AO84+AQ84-AS84),0) -> 0 | AV84: 4246347600 | AX84: =ROUND((AV84+AW84),0) -> 4246347600 | BC84: =ROUND((AX84+AZ84-BB84),0) -> 4246347600 | BF84: 0 | BH84: 0
C85: Stellar Seas Import Co, Ltd | F85: =D85+E85 -> 0 | G85: =F85-H85 -> 0 | H85: =ROUND((D85+E85),0) -> 0 | M85: =ROUND((H85+J85-L85),0) -> 0 | R85: =ROUND((P85+Q85),0) -> 0 | W85: =ROUND((R85+T85-V85),0) -> 0 | Y85: 0 | AA85: =ROUND((Y85+Z85),0) -> 0 | AF85: =ROUND((AA85+AC85-AE85),0) -> 0 | AI85: 0 | AO85: =ROUND((AM85+AN85),0) -> 0 | AT85: =ROUND((AO85+AQ85-AS85),0) -> 0 | AX85: =ROUND((AV85+AW85),0) -> 0 | BC85: =ROUND((AX85+AZ85-BB85),0) -> 0 | BF85: 0 | BH85: 0
C86: Eiger Co. Ltd | D86: 0 | F86: =D86+E86 -> 0 | G86: =F86-H86 -> 0 | H86: =ROUND((D86+E86),0) -> 0 | M86: =ROUND((H86+J86-L86),0) -> 0 | N86: Piutang usaha Pihak Ketiga (USD) | O86: ok | R86: =ROUND((P86+Q86),0) -> 0 | W86: =ROUND((R86+T86-V86),0) -> 0 | Y86: 0 | AA86: =ROUND((Y86+Z86),0) -> 0 | AF86: =ROUND((AA86+AC86-AE86),0) -> 0 | AI86: 550050588 | AO86: =ROUND((AM86+AN86),0) -> 0 | AT86: =ROUND((AO86+AQ86-AS86),0) -> 0 | AX86: =ROUND((AV86+AW86),0) -> 0 | BC86: =ROUND((AX86+AZ86-BB86),0) -> 0 | BF86: 1469275400 | BH86: 0
C87: Export Packer Co., Ltd | D87: 0 | F87: =D87+E87 -> 0 | G87: =F87-H87 -> 0 | H87: =ROUND((D87+E87),0) -> 0 | M87: =ROUND((H87+J87-L87),0) -> 0 | R87: =ROUND((P87+Q87),0) -> 0 | W87: =ROUND((R87+T87-V87),0) -> 0 | Y87: 0 | AA87: =ROUND((Y87+Z87),0) -> 0 | AF87: =ROUND((AA87+AC87-AE87),0) -> 0 | AI87: 0 | AO87: =ROUND((AM87+AN87),0) -> 0 | AT87: =ROUND((AO87+AQ87-AS87),0) -> 0 | AX87: =ROUND((AV87+AW87),0) -> 0 | BC87: =ROUND((AX87+AZ87-BB87),0) -> 0 | BF87: 398482118 | BH87: 0
C88: H & T SEAFOODS INC | D88: 0 | F88: =D88+E88 -> 0 | G88: =F88-H88 -> 0 | H88: =ROUND((D88+E88),0) -> 0 | M88: =ROUND((H88+J88-L88),0) -> 0 | R88: =ROUND((P88+Q88),0) -> 0 | W88: =ROUND((R88+T88-V88),0) -> 0 | Y88: 0 | AA88: =ROUND((Y88+Z88),0) -> 0 | AF88: =ROUND((AA88+AC88-AE88),0) -> 0 | AI88: 0 | AO88: =ROUND((AM88+AN88),0) -> 0 | AT88: =ROUND((AO88+AQ88-AS88),0) -> 0 | AX88: =ROUND((AV88+AW88),0) -> 0 | BC88: =ROUND((AX88+AZ88-BB88),0) -> 0 | BF88: 0 | BH88: 0
C89: Kyo Kuyo Co, Ltd | E89: 1.0062759e+10 | F89: =D89+E89 -> 1.0062759e+10 | G89: =F89-H89 -> -0.32000351 | H89: =ROUND((D89+E89),0) -> 10062759228 | M89: =ROUND((H89+J89-L89),0) -> 10062759228 | N89: Piutang usaha Pihak Ketiga (USD) | O89: ok | Q89: 1589028594 | R89: =ROUND((P89+Q89),0) -> 1589028594 | W89: =ROUND((R89+T89-V89),0) -> 1589028594 | Y89: 0 | AA89: =ROUND((Y89+Z89),0) -> 0 | AF89: =ROUND((AA89+AC89-AE89),0) -> 0 | AI89: 4226586219 | AO89: =ROUND((AM89+AN89),0) -> 0 | AT89: =ROUND((AO89+AQ89-AS89),0) -> 0 | AW89: 2142544861 | AX89: =ROUND((AV89+AW89),0) -> 2142544861 | BC89: =ROUND((AX89+AZ89-BB89),0) -> 2142544861 | BF89: 4709628265 | BH89: 1330066570
B90: ISP | C90: Nissui Corporation | E90: 1.3036668e+10 | F90: =D90+E90 -> 1.3036668e+10 | G90: =F90-H90 -> -0.099998474 | H90: =ROUND((D90+E90),0) -> 13036668402 | M90: =ROUND((H90+J90-L90),0) -> 13036668402 | N90: Piutang usaha Pihak Ketiga (USD) | O90: ok | Q90: =ROUND(4404451408.5,0) -> 4404451409 | R90: =ROUND((P90+Q90),0) -> 4404451409 | W90: =ROUND((R90+T90-V90),0) -> 4404451409 | Y90: 0 | Z90: 2323553040 | AA90: =ROUND((Y90+Z90),0) -> 2323553040 | AF90: =ROUND((AA90+AC90-AE90),0) -> 2323553040 | AO90: =ROUND((AM90+AN90),0) -> 0 | AT90: =ROUND((AO90+AQ90-AS90),0) -> 0 | AX90: =ROUND((AV90+AW90),0) -> 0 | BC90: =ROUND((AX90+AZ90-BB90),0) -> 0
B91: ISP | C91: Yantai City AOWEI Refrigeration Equipments CO,, Ltd | F91: =D91+E91 -> 0 | G91: =F91-H91 -> 0 | H91: =ROUND((D91+E91),0) -> 0 | M91: =ROUND((H91+J91-L91),0) -> 0 | R91: =ROUND((P91+Q91),0) -> 0 | W91: =ROUND((R91+T91-V91),0) -> 0 | Y91: 0 | AA91: =ROUND((Y91+Z91),0) -> 0 | AF91: =ROUND((AA91+AC91-AE91),0) -> 0 | AI91: 0 | AO91: =ROUND((AM91+AN91),0) -> 0 | AT91: =ROUND((AO91+AQ91-AS91),0) -> 0 | AX91: =ROUND((AV91+AW91),0) -> 0 | BC91: =ROUND((AX91+AZ91-BB91),0) -> 0 | BF91: 0 | BH91: 0
B92: ISP | C92: Laiyang Yuangkang Import and Export,, Co LTD | F92: =D92+E92 -> 0 | G92: =F92-H92 -> 0 | H92: =ROUND((D92+E92),0) -> 0 | M92: =ROUND((H92+J92-L92),0) -> 0 | R92: =ROUND((P92+Q92),0) -> 0 | W92: =ROUND((R92+T92-V92),0) -> 0 | Y92: 0 | AA92: =ROUND((Y92+Z92),0) -> 0 | AF92: =ROUND((AA92+AC92-AE92),0) -> 0 | AI92: 0 | AO92: =ROUND((AM92+AN92),0) -> 0 | AT92: =ROUND((AO92+AQ92-AS92),0) -> 0 | AX92: =ROUND((AV92+AW92),0) -> 0 | BC92: =ROUND((AX92+AZ92-BB92),0) -> 0 | BF92: 0 | BH92: 0
B93: ISP | C93: Mandiri Berkah Amerta, PT (Autorized Dieler) | F93: =D93+E93 -> 0 | G93: =F93-H93 -> 0 | H93: =ROUND((D93+E93),0) -> 0 | M93: =ROUND((H93+J93-L93),0) -> 0 | R93: =ROUND((P93+Q93),0) -> 0 | W93: =ROUND((R93+T93-V93),0) -> 0 | Y93: 0 | AA93: =ROUND((Y93+Z93),0) -> 0 | AF93: =ROUND((AA93+AC93-AE93),0) -> 0 | AI93: 0 | AO93: =ROUND((AM93+AN93),0) -> 0 | AT93: =ROUND((AO93+AQ93-AS93),0) -> 0 | AX93: =ROUND((AV93+AW93),0) -> 0 | BC93: =ROUND((AX93+AZ93-BB93),0) -> 0 | BF93: 0 | BH93: 0
B94: ISP | C94: Mayekawa Indonesia, PT | F94: =D94+E94 -> 0 | G94: =F94-H94 -> 0 | H94: =ROUND((D94+E94),0) -> 0 | M94: =ROUND((H94+J94-L94),0) -> 0 | R94: =ROUND((P94+Q94),0) -> 0 | W94: =ROUND((R94+T94-V94),0) -> 0 | Y94: 0 | AA94: =ROUND((Y94+Z94),0) -> 0 | AF94: =ROUND((AA94+AC94-AE94),0) -> 0 | AI94: 0 | AO94: =ROUND((AM94+AN94),0) -> 0 | AT94: =ROUND((AO94+AQ94-AS94),0) -> 0 | AX94: =ROUND((AV94+AW94),0) -> 0 | BC94: =ROUND((AX94+AZ94-BB94),0) -> 0 | BF94: 0 | BH94: 0
C95: Mazetta Company, Llc | F95: =D95+E95 -> 0 | G95: =F95-H95 -> 0 | H95: =ROUND((D95+E95),0) -> 0 | M95: =ROUND((H95+J95-L95),0) -> 0 | R95: =ROUND((P95+Q95),0) -> 0 | W95: =ROUND((R95+T95-V95),0) -> 0 | Y95: 0 | AA95: =ROUND((Y95+Z95),0) -> 0 | AF95: =ROUND((AA95+AC95-AE95),0) -> 0 | AI95: 0 | AO95: =ROUND((AM95+AN95),0) -> 0 | AT95: =ROUND((AO95+AQ95-AS95),0) -> 0 | AX95: =ROUND((AV95+AW95),0) -> 0 | BC95: =ROUND((AX95+AZ95-BB95),0) -> 0 | BF95: 0 | BH95: 0
C96: MIDLAND FOOD PRODUCTS INC | F96: =D96+E96 -> 0 | G96: =F96-H96 -> 0 | H96: =ROUND((D96+E96),0) -> 0 | M96: =ROUND((H96+J96-L96),0) -> 0 | R96: =ROUND((P96+Q96),0) -> 0 | W96: =ROUND((R96+T96-V96),0) -> 0 | Y96: 0 | AA96: =ROUND((Y96+Z96),0) -> 0 | AF96: =ROUND((AA96+AC96-AE96),0) -> 0 | AI96: 0 | AO96: =ROUND((AM96+AN96),0) -> 0 | AT96: =ROUND((AO96+AQ96-AS96),0) -> 0 | AX96: =ROUND((AV96+AW96),0) -> 0 | BC96: =ROUND((AX96+AZ96-BB96),0) -> 0 | BF96: 0 | BH96: 0
C97: Monarch Trading, LLC | D97: 0 | F97: =D97+E97 -> 0 | G97: =F97-H97 -> 0 | H97: =ROUND((D97+E97),0) -> 0 | M97: =ROUND((H97+J97-L97),0) -> 0 | R97: =ROUND((P97+Q97),0) -> 0 | W97: =ROUND((R97+T97-V97),0) -> 0 | Y97: 0 | AA97: =ROUND((Y97+Z97),0) -> 0 | AF97: =ROUND((AA97+AC97-AE97),0) -> 0 | AI97: 0 | AO97: =ROUND((AM97+AN97),0) -> 0 | AT97: =ROUND((AO97+AQ97-AS97),0) -> 0 | AX97: =ROUND((AV97+AW97),0) -> 0 | BC97: =ROUND((AX97+AZ97-BB97),0) -> 0 | BF97: 0 | BH97: 5278388480
C98: San Sugar Co, , Ltd | D98: 0 | F98: =D98+E98 -> 0 | G98: =F98-H98 -> 0 | H98: =ROUND((D98+E98),0) -> 0 | M98: =ROUND((H98+J98-L98),0) -> 0 | N98: Piutang usaha Pihak Ketiga (USD) | O98: ok | R98: =ROUND((P98+Q98),0) -> 0 | W98: =ROUND((R98+T98-V98),0) -> 0 | Y98: 0 | AA98: =ROUND((Y98+Z98),0) -> 0 | AF98: =ROUND((AA98+AC98-AE98),0) -> 0 | AH98: 27739814719 | AI98: 2028899760 | AO98: =ROUND((AM98+AN98),0) -> 0 | AT98: =ROUND((AO98+AQ98-AS98),0) -> 0 | AX98: =ROUND((AV98+AW98),0) -> 0 | BC98: =ROUND((AX98+AZ98-BB98),0) -> 0 | BF98: 1060584019 | BH98: 2374932359
C99: Slade Gorton,,Inc | D99: 2033454354 | F99: =D99+E99 -> 2033454354 | G99: =F99-H99 -> 0 | H99: =ROUND((D99+E99),0) -> 2033454354 | M99: =ROUND((H99+J99-L99),0) -> 2033454354 | N99: Piutang usaha Pihak Ketiga (USD) | P99: 3523030954 | R99: =ROUND((P99+Q99),0) -> 3523030954 | W99: =ROUND((R99+T99-V99),0) -> 3523030954 | Y99: 0 | AA99: =ROUND((Y99+Z99),0) -> 0 | AF99: =ROUND((AA99+AC99-AE99),0) -> 0 | AH99: =AF105-AH98 -> 22200778 | AI99: 0 | AO99: =ROUND((AM99+AN99),0) -> 0 | AT99: =ROUND((AO99+AQ99-AS99),0) -> 0 | AX99: =ROUND((AV99+AW99),0) -> 0 | BC99: =ROUND((AX99+AZ99-BB99),0) -> 0 | BF99: 1678812320 | BH99: 0
C100: H & T SEAFOODS INC | D100: 0 | F100: =D100+E100 -> 0 | G100: =F100-H100 -> 0 | H100: =ROUND((D100+E100),0) -> 0 | M100: =ROUND((H100+J100-L100),0) -> 0 | P100: 1981564200 | R100: =ROUND((P100+Q100),0) -> 1981564200 | W100: =ROUND((R100+T100-V100),0) -> 1981564200
C101: Yachiyo Corporation | D101: 752163318 | F101: =D101+E101 -> 752163318 | G101: =F101-H101 -> 0 | H101: =ROUND((D101+E101),0) -> 752163318 | M101: =ROUND((H101+J101-L101),0) -> 752163318 | N101: Piutang usaha Pihak Ketiga (USD) | O101: ok | R101: =ROUND((P101+Q101),0) -> 0 | W101: =ROUND((R101+T101-V101),0) -> 0 | Y101: 0 | AA101: =ROUND((Y101+Z101),0) -> 0 | AF101: =ROUND((AA101+AC101-AE101),0) -> 0 | AI101: 624270920 | AO101: =ROUND((AM101+AN101),0) -> 0 | AT101: =ROUND((AO101+AQ101-AS101),0) -> 0 | AX101: =ROUND((AV101+AW101),0) -> 0 | BC101: =ROUND((AX101+AZ101-BB101),0) -> 0 | BF101: 0 | BH101: 0
...

Sheet IPK ISP
D5: 2024 | F5: 2023
C7: Saldo awal | D7: =F16 -> 6654137321 | F7: 6056351464
C8: Beban imbalan paska kerja
C9: selama tahun berjalan | D9: =I13+I14 -> 593613940 | F9: 592555438
C10: Pengukuran kembali atas
C11: liabilitas diestimasi atas
C12: imbalan kerja karyawan | D12: =I16 -> -29507139 | F12: 5230419 | I12: =F16 -> 6654137321 | J12: Saldo awal ipk des 23 | K12: liabilitas
C13: Pembayaran Imbalan Pasca | I13: 147786739 | J13: Biaya Jasa Kini | K13: beban opex | M13: =I13+I14 -> 593613940 | N13: =M13*22% -> 1.3059507e+08
C14: Kerja pada tahun berjalan | F14: 0 | I14: 445827201 | J14: Biaya Bunga | K14: beban opex | M14: =I16 -> -29507139 | N14: =M14*22% -> -6491570.6
C16: Saldo Akhir Liabilitas | D16: =SUM(D7:D14) -> 7218244122 | F16: =SUM(F7:F14) -> 6654137321 | I16: -29507139 | J16: Pendapatan oci berjalan | K16: oci pl
I18: =SUM(I12:I16) -> 7218244122 | J18: Saldo akhir ipk des 24 | K18: liabilitas
C19: Total beban imbalan paska kerja karyawan adalah sebagai berikut:
I20: jurnal
D21: 2024 | F21: 2023 | I21: =I14+I13 -> 593613940 | J21: beban ipk (opex)
J22: =I16 -> -29507139 | K22: oci pl berjalan ipk
C23: Biaya Jasa Kini | D23: 147786739 | F23: 150441781 | G23: 255179128 | H23: =G23-F23 -> 104737347 | J23: =I21+J22 -> 564106801
C24: Biaya Bunga | D24: 445827201 | F24: 442113657 | G24: 616959638 | H24: =G24-F24 -> 174845981
C25: Biaya Jasa Lalu 1 | D25: 0 | F25: 0
C26: Biaya Jasa Lalu 2 | D26: 0 | F26: 0
C27: Pembayaran Imbalan Pasca
C28: Kerja pada tahun berjalan | D28: 0 | F28: 0
C30: Jumlah Beban Imbalan Pasca Kerja Karyawan | D30: =SUM(D23:D28) -> 593613940 | F30: =SUM(F23:F28) -> 592555438
C33: Persentase perubahan kenaikan atau penurunan 1% terhadap tingkat diskonto
C35: 2024
D36: Nilai Kini
D37: Liabilitas/ | F37: Biaya Jasa
D38: Present Value | F38: Kini/
D39: of Benefit | F39: Current Service
C40: Deskripsi | D40: Liabilities | F40: Cost
C42: Sesuai Laporan Aktuaris 7,1% | D42: 7218244122 | F42: 147786739
C43: Penurunan 1% atas Tingkat Diskonto | D43: 7293596629 | F43: 164097344
C44: Kenaikan 1% atas Tingkat Diskonto | D44: 7153428883 | F44: 133678787
C47: 2023
D48: Nilai Kini
D49: Liabilitas/ | F49: Biaya Jasa
D50: Present Value | F50: Kini/
D51: of Benefit | F51: Current Service
C52: Deskripsi | D52: Liabilities | F52: Cost
C54: Sesuai Laporan Aktuaris 7,3% | D54: 6654137321 | F54: 150441781
C55: Penurunan 1% atas Tingkat Diskonto | D55: 6056351464 | F55: 309479559
C56: Kenaikan 1% atas Tingkat Diskonto | D56: 5782998262 | F56: 132634097
C59: Persentase perubahan kenaikan atau penurunan 1% terhadap tingkat kenaikan gaji.
C61: 2024
D62: Nilai Kini
D63: Liabilitas/ | F63: Biaya Jasa
D64: Present Value | F64: Kini/
D65: of Benefit | F65: Current Service
C66: Deskripsi | D66: Liabilities | F66: Cost
C68: Sesuai Laporan Aktuaris 7,1% | D68: 7218244122 | F68: 147786739
C69: Penurunan 1% atas Tingkat Kenaikan Gaji | D69: 7149083542 | F69: 133542688
C70: Kenaikan 1% atas Tingkat Kenaikan Gaji | D70: 7297770211 | F70: 164951255
C73: 2023
D74: Nilai Kini
D75: Liabilitas/ | F75: Biaya Jasa
D76: Present Value | F76: Kini/
D77: of Benefit | F77: Current Service
C78: Deskripsi | D78: Liabilities | F78: Cost
C80: Sesuai Laporan Aktuaris 6,7%
C81: Penurunan 1% atas Tingkat Kenaikan Gaji | D81: 7254564686 | F81: 168104932
C82: Kenaikan 1% atas Tingkat Kenaikan Gaji | D82: 6128140154 | F82: 135297010

Sheet IPK Konsol 
D5: 2024 | F5: 2023
C7: Saldo awal | D7: =F16 -> 9301883257 | F7: 8419134989
C8: Beban imbalan paska kerja
C9: selama tahun berjalan | D9: ='IPK ISP'!D9+'IPK IAS'!D9 -> 883796658 | F9: 872138766
C10: Pengukuran kembali atas
C11: liabilitas diestimasi atas
C12: imbalan kerja karyawan | D12: ='IPK ISP'!D12+'IPK IAS'!D12 -> -81138443 | F12: 0 | I12: =F16 -> 9301883257 | J12: Saldo awal ipk des 23 | K12: liabilitas
C13: Pembayaran Imbalan Pasca | I13: 147786739 | J13: Biaya Jasa Kini | K13: beban opex
C14: Kerja pada tahun berjalan | D14: 0 | F14: 10609502 | I14: 445827201 | J14: Biaya Bunga | K14: beban opex
C16: Saldo Akhir Liabilitas | D16: =SUM(D7:D14) -> 10104541472 | F16: =SUM(F7:F14) -> 9301883257 | I16: -29507139 | J16: Pendapatan oci berjalan | K16: oci pl
D17: ='BS Konsol-Des 24'!G76 -> 10104541472
D18: =D16-D17 -> 0 | I18: =SUM(I12:I16) -> 9865990058 | J18: Saldo akhir ipk des 24 | K18: liabilitas
C19: Total beban imbalan paska kerja karyawan adalah sebagai berikut:
I20: jurnal
D21: 2024 | F21: 2023 | I21: =I14+I13 -> 593613940 | J21: beban ipk (opex)
J22: =I16 -> -29507139 | K22: oci pl berjalan ipk
C23: Biaya Jasa Kini | D23: ='IPK IAS'!D23+'IPK ISP'!D23 -> 255274987 | F23: 255179128 | J23: =I21+J22 -> 564106801
C24: Biaya Bunga | D24: ='IPK IAS'!D24+'IPK ISP'!D24 -> 628521671 | F24: 616959638
C25: Biaya Jasa Lalu 1 | D25: 0 | F25: 0
C26: Biaya Jasa Lalu 2 | D26: 0 | F26: 0
C27: Pembayaran Imbalan Pasca
C28: Kerja pada tahun berjalan | D28: 0 | F28: 0
C30: Jumlah Beban Imbalan Pasca Kerja Karyawan | D30: =SUM(D23:D28) -> 883796658 | F30: =SUM(F23:F28) -> 872138766
C33: Persentase perubahan kenaikan atau penurunan 1% terhadap tingkat diskonto
C35: 2024
D36: Nilai Kini
D37: Liabilitas/ | F37: Biaya Jasa
D38: Present Value | F38: Kini/
D39: of Benefit | F39: Current Service
C40: Deskripsi | D40: Liabilities | F40: Cost
C42: Sesuai Laporan Aktuaris 7,1% | D42: ='IPK IAS'!D42+'IPK ISP'!D42 -> 10104541472 | F42: ='IPK IAS'!F42+'IPK ISP'!F42 -> 255274987
C43: Penurunan 1% atas Tingkat Diskonto | D43: ='IPK IAS'!D43+'IPK ISP'!D43 -> 10518604249 | F43: ='IPK IAS'!F43+'IPK ISP'!F43 -> 289761137
C44: Kenaikan 1% atas Tingkat Diskonto | D44: ='IPK IAS'!D44+'IPK ISP'!D44 -> 9749509778 | F44: ='IPK IAS'!F44+'IPK ISP'!F44 -> 225938929
C47: 2023
D48: Nilai Kini
D49: Liabilitas/ | F49: Biaya Jasa
D50: Present Value | F50: Kini/
D51: of Benefit | F51: Current Service
C52: Deskripsi | D52: Liabilities | F52: Cost
C54: Sesuai Laporan Aktuaris 7,3% | D54: 9301883257 | F54: 255179128
C55: Penurunan 1% atas Tingkat Diskonto | D55: 10300546683 | F55: 291519996
C56: Kenaikan 1% atas Tingkat Diskonto | D56: 8437567711 | F56: 224516602
C59: Persentase perubahan kenaikan atau penurunan 1% terhadap tingkat kenaikan gaji.
C61: 2024
D62: Nilai Kini
D63: Liabilitas/ | F63: Biaya Jasa
D64: Present Value | F64: Kini/
D65: of Benefit | F65: Current Service
C66: Deskripsi | D66: Liabilities | F66: Cost
C68: Sesuai Laporan Aktuaris 7,1% | D68: ='IPK IAS'!D58+'IPK ISP'!D68 -> 10104541472 | F68: ='IPK IAS'!F58+'IPK ISP'!F68 -> 255274987
C69: Penurunan 1% atas Tingkat Kenaikan Gaji | D69: ='IPK IAS'!D59+'IPK ISP'!D69 -> 9728830736 | F69: ='IPK IAS'!F59+'IPK ISP'!F69 -> 225789806
C70: Kenaikan 1% atas Tingkat Kenaikan Gaji | D70: ='IPK IAS'!D60+'IPK ISP'!D70 -> 10537372834 | F70: ='IPK IAS'!F60+'IPK ISP'!F70 -> 290869567
C73: 2023
D74: Nilai Kini
D75: Liabilitas/ | F75: Biaya Jasa
D76: Present Value | F76: Kini/
D77: of Benefit | F77: Current Service
C78: Deskripsi | D78: Liabilities | F78: Cost
C80: Sesuai Laporan Aktuaris 6,7% | D80: 9301883257 | F80: 255179128
C81: Penurunan 1% atas Tingkat Kenaikan Gaji | D81: 8357246610 | F81: 223688470
C82: Kenaikan 1% atas Tingkat Kenaikan Gaji | D82: 10502426918 | F82: 295281766

Sheet BS Konsol-Des 24
A1: PT INDO AMERICAN SEAFOODS
A2: LAPORAN POSISI KEUANGAN KONSOLIDASIAN
A3: Tanggal 31 Desember 2024 dan 2023
A4: (Disajikan dalam Rupiah, kecuali dinyatakan lain)
E6: Catatan/
E7: Notes | G7: 2024 | Q7: 2023 | S7: 2022 | U7: 2021
A9: ASET | W9: ASSETS
A10: ASET LANCAR | W10: CURRENT ASSETS
A11: Kas dan Setara Kas | E11: 4 | G11: ='WS Konsol'!M52 -> 918209485 | I11: ='WS Konsol'!W52 -> 13187388399 | K11: ='WS Konsol'!AT52 -> 2814373246 | M11: ='WS Konsol'!AF52 -> 565886797 | O11: ='WS Konsol'!BC52 -> 5733063270 | Q11: ='WS Konsol'!AI52 -> 2570121355 | S11: ='WS Konsol'!BF52 -> 4920468963 | U11: ='WS Konsol'!BH52 -> 4972845584 | W11: Cash and Cash Equivalents
A12: Piutang Usaha | W12: Trade Accounts Receivable
B13: Pihak Berelasi | E13: 5 | G13: ='WS Konsol'!M111 -> 393935430 | I13: ='WS Konsol'!W111 -> 339894481 | K13: ='WS Konsol'!AT111 -> 482874409 | M13: ='WS Konsol'!AF111 -> 422639675 | O13: ='WS Konsol'!BC111 -> 1783377782 | Q13: ='WS Konsol'!AI111 -> 211054410 | S13: ='WS Konsol'!BF111 -> 1729176327 | U13: ='WS Konsol'!BH111 -> 1565918952 | X13: Related Party
B14: Pihak Ketiga | E14: 5 | G14: ='WS Konsol'!M105+'WS Konsol'!M115+'WS Konsol'!M127 -> 94399254849 | I14: ='WS Konsol'!W105+'WS Konsol'!W115+'WS Konsol'!W127 -> 37856978018 | K14: ='WS Konsol'!AT105+'WS Konsol'!AT115+'WS Konsol'!AT127 -> 5523361062 | M14: ='WS Konsol'!AF105+'WS Konsol'!AF115+'WS Konsol'!AF127 -> 26199584563 | O14: ='WS Konsol'!BC105+'WS Konsol'!BC115+'WS Konsol'!BC127 -> 25423470999 | Q14: ='WS Konsol'!AI105+'WS Konsol'!AI115+'WS Konsol'!AI127 -> 19981020112 | S14: ='WS Konsol'!BF105+'WS Konsol'!BF115+'WS Konsol'!BF127 -> 53102808880 | U14: ='WS Konsol'!BH105+'WS Konsol'!BH115+'WS Konsol'!BH127 -> 38673285818 | X14: Third Parties | AB14: =G14/Q14 -> 4.7244462
A15: Piutang Lain-lain Pihak dari Ketiga | E15: 6 | G15: ='WS Konsol'!M132+'WS Konsol'!M137+('WS Konsol'!M129+'WS Konsol'!M130+'WS Konsol'!M133) -> 697232257 | I15: ='WS Konsol'!W132+'WS Konsol'!W137 -> 510634104 | K15: ='WS Konsol'!AT132+'WS Konsol'!AT137+'WS Konsol'!AT131+'WS Konsol'!AT135 -> 638756399 | M15: ='WS Konsol'!AF132+'WS Konsol'!AF137 -> 510634104 | O15: ='WS Konsol'!BC132+'WS Konsol'!BC137 -> 549732399 | Q15: ='WS Konsol'!AI132+'WS Konsol'!AI137 -> 510634104 | S15: ='WS Konsol'!BF132+'WS Konsol'!BF137 -> 549732399 | U15: ='WS Konsol'!BH132+'WS Konsol'!BH120 -> 466154019 | W15: Other Receivables from Third Parties
A16: Persediaan | E16: 7 | G16: ='WS Konsol'!M147 -> 217742151701 | I16: ='WS Konsol'!W147 -> 262102659717 | K16: ='WS Konsol'!AT147 -> 215160428159 | M16: ='WS Konsol'!AF147 -> 224990831176 | O16: ='WS Konsol'!BC147 -> 215178073837 | Q16: ='WS Konsol'!AI147 -> 218071396362 | S16: ='WS Konsol'!BF147 -> 137179893500 | U16: ='WS Konsol'!BH147 -> 95865646086 | W16: Inventories
A17: Aset Biologis | E17: 8 | G17: ='WS Konsol'!M182 -> 913803984 | I17: ='WS Konsol'!W182 -> 3489807904 | K17: ='WS Konsol'!AT182 -> 2917522322 | M17: ='WS Konsol'!AF182 -> 2649404556 | O17: ='WS Konsol'!BC182 -> 1792056297 | Q17: ='WS Konsol'!AI182 -> 2415719386 | S17: ='WS Konsol'!BF182 -> 651253829 | U17: ='WS Konsol'!BH182 -> 871760289 | W17: Biological Assets | AB17: =G17/Q17 -> 0.37827406 | AC17: =Q17/G17 -> 2.643586
A18: Pajak Dibayar Dimuka | E18: 18a | G18: =SUM('WS Konsol'!M149:M157) -> 9035601705 | I18: =SUM('WS Konsol'!W149:W156) -> 11345112342 | K18: =SUM('WS Konsol'!AT149:AT156) -> 9387594367 | M18: =SUM('WS Konsol'!AF149:AF156) -> 10425187749 | O18: =SUM('WS Konsol'!BC149:BC156) -> 9041536321 | Q18: =SUM('WS Konsol'!AI149:AI156) -> 9663458887 | S18: =SUM('WS Konsol'!BF149:BF156) -> 8035438770 | U18: =SUM('WS Konsol'!BH149:BH156) -> 8635897222 | W18: Prepaid Taxes
A19: Uang Muka dan Biaya Dibayar | W19: Prepaid Expenses and
A20: Dimuka | E20: 9 | G20: ='WS Konsol'!M159+'WS Konsol'!M174+'WS Konsol'!M164+'WS Konsol'!M175+'WS Konsol'!M161 -> 33893674735 | I20: ='WS Konsol'!W159+'WS Konsol'!W174+'WS Konsol'!W164+'WS Konsol'!W175 -> 1488682854 | K20: ='WS Konsol'!AT159+'WS Konsol'!AT174+'WS Konsol'!AT164+'WS Konsol'!AT175 -> 924473645 | M20: ='WS Konsol'!AF159+'WS Konsol'!AF174+'WS Konsol'!AF164 -> 2074112410 | O20: ='WS Konsol'!BC159+'WS Konsol'!BC174 -> 903603741 | Q20: ='WS Konsol'!AI159+'WS Konsol'!AI174 -> 1104447053 | S20: ='WS Konsol'!BF164+'WS Konsol'!BF159 -> 349309986 | U20: =SUM('WS Konsol'!BH164:BH173)+'WS Konsol'!BH159+'WS Konsol'!BH247 -> 227462120 | W20: Advances | AB20: =Q20/G20 -> 0.032585639
A21: Uang Jaminan | E21: 12 | G21: ='WS Konsol'!M229 -> 3232400000 | Q21: 0 | W21: Security Deposit
A23: Jumlah Aset Lancar | G23: =SUM(G11:G21) -> 361226264146 | I23: =SUM(I11:I20) -> 330321157819 | K23: =SUM(K11:K20) -> 237849383609 | M23: =SUM(M11:M20) -> 267838281030 | O23: =SUM(O11:O20) -> 260404914646 | Q23: =SUM(Q11:Q21) -> 254527851669 | S23: =SUM(S11:S20) -> 206518082654 | U23: =SUM(U11:U20) -> 151278970090 | W23: Total Current Assets | AB23: 354387649562 | AC23: =G23-AB23 -> 6838614584
A25: ASET TIDAK LANCAR | W25: NON-CURRENT ASSETS
A27: Piutang Lain-lain dari | W27: Other Receivable from
A28: Pihak Berelasi | E28: 6 | G28: ='WS Konsol'!M133+'WS Konsol'!M187 -> 0 | I28: ='WS Konsol'!W133+'WS Konsol'!W187 -> 0 | K28: ='WS Konsol'!AT133+'WS Konsol'!AT187 -> 7148897634 | M28: ='WS Konsol'!AF133+'WS Konsol'!AF187 -> 0 | O28: ='WS Konsol'!BC133+'WS Konsol'!BC187+'WS Konsol'!BC130 -> 7348897634 | Q28: ='WS Konsol'!AI133+'WS Konsol'!AI187 -> 7022707423 | S28: ='WS Konsol'!BF133+'WS Konsol'!BF187+'WS Konsol'!BF130 -> 7197443207 | U28: ='WS Konsol'!BH133+'WS Konsol'!BH187+'WS Konsol'!BH130 -> 6836690211 | W28: Related Parties
A29: Aset Tetap | E29: 10 | G29: ='WS Konsol'!M219 -> 66637513685 | I29: ='WS Konsol'!W201-'WS Konsol'!W214+'WS Konsol'!W218 -> 68366993855 | K29: ='WS Konsol'!AT201-'WS Konsol'!AT214+'WS Konsol'!AT218 -> 76686886952 | M29: ='WS Konsol'!AF201-'WS Konsol'!AF214+'WS Konsol'!AF218 -> 70317926651 | O29: ='WS Konsol'!BC201-'WS Konsol'!BC214+'WS Konsol'!BC218 -> 79240630124 | Q29: ='WS Konsol'!AI201-'WS Konsol'!AI214+'WS Konsol'!AI218 -> 74113104582 | S29: ='WS Konsol'!BF201-'WS Konsol'!BF214+'WS Konsol'!BF218 -> 84248284795 | U29: ='WS Konsol'!BH201-'WS Konsol'!BH214+'WS Konsol'!BH218 -> 94612283276 | W29: Fixed Assets
A33: Aset Hak-Guna | E33: 11 | G33: ='WS Konsol'!M236 -> 7556618094 | I33: ='WS Konsol'!W236 -> 7635332866 | K33: ='WS Konsol'!AT236 -> 7950191953 | M33: ='WS Konsol'!AF236 -> 7714047638 | O33: ='WS Konsol'!BC236 -> 8028906725 | Q33: ='WS Konsol'!AI236 -> 7871477182 | S33: ='WS Konsol'!BF236 -> 8186336269 | U33: ='WS Konsol'!BH236 -> 8501195356 | W33: Right-of-Use Assets
A36: Aset Dalam Proses | W36: Work in Process
A37: Aset Pajak Tangguhan | E37: 18e | G37: ='WS Konsol'!M245 -> 1848977778 | I37: ='WS Konsol'!W245 -> 1790182139 | K37: ='WS Konsol'!AT245 -> 1508277305 | M37: ='WS Konsol'!AF245 -> 1790182139 | O37: ='WS Konsol'!BC245 -> 1508277305 | Q37: ='WS Konsol'!AI245+1 -> 1790182140 | S37: ='WS Konsol'!BF245 -> 1508277305 | U37: ='WS Konsol'!BH245 -> 1486561645 | W37: Deferred Tax Assets
A39: Jumlah Aset Tidak Lancar | G39: =SUM(G28:G37) -> 76043109557 | I39: =SUM(I28:I37) -> 77792508860 | K39: =SUM(K28:K37) -> 93294253844 | M39: =SUM(M28:M37) -> 79822156428 | O39: =SUM(O28:O37) -> 96126711788 | Q39: =SUM(Q28:Q37) -> 90797471327 | S39: =SUM(S28:S37) -> 101140341576 | U39: =SUM(U28:U37) -> 111436730488 | W39: Total Non-Current Assets
A42: JUMLAH ASET | G42: =G23+G39 -> 437269373703 | I42: =I23+I39 -> 408113666679 | K42: =K23+K39 -> 331143637453 | M42: =M23+M39 -> 347660437458 | O42: =O23+O39 -> 356531626434 | Q42: =Q23+Q39 -> 345325322996 | S42: =S23+S39 -> 307658424230 | U42: =ROUNDUP(U23+U39,0) -> 262715700578 | W42: TOTAL ASSETS
E46: Catatan/ | I46: =I6 -> 0 | M46: 30 Juni 2024/
E47: Notes | G47: 2024 | Q47: 2023 | S47: 2022 | U47: 2021
A48: LIABILITAS DAN EKUITAS | W48: LIABILITIES AND EQUITY
A49: LIABILITAS | W49: LIABILITIES
A50: LIABILITAS JANGKA PENDEK | W50: CURRENT LIABILITIES
W51: Trade Accounts Payable to
A52: Utang Usaha kepada Pihak Ketiga | E52: 13 | G52: ='WS Konsol'!M417+'WS Konsol'!M422+'WS Konsol'!M425 -> 10364486466 | I52: ='WS Konsol'!W417+'WS Konsol'!W422+'WS Konsol'!W425 -> 10645094570 | K52: ='WS Konsol'!AT417+'WS Konsol'!AT422+'WS Konsol'!AT425 -> 20367712664 | M52: ='WS Konsol'!AF417+'WS Konsol'!AF422+'WS Konsol'!AF425 -> 14186291754 | O52: ='WS Konsol'!BC417+'WS Konsol'!BC422+'WS Konsol'!BC425 -> 47195337849 | Q52: ='WS Konsol'!AI417+'WS Konsol'!AI422+'WS Konsol'!AI425 -> 20407901137 | S52: ='WS Konsol'!BF417+'WS Konsol'!BF422+'WS Konsol'!BF425 -> 12347357380 | U52: ='WS Konsol'!BH417+'WS Konsol'!BH422+'WS Konsol'!BH425 -> 14116621585 | W52: Thrid Parties | AC52: 6968061921 | AD52: =AC52-G52 -> -3396424545
A53: Utang Lain-lain | W53: Other Payables
B54: Pihak Ketiga | X54: Third Parties
A55: Utang Bank | E55: 19a | G55: ='WS Konsol'!M288-G64 -> 231271837921 | I55: ='WS Konsol'!W288-I64 -> 196870184183 | K55: ='WS Konsol'!AT288 -> 175110562667 | M55: ='WS Konsol'!AF288-M64 -> 207371015601 | O55: ='WS Konsol'!BC288 -> 166123612313 | Q55: ='WS Konsol'!AI288-Q64 -> 195441714689 | S55: ='WS Konsol'!BF288 -> 155339616431 | U55: ='WS Konsol'!BH288 -> 110815447741 | W55: Bank Loans | AB55: =G55/16162 -> 14309605
A56: Beban Akrual | E56: 15 | G56: ='WS Konsol'!M467-G61 -> 4970839301 | I56: ='WS Konsol'!W467-I61 -> 4949487657 | K56: ='WS Konsol'!AT467-K61 -> 6409271318 | M56: ='WS Konsol'!AF467-M61 -> 4322494743 | O56: ='WS Konsol'!BC467-O61 -> 8217143369 | Q56: ='WS Konsol'!AI467-Q61+1 -> 2870843989 | S56: ='WS Konsol'!BF467-S61+1 -> 5031429971 | U56: ='WS Konsol'!BH467-U61-2 -> 5655591014 | W56: Accrued Expenses | AB56: =Q55/15416 -> 12677849
A57: Utang Pajak | E57: 18b | G57: ='WS Konsol'!M453 -> 1467515499 | I57: ='WS Konsol'!W453 -> 4409068751 | K57: ='WS Konsol'!AT453 -> 2337914037 | M57: ='WS Konsol'!AF453 -> 404042742 | O57: ='WS Konsol'!BC453 -> 2317673499 | Q57: ='WS Konsol'!AI453 -> 2863697915 | S57: ='WS Konsol'!BF453 -> 2152621331 | U57: ='WS Konsol'!BH453 -> 712242589 | W57: Taxes Payable | AB57: 1467515279
A58: Bagian Lancar dari Utang | W58: Current Portion of
A59: Jangka Panjang | W59: Long-Term Liabilities
X60: Purchase of Fixed Assets
B61: Utang Pembelian Aset Tetap | E61: 16 | G61: ='WS Konsol'!M463 -> 0 | I61: ='WS Konsol'!W463 -> 19446177 | K61: ='WS Konsol'!AT463 -> 17659190 | M61: ='WS Konsol'!AF463 -> 38822068 | O61: ='WS Konsol'!BC463 -> 34780634 | Q61: ='WS Konsol'!AI463 -> 76360023 | S61: ='WS Konsol'!BF463 -> 67475296 | U61: ='WS Konsol'!BH463 -> 0 | X61: Liabilities
B62: Liabilitas Sewa kepada | X62: Lease Liabilities to
B63: Pihak Berelasi | E63: 17 | G63: ='WS Konsol'!M470 -> 0 | I63: ='WS Konsol'!W470 -> 0 | K63: ='WS Konsol'!AT470 -> 3533493723 | M63: ='WS Konsol'!AF470 -> 0 | O63: ='WS Konsol'!BC470 -> 3533493723 | Q63: ='WS Konsol'!AI470 -> 624277457 | S63: ='WS Konsol'!BF470 -> 3539216266 | U63: ='WS Konsol'!BH470 -> 0 | X63: Related Parties | AE63: =AD63-AD62 -> 0
B64: Utang Bank | E64: 18a | G64: ='WS Konsol'!M278 -> 0 | I64: ='WS Konsol'!W278 -> 900894064 | K64: ='WS Konsol'!AT472 -> 850908333 | M64: ='WS Konsol'!AF278 -> 1869894064 | O64: ='WS Konsol'!BC472 -> 6824412708 | Q64: ='WS Konsol'!AI278 -> 3807894064 | S64: ='WS Konsol'!BF472 -> 3403633332 | U64: ='WS Konsol'!BH472 -> 3403633332 | X64: Bank Loans
A66: Jumlah Liabilitas Jangka Pendek | G66: =SUM(G52:G64) -> 248074679187 | I66: =SUM(I52:I64) -> 217794175402 | K66: =SUM(K52:K64) -> 208627521932 | M66: =SUM(M52:M64) -> 228192560972 | O66: =SUM(O52:O64) -> 234246454095 | Q66: =SUM(Q52:Q64) -> 226092689274 | S66: =SUM(S52:S64) -> 181881350007 | U66: =SUM(U52:U64) -> 134703536261 | W66: Total Current Liabilities
A68: LIABILITAS JANGKA PANJANG | W68: NON-CURRENT LIABILITIES
A69: Liabiltas Jangka Panjang Dikurangi | W69: Long-Term Liabilities Net of
A70: Bagian Lancar | W70: Current Portion
B71: Utang Lain-lain kepada Pihak Berelasi | E71: 14 | G71: =SUM('WS Konsol'!M427:M432)+'WS Konsol'!M504 -> 0 | I71: =SUM('WS Konsol'!W427:W432)+'WS Konsol'!W504 -> 0 | K71: =SUM('WS Konsol'!AT427:AT432)+'WS Konsol'!AT504 -> 1288271695 | M71: =SUM('WS Konsol'!AF427:AF432)+'WS Konsol'!AF504 -> 0 | O71: =SUM('WS Konsol'!BC427:BC432)+'WS Konsol'!BC504 -> 1313271695 | Q71: =SUM('WS Konsol'!AI427:AI432)+'WS Konsol'!AI504 -> 595676695 | S71: =SUM('WS Konsol'!BF427:BF432)+'WS Konsol'!BF504 -> 533174595 | U71: =SUM('WS Konsol'!BH427:BH432)+'WS Konsol'!BH504 -> 137349400 | X71: Other Payable to Related Party
B72: Utang Lain-lain kepada Pihak Ketiga | E72: 14 | G72: ='WS Konsol'!M424 -> 0 | I72: ='WS Konsol'!W424 -> 0 | K72: ='WS Konsol'!AT424 -> 41000000 | M72: ='WS Konsol'!AF424 -> 0 | O72: ='WS Konsol'!BC424 -> 41000000 | Q72: ='WS Konsol'!AI424 -> 41000000 | S72: ='WS Konsol'!BF424 -> 41000000 | U72: ='WS Konsol'!BH424 -> 41000000 | X72: Other Payable to Third Party
B73: Utang Bank | E73: 19b | G73: ='WS Konsol'!AB494-G74 -> 0 | I73: ='WS Konsol'!AD494-I74 -> 0 | K73: ='WS Konsol'!AT494-K74 -> 3403633336 | M73: ='WS Konsol'!AF494-M74 -> 0 | O73: ='WS Konsol'!BC494-O74 -> 3403633336 | Q73: ='WS Konsol'!AI494-Q74 -> 0 | S73: ='WS Konsol'!BF494-S74 -> 8526229378 | U73: ='WS Konsol'!BH494-U74 -> 14285076353 | X73: Bank loans
B74: Utang Pembelian Aset Tetap | G74: ='WS Konsol'!AB484 -> 0 | I74: ='WS Konsol'!AD484 -> 0 | K74: ='WS Konsol'!AT484 -> 76360023 | M74: ='WS Konsol'!AF484 -> 0 | O74: ='WS Konsol'!BC484 -> 76360023 | Q74: ='WS Konsol'!AI484 -> 0 | S74: ='WS Konsol'!BF484 -> 76360023 | U74: ='WS Konsol'!BH484 -> 0 | X74: Purchase of Fixed Assets Liabilities
B75: Liabilitas Sewa kepada Pihak Berelasi | G75: 0 | I75: 0 | K75: ='WS Konsol'!AT497 -> 630000000 | M75: 0 | O75: ='WS Konsol'!BC497 -> 630000000 | Q75: 0 | S75: ='WS Konsol'!BF497 -> 624277457 | U75: ='WS Konsol'!BH497 -> 4125675035 | X75: Lease Liabilities to Related Parties
A76: Liabilitas Imbalan Pascakerja | E76: 20 | G76: ='WS Konsol'!M481 -> 10104541472 | I76: ='WS Konsol'!W481 -> 9955987332 | K76: ='WS Konsol'!AT481 -> 8706660415 | M76: ='WS Konsol'!AF481 -> 9301883257 | O76: ='WS Konsol'!BC481 -> 8419134989 | Q76: ='WS Konsol'!AI481 -> 9301883257 | S76: ='WS Konsol'!BF481 -> 8419134989 | U76: ='WS Konsol'!BH481 -> 8346918827 | W76: Post-Employment Benefits Liabilities
A80: Jumlah Liabilitas Jangka Panjang | G80: =SUM(G71:G77) -> 10104541472 | I80: =SUM(I71:I77) -> 9955987332 | K80: =SUM(K71:K77) -> 14145925469 | M80: =SUM(M71:M77) -> 9301883257 | O80: =SUM(O71:O77) -> 13883400043 | Q80: =SUM(Q71:Q77) -> 9938559952 | S80: =SUM(S71:S77) -> 18220176442 | U80: =SUM(U71:U77) -> 26936019615 | W80: Total Non-Current Liabilities
A82: JUMLAH LIABILITAS | G82: =G66+G80 -> 258179220659 | I82: =I66+I80 -> 227750162734 | K82: =K66+K80 -> 222773447401 | M82: =M66+M80 -> 237494444229 | O82: =O66+O80 -> 248129854138 | Q82: =Q66+Q80 -> 236031249226 | S82: =S66+S80 -> 200101526449 | U82: =U66+U80 -> 161639555876 | W82: TOTAL LIABILITIES
O83: =O82-'WS Konsol'!BC506 -> 0
E85: Catatan/ | G85: Juni 2024/ | I85: Juni 2024/ | K85: Juni 2024/ | M85: Juni 2024/ | Q85: Desember 2023/
E86: Notes | G86: June 2024 | I86: June 2024 | K86: June 2024 | M86: June 2024 | O86: =O7 -> 0 | Q86: December 2023 | S86: 2022 | U86: 2021*)
A88: EKUITAS | W88: EQUITY
A89: Modal Saham - Nilai Nominal | W89: Share Capital
A90: Rp 50,- per Saham | W90: Par value Rp 50 per share,
B91: Modal Dasar Sebesar 3.200.000.000 | X91: Authorized Capital 3,200,000,000
B92: Saham pada 31 Desember | X92: shares as of December 31,
B93: 2024 dan 800.000.000 Saham | X93: 2024 and 800,000,000 Shares
B94: pada 31 Desember 2023 | X94: as of December, 31 2023
B95: Modal Disetor dan Ditempatkan pada | S95: ='WS Konsol'!BF508-1000000000 -> 40000000000 | U95: 40000000000 | X95: Authorized and Subscribed
B96: 31 Desember 2024 dan 2023 | X96: as of December 31, 2024 and 2023
B97: masing-masing 1.390.000.000 | X97: 1,390,000,000 Shares and
B98: Saham dan 800.000.000 Saham | E98: 21a | G98: ='WS Konsol'!M508+'WS Konsol'!M509 -> 69500000000 | I98: ='WS Konsol'!W508-1000000000+'WS Konsol'!W509 -> 69500000000 | K98: ='WS Konsol'!AT508-1000000000 -> 40000000000 | M98: ='WS Konsol'!AF508-1000000000 -> 55000000000 | O98: ='WS Konsol'!BC508-1000000000 -> 40000000000 | Q98: ='WS Konsol'!AI508-1000000000 -> 40000000000 | X98: 800,000,000, respectively
A99: Tambahan Modal Disetor | E99: 22 | G99: =SUM('WS Konsol'!M510:M512) -> 104623471870 | I99: =SUM('WS Konsol'!W510:W512) -> 104623471870 | K99: ='WS Konsol'!AT512 -> 49739416785 | M99: ='WS Konsol'!AF512 -> 49739416785 | O99: ='WS Konsol'!BC512 -> 49739416785 | Q99: ='WS Konsol'!AI512 -> 49739416785 | S99: ='WS Konsol'!BF512 -> 25871690669 | U99: 25871690669 | W99: Additional Paid-in Capital | Y99: BAE -Daftar Pembeli Saham | AA99: Cek aturan OJK
A100: Proforma Ekuitas | G100: 0 | I100: 0 | K100: 0 | M100: 0 | O100: 0 | Q100: 0 | S100: 2.3406502e+10 | U100: 2.2389615e+10 | W100: Equity Pro forma
A101: Surplus revaluasi aset tetap | K101: 0 | M101: ='[192]WS Des Konsol Update'!Q494 -> 0 | O101: 0 | Q101: 0 | S101: 0 | U101: 0 | W101: Asset revalution surplus
A102: Penghasilan Komprehensif Lain | E102: 29 | G102: ='WS Konsol'!M536 -> -313784867 | I102: ='WS Konsol'!W536 -> -377072852 | K102: ='WS Konsol'!AT536 -> -368797440 | M102: ='WS Konsol'!AF536 -> -377072852 | O102: ='WS Konsol'!BC536 -> -368797440 | Q102: ='WS Konsol'!AI536 -> -377072852 | S102: ='WS Konsol'!BF536 -> -368797440 | U102: -611495277 | W102: Other Comprehensive Income
A103: Saldo Laba | W103: Retained Earnings
B104: Ditentukan Penggunaannya | E104: 21b | G104: =Q104 -> 410000000 | I104: =O104 -> 410000000 | K104: =Q104 -> 410000000 | M104: =Q104 -> 410000000 | O104: =400000000+10000000 -> 410000000 | Q104: =S104 -> 410000000 | S104: =400000000+10000000 -> 410000000 | U104: 0 | X104: Appropriated
B105: Tidak Ditentukan Penggunaannya | E105: 21b | G105: ='WS Konsol'!M525-G104 -> 4870466041 | I105: ='WS Konsol'!W525-'WS Konsol'!Q525+'WS Konsol'!Q525+'WS Konsol'!Q508-I104 -> 6207104927 | K105: ='WS Konsol'!AT525-'WS Konsol'!AN525+'WS Konsol'!AN525+'WS Konsol'!AN508-K104 -> 18589570707 | M105: ='WS Konsol'!AF525-'WS Konsol'!Z525+'WS Konsol'!Z525+'WS Konsol'!Z508-M104 -> 5393649296 | O105: ='WS Konsol'!BC525-'WS Konsol'!AW525+'WS Konsol'!AW525+'WS Konsol'!AW508-O104 -> 18621152951 | Q105: 19521729837 | S105: 18237502879 | U105: =ROUNDDOWN(13426333849.6015,0) -> 13426333849 | X105: Unappropriated
A107: JUMLAH EKUITAS | G107: =SUM(G91:G105) -> 179090153044 | I107: =SUM(I91:I105) -> 180363503945 | K107: =SUM(K91:K105) -> 108370190052 | M107: =SUM(M91:M105) -> 110165993229 | O107: =SUM(O91:O105) -> 108401772296 | Q107: =SUM(Q91:Q105) -> 109294073770 | S107: =SUM(S91:S105) -> 1.075569e+11 | U107: =SUM(U91:U105) -> 1.0107614e+11 | W107: TOTAL EQUITY
A110: JUMLAH LIABILITAS DAN EKUITAS | G110: =G82+G107 -> 437269373703 | I110: =I82+I107 -> 408113666679 | K110: =K82+K107 -> 331143637453 | M110: =M82+M107 -> 347660437458 | O110: =O82+O107 -> 356531626434 | Q110: =Q82+Q107 -> 345325322996 | S110: =S82+S107 -> 3.0765842e+11 | U110: =ROUNDUP(U82+U107,0) -> 262715700578 | W110: TOTAL LIABILITIES AND EQUITY
A112: *)Disajikan Kembali Catatan ..
C113: Control | G113: =G110-G42 -> 0 | I113: ='WS Konsol'!W539 -> 408113666679 | K113: ='WS Konsol'!AT539 -> 331143637453 | M113: ='WS Konsol'!AF539 -> 347660437458 | O113: ='WS Konsol'!BC539 -> 356531626434 | Q113: =Q110-Q42 -> 0 | S113: ='WS Konsol'!BF539 -> 307658424229 | U113: ='WS Konsol'!BH539 -> 262715700580
E117: Current Ratio | G117: =G23/G66 -> 1.456119 | I117: =I23/I66 -> 1.5166666 | M117: =M23/M66 -> 1.173738 | Q117: =Q23/Q66 -> 1.1257677 | S117: =S23/S66 -> 1.135455 | U117: =U23/U66 -> 1.1230512
E118: ROA | G118: ='PL Konsol'!E50/'BS Konsol-Des 24'!G42 -> 0 | I118: ='PL Konsol'!F50/I42 -> #REF! | M118: ='PL Konsol'!J50/M42 -> #REF! | Q118: ='PL Konsol'!O50/'BS Konsol-Des 24'!Q42 -> 0.0050305491 | S118: ='[192]PL Konsol'!L36/'[192]BS Konsol'!K55 -> 0.016938165 | U118: ='[192]PL Konsol'!N36/'[192]BS Konsol'!M55 -> 0.01269529
E119: ROE | G119: ='PL Konsol'!E50/G107 -> 0 | I119: ='PL Konsol'!F50/I107 -> #REF! | M119: ='PL Konsol'!J50/M107 -> #REF! | Q119: ='PL Konsol'!O50/Q107 -> 0.015894512 | S119: ='[192]PL Konsol'!L36/'[192]BS Konsol'!K122 -> 0.048450347 | U119: ='[192]PL Konsol'!N36/'[192]BS Konsol'!M122 -> 0.03299742
E120: EBITDA/Pendapatan | G120: ='RASIO KEUANGAN'!C12 -> 0.088497869 | Q120: ='RASIO KEUANGAN'!D12 -> 0.14611871 | S120: ='[192]Rasio DSCR'!D15/'[192]PL Konsol'!L11 -> 0.061853422 | U120: ='[192]Rasio DSCR'!F15/'[192]PL Konsol'!N11 -> 0

Sheet PL Konsol
A1: PT INDO AMERICAN SEAFOODS | Y1: Gross Margin
A2: LAPORAN LABA RUGI DAN PENGHASILAN KOMPREHENSIF LAIN KONSOLIDASIAN | AA2: 45536 | AC2: 45170 | AD2: 2024 | AF2: 45444 | AH2: 45078 | AJ2: 2023 | AL2: 2022 | AN2: 2021
A3: UNTUK TAHUN YANG BERAKHIR PADA TANGGAL-TANGGAL | AA3: =F14/F11 -> 0.33016358 | AC3: =H14/H11 -> 0.35141395 | AD3: =M14/M11 -> 0.23445382 | AF3: =J14/J11 -> 0.351238 | AH3: =L14/L11 -> 0.32999103 | AJ3: =O14/O11 -> 0.32631034 | AL3: =Q14/Q11 -> 0.22051538 | AN3: =S14/S11 -> 0.22495716
A4: 31 December 2024 dan 2023
A5: (Disajikan dalam Rupiah, kecuali dinyatakan lain)
D8: Catatan/
D9: Notes | F9: 45536 | H9: 45170 | J9: 45444 | L9: 45078 | M9: 2024 | O9: 2023 | Q9: 2022 | S9: 2021
A11: PENJUALAN | D11: 23 | F11: ='WS Konsol'!W554 -> 160540499628 | H11: ='WS Konsol'!AT554 -> 149774869471 | J11: ='WS Konsol'!AF554 -> 106697349798 | L11: ='WS Konsol'!BC554 -> 120318473492 | M11: ='WS Konsol'!M554 -> 3.2256021e+11 | O11: ='WS Konsol'!AI554 -> 199222794205 | Q11: ='WS Konsol'!BF554 -> 382316276945 | S11: ='WS Konsol'!BH554 -> 303872116071 | U11: SALES
A12: BEBAN POKOK PENJUALAN | D12: 24 | F12: =-'WS Konsol'!W640 -> -107535872927 | H12: =-'WS Konsol'!AT640 -> -97141890286 | J12: =-'WS Konsol'!AF640 -> -69221185606 | L12: =-'WS Konsol'!BC640 -> -80614456121 | M12: =-'WS Konsol'!M640 -> -2.4693474e+11 | O12: =-'WS Konsol'!AI640 -> -134214335812 | Q12: =-'WS Konsol'!BF640 -> -298009655959 | S12: =-'WS Konsol'!BH640 -> -235513908676 | U12: COST OF GOODS SOLD
A14: LABA KOTOR | F14: =ROUND(F11+F12,0) -> 53004626701 | H14: =ROUND(H11+H12,0) -> 52632979185 | J14: =ROUND(J11+J12,0) -> 37476164192 | L14: =ROUND(L11+L12,0) -> 39704017371 | M14: =ROUND(M11+M12,0) -> 75625474422 | O14: =ROUND(O11+O12,0) -> 65008458393 | Q14: =ROUND(Q11+Q12,0) -> 84306620986 | S14: =ROUND(S11+S12,0) -> 68358207395 | U14: GROSS PROFITS
A16: Beban Penjualan | D16: 25 | F16: =-'WS Konsol'!W662 -> -13450215380 | H16: =-'WS Konsol'!AT662 -> -18108262146 | J16: =-'WS Konsol'!AF662 -> -8866046154 | L16: =-'WS Konsol'!BC662 -> -13411387825 | M16: =-'WS Konsol'!M662 -> -16258997299 | O16: =-'WS Konsol'!AI662 -> -17958725423 | Q16: =-'WS Konsol'!BF662 -> -33826918356 | S16: =-'WS Konsol'!BH662 -> -26521142401 | U16: Selling Expenses
A17: Beban Umum dan Administrasi | D17: 26 | F17: =-'WS Konsol'!W719 -> -26167728635 | H17: =-'WS Konsol'!AT719 -> -20819164640 | J17: =-'WS Konsol'!AF719 -> -13412401091 | L17: =-'WS Konsol'!BC719 -> -15441855165 | M17: =-'WS Konsol'!M719 -> -36246687170 | O17: =-'WS Konsol'!AI719 -> -27733745691 | Q17: =-'WS Konsol'!BF719 -> -28248056723 | S17: =-'WS Konsol'!BH719 -> -26942834062 | U17: General and Administration Expenses
A18: Beban Lain-Lain - Bersih | D18: 27 | F18: ='WS Konsol'!X727 -> 2273092655 | H18: ='WS Konsol'!AU727 -> -906733107 | J18: ='WS Konsol'!AH727 -> -4496948237 | L18: ='WS Konsol'!BE727 -> -1927750383 | M18: ='WS Konsol'!O727 -> -2610994654 | O18: ='WS Konsol'!AL727 -> -1084534135 | Q18: ='WS Konsol'!BG727 -> -602810576 | S18: ='WS Konsol'!BI730 -> 112244184 | U18: Other Expenses - Net
A19: Beban Bunga dan Keuangan | D19: 28 | F19: =-'WS Konsol'!X737 -> -12487102791 | H19: =-'WS Konsol'!AU737-'WS Konsol'!AT741 -> -11466799581 | J19: =-'WS Konsol'!AH737-'WS Konsol'!AF741 -> -9308297571 | L19: =-'WS Konsol'!BE737-'WS Konsol'!BC741 -> -7603308083 | M19: =-'WS Konsol'!O737 -> -18184572249 | O19: =-'WS Konsol'!AL737-'WS Konsol'!AI741 -> -15677499788 | Q19: =-'WS Konsol'!BG737-'WS Konsol'!BF741 -> -13403963086 | S19: =-'WS Konsol'!BI737 -> -9352093192 | U19: Interest and Finance Cost
A21: Sub Jumlah | F21: =SUM(F16:F19) -> -49831954151 | H21: =SUM(H16:H19) -> -51300959474 | J21: =SUM(J16:J19) -> -36083693053 | L21: =SUM(L16:L19) -> -38384301456 | M21: =SUM(M16:M19) -> -73301251372 | O21: =SUM(O16:O19) -> -62454505037 | Q21: =SUM(Q16:Q19) -> -76081748741 | S21: =SUM(S16:S19) -> -62703825471 | U21: Sub Total
A23: LABA SEBELUM PAJAK PENGHASILAN | F23: =F14+F21 -> 3172672550 | H23: =H14+H21 -> 1332019711 | J23: =J14+J21 -> 1392471139 | L23: =L14+L21 -> 1319715915 | M23: =SUM(M14:M19) -> 2324223050 | O23: =SUM(O14:O19) -> 2553953356 | Q23: =Q14+Q21 -> 8224872245 | S23: =S14+S21 -> 5654381924 | U23: INCOME BEFORE INCOME TAX
A24: Beban Pajak Penghasilan: | U24: Income Tax Expenses:
B25: Pajak Kini | D25: 18c | F25: =-'WS Konsol'!W748 -> -1487297460 | H25: =-'WS Konsol'!AT748 -> -518727440 | J25: =-'WS Konsol'!AF748 -> -520551680 | L25: =-'WS Konsol'!BC748 -> -474841400 | M25: =-'WS Konsol'!M748 -> -2052132941 | O25: =-'WS Konsol'!AI748 -> -1088072700 | Q25: =-'WS Konsol'!BF748 -> -2076985900 | S25: =-'WS Konsol'!BH748 -> -1421390520 | V25: Current Tax
B26: Pajak Tangguhan | D26: 18e | F26: =-('WS Konsol'!AA753+'WS Konsol'!AA751) -> 0 | H26: =-('WS Konsol'!AX753+'WS Konsol'!AX751) -> 0 | J26: =-('WS Konsol'!AF753+'WS Konsol'!AF751) -> 0 | L26: =-('WS Konsol'!BC753+'WS Konsol'!BC751) -> 0 | M26: =-('WS Konsol'!M753+'WS Konsol'!M751+'WS Konsol'!M752) -> 76646095 | O26: =-('WS Konsol'!AI753+'WS Konsol'!AI751) -> 279570745 | Q26: =-('WS Konsol'!BF753+'WS Konsol'!BF751) -> 90168897 | S26: =('WS Konsol'!BH753+'WS Konsol'!BH751) -> 1446845971 | V26: Deferred Tax
A28: LABA TAHUN BERJALAN SEBELUM | U28: PROFIT FOR THE YEAR BEFORE IMPACT
A29: DAMPAK PENYESUAIAN PROFORMA | F29: =F23+F26+F25 -> 1685375090 | H29: =H23+H26+H25 -> 813292271 | J29: =J23+J26+J25 -> 871919459 | L29: =L23+L26+L25 -> 844874515 | M29: =M23+M26+M25 -> 348736204 | O29: =O23+O26+O25 -> 1745451401 | Q29: =Q23+Q26+Q25 -> 6238055242 | S29: =S23+S26+S25 -> 5679837375 | U29: OF PROFORMA ADJUSTMENT
F30: =F29/F11 -> 0.01049813 | H30: =H29/H11 -> 0.0054300983 | J30: =J29/J11 -> 0.0081718942 | L30: =L29/L11 -> 0.007021985 | M30: =M29/M11 -> 0.0010811507 | O30: =O29/O11 -> 0.0087613037 | Q30: =Q29/Q11 -> 0.016316478 | S30: =S29/S11 -> 0.018691539
A33: DAMPAK PENYESUAIAN PROFORMA | F33: 0 | H33: 0 | J33: 0 | L33: 0 | M33: 0 | O33: 0 | Q33: -1.0268862e+09 | S33: =-'[192]WS Des Konsol Update'!Y486 -> -2.3445854e+09 | U33: IMPACT OF PRO FORMA ADJUSTMENT
A35: LABA TAHUN BERJALAN | F35: =F29+F33 -> 1685375090 | H35: =H29+H33 -> 813292271 | J35: =J29+J33 -> 871919459 | L35: =L29+L33 -> 844874515 | M35: =SUM(M23:M26) -> 348736204 | O35: =SUM(O23:O26) -> 1745451401 | Q35: =Q29+Q33 -> 5.211169e+09 | S35: =S29+S33 -> 3.335252e+09 | U35: NET PROFIT FOR THE YEAR
A37: PENGHASILAN KOMPREHENSIF LAIN | U37: OTHER COMPREHENSIVE INCOME
A39: Pos yang Tidak Akan Direklasifikasi | U39: Items that Will Not Be Reclassified
A40: ke Laba Rugi: | U40: to Profit or Loss:
B41: Pengukuran Kembali Imbalan Pasti | D41: 18e | F41: =('WS Konsol'!AA759) -> 0 | H41: =('WS Konsol'!AX759) -> 0 | J41: =('WS Konsol'!AF759) -> 0 | L41: =('WS Konsol'!BC759) -> 0 | M41: =('WS Konsol'!M759)+1 -> 81138444 | O41: =('WS Konsol'!AI759) -> -10609502 | Q41: =('WS Konsol'!BF759) -> 311151073 | S41: =('WS Konsol'!BH759) -> 21039938 | V41: Remeasurement of Defined Benefit
B42: Pajak Penghasilan Terkait | D42: 18 | F42: =-('WS Konsol'!AA761) -> 0 | H42: =-('WS Konsol'!AX761) -> 0 | J42: =-('WS Konsol'!AF761) -> 0 | L42: =-('WS Konsol'!BC761) -> 0 | M42: =('WS Konsol'!M761) -> -17850458 | O42: =-('WS Konsol'!AI761) -> 2334090 | Q42: =-('WS Konsol'!BF761) -> -68453236 | S42: =-('WS Konsol'!BH761) -> -4628786 | V42: Related Income Tax
A47: DAMPAK PENYESUAIAN PROFORMA | F47: 0 | H47: 0 | J47: 0 | L47: 0 | M47: 0 | O47: 0 | Q47: =('[192]WS Des Konsol Update'!O716+'[192]WS Des Konsol Update'!O719) -> 1.8842722e+08 | S47: ='[192]WS Des Konsol Update'!Y716+'[192]WS Des Konsol Update'!Y719 -> -7593457.1 | U47: IMPACT OF PRO FORMA ADJUSTMENT
A49: LABA KOMPREHENSIF TAHUN | U49: COMPREHENSIVE INCOME FOR
A50: BERJALAN | F50: =F35+#REF! -> #REF! | H50: =H35+#REF! -> #REF! | J50: =J35+#REF! -> #REF! | L50: =L35+#REF! -> #REF! | M50: =SUM(M35:M42) -> 412024190 | O50: =SUM(O35:O42) -> 1737175989 | Q50: =Q35+#REF! -> #REF! | S50: =S35+#REF! -> #REF! | U50: THE YEAR
A52: LABA PER SAHAM | D52: 30 | H52: =LPS!B30 -> 0 | J52: =LPS!K30 -> 0.79265405 | L52: =LPS!M30 -> 1.0560931 | M52: =LPS!E30 -> 0.25088936 | O52: =LPS!O30 -> 2.1818143 | Q52: =LPS!Q30 -> 6.5139613 | S52: =LPS!S30 -> 4.169065 | U52: EARNINGS PER SHARE
M55: =M41*22% -> 17850458 | O55: =O41*22% -> -2334090.4 | Q55: =Q41*22% -> 68453236 | S55: =S41*22% -> 4628786.4
D57: Ctrl | F57: =F50-'WS Konsol'!W764 -> #REF! | H57: =H50-'WS Konsol'!AT764 -> #REF! | J57: =J50-'WS Konsol'!AF764 -> #REF! | L57: =L50-'WS Konsol'!BC764 -> #REF! | M57: ='WS Konsol'!M756-M35 -> 0 | O57: =O23-'WS Konsol'!AI746 -> 0 | Q57: =Q23-'WS Konsol'!BF746 -> 0 | S57: =S23-'WS Konsol'!BH746 -> 0

Sheet LPE Konsol Des 24
A1: LAPORAN PERUBAHAN EKUITAS KONSOLIDASIAN
A2: UNTUK TAHUN YANG BERAKHIR PADA TANGGAL-TANGGAL | Q2: ='[193]BS Konsol'!O119 -> 0
A3: 30 Juni 2024, 31 Desember 2023, 2022 dan 2021
A4: (Disajikan dalam Rupiah, kecuali dinyatakan lain)
O5: Saldo Laba/
O6: Retained Earning
S7: Proforma Ekuitas
S8: dari Kombinasi Bisnis
S9: Entitas Sepengendali/
K10: Tambahan | M10: Penghasilan | S10: Equity Proforma from
K11: Modal Disetor/ | M11: Komprehensif Lain/ | O11: Ditentukan | Q11: Tidak Ditentukan | S11: Business Combination
E12: Catatan/ | G12: Catatan/ | I12: Modal Saham/ | K12: Additional | M12: Other Comprehensive | O12: Penggunaannya/ | Q12: Penggunaannya/ | S12: of Entities Under | U12: Jumlah Ekuitas/
E13: Notes | G13: Notes | I13: Share Capital | K13: Paid-in-Capital | M13: Income | O13: Appropriated | Q13: Unappropriated | S13: Common Control | U13: Total Equity
A16: Saldo 1 Januari 2021 | I16: 40000000000 | K16: 25871690669 | M16: -627906429 | O16: 0 | Q16: =ROUNDDOWN(10091081877.7902,0) -> 10091081877 | S16: =ROUND(20045030056.9821,0) -> 20045030057 | U16: =SUM(I16:S16) -> 95379896174 | W16: Balance as of January 1, 2021
A17: Pengukuran Kembali Program | W17: Remeasurement of
A18: Imbalan Pasti | E18: 29 | I18: 0 | K18: 0 | M18: ='PL Konsol'!S42+'PL Konsol'!S41 -> 16411152 | O18: 0 | Q18: 0 | U18: =SUM(I18:T18) -> 16411152 | W18: Defined Benefit
A19: Laba Tahun Berjalan | I19: 0 | K19: 0 | M19: 0 | Q19: =ROUNDUP('PL Konsol'!S35,0) -> 3335251972 | S19: =ROUND((-'PL Konsol'!S33),0) -> 2344585403 | U19: =SUM(I19:T19) -> 5679837375 | W19: Profit for The Year
A21: Saldo 31 Desember 2021 | I21: =SUM(I16:I19) -> 40000000000 | K21: =SUM(K16:K19) -> 25871690669 | M21: =SUM(M16:M19) -> -611495277 | O21: =SUM(O16:O19) -> 0 | Q21: =ROUNDUP(SUM(Q16:Q19),0) -> 13426333849 | S21: =SUM(S16:S19) -> 22389615460 | U21: =SUM(U16:U19) -> 101076144701 | W21: Balance as of December 31, 2021
A23: Pengukuran Kembali Program | W23: Remeasurement of
A24: Imbalan Pasti | E24: 29 | I24: 0 | K24: 0 | M24: ='PL Konsol'!Q41+'PL Konsol'!Q42 -> 242697837 | O24: 0 | Q24: 0 | S24: 0 | U24: =SUM(I24:S24) -> 242697837 | W24: Defined Benefit
A25: Laba Tahun Berjalan | I25: 0 | K25: 0 | M25: 0 | O25: 0 | Q25: =ROUNDUP('PL Konsol'!Q35,0) -> 5211169030 | S25: =ROUNDUP((-'PL Konsol'!Q33),0) -> 1026886213 | U25: =SUM(I25:S25) -> 6238055243 | W25: Profit for The Year
A26: Cadangan Umum | E26: 21b | O26: ='BS Konsol'!N104 -> 410000000 | Q26: =-('BS Konsol'!N104-10000000) -> -400000000 | S26: =-10000000 -> -10000000 | U26: 0
A27: Saldo 1 Januari 2023 | I27: =SUM(I21:I26) -> 40000000000 | K27: =SUM(K21:K26) -> 25871690669 | M27: =SUM(M21:M26) -> -368797440 | O27: =SUM(O21:O26) -> 410000000 | Q27: =ROUNDUP(SUM(Q21:Q26),0) -> 18237502879 | S27: =ROUND(SUM(S21:S26),0) -> 23406501673 | U27: =SUM(U21:U26) -> 107556897781 | W27: Balance as at January 1, 2023
A30: Pengukuran Kembali Program | W30: Remeasurement of
A31: Imbalan Pasti | E31: 29 | M31: ='PL Konsol'!L41+'PL Konsol'!L42 -> 0 | O31: 0 | U31: =SUM(I31:S31) -> 0 | W31: Defined Benefit
A32: Laba Tahun Berjalan | I32: 0 | K32: 0 | M32: 0 | O32: 0 | Q32: =ROUND('PL Konsol'!L35,0) -> 844874515 | S32: 0 | U32: =SUM(I32:S32) -> 844874515 | W32: Profit for The Year
A33: Pembalikan atas Proforma Ekuitas | W33: Reversed to the Proforma
A34: yang Timbul dari Kombinasi | W34: Equity from Business Combination of
A35: Bisnis Entitas Sepengendali | E35: 1c | I35: 0 | K35: 23867726116 | M35: 0 | O35: 0 | Q35: =-806735547+345511104 -> -461224443 | S35: =ROUND((-22356501672.8449-1050000000),0) -> -23406501673 | U35: 0 | W35: Entities Under Common Control
A37: Saldo 30 Juni 2023 | I37: =SUM(I27:I35) -> 40000000000 | K37: =SUM(K27:K35) -> 49739416785 | M37: =SUM(M27:M35) -> -368797440 | O37: =SUM(O27:O35) -> 410000000 | Q37: =SUM(Q27:Q35) -> 18621152951 | S37: =SUM(S27:S35) -> 0 | U37: =SUM(U27:U35) -> 108401772296 | W37: Balance as of June 30, 2023
A39: Pengukuran Kembali Program | W39: Remeasurement of
A40: Imbalan Pasti | E40: 29 | G40: 20 | M40: ='PL Konsol'!O42+'PL Konsol'!O41 -> -8275412 | O40: 0 | U40: =SUM(I40:S40) -> -8275412 | W40: Defined Benefit
A41: Laba Tahun Berjalan | G41: 20b | I41: 0 | K41: 0 | M41: 0 | O41: 0 | Q41: =ROUNDDOWN('PL Konsol'!O35,0) -> 1745451401 | S41: 0 | U41: =SUM(I41:S41) -> 1745451401 | W41: Profit for The Year
A42: Pembalikan atas Proforma Ekuitas | W42: Reversed to the Proforma
A43: yang Timbul dari Kombinasi | W43: Equity from Business Combination of
A44: Bisnis Entitas Sepengendali | E44: 1c | I44: 0 | K44: =ROUND(23867726116,0) -> 23867726116 | M44: 0 | O44: 0 | Q44: =ROUND((-806735547+345511104),0) -> -461224443 | S44: =ROUND((-22356501672.8449-1050000000),0) -> -23406501673 | U44: 0 | W44: Entities Under Common Control
A46: Laba Periode Berjalan | I46: 0 | K46: 0 | M46: 0 | O46: 0 | Q46: ='PL Konsol'!H50 -> #REF! | S46: 0 | U46: =SUM(I46:S46) -> #REF! | W46: Profit for The Period
A47: Pembalikan atas Proforma Ekuitas | W47: Reversed to the Proforma
A48: yang Timbul dari Kombinasi | W48: Equity from Business Combination of
A49: Bisnis Entitas Sepengendali | E49: 1c | I49: 0 | K49: 23867726116 | M49: 0 | O49: 0 | Q49: =-806735547+345511104 -> -461224443 | S49: =ROUND((-22356501672.8449-1050000000),0) -> -23406501673 | U49: 0 | W49: Entities Under Common Control
A51: Saldo 30 September 2023 | I51: =I27+SUM(I46:I49) -> 40000000000 | K51: =K27+SUM(K46:K49) -> 49739416785 | M51: =M27+SUM(M46:M49) -> -368797440 | O51: =O27+SUM(O46:O49) -> 410000000 | Q51: =Q27+SUM(Q46:Q49) -> #REF! | S51: =S27+SUM(S46:S49) -> 0 | U51: =U27+SUM(U46:U49) -> #REF! | W51: Balance as of September 30, 2023
A53: Saldo 31 Desember 2023 | I53: =SUM(I39:I44)+I27 -> 40000000000 | K53: =SUM(K39:K44)+K27 -> 49739416785 | M53: =SUM(M39:M44)+M27 -> -377072852 | O53: =SUM(O39:O44)+O27 -> 410000000 | Q53: =ROUNDUP(SUM(Q39:Q44)+Q27,0) -> 19521729837 | S53: =SUM(S39:S44)+S27 -> 0 | U53: =SUM(U39:U44)+U27 -> 109294073770 | W53: Balance as at December 31, 2023
A55: Setoran Modal | I55: 15000000000 | Q55: -15000000000 | U55: =SUM(I55:S55) -> 0 | W55: Paid up Capital
A56: Pengukuran Kembali Program | W56: Remeasurement of
A57: Imbalan Pasti | E57: 29 | M57: ='PL Konsol'!J41+'PL Konsol'!J42 -> 0 | O57: 0 | U57: =SUM(I57:S57) -> 0 | W57: Defined Benefit
A58: Laba Tahun Berjalan | I58: 0 | K58: 0 | M58: 0 | O58: 0 | Q58: ='PL Konsol'!J35 -> 871919459 | S58: 0 | U58: =SUM(I58:S58) -> 871919459 | W58: Profit for The Year
A59: Pembalikan atas Proforma Ekuitas | W59: Reversed to the Proforma
A60: yang Timbul dari Kombinasi | W60: Equity from Business Combination of
A61: Bisnis Entitas Sepengendali | E61: 1c | I61: 0 | K61: 0 | M61: 0 | O61: 0 | Q61: 0 | S61: 0 | U61: =SUM(I61:S61) -> 0 | W61: Entities Under Common Control
A63: Saldo 30 Juni 2024 | I63: =SUM(I55:I61)+#REF! -> #REF! | K63: =SUM(K57:K61)+#REF! -> #REF! | M63: =SUM(M57:M61)+#REF! -> #REF! | O63: =SUM(O57:O61)+#REF! -> #REF! | Q63: =SUM(Q55:Q61)+#REF! -> #REF! | S63: =SUM(S57:S61)+#REF! -> #REF! | U63: =SUM(U57:U61)+#REF! -> #REF! | W63: Balance as of June 30, 2024
A65: Tambahan Modal di Setor | K65: =SUM('WS Konsol'!W510:W511) -> 54884055085 | M65: 0 | O65: 0 | Q65: 0 | S65: 0 | U65: =SUM(I65:S65) -> 54884055085 | W65: Additional Paid-in Capital
A66: Setoran Modal | I66: =15000000000 -> 15000000000 | K66: 0 | M66: 0 | O66: 0 | Q66: -15000000000 | S66: 0 | U66: =SUM(I66:S66) -> 0 | W66: Paid up Capital
A67: Pengukuran Kembali Program | W67: Remeasurement of
A68: Imbalan Pasti | E68: 29 | M68: 0 | O68: 0 | U68: =SUM(I68:S68) -> 0 | W68: Defined Benefit
A69: Masyarakat (dibawah 5%) | I69: ='WS Konsol'!W509 -> 14500000000 | K69: 0 | M69: 0 | O69: 0 | Q69: 0 | S69: 0 | U69: =SUM(I69:S69) -> 14500000000 | W69: Public (each below 5%)
A70: Laba Periode Berjalan | I70: 0 | K70: 0 | M70: 0 | O70: 0 | Q70: ='PL Konsol'!F50 -> #REF! | S70: 0 | U70: =SUM(I70:S70) -> #REF! | W70: Profit for The Period
A71: Pembalikan atas Proforma Ekuitas | W71: Reversed to the Proforma
A72: yang Timbul dari Kombinasi | W72: Equity from Business Combination of
A73: Bisnis Entitas Sepengendali | E73: 1c | I73: 0 | K73: 0 | M73: 0 | O73: 0 | Q73: 0 | S73: 0 | U73: =SUM(I73:S73) -> 0 | W73: Entities Under Common Control
A75: Saldo 30 September 2024 | I75: =SUM(I65:I73)+#REF! -> #REF! | K75: =SUM(K65:K73)+#REF! -> #REF! | M75: =SUM(M65:M73)+#REF! -> #REF! | O75: =SUM(O65:O73)+#REF! -> #REF! | Q75: =SUM(Q65:Q73)+#REF! -> #REF! | S75: =SUM(S65:S73)+#REF! -> #REF! | U75: =SUM(U65:U73)+#REF! -> #REF! | W75: Balance as of September 30, 2024
A76: Setoran Modal Melalui Penawaran Umum | W76: Paid-Up Capital through Initial
A77: Perdana Saham | G77: 20a | I77: ='WS Konsol'!M509 -> 14500000000 | K77: 0 | M77: 0 | O77: 0 | Q77: 0 | S77: 0 | U77: =SUM(I77:S77) -> 14500000000 | W77: Public Offering
A78: Penerimaan Agio Saham | W78: Proceeds Additional Paid-in
A79: Sehubungan dengan Penawaran | W79: Capital related to Initial
A80: Umum Perdana Saham | G80: 22 | I80: 0 | K80: ='WS Konsol'!M510 -> 58000000000 | M80: 0 | O80: 0 | Q80: 0 | S80: 0 | U80: =SUM(I80:S80) -> 58000000000 | W80: Public Offering
A81: Biaya Emisi Saham | G81: 22 | I81: 0 | K81: ='WS Konsol'!M511 -> -3115944915 | M81: 0 | O81: 0 | Q81: 0 | S81: 0 | U81: =SUM(I81:S81) -> -3115944915 | W81: Share Issuance Cost
A82: Setoran Modal melalui Dividen Saham | G82: 21a | I82: =15000000000 -> 15000000000 | K82: 0 | M82: 0 | O82: 0 | Q82: -15000000000 | S82: 0 | U82: =SUM(I82:S82) -> 0 | W82: Paid-up Capital through Share Dividends
A83: Pengukuran Kembali Imbalan Pasti | E83: 29 | G83: 20 | I83: - | K83: - | M83: ='PL Konsol'!M41+'PL Konsol'!M42 -> 63287986 | O83: 0 | Q83: - | S83: - | U83: =SUM(I83:S83) -> 63287986 | W83: Remeasurement of Defined Benefit
A84: Laba Tahun Berjalan | G84: 20b | I84: 0 | K84: 0 | M84: 0 | O84: 0 | Q84: ='PL Konsol'!M35 -> 348736204 | S84: 0 | U84: =SUM(I84:S84) -> 348736204 | W84: Profit for The Year
A85: Pembalikan atas Proforma Ekuitas | W85: Reversed to the Proforma
A86: yang Timbul dari Kombinasi | W86: Equity from Business Combination of
A87: Bisnis Entitas Sepengendali | E87: 1c | I87: 0 | K87: 0 | M87: 0 | O87: 0 | Q87: 0 | S87: 0 | U87: =SUM(I87:S87) -> 0 | W87: Entities Under Common Control
A89: Saldo 31 Desember 2024 | I89: =SUM(I77:I87)+I53 -> 69500000000 | K89: =SUM(K77:K87)+K53 -> 104623471870 | M89: =SUM(M77:M87)+M53 -> -313784866 | O89: =SUM(O77:O87)+O53 -> 410000000 | Q89: =SUM(Q77:Q87)+Q53 -> 4870466041 | S89: =SUM(S77:S87)+S53 -> 0 | U89: =SUM(U77:U87)+U53 -> 179090153045 | W89: Balance as at December 31, 2024
D96: 45657 | I96: =I89-'BS Konsol-Des 24'!G98 -> 0 | K96: =K89-'BS Konsol-Des 24'!G99 -> 0 | M96: ='BS Konsol-Des 24'!G102 -> -313784867 | O96: =O89-'BS Konsol-Des 24'!G104 -> 0 | Q96: =Q89-'BS Konsol-Des 24'!G105 -> 0 | S96: 0 | U96: =U89-'BS Konsol-Des 24'!G107 -> 1 | W96: 45657
D97: 45536 | I97: =(I75-'BS Konsol-Des 24'!I98) -> #REF! | K97: =K75-SUM('BS Konsol-Des 24'!I99) -> #REF! | M97: =M75-'BS Konsol-Des 24'!I102 -> #REF! | O97: =O75-'BS Konsol-Des 24'!I104 -> #REF! | Q97: =Q75-'BS Konsol-Des 24'!I105 -> #REF! | S97: 0 | U97: =U75-'BS Konsol-Des 24'!I107 -> #REF! | W97: 45536
D98: 45170 | I98: =I51-'BS Konsol-Des 24'!K98 -> 0 | K98: =K51-'BS Konsol-Des 24'!K99 -> 0 | M98: =M51-'BS Konsol-Des 24'!K102 -> 0 | O98: =O51-'BS Konsol-Des 24'!K104 -> 0 | Q98: =Q51-'BS Konsol-Des 24'!K105 -> #REF! | S98: 0 | U98: =U51-'BS Konsol-Des 24'!K107 -> #REF! | W98: 45170
D99: 45444 | I99: =I63-'BS Konsol'!H97 -> #REF! | K99: =K63-'BS Konsol'!H99 -> #REF! | M99: =M63-'BS Konsol'!H102 -> #REF! | O99: =O63-'BS Konsol'!H104 -> #REF! | Q99: =Q63-'BS Konsol'!H105 -> #REF! | S99: =S63-'BS Konsol'!H100 -> #REF! | U99: =U63-'BS Konsol'!H107 -> #REF! | W99: 45444
M100: =M89-M96 -> 1
D101: 45291 | I101: =I36-'BS Konsol'!L96 -> 0 | K101: =K36-'BS Konsol'!L98 -> 0 | M101: =M63-'BS Konsol'!L102 -> #REF! | O101: =O36-'BS Konsol'!L103 -> 0 | Q101: =#REF!-'BS Konsol'!L105 -> #REF! | S101: =S36-'BS Konsol'!L100 -> 0 | U101: =U36-'BS Konsol'!L106 -> 0 | W101: 45291
D102: 45078 | I102: =I37-'BS Konsol'!J97 -> 0 | K102: =K37-'BS Konsol'!J99 -> 0 | M102: =M37-'BS Konsol'!J102 -> 0 | O102: =O37-'BS Konsol'!J104 -> 0 | Q102: =Q37-'BS Konsol'!J105 -> 0 | S102: =S37-'BS Konsol'!J100 -> 0 | U102: =U37-'BS Konsol'!J107 -> 0 | W102: 45078
D103: 2022 | I103: =I27-'BS Konsol'!N97 -> 0 | K103: =K27-'BS Konsol'!N99 -> 0 | M103: =M27-'BS Konsol'!N102 -> 0 | O103: ='LPE Konsol'!M27-'BS Konsol'!N104 -> 0 | Q103: =Q27-'BS Konsol'!N105 -> 0 | S103: =S27-'BS Konsol'!N100 -> 0.13722992 | U103: =U27-'BS Konsol'!N107 -> 0.13723755 | W103: CTRL
D104: 2021 | I104: =I21-'BS Konsol'!P97 -> 0 | K104: =K21-'BS Konsol'!P99 -> 0 | M104: =M21-'BS Konsol'!P102 -> 0 | O104: =O21-'BS Konsol'!P104 -> 0 | Q104: =Q21-'BS Konsol'!P105 -> 0 | S104: =S21-'BS Konsol'!P100 -> -0.39854431 | U104: =U21-'BS Konsol'!P107 -> -0.39854431

Sheet Sheet2
F4: Harga Nominal Persaham | G4: 50 | H4: =G4*G8 -> 14500000000
F5: Agio Saham | G5: =G6-G4 -> 200 | H5: =G5*G8 -> 58000000000
F6: Harga Penawaran | G6: 250
F8: Jumlah Saham (Masyarakat) | G8: 290000000

Sheet BS Konsol
A1: PT INDO AMERICAN SEAFOODS
A2: LAPORAN POSISI KEUANGAN KONSOLIDASIAN
A3: Tanggal 30 Juni 2024, serta 31 Desember 2023, 2022, 2021, dan 2020 | T3: 21754505456
A4: (Disajikan dalam Rupiah, kecuali dinyatakan lain) | T4: -1562430934
F6: Catatan/ | L6: 31 Desember/ December 31
F7: Notes | H7: 45444 | J7: 45078 | L7: 2023 | N7: 2022 | P7: 2021
A9: ASET | R9: ASSETS
A10: ASET LANCAR | R10: CURRENT ASSETS
A11: Kas dan Setara Kas | F11: 5 | H11: ='WS Konsol'!AF52 -> 565886797 | J11: ='WS Konsol'!BC52 -> 5733063270 | L11: ='WS Konsol'!AI52 -> 2570121355 | N11: ='WS Konsol'!BF52 -> 4920468963 | P11: ='WS Konsol'!BH52 -> 4972845584 | R11: Cash and Cash Equivalents
A12: Piutang Usaha | R12: Trade Accounts Receivable
B13: Pihak Berelasi | F13: 6 | H13: ='WS Konsol'!AF111 -> 422639675 | J13: ='WS Konsol'!BC111 -> 1783377782 | L13: ='WS Konsol'!AI111 -> 211054410 | N13: ='WS Konsol'!BF111 -> 1729176327 | P13: ='WS Konsol'!BH111 -> 1565918952 | S13: Related Parties
B14: Pihak Ketiga | F14: 6 | H14: ='WS Konsol'!AF105+'WS Konsol'!AF115+'WS Konsol'!AF127 -> 26199584563 | J14: ='WS Konsol'!BC105+'WS Konsol'!BC115+'WS Konsol'!BC127 -> 25423470999 | L14: ='WS Konsol'!AI105+'WS Konsol'!AI115+'WS Konsol'!AI127 -> 19981020112 | N14: ='WS Konsol'!BF105+'WS Konsol'!BF115+'WS Konsol'!BF127 -> 53102808880 | P14: ='WS Konsol'!BH105+'WS Konsol'!BH115+'WS Konsol'!BH127 -> 38673285818 | S14: Third Parties
A15: Piutang Lain-lain | R15: Other Receivables
B16: Pihak Ketiga | F16: 7 | H16: ='WS Konsol'!AF132+'WS Konsol'!AF137 -> 510634104 | J16: ='WS Konsol'!BC132+'WS Konsol'!BC137 -> 549732399 | L16: ='WS Konsol'!AI132+'WS Konsol'!AI137 -> 510634104 | N16: ='WS Konsol'!BF132+'WS Konsol'!BF137 -> 549732399 | P16: ='WS Konsol'!BH132+'WS Konsol'!BH120 -> 466154019 | S16: Third Parties
A17: Persediaan | F17: 8 | H17: ='WS Konsol'!AF147 -> 224990831176 | J17: ='WS Konsol'!BC147 -> 215178073837 | L17: ='WS Konsol'!AI147 -> 218071396362 | N17: ='WS Konsol'!BF147 -> 137179893500 | P17: ='WS Konsol'!BH147 -> 95865646086 | R17: Inventories
A18: Aset Biologis | F18: 9 | H18: ='WS Konsol'!AF182 -> 2649404556 | J18: ='WS Konsol'!BC182 -> 1792056297 | L18: ='WS Konsol'!AI182 -> 2415719386 | N18: ='WS Konsol'!BF182 -> 651253829 | P18: ='WS Konsol'!BH182 -> 871760289 | R18: Biological Assets
A19: Pajak Dibayar Dimuka | F19: 18a | H19: =SUM('WS Konsol'!AF149:AF156) -> 10425187749 | J19: =SUM('WS Konsol'!BC149:BC156) -> 9041536321 | L19: =SUM('WS Konsol'!AI149:AI156) -> 9663458887 | N19: =SUM('WS Konsol'!BF149:BF156) -> 8035438770 | P19: =SUM('WS Konsol'!BH149:BH156) -> 8635897222 | R19: Prepaid Tax
A20: Uang Muka dan Biaya Dibayar Dimuka | F20: 10 | H20: ='WS Konsol'!AF159+'WS Konsol'!AF174+'WS Konsol'!AF164 -> 2074112410 | J20: ='WS Konsol'!BC159+'WS Konsol'!BC174 -> 903603741 | L20: ='WS Konsol'!AI159+'WS Konsol'!AI174 -> 1104447053 | N20: ='WS Konsol'!BF164+'WS Konsol'!BF159 -> 349309986 | P20: =SUM('WS Konsol'!BH164:BH173)+'WS Konsol'!BH159+'WS Konsol'!BH247 -> 227462120 | R20: Prepaid Expenses and Advances
A22: Jumlah Aset Lancar | H22: =SUM(H11:H20) -> 267838281030 | J22: =SUM(J11:J20) -> 260404914646 | L22: =SUM(L11:L20) -> 254527851669 | N22: =SUM(N11:N20) -> 206518082654 | P22: =SUM(P11:P20) -> 151278970090 | R22: Total Current Assets
A24: ASET TIDAK LANCAR | R24: NON-CURRENT ASSETS
A26: Piutang Lain-lain dari Pihak Berelasi | F26: 7 | H26: ='WS Konsol'!AF133+'WS Konsol'!AF187 -> 0 | J26: ='WS Konsol'!BC133+'WS Konsol'!BC187+'WS Konsol'!BC130 -> 7348897634 | L26: ='WS Konsol'!AI133+'WS Konsol'!AI187 -> 7022707423 | N26: ='WS Konsol'!BF133+'WS Konsol'!BF187+'WS Konsol'!BF130 -> 7197443207 | P26: ='WS Konsol'!BH133+'WS Konsol'!BH187+'WS Konsol'!BH130 -> 6836690211 | R26: Other Receivable to Related Parties
A27: Aset Tetap | R27: Fixed Assets
B28: (Setelah dikurangi akumulasi | S28: (Net of accumulated
B29: penyusutan pada tanggal | S29: depreciation as of December 31,
B30: 31 Desember 2023, 2022 | S30: 2023, 2022 and 2021
B31: dan 2021 masing-masing | S31: amounted to 'Rp 73,711,192,647,
B32: Rp 73.711.192.647, | S32: Rp 63,426,897,434
B33: Rp 63.426.897.434 dan | S33: and Rp 52,725,081,835
B34: Rp 52.725.081.835) | F34: 11 | H34: ='WS Konsol'!AF201-'WS Konsol'!AF214+'WS Konsol'!AF218 -> 70317926651 | J34: ='WS Konsol'!BC201-'WS Konsol'!BC214+'WS Konsol'!BC218 -> 79240630124 | L34: ='WS Konsol'!AI201-'WS Konsol'!AI214+'WS Konsol'!AI218 -> 74113104582 | N34: ='WS Konsol'!BF201-'WS Konsol'!BF214+'WS Konsol'!BF218 -> 84248284795 | P34: ='WS Konsol'!BH201-'WS Konsol'!BH214+'WS Konsol'!BH218 -> 94612283276 | S34: respectivley)
A36: Aset Hak Guna | R36: Right-of-Use Assets
B37: (Setelah dikurangi akumulasi | S37: (Net of accumulated
B38: penyusutan pada tanggal | S38: depreciation as of December
B39: 31 Desember 2023, 2022 | S39: 2023, 2022 dan 2021
B40: dan 2021 masing-masing | S40: amounted to Rp 1,178,447,040 ,
B41: Sebesar 'Rp 1.178.447.040, | S41: Rp 1,259,436,349
B42: Rp 1.259.436.349 dan | S42: and Rp 944,577,262
B43: Rp 944.577.262) | F43: 12 | H43: ='WS Konsol'!AF236 -> 7714047638 | J43: ='WS Konsol'!BC236 -> 8028906725 | L43: ='WS Konsol'!AI236 -> 7871477182 | N43: ='WS Konsol'!BF236 -> 8186336269 | P43: ='WS Konsol'!BH236 -> 8501195356 | S43: respectively)
A44: Aset Dalam Proses | F44: 12 | R44: Work in Process
A45: Aset Pajak Tangguhan | F45: 18e | H45: ='WS Konsol'!AF245 -> 1790182139 | J45: ='WS Konsol'!BC245 -> 1508277305 | L45: ='WS Konsol'!AI245 -> 1790182139 | N45: ='WS Konsol'!BF245 -> 1508277305 | P45: ='WS Konsol'!BH245 -> 1486561645 | R45: Deferred Tax Assets
A46: Jumlah Aset Tidak Lancar | H46: =SUM(H26:H45) -> 79822156428 | J46: =SUM(J26:J45) -> 96126711788 | L46: =SUM(L26:L45) -> 90797471326 | N46: =SUM(N26:N45) -> 101140341576 | P46: =SUM(P26:P45) -> 111436730488 | R46: Total Non-Current Assets
A48: JUMLAH ASET | H48: =H22+H46 -> 347660437458 | J48: =J22+J46 -> 356531626434 | L48: =L22+L46 -> 345325322995 | N48: =N22+N46 -> 307658424230 | P48: =ROUNDUP(P22+P46,0) -> 262715700578 | R48: TOTAL ASSETS
F52: Catatan/ | L52: 31 Desember/ December 31
F53: Notes | H53: =H7 -> 45444 | J53: =J7 -> 45078 | L53: 2023 | N53: 2022 | P53: 2021
A54: LIABILITAS DAN EKUITAS | R54: LIABILITIES AND EQUITY
A55: LIABILITAS | R55: LIABILITIES
A56: LIABILITAS JANGKA PENDEK | R56: CURRENT LIABILITIES
A57: Utang Usaha | R57: Trade Accounts Payable
A58: Utang Usaha - Pihak Ketiga | F58: 13 | H58: ='WS Konsol'!AF417+'WS Konsol'!AF422+'WS Konsol'!AF425 -> 14186291754 | J58: ='WS Konsol'!BC417+'WS Konsol'!BC422+'WS Konsol'!BC425 -> 47195337849 | L58: ='WS Konsol'!AI417+'WS Konsol'!AI422+'WS Konsol'!AI425 -> 20407901137 | N58: ='WS Konsol'!BF417+'WS Konsol'!BF422+'WS Konsol'!BF425 -> 12347357380 | P58: ='WS Konsol'!BH417+'WS Konsol'!BH422+'WS Konsol'!BH425 -> 14116621585 | R58: Related Parties
A59: Utang Lain-lain | R59: Other Payables
B60: Pihak Ketiga | F60: 14 | S60: Third Parties
A61: Utang Bank | F61: 19 | H61: ='WS Konsol'!AF288-H69 -> 207371015601 | J61: ='WS Konsol'!BC288 -> 166123612313 | L61: ='WS Konsol'!AI288-L69 -> 195441714689 | N61: ='WS Konsol'!BF288 -> 155339616431 | P61: ='WS Konsol'!BH288 -> 110815447741 | R61: Bank Loans | T61: =L61-H61 -> -11929300912
A62: Beban Akrual | F62: 15 | H62: ='WS Konsol'!AF467-H66 -> 4322494743 | J62: ='WS Konsol'!BC467-J66 -> 8217143369 | L62: ='WS Konsol'!AI467-L66 -> 2870843988 | N62: ='WS Konsol'!BF467-N66+1 -> 5031429971 | P62: ='WS Konsol'!BH467-P66-2 -> 5655591014 | R62: Accrued Expenses
A63: Utang Pajak | F63: 18b | H63: ='WS Konsol'!AF453 -> 404042742 | J63: ='WS Konsol'!BC453 -> 2317673499 | L63: ='WS Konsol'!AI453 -> 2863697915 | N63: ='WS Konsol'!BF453 -> 2152621331 | P63: ='WS Konsol'!BH453 -> 712242589 | R63: Taxes Payable
A64: Bagian Lancar dari Utang
A65: Jangka Panjang | R65: Current Portion of Long-Term Debt
B66: Utang Pembelian Aset Tetap | F66: 16 | H66: ='WS Konsol'!AF463 -> 38822068 | J66: ='WS Konsol'!BC463 -> 34780634 | L66: ='WS Konsol'!AI463 -> 76360023 | N66: ='WS Konsol'!BF463 -> 67475296 | P66: ='WS Konsol'!BH463 -> 0 | S66: Purchase of Fixed Assets Liabilities
B67: Liabilitas Sewa kepada | S67: Lease Liabilities to
B68: Pihak Berelasi | F68: 17 | H68: ='WS Konsol'!AF470 -> 0 | J68: ='WS Konsol'!BC470 -> 3533493723 | L68: ='WS Konsol'!AI470 -> 624277457 | N68: ='WS Konsol'!BF470 -> 3539216266 | P68: ='WS Konsol'!BH470 -> 0 | S68: Related Parties
B69: Utang Bank | F69: 19 | H69: ='WS Konsol'!AF278 -> 1869894064 | J69: ='WS Konsol'!BC472 -> 6824412708 | L69: ='WS Konsol'!AI278 -> 3807894064 | N69: ='WS Konsol'!BF472 -> 3403633332 | P69: ='WS Konsol'!BH472 -> 3403633332 | S69: Bank Loans
A71: Jumlah Liabilitas Jangka Pendek | H71: =SUM(H58:H69) -> 228192560972 | J71: =SUM(J58:J69) -> 234246454095 | L71: =SUM(L58:L69) -> 226092689273 | N71: =SUM(N58:N69) -> 181881350007 | P71: =SUM(P58:P69) -> 134703536261 | R71: Total Current Liabilities
A73: LIABILITAS JANGKA PANJANG | R73: NON-CURRENT LIABILITIES
A74: Liabiltas Jangka Panjang - Setelah | R74: Long-Term Debt Net of
A75: Dikurangi Bagian Lancar | R75: Current Portion
B76: Pihak Berelasi | F76: 14 | H76: =SUM('WS Konsol'!AF427:AF432)+'WS Konsol'!AF504 -> 0 | J76: =SUM('WS Konsol'!BC427:BC432)+'WS Konsol'!BC504 -> 1313271695 | L76: =SUM('WS Konsol'!AI427:AI432)+'WS Konsol'!AI504 -> 595676695 | N76: =SUM('WS Konsol'!BF427:BF432)+'WS Konsol'!BF504 -> 533174595 | P76: =SUM('WS Konsol'!BH427:BH432)+'WS Konsol'!BH504 -> 137349400 | S76: Related Parties
B77: Utang Lain-lain Pihak Ketiga | F77: 14 | H77: ='WS Konsol'!AF424 -> 0 | J77: ='WS Konsol'!BC424 -> 41000000 | L77: ='WS Konsol'!AI424 -> 41000000 | N77: ='WS Konsol'!BF424 -> 41000000 | P77: ='WS Konsol'!BH424 -> 41000000 | S77: Other Payable Third Parties
B78: Utang Bank | F78: 19 | H78: ='WS Konsol'!AF494-H79 -> 0 | J78: ='WS Konsol'!BC494-J79 -> 3403633336 | L78: ='WS Konsol'!AI494-L79 -> 0 | N78: ='WS Konsol'!BF494-N79 -> 8526229378 | P78: ='WS Konsol'!BH494-P79 -> 14285076353 | S78: Bank loans
B79: Utang Pembelian Aset Tetap | F79: 16 | H79: ='WS Konsol'!AF484 -> 0 | J79: ='WS Konsol'!BC484 -> 76360023 | L79: ='WS Konsol'!AI484 -> 0 | N79: ='WS Konsol'!BF484 -> 76360023 | P79: ='WS Konsol'!BH484 -> 0 | S79: Purchase of Fixed Assets Liabilities
B80: Liabilitas Sewa kepada Pihak Berelasi | F80: 17 | H80: 0 | J80: ='WS Konsol'!BC497 -> 630000000 | L80: 0 | N80: ='WS Konsol'!BF497 -> 624277457 | P80: ='WS Konsol'!BH497 -> 4125675035 | S80: Lease Liabilities to Related Parties
A81: Liabilitas Imbalan PascaKerja | F81: 20 | H81: ='WS Konsol'!AF481 -> 9301883257 | J81: ='WS Konsol'!BC481 -> 8419134989 | L81: ='WS Konsol'!AI481 -> 9301883257 | N81: ='WS Konsol'!BF481 -> 8419134989 | P81: ='WS Konsol'!BH481 -> 8346918827 | R81: Post Employment Benefits Liability
A85: Jumlah Liabilitas Jangka Panjang | H85: =SUM(H76:H82) -> 9301883257 | J85: =SUM(J76:J82) -> 13883400043 | L85: =SUM(L76:L82) -> 9938559952 | N85: =SUM(N76:N82) -> 18220176442 | P85: =SUM(P76:P82) -> 26936019615 | R85: Total Non-Current Liabilities
A87: JUMLAH LIABILITAS | H87: =H71+H85 -> 237494444229 | J87: =J71+J85 -> 248129854138 | L87: =L71+L85 -> 236031249225 | N87: =N71+N85 -> 200101526449 | P87: =P71+P85 -> 161639555876 | R87: TOTAL LIABILITIES
J88: =J87-'WS Konsol'!BC506 -> 0
F90: Catatan/ | N90: 31 Desember
F91: Notes | H91: =H7 -> 45444 | J91: =J7 -> 45078 | L91: =L7 -> 2023 | N91: 2022 | P91: 2021*)
A93: EKUITAS | R93: EQUITY
A94: Modal Saham - Nilai Nominal | R94: Share capital
A95: Rp 50,- per Saham | R95: Par value Rp 50 per share,
B96: Modal Dasar Ditempatkan dan Disetor | S96: Authorized, Subscribed and Fully
B97: Sebesar 800.000.000 Saham | F97: 21 | H97: ='WS Konsol'!AF508-1000000000 -> 55000000000 | J97: ='WS Konsol'!BC508-1000000000 -> 40000000000 | L97: ='WS Konsol'!AI508-1000000000 -> 40000000000 | N97: ='WS Konsol'!BF508-1000000000 -> 40000000000 | P97: 40000000000 | S97: Paid-up Capital 800,000,000
A99: Tambahan Modal Disetor | F99: 22 | H99: ='WS Konsol'!AF512 -> 49739416785 | J99: ='WS Konsol'!BC512 -> 49739416785 | L99: ='WS Konsol'!AI512 -> 49739416785 | N99: ='WS Konsol'!BF512 -> 25871690669 | P99: 25871690669 | R99: Additional paid-in capital
A100: Proforma Ekuitas | H100: 0 | J100: 0 | L100: 0 | N100: 2.3406502e+10 | P100: 2.2389615e+10 | R100: Equity Pro forma
A101: Surplus revaluasi aset tetap | H101: ='[192]WS Des Konsol Update'!Q494 -> 0 | J101: 0 | L101: 0 | N101: 0 | P101: 0 | R101: Asset revalution surplus
A102: Penghasilan Komprehensif lain | F102: 29 | H102: ='WS Konsol'!AF536 -> -377072852 | J102: ='WS Konsol'!BC536 -> -368797440 | L102: ='WS Konsol'!AI536 -> -377072852 | N102: ='WS Konsol'!BF536 -> -368797440 | P102: -611495277 | R102: Other comprehensive income
A103: Saldo Laba | R103: Retained earnings
B104: Ditentukan Penggunaannya | F104: 21b | H104: =L104 -> 410000000 | J104: =400000000+10000000 -> 410000000 | L104: =N104 -> 410000000 | N104: =400000000+10000000 -> 410000000 | P104: 0 | S104: Appropriated
B105: Tidak Ditentukan Penggunaannya | F105: 21b | H105: ='WS Konsol'!AF525-'WS Konsol'!Z525+'WS Konsol'!Z525+'WS Konsol'!Z508-H104 -> 5393649296 | J105: ='WS Konsol'!BC525-'WS Konsol'!AW525+'WS Konsol'!AW525+'WS Konsol'!AW508-J104 -> 18621152951 | L105: 19521729837 | N105: 18237502879 | P105: =ROUNDDOWN(13426333849.6015,0) -> 13426333849 | S105: Unappropriated | T105: pastikan rumus link nya
T106: ='PL Konsol'!L29 -> 844874515
A107: JUMLAH EKUITAS | H107: =SUM(H96:H105) -> 110165993229 | J107: =SUM(J96:J105) -> 108401772296 | L107: =SUM(L96:L105) -> 109294073770 | N107: =SUM(N96:N105) -> 1.075569e+11 | P107: =SUM(P96:P105) -> 1.0107614e+11 | R107: TOTAL EQUITY | T107: =SUM(J97:J106) -> 108401772296
T108: =T107-T106 -> 107556897781
A109: JUMLAH LIABILITAS DAN | R109: TOTAL LIABILITIES | T109: 108018122224
A110: EKUITAS | H110: =H87+H107 -> 347660437458 | J110: =J87+J107 -> 356531626434 | L110: =L87+L107 -> 345325322995 | N110: =N87+N107 -> 3.0765842e+11 | P110: =ROUNDUP(P87+P107,0) -> 262715700578 | R110: AND EQUITY | T110: =T108-T109 -> -461224443
A112: *)Disajikan Kembali Catatan ..
C113: ='[192]WS Des Konsol Update'!K245 -> 345325322995 | H113: =H48 -> 347660437458 | J113: =J48 -> 356531626434 | L113: =L48 -> 345325322995 | N113: =N48 -> 307658424230 | P113: =P48 -> 262715700578
C114: Control | H114: ='WS Konsol'!AF539 -> 347660437458 | J114: ='WS Konsol'!BC539 -> 356531626434 | L114: ='WS Konsol'!AI539 -> 345325322995 | N114: ='WS Konsol'!BF539 -> 307658424229 | P114: ='WS Konsol'!BH539 -> 262715700580
C115: =C113-L110 -> 0 | H115: =H110-H48 -> 0 | J115: =J110-J48 -> 0 | L115: =L110-L48 -> 0 | N115: =N110-N48 -> -0.13720703 | P115: =P110-P48 -> 0
F119: Current Ratio | L119: =L22/L71 -> 1.1257677 | N119: =N22/N71 -> 1.135455 | P119: =P22/P71 -> 1.1230512
F120: ROA | L120: ='[192]PL Konsol'!J36/'[192]BS Konsol'!I55 -> 0.0060550512 | N120: ='[192]PL Konsol'!L36/'[192]BS Konsol'!K55 -> 0.016938165 | P120: ='[192]PL Konsol'!N36/'[192]BS Konsol'!M55 -> 0.01269529
F121: ROE | L121: ='[192]PL Konsol'!J36/'[192]BS Konsol'!I122 -> 0.019131527 | N121: ='[192]PL Konsol'!L36/'[192]BS Konsol'!K122 -> 0.048450347 | P121: ='[192]PL Konsol'!N36/'[192]BS Konsol'!M122 -> 0.03299742
F122: EBITDA/Pendapatan | L122: ='[192]Rasio DSCR'!B15/'[192]PL Konsol'!J11 -> 0.1466267 | N122: ='[192]Rasio DSCR'!D15/'[192]PL Konsol'!L11 -> 0.061853422 | P122: ='[192]Rasio DSCR'!F15/'[192]PL Konsol'!N11 -> 0

Sheet CF Konsol
A1: PT Indo American Seafoods
A2: LAPORAN ARUS KAS KONSOLIDASIAN
A3: Untuk Tahun-tahun yang Berakhir pada 31 Desember 2024 dan 2023
A4: (Disajikan dalam Rupiah, kecuali Dinyatakan Lain)
D6: Catatan/
D7: Notes | F7: 2024 | H7: 45536 | J7: 45170 | L7: 45444 | N7: 45078 | P7: 2023 | R7: 2022 | T7: 2021 | V7: 2020*)
A9: ARUS KAS DARI AKTIVITAS | X9: CASH FLOWS FROM OPERATING
A10: OPERASI | X10: ACTIVITIES
A11: Penerimaan Kas dari Pelanggan | D11: 6.23 | F11: ='KK CF Des 24'!B12 -> 2.479591e+11 | H11: ='KK CF Konsol Sept 24'!B12 -> 142535701651 | J11: ='KK CF Konsol Sept 23'!B12 -> 198600619207 | L11: =ROUND('KK CF Konsol Juni 24'!B12,0) -> 100267200082 | N11: =ROUND('KK CF Konsol Juni 23'!B12,0) -> 147943609918 | P11: 233862704890 | R11: 367723496508 | T11: 295637097279 | V11: ='[188]CF Des 2020'!B12 -> 2.3119964e+11 | X11: Cash Receipts from Customers
A12: Pembayaran kepada Pemasok | D12: 7,8,10,13,15,16,17 | F12: ='KK CF Des 24'!B13 -> -2.8437732e+11 | H12: ='KK CF Konsol Sept 24'!B13 -> -153211436065 | J12: ='KK CF Konsol Sept 23'!B13 -> -153671439280 | L12: =ROUND('KK CF Konsol Juni 24'!B13,0) -> -73323475715 | N12: =ROUND('KK CF Konsol Juni 23'!B13,0) -> -113398734628 | P12: -2.1589419e+11 | R12: -338209234805 | T12: -2.4548691e+11 | V12: ='[188]CF Des 2020'!B13+'[188]CF Des 2020'!B18 -> -2.1331067e+11 | X12: Cash Paid to Suppliers
D13: 24,26,27,29
A14: Pembayaran kepada Karyawan | D14: 20b,24,26 | F14: ='KK CF Des 24'!B14 -> -34022364196 | H14: ='KK CF Konsol Sept 24'!B14 -> -24434393698 | J14: ='KK CF Konsol Sept 23'!B14 -> -25590754706 | L14: =ROUND('KK CF Konsol Juni 24'!B14,0) -> -15569341077 | N14: =ROUND('KK CF Konsol Juni 23'!B14,0) -> -18032431758 | P14: -1.6774e+10 | R14: -17641958141 | T14: -19169374181 | V14: ='[188]CF Des 2020'!AU14 -> -5470819837 | X14: Cash Paid to Employees
A15: Pembayaran Beban Operasional Lainnya | D15: 9,11,18a,12,18e,19a | F15: ='KK CF Des 24'!B15 -> -16505528793 | H15: ='KK CF Konsol Sept 24'!B15 -> -9593676650 | J15: ='KK CF Konsol Sept 23'!B15 -> -1.2898953e+10 | L15: =ROUND('KK CF Konsol Juni 24'!B15,0) -> -7910563784 | N15: =ROUND('KK CF Konsol Juni 23'!B15,0) -> -13990581180 | P15: -15514922507 | R15: -36504076478 | T15: -2.3422128e+10 | V15: ='[188]CF Des 2020'!B15-AJ16 -> -2.1446182e+10 | X15: Cash Paid for Other Operating Expenses
A16: Kas Dihasilkan dari Operasi | F16: =SUM(F11:F15) -> -8.6946115e+10 | H16: =SUM(H11:H15) -> -44703804762 | J16: =SUM(J11:J15) -> 6.4394726e+09 | L16: =SUM(L11:L15) -> 3463819506 | N16: =SUM(N11:N15) -> 2521862352 | P16: =SUM(P11:P15) -> -1.432041e+10 | R16: =SUM(R11:R15) -> -24631772916 | T16: =SUM(T11:T15) -> 7.558687e+09 | V16: =SUM(V11:V15)-1 -> -9.0280324e+09 | X16: Cash Generated from Operating
A17: Penerimaan bunga | X17: Interest Received
A18: Pembayaran Pajak Penghasilan | D18: 18 | F18: ='KK CF Des 24'!B21 -> -3483902607 | H18: ='KK CF Konsol Sept 24'!B21 -> -2993103253 | J18: ='KK CF Konsol Sept 23'!B21 -> -2280513846 | L18: =ROUND('KK CF Konsol Juni 24'!B21,0) -> -2993103253 | N18: =ROUND('KK CF Konsol Juni 23'!B21,0) -> -2231324752 | P18: -701013069 | R18: -696135092 | T18: -411274129 | V18: ='[188]CF Des 2020'!B21+'[188]CF Des 2020'!B17 -> -1.9018995e+09 | X18: Cash Paid for Income Taxes Paid
A19: Pembayaran Beban Bunga dan Keuangan | D19: 28 | F19: ='KK CF Des 24'!B20 -> -18184572249 | H19: ='KK CF Konsol Sept 24'!B20 -> -12487102791 | J19: ='KK CF Konsol Sept 23'!B20 -> -11291340727 | L19: =ROUND('KK CF Konsol Juni 24'!B20,0) -> -9308297571 | N19: =ROUND('KK CF Konsol Juni 23'!B20,0) -> -7489287943 | P19: -15677499788 | R19: -13403963086 | T19: -9352093192 | V19: ='[188]CF Des 2020'!B16+'[188]CF Des 2020'!B20 -> -3024695925 | X19: Payment of Interest and Finance Costs
A21: Kas Bersih Digunakan Untuk | X21: Net Cash Used in
A22: Aktivitas Operasi | F22: =SUM(F16:F19) -> -1.0861459e+11 | H22: =SUM(H16:H19) -> -60184010806 | J22: =SUM(J16:J19) -> -7.132382e+09 | L22: =SUM(L16:L19) -> -8837581318 | N22: =SUM(N16:N19) -> -7198750343 | P22: =SUM(P16:P19) -> -3.0698923e+10 | R22: =SUM(R16:R19) -> -38731871094 | T22: =SUM(T16:T19) -> -2.2046803e+09 | V22: =SUM(V16:V19) -> -1.3954628e+10 | X22: Operating Expenses
A25: ARUS KAS DARI AKTIVITAS | X25: CASH FLOWS FROM INVESTING
A26: Hasil Penjualan Aset Tetap | R26: #REF! | V26: #REF!
A27: Pembayaran Uang Muka Pembelian | X27: Advance Payments for
A28: Aset Tetap | P28: 0 | R28: 0 | T28: 0 | V28: ='[188]CF Des 2020'!B28 -> -862722001 | X28: Purchase of Property, Plant and Equipment
A29: INVESTASI | X29: ACTIVITIES
A30: Perolehan Aset Tetap | D30: 11 | F30: ='KK CF Des 24'!B28 -> -170000000 | H30: ='KK CF Konsol Sept 24'!B28 -> 0 | J30: ='KK CF Konsol Sept 23'!B28 -> -149115000 | L30: ='KK CF Konsol Juni 24'!B28 -> 0 | N30: =ROUND('KK CF Konsol Juni 23'!B28,0) -> -149115000 | P30: -149115000 | R30: -337817118 | T30: -1.7752124e+10 | V30: ='[188]CF Des 2020'!B29 -> -4598783202 | X30: Acquisition of Fixed Assets
A31: Penerimaan Desposito | F31: ='KK CF Des 24'!B32 -> 0 | H31: ='KK CF Konsol Sept 24'!B32 -> 0 | J31: 0 | P31: 0 | X31: Receipt of Deposits
A32: Penerimaan Piutang Lain-Lain | X32: Proceeds from Other Recivable
A33: dari Pihak Berelasi | D33: 7 | F33: ='KK CF Des 24'!B33 -> 7022707423 | H33: ='KK CF Konsol Sept 24'!B33 -> 7022707423 | J33: 0 | P33: 0 | X33: from Related Parties
A34: Perolehan Aset Hak Guna | D34: 7
A36: Kas Bersih Diperoleh dari (Digunakan untuk) | X36: Net Cash Provided by (Used in)
A37: Aktivitas Investasi | F37: =SUM(F26:F34) -> 6852707423 | H37: =SUM(H26:H34) -> 7022707423 | J37: =SUM(J26:J34) -> -149115000 | L37: =SUM(L26:L34) -> 0 | N37: =SUM(N26:N34) -> -149115000 | P37: =SUM(P26:P34) -> -149115000 | R37: =SUM(R26:R34) -> -337817118 | T37: =SUM(T26:T34) -> -1.7752124e+10 | V37: =SUM(V26:V34) -> -5461505203 | X37: from Investing Activities
A39: ARUS KAS DARI AKTIVITAS | X39: CASH FLOWS FROM FINANCING
A40: PENDANAAN | X40: ACTIVITIES
A41: Utang Bank | X41: Bank Loans
A42: Penerimaan | D42: 18.19 | F42: ='KK CF Des 24'!B38 -> 826004939945 | H42: ='KK CF Konsol Sept 24'!B38 -> 649398050028 | J42: ='KK CF Konsol Sept 23'!B37 -> 320718850062 | L42: =ROUND('KK CF Konsol Juni 24'!B37,0) -> 369706236685 | N42: =ROUND('KK CF Konsol Juni 23'!B37,0) -> 223626289709 | P42: 527352848743 | R42: 417886251544 | T42: 355278938231 | V42: ='[188]CF Des 2020'!B38 -> 6138558333 | X42: Proceeds
A43: Pembayaran | D43: 18.19 | F43: ='KK CF Des 24'!B39 -> -793982710777 | H43: ='KK CF Konsol Sept 24'!B39 -> -653783580534 | J43: ='KK CF Konsol Sept 23'!B38 -> -316298545908 | L43: =ROUND('KK CF Konsol Juni 24'!B38,0) -> -361652935773 | N43: =ROUND('KK CF Konsol Juni 23'!B38,0) -> -216245927159 | P43: -495372719131 | R43: -379120929829 | T43: -338461235558 | V43: ='[188]CF Des 2020'!B39 -> -3075000000 | X43: Payments
A44: Pembayaran Liabilitas Sewa | D44: 17 | F44: ='KK CF Des 24'!B41 -> -624277457 | H44: ='KK CF Konsol Sept 24'!B41 -> -624277457 | J44: 0 | L44: ='KK CF Konsol Juni 24'!B40 -> -624277457 | N44: ='KK CF Konsol Juni 23'!B39 -> 0 | P44: -3544941809 | R44: 0 | T44: 0 | X44: Payment for Lease Liabilities
A45: Utang Pembelian Aset Tetap | D45: 17 | X45: Liabilities for Purchase of Fixed Asset
B46: Pembayaran | R46: -143835319 | X46: Payments
A47: Pembayaran Utang Pembelian | X47: Liabilities for Purchase of
A48: Aset Tetap | D48: 16 | F48: ='KK CF Des 24'!B43 -> -76360023 | P48: 0 | X48: Fixed Asset
A49: Modal Disetor dari Penawaran Umum | X49: Paid-Up Capital from Initial
A50: Perdana Saham | D50: 21 | F50: ='KK CF Des 24'!B44 -> 14500000000 | H50: ='KK CF Konsol Sept 24'!B44 -> 14500000000 | J50: 0 | P50: 0 | X50: Public Offering of Shares
A51: Penerimaan Agio Saham sehubungan | X51: Proceeds from Additional Paid-in Capital
A52: dengan Penawaran Umum Perdana Saham | D52: 22 | F52: ='KK CF Des 24'!B45 -> 58000000000 | H52: ='KK CF Konsol Sept 24'!B45 -> 58000000000 | J52: 0 | P52: 0 | X52: through Initial Public Offering of Shares
X53: Emission Costs for Initial
A54: Pembayaran Biaya Emisi Saham | D54: 22 | F54: ='KK CF Des 24'!B46 -> -3115944915 | H54: ='KK CF Konsol Sept 24'!B46 -> -3115944915 | J54: 0 | P54: 0 | X54: Share Issuance Cost
A55: Utang Lain-Lain kepada Pihak Berelasi | X55: Other Payable to Related Parties
B56: Penerimaan | F56: 0 | H56: 0 | J56: ='KK CF Konsol Sept 23'!B43 -> 755097100 | L56: 0 | N56: ='KK CF Konsol Juni 23'!B43 -> 780097100 | P56: 62502100 | R56: 395825195 | Y56: Proceed
B57: Pembayaran | D57: 14 | F57: ='KK CF Des 24'!B47 -> -595676695 | H57: ='KK CF Konsol Sept 24'!B47 -> -595676695 | J57: 0 | L57: ='KK CF Konsol Juni 24'!B43 -> -595676695 | N57: 0 | P57: 0 | T57: -247604400 | V57: 0 | Y57: Payments
B58: Pembayaran | D58: 14 | P58: - | T58: -247604400 | Y58: Payments
A60: Kas Bersih Diperoleh dari | X60: Net Cash Provided by
A61: Aktivitas Pendanaan | F61: =SUBTOTAL(9,F42:F57) -> 100109970078 | H61: =SUBTOTAL(9,H42:H57) -> 63778570427 | J61: =SUBTOTAL(9,J42:J57) -> 5175401254 | L61: =SUBTOTAL(9,L42:L57) -> 6833346760 | N61: =SUBTOTAL(9,N42:N57) -> 8160459650 | P61: =SUBTOTAL(9,P42:P58) -> 28497689903 | R61: =SUM(R42:R57) -> 39017311591 | T61: 19415033454 | V61: =SUM(V42:V57) -> 3063558333 | X61: Financing Activities
A64: PENURUNAN BERSIH KAS | X64: NET DECREASE IN CASH
A65: DAN SETARA KAS | F65: =F61+F37+F22 -> -1.6519119e+09 | H65: =H61+H37+H22 -> 10617267044 | J65: =J61+J37+J22 -> -2.1060957e+09 | L65: =L61+L37+L22 -> -2004234558 | N65: =N61+N37+N22 -> 812594307 | P65: =P61+P37+P22 -> -2.3503476e+09 | R65: =R61+R37+R22 -> -52376621 | T65: =T61+T37+T22 -> -541770942 | V65: =V61+V37+V22 -> -1.6352575e+10 | X65: AND CASH EQUIVALENTS
A67: KAS DAN SETARA KAS | X67: CASH AND CASH EQUIVALENTS
A69: AWAL TAHUN | F69: ='WS Konsol'!AI52 -> 2570121355 | H69: ='BS Konsol-Des 24'!Q11 -> 2570121355 | J69: ='BS Konsol-Des 24'!S11 -> 4920468963 | L69: =P73 -> 2.5701214e+09 | N69: ='WS Konsol'!BF52 -> 4920468963 | P69: =R73 -> 4.920469e+09 | R69: =T73 -> 4.9728456e+09 | T69: 5.5146165e+09 | V69: ='[188]WS Des Konsol Update'!AR57 -> 22532809247 | X69: AT BEGINNING OF YEAR
A71: KAS DAN SETARA KAS | X71: CASH AND CASH EQUIVALENTS
A73: AKHIR TAHUN | F73: =ROUND((F65+F69),0) -> 918209485 | H73: =ROUND((H65+H69),0) -> 13187388399 | J73: =J65+J69 -> 2.8143732e+09 | L73: =ROUND((L65+L69),0) -> 565886797 | N73: =N65+N69 -> 5733063270 | P73: =P65+P69 -> 2.5701214e+09 | R73: =R65+R69 -> 4.920469e+09 | T73: =SUM(T65:T69) -> 4.9728456e+09 | V73: =V65+V69 -> 6.1802345e+09 | X73: AT END OF YEAR
F76: ='BS Konsol-Des 24'!G11 -> 918209485 | H76: ='BS Konsol-Des 24'!I11 -> 13187388399 | J76: ='BS Konsol-Des 24'!K11 -> 2814373246 | L76: ='BS Konsol'!H11 -> 565886797 | N76: ='BS Konsol'!J11 -> 5733063270 | P76: ='BS Konsol-Des 24'!Q11 -> 2570121355 | R76: 4920468963 | T76: ='[188]BS Konsol'!M14 -> 4972845584 | V76: 5.5146165e+09
F77: =F73-F76 -> 0 | H77: =H73-H76 -> 0 | J77: =J76-J73 -> -0.13722992 | L77: =L73-L76 -> 0 | N77: =N76-N73 -> 0 | P77: =P76-P73 -> 0.099306107 | R77: =R76-R73 -> 0 | T77: =T73-T76 -> 0 | V77: =V73-V76 -> 6.6561802e+08

Sheet WP CF-Direct 23
F1: 100 | G1: 110 | H1: 120 | I1: 130 | J1: 140 | K1: 150 | L1: 160 | M1: 170 | O1: 145 | P1: 190 | R1: 200 | S1: 280 | T1: 270 | U1: 240 | V1: 230 | W1: 220 | X1: 210 | Y1: 211 | Z1: 250 | AA1: 300 | AB1: 330 | AC1: 320 | AD1: 310 | AE1: 400 | AF1: 500 | AG1: 600 | AH1: 650 | AI1: 700 | AJ1: 810 | AK1: 800 | AL1: 900
E2: =SUM(F5:P5) -> 918209485 | F2: Kas dan Bank | G2: Piutang Usaha dari Pihak Ketiga | H2: Piutang Lain-lain dari Pihak Ketiga | I2: Persediaan | J2: Biaya Dibayar Dimuka | K2: Pajak Dibayar Dimuka | L2: Aset | M2: Aset | P2: Aset | R2: Utang | S2: Beban | T2: Aset | U2: Liabilitas | V2: Utang | W2: Utang | X2: Utang Pemegang | Y2: Utang Pembelian | Z2: Imbalan | AA2: Modal Saham | AB2: Tambahan Modal | AC2: Penghasilan Komprehensif Lainnya | AD2: Saldo Laba | AE2: Pendapatan Usaha | AF2: Beban Pokok Pendapatan Usaha | AG2: Beban Umum dan Administrasi | AH2: Beban Bunga dan Keuangan | AI2: Pendapatan (Beban) | AJ2: Beban Pajak Penghasilan | AK2: Pajak | AL2: Penghasilan Komprehensif Lainnya
E3: =-SUM(R5:AL5) -> 0 | L3: Tetap | M3: Hak Guna | O3: Uang Muka | P3: Pajak Ditangguhkan | R3: Usaha | S3: Akrual | T3: Pajak Ditangguhkan | U3: Sewa | V3: Pajak | W3: Bank | X3: Saham | Y3: Belum Ditagih | Z3: Pascakerja | AB3: Disetor | AI3: Lain-lain | AK3: Tangguhan
E4: =E2-E3 -> 918209485
E5: 45657 | F5: ='BS Konsol-Des 24'!G11 -> 918209485 | AM5: =SUM(F5:AL5) -> 918209485
E6: 45291 | AM6: =SUM(F6:AL6) -> 0
E7: Selisih 2024-2023 | F7: =F5-F6 -> 918209485 | G7: =G5-G6 -> 0 | H7: =H5-H6 -> 0 | I7: =I5-I6 -> 0 | J7: =J5-J6 -> 0 | K7: =K5-K6 -> 0 | L7: =L5-L6 -> 0 | M7: =M5-M6 -> 0 | O7: =O5-O6 -> 0 | P7: =P5-P6 -> 0 | R7: =R5-R6 -> 0 | S7: =S5-S6 -> 0 | T7: =T5-T6 -> 0 | U7: =U5-U6 -> 0 | V7: =V5-V6 -> 0 | W7: =W5-W6 -> 0 | X7: =X5-X6 -> 0 | Y7: =Y5-Y6 -> 0 | ... AM7: =AM5-AM6 -> 918209485
E8: Movement
B9: ARUS KAS DARI AKTIVITAS OPERASI
C10: Penerimaan Kas dari Aktivitas Operasi
A11: 100 | D11: Penerimaan Kas dari Pelanggan | E11: =ROUND(SUM(G11:AL11),0) -> 0 | G11: =-G7 -> 0 | AE11: =-AE7 -> 0
A12: 100 | D12: Penerimaan Kas Lainnya dari Aktivitas Operasi | E12: =SUM(G12:AL12) -> 0
C13: Pembayaran Kas dari Aktivitas Operasi
A14: 102 | D14: Pembayaran Kepada Pemasok Atas Barang dan Jasa | E14: =ROUND(SUM(G14:AL14),0) -> 5867331342 | I14: =-I7 -> 0 | R14: =-R7 -> 0 | AC14: =-AC7-AC53 -> 0 | AF14: =-AF7-AF15-AF16 -> 3054332885 | AG14: =-AG7-AG15-AG16 -> 2812998457
A15: 103 | D15: Pembayaran Gaji dan Tunjangan | E15: =ROUND(SUM(G15:AL15),0) -> -3807729601 | Z15: =-Z7 -> 0 | AF15: -1512779164 | AG15: -2294950437
A16: 200 | D16: Pembayaran Beban Operasional Lainnya | E16: =ROUND(SUM(G16:AL16),0) -> -17882306442 | H16: =-H7 -> 0 | J16: =-J7 -> 0 | K16: =-K7 -> 0 | L16: =-L7-L28 -> 5215957180 | M16: =-M7-M50 -> 0 | O16: =-O7 -> 0 | P16: =-P7 -> 0 | S16: =-S7 -> 0 | T16: =-T7 -> 0 | U16: =-U7-U50 -> 150000000 | V16: =-V7 -> 0 | X16: =-X7-X57 -> -1500000000 | Y16: =-Y7 -> 0 | AA16: =-AA7-AA52 -> -20000000000 | AF16: -1541553721 | AG16: -518048020 | AI16: =-AI7-AI17 -> 0 | AJ16: =-AJ7-AJ19 -> 311338119 | AK16: =-AK7 -> 0 | AL16: =-AL7 -> 0
A17: 102 | C17: Penerimaan Bunga dari Aktivitas Operasi | E17: =SUM(G17:AL17) -> 0
A18: 105 | C18: Pembayaran Bunga dari Aktivitas Operasi | E18: =ROUND(SUM(G18:AL18),0) -> 0 | AH18: =-AH7 -> 0
A19: 104 | C19: Pembayaran Pajak Penghasilah | E19: =SUM(G19:AL19) -> -311338119 | AJ19: -311338119
B21: Jumlah arus kas bersih yang diperoleh dari (digunakan untuk) aktivitas operasi | E21: =SUM(E11:E19) -> -16134042820
B23: ARUS KAS DARI AKTIVITAS INVESTASI
C24: Pembayaran Uang Muka Pembelian Aset Tetap | E24: =SUM(G24:AL24) -> 0
C25: Penerimaan dari Penjualan Properti Investasi | E25: =SUM(G25:AL25) -> 0
C26: Pembayaran Untuk Perolehan Properti Investasi | E26: =SUM(G26:AL26) -> 0
C27: Penerimaan dari Penjualan Aset Tetap | E27: =SUM(G27:AL27) -> 0
A28: 106 | C28: Pembayaran Untuk Perolehan Aset Tetap | E28: =ROUND(SUM(G28:AL28),0) -> -5215957180 | L28: -5215957180
C29: Penerimaan dari Penjualan Aset Takberwujud | E29: =SUM(G29:AL29) -> 0
C30: Pembayaran Untuk Perolehan Aset Takberwujud | E30: =SUM(G30:AL30) -> 0
C31: Penerimaan dari Future Contracts, Forward Contracts, Option Contracts, dan Swap Contracts | E31: =SUM(G31:AL31) -> 0
C32: Pembayaran Untuk Future Contracts, Forward Contracts, Option Contracts, dan Swap Contracts | E32: =SUM(G32:AL32) -> 0
C33: Pembayaran Uang Muka Investasi | E33: =SUM(G33:AL33) -> 0
C34: Penerimaan Pembayaran Piutang dari Pihak Berelasi | E34: =SUM(G34:AL34) -> 0
C35: Pembayaran Pemberian Piutang Kepada Pihak Berelasi | E35: =SUM(G35:AL35) -> 0
C36: Penerimaan Pembayaran Piutang dari Pemegang Saham | E36: =SUM(G36:AL36) -> 0
C37: Pembayaran Pemberian Piutang Kepada Pemegang Saham | E37: =SUM(G37:AL37) -> 0
C38: Penerimaan Dividen dari Aktivitas Investasi | E38: =SUM(G38:AL38) -> 0
C39: Penerimaan Bunga dari Aktivitas Investasi | E39: =SUM(G39:AL39) -> 0
C40: Pembayaran Bunga dari Aktivitas Investasi | E40: =SUM(G40:AL40) -> 0
B42: Jumlah arus kas bersih yang diperoleh dari (digunakan untuk) aktivitas investasi | E42: =ROUND(SUM(E24:E41),0) -> -5215957180
B44: ARUS KAS DARI AKTIVITAS PENDANAAN
A45: 107 | C45: Penerimaan Pinjaman Bank | E45: =SUM(G45:AL45) -> 0
A46: 108 | C46: Pembayaran Pinjaman Bank | E46: =SUM(G46:AL46) -> 0
A47: 110 | C47: Penerimaan Utang Pembiayaan Konsumen | E47: =SUM(G47:AL47) -> 0
C48: Pembayaran Utang Pembiayaan Konsumen | E48: =SUM(G48:AL48) -> 0
C49: Penerimaan Liabilitas Sewa Pembiayaan | E49: =SUM(G49:AL49) -> 0
A50: 109 | C50: Pembayaran Liabilitas Sewa Pembiayaan | E50: =SUM(G50:AL50) -> -150000000 | U50: -150000000
