Workbook
Name \1: #REF!
Name \2: #REF!
Name \3: #REF!
Name \4: #REF!
Name \5: #REF!
Name \6: #REF!
Name \a: [1]JUL!#REF!
Name \A: #REF!
Name \APR: #REF!
Name \AUG: #REF!
Name \b: [2]T.B!#REF!
Name \B: #REF!
Name \BCYTD: '[3]CF WORKSHEET'!#REF!
Name \BRYTD: #REF!
Name \BSYTD: #REF!
Name \BTWO: #REF!
Name \BUYTD: #REF!
Name \C: #REF!
Name \CTWO: #REF!
Name \d: [2]T.B!#REF!
Name \D: #REF!
Name \DEC: #REF!
Name \DTWO: #REF!
Name \E: [4]SMITH!#REF!
Name \E: #REF!
Name \F: [4]SMITH!#REF!
Name \F: #REF!
Name \FEB: #REF!
Name \G: #REF!
Name \H: #REF!
Name \I: #REF!
Name \J: #REF!
Name \JAN: #REF!
Name \K: #REF!
Name \L: #REF!
Name \m: [2]T.B!#REF!
Name \M: #REF!
Name \MAR: #REF!
Name \MAY: #REF!
Name \MSN: #N/A
Name \n: #N/A
Name \NOV: #REF!
Name \O: #REF!
Name \OCT: #REF!
Name \p: #REF!
Name \Q: #REF!
Name \r: #REF!
Name \s: #REF!
Name \SEP: #REF!
Name \T: '[3]CF WORKSHEET'!#REF!
Name \T: #REF!
Name \T2: '[5]ban-ling'!#REF!
Name \U: #REF!
Name \V: #REF!
Name \w: #N/A
Name \x: #N/A
Name \y: #N/A
Name \Z: #REF!
Name \z: #N/A
Name _\b: #N/A

Sheet MAP
A1: ACCOUNTS PAYABLE AND ACCRUED LIABILITIES – AUDIT PROGRAM | C1: RMAP
A3: Client name: | B3: PT Indo American Seafoods Tbk dan Entitas Anak | C3: Sign-off: | D3: Initials | E3: Date
C4: Prepared: | D4: NLS | E4: 45814
C5: Reviewed: | D5: KNW | E5: 45817
A6: Period end: | B6: 45657 | C6: Approved: | D6: MGN | E6: 45822
A8: Financial Statement Assertions
A10: C. Completeness
A11: E. Existence
A12: A. Accuracy
A13: V. Valuation
A15: A. BASIC PROCEDURES
A16: No. | B16: Audit Procedure | C16: Assert | D16: Comment | E16: Ref.
A17: Accounts Payable Listing
A18: 0.041666667 | B18: For manual listings: | C18: A
B19: Obtain client's accounts payable listing and:
B20: a) Agree listing to general ledger.
B21: b) Test mathematical accuracy of listing.
A22: 0.083333333 | B22: For electronic listings: | C22: A
B23: Obtain electronically the client's detailed accounts payable listing and using the IDEA Audit Automation Tool:
B24: a) Agree control total to general ledger to ensure the listing was imported accurately and completely.
B25: b) Test mathematical accuracy of accounts payable listing.
A26: Debit balances
A27: 0.125 | B27: For electronic listings: | C27: A
B28: Using the Audit Automation tool, extract debit balances. Investigate significant debit balances and consider their transfer to accounts receivable.
A29: 0.16666667 | B29: For manual listings: | C29: A
B30: Investigate significant debit balances and consider their transfer to accounts receivable.
A31: Related Party Transactions
A32: 0.20833333 | B32: Document transactions and ending balances with related parties and ensure they are disclosed in the financial statements. | C32: CEAV
A33: 0.25 | B33: Verify that inter entity accounts are in agreement if we are the auditors of both entities. If not, obtain written confirmation. | C33: CEA
A34: 0.29166667 | B34: Enquire of management whether all related party transactions were appropriately identified (e.g. major cancelable contract, transact a significant volume of business with a sole customer, provide free use of space, personnel and services, preferential rates or lease property to and from related party) and recorded. | C34: C
A35: Merchandise Received on Consignment
A36: 0.33333333 | B36: Discuss with a responsible official that no amounts payable are included for merchandise received on consignment. | C36: A
A37: Major Suppliers
A38: 0.375 | B38: Select a sample of the client's major supplier(s) based on annual purchases and review a statement showing all outstanding invoices as at year end. (The statement may be obtained internally or by confirmation depending on the circumstances). | C38: CEAV
B39: a) Agree accounts payable on the A/P listing to supplier's statement or confirmation.
B40: b) Summarize the results and investigate differences by examining the supporting documentation and enquiry.
A41: 0.41666667 | B41: Perform alternative procedures where no reply was received from the supplier or where suppliers’ statements were not retained by the client. | C41: CE
B42: a) Obtain a detailed general ledger breakdown of the account;
B43: b) Review payments in the subsequent period and consider the need to examine supporting documentation;
B44: c) Check other significant debits to supporting documentation;
B45: d) Select a sample of goods received notes for that supplier and check that the related invoices have been posted to the purchase ledger account.
A46: Unrecorded Transactions
A47: 0.45833333 | B47: Discuss with a responsible official as to the existence of any unrecorded liabilities. | C47: C
A48: Volume Rebates or Cash Discounts
A49: 0.5 | B49: a) Enquire of management for accruals related to volume rebates or cash discounts. | C49: AV
B50: b) Compare level of accruals with prior year or investigate significant variances between expectations and recorded amounts.
A51: Translation
A52: 0.54166667 | B52: Verify that accounts payable denominated in foreign currencies were translated at the appropriate exchange rate. | C52: V
B53: Supplier Reconciliations – Other than Period End
A54: 0.58333333 | B54: If supplier reconciliation is carried out at a date other than period end | C54: A
B55: a) Test the mathematical accuracy of the purchase journal affecting that period;
B56: b) Compare the supplier balance at different dates and explain significant or unexpected changes;
B57: c) Scan the sub-ledger in the general ledger for high value or unusual entries and investigating those items;
B58: e) Perform additional cut off procedures at the date of the tests in addition to year end cut-off procedures.
A59: Accrued Liabilities
A60: 0.625 | B60: Verify accrued liabilities (other than income taxes payable): | C60: A
B61: a) Document the basis and rationale for calculating the accrual.
B62: b) Assess the reasonability of the accrual by:
B63: i) Performing a predictive test;
B64: ii)Examine supporting documentation.
B65: c) Consider whether adequate provision for accruals has been made where necessary (i.e. warranties, rebates, special discounts, professional fees, sales taxes, pension, interest and royalties).
A66: Unmatched Invoices
A67: 0.66666667 | B67: Examine unmatched and/or not posted invoices and receiving documents to ensure that all expenditures relating to the period are properly recorded in the correct period. | C67: A
A68: Accrued Wages and Salaries
A69: 0.70833333 | B69: Obtain the calculation for accrued wages and salaries, accrued commissions, accrued vacation pay and accrued bonuses and perform the following: | C69: A
B70: a) Agree balance to the general ledger.
B71: b) Assess reasonableness of accruals by:
B72: i) Performing a predictive test (i.e., number of days accrued for payroll/payroll expense); and/or
B73: ii) Examining supporting documentation.
B74: c) Test mathematical accuracy
B75: d) Agree the subsequent payment of accrued salaries (if any) and wages to payroll records
A76: Payroll Deductions at Source
A77: 0.75 | B77: Review payments made subsequent to year end for payroll deductions to ensure that payroll accruals at year end are complete. | C77: CA
A78: Payroll Deductions
A79: 0.79166667 | B79: Review employee deduction accounts to ensure proper clearance each month and no accumulation of material unreconciled amount for: | C79: C
B80: i) Income tax
B81: ii) CPP
B82: iii) Unemployment insurance
B83: iv) Provincial health insurance plan
B84: v) Other health insurance plans
B85: vi) Pension plans
B86: vii) Group insurance
A87: GST/HST and Other Sales Taxes
A88: 0.83333333 | B88: Obtain a summary of GST/HST filings for the year and perform the following: | C88: CA
B89: a) Select a sample of ___- months from the summary and agree the sales figure from the filing to the general ledger.
B90: b) Ensure that the sample selected was assessed as filed.
A92: B. EXTENDED PROCEDURES
A94: No. | B94: Audit Procedure | C94: Assert | D94: Comment | E94: Ref.
A95: Significant Debit Balances
A96: 0.875 | B96: Consider sending a confirmation for significant debit balances in accounts payable. | C96: A
A97: Debit Notes
A98: 0.91666667 | B98: Review debit notes received after the balance sheet date to check that they are accounted for in the correct period. | C98: CA
A99: Disputed/unprocessed invoices
A100: 0.95833333 | B100: Obtain from the client the file of unprocessed and disputed invoices until the end of fieldwork and for all invoices over a specified amount, determine whether the invoice is properly included or excluded from trade creditors at the balance sheet date. | C100: C
A101: Purchase Commitments
A102: 1 | B102: Review outstanding purchase commitments at the balance sheet date and consider the extent to which material losses could arise and provisions be required. In particular: | C102: CV
B103: a) Check client records of outstanding purchase commitments and consider need for confirmation;
B104: b) Consider management's system for evaluating the need for provisions (if any);
B105: c) Review post balance sheet evidence as to changes in market prices, selling prices, excess quantities, relevant changes in exchange rates.
A106: Accounts Payable Confirmations – Fraud Risk
...

Sheet G. 100 Memo
A5: Client | B5: : PT Indo American Seafoods Tbk dan Entitas Anak | E5: Prepared by | F5: : NLS | K5: Date : | L5: 45814
A6: Account | B6: : Trade payable | E6: Reviewed by | F6: : KNW | K6: Date : | L6: 45817
A7: Period | B7: : 31 Desember 2024 | E7: Approved by: | F7: : MGN | K7: Date : | L7: 45822
A8: Matter | B8: : Memo
A11: NATURE OF ACCOUNT
B13: Utang Usaha | C13: : Merupakan utang usaha kepada supplier dan vendor terkait untuk kegiatan operasional Perusahaan
A15: PROCEDURES
B18: - Mencocokan angka Inhouse dengan general ledger
B19: - Mengirimkan Surat Konfirmasi
B20: - Meminta List AP
B21: - Mapping to Report
B22: - Meminta Aging Utang Usaha
A23: FINDINGS
B25: Pada akun Utang tidak ditemukan temuan yang material
A27: CONCLUSION
B29: Semua transaksi terkait Utang sudah disajikan dan telah sesuai dengan periode terjadinya transaksi, maka Utang telah disajikan secara wajar

Sheet G.200 Eliminasi 2023
B1: JURNAL ELIMINASI | F1: =SUM(F7:F513) -> 204309487586 | G1: =SUM(G7:G513) -> 204309487586 | I1: =F109-F112 -> 0
B2: KONSOLIDASI 2022
B5: Account No. | C5: Account Name | E5: WP Reff | F5: Balance Sheet | H5: Income Statement | J5: Description
F6: Debit | G6: Credit | H6: Debit | I6: Credit
A8: EL | C8: IAS - Modal | G8: 1050000000
D9: Investasi pada entitas anak | F9: =G8 -> 1050000000
C11: Piutang ISP | G11: 62518053072
D12: Utang IAS ke ISP | F12: =G11 -> 62518053072
D13: Penjualan ke IAS _ Pembelian ISP
A15: 2 | D15: Piutang IAS | G15: 132646777153
D16: Utang ISP | F16: =G15 -> 132646777153
D17: Penjualan ke ISP _
A18: 3
D19: Piutang IAS | G19: 8079657361
D20: Utang ISP | F20: =G19 -> 8079657361
A22: 4 | D22: Total Pembelian IAS ke ISP Udang | H22: 86959145763
D23: Roti | H23: 1694239200
D24: Lain" Sticker | H24: 583412160
D25: Pembelian IAS ke ISP Udang | I25: 86959145763
D26: Roti | I26: 1694239200
D27: Lain" Sticker | I27: 583412160
D30: Penjualan ke ISP | H30: 16455117914
D32: Pembelian | I32: =H30 -> 16455117914
D34: Pendapatan Lain" Sewa IPAL | H34: =15000000 -> 15000000
D35: Beban Sewa IPAL | I35: =H34 -> 15000000
B37: AJE | D37: Biaya YMH | F37: 15000000
D38: Piutang Lain-lain | G38: =F37 -> 15000000
D42: Jurnal Eliminasi 2022 & 2021

Sheet ELIM & CAJE Des 24
A1: JURNAL ELIMINASI | F1: Diff | G1: =G2-H2 -> 0
A2: Konsolidasi Desember 2024 | F2: Kontrol | G2: =F3+H3 -> 34150403486 | H2: =G3+I3 -> 34150403486
F3: =SUM(F8:F12) -> 34150403486 | G3: =SUM(G8:G12) -> 34150403486 | H3: =SUM(H8:H12) -> 0 | I3: =SUM(I8:I12) -> 0
A5: Account No. | B5: Date | C5: Account Name | E5: WP Reff | F5: Balance Sheet | H5: PL | J5: Description
F6: Debit | G6: Credit | H6: Debit | I6: Credit
A8: ELIM 2 | C8: PT Indokom Samudra Persada | F8: 29592782261 | J8: Eleminasi Utang Piutang
A9: =A8 -> ELIM 2 | D9: PT Indo American Seafoods | G9: =F8 -> 29592782261 | J9: =J8 -> Eleminasi Utang Piutang
A11: ELIM 3 | C11: PT Indo American Seafoods | F11: 4557621225 | J11: Eleminasi Utang Piutang
A12: =A11 -> ELIM 3 | D12: PT Indokom Samudra Persada | G12: =F11 -> 4557621225 | J12: =J11 -> Eleminasi Utang Piutang

Sheet G.500 LeadSheet
B6: Client | C6: : PT Indo American Seafoods Tbk dan Entitas Anak | F6: Prepared by | G6: : LFS | M6: Date : | N6: 03/07/2024
B7: Account | C7: : Piutang Usaha | F7: Reviewed by | G7: : FMN | M7: Date : | N7: 06/07/2024
B8: Period | C8: : 31 Desember 203,2022, dan 2021 | F8: Approved by: | G8: : MGN | M8: Date : | N8: 10/07/2024
B9: Index | C9: : Memo
B11: NO | C11: Description | D11: Audited PT IAS | E11: Audited PT ISP | F11: Audited PT Konsol | G11: Eliminasi | K11: Audited Konsol | M11: Audited PT IAS | N11: Audited PT ISP | O11: Audited PT Konsol | P11: Eliminasi | T11: Audited Konsol | V11: Incrase/Decrase 2024 dan 2023 | Y11: Incrase/Decrase 2021 dan 2020
B12: Account | D12: 31 Desember 2024 | E12: 31 Desember 2024 | F12: 31 Desember 2024 | G12: Ref | H12: Dr | I12: Ref | J12: Cr | K12: =F12 -> 31 Desember 2024 | M12: 45291 | N12: =M12 -> 45291 | O12: =N12 -> 45291 | P12: Ref | Q12: Dr | R12: Ref | S12: Cr | T12: =O12 -> 45291 | V12: Rp | W12: % | Y12: Rp | Z12: %
B13: Trade Payable
C14: Hutang Usaha | D14: 0 | F14: =ROUND((D14+E14),0) -> 0 | K14: =ROUND((F14-H14+J14),0) -> 0 | M14: 0 | N14: 0 | O14: =ROUND((M14+N14),0) -> 0 | T14: =ROUND((O14-Q14+S14),0) -> 0 | V14: =K14-T14 -> 0 | W14: =IFERROR(V14/T14,0) -> 0
B15: ISP | C15: Bapak Cipto | D15: 0 | E15: 19544752 | F15: =ROUND((D15+E15),0) -> 19544752 | K15: =ROUND((F15-H15+J15),0) -> 19544752 | M15: 0 | N15: 21911630 | O15: =ROUND((M15+N15),0) -> 21911630 | T15: =ROUND((O15-Q15+S15),0) -> 21911630 | V15: =K15-T15 -> -2366878 | W15: =IFERROR(V15/T15,0) -> -0.10801926
B16: ISP | C16: Supplier Bahan Baku Udang & Non Udang | D16: 0 | E16: 0 | F16: =ROUND((D16+E16),0) -> 0 | K16: =ROUND((F16-H16+J16),0) -> 0 | M16: 0 | N16: 0 | O16: =ROUND((M16+N16),0) -> 0 | T16: =ROUND((O16-Q16+S16),0) -> 0 | V16: =K16-T16 -> 0 | W16: =IFERROR(V16/T16,0) -> 0
B17: ISP | C17: Bakti Angurah Kreasi,CV | D17: 0 | E17: 0 | F17: =ROUND((D17+E17),0) -> 0 | K17: =ROUND((F17-H17+J17),0) -> 0 | M17: 0 | N17: 0 | O17: =ROUND((M17+N17),0) -> 0 | T17: =ROUND((O17-Q17+S17),0) -> 0 | V17: =K17-T17 -> 0 | W17: =IFERROR(V17/T17,0) -> 0
B18: ISP | C18: AGS Sejahtera, CV, | D18: 0 | E18: 40019800 | F18: =ROUND((D18+E18),0) -> 40019800 | K18: =ROUND((F18-H18+J18),0) -> 40019800 | M18: 0 | N18: 0 | O18: =ROUND((M18+N18),0) -> 0 | T18: =ROUND((O18-Q18+S18),0) -> 0 | V18: =K18-T18 -> 40019800 | W18: =IFERROR(V18/T18,0) -> 0
B19: ISP | C19: GEA Refrigeration Indonesia, PT | D19: 0 | E19: 0 | F19: =ROUND((D19+E19),0) -> 0 | K19: =ROUND((F19-H19+J19),0) -> 0 | M19: 0 | N19: 0 | O19: =ROUND((M19+N19),0) -> 0 | T19: =ROUND((O19-Q19+S19),0) -> 0 | V19: =K19-T19 -> 0 | W19: =IFERROR(V19/T19,0) -> 0
B20: ISP | C20: Halim Sakti Pratama, PT | D20: 0 | E20: 13506480 | F20: =ROUND((D20+E20),0) -> 13506480 | K20: =ROUND((F20-H20+J20),0) -> 13506480 | M20: 0 | N20: 1720500 | O20: =ROUND((M20+N20),0) -> 1720500 | T20: =ROUND((O20-Q20+S20),0) -> 1720500 | V20: =K20-T20 -> 11785980 | W20: =IFERROR(V20/T20,0) -> 6.8503226
B21: ISP | C21: Harapan Abadi, CV | D21: 0 | E21: 0 | F21: =ROUND((D21+E21),0) -> 0 | K21: =ROUND((F21-H21+J21),0) -> 0 | M21: 0 | N21: 0 | O21: =ROUND((M21+N21),0) -> 0 | T21: =ROUND((O21-Q21+S21),0) -> 0 | V21: =K21-T21 -> 0 | W21: =IFERROR(V21/T21,0) -> 0
B22: ISP | C22: Intiragam Oliefindo, PT | D22: 0 | E22: 24975000 | F22: =ROUND((D22+E22),0) -> 24975000 | K22: =ROUND((F22-H22+J22),0) -> 24975000 | M22: 0 | N22: 49950000 | O22: =ROUND((M22+N22),0) -> 49950000 | T22: =ROUND((O22-Q22+S22),0) -> 49950000 | V22: =K22-T22 -> -24975000 | W22: =IFERROR(V22/T22,0) -> -0.5
B23: ISP | C23: KARYA EKATAMA, PT | D23: 0 | E23: 0 | F23: =ROUND((D23+E23),0) -> 0 | K23: =ROUND((F23-H23+J23),0) -> 0 | M23: 0 | N23: 0 | O23: =ROUND((M23+N23),0) -> 0 | T23: =ROUND((O23-Q23+S23),0) -> 0 | V23: =K23-T23 -> 0 | W23: =IFERROR(V23/T23,0) -> 0
C24: R&B FOOD SUPPLY CO, LTD, | E24: 355200000 | F24: =ROUND((D24+E24),0) -> 355200000 | K24: =ROUND((F24-H24+J24),0) -> 355200000
B25: ISP | C25: Samara Cipta Solution, CV | D25: 0 | E25: 0 | F25: =ROUND((D25+E25),0) -> 0 | K25: =ROUND((F25-H25+J25),0) -> 0 | M25: 0 | N25: 122323133 | O25: =ROUND((M25+N25),0) -> 122323133 | T25: =ROUND((O25-Q25+S25),0) -> 122323133 | V25: =K25-T25 -> -122323133 | W25: =IFERROR(V25/T25,0) -> -1
B26: ISP | C26: Seven Mountain Internasional, PT | D26: 0 | E26: 29859000 | F26: =ROUND((D26+E26),0) -> 29859000 | K26: =ROUND((F26-H26+J26),0) -> 29859000 | M26: 0 | N26: 20684850 | O26: =ROUND((M26+N26),0) -> 20684850 | T26: =ROUND((O26-Q26+S26),0) -> 20684850 | V26: =K26-T26 -> 9174150 | W26: =IFERROR(V26/T26,0) -> 0.44352026
B27: ISP | C27: Sinar Panca Surya, PT | D27: 0 | E27: 0 | F27: =ROUND((D27+E27),0) -> 0 | K27: =ROUND((F27-H27+J27),0) -> 0 | M27: 0 | N27: 34576502 | O27: =ROUND((M27+N27),0) -> 34576502 | T27: =ROUND((O27-Q27+S27),0) -> 34576502 | V27: =K27-T27 -> -34576502 | W27: =IFERROR(V27/T27,0) -> -1
B28: ISP | C28: Sinar Setia Mulia , PT | D28: 0 | E28: 55230003 | F28: =ROUND((D28+E28),0) -> 55230003 | K28: =ROUND((F28-H28+J28),0) -> 55230003 | M28: 0 | N28: 56950000 | O28: =ROUND((M28+N28),0) -> 56950000 | T28: =ROUND((O28-Q28+S28),0) -> 56950000 | V28: =K28-T28 -> -1719997 | W28: =IFERROR(V28/T28,0) -> -0.030201879
C29: CV Windu Segara Hatchery | D29: 0 | E29: 0 | F29: =ROUND((D29+E29),0) -> 0 | K29: =ROUND((F29-H29+J29),0) -> 0 | O29: =ROUND((M29+N29),0) -> 0 | T29: =ROUND((O29-Q29+S29),0) -> 0 | V29: =K29-T29 -> 0 | W29: =IFERROR(V29/T29,0) -> 0
B30: ISP | C30: Central Proteina Prima, PT | D30: 0 | E30: 0 | F30: =ROUND((D30+E30),0) -> 0 | K30: =ROUND((F30-H30+J30),0) -> 0 | M30: 0 | N30: 0 | O30: =ROUND((M30+N30),0) -> 0 | T30: =ROUND((O30-Q30+S30),0) -> 0 | V30: =K30-T30 -> 0 | W30: =IFERROR(V30/T30,0) -> 0
B31: ISP | C31: Citra Boga Sentosa, PT | D31: 0 | E31: 0 | F31: =ROUND((D31+E31),0) -> 0 | K31: =ROUND((F31-H31+J31),0) -> 0 | M31: 0 | N31: 0 | O31: =ROUND((M31+N31),0) -> 0 | T31: =ROUND((O31-Q31+S31),0) -> 0 | V31: =K31-T31 -> 0 | W31: =IFERROR(V31/T31,0) -> 0
B32: ISP | C32: Indo Surya Cemerlang, CV | D32: 0 | E32: 0 | F32: =ROUND((D32+E32),0) -> 0 | K32: =ROUND((F32-H32+J32),0) -> 0 | M32: 0 | N32: 0 | O32: =ROUND((M32+N32),0) -> 0 | T32: =ROUND((O32-Q32+S32),0) -> 0 | V32: =K32-T32 -> 0 | W32: =IFERROR(V32/T32,0) -> 0
B33: ISP | C33: Nusantara, Toko | D33: 0 | E33: 0 | F33: =ROUND((D33+E33),0) -> 0 | K33: =ROUND((F33-H33+J33),0) -> 0 | M33: 0 | N33: 5025000 | O33: =ROUND((M33+N33),0) -> 5025000 | T33: =ROUND((O33-Q33+S33),0) -> 5025000 | V33: =K33-T33 -> -5025000 | W33: =IFERROR(V33/T33,0) -> -1
B34: ISP | C34: Newhope Aqua Feed Indonesia, PT | D34: 0 | E34: 0 | F34: =ROUND((D34+E34),0) -> 0 | K34: =ROUND((F34-H34+J34),0) -> 0 | M34: 0 | N34: 0 | O34: =ROUND((M34+N34),0) -> 0 | T34: =ROUND((O34-Q34+S34),0) -> 0 | V34: =K34-T34 -> 0 | W34: =IFERROR(V34/T34,0) -> 0
B35: ISP | C35: Surya Serba Mulia, PT | D35: 0 | E35: 0 | F35: =ROUND((D35+E35),0) -> 0 | K35: =ROUND((F35-H35+J35),0) -> 0 | M35: 0 | N35: 0 | O35: =ROUND((M35+N35),0) -> 0 | T35: =ROUND((O35-Q35+S35),0) -> 0 | V35: =K35-T35 -> 0 | W35: =IFERROR(V35/T35,0) -> 0
B36: ISP | C36: Sumatra Motor Teknindo, PT | D36: 0 | E36: 0 | F36: =ROUND((D36+E36),0) -> 0 | K36: =ROUND((F36-H36+J36),0) -> 0 | M36: 0 | N36: 97993099 | O36: =ROUND((M36+N36),0) -> 97993099 | T36: =ROUND((O36-Q36+S36),0) -> 97993099 | V36: =K36-T36 -> -97993099 | W36: =IFERROR(V36/T36,0) -> -1
B37: ISP | C37: Tri Jaya Sukses | D37: 17646570 | E37: 34791785 | F37: =ROUND((D37+E37),0) -> 52438355 | K37: =ROUND((F37-H37+J37),0) -> 52438355 | M37: 0 | N37: 0 | O37: =ROUND((M37+N37),0) -> 0 | T37: =ROUND((O37-Q37+S37),0) -> 0 | V37: =K37-T37 -> 52438355 | W37: =IFERROR(V37/T37,0) -> 0
B38: ISP | C38: Perc, Salma | D38: 0 | E38: 0 | F38: =ROUND((D38+E38),0) -> 0 | K38: =ROUND((F38-H38+J38),0) -> 0 | M38: 0 | N38: 0 | O38: =ROUND((M38+N38),0) -> 0 | T38: =ROUND((O38-Q38+S38),0) -> 0 | V38: =K38-T38 -> 0 | W38: =IFERROR(V38/T38,0) -> 0
B39: ISP | C39: AKR Corporindo Tbk, PT | D39: 0 | E39: 0 | F39: =ROUND((D39+E39),0) -> 0 | K39: =ROUND((F39-H39+J39),0) -> 0 | M39: 0 | N39: 75000000 | O39: =ROUND((M39+N39),0) -> 75000000 | T39: =ROUND((O39-Q39+S39),0) -> 75000000 | V39: =K39-T39 -> -75000000 | W39: =IFERROR(V39/T39,0) -> -1
B40: ISP | C40: General Agromesin Lestari, PT | D40: 0 | E40: 0 | F40: =ROUND((D40+E40),0) -> 0 | K40: =ROUND((F40-H40+J40),0) -> 0 | M40: 0 | N40: 116369995 | O40: =ROUND((M40+N40),0) -> 116369995 | T40: =ROUND((O40-Q40+S40),0) -> 116369995 | V40: =K40-T40 -> -116369995 | W40: =IFERROR(V40/T40,0) -> -1
B41: ISP | C41: Maju Tambak Sumur, PT | D41: 0 | E41: 0 | F41: =ROUND((D41+E41),0) -> 0 | K41: =ROUND((F41-H41+J41),0) -> 0 | M41: 0 | N41: 29249998 | O41: =ROUND((M41+N41),0) -> 29249998 | T41: =ROUND((O41-Q41+S41),0) -> 29249998 | V41: =K41-T41 -> -29249998 | W41: =IFERROR(V41/T41,0) -> -1
B42: ISP | C42: SUMBERDAYA SINAR BARU, PT | D42: 0 | E42: 55366010 | F42: =ROUND((D42+E42),0) -> 55366010 | K42: =ROUND((F42-H42+J42),0) -> 55366010 | M42: 0 | N42: 19068210 | O42: =ROUND((M42+N42),0) -> 19068210 | T42: =ROUND((O42-Q42+S42),0) -> 19068210 | V42: =K42-T42 -> 36297800 | W42: =IFERROR(V42/T42,0) -> 1.9035767
C43: PT Anesta Agung | D43: 494401450 | E43: 398165412 | F43: =ROUND((D43+E43),0) -> 892566862 | K43: =ROUND((F43-H43+J43),0) -> 892566862 | M43: 0 | N43: 9 | O43: =ROUND((M43+N43),0) -> 9 | T43: =ROUND((O43-Q43+S43),0) -> 9 | V43: =K43-T43 -> 892566853 | W43: =IFERROR(V43/T43,0) -> 99174095
C44: Choice Canning Company Inc, | D44: 0 | E44: 0 | F44: =ROUND((D44+E44),0) -> 0 | K44: =ROUND((F44-H44+J44),0) -> 0 | M44: 1356603529 | N44: 0 | O44: =ROUND((M44+N44),0) -> 1356603529 | T44: =ROUND((O44-Q44+S44),0) -> 1356603529 | V44: =K44-T44 -> -1356603529 | W44: =IFERROR(V44/T44,0) -> -1
C45: Tn. Julius Juyanto | D45: 0 | E45: 0 | F45: =ROUND((D45+E45),0) -> 0 | K45: =ROUND((F45-H45+J45),0) -> 0 | M45: 0 | N45: 0 | O45: =ROUND((M45+N45),0) -> 0 | T45: =ROUND((O45-Q45+S45),0) -> 0 | V45: =K45-T45 -> 0 | W45: =IFERROR(V45/T45,0) -> 0
C46: Tn. Sudirman | D46: 0 | E46: 0 | F46: =ROUND((D46+E46),0) -> 0 | K46: =ROUND((F46-H46+J46),0) -> 0 | M46: 0 | N46: 0 | O46: =ROUND((M46+N46),0) -> 0 | T46: =ROUND((O46-Q46+S46),0) -> 0 | V46: =K46-T46 -> 0 | W46: =IFERROR(V46/T46,0) -> 0
C47: PT Anugerah Berkah Usaha | D47: 0 | E47: 0 | F47: =ROUND((D47+E47),0) -> 0 | K47: =ROUND((F47-H47+J47),0) -> 0 | M47: 0 | N47: 1.1781822e+08 | O47: =ROUND((M47+N47),0) -> 117818222 | T47: =ROUND((O47-Q47+S47),0) -> 117818222 | V47: =K47-T47 -> -117818222 | W47: =IFERROR(V47/T47,0) -> -1
C48: PT Delos Rantai Maritim | D48: 0 | E48: 2102768 | F48: =ROUND((D48+E48),0) -> 2102768 | K48: =ROUND((F48-H48+J48),0) -> 2102768 | M48: 0 | N48: 0 | O48: =ROUND((M48+N48),0) -> 0 | T48: =ROUND((O48-Q48+S48),0) -> 0 | V48: =K48-T48 -> 2102768 | W48: =IFERROR(V48/T48,0) -> 0
C49: PT International Packaging Manufacturing | D49: 0 | E49: 971250 | F49: =ROUND((D49+E49),0) -> 971250 | K49: =ROUND((F49-H49+J49),0) -> 971250 | M49: 668830500 | N49: 971250 | O49: =ROUND((M49+N49),0) -> 669801750 | T49: =ROUND((O49-Q49+S49),0) -> 669801750 | V49: =K49-T49 -> -668830500 | W49: =IFERROR(V49/T49,0) -> -0.99854994
B50: ISP | C50: Tn. Agus Sujono | D50: 0 | E50: 0 | F50: =ROUND((D50+E50),0) -> 0 | K50: =ROUND((F50-H50+J50),0) -> 0 | M50: 0 | N50: 0 | O50: =ROUND((M50+N50),0) -> 0 | T50: =ROUND((O50-Q50+S50),0) -> 0 | V50: =K50-T50 -> 0 | W50: =IFERROR(V50/T50,0) -> 0
B51: ISP | C51: Ahmad Ruba'i | D51: 0 | E51: 0 | F51: =ROUND((D51+E51),0) -> 0 | K51: =ROUND((F51-H51+J51),0) -> 0 | M51: 0 | N51: 0 | O51: =ROUND((M51+N51),0) -> 0 | T51: =ROUND((O51-Q51+S51),0) -> 0 | V51: =K51-T51 -> 0 | W51: =IFERROR(V51/T51,0) -> 0
B52: ISP | C52: Ahmad Heriyadi | D52: 0 | E52: 0 | F52: =ROUND((D52+E52),0) -> 0 | K52: =ROUND((F52-H52+J52),0) -> 0 | M52: 0 | N52: 1.1283047e+08 | O52: =ROUND((M52+N52),0) -> 112830473 | T52: =ROUND((O52-Q52+S52),0) -> 112830473 | V52: =K52-T52 -> -112830473 | W52: =IFERROR(V52/T52,0) -> -1
B53: ISP | C53: Disanta, PT | D53: 0 | E53: 0 | F53: =ROUND((D53+E53),0) -> 0 | K53: =ROUND((F53-H53+J53),0) -> 0 | M53: 0 | N53: -4 | O53: =ROUND((M53+N53),0) -> -4 | T53: =ROUND((O53-Q53+S53),0) -> -4 | V53: =K53-T53 -> 4 | W53: =IFERROR(V53/T53,0) -> -1
B54: ISP | C54: Jwartono | D54: 0 | E54: 0 | F54: =ROUND((D54+E54),0) -> 0 | K54: =ROUND((F54-H54+J54),0) -> 0 | M54: 0 | N54: 0 | O54: =ROUND((M54+N54),0) -> 0 | T54: =ROUND((O54-Q54+S54),0) -> 0 | V54: =K54-T54 -> 0 | W54: =IFERROR(V54/T54,0) -> 0
B55: ISP | C55: PT Konverta Mitra Abadi | D55: 338146802 | E55: 164562392 | F55: =ROUND((D55+E55),0) -> 502709194 | K55: =ROUND((F55-H55+J55),0) -> 502709194 | M55: 304771930 | N55: 101470448 | O55: =ROUND((M55+N55),0) -> 406242378 | T55: =ROUND((O55-Q55+S55),0) -> 406242378 | V55: =K55-T55 -> 96466816 | W55: =IFERROR(V55/T55,0) -> 0.23746123
B56: ISP | C56: CV Mekar Karya Mulia | D56: 0 | E56: 0 | F56: =ROUND((D56+E56),0) -> 0 | K56: =ROUND((F56-H56+J56),0) -> 0 | M56: 0 | N56: 0 | O56: =ROUND((M56+N56),0) -> 0 | T56: =ROUND((O56-Q56+S56),0) -> 0 | V56: =K56-T56 -> 0 | W56: =IFERROR(V56/T56,0) -> 0
B57: ISP | C57: Syarifuddin Arief, Hj, | D57: 0 | E57: 0 | F57: =ROUND((D57+E57),0) -> 0 | K57: =ROUND((F57-H57+J57),0) -> 0 | M57: 0 | N57: 0 | O57: =ROUND((M57+N57),0) -> 0 | T57: =ROUND((O57-Q57+S57),0) -> 0 | V57: =K57-T57 -> 0 | W57: =IFERROR(V57/T57,0) -> 0
B58: ISP | C58: Multidaya Teknologi Nusantara PT | D58: 0 | E58: 210906705 | F58: =ROUND((D58+E58),0) -> 210906705 | K58: =ROUND((F58-H58+J58),0) -> 210906705 | M58: 0 | N58: 3.1090671e+08 | O58: =ROUND((M58+N58),0) -> 310906705 | T58: =ROUND((O58-Q58+S58),0) -> 310906705 | V58: =K58-T58 -> -100000000 | W58: =IFERROR(V58/T58,0) -> -0.3216399
C59: Prima Larvae, PT | D59: 0 | E59: 54504000 | F59: =ROUND((D59+E59),0) -> 54504000 | K59: =ROUND((F59-H59+J59),0) -> 54504000 | M59: 0 | N59: 0 | O59: =ROUND((M59+N59),0) -> 0 | T59: =ROUND((O59-Q59+S59),0) -> 0 | V59: =K59-T59 -> 54504000 | W59: =IFERROR(V59/T59,0) -> 0
B60: ISP | C60: Sinar Hidup Satwa, PT | D60: 0 | E60: 0 | F60: =ROUND((D60+E60),0) -> 0 | K60: =ROUND((F60-H60+J60),0) -> 0 | M60: 0 | N60: 0 | O60: =ROUND((M60+N60),0) -> 0 | T60: =ROUND((O60-Q60+S60),0) -> 0 | V60: =K60-T60 -> 0 | W60: =IFERROR(V60/T60,0) -> 0
C61: RBFood Manufaktur Indonesia, PT | D61: 306138000 | F61: =ROUND((D61+E61),0) -> 306138000 | K61: =ROUND((F61-H61+J61),0) -> 306138000
B62: ISP | C62: PT RBFood Supply Indonesia | D62: 384060000 | E62: 0 | F62: =ROUND((D62+E62),0) -> 384060000 | K62: =ROUND((F62-H62+J62),0) -> 384060000 | M62: 0 | N62: 0 | O62: =ROUND((M62+N62),0) -> 0 | T62: =ROUND((O62-Q62+S62),0) -> 0 | V62: =K62-T62 -> 384060000 | W62: =IFERROR(V62/T62,0) -> 0
C63: Mitra Lestari Mandiri | D63: 483155250 | E63: 0 | F63: =ROUND((D63+E63),0) -> 483155250 | K63: =ROUND((F63-H63+J63),0) -> 483155250 | M63: 0 | N63: 0 | O63: =ROUND((M63+N63),0) -> 0 | T63: =ROUND((O63-Q63+S63),0) -> 0 | V63: =K63-T63 -> 483155250 | W63: =IFERROR(V63/T63,0) -> 0
C64: PT CJ Cheiljedang Feed Lampung | D64: 0 | E64: 2043145000 | F64: =ROUND((D64+E64),0) -> 2043145000 | K64: =ROUND((F64-H64+J64),0) -> 2043145000 | M64: 0 | N64: 1115222500 | O64: =ROUND((M64+N64),0) -> 1115222500 | T64: =ROUND((O64-Q64+S64),0) -> 1115222500 | V64: =K64-T64 -> 927922500 | W64: =IFERROR(V64/T64,0) -> 0.83205145
C65: Grahamakmur Ciptapratama | D65: 0 | E65: 0 | F65: =ROUND((D65+E65),0) -> 0 | K65: =ROUND((F65-H65+J65),0) -> 0 | M65: 1618149192 | N65: 0 | O65: =ROUND((M65+N65),0) -> 1618149192 | T65: =ROUND((O65-Q65+S65),0) -> 1618149192 | V65: =K65-T65 -> -1618149192 | W65: =IFERROR(V65/T65,0) -> -1
C66: Tn. Ismanto | D66: 0 | E66: 0 | F66: =ROUND((D66+E66),0) -> 0 | K66: =ROUND((F66-H66+J66),0) -> 0 | M66: 0 | N66: 0 | O66: =ROUND((M66+N66),0) -> 0 | T66: =ROUND((O66-Q66+S66),0) -> 0 | V66: =K66-T66 -> 0 | W66: =IFERROR(V66/T66,0) -> 0
B67: ISP | C67: Yeremia Sukamto | D67: 0 | E67: 0 | F67: =ROUND((D67+E67),0) -> 0 | K67: =ROUND((F67-H67+J67),0) -> 0 | M67: 0 | N67: 0 | O67: =ROUND((M67+N67),0) -> 0 | T67: =ROUND((O67-Q67+S67),0) -> 0 | V67: =K67-T67 -> 0 | W67: =IFERROR(V67/T67,0) -> 0
B68: ISP | C68: Prayoga Maju Sejahtera,CV | D68: 0 | E68: 0 | F68: =ROUND((D68+E68),0) -> 0 | K68: =ROUND((F68-H68+J68),0) -> 0 | M68: 0 | N68: 0 | O68: =ROUND((M68+N68),0) -> 0 | T68: =ROUND((O68-Q68+S68),0) -> 0 | V68: =K68-T68 -> 0 | W68: =IFERROR(V68/T68,0) -> 0
C69: PT Sumber Energy | D69: 31635000 | E69: 31635000 | F69: =ROUND((D69+E69),0) -> 63270000 | K69: =ROUND((F69-H69+J69),0) -> 63270000 | M69: 0 | N69: 27000000 | O69: =ROUND((M69+N69),0) -> 27000000 | T69: =ROUND((O69-Q69+S69),0) -> 27000000 | V69: =K69-T69 -> 36270000 | W69: =IFERROR(V69/T69,0) -> 1.3433333
C70: PT Indojaya Sukses Makmur | D70: 0 | E70: 0 | F70: =ROUND((D70+E70),0) -> 0 | K70: =ROUND((F70-H70+J70),0) -> 0 | M70: 0 | N70: 0 | O70: =ROUND((M70+N70),0) -> 0 | T70: =ROUND((O70-Q70+S70),0) -> 0 | V70: =K70-T70 -> 0 | W70: =IFERROR(V70/T70,0) -> 0
B71: ISP | C71: PT Gemilang Primajaya Trimandiri | D71: 1.7992629e+08 | E71: 0 | F71: =ROUND((D71+E71),0) -> 179926294 | K71: =ROUND((F71-H71+J71),0) -> 179926294 | M71: 0 | N71: 30862329 | O71: =ROUND((M71+N71),0) -> 30862329 | T71: =ROUND((O71-Q71+S71),0) -> 30862329 | V71: =K71-T71 -> 149063965 | W71: =IFERROR(V71/T71,0) -> 4.8299649
C72: PT Indonesia Makan Udang | D72: 2070057384 | E72: 817717862 | F72: =ROUND((D72+E72),0) -> 2887775246 | K72: =ROUND((F72-H72+J72),0) -> 2887775246 | M72: 2634498031 | N72: 1.817396e+09 | O72: =ROUND((M72+N72),0) -> 4451894010 | T72: =ROUND((O72-Q72+S72),0) -> 4451894010 | V72: =K72-T72 -> -1564118764 | W72: =IFERROR(V72/T72,0) -> -0.35133783
C73: Putra Widjaja Marine, CV | D73: 0 | E73: 0 | F73: =ROUND((D73+E73),0) -> 0 | K73: =ROUND((F73-H73+J73),0) -> 0 | M73: 4355506677 | N73: 885486308 | O73: =ROUND((M73+N73),0) -> 5240992985 | T73: =ROUND((O73-Q73+S73),0) -> 5240992985 | V73: =K73-T73 -> -5240992985 | W73: =IFERROR(V73/T73,0) -> -1
C74: PT SAEIKI TANGGUH COOLER | D74: 0 | E74: 0 | F74: =ROUND((D74+E74),0) -> 0 | K74: =ROUND((F74-H74+J74),0) -> 0 | M74: 0 | N74: 0 | O74: =ROUND((M74+N74),0) -> 0 | T74: =ROUND((O74-Q74+S74),0) -> 0 | V74: =K74-T74 -> 0 | W74: =IFERROR(V74/T74,0) -> 0
C75: Utomo Print | D75: 0 | E75: 0 | F75: =ROUND((D75+E75),0) -> 0 | K75: =ROUND((F75-H75+J75),0) -> 0 | M75: 75821880 | N75: 0 | O75: =ROUND((M75+N75),0) -> 75821880 | T75: =ROUND((O75-Q75+S75),0) -> 75821880 | V75: =K75-T75 -> -75821880 | W75: =IFERROR(V75/T75,0) -> -1
B76: ISP | C76: Bio Tirta, CV | D76: 0 | E76: 0 | F76: =ROUND((D76+E76),0) -> 0 | K76: =ROUND((F76-H76+J76),0) -> 0 | M76: 0 | N76: 0 | O76: =ROUND((M76+N76),0) -> 0 | T76: =ROUND((O76-Q76+S76),0) -> 0 | V76: =K76-T76 -> 0 | W76: =IFERROR(V76/T76,0) -> 0
B77: ISP | C77: Brandon Teknik | D77: 0 | E77: 0 | F77: =ROUND((D77+E77),0) -> 0 | K77: =ROUND((F77-H77+J77),0) -> 0 | M77: 0 | N77: 0 | O77: =ROUND((M77+N77),0) -> 0 | T77: =ROUND((O77-Q77+S77),0) -> 0 | V77: =K77-T77 -> 0 | W77: =IFERROR(V77/T77,0) -> 0
C78: Toko Sumber Matahari | D78: 0 | E78: 0 | F78: =ROUND((D78+E78),0) -> 0 | K78: =ROUND((F78-H78+J78),0) -> 0 | M78: 0 | N78: 0 | O78: =ROUND((M78+N78),0) -> 0 | T78: =ROUND((O78-Q78+S78),0) -> 0 | V78: =K78-T78 -> 0 | W78: =IFERROR(V78/T78,0) -> 0
C79: Suharto | D79: 0 | E79: 0 | F79: =ROUND((D79+E79),0) -> 0 | K79: =ROUND((F79-H79+J79),0) -> 0 | M79: 0 | N79: 0 | O79: =ROUND((M79+N79),0) -> 0 | T79: =ROUND((O79-Q79+S79),0) -> 0 | V79: =K79-T79 -> 0 | W79: =IFERROR(V79/T79,0) -> 0
B80: ISP | C80: PT Sinergy Indopack Makmur | D80: 59140800 | E80: 0 | F80: =ROUND((D80+E80),0) -> 59140800 | K80: =ROUND((F80-H80+J80),0) -> 59140800 | M80: 40182000 | N80: 0 | O80: =ROUND((M80+N80),0) -> 40182000 | T80: =ROUND((O80-Q80+S80),0) -> 40182000 | V80: =K80-T80 -> 18958800 | W80: =IFERROR(V80/T80,0) -> 0.4718232
B81: ISP | C81: SJP, Toko | D81: 0 | E81: 0 | F81: =ROUND((D81+E81),0) -> 0 | K81: =ROUND((F81-H81+J81),0) -> 0 | M81: 0 | N81: 0 | O81: =ROUND((M81+N81),0) -> 0 | T81: =ROUND((O81-Q81+S81),0) -> 0 | V81: =K81-T81 -> 0 | W81: =IFERROR(V81/T81,0) -> 0
C82: UD, Slamet | D82: 0 | E82: 0 | F82: =ROUND((D82+E82),0) -> 0 | K82: =ROUND((F82-H82+J82),0) -> 0 | M82: 0 | N82: 0 | O82: =ROUND((M82+N82),0) -> 0 | T82: =ROUND((O82-Q82+S82),0) -> 0 | V82: =K82-T82 -> 0 | W82: =IFERROR(V82/T82,0) -> 0
B83: ISP | C83: Prima Sari Indotama, PT | D83: 32435303 | E83: 0 | F83: =ROUND((D83+E83),0) -> 32435303 | K83: =ROUND((F83-H83+J83),0) -> 32435303 | M83: 28510258 | N83: 0 | O83: =ROUND((M83+N83),0) -> 28510258 | T83: =ROUND((O83-Q83+S83),0) -> 28510258 | V83: =K83-T83 -> 3925045 | W83: =IFERROR(V83/T83,0) -> 0.13767133
B84: ISP | C84: PSI | D84: 0 | E84: 0 | F84: =ROUND((D84+E84),0) -> 0 | K84: =ROUND((F84-H84+J84),0) -> 0 | M84: 0 | N84: 0 | O84: =ROUND((M84+N84),0) -> 0 | T84: =ROUND((O84-Q84+S84),0) -> 0 | V84: =K84-T84 -> 0 | W84: =IFERROR(V84/T84,0) -> 0
C85: Sumatraco Langgeng Abadi, PT | D85: 20535000 | E85: 0 | F85: =ROUND((D85+E85),0) -> 20535000 | K85: =ROUND((F85-H85+J85),0) -> 20535000 | M85: 34965000 | N85: 0 | O85: =ROUND((M85+N85),0) -> 34965000 | T85: =ROUND((O85-Q85+S85),0) -> 34965000 | V85: =K85-T85 -> -14430000 | W85: =IFERROR(V85/T85,0) -> -0.41269841
C86: R & R COLECTION | D86: 0 | E86: 0 | F86: =ROUND((D86+E86),0) -> 0 | K86: =ROUND((F86-H86+J86),0) -> 0 | M86: 0 | N86: 0 | O86: =ROUND((M86+N86),0) -> 0 | T86: =ROUND((O86-Q86+S86),0) -> 0 | V86: =K86-T86 -> 0 | W86: =IFERROR(V86/T86,0) -> 0
C87: PT Rahayu Perdana Trans | D87: 0 | E87: 0 | F87: =ROUND((D87+E87),0) -> 0 | K87: =ROUND((F87-H87+J87),0) -> 0 | M87: 0 | N87: 0 | O87: =ROUND((M87+N87),0) -> 0 | T87: =ROUND((O87-Q87+S87),0) -> 0 | V87: =K87-T87 -> 0 | W87: =IFERROR(V87/T87,0) -> 0
B88: ISP | C88: Toko Percetakan A1 Printing | D88: 0 | E88: 0 | F88: =ROUND((D88+E88),0) -> 0 | K88: =ROUND((F88-H88+J88),0) -> 0 | M88: 0 | N88: 0 | O88: =ROUND((M88+N88),0) -> 0 | T88: =ROUND((O88-Q88+S88),0) -> 0 | V88: =K88-T88 -> 0 | W88: =IFERROR(V88/T88,0) -> 0
C89: Toko R & R Collection | D89: 0 | E89: 0 | F89: =ROUND((D89+E89),0) -> 0 | K89: =ROUND((F89-H89+J89),0) -> 0 | M89: 0 | N89: 0 | O89: =ROUND((M89+N89),0) -> 0 | T89: =ROUND((O89-Q89+S89),0) -> 0 | V89: =K89-T89 -> 0 | W89: =IFERROR(V89/T89,0) -> 0
C90: CV Beltraco | D90: 0 | E90: 0 | F90: =ROUND((D90+E90),0) -> 0 | K90: =ROUND((F90-H90+J90),0) -> 0 | M90: 0 | N90: 0 | O90: =ROUND((M90+N90),0) -> 0 | T90: =ROUND((O90-Q90+S90),0) -> 0 | V90: =K90-T90 -> 0 | W90: =IFERROR(V90/T90,0) -> 0
C91: PT Sumatraco Langgeng Abadi | D91: 0 | E91: 0 | F91: =ROUND((D91+E91),0) -> 0 | K91: =ROUND((F91-H91+J91),0) -> 0 | M91: 0 | N91: 0 | O91: =ROUND((M91+N91),0) -> 0 | T91: =ROUND((O91-Q91+S91),0) -> 0 | V91: =K91-T91 -> 0 | W91: =IFERROR(V91/T91,0) -> 0
C92: PT Jodabo Sukses | D92: 0 | E92: 0 | F92: =ROUND((D92+E92),0) -> 0 | K92: =ROUND((F92-H92+J92),0) -> 0 | M92: 0 | N92: 0 | O92: =ROUND((M92+N92),0) -> 0 | T92: =ROUND((O92-Q92+S92),0) -> 0 | V92: =K92-T92 -> 0 | W92: =IFERROR(V92/T92,0) -> 0
B93: ISP | C93: Lima Pendawa, CV | D93: 0 | E93: 22200000 | F93: =ROUND((D93+E93),0) -> 22200000 | K93: =ROUND((F93-H93+J93),0) -> 22200000 | M93: 22200000 | N93: 22200000 | O93: =ROUND((M93+N93),0) -> 44400000 | T93: =ROUND((O93-Q93+S93),0) -> 44400000 | V93: =K93-T93 -> -22200000 | W93: =IFERROR(V93/T93,0) -> -0.5
B94: ISP | C94: NURTANSA MANDIRI, TB | D94: 0 | E94: 0 | F94: =ROUND((D94+E94),0) -> 0 | K94: =ROUND((F94-H94+J94),0) -> 0 | M94: 0 | N94: 0 | O94: =ROUND((M94+N94),0) -> 0 | T94: =ROUND((O94-Q94+S94),0) -> 0 | V94: =K94-T94 -> 0 | W94: =IFERROR(V94/T94,0) -> 0
C95: Indonesia Nisshin Technomic, PT | D95: 0 | E95: 0 | F95: =ROUND((D95+E95),0) -> 0 | K95: =ROUND((F95-H95+J95),0) -> 0 | M95: 0 | N95: 0 | O95: =ROUND((M95+N95),0) -> 0 | T95: =ROUND((O95-Q95+S95),0) -> 0 | V95: =K95-T95 -> 0 | W95: =IFERROR(V95/T95,0) -> 0
C96: Lumina Packaging, PT | D96: 0 | E96: 0 | F96: =ROUND((D96+E96),0) -> 0 | K96: =ROUND((F96-H96+J96),0) -> 0 | M96: 0 | N96: 0 | O96: =ROUND((M96+N96),0) -> 0 | T96: =ROUND((O96-Q96+S96),0) -> 0 | V96: =K96-T96 -> 0 | W96: =IFERROR(V96/T96,0) -> 0
C97: Prima Akuakultur Lestari, PT | D97: 0 | E97: 0 | F97: =ROUND((D97+E97),0) -> 0 | K97: =ROUND((F97-H97+J97),0) -> 0 | M97: 0 | N97: 24990000 | O97: =ROUND((M97+N97),0) -> 24990000 | T97: =ROUND((O97-Q97+S97),0) -> 24990000 | V97: =K97-T97 -> -24990000 | W97: =IFERROR(V97/T97,0) -> -1
C98: Serbaguna Karya Mandiri, CV | D98: 0 | E98: 0 | F98: =ROUND((D98+E98),0) -> 0 | K98: =ROUND((F98-H98+J98),0) -> 0 | M98: 0 | N98: 0 | O98: =ROUND((M98+N98),0) -> 0 | T98: =ROUND((O98-Q98+S98),0) -> 0 | V98: =K98-T98 -> 0 | W98: =IFERROR(V98/T98,0) -> 0
C99: Nusa Jaya | D99: 25502001 | E99: 0 | F99: =ROUND((D99+E99),0) -> 25502001 | K99: =ROUND((F99-H99+J99),0) -> 25502001 | M99: 8980462 | N99: 38172000 | O99: =ROUND((M99+N99),0) -> 47152462 | T99: =ROUND((O99-Q99+S99),0) -> 47152462 | V99: =K99-T99 -> -21650461 | W99: =IFERROR(V99/T99,0) -> -0.45915865
C100: Persahabatan Electric | D100: 0 | E100: 0 | F100: =ROUND((D100+E100),0) -> 0 | K100: =ROUND((F100-H100+J100),0) -> 0 | M100: 11070021 | N100: 0 | O100: =ROUND((M100+N100),0) -> 11070021 | T100: =ROUND((O100-Q100+S100),0) -> 11070021 | V100: =K100-T100 -> -11070021 | W100: =IFERROR(V100/T100,0) -> -1
C101: Sumatra Motor Teknindo, PT | D101: 0 | E101: 0 | F101: =ROUND((D101+E101),0) -> 0 | K101: =ROUND((F101-H101+J101),0) -> 0 | M101: 58393893 | N101: 0 | O101: =ROUND((M101+N101),0) -> 58393893 | T101: =ROUND((O101-Q101+S101),0) -> 58393893 | V101: =K101-T101 -> -58393893 | W101: =IFERROR(V101/T101,0) -> -1
C102: Multi Daya Teknologi Nusantara, PT | D102: 0 | E102: 0 | F102: =ROUND((D102+E102),0) -> 0 | K102: =ROUND((F102-H102+J102),0) -> 0 | M102: 0 | N102: 0 | O102: =ROUND((M102+N102),0) -> 0 | T102: =ROUND((O102-Q102+S102),0) -> 0 | V102: =K102-T102 -> 0 | W102: =IFERROR(V102/T102,0) -> 0
C103: Indoplast Jaya Sukses Makmur, PT | D103: 0 | E103: 0 | F103: =ROUND((D103+E103),0) -> 0 | K103: =ROUND((F103-H103+J103),0) -> 0 | M103: 121624520 | N103: 0 | O103: =ROUND((M103+N103),0) -> 121624520 | T103: =ROUND((O103-Q103+S103),0) -> 121624520 | V103: =K103-T103 -> -121624520 | W103: =IFERROR(V103/T103,0) -> -1
C104: Masatu Putra, CV | D104: 0 | E104: 0 | F104: =ROUND((D104+E104),0) -> 0 | K104: =ROUND((F104-H104+J104),0) -> 0 | M104: 31635000 | N104: 0 | O104: =ROUND((M104+N104),0) -> 31635000 | T104: =ROUND((O104-Q104+S104),0) -> 31635000 | V104: =K104-T104 -> -31635000 | W104: =IFERROR(V104/T104,0) -> -1
B105: ISP | C105: Optimis Group, CV | D105: 0 | E105: 0 | F105: =ROUND((D105+E105),0) -> 0 | K105: =ROUND((F105-H105+J105),0) -> 0 | M105: 0 | N105: -3 | O105: =ROUND((M105+N105),0) -> -3 | T105: =ROUND((O105-Q105+S105),0) -> -3 | V105: =K105-T105 -> 3 | W105: =IFERROR(V105/T105,0) -> -1
B106: ISP | C106: Voltric Jaya Mandiri, PT | D106: 0 | E106: 21978000 | F106: =ROUND((D106+E106),0) -> 21978000 | K106: =ROUND((F106-H106+J106),0) -> 21978000 | M106: 0 | N106: 0 | O106: =ROUND((M106+N106),0) -> 0 | T106: =ROUND((O106-Q106+S106),0) -> 0 | V106: =K106-T106 -> 21978000 | W106: =IFERROR(V106/T106,0) -> 0
...

Sheet G.600 Konfirmasi Induk 2023
B6: Client | C6: : PT Indo American Seafoods Tbk dan Entitas Anak | F6: Prepared by | G6: : LFS | H6: Date : | I6: 45476
B7: Account | C7: : Trade payable | F7: Reviewed by | G7: : FMN | H7: Date : | I7: 45479
B8: Period | C8: : 31 Desember 2023, 2022, dan 2021 | F8: Approved by: | G8: : MGN | H8: Date : | I8: 45483
B9: Matter | C9: : Memo
B11: LIST KONFIRMASI UTANG USAHA (IDR)
B13: Item | C13: Nama | D13: Tanggal Konfirmasi Dikirim | E13: Tanggal Konfirmasi Diterima | F13: Saldo per LK | G13: Saldo per Konfirmasi | H13: Selisih | I13: Dokumen | J13: Telah Didiskusikan dengan Klien/Tim
B14: 1 | C14: Graha Makmur Cipta Pratama | D14: 45331 | E14: 45335 | F14: 1618149192 | G14: 1618150000 | H14: =F14-G14 -> -808
B15: 2 | C15: PT Konverta Mitra Abadi | D15: 45331 | E15: 45338 | F15: 304771930 | G15: 304771919 | H15: =F15-G15 -> 11
B16: 3 | C16: CV Putra Widjaja Marine | D16: 45331 | E16: 45355 | F16: 4355506677 | G16: 5016334672 | H16: =F16-G16 -> -660827995
B17: 4 | C17: Choice Canning Company Income | D17: 45331 | E17: 45355 | F17: 1356603529 | G17: 1356603529 | H17: =F17-G17 -> 0
B18: 5 | C18: PT Indocom Samudra Persada | D18: 45331 | E18: 45357 | F18: 62518053072 | G18: 62518053072 | H18: =F18-G18 -> 0
B19: 6 | C19: PT Indonesia Makan Udang | D19: 45331 | E19: 45357 | F19: 2634498031 | G19: 2634498031 | H19: =F19-G19 -> 0
B20: 7 | C20: PT Indoplast Jaya Sukses Makmur | D20: 45331 | F20: 121624520
B21: 8 | C21: PT International Packaging Manufaktuaring | D21: 45331 | F21: 668830500
B25: LIST KONFIRMASI UTANG USAHA (USD)
B27: Item | C27: Nama | D27: Tanggal Konfirmasi Dikirim | E27: Tanggal Konfirmasi Diterima | F27: Saldo per LK | G27: Saldo per Konfirmasi (USD) | H27: KURS | I27: IDR | J27: Selisih | K27: Dokumen
B28: 1 | C28: Choice Canning Company Income | D28: 45331 | E28: 45341 | F28: 1356603529 | G28: 87999.71 | H28: 15416 | I28: =G28*H28 -> 1.3566035e+09 | J28: =F28-I28 -> -0.36000013

Sheet KONSOL
A2: Aging Utang Usaha Konsol
D3: 45627 | F3: 45536 | H3: 45444 | J3: 2023 | L3: 2022 | N3: 2021 | P3: 2020
B5: Lancar | D5: ='Summary ISP'!D5+'Summay IAS'!E6 -> 2.2146511e+09 | F5: ='Summary ISP'!F5+'Summay IAS'!G6 -> 7.7670721e+09 | H5: ='Summay IAS'!I6+'Summary ISP'!H5 -> #REF! | J5: =#REF!+#REF! -> #REF! | L5: ='Summary ISP'!L5+'Summay IAS'!M6 -> #REF! | N5: ='Summary ISP'!N5+'Summay IAS'!O6 -> #REF! | P5: ='Summary ISP'!P5+'Summay IAS'!Q6 -> 13648880412
B6: 1-30 Hari | D6: ='Summary ISP'!D6+'Summay IAS'!E7 -> 2.1037291e+09 | F6: ='Summary ISP'!F6+'Summay IAS'!G7 -> 2.4155684e+09 | H6: ='Summay IAS'!I7+'Summary ISP'!H6 -> #REF! | J6: =#REF!+#REF! -> #REF! | L6: ='Summary ISP'!L6+'Summay IAS'!M7 -> #REF! | N6: ='Summary ISP'!N6+'Summay IAS'!O7 -> #REF! | P6: ='Summary ISP'!P6+'Summay IAS'!Q7 -> 2376774695
B7: 31-60 Hari | D7: ='Summary ISP'!D7+'Summay IAS'!E8 -> 1073353781 | F7: ='Summary ISP'!F7+'Summay IAS'!G8 -> 198335036 | H7: ='Summay IAS'!I8+'Summary ISP'!H7 -> #REF! | J7: =#REF!+#REF! -> #REF! | L7: ='Summary ISP'!L7+'Summay IAS'!M8 -> #REF! | N7: ='Summary ISP'!N7+'Summay IAS'!O8 -> #REF! | P7: ='Summary ISP'!P7+'Summay IAS'!Q8 -> 1327345930
B8: 61-90 Hari | D8: ='Summary ISP'!D8+'Summay IAS'!E9 -> 92483018 | F8: ='Summary ISP'!F8+'Summay IAS'!G9 -> 90386309 | H8: ='Summay IAS'!I9+'Summary ISP'!H8 -> #REF! | J8: =#REF!+#REF! -> #REF! | L8: ='Summary ISP'!L8+'Summay IAS'!M9 -> #REF! | N8: ='Summary ISP'!N8+'Summay IAS'!O9 -> #REF! | P8: ='Summary ISP'!P8+'Summay IAS'!Q9 -> 641088591 | R8: Utang Pph 28 A (IAS)
B9: > 90 Hari | D9: ='Summary ISP'!D9+'Summay IAS'!E10 -> 220877955 | F9: ='Summary ISP'!F9+'Summay IAS'!G10 -> 1.7373273e+08 | H9: ='Summay IAS'!I10+'Summary ISP'!H9 -> #REF! | J9: =#REF!+#REF!+R9 -> #REF! | L9: ='Summary ISP'!L9+'Summay IAS'!M10 -> #REF! | N9: ='Summary ISP'!N9+'Summay IAS'!O10 -> #REF! | P9: ='Summary ISP'!P9+'Summay IAS'!Q10 -> 143873935 | R9: 451584604
D11: =SUM(D5:D9) -> 5.705095e+09 | F11: =SUM(F5:F9) -> 1.0645095e+10 | H11: =SUM(H5:H9) -> #REF! | J11: =SUM(J5:J9) -> #REF! | L11: =SUM(L5:L9) -> #REF! | N11: =SUM(N5:N9) -> #REF! | P11: =SUM(P5:P9) -> 18137963563
F12: 10645094570 | J12: 19956316532
D13: =D11-D12 -> 5.705095e+09 | F13: =F11-F12 -> -0.16999817 | J13: =J12-J11 -> #REF!
A14: Aging Piutang Usaha Konsol
D15: =D3 -> 45627 | F15: =F3 -> 45536 | H15: =H3 -> 45444 | J15: 2023 | L15: 2022 | N15: 2021 | P15: 2020
B17: Lancar | D17: ='Summary ISP'!D18+'Summay IAS'!E18 -> #REF! | F17: ='Summary ISP'!F18+'Summay IAS'!G18 -> #REF! | H17: ='Summay IAS'!I18+'Summary ISP'!H18 -> #REF! | J17: =#REF!+#REF! -> #REF! | L17: ='Summary ISP'!L18+'Summay IAS'!M18 -> #REF! | N17: ='Summary ISP'!N18+'Summay IAS'!O18 -> #REF! | P17: ='Summary ISP'!P18+'Summay IAS'!Q18 -> #REF!
B18: 1-30 Hari | D18: ='Summary ISP'!D19+'Summay IAS'!E19 -> #REF! | F18: ='Summary ISP'!F19+'Summay IAS'!G19 -> #REF! | H18: ='Summay IAS'!I19+'Summary ISP'!H19 -> #REF! | J18: =#REF!+#REF! -> #REF! | L18: ='Summary ISP'!L19+'Summay IAS'!M19 -> #REF! | N18: ='Summary ISP'!N19+'Summay IAS'!O19 -> #REF! | P18: ='Summary ISP'!P19+'Summay IAS'!Q19 -> #REF!
B19: 31-60 Hari | D19: ='Summary ISP'!D20+'Summay IAS'!E20 -> #REF! | F19: ='Summary ISP'!F20+'Summay IAS'!G20 -> #REF! | H19: ='Summay IAS'!I20+'Summary ISP'!H20 -> #REF! | J19: =#REF!+#REF! -> #REF! | L19: ='Summary ISP'!L20+'Summay IAS'!M20 -> #REF! | N19: ='Summary ISP'!N20+'Summay IAS'!O20 -> #REF! | P19: ='Summary ISP'!P20+'Summay IAS'!Q20 -> #REF!
B20: 61-90 Hari | D20: ='Summary ISP'!D21+'Summay IAS'!E21 -> #REF! | F20: ='Summary ISP'!F21+'Summay IAS'!G21 -> #REF! | H20: ='Summay IAS'!I21+'Summary ISP'!H21 -> #REF! | J20: =#REF!+#REF! -> #REF! | L20: ='Summary ISP'!L21+'Summay IAS'!M21 -> #REF! | N20: ='Summary ISP'!N21+'Summay IAS'!O21 -> #REF! | P20: ='Summary ISP'!P21+'Summay IAS'!Q21 -> #REF!
B21: > 90 Hari | D21: ='Summary ISP'!D22+'Summay IAS'!E22 -> #REF! | F21: ='Summary ISP'!F22+'Summay IAS'!G22 -> #REF! | H21: ='Summay IAS'!I22+'Summary ISP'!H22 -> #REF! | J21: =#REF!+#REF! -> #REF! | L21: ='Summary ISP'!L22+'Summay IAS'!M22 -> #REF! | N21: ='Summary ISP'!N22+'Summay IAS'!O22 -> #REF! | P21: ='Summary ISP'!P22+'Summay IAS'!Q22 -> #REF!
D23: =SUM(D17:D21) -> #REF! | F23: =SUM(F17:F21) -> #REF! | H23: =SUM(H17:H21) -> #REF! | J23: =SUM(J17:J21) -> #REF! | L23: =SUM(L17:L21) -> #REF! | N23: =SUM(N17:N21) -> #REF! | P23: =SUM(P17:P21) -> #REF!
B24: WBS | F24: 39419408952 | H24: 27762015495 | J24: =21754550980-102746 -> 21754448234
B25: CV Kanian | D25: =D23-D24 -> #REF! | F25: =F23-F24 -> #REF! | H25: =H23-H24 -> #REF! | J25: =J23-J24 -> #REF!

Sheet Summary ISP
A2: Aging Utang Usaha
D3: 45627 | F3: 45536 | H3: 45444 | J3: 2023 | L3: 2022 | N3: 2021 | P3: 2020
B5: Lancar | D5: ='Hutang ISP Des 24'!H4 -> 8.8174967e+08 | F5: ='Hutang Usaha ISP Sept 2024'!H$4 -> 4.9834664e+09 | H5: =#REF! -> #REF! | J5: =#REF! -> #REF! | L5: =#REF! -> #REF! | N5: =#REF! -> #REF! | P5: ='[188]Utang Usaha ISP 2020'!K552 -> 7552183808
B6: 1-30 Hari | D6: ='Hutang ISP Des 24'!I4 -> 5.2566013e+08 | F6: ='Hutang Usaha ISP Sept 2024'!I$4 -> 1982303832 | H6: =#REF! -> #REF! | J6: =#REF! -> #REF! | L6: =#REF! -> #REF! | N6: =#REF! -> #REF! | P6: ='[188]Utang Usaha ISP 2020'!L552 -> 1169547930
B7: 31-60 Hari | D7: ='Hutang ISP Des 24'!J4 -> 623745086 | F7: ='Hutang Usaha ISP Sept 2024'!J$4 -> 184180750 | H7: =#REF! -> #REF! | J7: =#REF! -> #REF! | L7: =#REF! -> #REF! | N7: =#REF! -> #REF! | P7: ='[188]Utang Usaha ISP 2020'!M552 -> 265263198
B8: 61-90 Hari | D8: ='Hutang ISP Des 24'!K4 -> 69093320 | F8: ='Hutang Usaha ISP Sept 2024'!K$4 -> 82354849 | H8: =#REF! -> #REF! | J8: =#REF! -> #REF! | L8: =#REF! -> #REF! | N8: =#REF! -> #REF! | P8: ='[188]Utang Usaha ISP 2020'!N552 -> 75373754
B9: > 90 Hari | D9: ='Hutang ISP Des 24'!L4 -> 220877955 | F9: ='Hutang Usaha ISP Sept 2024'!L$4-2.49000072479248 -> 1.5486446e+08 | H9: =#REF!+1.80000019073486 -> #REF! | J9: =#REF! -> #REF! | L9: =#REF! -> #REF! | N9: =#REF! -> #REF! | P9: ='[188]Utang Usaha ISP 2020'!O552+52 -> 143873935
D11: =SUM(D5:D9) -> 2.3211262e+09 | F11: =SUM(F5:F9) -> 7387170280 | H11: =SUM(H5:H9) -> #REF! | J11: =SUM(J5:J9) -> #REF! | L11: =SUM(L5:L9) -> #REF! | N11: =SUM(N5:N9) -> #REF! | P11: =SUM(P5:P9) -> 9206242625
A12: Ctrl WBS | F12: 7387170280 | H12: 6809572845 | J12: =16458420785.62-J11 -> #REF! | L12: =23019876420-L11-759090 -> #REF! | N12: =19763642459-N11-759090 -> #REF! | P12: =9206242625-P11 -> 0
D13: =D11-D12 -> 2.3211262e+09 | F13: =F11-F12 -> 0 | H13: =H11-H12 -> #REF!
A15: Aging Piutang Usaha
D16: =D3 -> 45627 | F16: 45536 | H16: 45444 | J16: 2023 | L16: 2022 | N16: 2021 | P16: 2020
B18: Lancar | D18: =#REF! -> #REF! | F18: =#REF! -> #REF! | H18: =#REF! -> #REF! | J18: =#REF! -> #REF! | L18: =#REF! -> #REF! | N18: =#REF! -> #REF! | P18: =#REF! -> #REF!
B19: 1-30 Hari | D19: =#REF! -> #REF! | F19: =#REF!-0.239997863769531 -> #REF! | H19: =#REF! -> #REF! | J19: =#REF! -> #REF! | L19: =#REF! -> #REF! | N19: =#REF! -> #REF! | P19: =#REF! -> #REF!
B20: 31-60 Hari | D20: =#REF! -> #REF! | H20: =#REF! -> #REF! | J20: =#REF! -> #REF! | L20: =#REF! -> #REF! | N20: =#REF! -> #REF! | P20: =#REF! -> #REF!
B21: 61-90 Hari | D21: =#REF! -> #REF! | H21: =#REF! -> #REF! | J21: =#REF! -> #REF! | L21: =#REF! -> #REF! | N21: =#REF! -> #REF! | P21: =#REF! -> #REF!
B22: > 90 Hari | D22: =#REF! -> #REF! | H22: =#REF! -> #REF! | J22: =#REF! -> #REF! | L22: =#REF! -> #REF! | N22: =#REF! -> #REF! | P22: =#REF!-5.08 -> #REF!
D24: =SUM(D18:D22) -> #REF! | F24: =SUM(F18:F22) -> #REF! | H24: =SUM(H18:H22) -> #REF! | J24: =SUM(J18:J22) -> #REF! | L24: =SUM(L18:L22) -> #REF! | N24: =SUM(N18:N22) -> #REF! | P24: =SUM(P18:P22) -> #REF!
F25: 1.5888229e+10
A26: Ctrl WBS | D26: =D24-D25 -> #REF! | F26: =F24-F25 -> #REF! | J26: =70242197387-J24 -> #REF! | L26: =28760265833.56-L24 -> #REF! | N26: =24987319485.2-N24 -> #REF! | P26: =20131289994 -P24 -> #REF!

Sheet Summay IAS
B3: Aging Utang Usaha
E4: 45627 | G4: 45536 | I4: 45444 | K4: 2023 | M4: 2022 | O4: 2021 | Q4: 2020
C6: Lancar | E6: ='Hutang IAS Des 24'!H4 -> 1332901449 | G6: ='Hutang IAS Sept 24'!H4 -> 2.7836057e+09 | I6: =#REF! -> #REF! | K6: =#REF! -> #REF! | M6: 2552178138 | O6: 2580119628 | Q6: 6096696604
C7: 1-30 Hari | E7: ='Hutang IAS Des 24'!I4 -> 1.578069e+09 | G7: ='Hutang IAS Sept 24'!I$4 -> 4.332646e+08 | I7: =#REF! -> #REF! | K7: =#REF! -> #REF! | M7: 2175564942 | O7: 5103188666 | Q7: 1207226765
C8: 31-60 Hari | E8: ='Hutang IAS Des 24'!J4 -> 449608695 | G8: ='Hutang IAS Sept 24'!J$4 -> 14154286 | I8: =#REF! -> #REF! | K8: =#REF! -> #REF! | M8: 1567526266 | O8: 351492284 | Q8: 1062082732
C9: 61-90 Hari | E9: ='Hutang IAS Des 24'!K4 -> 23389698 | G9: ='Hutang IAS Sept 24'!K$4 -> 8031460 | I9: =#REF! -> #REF! | K9: =#REF! -> #REF! | M9: 224952512 | O9: 454277978 | Q9: 565714837
C10: > 90 Hari | E10: ='Hutang IAS Des 24'!L4 -> 0 | G10: ='Hutang IAS Sept 24'!L$4+0.100000381469727 -> 18868270 | I10: =#REF! -> #REF! | K10: =#REF! -> #REF! | M10: 224952512 | O10: 360998482 | Q10: 0
E12: =SUM(E6:E10) -> 3.3839688e+09 | G12: =SUM(G6:G10) -> 3.2579243e+09 | I12: =SUM(I6:I10) -> #REF! | K12: =SUM(K6:K10) -> #REF! | M12: =SUM(M6:M10) -> 6745174370 | O12: =SUM(O6:O10) -> 8850077038 | Q12: =SUM(Q6:Q10) -> 8931720938
G13: =3257924291-1 -> 3257924290
E14: =E12-E13 -> 3.3839688e+09 | G14: =G12-G13 -> -0.17000008
B15: Aging Piutang Usaha
E16: =E4 -> 45627 | G16: 45536 | I16: 45444 | K16: 2023 | M16: 2022 | O16: 2021 | Q16: 2020
C18: Lancar | E18: =#REF! -> #REF! | G18: =#REF!+0.5 -> #REF! | I18: =#REF! -> #REF! | K18: =#REF! -> #REF! | M18: 0 | O18: 0 | Q18: =#REF! -> #REF!
C19: 1-30 Hari | E19: =#REF! -> #REF! | G19: =#REF! -> #REF! | I19: =#REF! -> #REF! | K19: =#REF! -> #REF! | M19: 5923911096 | O19: 8816275366 | Q19: 2788921952
C20: 31-60 Hari | E20: =#REF! -> #REF! | G20: =#REF! -> #REF! | I20: =#REF! -> #REF! | K20: =#REF! -> #REF! | M20: 24721078650 | O20: 8872293947 | Q20: 19885079001
C21: 61-90 Hari | E21: =#REF! -> #REF! | G21: =#REF! -> #REF! | I21: =#REF! -> #REF! | K21: =#REF! -> #REF! | M21: 6313862115 | O21: 14206236599 | Q21: 378957063
C22: > 90 Hari | E22: =#REF! -> #REF! | G22: =#REF! -> #REF! | I22: =#REF! -> #REF! | K22: =#REF! -> #REF! | M22: 14738580699 | O22: 5093397335 | Q22: 0
E24: =SUM(E18:E22) -> #REF! | G24: =SUM(G18:G22) -> #REF! | I24: =SUM(I18:I22) -> #REF! | K24: =SUM(K18:K22) -> #REF! | M24: =SUM(M18:M22) -> 51697432560 | O24: =SUM(O18:O22) -> 36988203247 | Q24: =SUM(Q18:Q22) -> #REF!
G25: 23871074595 | I25: 11323392105
E26: =E24-E25 -> #REF! | G26: =G24-G25 -> #REF! | I26: =I24-I25 -> #REF!

Sheet Hutang IAS Des 24
A1: Aging Hutang Usaha & Subsequent | B1: =SUM(B3:B4)-B2 -> 0.43000031
A2: PT Indo American Seafoods | B2: 4.3068897e+09 | C2: WBS
A3: 45657
B4: =SUBTOTAL(9,B6:B105) -> 4.3068897e+09 | H4: =SUBTOTAL(9,H6:H90) -> 1332901449 | I4: =SUBTOTAL(9,I6:I90) -> 1.578069e+09 | J4: =SUBTOTAL(9,J6:J90) -> 449608695 | K4: =SUBTOTAL(9,K6:K90) -> 23389698 | L4: =SUBTOTAL(9,L6:L90) -> 0 | M4: =SUM(H4:L4)-B4 -> -9.2292085e+08
A5: Nama | B5: Nominal | C5: No Invoice | D5: Tgl Invoice | E5: Jatuh Tempo | F5: Tgl Jatuh Tempo | G5: Aging | H5: Lancar | I5: 1-30 Hari | J5: 31-60 Hari | K5: 61-90 Hari | L5: >90 Hari
A6: PT Anesta Agung | B6: 284103154 | C6: 1048 | D6: 45649 | E6: 30 | F6: =D6+E6 -> 45679 | G6: =$A$3-F6 -> -22 | H6: =B6 -> 284103154
A7: PT Anesta Agung | B7: 210298296 | C7: 1057 | D7: 45650 | E7: 30 | F7: =D7+E7 -> 45680 | G7: =$A$3-F7 -> -23 | H7: =B7 -> 210298296
A9: PT Konverta Mitra Abadi | B9: 15717156 | C9: 704 | D9: 45572 | E9: 30 | F9: =D9+E9 -> 45602 | G9: =$A$3-F9 -> 55 | J9: =B9 -> 15717156
A10: PT Konverta Mitra Abadi | B10: 84992700 | C10: 719 | D10: 45577 | E10: 30 | F10: =D10+E10 -> 45607 | G10: =$A$3-F10 -> 50 | J10: =B10 -> 84992700
A11: PT Konverta Mitra Abadi | B11: =1403317+12 -> 1403329 | C11: 738 | D11: 45582 | E11: 30 | F11: =D11+E11 -> 45612 | G11: =$A$3-F11 -> 45 | J11: =B11 -> 1403329
A12: PT Konverta Mitra Abadi | B12: 29592600 | C12: 739 | D12: 45582 | E12: 30 | F12: =D12+E12 -> 45612 | G12: =$A$3-F12 -> 45 | J12: =B12 -> 29592600
A13: PT Konverta Mitra Abadi | B13: 48518100 | C13: 743 | D13: 45584 | E13: 30 | F13: =D13+E13 -> 45614 | G13: =$A$3-F13 -> 43 | J13: =B13 -> 48518100
A14: PT Konverta Mitra Abadi | B14: 2752800 | C14: 744 | D14: 45584 | E14: 30 | F14: =D14+E14 -> 45614 | G14: =$A$3-F14 -> 43 | J14: =B14 -> 2752800
A15: PT Konverta Mitra Abadi | B15: 4129200 | C15: 747 | D15: 45586 | E15: 30 | F15: =D15+E15 -> 45616 | G15: =$A$3-F15 -> 41 | J15: =B15 -> 4129200
A16: PT Konverta Mitra Abadi | B16: 1455432 | C16: 748 | D16: 45586 | E16: 30 | F16: =D16+E16 -> 45616 | G16: =$A$3-F16 -> 41 | J16: =B16 -> 1455432
A17: PT Konverta Mitra Abadi | B17: 46825905 | C17: 760 | D17: 45588 | E17: 30 | F17: =D17+E17 -> 45618 | G17: =$A$3-F17 -> 39 | J17: =B17 -> 46825905
A18: PT Konverta Mitra Abadi | B18: 13382604 | C18: 866 | D18: 45621 | E18: 30 | F18: =D18+E18 -> 45651 | G18: =$A$3-F18 -> 6 | I18: =B18 -> 13382604
A19: PT Konverta Mitra Abadi | B19: 5017477 | C19: 867 | D19: 45621 | E19: 30 | F19: =D19+E19 -> 45651 | G19: =$A$3-F19 -> 6 | I19: =B19 -> 5017477
A20: PT Konverta Mitra Abadi | B20: 8559432 | C20: 868 | D20: 45621 | E20: 30 | F20: =D20+E20 -> 45651 | G20: =$A$3-F20 -> 6 | I20: =B20 -> 8559432
A21: PT Konverta Mitra Abadi | B21: 5839809.9 | C21: 869 | D21: 45621 | E21: 30 | F21: =D21+E21 -> 45651 | G21: =$A$3-F21 -> 6 | I21: =B21 -> 5839809.9
A22: PT Konverta Mitra Abadi | B22: 4856250 | C22: 870 | D22: 45621 | E22: 30 | F22: =D22+E22 -> 45651 | G22: =$A$3-F22 -> 6 | I22: =B22 -> 4856250
A23: PT Konverta Mitra Abadi | B23: 4944184 | C23: 871 | D23: 45621 | E23: 30 | F23: =D23+E23 -> 45651 | G23: =$A$3-F23 -> 6 | I23: =B23 -> 4944184
A24: PT Konverta Mitra Abadi | B24: 2593670 | C24: 895 | D24: 45631 | E24: 30 | F24: =D24+E24 -> 45661 | G24: =$A$3-F24 -> -4 | H24: =B24 -> 2593670
A25: PT Konverta Mitra Abadi | B25: 47416980 | C25: 939 | D25: 45655 | E25: 30 | F25: =D25+E25 -> 45685 | G25: =$A$3-F25 -> -28 | H25: =B25 -> 47416980
A26: PT Konverta Mitra Abadi | B26: 5011650 | C26: 940 | D26: 45655 | E26: 30 | F26: =D26+E26 -> 45685 | G26: =$A$3-F26 -> -28 | H26: =B26 -> 5011650
A27: PT Konverta Mitra Abadi | B27: 5137524 | C27: 941 | D27: 45655 | E27: 30 | F27: =D27+E27 -> 45685 | G27: =$A$3-F27 -> -28 | H27: =B27 -> 5137524
A29: PT Sumber Energy | B29: 31635000 | C29: 819 | D29: 45598 | E29: 30 | F29: =D29+E29 -> 45628 | G29: =$A$3-F29 -> 29 | I29: =B29 -> 31635000
A31: PT Indonesia Makan Udang | B31: 263573280 | C31: 991 | D31: 45644 | E31: 30 | F31: =D31+E31 -> 45674 | G31: =$A$3-F31 -> -17 | H31: =B31 -> 263573280
A32: PT Indonesia Makan Udang | B32: 195716165 | C32: 990 | D32: 45644 | E32: 30 | F32: =D32+E32 -> 45674 | G32: =$A$3-F32 -> -17 | H32: =B32 -> 195716165
A33: PT Indonesia Makan Udang | B33: 258146422 | C33: 989 | D33: 45644 | E33: 30 | F33: =D33+E33 -> 45674 | G33: =$A$3-F33 -> -17 | H33: =B33 -> 258146422
A34: PT Indonesia Makan Udang | B34: 97381200 | C34: 948 | D34: 45619 | E34: 30 | F34: =D34+E34 -> 45649 | G34: =$A$3-F34 -> 8 | I34: =B34 -> 97381200
A35: PT Indonesia Makan Udang | B35: 133422750 | C35: 943 | D35: 45618 | E35: 30 | F35: =D35+E35 -> 45648 | G35: =$A$3-F35 -> 9 | I35: =B35 -> 133422750
A36: PT Indonesia Makan Udang | B36: 259527644 | C36: 897 | D36: 45608 | E36: 30 | F36: =D36+E36 -> 45638 | G36: =$A$3-F36 -> 19 | I36: =B36 -> 259527644
A37: PT Indonesia Makan Udang | B37: 369633462 | C37: 851 | D37: 45598 | E37: 30 | F37: =D37+E37 -> 45628 | G37: =$A$3-F37 -> 29 | I37: =B37 -> 369633462
A38: PT Indonesia Makan Udang | B38: 289827482 | C38: 847 | D38: 45597 | E38: 30 | F38: =D38+E38 -> 45627 | G38: =$A$3-F38 -> 30 | I38: =B38 -> 289827482
A39: PT Indonesia Makan Udang | B39: 69901783 | C39: 813 | D39: 45591 | E39: 30 | F39: =D39+E39 -> 45621 | G39: =$A$3-F39 -> 36 | J39: =B39 -> 69901783
A40: PT Indonesia Makan Udang | B40: 132927190 | C40: 805 | D40: 45590 | E40: 30 | F40: =D40+E40 -> 45620 | G40: =$A$3-F40 -> 37 | J40: =B40 -> 132927190
A43: PT Sinergy Indopack Makmur | B43: 23976000 | C43: 859 | D43: 45618 | E43: 30 | F43: =D43+E43 -> 45648 | G43: =$A$3-F43 -> 9 | I43: =B43 -> 23976000
A44: PT Sinergy Indopack Makmur | B44: 23976000 | C44: 860 | D44: 45618 | E44: 30 | F44: =D44+E44 -> 45648 | G44: =$A$3-F44 -> 9 | I44: =B44 -> 23976000
A45: PT Sinergy Indopack Makmur | B45: 11188800 | C45: 908 | D45: 45635 | E45: 30 | F45: =D45+E45 -> 45665 | G45: =$A$3-F45 -> -8 | H45: =B45 -> 11188800
A47: Prima Sari Indotama, PT | B47: 3018928 | C47: 3527 | D47: 45653 | E47: 30 | F47: =D47+E47 -> 45683 | G47: =$A$3-F47 -> -26 | H47: =B47 -> 3018928
A48: Prima Sari Indotama, PT | B48: =2968625-538843 -> 2429782 | C48: 3287 | D48: 45627 | E48: 30 | F48: =D48+E48 -> 45657 | G48: =$A$3-F48 -> 0 | H48: =B48 -> 2429782
A49: Prima Sari Indotama, PT | B49: 26987500 | C49: 3226 | D49: 45624 | E49: 30 | F49: =D49+E49 -> 45654 | G49: =$A$3-F49 -> 3 | I49: =B49 -> 26987500
A51: Sumatraco Langgeng Abadi, PT | B51: 20535000 | C51: 828 | D51: 45610 | E51: 30 | F51: =D51+E51 -> 45640 | G51: =$A$3-F51 -> 17 | I51: =B51 -> 20535000
A53: Nusa Jaya | B53: 1200000 | C53: 637 | D53: 45548 | E53: 30 | F53: =D53+E53 -> 45578 | G53: =$A$3-F53 -> 79 | K53: =B53 -> 1200000
A54: Nusa Jaya | B54: 825000 | C54: 746 | D54: 45586 | E54: 30 | F54: =D54+E54 -> 45616 | G54: =$A$3-F54 -> 41 | J54: =B54 -> 825000
A55: Nusa Jaya | B55: 3363500 | C55: 759 | D55: 45588 | E55: 30 | F55: =D55+E55 -> 45618 | G55: =$A$3-F55 -> 39 | J55: =B55 -> 3363500
A56: Nusa Jaya | B56: 4864000 | C56: 766 | D56: 45589 | E56: 30 | F56: =D56+E56 -> 45619 | G56: =$A$3-F56 -> 38 | J56: =B56 -> 4864000
A57: Nusa Jaya | B57: 2340000 | C57: 776 | D57: 45594 | E57: 30 | F57: =D57+E57 -> 45624 | G57: =$A$3-F57 -> 33 | J57: =B57 -> 2340000
A58: Nusa Jaya | B58: 1600000 | C58: 781 | D58: 45597 | E58: 30 | F58: =D58+E58 -> 45627 | G58: =$A$3-F58 -> 30 | I58: =B58 -> 1600000
A59: Nusa Jaya | B59: =850500-1500 -> 849000 | C59: 793 | D59: 45601 | E59: 30 | F59: =D59+E59 -> 45631 | G59: =$A$3-F59 -> 26 | I59: =B59 -> 849000
A60: Nusa Jaya | B60: 2280000 | C60: 818 | D60: 45608 | E60: 30 | F60: =D60+E60 -> 45638 | G60: =$A$3-F60 -> 19 | I60: =B60 -> 2280000
A61: Nusa Jaya | B61: 640000 | C61: 834 | D61: 45611 | E61: 30 | F61: =D61+E61 -> 45641 | G61: =$A$3-F61 -> 16 | I61: =B61 -> 640000
A62: Nusa Jaya | B62: 1540000 | C62: 835 | D62: 45611 | E62: 30 | F62: =D62+E62 -> 45641 | G62: =$A$3-F62 -> 16 | I62: =B62 -> 1540000
A63: Nusa Jaya | B63: 1600000 | C63: 841 | D63: 45615 | E63: 30 | F63: =D63+E63 -> 45645 | G63: =$A$3-F63 -> 12 | I63: =B63 -> 1600000
A64: Nusa Jaya | B64: 580000 | C64: 842 | D64: 45615 | E64: 30 | F64: =D64+E64 -> 45645 | G64: =$A$3-F64 -> 12 | I64: =B64 -> 580000
A65: Nusa Jaya | B65: 718000 | C65: 844 | D65: 45615 | E65: 30 | F65: =D65+E65 -> 45645 | G65: =$A$3-F65 -> 12 | I65: =B65 -> 718000
A66: Nusa Jaya | B66: 1005000 | C66: 885 | D66: 45626 | E66: 30 | F66: =D66+E66 -> 45656 | G66: =$A$3-F66 -> 1 | I66: =B66 -> 1005000
A67: Nusa Jaya | B67: 1342500 | C67: 892 | D67: 45629 | E67: 30 | F67: =D67+E67 -> 45659 | G67: =$A$3-F67 -> -2 | H67: =B67 -> 1342500
A68: Nusa Jaya | B68: 105000 | C68: 915 | D68: 45637 | E68: 30 | F68: =D68+E68 -> 45667 | G68: =$A$3-F68 -> -10 | H68: =B68 -> 105000
A69: Nusa Jaya | B69: 350000 | C69: 927 | D69: 45643 | E69: 30 | F69: =D69+E69 -> 45673 | G69: =$A$3-F69 -> -16 | H69: =B69 -> 350000
A70: Nusa Jaya | B70: 300000 | C70: 931 | D70: 45646 | E70: 30 | F70: =D70+E70 -> 45676 | G70: =$A$3-F70 -> -19 | H70: =B70 -> 300000
A72: Sumatra Motor Teknindo, PT | B72: 596070 | C72: 956 | D72: 45657 | E72: 30 | F72: =D72+E72 -> 45687 | G72: =$A$3-F72 -> -30 | H72: =B72 -> 596070
A73: Sumatra Motor Teknindo, PT | B73: 188700 | C73: 955 | D73: 45657 | E73: 30 | F73: =D73+E73 -> 45687 | G73: =$A$3-F73 -> -30 | H73: =B73 -> 188700
A74: Sumatra Motor Teknindo, PT | B74: 421800 | C74: 931 | D74: 45643 | E74: 30 | F74: =D74+E74 -> 45673 | G74: =$A$3-F74 -> -16 | H74: =B74 -> 421800
A75: Sumatra Motor Teknindo, PT | B75: 255300 | C75: 922 | D75: 45637 | E75: 30 | F75: =D75+E75 -> 45667 | G75: =$A$3-F75 -> -10 | H75: =B75 -> 255300
A76: Sumatra Motor Teknindo, PT | B76: 16183800 | C76: 890 | D76: 45629 | E76: 30 | F76: =D76+E76 -> 45659 | G76: =$A$3-F76 -> -2 | H76: =B76 -> 16183800
A78: Dinamika Lubsindo Utama, PT | B78: 11094848 | C78: 952 | D78: 45656 | E78: 30 | F78: =D78+E78 -> 45686 | G78: =$A$3-F78 -> -29 | H78: =B78 -> 11094848 | M78: TBC
A79: Dinamika Lubsindo Utama, PT | B79: 11094849 | C79: 812 | D79: 45607 | E79: 30 | F79: =D79+E79 -> 45637 | G79: =$A$3-F79 -> 20 | I79: =B79 -> 11094849
A80: Dinamika Lubsindo Utama, PT | B80: 11094849 | C80: 681 | D80: 45560 | E80: 30 | F80: =D80+E80 -> 45590 | G80: =$A$3-F80 -> 67 | K80: =B80 -> 11094849
A81: Dinamika Lubsindo Utama, PT | B81: 11094849 | C81: 635 | D81: 45547 | E81: 30 | F81: =D81+E81 -> 45577 | G81: =$A$3-F81 -> 80 | K81: =B81 -> 11094849
A84: Maju Tambak Sumur, PT | B84: 1.9958524e+08 | C84: 962 | D84: 45624 | E84: 30 | F84: =D84+E84 -> 45654 | G84: =$A$3-F84 -> 3 | I84: =B84 -> 1.9958524e+08
A86: Indolabel Surya Pratama, PT | B86: 10509480 | C86: 831 | D86: 45611 | E86: 30 | F86: =D86+E86 -> 45641 | G86: =$A$3-F86 -> 16 | I86: =B86 -> 10509480
A87: Indolabel Surya Pratama, PT | B87: 16056150 | C87: 832 | D87: 45611 | E87: 30 | F87: =D87+E87 -> 45641 | G87: =$A$3-F87 -> 16 | I87: =B87 -> 16056150
A88: Indolabel Surya Pratama, PT | B88: 10509480 | C88: 843 | D88: 45615 | E88: 30 | F88: =D88+E88 -> 45645 | G88: =$A$3-F88 -> 12 | I88: =B88 -> 10509480
A89: Indolabel Surya Pratama, PT | B89: 8174040 | C89: 904 | D89: 45633 | E89: 30 | F89: =D89+E89 -> 45663 | G89: =$A$3-F89 -> -6 | H89: =B89 -> 8174040
A90: Indolabel Surya Pratama, PT | B90: 5254740 | C90: 912 | D90: 45637 | E90: 30 | F90: =D90+E90 -> 45667 | G90: =$A$3-F90 -> -10 | H90: =B90 -> 5254740
A91: Indolabel Surya Pratama, PT | B91: 20727030 | C91: 934 | D91: 45650 | E91: 30 | F91: =D91+E91 -> 45680 | G91: =$A$3-F91 -> -23 | H91: =B91 -> 20727030
A93: Mida Trade Ventures Indonesia, PT | B93: 27283556 | C93: 3470 | D93: 45647 | E93: 30 | F93: =D93+E93 -> 45677 | G93: =$A$3-F93 -> -20 | H93: =B93 -> 27283556
A94: Mida Trade Ventures Indonesia, PT | B94: 27551908 | C94: 3520 | D94: 45656 | E94: 30 | F94: =D94+E94 -> 45686 | G94: =$A$3-F94 -> -29 | H94: =B94 -> 27551908
A96: Sion Vannamei Raharja, CV | B96: 333500475 | C96: 983 | D96: 45643 | E96: 30 | F96: =D96+E96 -> 45673 | G96: =$A$3-F96 -> -16 | H96: =B96 -> 333500475
A97: Sion Vannamei Raharja, CV | B97: 315048300 | C97: 988 | D97: 45644 | E97: 30 | F97: =D97+E97 -> 45674 | G97: =$A$3-F97 -> -17 | H97: =B97 -> 315048300
A99: Sri Rejeki, CV | B99: 5993112 | C99: 854 | D99: 45617 | E99: 30 | F99: =D99+E99 -> 45647 | G99: =$A$3-F99 -> 10 | I99: =B99 -> 5993112
A100: Sri Rejeki, CV | B100: 11604107 | C100: 858 | D100: 45618 | E100: 30 | F100: =D100+E100 -> 45648 | G100: =$A$3-F100 -> 9 | I100: =B100 -> 11604107
A101: Sri Rejeki, CV | B101: 5134527 | C101: 879 | D101: 45624 | E101: 30 | F101: =D101+E101 -> 45654 | G101: =$A$3-F101 -> 3 | I101: =B101 -> 5134527
A102: Sri Rejeki, CV | B102: 4937337 | C102: 933 | D102: 45649 | E102: 30 | F102: =D102+E102 -> 45679 | G102: =$A$3-F102 -> -22 | H102: =B102 -> 4937337
A103: Sri Rejeki, CV | B103: 1730000 | C103: 535 | D103: 45348 | E103: 30 | F103: =D103+E103 -> 45378 | G103: =$A$3-F103 -> 279 | L103: =B103 -> 1730000
A105: Lain-lain (masing-masing di bawah Rp 20.000.000) | B105: 169410500 | I105: =B105 -> 169410500

Sheet Hutang ISP Des 24
A1: Aging Hutang Usaha & Subsequent
A2: PT Indokom Samudra Persada | B2: =B3-B4 -> -0.46000004
A3: 45657 | B3: 2321126163 | C3: WBS
B4: =SUBTOTAL(9,B6:B78) -> 2.3211262e+09 | H4: =SUBTOTAL(9,H6:H78) -> 8.8174967e+08 | I4: =SUBTOTAL(9,I6:I78) -> 5.2566013e+08 | J4: =SUBTOTAL(9,J6:J78) -> 623745086 | K4: =SUBTOTAL(9,K6:K78) -> 69093320 | L4: =SUBTOTAL(9,L6:L78) -> 220877955 | M4: =SUM(H4:L4)-B4 -> 0
A5: Nama | B5: Nominal | C5: No Invoice | D5: Tgl Invoice | E5: Jatuh Tempo | F5: Tgl Jatuh Tempo | G5: Aging | H5: Lancar | I5: 1-30 Hari | J5: 31-60 Hari | K5: 61-90 Hari | L5: >90 Hari
A6: Bapak Cipto | B6: 19544752 | I6: =B6 -> 19544752
A8: AGS Sejahtera, CV, | B8: 22904000 | C8: 18 | D8: 45566 | E8: 30 | F8: =D8+E8 -> 45596 | G8: =$A$3-F8 -> 61 | K8: =B8 -> 22904000
A9: AGS Sejahtera, CV, | B9: 17115800 | C9: 23 | D9: 45640 | E9: 30 | F9: =D9+E9 -> 45670 | G9: =$A$3-F9 -> -13 | H9: =B9 -> 17115800
A11: Halim Sakti Pratama, PT | B11: 13506480 | C11: 36 | D11: 45553 | E11: 30 | F11: =D11+E11 -> 45583 | G11: =$A$3-F11 -> 74 | K11: =B11 -> 13506480
A13: Intiragam Oliefindo, PT | B13: 24975000 | C13: 397 | D13: 45546 | E13: 30 | F13: =D13+E13 -> 45576 | G13: =$A$3-F13 -> 81 | K13: =B13 -> 24975000
A15: Konverta Mitra Abadi, PT | B15: 7707840 | C15: 518 | D15: 45586 | E15: 30 | F15: =D15+E15 -> 45616 | G15: =$A$3-F15 -> 41 | K15: =B15 -> 7707840
A16: Konverta Mitra Abadi, PT | B16: 9145290 | C16: 529 | D16: 45593 | E16: 30 | F16: =D16+E16 -> 45623 | G16: =$A$3-F16 -> 34 | J16: =B16 -> 9145290
A17: Konverta Mitra Abadi, PT | B17: 23742900 | C17: 540 | D17: 45597 | E17: 30 | F17: =D17+E17 -> 45627 | G17: =$A$3-F17 -> 30 | I17: =B17 -> 23742900
A18: Konverta Mitra Abadi, PT | B18: 5505600 | C18: 602 | D18: 45621 | E18: 30 | F18: =D18+E18 -> 45651 | G18: =$A$3-F18 -> 6 | I18: =B18 -> 5505600
A19: Konverta Mitra Abadi, PT | B19: =1340325-408848 -> 931477 | C19: 603 | D19: 45621 | E19: 30 | F19: =D19+E19 -> 45651 | G19: =$A$3-F19 -> 6 | I19: =B19 -> 931477
A20: Konverta Mitra Abadi, PT | B20: 8286705 | C20: 605 | D20: 45621 | E20: 30 | F20: =D20+E20 -> 45651 | G20: =$A$3-F20 -> 6 | I20: =B20 -> 8286705
A21: Konverta Mitra Abadi, PT | B21: 10217938 | C21: 606 | D21: 45621 | E21: 30 | F21: =D21+E21 -> 45651 | G21: =$A$3-F21 -> 6 | I21: =B21 -> 10217938
A22: Konverta Mitra Abadi, PT | B22: 16350566 | C22: 607 | D22: 45621 | E22: 30 | F22: =D22+E22 -> 45651 | G22: =$A$3-F22 -> 6 | I22: =B22 -> 16350566
A23: Konverta Mitra Abadi, PT | B23: 6643350 | C23: 608 | D23: 45621 | E23: 30 | F23: =D23+E23 -> 45651 | G23: =$A$3-F23 -> 6 | I23: =B23 -> 6643350
A24: Konverta Mitra Abadi, PT | B24: 8974350 | C24: 609 | D24: 45621 | E24: 30 | F24: =D24+E24 -> 45651 | G24: =$A$3-F24 -> 6 | I24: =B24 -> 8974350
A25: Konverta Mitra Abadi, PT | B25: 8974350 | C25: 610 | D25: 45621 | E25: 30 | F25: =D25+E25 -> 45651 | G25: =$A$3-F25 -> 6 | I25: =B25 -> 8974350
A26: Konverta Mitra Abadi, PT | B26: 3869404 | C26: 611 | D26: 45621 | E26: 30 | F26: =D26+E26 -> 45651 | G26: =$A$3-F26 -> 6 | I26: =B26 -> 3869404
A27: Konverta Mitra Abadi, PT | B27: 8602500 | C27: 616 | D27: 45624 | E27: 30 | F27: =D27+E27 -> 45654 | G27: =$A$3-F27 -> 3 | I27: =B27 -> 8602500
A28: Konverta Mitra Abadi, PT | B28: 6959700 | C28: 620 | D28: 45628 | E28: 30 | F28: =D28+E28 -> 45658 | G28: =$A$3-F28 -> -1 | H28: =B28 -> 6959700
A29: Konverta Mitra Abadi, PT | B29: 23742900 | C29: 654 | D29: 45639 | E29: 30 | F29: =D29+E29 -> 45669 | G29: =$A$3-F29 -> -12 | H29: =B29 -> 23742900
A30: Konverta Mitra Abadi, PT | B30: 7776660 | C30: 655 | D30: 45639 | E30: 30 | F30: =D30+E30 -> 45669 | G30: =$A$3-F30 -> -12 | H30: =B30 -> 7776660
A31: Konverta Mitra Abadi, PT | B31: 2408700 | C31: 656 | D31: 45639 | E31: 30 | F31: =D31+E31 -> 45669 | G31: =$A$3-F31 -> -12 | H31: =B31 -> 2408700
A32: Konverta Mitra Abadi, PT | B32: 2381172 | C32: 658 | D32: 45639 | E32: 30 | F32: =D32+E32 -> 45669 | G32: =$A$3-F32 -> -12 | H32: =B32 -> 2381172
A33: Konverta Mitra Abadi, PT | B33: 2340990 | C33: 659 | D33: 45639 | E33: 30 | F33: =D33+E33 -> 45669 | G33: =$A$3-F33 -> -12 | H33: =B33 -> 2340990
A35: Lima Pendawa, CV | B35: 22200000 | C35: 657 | D35: 45639 | E35: 30 | F35: =D35+E35 -> 45669 | G35: =$A$3-F35 -> -12 | H35: =B35 -> 22200000
A37: Seven Mountain Internasional, PT | B37: 13098000 | C37: 601 | D37: 45621 | E37: 30 | F37: =D37+E37 -> 45651 | G37: =$A$3-F37 -> 6 | I37: =B37 -> 13098000
A38: Seven Mountain Internasional, PT | B38: 16761000 | C38: 664 | D38: 45642 | E38: 30 | F38: =D38+E38 -> 45672 | G38: =$A$3-F38 -> -15 | H38: =B38 -> 16761000
A40: Sinar Setia Mulia , PT | B40: 13470000 | C40: 43 | D40: 45604 | E40: 30 | F40: =D40+E40 -> 45634 | G40: =$A$3-F40 -> 23 | I40: =B40 -> 13470000
A41: Sinar Setia Mulia , PT | B41: 960000 | C41: 44 | D41: 45604 | E41: 30 | F41: =D41+E41 -> 45634 | G41: =$A$3-F41 -> 23 | I41: =B41 -> 960000
A42: Sinar Setia Mulia , PT | B42: 40800000 | C42: 46 | D42: 45611 | E42: 30 | F42: =D42+E42 -> 45641 | G42: =$A$3-F42 -> 16 | I42: =B42 -> 40800000
A44: Sumber Energy, PT | B44: 31635000 | C44: 579 | D44: 45614 | E44: 30 | F44: =D44+E44 -> 45644 | G44: =$A$3-F44 -> 13 | I44: =B44 -> 31635000
A46: Prima Larvae, PT | B46: 25704000 | C46: 575 | D46: 45637 | E46: 30 | F46: =D46+E46 -> 45667 | G46: =$A$3-F46 -> -10 | H46: =B46 -> 25704000
A47: Prima Larvae, PT | B47: 28800000 | C47: 607 | D47: 45656 | E47: 30 | F47: =D47+E47 -> 45686 | G47: =$A$3-F47 -> -29 | H47: =B47 -> 28800000
A49: Sumatra Motor Teknindo, PT | B49: 34791785 | I49: =B49 -> 34791785
A51: International Packaging M, (IPM), PT | B51: 971250 | L51: =B51 -> 971250 | M51: Info Manajemen angka ini sudah sesuai untuk LK 24 (04.02.2025)
A53: SUMBERDAYA SINAR BARU, PT | B53: 21612870 | C53: 618 | D53: 45657 | E53: 30 | F53: =D53+E53 -> 45687 | G53: =$A$3-F53 -> -30 | H53: =B53 -> 21612870
A54: SUMBERDAYA SINAR BARU, PT | B54: 12076100 | C54: 617 | D54: 45657 | E54: 30 | F54: =D54+E54 -> 45687 | G54: =$A$3-F54 -> -30 | H54: =B54 -> 12076100
A55: SUMBERDAYA SINAR BARU, PT | B55: 21677040 | C55: 567 | D55: 45629 | E55: 30 | F55: =D55+E55 -> 45659 | G55: =$A$3-F55 -> -2 | H55: =B55 -> 21677040
A57: Voltric Jaya Mandiri, PT | B57: 5716500 | C57: 480 | D57: 45575 | E57: 30 | F57: =D57+E57 -> 45605 | G57: =$A$3-F57 -> 52 | J57: =B57 -> 5716500
A58: Voltric Jaya Mandiri, PT | B58: 610500 | C58: 42 | D58: 45597 | E58: 30 | F58: =D58+E58 -> 45627 | G58: =$A$3-F58 -> 30 | I58: =B58 -> 610500
A59: Voltric Jaya Mandiri, PT | B59: 15651000 | C59: 538 | D59: 45597 | E59: 30 | F59: =D59+E59 -> 45627 | G59: =$A$3-F59 -> 30 | I59: =B59 -> 15651000
A61: Suranto | B61: 61090000 | C61: 599 | D61: 45650 | E61: 30 | F61: =D61+E61 -> 45680 | G61: =$A$3-F61 -> -23 | H61: =B61 -> 61090000
A63: Anesta Agung, PT | B63: 262620170 | C63: 633 | D63: 45652 | E63: 30 | F63: =D63+E63 -> 45682 | G63: =$A$3-F63 -> -25 | H63: =B63 -> 262620170
A64: Anesta Agung, PT | B64: 135545234 | C64: 626 | D64: 45650 | E64: 30 | F64: =D64+E64 -> 45680 | G64: =$A$3-F64 -> -23 | H64: =B64 -> 135545234
A66: Delos Rantai Maritim PT | B66: 2102768.2 | C66: 3379 | D66: 45632 | E66: 30 | F66: =D66+E66 -> 45662 | G66: =$A$3-F66 -> -5 | H66: =B66 -> 2102768.2
A68: Indonesia Makan Udang PT | B68: 208834566 | C68: 593 | D68: 45638 | E68: 30 | F68: =D68+E68 -> 45668 | G68: =$A$3-F68 -> -11 | H68: =B68 -> 208834566
A69: Indonesia Makan Udang PT | B69: 80983867 | C69: 522 | D69: 45593 | E69: 30 | F69: =D69+E69 -> 45623 | G69: =$A$3-F69 -> 34 | J69: =B69 -> 80983867
A70: Indonesia Makan Udang PT | B70: 214996197 | C70: 520 | D70: 45593 | E70: 30 | F70: =D70+E70 -> 45623 | G70: =$A$3-F70 -> 34 | J70: =B70 -> 214996197
A71: Indonesia Makan Udang PT | B71: 70068807 | C71: 516 | D71: 45591 | E71: 30 | F71: =D71+E71 -> 45621 | G71: =$A$3-F71 -> 36 | J71: =B71 -> 70068807
A72: Indonesia Makan Udang PT | B72: 242834425 | C72: 511 | D72: 45590 | E72: 30 | F72: =D72+E72 -> 45620 | G72: =$A$3-F72 -> 37 | J72: =B72 -> 242834425
A74: Multidaya Teknologi Nusantara PT | B74: 210906705 | L74: =B74 -> 210906705 | M74: Info Manajemen angka ini sudah sesuai untuk LK 24 - per 2025 sudah mulai dicicil dan akan selesai (04.02.2025)
A76: Nutritek Pratama Indonesia, PT | B76: 9000000 | L76: =B76 -> 9000000 | M76: Info Manajemen angka ini sudah sesuai untuk LK 24 (04.02.2025)
A78: Lain-lain (masing-masing di bawah Rp 20.000.000) | B78: =252999942+13 -> 252999955 | I78: =B78 -> 252999955
A81: PT Indo American Seafoods | B81: =8079657361-SUM(B82:B150) -> 2.6539202e+09
A82: PT Indo American Seafoods | B82: 15684827 | C82: 22 | D82: 45328 | E82: 30
A83: PT Indo American Seafoods | B83: 17212340 | C83: 23 | D83: 45337 | E83: 30
A84: PT Indo American Seafoods | B84: 5253259.6 | C84: 24 | D84: 45358 | E84: 30
A85: PT Indo American Seafoods | B85: 13964904 | C85: 35 | D85: 45359 | E85: 30
A86: PT Indo American Seafoods | B86: 1.4978491e+08 | C86: 26 | D86: 45359 | E86: 30
A87: PT Indo American Seafoods | B87: 7563972.8 | C87: 27 | D87: 45363 | E87: 30
A88: PT Indo American Seafoods | B88: 50237588 | C88: 28 | D88: 45369 | E88: 30
A89: PT Indo American Seafoods | B89: 69871628 | C89: 31 | D89: 45370 | E89: 30
A90: PT Indo American Seafoods | B90: 1.618199e+08 | C90: 29 | D90: 45370 | E90: 30
A91: PT Indo American Seafoods | B91: 1.618199e+08 | C91: 30 | D91: 45370 | E91: 30
A92: PT Indo American Seafoods | B92: 39275303 | C92: 32 | D92: 45371 | E92: 30
A93: PT Indo American Seafoods | B93: 50843861 | C93: 33 | D93: 45373 | E93: 30
... A95: PT Indo American Seafoods | B95: 32465954 | C95: 75 | D95: 45474 | E95: 30
A96: PT Indo American Seafoods | B96: 52470000 | D96: 45518 | E96: 30
A97: PT Indo American Seafoods | B97: 31700000 | D97: 45518 | E97: 30
A98: PT Indo American Seafoods | B98: 31700000 | D98: 45518 | E98: 30
A99: PT Indo American Seafoods | B99: 31700000 | D99: 45518 | E99: 30
A100: PT Indo American Seafoods | B100: 77500000 | D100: 45518 | E100: 30
A101: PT Indo American Seafoods | B101: 46500000 | D101: 45520 | E101: 30
A102: PT Indo American Seafoods | B102: 62000000 | D102: 45520 | E102: 30
A103: PT Indo American Seafoods | B103: 39125000 | D103: 45527 | E103: 30
A104: PT Indo American Seafoods | B104: 77500000 | D104: 45530 | E104: 30
A105: PT Indo American Seafoods | B105: 77500000 | D105: 45530 | E105: 30
A106: PT Indo American Seafoods | B106: 38950000 | D106: 45530 | E106: 30
A107: PT Indo American Seafoods | B107: 63600000 | D107: 45530 | E107: 30
... A118: PT Indo American Seafoods | B118: 79325000 | D118: 45548 | E118: 30
A119: PT Indo American Seafoods | B119: 1.2488194e+08 | C119: 95 | D119: 45569 | E119: 30
A120: PT Indo American Seafoods | B120: 18376876 | C120: 96 | D120: 45582 | E120: 30
A121: PT Indo American Seafoods | B121: 57706367 | C121: 97 | D121: 45583 | E121: 30
A122: PT Indo American Seafoods | B122: 19078839 | C122: 98 | D122: 45590 | E122: 30
A123: PT Indo American Seafoods | B123: 75708395 | C123: 99 | D123: 45591 | E123: 30
A124: PT Indo American Seafoods | B124: 1.4929074e+08 | C124: 102 | D124: 45597 | E124: 30
A125: PT Indo American Seafoods | B125: 1.6720725e+08 | C125: 101 | D125: 45597 | E125: 30
A126: PT Indo American Seafoods | B126: 73283676 | C126: 100 | D126: 45597 | E126: 30
A127: PT Indo American Seafoods | B127: 30957607 | C127: 103 | D127: 45598 | E127: 30
A128: PT Indo American Seafoods | B128: 4.1748831e+08 | C128: 104 | D128: 45608 | E128: 30
A129: PT Indo American Seafoods | B129: 45873282 | C129: 105 | D129: 45610 | E129: 30
A130: PT Indo American Seafoods | B130: 52673209 | C130: 106 | D130: 45611 | E130: 30
... A145: PT Indo American Seafoods | B145: 97335311 | C145: 122 | D145: 45645 | E145: 30
A146: PT Indo American Seafoods | B146: 1155954 | D146: 45649 | E146: 30
A147: PT Indo American Seafoods | B147: 1320678 | D147: 45650 | E147: 30
...

Sheet Hutang IAS Sept 24
A1: Aging Hutang Usaha & Subsequent
A2: PT Indo American Seafoods
A3: 45565
B4: =SUBTOTAL(9,B6:B107) -> 3.2579243e+09 | H4: =SUBTOTAL(9,H6:H107) -> 2.7836057e+09 | I4: =SUBTOTAL(9,I6:I107) -> 4.332646e+08 | J4: =SUBTOTAL(9,J6:J107) -> 14154286 | K4: =SUBTOTAL(9,K6:K107) -> 8031460 | L4: =SUBTOTAL(9,L6:L107) -> 18868270 | M4: =SUM(H4:L4)-B4 -> 0
A5: Nama | B5: Nominal | C5: No Invoice | D5: Tgl Invoice | E5: Jatuh Tempo | F5: Tgl Jatuh Tempo | G5: Aging | H5: Lancar | I5: 1-30 Hari | J5: 31-60 Hari | K5: 61-90 Hari | L5: >90 Hari
A6: PT Anesta Agung | B6: 2.8762729e+08 | C6: 648 | D6: 45561 | E6: 30 | F6: =D6+E6 -> 45591 | G6: =$A$3-F6 -> -26 | H6: =B6 -> 2.8762729e+08
A8: PT Konverta Mitra Abadi | B8: 1113430 | D8: 45443 | E8: 30 | F8: =D8+E8 -> 45473 | G8: =$A$3-F8 -> 92 | L8: =B8 -> 1113430
A9: PT Konverta Mitra Abadi | B9: 8031460 | C9: 417 | D9: 45448 | E9: 30 | F9: =D9+E9 -> 45478 | G9: =$A$3-F9 -> 87 | K9: =B9 -> 8031460
A10: PT Konverta Mitra Abadi | B10: 3059437 | C10: 484 | D10: 45489 | E10: 30 | F10: =D10+E10 -> 45519 | G10: =$A$3-F10 -> 46 | J10: =B10 -> 3059437
A11: PT Konverta Mitra Abadi | B11: 27872100 | C11: 543 | D11: 45523 | E11: 30 | F11: =D11+E11 -> 45553 | G11: =$A$3-F11 -> 12 | I11: =B11 -> 27872100
A12: PT Konverta Mitra Abadi | B12: 24431100 | C12: 544 | D12: 45523 | E12: 30 | F12: =D12+E12 -> 45553 | G12: =$A$3-F12 -> 12 | I12: =B12 -> 24431100
A13: PT Konverta Mitra Abadi | B13: 16516800 | C13: 551 | D13: 45526 | E13: 30 | F13: =D13+E13 -> 45556 | G13: =$A$3-F13 -> 9 | I13: =B13 -> 16516800
A14: PT Konverta Mitra Abadi | B14: 7914300 | C14: 552 | D14: 45527 | E14: 30 | F14: =D14+E14 -> 45557 | G14: =$A$3-F14 -> 8 | I14: =B14 -> 7914300
A15: PT Konverta Mitra Abadi | B15: 5782045.5 | C15: 555 | D15: 45528 | E15: 30 | F15: =D15+E15 -> 45558 | G15: =$A$3-F15 -> 7 | I15: =B15 -> 5782045.5
A16: PT Konverta Mitra Abadi | B16: 4142320 | C16: 556 | D16: 45528 | E16: 30 | F16: =D16+E16 -> 45558 | G16: =$A$3-F16 -> 7 | I16: =B16 -> 4142320
A17: PT Konverta Mitra Abadi | B17: 3291838 | C17: 557 | D17: 45528 | E17: 30 | F17: =D17+E17 -> 45558 | G17: =$A$3-F17 -> 7 | I17: =B17 -> 3291838
A18: PT Konverta Mitra Abadi | B18: 11507203 | C18: 558 | D18: 45529 | E18: 30 | F18: =D18+E18 -> 45559 | G18: =$A$3-F18 -> 6 | I18: =B18 -> 11507203
A19: PT Konverta Mitra Abadi | B19: 787212 | C19: 559 | D19: 45529 | E19: 30 | F19: =D19+E19 -> 45559 | G19: =$A$3-F19 -> 6 | I19: =B19 -> 787212
A20: PT Konverta Mitra Abadi | B20: 4784377 | C20: 577 | D20: 45533 | E20: 30 | F20: =D20+E20 -> 45563 | G20: =$A$3-F20 -> 2 | I20: =B20 -> 4784377
A21: PT Konverta Mitra Abadi | B21: 39463164 | C21: 580 | D21: 45534 | E21: 30 | F21: =D21+E21 -> 45564 | G21: =$A$3-F21 -> 1 | I21: =B21 -> 39463164
A22: PT Konverta Mitra Abadi | B22: 35519500 | C22: 581 | D22: 45534 | E22: 30 | F22: =D22+E22 -> 45564 | G22: =$A$3-F22 -> 1 | I22: =B22 -> 35519500
A23: PT Konverta Mitra Abadi | B23: 17118975 | C23: 582 | D23: 45534 | E23: 30 | F23: =D23+E23 -> 45564 | G23: =$A$3-F23 -> 1 | I23: =B23 -> 17118975
A24: PT Konverta Mitra Abadi | B24: 3892548 | C24: 587 | D24: 45535 | E24: 30 | F24: =D24+E24 -> 45565 | G24: =$A$3-F24 -> 0 | H24: =B24 -> 3892548
A25: PT Konverta Mitra Abadi | B25: 23605260 | C25: 588 | D25: 45535 | E25: 30 | F25: =D25+E25 -> 45565 | G25: =$A$3-F25 -> 0 | H25: =B25 -> 23605260
A26: PT Konverta Mitra Abadi | B26: 21403020 | C26: 597 | D26: 45540 | E26: 30 | F26: =D26+E26 -> 45570 | G26: =$A$3-F26 -> -5 | H26: =B26 -> 21403020
A27: PT Konverta Mitra Abadi | B27: 2339880 | C27: 609 | D27: 45542 | E27: 30 | F27: =D27+E27 -> 45572 | G27: =$A$3-F27 -> -7 | H27: =B27 -> 2339880
A28: PT Konverta Mitra Abadi | B28: 94076940 | C28: 631 | D28: 45547 | E28: 30 | F28: =D28+E28 -> 45577 | G28: =$A$3-F28 -> -12 | H28: =B28 -> 94076940
A29: PT Konverta Mitra Abadi | B29: 961537 | C29: 632 | D29: 45547 | E29: 30 | F29: =D29+E29 -> 45577 | G29: =$A$3-F29 -> -12 | H29: =B29 -> 961537
A30: PT Konverta Mitra Abadi | B30: 17120473 | C30: 649 | D30: 45551 | E30: 30 | F30: =D30+E30 -> 45581 | G30: =$A$3-F30 -> -16 | H30: =B30 -> 17120473
A31: PT Konverta Mitra Abadi | B31: 11837040 | C31: 655 | D31: 45552 | E31: 30 | F31: =D31+E31 -> 45582 | G31: =$A$3-F31 -> -17 | H31: =B31 -> 11837040
A32: PT Konverta Mitra Abadi | B32: 6905587 | C32: 658 | D32: 45553 | E32: 30 | F32: =D32+E32 -> 45583 | G32: =$A$3-F32 -> -18 | H32: =B32 -> 6905587
A33: PT Konverta Mitra Abadi | B33: 11905860 | C33: 659 | D33: 45553 | E33: 30 | F33: =D33+E33 -> 45583 | G33: =$A$3-F33 -> -18 | H33: =B33 -> 11905860
A34: PT Konverta Mitra Abadi | B34: 39164352 | C34: 660 | D34: 45553 | E34: 30 | F34: =D34+E34 -> 45583 | G34: =$A$3-F34 -> -18 | H34: =B34 -> 39164352
A35: PT Konverta Mitra Abadi | B35: 5292480 | C35: 664 | D35: 45554 | E35: 30 | F35: =D35+E35 -> 45584 | G35: =$A$3-F35 -> -19 | H35: =B35 -> 5292480
... A39: PT Konverta Mitra Abadi | B39: 8031460 | C39: 685 | D39: 45565 | E39: 30 | F39: =D39+E39 -> 45595 | G39: =$A$3-F39 -> -30 | H39: =B39 -> 8031460
A41: PT RBFood Supply Indonesia | B41: 28860000 | C41: 616 | D41: 45514 | E41: 30 | F41: =D41+E41 -> 45544 | G41: =$A$3-F41 -> 21 | I41: =B41 -> 28860000
A42: PT RBFood Supply Indonesia | B42: 28860000 | C42: 527 | D42: 45546 | E42: 30 | F42: =D42+E42 -> 45576 | G42: =$A$3-F42 -> -11 | H42: =B42 -> 28860000
A43: PT RBFood Supply Indonesia | B43: 6660000 | C43: 31 | D43: 45302 | E43: 30 | F43: =D43+E43 -> 45332 | G43: =$A$3-F43 -> 233 | L43: =B43 -> 6660000
A45: PT CJ Cheiljedang Feed Lampung | B45: 79300000 | C45: 2434 | D45: 45548 | E45: 30 | F45: =D45+E45 -> 45578 | G45: =$A$3-F45 -> -13 | H45: =B45 -> 79300000
A46: PT CJ Cheiljedang Feed Lampung | B46: 79325000 | C46: 2435 | D46: 45548 | E46: 30 | F46: =D46+E46 -> 45578 | G46: =$A$3-F46 -> -13 | H46: =B46 -> 79325000
A48: Tn. Ismanto | B48: 1.2950778e+08 | C48: 655 | D48: 45562 | E48: 30 | F48: =D48+E48 -> 45592 | G48: =$A$3-F48 -> -27 | H48: =B48 -> 1.2950778e+08
A50: PT Sumber Energy | B50: 31635000 | C50: 687 | D50: 45565 | E50: 30 | F50: =D50+E50 -> 45595 | G50: =$A$3-F50 -> -30 | H50: =B50 -> 31635000
A52: PT Indonesia Makan Udang | B52: 252234395 | C52: 649 | D52: 45561 | E52: 30 | F52: =D52+E52 -> 45591 | G52: =$A$3-F52 -> -26 | H52: =B52 -> 252234395
A53: PT Indonesia Makan Udang | B53: 225407721 | C53: 650 | D53: 45561 | E53: 30 | F53: =D53+E53 -> 45591 | G53: =$A$3-F53 -> -26 | H53: =B53 -> 225407721
A54: PT Indonesia Makan Udang | B54: 44990866 | C54: 675 | D54: 45565 | E54: 30 | F54: =D54+E54 -> 45595 | G54: =$A$3-F54 -> -30 | H54: =B54 -> 44990866
A55: PT Indonesia Makan Udang | B55: 67875183 | C55: 572 | D55: 45548 | E55: 30 | F55: =D55+E55 -> 45578 | G55: =$A$3-F55 -> -13 | H55: =B55 -> 67875183
A57: Nerimo Ing Pandum, CV | B57: =200753868.45*0 -> 0 | C57: 630 | D57: 45560 | E57: 30 | F57: =D57+E57 -> 45590 | G57: =$A$3-F57 -> -25 | H57: =B57 -> 0
A59: Utomo Print | B59: 33776865 | C59: 575 | D59: 45533 | E59: 30 | F59: =D59+E59 -> 45563 | G59: =$A$3-F59 -> 2 | I59: =B59 -> 33776865
A60: Utomo Print | B60: 25054920 | C60: 600 | D60: 45540 | E60: 30 | F60: =D60+E60 -> 45570 | G60: =$A$3-F60 -> -5 | H60: =B60 -> 25054920
A61: Utomo Print | B61: 25054920 | C61: 601 | D61: 45540 | E61: 30 | F61: =D61+E61 -> 45570 | G61: =$A$3-F61 -> -5 | H61: =B61 -> 25054920
A62: Utomo Print | B62: 42475704 | C62: 610 | D62: 45542 | E62: 30 | F62: =D62+E62 -> 45572 | G62: =$A$3-F62 -> -7 | H62: =B62 -> 42475704
A63: Utomo Print | B63: 48999840 | C63: 6111 | D63: 45542 | E63: 30 | F63: =D63+E63 -> 45572 | G63: =$A$3-F63 -> -7 | H63: =B63 -> 48999840
A64: Utomo Print | B64: 74325600 | C64: 665 | D64: 45554 | E64: 30 | F64: =D64+E64 -> 45584 | G64: =$A$3-F64 -> -19 | H64: =B64 -> 74325600
A65: Utomo Print | B65: 688200 | C65: 666 | D65: 45554 | E65: 30 | F65: =D65+E65 -> 45584 | G65: =$A$3-F65 -> -19 | H65: =B65 -> 688200
A67: PT Sinergy Indopack Makmur | B67: 23976000 | C67: 650 | D67: 45552 | E67: 30 | F67: =D67+E67 -> 45582 | G67: =$A$3-F67 -> -17 | H67: =B67 -> 23976000
A68: PT Sinergy Indopack Makmur | B68: 46353600 | C68: 651 | D68: 45552 | E68: 30 | F68: =D68+E68 -> 45582 | G68: =$A$3-F68 -> -17 | H68: =B68 -> 46353600
A70: Sumatraco Langgeng Abadi, PT | B70: 20535000 | C70: 576 | D70: 45533 | E70: 30 | F70: =D70+E70 -> 45563 | G70: =$A$3-F70 -> 2 | I70: =B70 -> 20535000
A72: R & R COLECTION | B72: 1080000 | C72: 593 | D72: 45539 | E72: 30 | F72: =D72+E72 -> 45569 | G72: =$A$3-F72 -> -4 | H72: =B72 -> 1080000
A73: R & R COLECTION | B73: 360000 | C73: 607 | D73: 45542 | E73: 30 | F73: =D73+E73 -> 45572 | G73: =$A$3-F73 -> -7 | H73: =B73 -> 360000
A74: R & R COLECTION | B74: 10290000 | C74: 613 | D74: 45545 | E74: 30 | F74: =D74+E74 -> 45575 | G74: =$A$3-F74 -> -10 | H74: =B74 -> 10290000
A75: R & R COLECTION | B75: 4320000 | C75: 654 | D75: 45552 | E75: 30 | F75: =D75+E75 -> 45582 | G75: =$A$3-F75 -> -17 | H75: =B75 -> 4320000
A76: R & R COLECTION | B76: 16990000 | C76: 682 | D76: 45562 | E76: 30 | F76: =D76+E76 -> 45592 | G76: =$A$3-F76 -> -27 | H76: =B76 -> 16990000
A77: R & R COLECTION | B77: 10290000 | C77: 684 | D77: 45565 | E77: 30 | F77: =D77+E77 -> 45595 | G77: =$A$3-F77 -> -30 | H77: =B77 -> 10290000
A79: Lima Pendawa, CV | B79: 33300000 | C79: 542 | D79: 45523 | E79: 30 | F79: =D79+E79 -> 45553 | G79: =$A$3-F79 -> 12 | I79: =B79 -> 33300000
A81: Sumatra Motor Teknindo, PT | B81: =44100+1200 -> 45300 | C81: 589 | D81: 45536 | E81: 30 | F81: =D81+E81 -> 45566 | G81: =$A$3-F81 -> -1 | H81: =B81 -> 45300
A82: Sumatra Motor Teknindo, PT | B82: 199800 | C82: 630 | D82: 45547 | E82: 30 | F82: =D82+E82 -> 45577 | G82: =$A$3-F82 -> -12 | H82: =B82 -> 199800
A84: Indoplast Jaya Sukses Makmur, PT | B84: 9090900 | C84: 521 | D84: 45512 | E84: 30 | F84: =D84+E84 -> 45542 | G84: =$A$3-F84 -> 23 | I84: =B84 -> 9090900
A86: Dinamika Lubsindo Utama, PT | B86: 11094840 | D86: 45292 | E86: 30 | F86: =D86+E86 -> 45322 | G86: =$A$3-F86 -> 243 | L86: =B86 -> 11094840
A87: Dinamika Lubsindo Utama, PT | B87: 11094849 | C87: 506 | D87: 45504 | E87: 30 | F87: =D87+E87 -> 45534 | G87: =$A$3-F87 -> 31 | J87: =B87 -> 11094849
A88: Dinamika Lubsindo Utama, PT | B88: 11094849 | C88: 678 | D88: 45560 | E88: 30 | F88: =D88+E88 -> 45590 | G88: =$A$3-F88 -> -25 | H88: =B88 -> 11094849
A89: Dinamika Lubsindo Utama, PT | B89: 11094849 | C89: 681 | D89: 45560 | E89: 30 | F89: =D89+E89 -> 45590 | G89: =$A$3-F89 -> -25 | H89: =B89 -> 11094849
A91: Maju Tambak Sumur, PT | B91: =471004404.7 -> 4.710044e+08 | C91: 633 | D91: 45560 | E91: 30 | F91: =D91+E91 -> 45590 | G91: =$A$3-F91 -> -25 | H91: =B91 -> 4.710044e+08
A93: Andalan Traiding Mina, CV | B93: =390700399.72*0 -> 0 | C93: 674 | D93: 45565 | E93: 30 | F93: =D93+E93 -> 45595 | G93: =$A$3-F93 -> -30 | H93: =B93 -> 0
A95: Gatot Eko Andoyo | B95: 97875017 | C95: 599 | D95: 45555 | E95: 30 | F95: =D95+E95 -> 45585 | G95: =$A$3-F95 -> -20 | H95: =B95 -> 97875017
A97: Sakti Biru Indonesia, PT | B97: 2.8529717e+08 | C97: 677 | D97: 45565 | E97: 30 | F97: =D97+E97 -> 45595 | G97: =$A$3-F97 -> -30 | H97: =B97 -> 2.8529717e+08
A99: Indolabel Surya Pratama, PT | B99: 10509480 | C99: 603 | D99: 45541 | E99: 30 | F99: =D99+E99 -> 45571 | G99: =$A$3-F99 -> -6 | H99: =B99 -> 10509480
A100: Indolabel Surya Pratama, PT | B100: 15180360 | C100: 621 | D100: 45546 | E100: 30 | F100: =D100+E100 -> 45576 | G100: =$A$3-F100 -> -11 | H100: =B100 -> 15180360
A101: Indolabel Surya Pratama, PT | B101: 13977608 | C101: 623 | D101: 45547 | E101: 30 | F101: =D101+E101 -> 45577 | G101: =$A$3-F101 -> -12 | H101: =B101 -> 13977608
A102: Indolabel Surya Pratama, PT | B102: 4203792 | C102: 624 | D102: 45547 | E102: 30 | F102: =D102+E102 -> 45577 | G102: =$A$3-F102 -> -12 | H102: =B102 -> 4203792
A103: Indolabel Surya Pratama, PT | B103: 1786612 | C103: 625 | D103: 45547 | E103: 30 | F103: =D103+E103 -> 45577 | G103: =$A$3-F103 -> -12 | H103: =B103 -> 1786612
A104: Indolabel Surya Pratama, PT | B104: 5126291 | C104: 668 | D104: 45554 | E104: 30 | F104: =D104+E104 -> 45584 | G104: =$A$3-F104 -> -19 | H104: =B104 -> 5126291
A105: Indolabel Surya Pratama, PT | B105: 10217550 | C105: 675 | D105: 45556 | E105: 30 | F105: =D105+E105 -> 45586 | G105: =$A$3-F105 -> -21 | H105: =B105 -> 10217550
A107: Lain-lain (masing-masing di bawah Rp 20.000.000) | B107: 108570905 | I107: =B107 -> 108570905

Sheet Hutang Usaha ISP Sept 2024
A1: Aging Hutang Usaha & Subsequent
A2: PT Indokom Samudra Persada
A3: 45565
B4: =SUM(B6:B216) -> 7.3871703e+09 | H4: =SUM(H6:H216) -> 4.9834664e+09 | I4: =SUM(I6:I216) -> 1982303832 | J4: =SUM(J6:J216) -> 184180750 | K4: =SUM(K6:K216) -> 82354849 | L4: =SUM(L6:L216) -> 154864460 | M4: =SUM(H4:L4)-B4 -> 0
A5: Nama | B5: Nominal | C5: No Purchase | D5: Tgl Purchase | E5: Jatuh Tempo | F5: Tgl Jatuh Tempo | G5: Aging | H5: Lancar | I5: 1-30 Hari | J5: 31-60 Hari | K5: 61-90 Hari | L5: >90 Hari
A6: Bapak Cipto | B6: 27237008 | E6: 30 | I6: =B6 -> 27237008
A8: Halim Sakti Pratama, PT | B8: 13506480 | C8: 36 | D8: 45553 | E8: 30 | F8: =D8+E8 -> 45583 | G8: =$A$3-F8 -> -18 | H8: =B8 -> 13506480
A10: Intiragam Oliefindo, PT | B10: 24975000 | C10: 397 | D10: 45546 | E10: 30 | F10: =D10+E10 -> 45576 | G10: =$A$3-F10 -> -11 | H10: =B10 -> 24975000
A12: Samara Cipta Solution, CV | B12: 69903226 | C12: 311 | D12: 45514 | E12: 30 | F12: =D12+E12 -> 45544 | G12: =$A$3-F12 -> 21 | I12: =B12 -> 69903226
B13: 32190000 | C13: 438 | D13: 45560 | E13: 30 | F13: =D13+E13 -> 45590 | G13: =$A$3-F13 -> -25 | H13: =B13 -> 32190000
B14: 48037780 | C14: 439 | D14: 45560 | E14: 30 | F14: =D14+E14 -> 45590 | G14: =$A$3-F14 -> -25 | H14: =B14 -> 48037780
A16: Seven Mountain Internasional, PT | B16: 29859000 | C16: 314 | D16: 45516 | E16: 30 | F16: =D16+E16 -> 45546 | G16: =$A$3-F16 -> 19 | I16: =B16 -> 29859000
A18: Sinar Panca Surya, PT | B18: 48888562 | C18: 405 | D18: 45548 | E18: 30 | F18: =D18+E18 -> 45578 | G18: =$A$3-F18 -> -13 | H18: =B18 -> 48888562
B19: 41990190 | C19: 442 | D19: 45561 | E19: 30 | F19: =D19+E19 -> 45591 | G19: =$A$3-F19 -> -26 | H19: =B19 -> 41990190
B20: 42525657 | C20: 447 | D20: 45563 | E20: 30 | F20: =D20+E20 -> 45593 | G20: =$A$3-F20 -> -28 | H20: =B20 -> 42525657
A22: Sinar Setia Mulia , PT | B22: 40800003 | C22: 35 | D22: 45546 | E22: 30 | F22: =D22+E22 -> 45576 | G22: =$A$3-F22 -> -11 | H22: =B22 -> 40800003
A24: Nusantara, Toko | B24: 5025000 | D24: 45292 | E24: 30 | F24: =D24+E24 -> 45322 | G24: =$A$3-F24 -> 243 | L24: =B24 -> 5025000 | M24: apakah perlu di adj ?
A26: Surya Serba Mulia, PT | B26: 70999869 | C26: 411 | D26: 45549 | E26: 30 | F26: =D26+E26 -> 45579 | G26: =$A$3-F26 -> -14 | H26: =B26 -> 70999869
A28: Sumatra Motor Teknindo, PT | B28: 8646900 | C28: 231 | D28: 45477 | E28: 30 | F28: =D28+E28 -> 45507 | G28: =$A$3-F28 -> 58 | J28: =B28 -> 8646900
B29: 301032 | C29: 232 | D29: 45477 | E29: 30 | F29: =D29+E29 -> 45507 | G29: =$A$3-F29 -> 58 | J29: =B29 -> 301032
B30: 357420 | C30: 233 | D30: 45477 | E30: 30 | F30: =D30+E30 -> 45507 | G30: =$A$3-F30 -> 58 | J30: =B30 -> 357420
B31: 619380 | C31: 14 | D31: 45477 | E31: 30 | F31: =D31+E31 -> 45507 | G31: =$A$3-F31 -> 58 | J31: =B31 -> 619380
B32: 2426460 | C32: 327 | D32: 45505 | E32: 30 | F32: =D32+E32 -> 45535 | G32: =$A$3-F32 -> 30 | I32: =B32 -> 2426460
B33: 7856025 | C33: 328 | D33: 45505 | E33: 30 | F33: =D33+E33 -> 45535 | G33: =$A$3-F33 -> 30 | I33: =B33 -> 7856025
B34: =457875-17988 -> 439887 | C34: 331 | D34: 45505 | E34: 30 | F34: =D34+E34 -> 45535 | G34: =$A$3-F34 -> 30 | I34: =B34 -> 439887
B35: 567432 | C35: 306 | D35: 45514 | E35: 30 | F35: =D35+E35 -> 45544 | G35: =$A$3-F35 -> 21 | I35: =B35 -> 567432
B36: 2411475 | C36: 307 | D36: 45514 | E36: 30 | F36: =D36+E36 -> 45544 | G36: =$A$3-F36 -> 21 | I36: =B36 -> 2411475
B37: 510600 | C37: 308 | D37: 45514 | E37: 30 | F37: =D37+E37 -> 45544 | G37: =$A$3-F37 -> 21 | I37: =B37 -> 510600
B38: 222000 | C38: 32 | D38: 45533 | E38: 30 | F38: =D38+E38 -> 45563 | G38: =$A$3-F38 -> 2 | I38: =B38 -> 222000
B39: 366300 | C39: 365 | D39: 45537 | E39: 30 | F39: =D39+E39 -> 45567 | G39: =$A$3-F39 -> -2 | H39: =B39 -> 366300
B40: 3046950 | C40: 366 | D40: 45537 | E40: 30 | F40: =D40+E40 -> 45567 | G40: =$A$3-F40 -> -2 | H40: =B40 -> 3046950
B41: 1198800 | C41: 34 | D41: 45537 | E41: 30 | F41: =D41+E41 -> 45567 | G41: =$A$3-F41 -> -2 | H41: =B41 -> 1198800
B42: 2424240 | C42: 390 | D42: 45536 | E42: 30 | F42: =D42+E42 -> 45566 | G42: =$A$3-F42 -> -1 | H42: =B42 -> 2424240
B43: 3762900 | C43: 391 | D43: 45536 | E43: 30 | F43: =D43+E43 -> 45566 | G43: =$A$3-F43 -> -1 | H43: =B43 -> 3762900
A45: Tri Jaya Sukses | B45: 38500000 | C45: 271 | D45: 45475 | E45: 30 | F45: =D45+E45 -> 45505 | G45: =$A$3-F45 -> 60 | J45: =B45 -> 38500000
B46: 38500000 | C46: 311 | D46: 45500 | E46: 30 | F46: =D46+E46 -> 45530 | G46: =$A$3-F46 -> 35 | J46: =B46 -> 38500000
B47: 26500000 | C47: 365 | D47: 45523 | E47: 30 | F47: =D47+E47 -> 45553 | G47: =$A$3-F47 -> 12 | I47: =B47 -> 26500000
B48: 2537500 | C48: 366 | D48: 45523 | E48: 30 | F48: =D48+E48 -> 45553 | G48: =$A$3-F48 -> 12 | I48: =B48 -> 2537500
A50: General Agromesin Lestari, PT | B50: 58185000 | C50: 416 | D50: 45548 | E50: 30 | F50: =D50+E50 -> 45578 | G50: =$A$3-F50 -> -13 | H50: =B50 -> 58185000
B51: 27153000 | C51: 417 | D51: 45548 | E51: 30 | F51: =D51+E51 -> 45578 | G51: =$A$3-F51 -> -13 | H51: =B51 -> 27153000
B52: =9050000-5 -> 9049995 | C52: 418 | D52: 45548 | E52: 30 | F52: =D52+E52 -> 45578 | G52: =$A$3-F52 -> -13 | H52: =B52 -> 9049995
A54: Maju Tambak Sumur, PT | B54: 463814236 | C54: 404 | D54: 45556 | E54: 30 | F54: =D54+E54 -> 45586 | G54: =$A$3-F54 -> -21 | H54: =B54 -> 463814236
B55: 179764092 | C55: 410 | D55: 45559 | E55: 30 | F55: =D55+E55 -> 45589 | G55: =$A$3-F55 -> -24 | H55: =B55 -> 179764092
A57: SUMBERDAYA SINAR BARU, PT | B57: 19068210 | D57: 45292 | E57: 30 | F57: =D57+E57 -> 45322 | G57: =$A$3-F57 -> 243 | L57: =B57 -> 19068210 | M57: apakah perlu di adj ?
A59: PT Anesta Agung | B59: =267923543*0 -> 0 | C59: 405 | D59: 45558 | E59: 30 | F59: =D59+E59 -> 45588 | G59: =$A$3-F59 -> -23 | H59: =B59 -> 0
A61: PT Delos Rantai Maritim | B61: 39720732 | C61: 388 | D61: 45549 | E61: 30 | F61: =D61+E61 -> 45579 | G61: =$A$3-F61 -> -14 | H61: =B61 -> 39720732
A63: PT International Packaging Manufacturing | B63: 971250 | D63: 45292 | E63: 30 | F63: =D63+E63 -> 45322 | G63: =$A$3-F63 -> 243 | L63: =B63 -> 971250 | M63: apakah perlu di adj ?
A65: PT Konverta Mitra Abadi | B65: 966753 | D65: 45523 | E65: 30 | F65: =D65+E65 -> 45553 | G65: =$A$3-F65 -> 12 | I65: =B65 -> 966753
A66: PT Konverta Mitra Abadi | B66: 23742900 | C66: 324 | D66: 45523 | E66: 30 | F66: =D66+E66 -> 45553 | G66: =$A$3-F66 -> 12 | I66: =B66 -> 23742900
A67: PT Konverta Mitra Abadi | B67: 11680141 | C67: 338 | D67: 45529 | E67: 30 | F67: =D67+E67 -> 45559 | G67: =$A$3-F67 -> 6 | I67: =B67 -> 11680141
A68: PT Konverta Mitra Abadi | B68: 13805625 | C68: 357 | D68: 45534 | E68: 30 | F68: =D68+E68 -> 45564 | G68: =$A$3-F68 -> 1 | I68: =B68 -> 13805625
A69: PT Konverta Mitra Abadi | B69: 12337650 | C69: 359 | D69: 45535 | E69: 30 | F69: =D69+E69 -> 45565 | G69: =$A$3-F69 -> 0 | H69: =B69 -> 12337650
A70: PT Konverta Mitra Abadi | B70: 16516800 | C70: 377 | D70: 45540 | E70: 30 | F70: =D70+E70 -> 45570 | G70: =$A$3-F70 -> -5 | H70: =B70 -> 16516800
A71: PT Konverta Mitra Abadi | B71: 46109400 | C71: 380 | D71: 45542 | E71: 30 | F71: =D71+E71 -> 45572 | G71: =$A$3-F71 -> -7 | H71: =B71 -> 46109400
A72: PT Konverta Mitra Abadi | B72: 19297350 | C72: 385 | D72: 45542 | E72: 30 | F72: =D72+E72 -> 45572 | G72: =$A$3-F72 -> -7 | H72: =B72 -> 19297350
A73: PT Konverta Mitra Abadi | B73: 5536224 | C73: 386 | D73: 45543 | E73: 30 | F73: =D73+E73 -> 45573 | G73: =$A$3-F73 -> -8 | H73: =B73 -> 5536224
A74: PT Konverta Mitra Abadi | B74: 1858140 | C74: 388 | D74: 45544 | E74: 30 | F74: =D74+E74 -> 45574 | G74: =$A$3-F74 -> -9 | H74: =B74 -> 1858140
A75: PT Konverta Mitra Abadi | B75: 6667281 | C75: 389 | D75: 45544 | E75: 30 | F75: =D75+E75 -> 45574 | G75: =$A$3-F75 -> -9 | H75: =B75 -> 6667281
A76: PT Konverta Mitra Abadi | B76: 18237300 | C76: 406 | D76: 45548 | E76: 30 | F76: =D76+E76 -> 45578 | G76: =$A$3-F76 -> -13 | H76: =B76 -> 18237300
A77: PT Konverta Mitra Abadi | B77: 2724783 | C77: 407 | D77: 45548 | E77: 30 | F77: =D77+E77 -> 45578 | G77: =$A$3-F77 -> -13 | H77: =B77 -> 2724783
A78: PT Konverta Mitra Abadi | B78: 13850025 | C78: 414 | D78: 45551 | E78: 30 | F78: =D78+E78 -> 45581 | G78: =$A$3-F78 -> -16 | H78: =B78 -> 13850025
A79: PT Konverta Mitra Abadi | B79: 5505600 | C79: 415 | D79: 45551 | E79: 30 | F79: =D79+E79 -> 45581 | G79: =$A$3-F79 -> -16 | H79: =B79 -> 5505600
A80: PT Konverta Mitra Abadi | B80: 6422704 | C80: 416 | D80: 45551 | E80: 30 | F80: =D80+E80 -> 45581 | G80: =$A$3-F80 -> -16 | H80: =B80 -> 6422704
... A86: PT Konverta Mitra Abadi | B86: 2693304 | C86: 451 | D86: 45565 | E86: 30 | F86: =D86+E86 -> 45595 | G86: =$A$3-F86 -> -30 | H86: =B86 -> 2693304
A88: Multidaya Teknologi Nusantara PT | B88: =310906705*0 -> 0 | C88: 76 | D88: 44956 | E88: 30 | F88: =D88+E88 -> 44986 | G88: =$A$3-F88 -> 579 | L88: =B88 -> 0 | M88: Perlu confirm
A90: Prima Larvae, PT | B90: 67680000 | C90: 433 | D90: 45549 | E90: 30 | F90: =D90+E90 -> 45579 | G90: =$A$3-F90 -> -14 | H90: =B90 -> 67680000
A91: Prima Larvae, PT | B91: 4445196 | C91: 385 | D91: 45548 | E91: 30 | F91: =D91+E91 -> 45578 | G91: =$A$3-F91 -> -13 | H91: =B91 -> 4445196
A92: Prima Larvae, PT | B92: 25783692 | C92: 422 | D92: 45563 | E92: 30 | F92: =D92+E92 -> 45593 | G92: =$A$3-F92 -> -28 | H92: =B92 -> 25783692
A94: PT RBFood Supply Indonesia | B94: 177600000 | C94: 392 | D94: 45546 | E94: 30 | F94: =D94+E94 -> 45576 | G94: =$A$3-F94 -> -11 | H94: =B94 -> 177600000
A95: PT RBFood Supply Indonesia | B95: 88800000 | C95: 422 | D95: 45553 | E95: 30 | F95: =D95+E95 -> 45583 | G95: =$A$3-F95 -> -18 | H95: =B95 -> 88800000
A97: PT CJ Cheiljedang Feed Lampung | B97: 79500000 | C97: 2424 | D97: 45552 | E97: 30 | F97: =D97+E97 -> 45582 | G97: =$A$3-F97 -> -17 | H97: =B97 -> 79500000
A98: PT CJ Cheiljedang Feed Lampung | B98: 79500000 | C98: 2425 | D98: 45552 | E98: 30 | F98: =D98+E98 -> 45582 | G98: =$A$3-F98 -> -17 | H98: =B98 -> 79500000
A99: PT CJ Cheiljedang Feed Lampung | B99: 47700000 | C99: 2426 | D99: 45552 | E99: 30 | F99: =D99+E99 -> 45582 | G99: =$A$3-F99 -> -17 | H99: =B99 -> 47700000
A100: PT CJ Cheiljedang Feed Lampung | B100: 57050000 | C100: 2427 | D100: 45552 | E100: 30 | F100: =D100+E100 -> 45582 | G100: =$A$3-F100 -> -17 | H100: =B100 -> 57050000
A101: PT CJ Cheiljedang Feed Lampung | B101: 3270000 | C101: 2428 | D101: 45552 | E101: 30 | F101: =D101+E101 -> 45582 | G101: =$A$3-F101 -> -17 | H101: =B101 -> 3270000
A102: PT CJ Cheiljedang Feed Lampung | B102: 24525000 | C102: 2435 | D102: 45553 | E102: 30 | F102: =D102+E102 -> 45583 | G102: =$A$3-F102 -> -18 | H102: =B102 -> 24525000
A103: PT CJ Cheiljedang Feed Lampung | B103: 65400000 | C103: 2436 | D103: 45553 | E103: 30 | F103: =D103+E103 -> 45583 | G103: =$A$3-F103 -> -18 | H103: =B103 -> 65400000
... A111: PT Sumber Energy | B111: 31635000 | C111: 413 | D111: 45549 | E111: 30 | F111: =D111+E111 -> 45579 | G111: =$A$3-F111 -> -14 | H111: =B111 -> 31635000
A113: PT Gemilang Primajaya Trimandiri | B113: 44259518 | C113: 294 | D113: 45504 | E113: 30 | F113: =D113+E113 -> 45534 | G113: =$A$3-F113 -> 31 | J113: =B113 -> 44259518
B114: 23558462 | C114: 393 | D114: 45546 | E114: 30 | F114: =D114+E114 -> 45576 | G114: =$A$3-F114 -> -11 | H114: =B114 -> 23558462
A116: PT Indonesia Makan Udang | B116: =66746778-22995056 -> 43751722 | D116: 45526 | E116: 30 | F116: =D116+E116 -> 45556 | G116: =$A$3-F116 -> 9 | I116: =B116 -> 43751722
A117: PT Indonesia Makan Udang | B117: 82810229 | C117: 342 | D117: 45532 | E117: 30 | F117: =D117+E117 -> 45562 | G117: =$A$3-F117 -> 3 | I117: =B117 -> 82810229
A118: PT Indonesia Makan Udang | B118: 260250221 | C118: 343 | D118: 45532 | E118: 30 | F118: =D118+E118 -> 45562 | G118: =$A$3-F118 -> 3 | I118: =B118 -> 260250221
A119: PT Indonesia Makan Udang | B119: 260393273 | C119: 352 | D119: 45534 | E119: 30 | F119: =D119+E119 -> 45564 | G119: =$A$3-F119 -> 1 | I119: =B119 -> 260393273
A120: PT Indonesia Makan Udang | B120: 284268646 | C120: 353 | D120: 45534 | E120: 30 | F120: =D120+E120 -> 45564 | G120: =$A$3-F120 -> 1 | I120: =B120 -> 284268646
A121: PT Indonesia Makan Udang | B121: 79473976 | C121: 354 | D121: 45534 | E121: 30 | F121: =D121+E121 -> 45564 | G121: =$A$3-F121 -> 1 | I121: =B121 -> 79473976
A122: PT Indonesia Makan Udang | B122: 236570150 | C122: 358 | D122: 45537 | E122: 30 | F122: =D122+E122 -> 45567 | G122: =$A$3-F122 -> -2 | H122: =B122 -> 236570150
A123: PT Indonesia Makan Udang | B123: 31230552 | C123: 364 | D123: 45540 | E123: 30 | F123: =D123+E123 -> 45570 | G123: =$A$3-F123 -> -5 | H123: =B123 -> 31230552
A124: PT Indonesia Makan Udang | B124: 233049683 | C124: 377 | D124: 45546 | E124: 30 | F124: =D124+E124 -> 45576 | G124: =$A$3-F124 -> -11 | H124: =B124 -> 233049683
A125: PT Indonesia Makan Udang | B125: 136671015 | C125: 387 | D125: 45548 | E125: 30 | F125: =D125+E125 -> 45578 | G125: =$A$3-F125 -> -13 | H125: =B125 -> 136671015
A126: PT Indonesia Makan Udang | B126: 234463203 | C126: 389 | D126: 45549 | E126: 30 | F126: =D126+E126 -> 45579 | G126: =$A$3-F126 -> -14 | H126: =B126 -> 234463203
A127: PT Indonesia Makan Udang | B127: 224854354 | C127: 390 | D127: 45549 | E127: 30 | F127: =D127+E127 -> 45579 | G127: =$A$3-F127 -> -14 | H127: =B127 -> 224854354
A129: Utomo Print | B129: 24775200 | C129: 349 | D129: 45533 | E129: 30 | F129: =D129+E129 -> 45563 | G129: =$A$3-F129 -> 2 | I129: =B129 -> 24775200
A130: Utomo Print | B130: 24499920 | C130: 381 | D130: 45542 | E130: 30 | F130: =D130+E130 -> 45572 | G130: =$A$3-F130 -> -7 | H130: =B130 -> 24499920
A131: Utomo Print | B131: 24465510 | C131: 382 | D131: 45542 | E131: 30 | F131: =D131+E131 -> 45572 | G131: =$A$3-F131 -> -7 | H131: =B131 -> 24465510
A132: Utomo Print | B132: 24499920 | C132: 383 | D132: 45542 | E132: 30 | F132: =D132+E132 -> 45572 | G132: =$A$3-F132 -> -7 | H132: =B132 -> 24499920
A133: Utomo Print | B133: 688200 | C133: 424 | D133: 45554 | E133: 30 | F133: =D133+E133 -> 45584 | G133: =$A$3-F133 -> -19 | H133: =B133 -> 688200
A134: Utomo Print | B134: 688200 | C134: 425 | D134: 45554 | E134: 30 | F134: =D134+E134 -> 45584 | G134: =$A$3-F134 -> -19 | H134: =B134 -> 688200
A135: Utomo Print | B135: 1120389 | C135: 426 | D135: 45554 | E135: 30 | F135: =D135+E135 -> 45584 | G135: =$A$3-F135 -> -19 | H135: =B135 -> 1120389
A136: Utomo Print | B136: 52275672 | C136: 427 | D136: 45554 | E136: 30 | F136: =D136+E136 -> 45584 | G136: =$A$3-F136 -> -19 | H136: =B136 -> 52275672
...

Sheet Mapping to Report 
C2: UTANG USAHA | I2: TRADE ACCOUNTS PAYABLES
E4: 2024 | G4: 2023
C6: PT Indonesia Makan Udang | E6: 2887775246 | G6: 4451894010 | I6: PT Indonesia Makan Udang
C7: PT CJ Cheiljedang Feed Lampung | E7: 2043145000 | G7: 1115222500 | I7: PT CJ Cheiljedang Feed Lampung
C8: PT Anesta Agung | E8: 892566862 | G8: - | I8: PT Anesta Agung
C9: PT R&B Food Supply Co, Ltd | E9: 739260000 | G9: - | I9: R&B Food Supply Co, Ltd
C10: CV Sion Vannamei Raharja | E10: 648548775 | G10: - | I10: CV Sion Vannamei Raharja
C11: PT Konverta Mitra Abadi | E11: 502709194 | G11: 406242378 | I11: PT Konverta Mitra Abadi
C12: PT Mitra Lestari Mandiri | E12: 483155250 | G12: - | I12: PT Mitra Lestari Mandiri
C13: PT RBFood Manufaktur Indonesia | E13: 306138000 | G13: - | I13: PT RBFood Manufaktur Indonesia
C14: PT Multidaya Teknologi Nusantara | E14: 210906705 | G14: 310906705 | I14: PT Multidaya Teknologi Nusantara
C15: PT Maju Tambak Sumur | E15: 199585239 | G15: 29249998 | I15: PT Maju Tambak Sumur
C16: PT Gemilang Primajaya Trimandiri | E16: 179926294 | G16: 30862329 | I16: PT Gemilang Primajaya Trimandiri
C17: PT Indolabel Surya Pratama | E17: 71230920 | G17: - | I17: PT Indolabel Surya Pratama
C18: PT Sumber Energy | E18: 63270000 | G18: 27000000 | I18: PT Sumber Energy
C19: Suranto | E19: 61090000 | G19: - | I19: Suranto
C20: PT Sinergy Indopack Makmur | E20: 59140800 | G20: 40182000 | I20: PT Sinergy Indopack Makmur
C21: PT Sumberdaya Sinar Baru | E21: 55366010 | G21: 19068210 | I21: PT Sumberdaya Sinar Baru
C22: PT Sinar Setia Mulia | E22: 55230003 | G22: 56950000 | I22: PT Sinar Setia Mulia
C23: PT Mida Trade Ventures Indonesia | E23: 54835465 | G23: - | I23: PT Mida Trade Ventures Indonesia
C24: PT Prima Larvae | E24: 54504000 | G24: - | I24: PT Prima Larvae
C25: PT Sumatra Motor Teknindo | E25: 52438355 | G25: 156386992 | I25: PT Sumatra Motor Teknindo
C26: PT Dinamika Lubsindo Utama | E26: 44379395 | G26: 50335347 | I26: PT Dinamika Lubsindo Utama
C27: CV AGS Sejahtera | E27: 40019800 | G27: - | I27: CV AGS Sejahtera
C28: PT Prima Sari Indotama | E28: 32435303 | G28: 28510258 | I28: PT Prima Sari Indotama
C29: PT Seven Mountain Internasional | E29: 29859000 | G29: 20684850 | I29: PT Seven Mountain Internasional
C30: CV Sri Rejeki | E30: 29399082 | G30: - | I30: CV Sri Rejeki
C31: Nusa Jaya | E31: 25502001 | G31: 47152462 | I31: Nusa Jaya
C32: PT Intiragam Oliefindo | E32: 24975000 | G32: 49950000 | I32: PT Intiragam Oliefindo
C33: CV Lima Pendawa | E33: 22200000 | G33: 44400000 | I33: CV Lima Pendawa
C34: PT Sumatraco Langgeng Abadi | E34: 20535000 | G34: 34965000 | I34: PT Sumatraco Langgeng Abadi
C35: PT International Packaging Manufacturing | E35: 971250 | G35: 669801750 | I35: PT International Packaging Manufacturing
C36: CV Putra Widjaja Marine | E36: - | G36: 5240992985 | I36: CV Putra Widjaja Marine
C37: PT Grahamakmur Ciptapratama | E37: - | G37: 1618149192 | I37: PT Grahamakmur Ciptapratama
C38: Choice Canning Company Inc, | E38: - | G38: 1356603529 | I38: Choice Canning Company Inc,
C39: PT CJ Cheiljedang Feed Lampung | E39: - | G39: 1115222500 | I39: PT CJ Cheiljedang Feed Lampung
C40: Hendro Hariyanto | E40: - | G40: 323468632 | I40: Hendro Hariyanto
C41: Toko Nusantara | E41: - | G41: 310906705 | I41: Nusantara
C42: CV Windu Segara Hatchery | E42: - | G42: 190050000 | I42: CV Windu Segara Hatchery
C43: CV Nerimo Ing Pandum | E43: - | G43: 187956458 | I43: CV Nerimo Ing Pandum
C44: PT Samara Cipta Solution | E44: - | G44: 122323133 | I44: PT Samara Cipta Solution
C45: PT Indoplast Jaya Sukses Makmur | E45: - | G45: 121624520 | I45: PT Indoplast Jaya Sukses Makmur
C46: PT Anugerah Berkah Usaha | E46: - | G46: 117818222 | I46: PT Anugerah Berkah Usaha
C47: PT General Agromesin Lestari | E47: - | G47: 116369995 | I47: PT General Agromesin Lestari
... C57: PT Prima Akuakultur Lestari | E57: - | G57: 24990000 | I57: PT Prima Akuakultur Lestari
C58: Lain-lain (masing-masing | I58: Others (each belows
C59: dibawah Rp 25.000.000) | E59: 473388517 | G59: 2962354377 | I59: Rp 25,000,000)
C61: Jumlah | E61: 10364486466 | G61: 20407901137 | I61: Total
C64: Analisis umur utang usaha yang dihitung dari tanggal jatuh tempo adalah sebagai berikut: | I64: The aging analysis of trade payables based on due date is presented below:
E66: 2024 | G66: 2023
C68: Belum jatuh tempo | E68: 4019944007 | G68: 9413893368 | I68: Not yet due
C69: Jatuh tempo: | I69: Due date:
C70: 1-30 hari | E70: 3706048328 | G70: 2293429031 | I70: 1-30 days
C71: 31-60 hari | E71: 2051952657 | G71: 820703899 | I71: 31-60 days
C72: 61-90 hari | E72: 306324518 | G72: 620617659 | I72: 61-90 days
C73: >90 hari | E73: 280216956 | G73: 7259257180 | I73: >90 days
C75: Jumlah | E75: 10364486466 | G75: 20407901137 | I75: Total
